Workbook
Name MesEntrada: 'Configuración'!$C$4
Name InicioCiclo: 'Configuración'!$C$5
Name FechaRef: 'Configuración'!$C$6
Name SemanaActual: 'Configuración'!$C$7
Name SemanaManual: 'Configuración'!$C$8
Name DiasAlerta: 'Configuración'!$C$9
Name ObsObligatoria: 'Configuración'!$C$10
Name MetaFinal: 'Configuración'!$C$11
Name HistInicio: 'Configuración'!$C$12
Name PlanRef: 'Configuración'!$C$15:$C$18
Name ListaPuestos: 'Configuración'!$B$22:$B$25
Name ListaEstados: 'Configuración'!$B$28:$B$30
Name ListaSemanas: 'Configuración'!$B$33:$B$36
Name ListaSiNo: 'Configuración'!$B$39:$B$40
Name rFLim_RO: 'Cronograma R. Operacional'!$AS$5:$AS$1000
Name rIni_RO: 'Cronograma R. Operacional'!$E$5:$E$1000
Name rLim_RO: 'Cronograma R. Operacional'!$F$5:$F$1000
Name rDname_RO: 'Cronograma R. Operacional'!$AP$5:$AP$1000
Name rPeso_RO: 'Cronograma R. Operacional'!$AL$5:$AL$1000
Name rPesoEscrito_RO: 'Cronograma R. Operacional'!$H$5:$H$1000
Name rS1_RO: 'Cronograma R. Operacional'!$I$5:$I$1000
Name rS2_RO: 'Cronograma R. Operacional'!$J$5:$J$1000
Name rS3_RO: 'Cronograma R. Operacional'!$K$5:$K$1000
Name rS4_RO: 'Cronograma R. Operacional'!$L$5:$L$1000
Name rAvance_RO: 'Cronograma R. Operacional'!$M$5:$M$1000
Name rEstado_RO: 'Cronograma R. Operacional'!$N$5:$N$1000
Name rAlerta_RO: 'Cronograma R. Operacional'!$O$5:$O$1000
Name rValid_RO: 'Cronograma R. Operacional'!$R$5:$R$1000
Name rMes_RO: 'Cronograma R. Operacional'!$S$5:$S$1000
Name rOrden_RO: 'Cronograma R. Operacional'!$T$5:$T$1000
Name rTipo_RO: 'Cronograma R. Operacional'!$V$5:$V$1000
Name rEf1_RO: 'Cronograma R. Operacional'!$AH$5:$AH$1000
Name rEf2_RO: 'Cronograma R. Operacional'!$AI$5:$AI$1000
Name rEf3_RO: 'Cronograma R. Operacional'!$AJ$5:$AJ$1000
Name rEf4_RO: 'Cronograma R. Operacional'!$AK$5:$AK$1000
Name rAct_RO: 'Cronograma R. Operacional'!$C$5:$C$1000
Name rDeleg_RO: 'Cronograma R. Operacional'!$D$5:$D$1000
Name rDkey_RO: 'Cronograma R. Operacional'!$AO$5:$AO$1000
Name rFLim_RN: 'Cronograma R. Normativo'!$AS$5:$AS$1000
Name rIni_RN: 'Cronograma R. Normativo'!$E$5:$E$1000
Name rLim_RN: 'Cronograma R. Normativo'!$F$5:$F$1000
Name rDname_RN: 'Cronograma R. Normativo'!$AP$5:$AP$1000
Name rPeso_RN: 'Cronograma R. Normativo'!$AL$5:$AL$1000
Name rPesoEscrito_RN: 'Cronograma R. Normativo'!$H$5:$H$1000
Name rS1_RN: 'Cronograma R. Normativo'!$I$5:$I$1000
Name rS2_RN: 'Cronograma R. Normativo'!$J$5:$J$1000
Name rS3_RN: 'Cronograma R. Normativo'!$K$5:$K$1000
Name rS4_RN: 'Cronograma R. Normativo'!$L$5:$L$1000
Name rAvance_RN: 'Cronograma R. Normativo'!$M$5:$M$1000
Name rEstado_RN: 'Cronograma R. Normativo'!$N$5:$N$1000
Name rAlerta_RN: 'Cronograma R. Normativo'!$O$5:$O$1000
Name rValid_RN: 'Cronograma R. Normativo'!$R$5:$R$1000
Name rMes_RN: 'Cronograma R. Normativo'!$S$5:$S$1000
Name rOrden_RN: 'Cronograma R. Normativo'!$T$5:$T$1000
Name rTipo_RN: 'Cronograma R. Normativo'!$V$5:$V$1000
Name rEf1_RN: 'Cronograma R. Normativo'!$AH$5:$AH$1000
Name rEf2_RN: 'Cronograma R. Normativo'!$AI$5:$AI$1000
Name rEf3_RN: 'Cronograma R. Normativo'!$AJ$5:$AJ$1000
Name rEf4_RN: 'Cronograma R. Normativo'!$AK$5:$AK$1000
Name rAct_RN: 'Cronograma R. Normativo'!$C$5:$C$1000

Sheet Dashboard - Consolidado
B1: Dashboard Consolidado – Gestión de Riesgos · Ciclo mensual de 4 semanas
B2: Período: | C2: =MesCiclo | D2: Semana actual: | E2: =SemanaActual | F2: Fecha de corte: | G2: =FechaRef | H2: Se actualiza solo con las hojas «Cronograma …» y «Actividades …» de cada puesto. El período y la semana se calculan con la fecha de hoy (ver Configuración).
B4: Avance general de las actividades | E4: Meta de cumplimiento | H4: Macroactividades registradas | K4: Actividades completadas
B5: =IF('Calculos'!$E$8,'Calculos'!$F$8,"No definitivo") | E5: =MetaFinal | H5: ='Calculos'!$B$11 | K5: ='Calculos'!$N$8
B6: =IF('Calculos'!$E$8,"Promedio simple de los 4 puestos",IF('Calculos'!$C$8=0,"Ningún puesto con datos válidos","Provisional "&TEXT('Calculos'!$D$8,"0%")&" ("&'Calculos'!$C$8&" de 4 puestos válidos)")) | E6: Al cierre de la Semana 4 | H6: ="En los 4 cronogramas · "&'Calculos'!$U$8&" delegada(s) por la jefatura" | K6: =IF('Calculos'!$B$11=0,"—",TEXT('Calculos'!$N$8/'Calculos'!$B$11,"0%")&" del total")
B8: Actividades en curso | E8: Actividades pendientes | H8: Puestos que alcanzaron el 100% | K8: Actividades con alertas
B9: ='Calculos'!$O$8 | E9: ='Calculos'!$P$8 | H9: ='Calculos'!$B$12 | K9: ='Calculos'!$R$8
B10: Avance > 0% y < 100% | E10: ="De todas las actividades, vencidas: "&'Calculos'!$Q$8 | H10: Con ponderación válida | K10: ="Próximas a vencer: "&'Calculos'!$B$13
B12: =IF('Calculos'!$E$8,"Avance general vs meta 100%","Avance PROVISIONAL vs meta") | C12: =IF('Calculos'!$E$8,'Calculos'!$F$8,N('Calculos'!$D$8)) | G12: =IF('Calculos'!$B$11=0,"⚠ No hay actividades registradas en este mes. Cada puesto registra sus actividades y pesos en su hoja «Cronograma …».",IF(NOT('Calculos'!$E$8),"⚠ Avance general NO definitivo: "&(4-'Calculos'!$C$8)&" puesto(s) sin actividades válidas o con pesos que no suman 100%.",IF('Calculos'!$M$8,"Actividades del mes: ¡Enhorabuena, completado anticipadamente!",IF('Calculos'!$L$8,"Actividades del mes completadas: meta del 100% alcanzada.","Actividades del mes en ejecución – Semana "&SemanaActual&" de 4."))))
B14: Avance individual por puesto (ponderado por el peso de cada actividad)
B15: Puesto | C15: Avance ponderado | D15: Progreso | E15: Total actividades | F15: Completadas | G15: En curso | H15: Pendientes | I15: Vencidas | J15: Con alertas | K15: Estado general | L15: Mensaje de finalización
B16: ='Calculos'!A4 | C16: =IF('Calculos'!B4=0,"Sin actividades",IF(NOT('Calculos'!E4),"Revisar pesos",'Calculos'!F4)) | D16: =IF(ISNUMBER(C16),C16,0) | E16: ='Calculos'!B4 | F16: ='Calculos'!N4 | G16: ='Calculos'!O4 | H16: ='Calculos'!P4 | I16: ='Calculos'!Q4 | J16: ='Calculos'!R4 | K16: =IF('Calculos'!B4=0,"Sin actividades",IF(NOT('Calculos'!E4),"Pesos no válidos",IF('Calculos'!L4,"Completado",IF('Calculos'!F4>0,"En curso","Pendiente")))) | L16: =IF('Calculos'!B4=0,"⚠ Registrar actividades",IF(NOT('Calculos'!E4),"⚠ Corregir pesos no válidos",IF('Calculos'!M4,"¡Enhorabuena, completado anticipadamente!",IF('Calculos'!L4,"Completado","En ejecución")))) | P16: R. Operacional
B17: ='Calculos'!A5 | C17: =IF('Calculos'!B5=0,"Sin actividades",IF(NOT('Calculos'!E5),"Revisar pesos",'Calculos'!F5)) | D17: =IF(ISNUMBER(C17),C17,0) | E17: ='Calculos'!B5 | F17: ='Calculos'!N5 | G17: ='Calculos'!O5 | H17: ='Calculos'!P5 | I17: ='Calculos'!Q5 | J17: ='Calculos'!R5 | K17: =IF('Calculos'!B5=0,"Sin actividades",IF(NOT('Calculos'!E5),"Pesos no válidos",IF('Calculos'!L5,"Completado",IF('Calculos'!F5>0,"En curso","Pendiente")))) | L17: =IF('Calculos'!B5=0,"⚠ Registrar actividades",IF(NOT('Calculos'!E5),"⚠ Corregir pesos no válidos",IF('Calculos'!M5,"¡Enhorabuena, completado anticipadamente!",IF('Calculos'!L5,"Completado","En ejecución")))) | P17: R. Normativo
B18: ='Calculos'!A6 | C18: =IF('Calculos'!B6=0,"Sin actividades",IF(NOT('Calculos'!E6),"Revisar pesos",'Calculos'!F6)) | D18: =IF(ISNUMBER(C18),C18,0) | E18: ='Calculos'!B6 | F18: ='Calculos'!N6 | G18: ='Calculos'!O6 | H18: ='Calculos'!P6 | I18: ='Calculos'!Q6 | J18: ='Calculos'!R6 | K18: =IF('Calculos'!B6=0,"Sin actividades",IF(NOT('Calculos'!E6),"Pesos no válidos",IF('Calculos'!L6,"Completado",IF('Calculos'!F6>0,"En curso","Pendiente")))) | L18: =IF('Calculos'!B6=0,"⚠ Registrar actividades",IF(NOT('Calculos'!E6),"⚠ Corregir pesos no válidos",IF('Calculos'!M6,"¡Enhorabuena, completado anticipadamente!",IF('Calculos'!L6,"Completado","En ejecución")))) | P18: R. Financiero
B19: ='Calculos'!A7 | C19: =IF('Calculos'!B7=0,"Sin actividades",IF(NOT('Calculos'!E7),"Revisar pesos",'Calculos'!F7)) | D19: =IF(ISNUMBER(C19),C19,0) | E19: ='Calculos'!B7 | F19: ='Calculos'!N7 | G19: ='Calculos'!O7 | H19: ='Calculos'!P7 | I19: ='Calculos'!Q7 | J19: ='Calculos'!R7 | K19: =IF('Calculos'!B7=0,"Sin actividades",IF(NOT('Calculos'!E7),"Pesos no válidos",IF('Calculos'!L7,"Completado",IF('Calculos'!F7>0,"En curso","Pendiente")))) | L19: =IF('Calculos'!B7=0,"⚠ Registrar actividades",IF(NOT('Calculos'!E7),"⚠ Corregir pesos no válidos",IF('Calculos'!M7,"¡Enhorabuena, completado anticipadamente!",IF('Calculos'!L7,"Completado","En ejecución")))) | P19: Asistente Técnico
B20: Total actividades | C20: =IF('Calculos'!$E$8,'Calculos'!$F$8,"No definitivo") | D20: =IF(ISNUMBER(C20),C20,0) | E20: ='Calculos'!B11 | F20: ='Calculos'!N8 | G20: ='Calculos'!O8 | H20: ='Calculos'!P8 | I20: ='Calculos'!Q8 | J20: ='Calculos'!R8 | K20: =IF('Calculos'!$E$8,"Promedio 4 puestos","No definitivo") | L20: =IF(NOT('Calculos'!$E$8),"⚠ Completar configuración de todos los puestos",IF('Calculos'!$M$8,"¡Enhorabuena, completado anticipadamente!",IF('Calculos'!$L$8,"Completado","En ejecución")))
B22: Seguimiento semanal: avance acumulado ponderado e incremento semanal
C23: Avance ACUMULADO ponderado al cierre de cada semana | H23: INCREMENTO respecto a la semana anterior (puntos %) | L23: Brecha vs meta 100%
B24: Puesto / Indicador | C24: Semana 1 | D24: Semana 2 | E24: Semana 3 | F24: Semana 4 | H24: Semana 1 | I24: Semana 2 | J24: Semana 3 | K24: Semana 4 | L24: Pendiente para la meta
B25: ='Calculos'!A4 | C25: =IF(NOT('Calculos'!G$10),"",IF('Calculos'!$E4,'Calculos'!G4,"–")) | D25: =IF(NOT('Calculos'!H$10),"",IF('Calculos'!$E4,'Calculos'!H4,"–")) | E25: =IF(NOT('Calculos'!I$10),"",IF('Calculos'!$E4,'Calculos'!I4,"–")) | F25: =IF(NOT('Calculos'!J$10),"",IF('Calculos'!$E4,'Calculos'!J4,"–")) | H25: =IF(ISNUMBER(C25),C25,"") | I25: =IF(AND(ISNUMBER(D25),ISNUMBER(C25)),D25-C25,"") | J25: =IF(AND(ISNUMBER(E25),ISNUMBER(D25)),E25-D25,"") | K25: =IF(AND(ISNUMBER(F25),ISNUMBER(E25)),F25-E25,"") | L25: =IFERROR(MetaFinal-LOOKUP(2,1/ISNUMBER(C25:F25),C25:F25),"") | P25: R. Operacional
B26: ='Calculos'!A5 | C26: =IF(NOT('Calculos'!G$10),"",IF('Calculos'!$E5,'Calculos'!G5,"–")) | D26: =IF(NOT('Calculos'!H$10),"",IF('Calculos'!$E5,'Calculos'!H5,"–")) | E26: =IF(NOT('Calculos'!I$10),"",IF('Calculos'!$E5,'Calculos'!I5,"–")) | F26: =IF(NOT('Calculos'!J$10),"",IF('Calculos'!$E5,'Calculos'!J5,"–")) | H26: =IF(ISNUMBER(C26),C26,"") | I26: =IF(AND(ISNUMBER(D26),ISNUMBER(C26)),D26-C26,"") | J26: =IF(AND(ISNUMBER(E26),ISNUMBER(D26)),E26-D26,"") | K26: =IF(AND(ISNUMBER(F26),ISNUMBER(E26)),F26-E26,"") | L26: =IFERROR(MetaFinal-LOOKUP(2,1/ISNUMBER(C26:F26),C26:F26),"") | P26: R. Normativo
B27: ='Calculos'!A6 | C27: =IF(NOT('Calculos'!G$10),"",IF('Calculos'!$E6,'Calculos'!G6,"–")) | D27: =IF(NOT('Calculos'!H$10),"",IF('Calculos'!$E6,'Calculos'!H6,"–")) | E27: =IF(NOT('Calculos'!I$10),"",IF('Calculos'!$E6,'Calculos'!I6,"–")) | F27: =IF(NOT('Calculos'!J$10),"",IF('Calculos'!$E6,'Calculos'!J6,"–")) | H27: =IF(ISNUMBER(C27),C27,"") | I27: =IF(AND(ISNUMBER(D27),ISNUMBER(C27)),D27-C27,"") | J27: =IF(AND(ISNUMBER(E27),ISNUMBER(D27)),E27-D27,"") | K27: =IF(AND(ISNUMBER(F27),ISNUMBER(E27)),F27-E27,"") | L27: =IFERROR(MetaFinal-LOOKUP(2,1/ISNUMBER(C27:F27),C27:F27),"") | P27: R. Financiero
B28: ='Calculos'!A7 | C28: =IF(NOT('Calculos'!G$10),"",IF('Calculos'!$E7,'Calculos'!G7,"–")) | D28: =IF(NOT('Calculos'!H$10),"",IF('Calculos'!$E7,'Calculos'!H7,"–")) | E28: =IF(NOT('Calculos'!I$10),"",IF('Calculos'!$E7,'Calculos'!I7,"–")) | F28: =IF(NOT('Calculos'!J$10),"",IF('Calculos'!$E7,'Calculos'!J7,"–")) | H28: =IF(ISNUMBER(C28),C28,"") | I28: =IF(AND(ISNUMBER(D28),ISNUMBER(C28)),D28-C28,"") | J28: =IF(AND(ISNUMBER(E28),ISNUMBER(D28)),E28-D28,"") | K28: =IF(AND(ISNUMBER(F28),ISNUMBER(E28)),F28-E28,"") | L28: =IFERROR(MetaFinal-LOOKUP(2,1/ISNUMBER(C28:F28),C28:F28),"") | P28: Asistente Técnico
B29: Avance general de las actividades | C29: =IF(NOT('Calculos'!G$10),"",IF('Calculos'!$E$8,'Calculos'!G8,"n/d")) | D29: =IF(NOT('Calculos'!H$10),"",IF('Calculos'!$E$8,'Calculos'!H8,"n/d")) | E29: =IF(NOT('Calculos'!I$10),"",IF('Calculos'!$E$8,'Calculos'!I8,"n/d")) | F29: =IF(NOT('Calculos'!J$10),"",IF('Calculos'!$E$8,'Calculos'!J8,"n/d")) | H29: =IF(ISNUMBER(C29),C29,"") | I29: =IF(AND(ISNUMBER(D29),ISNUMBER(C29)),D29-C29,"") | J29: =IF(AND(ISNUMBER(E29),ISNUMBER(D29)),E29-D29,"") | K29: =IF(AND(ISNUMBER(F29),ISNUMBER(E29)),F29-E29,"") | L29: =IFERROR(MetaFinal-LOOKUP(2,1/ISNUMBER(C29:F29),C29:F29),"")
B30: Plan de referencia (supuesto) | C30: =INDEX(PlanRef,1) | D30: =INDEX(PlanRef,2) | E30: =INDEX(PlanRef,3) | F30: =INDEX(PlanRef,4) | P30: Plan de referencia
B31: Meta final | C31: =MetaFinal | D31: =MetaFinal | E31: =MetaFinal | F31: =MetaFinal
B33: Lectura: el acumulado NO se suma entre semanas; el incremento es la diferencia entre semanas consecutivas. «–» = puesto sin configuración válida; «n/d» = avance general no definitivo; celda vacía = semana aún no alcanzada. Ámbar = acumulado por debajo del plan de referencia.
B68: Control de calidad de datos
B69: Verificación | G69: Casos | H69: Resultado | I69: Acción sugerida
B70: Puestos sin actividades registradas | G70: =COUNTIF('Calculos'!B4:B7,0) | H70: =IF(G70=0,"✔ OK",IF("crit"="warn","● Atención","⚠ Revisar")) | I70: Registrar al menos una macroactividad por puesto.
B71: Puestos con pesos no válidos (fuera de 0–100%) | G71: =COUNTIFS('Calculos'!B4:B7,">0",'Calculos'!E4:E7,FALSE) | H71: =IF(G71=0,"✔ OK",IF("crit"="warn","● Atención","⚠ Revisar")) | I71: Corregir el peso (los pesos se ajustan solos a 100%).
B72: Actividades con peso vacío o fuera de rango | G72: =SUMPRODUCT((rMes_RO=MesCiclo)*((ISNUMBER(SEARCH("Peso vacío",rValid_RO))+ISNUMBER(SEARCH("Peso fuera de rango",rValid_RO)))>0))+SUMPRODUCT((rMes_RN=MesCiclo)*((ISNUMBER(SEARCH("Peso vacío",rValid_RN))+ISNUMBER(SEARCH("Peso fuera de rango",rValid_RN)))>0))+SUMPRODUCT((rMes_RF=MesCiclo)*((ISNUMBER(SEARCH("Peso vacío",rValid_RF))+ISNUMBER(SEARCH("Peso fuera de rango",rValid_RF)))>0))+SUMPRODUCT((rMes_ATR=MesCiclo)*((ISNUMBER(SEARCH("Peso vacío",rValid_ATR))+ISNUMBER(SEARCH("Peso fuera de rango",rValid_ATR)))>0)) | H72: =IF(G72=0,"✔ OK",IF("crit"="warn","● Atención","⚠ Revisar")) | I72: Ingresar un peso entre 0% y 100% (mayor que 0).
B73: Actividades sin fecha límite | G73: =SUMPRODUCT((rMes_RO=MesCiclo)*((ISNUMBER(SEARCH("Sin fecha límite",rValid_RO)))>0))+SUMPRODUCT((rMes_RN=MesCiclo)*((ISNUMBER(SEARCH("Sin fecha límite",rValid_RN)))>0))+SUMPRODUCT((rMes_RF=MesCiclo)*((ISNUMBER(SEARCH("Sin fecha límite",rValid_RF)))>0))+SUMPRODUCT((rMes_ATR=MesCiclo)*((ISNUMBER(SEARCH("Sin fecha límite",rValid_ATR)))>0)) | H73: =IF(G73=0,"✔ OK",IF("crit"="warn","● Atención","⚠ Revisar")) | I73: Registrar la fecha límite.
B74: Fechas incoherentes o no válidas (incluye sin fecha de inicio) | G74: =SUMPRODUCT((rMes_RO=MesCiclo)*((ISNUMBER(SEARCH("Inicio posterior",rValid_RO))+ISNUMBER(SEARCH("Fecha no válida",rValid_RO))+ISNUMBER(SEARCH("Sin fecha de inicio",rValid_RO)))>0))+SUMPRODUCT((rMes_RN=MesCiclo)*((ISNUMBER(SEARCH("Inicio posterior",rValid_RN))+ISNUMBER(SEARCH("Fecha no válida",rValid_RN))+ISNUMBER(SEARCH("Sin fecha de inicio",rValid_RN)))>0))+SUMPRODUCT((rMes_RF=MesCiclo)*((ISNUMBER(SEARCH("Inicio posterior",rValid_RF))+ISNUMBER(SEARCH("Fecha no válida",rValid_RF))+ISNUMBER(SEARCH("Sin fecha de inicio",rValid_RF)))>0))+SUMPRODUCT((rMes_ATR=MesCiclo)*((ISNUMBER(SEARCH("Inicio posterior",rValid_ATR))+ISNUMBER(SEARCH("Fecha no válida",rValid_ATR))+ISNUMBER(SEARCH("Sin fecha de inicio",rValid_ATR)))>0)) | H74: =IF(G74=0,"✔ OK",IF("crit"="warn","● Atención","⚠ Revisar")) | I74: La fecha de inicio debe ser anterior o igual a la fecha límite.
B75: Porcentajes de avance > 100%, < 0% o no numéricos | G75: =SUMPRODUCT((rMes_RO=MesCiclo)*((ISNUMBER(SEARCH("Avance fuera de rango",rValid_RO)))>0))+SUMPRODUCT((rMes_RN=MesCiclo)*((ISNUMBER(SEARCH("Avance fuera de rango",rValid_RN)))>0))+SUMPRODUCT((rMes_RF=MesCiclo)*((ISNUMBER(SEARCH("Avance fuera de rango",rValid_RF)))>0))+SUMPRODUCT((rMes_ATR=MesCiclo)*((ISNUMBER(SEARCH("Avance fuera de rango",rValid_ATR)))>0)) | H75: =IF(G75=0,"✔ OK",IF("crit"="warn","● Atención","⚠ Revisar")) | I75: Corregir: los avances deben estar entre 0% y 100%.
B76: Avance semanal menor que el de una semana anterior | G76: =SUMPRODUCT((rMes_RO=MesCiclo)*((ISNUMBER(SEARCH("decreciente",rValid_RO)))>0))+SUMPRODUCT((rMes_RN=MesCiclo)*((ISNUMBER(SEARCH("decreciente",rValid_RN)))>0))+SUMPRODUCT((rMes_RF=MesCiclo)*((ISNUMBER(SEARCH("decreciente",rValid_RF)))>0))+SUMPRODUCT((rMes_ATR=MesCiclo)*((ISNUMBER(SEARCH("decreciente",rValid_ATR)))>0)) | H76: =IF(G76=0,"✔ OK",IF("crit"="warn","● Atención","⚠ Revisar")) | I76: Revisar: el avance es acumulado y no debería disminuir.
B77: Actividades vencidas no completadas | G77: ='Calculos'!Q8 | H77: =IF(G77=0,"✔ OK",IF("crit"="warn","● Atención","⚠ Revisar")) | I77: Actualizar avance o reprogramar con justificación en Observaciones.
B78: Actividades próximas a vencer (no completadas) | G78: ='Calculos'!B13 | H78: =IF(G78=0,"✔ OK",IF("warn"="warn","● Atención","⚠ Revisar")) | I78: Alerta preventiva: priorizar seguimiento.
B79: Filas con datos pero sin nombre de macroactividad | G79: =SUMPRODUCT((rMes_RO=MesCiclo)*((ISNUMBER(SEARCH("Macroactividad vacía",rValid_RO)))>0))+SUMPRODUCT((rMes_RN=MesCiclo)*((ISNUMBER(SEARCH("Macroactividad vacía",rValid_RN)))>0))+SUMPRODUCT((rMes_RF=MesCiclo)*((ISNUMBER(SEARCH("Macroactividad vacía",rValid_RF)))>0))+SUMPRODUCT((rMes_ATR=MesCiclo)*((ISNUMBER(SEARCH("Macroactividad vacía",rValid_ATR)))>0)) | H79: =IF(G79=0,"✔ OK",IF("crit"="warn","● Atención","⚠ Revisar")) | I79: Escribir el nombre de la actividad.
B80: Actividades vencidas sin observación que explique el incumplimiento | G80: =SUMPRODUCT((rMes_RO=MesCiclo)*((ISNUMBER(SEARCH("sin observación",rValid_RO)))>0))+SUMPRODUCT((rMes_RN=MesCiclo)*((ISNUMBER(SEARCH("sin observación",rValid_RN)))>0))+SUMPRODUCT((rMes_RF=MesCiclo)*((ISNUMBER(SEARCH("sin observación",rValid_RF)))>0))+SUMPRODUCT((rMes_ATR=MesCiclo)*((ISNUMBER(SEARCH("sin observación",rValid_ATR)))>0)) | H80: =IF(G80=0,"✔ OK",IF("crit"="warn","● Atención","⚠ Revisar")) | I80: Escribir en Observaciones por qué no se cumplió y la nueva fecha prevista.
B81: Avance general no definitivo (puestos no válidos) | G81: =4-'Calculos'!C8 | H81: =IF(G81=0,"✔ OK",IF("crit"="warn","● Atención","⚠ Revisar")) | I81: El avance general solo es definitivo con los 4 puestos válidos.
B82: Detalle por actividad: columna «Revisión automática (alertas)» de la hoja «Cronograma …» de cada puesto (filtrar por «⚠»). Pendiente normal = sin avance y dentro de plazo; Vencida = fecha límite anterior a la fecha de corte sin llegar a 100%.
B84: Entregas por semana y alertas de plazo (macroactividades completadas / programadas)
B85: Puesto | C85: Semana 1 | D85: Semana 2 | E85: Semana 3 | F85: Semana 4 | G85: Total | H85: Vencidas | I85: Por vencer | J85: Alerta de plazo (actividades y subactividades del mes)
B86: ='Calculos'!A4 | C86: =COUNTIFS(hSemana_RO,"Semana 1",hEstado_RO,"Completado",hTipo_RO,"Macro")&" / "&COUNTIFS(hSemana_RO,"Semana 1",hTipo_RO,"Macro") | D86: =COUNTIFS(hSemana_RO,"Semana 2",hEstado_RO,"Completado",hTipo_RO,"Macro")&" / "&COUNTIFS(hSemana_RO,"Semana 2",hTipo_RO,"Macro") | E86: =COUNTIFS(hSemana_RO,"Semana 3",hEstado_RO,"Completado",hTipo_RO,"Macro")&" / "&COUNTIFS(hSemana_RO,"Semana 3",hTipo_RO,"Macro") | F86: =COUNTIFS(hSemana_RO,"Semana 4",hEstado_RO,"Completado",hTipo_RO,"Macro")&" / "&COUNTIFS(hSemana_RO,"Semana 4",hTipo_RO,"Macro") | G86: =COUNTIFS(hEstado_RO,"Completado",hTipo_RO,"Macro")&" / "&COUNTIFS(hEstado_RO,"?*",hTipo_RO,"Macro") | H86: =COUNTIFS(rMes_RO,MesCiclo,rAlerta_RO,"Vencida*") | I86: =COUNTIFS(rMes_RO,MesCiclo,rAlerta_RO,"Vence*") | J86: =IF(H86+I86=0,"✔ Sin vencidas ni por vencer",IF(H86>0,"⚠ "&H86&" vencida(s) sin cumplir","")&IF(AND(H86>0,I86>0)," · ","")&IF(I86>0,I86&" por vencer (≤ "&DiasAlerta&" días)",""))
B87: ='Calculos'!A5 | C87: =COUNTIFS(hSemana_RN,"Semana 1",hEstado_RN,"Completado",hTipo_RN,"Macro")&" / "&COUNTIFS(hSemana_RN,"Semana 1",hTipo_RN,"Macro") | D87: =COUNTIFS(hSemana_RN,"Semana 2",hEstado_RN,"Completado",hTipo_RN,"Macro")&" / "&COUNTIFS(hSemana_RN,"Semana 2",hTipo_RN,"Macro") | E87: =COUNTIFS(hSemana_RN,"Semana 3",hEstado_RN,"Completado",hTipo_RN,"Macro")&" / "&COUNTIFS(hSemana_RN,"Semana 3",hTipo_RN,"Macro") | F87: =COUNTIFS(hSemana_RN,"Semana 4",hEstado_RN,"Completado",hTipo_RN,"Macro")&" / "&COUNTIFS(hSemana_RN,"Semana 4",hTipo_RN,"Macro") | G87: =COUNTIFS(hEstado_RN,"Completado",hTipo_RN,"Macro")&" / "&COUNTIFS(hEstado_RN,"?*",hTipo_RN,"Macro") | H87: =COUNTIFS(rMes_RN,MesCiclo,rAlerta_RN,"Vencida*") | I87: =COUNTIFS(rMes_RN,MesCiclo,rAlerta_RN,"Vence*") | J87: =IF(H87+I87=0,"✔ Sin vencidas ni por vencer",IF(H87>0,"⚠ "&H87&" vencida(s) sin cumplir","")&IF(AND(H87>0,I87>0)," · ","")&IF(I87>0,I87&" por vencer (≤ "&DiasAlerta&" días)",""))
B88: ='Calculos'!A6 | C88: =COUNTIFS(hSemana_RF,"Semana 1",hEstado_RF,"Completado",hTipo_RF,"Macro")&" / "&COUNTIFS(hSemana_RF,"Semana 1",hTipo_RF,"Macro") | D88: =COUNTIFS(hSemana_RF,"Semana 2",hEstado_RF,"Completado",hTipo_RF,"Macro")&" / "&COUNTIFS(hSemana_RF,"Semana 2",hTipo_RF,"Macro") | E88: =COUNTIFS(hSemana_RF,"Semana 3",hEstado_RF,"Completado",hTipo_RF,"Macro")&" / "&COUNTIFS(hSemana_RF,"Semana 3",hTipo_RF,"Macro") | F88: =COUNTIFS(hSemana_RF,"Semana 4",hEstado_RF,"Completado",hTipo_RF,"Macro")&" / "&COUNTIFS(hSemana_RF,"Semana 4",hTipo_RF,"Macro") | G88: =COUNTIFS(hEstado_RF,"Completado",hTipo_RF,"Macro")&" / "&COUNTIFS(hEstado_RF,"?*",hTipo_RF,"Macro") | H88: =COUNTIFS(rMes_RF,MesCiclo,rAlerta_RF,"Vencida*") | I88: =COUNTIFS(rMes_RF,MesCiclo,rAlerta_RF,"Vence*") | J88: =IF(H88+I88=0,"✔ Sin vencidas ni por vencer",IF(H88>0,"⚠ "&H88&" vencida(s) sin cumplir","")&IF(AND(H88>0,I88>0)," · ","")&IF(I88>0,I88&" por vencer (≤ "&DiasAlerta&" días)",""))
B89: ='Calculos'!A7 | C89: =COUNTIFS(hSemana_ATR,"Semana 1",hEstado_ATR,"Completado",hTipo_ATR,"Macro")&" / "&COUNTIFS(hSemana_ATR,"Semana 1",hTipo_ATR,"Macro") | D89: =COUNTIFS(hSemana_ATR,"Semana 2",hEstado_ATR,"Completado",hTipo_ATR,"Macro")&" / "&COUNTIFS(hSemana_ATR,"Semana 2",hTipo_ATR,"Macro") | E89: =COUNTIFS(hSemana_ATR,"Semana 3",hEstado_ATR,"Completado",hTipo_ATR,"Macro")&" / "&COUNTIFS(hSemana_ATR,"Semana 3",hTipo_ATR,"Macro") | F89: =COUNTIFS(hSemana_ATR,"Semana 4",hEstado_ATR,"Completado",hTipo_ATR,"Macro")&" / "&COUNTIFS(hSemana_ATR,"Semana 4",hTipo_ATR,"Macro") | G89: =COUNTIFS(hEstado_ATR,"Completado",hTipo_ATR,"Macro")&" / "&COUNTIFS(hEstado_ATR,"?*",hTipo_ATR,"Macro") | H89: =COUNTIFS(rMes_ATR,MesCiclo,rAlerta_ATR,"Vencida*") | I89: =COUNTIFS(rMes_ATR,MesCiclo,rAlerta_ATR,"Vence*") | J89: =IF(H89+I89=0,"✔ Sin vencidas ni por vencer",IF(H89>0,"⚠ "&H89&" vencida(s) sin cumplir","")&IF(AND(H89>0,I89>0)," · ","")&IF(I89>0,I89&" por vencer (≤ "&DiasAlerta&" días)",""))
B90: Administración (jefatura) | C90: — | D90: — | E90: — | F90: — | G90: =COUNTIFS(rMes_ADM,MesCiclo,rTipo_ADM,"Macro",rEstado_ADM,"Completado")&" / "&COUNTIFS(rMes_ADM,MesCiclo,rTipo_ADM,"Macro") | H90: =COUNTIFS(rMes_ADM,MesCiclo,rAlerta_ADM,"Vencida*") | I90: =COUNTIFS(rMes_ADM,MesCiclo,rAlerta_ADM,"Vence*") | J90: =IF(H90+I90=0,"✔ Sin vencidas ni por vencer",IF(H90>0,"⚠ "&H90&" vencida(s) sin cumplir","")&IF(AND(H90>0,I90>0)," · ","")&IF(I90>0,I90&" por vencer (≤ "&DiasAlerta&" días)",""))

Sheet Administración
A1: Administración (jefatura) – Actividades de la jefatura
A2: Llene solo las celdas GRIS SUAVE; las AZUL CLARO son automáticas. En «Tipo» elija Macroactividad o Subactividad: las subactividades van en las filas de ABAJO de su macroactividad (se ven con ↳); a cada una póngale su avance en las semanas o, cuando la termine, su FECHA DE CUMPLIMIENTO, y la macroactividad se llena sola. Cuando termine algo, escriba la FECHA DE CUMPLIMIENTO: queda al 100% y ya no aparece vencido. Si quiere registrar avances parciales, escriba en cada semana el % total logrado hasta esa semana. Cada mes agregue sus actividades debajo de las anteriores (no borre los meses pasados: quedan como historial).
A3: Llenar | B3: Automático | C3: Macroactividad (fila resaltada) | E3: Peso: macro = cuánto vale en el mes (opcional). Subactividad = su % dentro de la macro. Fechas de cada semana → | I3: =TEXT(DAY((InicioCiclo+0)),"00")&"/"&TEXT(MONTH((InicioCiclo+0)),"00")&" – "&TEXT(DAY((InicioCiclo+0)+6),"00")&"/"&TEXT(MONTH((InicioCiclo+0)+6),"00") | J3: =TEXT(DAY((InicioCiclo+7)),"00")&"/"&TEXT(MONTH((InicioCiclo+7)),"00")&" – "&TEXT(DAY((InicioCiclo+7)+6),"00")&"/"&TEXT(MONTH((InicioCiclo+7)+6),"00") | K3: =TEXT(DAY((InicioCiclo+14)),"00")&"/"&TEXT(MONTH((InicioCiclo+14)),"00")&" – "&TEXT(DAY((InicioCiclo+14)+6),"00")&"/"&TEXT(MONTH((InicioCiclo+14)+6),"00") | L3: =TEXT(DAY((InicioCiclo+21)),"00")&"/"&TEXT(MONTH((InicioCiclo+21)),"00")&" – "&TEXT(DAY((InicioCiclo+21)+6),"00")&"/"&TEXT(MONTH((InicioCiclo+21)+6),"00") | M3: ="Plazos del mes: "&COUNTIFS($S$5:$S$1000,MesCiclo,$O$5:$O$1000,"Vencida*")&" vencida(s) · "&COUNTIFS($S$5:$S$1000,MesCiclo,$O$5:$O$1000,"Vence*")&" por vencer" | Q3: En «Delegar a» elija el puesto: la actividad le llega a su Cronograma y aquí verá su avance.
A4: N° | B4: Tipo | C4: Actividad | D4: Delegar a | E4: Fecha de inicio | F4: Fecha límite | G4: Fecha de cumplimiento | H4: Peso / % de la subactividad | I4: Avance Semana 1 (%) | J4: Avance Semana 2 (%) | K4: Avance Semana 3 (%) | L4: Avance Semana 4 (%) | M4: % de Avance Total Actual | N4: Estado | O4: Alerta de plazo | P4: Seguimiento de la delegación | Q4: Observaciones | R4: Revisión automática (alertas) | S4: Mes | T4: Orden en el mes (aux) | U4: Grupo (aux) | V4: Tipo (aux) | W4: N subactividades (aux) | X4: % efectivo de la subactividad (aux) | Y4: Avance propio (aux) | Z4: Propio S1 (aux) | AA4: Propio S2 (aux) | AB4: Propio S3 (aux) | AC4: Propio S4 (aux) | AD4: Sub cumplida S1 (aux) | AE4: Sub cumplida S2 (aux) | AF4: Sub cumplida S3 (aux) | AG4: Sub cumplida S4 (aux) | AH4: Efectivo S1 (aux) | AI4: Efectivo S2 (aux) | AJ4: Efectivo S3 (aux) | AK4: Efectivo S4 (aux) | AL4: Peso efectivo (aux) | AM4: Fila en el puesto (aux) | AN4: N° delegada en el mes (aux) | AO4: Clave delegada (aux) | AP4: Clave puesto-actividad (aux) | AQ4: Fila en Administración (aux) | AR4: Inicio efectivo (aux) | AS4: Límite efectivo (aux)
A5: =IF(NOT((COUNTA($B5:$D5)+COUNTA($G5:$H5)+COUNTA($Q5))>0),"",IF($V5="Macro",COUNTIFS($V$5:$V5,"Macro",$S$5:$S5,$S5),IF(N($U5)=0,"?",COUNTIFS(INDEX($V$5:$V$1000,1):INDEX($V$5:$V$1000,$U5-4),"Macro",INDEX($S$5:$S$1000,1):INDEX($S$5:$S$1000,$U5-4),INDEX($S$5:$S$1000,$U5-4))&"."&COUNTIFS($U$5:$U5,$U5,$V$5:$V5,"Sub")))) | I5: =IF(N($W5)=0,"",IF(AND($S5=MesCiclo,1>SemanaActual),"",MIN(1,SUMIFS(OFFSET($A$1,ROW(),29,1000-ROW(),1),OFFSET($A$1,ROW(),20,1000-ROW(),1),ROW(),OFFSET($A$1,ROW(),21,1000-ROW(),1),"Sub")))) | J5: =IF(N($W5)=0,"",IF(AND($S5=MesCiclo,2>SemanaActual),"",MIN(1,SUMIFS(OFFSET($A$1,ROW(),30,1000-ROW(),1),OFFSET($A$1,ROW(),20,1000-ROW(),1),ROW(),OFFSET($A$1,ROW(),21,1000-ROW(),1),"Sub")))) | K5: =IF(N($W5)=0,"",IF(AND($S5=MesCiclo,3>SemanaActual),"",MIN(1,SUMIFS(OFFSET($A$1,ROW(),31,1000-ROW(),1),OFFSET($A$1,ROW(),20,1000-ROW(),1),ROW(),OFFSET($A$1,ROW(),21,1000-ROW(),1),"Sub")))) | L5: =IF(N($W5)=0,"",IF(AND($S5=MesCiclo,4>SemanaActual),"",MIN(1,SUMIFS(OFFSET($A$1,ROW(),32,1000-ROW(),1),OFFSET($A$1,ROW(),20,1000-ROW(),1),ROW(),OFFSET($A$1,ROW(),21,1000-ROW(),1),"Sub")))) | M5: =IF(NOT((COUNTA($B5:$D5)+COUNTA($G5:$H5)+COUNTA($Q5))>0),"",IF(AND($D5<>"",$V5="Macro"),IF(N($AM5)>0,N(CHOOSE(MATCH($D5,ListaPuestos,0),INDEX('Cronograma R. Operacional'!$M$5:$M$1000,$AM5),INDEX('Cronograma R. Normativo'!$M$5:$M$1000,$AM5),INDEX('Cronograma R. Financiero'!$M$5:$M$1000,$AM5),INDEX('Cronograma Asistente Técnico'!$M$5:$M$1000,$AM5))),0),IF(ISNUMBER($G5),1,IF(N($W5)>0,MIN(1,SUMIFS($Y$5:$Y$1000,$U$5:$U$1000,ROW(),$V$5:$V$1000,"Sub")),$Y5)))) | N5: =IF(OR($M5="",$V5="Sub"),"",IF($M5>=1,"Completado",IF($M5>0,"En curso","Pendiente"))) | O5: =IF(NOT((COUNTA($B5:$D5)+COUNTA($G5:$H5)+COUNTA($Q5))>0),"",IF(AND(AND($D5<>"",$V5="Macro"),N($AM5)>0),CHOOSE(MATCH($D5,ListaPuestos,0),INDEX('Cronograma R. Operacional'!$O$5:$O$1000,$AM5),INDEX('Cronograma R. Normativo'!$O$5:$O$1000,$AM5),INDEX('Cronograma R. Financiero'!$O$5:$O$1000,$AM5),INDEX('Cronograma Asistente Técnico'!$O$5:$O$1000,$AM5))&"",IF(ISNUMBER($G5),IF(AND(ISNUMBER($AS5),$G5>$AS5),"Cumplida con "&($G5-$AS5)&IF($G5-$AS5=1," día"," días")&" de retraso","Cumplida"),IF(N($M5)>=1,"Cumplida",IF(NOT(ISNUMBER($AS5)),"Sin fecha límite",IF($AS5<FechaRef,"Vencida hace "&(FechaRef-$AS5)&IF(FechaRef-$AS5=1," día"," días"),IF($AS5=FechaRef,"Vence hoy",IF($AS5-FechaRef<=DiasAlerta,"Vence en "&($AS5-FechaRef)&IF($AS5-FechaRef=1," día"," días"),"En plazo")))))))) | P5: =IF(NOT((COUNTA($B5:$D5)+COUNTA($G5:$H5)+COUNTA($Q5))>0),"",IF($D5="","Propia",IF($V5<>"Macro","Solo se delegan macroactividades",IF(N($AM5)>0,"✔ Recibida por "&$D5,"⚠ "&$D5&" aún no la agrega")))) | R5: =IF(NOT((COUNTA($B5:$D5)+COUNTA($G5:$H5)+COUNTA($Q5))>0),"",IF((IF($C5="","Falta el nombre de la actividad"&" · ","")&IF(AND($V5="Sub",N($U5)=0),"Subactividad sin macroactividad arriba"&" · ","")&IF(AND($V5="Macro",$AR5=""),"Sin fecha de inicio"&" · ","")&IF(AND($V5="Macro",$AS5=""),"Sin fecha límite"&" · ","")&IF(AND(LEFT($C5,11)="[Jefatura] ",N($AQ5)=0),"No se encuentra en la hoja de la jefatura (elíjala de nuevo en la lista)"&" · ","")&IF(OR(AND($E5<>"",NOT(ISNUMBER($E5))),AND($F5<>"",NOT(ISNUMBER($F5))),AND($G5<>"",NOT(ISNUMBER($G5)))),"Fecha no válida"&" · ","")&IF(AND(ISNUMBER($AR5),ISNUMBER($AS5),$AR5>$AS5),"Inicio posterior a fecha límite"&" · ","")&IF(AND($V5="Macro",$H5<>"",OR(NOT(ISNUMBER($H5)),$H5<0,$H5>1)),"Peso fuera de rango"&" · ","")&IF(AND($V5="Sub",$H5<>"",OR(NOT(ISNUMBER($H5)),$H5<0,$H5>1)),"% de la subactividad fuera de rango 0-100%"&" · ","")&IF(AND(N($W5)>0,SUMIFS($H$5:$H$1000,$U$5:$U$1000,ROW(),$V$5:$V$1000,"Sub")>1.0001),"Las subactividades suman más de 100%"&" · ","")&IF(AND(N($W5)>0,OR(IF(ISNUMBER($I5),ROUND($I5,6)<>ROUND(MIN(1,SUMIFS($AD$5:$AD$1000,$U$5:$U$1000,ROW(),$V$5:$V$1000,"Sub")),6),FALSE),IF(ISNUMBER($J5),ROUND($J5,6)<>ROUND(MIN(1,SUMIFS($AE$5:$AE$1000,$U$5:$U$1000,ROW(),$V$5:$V$1000,"Sub")),6),FALSE),IF(ISNUMBER($K5),ROUND($K5,6)<>ROUND(MIN(1,SUMIFS($AF$5:$AF$1000,$U$5:$U$1000,ROW(),$V$5:$V$1000,"Sub")),6),FALSE),IF(ISNUMBER($L5),ROUND($L5,6)<>ROUND(MIN(1,SUMIFS($AG$5:$AG$1000,$U$5:$U$1000,ROW(),$V$5:$V$1000,"Sub")),6),FALSE))),"Con subactividades: no escriba en las semanas (se llenan solas)"&" · ","")&IF((COUNTIF($I5:$L5,">1")+COUNTIF($I5:$L5,"<0")+SUMPRODUCT((LEN($I5:$L5)>0)*NOT(ISNUMBER($I5:$L5))))>0,"Avance fuera de rango 0-100%"&" · ","")&IF(OR(AND(ISNUMBER($J5),$J5<N($I5)),AND(ISNUMBER($K5),$K5<MAX($I5:$J5)),AND(ISNUMBER($L5),$L5<MAX($I5:$K5))),"Avance semanal decreciente"&" · ","")&IF(AND(ISNUMBER($AS5),$AS5<FechaRef,IF($V5="Sub",1,N($M5))<1),"Vencida"&" · ","")&IF(AND(ObsObligatoria="Sí",ISNUMBER($AS5),$AS5<FechaRef,IF($V5="Sub",1,N($M5))<1,$Q5=""),"Vencida sin observación"&" · ",""))="","✔ OK","⚠ "&LEFT(IF($C5="","Falta el nombre de la actividad"&" · ","")&IF(AND($V5="Sub",N($U5)=0),"Subactividad sin macroactividad arriba"&" · ","")&IF(AND($V5="Macro",$AR5=""),"Sin fecha de inicio"&" · ","")&IF(AND($V5="Macro",$AS5=""),"Sin fecha límite"&" · ","")&IF(AND(LEFT($C5,11)="[Jefatura] ",N($AQ5)=0),"No se encuentra en la hoja de la jefatura (elíjala de nuevo en la lista)"&" · ","")&IF(OR(AND($E5<>"",NOT(ISNUMBER($E5))),AND($F5<>"",NOT(ISNUMBER($F5))),AND($G5<>"",NOT(ISNUMBER($G5)))),"Fecha no válida"&" · ","")&IF(AND(ISNUMBER($AR5),ISNUMBER($AS5),$AR5>$AS5),"Inicio posterior a fecha límite"&" · ","")&IF(AND($V5="Macro",$H5<>"",OR(NOT(ISNUMBER($H5)),$H5<0,$H5>1)),"Peso fuera de rango"&" · ","")&IF(AND($V5="Sub",$H5<>"",OR(NOT(ISNUMBER($H5)),$H5<0,$H5>1)),"% de la subactividad fuera de rango 0-100%"&" · ","")&IF(AND(N($W5)>0,SUMIFS($H$5:$H$1000,$U$5:$U$1000,ROW(),$V$5:$V$1000,"Sub")>1.0001),"Las subactividades suman más de 100%"&" · ","")&IF(AND(N($W5)>0,OR(IF(ISNUMBER($I5),ROUND($I5,6)<>ROUND(MIN(1,SUMIFS($AD$5:$AD$1000,$U$5:$U$1000,ROW(),$V$5:$V$1000,"Sub")),6),FALSE),IF(ISNUMBER($J5),ROUND($J5,6)<>ROUND(MIN(1,SUMIFS($AE$5:$AE$1000,$U$5:$U$1000,ROW(),$V$5:$V$1000,"Sub")),6),FALSE),IF(ISNUMBER($K5),ROUND($K5,6)<>ROUND(MIN(1,SUMIFS($AF$5:$AF$1000,$U$5:$U$1000,ROW(),$V$5:$V$1000,"Sub")),6),FALSE),IF(ISNUMBER($L5),ROUND($L5,6)<>ROUND(MIN(1,SUMIFS($AG$5:$AG$1000,$U$5:$U$1000,ROW(),$V$5:$V$1000,"Sub")),6),FALSE))),"Con subactividades: no escriba en las semanas (se llenan solas)"&" · ","")&IF((COUNTIF($I5:$L5,">1")+COUNTIF($I5:$L5,"<0")+SUMPRODUCT((LEN($I5:$L5)>0)*NOT(ISNUMBER($I5:$L5))))>0,"Avance fuera de rango 0-100%"&" · ","")&IF(OR(AND(ISNUMBER($J5),$J5<N($I5)),AND(ISNUMBER($K5),$K5<MAX($I5:$J5)),AND(ISNUMBER($L5),$L5<MAX($I5:$K5))),"Avance semanal decreciente"&" · ","")&IF(AND(ISNUMBER($AS5),$AS5<FechaRef,IF($V5="Sub",1,N($M5))<1),"Vencida"&" · ","")&IF(AND(ObsObligatoria="Sí",ISNUMBER($AS5),$AS5<FechaRef,IF($V5="Sub",1,N($M5))<1,$Q5=""),"Vencida sin observación"&" · ",""),LEN(IF($C5="","Falta el nombre de la actividad"&" · ","")&IF(AND($V5="Sub",N($U5)=0),"Subactividad sin macroactividad arriba"&" · ","")&IF(AND($V5="Macro",$AR5=""),"Sin fecha de inicio"&" · ","")&IF(AND($V5="Macro",$AS5=""),"Sin fecha límite"&" · ","")&IF(AND(LEFT($C5,11)="[Jefatura] ",N($AQ5)=0),"No se encuentra en la hoja de la jefatura (elíjala de nuevo en la lista)"&" · ","")&IF(OR(AND($E5<>"",NOT(ISNUMBER($E5))),AND($F5<>"",NOT(ISNUMBER($F5))),AND($G5<>"",NOT(ISNUMBER($G5)))),"Fecha no válida"&" · ","")&IF(AND(ISNUMBER($AR5),ISNUMBER($AS5),$AR5>$AS5),"Inicio posterior a fecha límite"&" · ","")&IF(AND($V5="Macro",$H5<>"",OR(NOT(ISNUMBER($H5)),$H5<0,$H5>1)),"Peso fuera de rango"&" · ","")&IF(AND($V5="Sub",$H5<>"",OR(NOT(ISNUMBER($H5)),$H5<0,$H5>1)),"% de la subactividad fuera de rango 0-100%"&" · ","")&IF(AND(N($W5)>0,SUMIFS($H$5:$H$1000,$U$5:$U$1000,ROW(),$V$5:$V$1000,"Sub")>1.0001),"Las subactividades suman más de 100%"&" · ","")&IF(AND(N($W5)>0,OR(IF(ISNUMBER($I5),ROUND($I5,6)<>ROUND(MIN(1,SUMIFS($AD$5:$AD$1000,$U$5:$U$1000,ROW(),$V$5:$V$1000,"Sub")),6),FALSE),IF(ISNUMBER($J5),ROUND($J5,6)<>ROUND(MIN(1,SUMIFS($AE$5:$AE$1000,$U$5:$U$1000,ROW(),$V$5:$V$1000,"Sub")),6),FALSE),IF(ISNUMBER($K5),ROUND($K5,6)<>ROUND(MIN(1,SUMIFS($AF$5:$AF$1000,$U$5:$U$1000,ROW(),$V$5:$V$1000,"Sub")),6),FALSE),IF(ISNUMBER($L5),ROUND($L5,6)<>ROUND(MIN(1,SUMIFS($AG$5:$AG$1000,$U$5:$U$1000,ROW(),$V$5:$V$1000,"Sub")),6),FALSE))),"Con subactividades: no escriba en las semanas (se llenan solas)"&" · ","")&IF((COUNTIF($I5:$L5,">1")+COUNTIF($I5:$L5,"<0")+SUMPRODUCT((LEN($I5:$L5)>0)*NOT(ISNUMBER($I5:$L5))))>0,"Avance fuera de rango 0-100%"&" · ","")&IF(OR(AND(ISNUMBER($J5),$J5<N($I5)),AND(ISNUMBER($K5),$K5<MAX($I5:$J5)),AND(ISNUMBER($L5),$L5<MAX($I5:$K5))),"Avance semanal decreciente"&" · ","")&IF(AND(ISNUMBER($AS5),$AS5<FechaRef,IF($V5="Sub",1,N($M5))<1),"Vencida"&" · ","")&IF(AND(ObsObligatoria="Sí",ISNUMBER($AS5),$AS5<FechaRef,IF($V5="Sub",1,N($M5))<1,$Q5=""),"Vencida sin observación"&" · ",""))-3))) | S5: =IF(NOT((COUNTA($B5:$D5)+COUNTA($G5:$H5)+COUNTA($Q5))>0),"",IF(AND($V5="Sub",N($U5)>0),IF(ISNUMBER(INDEX($AR$5:$AR$1000,$U5-4)),DATE(YEAR(INDEX($AR$5:$AR$1000,$U5-4)),MONTH(INDEX($AR$5:$AR$1000,$U5-4)),1),IF(ISNUMBER(INDEX($AS$5:$AS$1000,$U5-4)),DATE(YEAR(INDEX($AS$5:$AS$1000,$U5-4)),MONTH(INDEX($AS$5:$AS$1000,$U5-4)),1),MesCiclo)),IF(ISNUMBER($AR5),DATE(YEAR($AR5),MONTH($AR5),1),IF(ISNUMBER($AS5),DATE(YEAR($AS5),MONTH($AS5),1),MesCiclo)))) | T5: =IF(OR($S5="",$S5<>MesCiclo,$V5<>"Macro"),"",COUNTIFS($S$5:$S5,MesCiclo,$V$5:$V5,"Macro")) | U5: =IF($V5="","",IF($V5="Macro",ROW(),IFERROR(LOOKUP(2,1/($V$5:$V5="Macro"),ROW($V$5:$V5)),0))) | V5: =IF(NOT((COUNTA($B5:$D5)+COUNTA($G5:$H5)+COUNTA($Q5))>0),"",IF($B5="Subactividad","Sub","Macro")) | W5: =IF($V5="Macro",COUNTIFS($U$5:$U$1000,ROW(),$V$5:$V$1000,"Sub"),"") | X5: =IF($V5<>"Sub","",IF(AND(ISNUMBER($H5),N($H5)>0),$H5,IFERROR(MAX(0,1-SUMIFS($H$5:$H$1000,$U$5:$U$1000,$U5,$V$5:$V$1000,"Sub"))/(COUNTIFS($U$5:$U$1000,$U5,$V$5:$V$1000,"Sub")-COUNTIFS($U$5:$U$1000,$U5,$V$5:$V$1000,"Sub",$H$5:$H$1000,">0")),0))) | Y5: =IF($V5="","",IF($V5="Sub",N($X5)*IF(ISNUMBER($G5),1,MIN(1,MAX(0,IFERROR(LOOKUP(2,1/ISNUMBER($I5:$L5),$I5:$L5),0)))),IF(ISNUMBER($G5),1,IFERROR(LOOKUP(2,1/($I5:$L5<>""),$I5:$L5),0)))) | Z5: =IF($V5="","",IF(AND(ISNUMBER($G5),$G5<=IF($S5=MesCiclo,InicioCiclo,$S5+MOD(2-WEEKDAY($S5),7))+6),1,IF(ISNUMBER($I5),$I5,0))) | AA5: =IF($V5="","",IF(AND(ISNUMBER($G5),$G5<=IF($S5=MesCiclo,InicioCiclo,$S5+MOD(2-WEEKDAY($S5),7))+13),1,IF(ISNUMBER($J5),$J5,$Z5))) | AB5: =IF($V5="","",IF(AND(ISNUMBER($G5),$G5<=IF($S5=MesCiclo,InicioCiclo,$S5+MOD(2-WEEKDAY($S5),7))+20),1,IF(ISNUMBER($K5),$K5,$AA5))) | AC5: =IF($V5="","",IF(AND(ISNUMBER($G5),$G5<=IF($S5=MesCiclo,InicioCiclo,$S5+MOD(2-WEEKDAY($S5),7))+27),1,IF(ISNUMBER($L5),$L5,$AB5))) | AD5: =IF($V5<>"Sub","",N($X5)*IF(AND(ISNUMBER($G5),$G5<=IF($S5=MesCiclo,InicioCiclo,$S5+MOD(2-WEEKDAY($S5),7))+6),1,MIN(1,MAX(0,IF(ISNUMBER(OFFSET($A$1,ROW()-1,8)),OFFSET($A$1,ROW()-1,8),0))))) | AE5: =IF($V5<>"Sub","",N($X5)*IF(AND(ISNUMBER($G5),$G5<=IF($S5=MesCiclo,InicioCiclo,$S5+MOD(2-WEEKDAY($S5),7))+13),1,MIN(1,MAX(0,IF(ISNUMBER(OFFSET($A$1,ROW()-1,9)),OFFSET($A$1,ROW()-1,9),IF(ISNUMBER(OFFSET($A$1,ROW()-1,8)),OFFSET($A$1,ROW()-1,8),0)))))) | AF5: =IF($V5<>"Sub","",N($X5)*IF(AND(ISNUMBER($G5),$G5<=IF($S5=MesCiclo,InicioCiclo,$S5+MOD(2-WEEKDAY($S5),7))+20),1,MIN(1,MAX(0,IF(ISNUMBER(OFFSET($A$1,ROW()-1,10)),OFFSET($A$1,ROW()-1,10),IF(ISNUMBER(OFFSET($A$1,ROW()-1,9)),OFFSET($A$1,ROW()-1,9),IF(ISNUMBER(OFFSET($A$1,ROW()-1,8)),OFFSET($A$1,ROW()-1,8),0))))))) | AG5: =IF($V5<>"Sub","",N($X5)*IF(AND(ISNUMBER($G5),$G5<=IF($S5=MesCiclo,InicioCiclo,$S5+MOD(2-WEEKDAY($S5),7))+27),1,MIN(1,MAX(0,IF(ISNUMBER(OFFSET($A$1,ROW()-1,11)),OFFSET($A$1,ROW()-1,11),IF(ISNUMBER(OFFSET($A$1,ROW()-1,10)),OFFSET($A$1,ROW()-1,10),IF(ISNUMBER(OFFSET($A$1,ROW()-1,9)),OFFSET($A$1,ROW()-1,9),IF(ISNUMBER(OFFSET($A$1,ROW()-1,8)),OFFSET($A$1,ROW()-1,8),0)))))))) | AH5: =IF($V5="","",IF(AND(ISNUMBER($G5),$G5<=IF($S5=MesCiclo,InicioCiclo,$S5+MOD(2-WEEKDAY($S5),7))+6),1,IF(N($W5)>0,MIN(1,SUMIFS($AD$5:$AD$1000,$U$5:$U$1000,ROW(),$V$5:$V$1000,"Sub")),$Z5))) | AI5: =IF($V5="","",IF(AND(ISNUMBER($G5),$G5<=IF($S5=MesCiclo,InicioCiclo,$S5+MOD(2-WEEKDAY($S5),7))+13),1,IF(N($W5)>0,MIN(1,SUMIFS($AE$5:$AE$1000,$U$5:$U$1000,ROW(),$V$5:$V$1000,"Sub")),$AA5))) | AJ5: =IF($V5="","",IF(AND(ISNUMBER($G5),$G5<=IF($S5=MesCiclo,InicioCiclo,$S5+MOD(2-WEEKDAY($S5),7))+20),1,IF(N($W5)>0,MIN(1,SUMIFS($AF$5:$AF$1000,$U$5:$U$1000,ROW(),$V$5:$V$1000,"Sub")),$AB5))) | AK5: =IF($V5="","",IF(AND(ISNUMBER($G5),$G5<=IF($S5=MesCiclo,InicioCiclo,$S5+MOD(2-WEEKDAY($S5),7))+27),1,IF(N($W5)>0,MIN(1,SUMIFS($AG$5:$AG$1000,$U$5:$U$1000,ROW(),$V$5:$V$1000,"Sub")),$AC5))) | AL5: =IF($V5<>"Macro","",IF(COUNTIFS($S$5:$S$1000,$S5,$V$5:$V$1000,"Macro",$H$5:$H$1000,">0")=0,1/COUNTIFS($S$5:$S$1000,$S5,$V$5:$V$1000,"Macro"),IF(AND(ISNUMBER($H5),N($H5)>0),$H5,SUMIFS($H$5:$H$1000,$S$5:$S$1000,$S5,$V$5:$V$1000,"Macro")/COUNTIFS($S$5:$S$1000,$S5,$V$5:$V$1000,"Macro",$H$5:$H$1000,">0"))/(COUNTIFS($S$5:$S$1000,$S5,$V$5:$V$1000,"Macro")*SUMIFS($H$5:$H$1000,$S$5:$S$1000,$S5,$V$5:$V$1000,"Macro")/COUNTIFS($S$5:$S$1000,$S5,$V$5:$V$1000,"Macro",$H$5:$H$1000,">0")))) | AM5: =IF(NOT(AND($D5<>"",$V5="Macro")),"",IFERROR(CHOOSE(MATCH($D5,ListaPuestos,0),MATCH("[Jefatura] "&$C5,'Cronograma R. Operacional'!$C$5:$C$1000,0),MATCH("[Jefatura] "&$C5,'Cronograma R. Normativo'!$C$5:$C$1000,0),MATCH("[Jefatura] "&$C5,'Cronograma R. Financiero'!$C$5:$C$1000,0),MATCH("[Jefatura] "&$C5,'Cronograma Asistente Técnico'!$C$5:$C$1000,0)),0)) | AN5: =IF(AND(AND($D5<>"",$V5="Macro"),$S5=MesCiclo),COUNTIFS($D$5:$D5,$D5,$S$5:$S5,MesCiclo,$V$5:$V5,"Macro"),"") | AO5: =IF($AN5="","",$D5&"|"&$AN5) | AP5: =IF(AND($D5<>"",$V5="Macro"),$D5&"|"&$C5,"") | AQ5: ="" | AR5: =IF(N($AQ5)>0,INDEX(rIni_ADM,$AQ5),IF(ISNUMBER($E5),$E5,"")) | AS5: =IF(N($AQ5)>0,INDEX(rLim_ADM,$AQ5),IF(ISNUMBER($F5),$F5,""))
A6: =IF(NOT((COUNTA($B6:$D6)+COUNTA($G6:$H6)+COUNTA($Q6))>0),"",IF($V6="Macro",COUNTIFS($V$5:$V6,"Macro",$S$5:$S6,$S6),IF(N($U6)=0,"?",COUNTIFS(INDEX($V$5:$V$1000,1):INDEX($V$5:$V$1000,$U6-4),"Macro",INDEX($S$5:$S$1000,1):INDEX($S$5:$S$1000,$U6-4),INDEX($S$5:$S$1000,$U6-4))&"."&COUNTIFS($U$5:$U6,$U6,$V$5:$V6,"Sub")))) | I6: =IF(N($W6)=0,"",IF(AND($S6=MesCiclo,1>SemanaActual),"",MIN(1,SUMIFS(OFFSET($A$1,ROW(),29,1000-ROW(),1),OFFSET($A$1,ROW(),20,1000-ROW(),1),ROW(),OFFSET($A$1,ROW(),21,1000-ROW(),1),"Sub")))) | J6: =IF(N($W6)=0,"",IF(AND($S6=MesCiclo,2>SemanaActual),"",MIN(1,SUMIFS(OFFSET($A$1,ROW(),30,1000-ROW(),1),OFFSET($A$1,ROW(),20,1000-ROW(),1),ROW(),OFFSET($A$1,ROW(),21,1000-ROW(),1),"Sub")))) | K6: =IF(N($W6)=0,"",IF(AND($S6=MesCiclo,3>SemanaActual),"",MIN(1,SUMIFS(OFFSET($A$1,ROW(),31,1000-ROW(),1),OFFSET($A$1,ROW(),20,1000-ROW(),1),ROW(),OFFSET($A$1,ROW(),21,1000-ROW(),1),"Sub")))) | L6: =IF(N($W6)=0,"",IF(AND($S6=MesCiclo,4>SemanaActual),"",MIN(1,SUMIFS(OFFSET($A$1,ROW(),32,1000-ROW(),1),OFFSET($A$1,ROW(),20,1000-ROW(),1),ROW(),OFFSET($A$1,ROW(),21,1000-ROW(),1),"Sub")))) | M6: =IF(NOT((COUNTA($B6:$D6)+COUNTA($G6:$H6)+COUNTA($Q6))>0),"",IF(AND($D6<>"",$V6="Macro"),IF(N($AM6)>0,N(CHOOSE(MATCH($D6,ListaPuestos,0),INDEX('Cronograma R. Operacional'!$M$5:$M$1000,$AM6),INDEX('Cronograma R. Normativo'!$M$5:$M$1000,$AM6),INDEX('Cronograma R. Financiero'!$M$5:$M$1000,$AM6),INDEX('Cronograma Asistente Técnico'!$M$5:$M$1000,$AM6))),0),IF(ISNUMBER($G6),1,IF(N($W6)>0,MIN(1,SUMIFS($Y$5:$Y$1000,$U$5:$U$1000,ROW(),$V$5:$V$1000,"Sub")),$Y6)))) | N6: =IF(OR($M6="",$V6="Sub"),"",IF($M6>=1,"Completado",IF($M6>0,"En curso","Pendiente"))) | O6: =IF(NOT((COUNTA($B6:$D6)+COUNTA($G6:$H6)+COUNTA($Q6))>0),"",IF(AND(AND($D6<>"",$V6="Macro"),N($AM6)>0),CHOOSE(MATCH($D6,ListaPuestos,0),INDEX('Cronograma R. Operacional'!$O$5:$O$1000,$AM6),INDEX('Cronograma R. Normativo'!$O$5:$O$1000,$AM6),INDEX('Cronograma R. Financiero'!$O$5:$O$1000,$AM6),INDEX('Cronograma Asistente Técnico'!$O$5:$O$1000,$AM6))&"",IF(ISNUMBER($G6),IF(AND(ISNUMBER($AS6),$G6>$AS6),"Cumplida con "&($G6-$AS6)&IF($G6-$AS6=1," día"," días")&" de retraso","Cumplida"),IF(N($M6)>=1,"Cumplida",IF(NOT(ISNUMBER($AS6)),"Sin fecha límite",IF($AS6<FechaRef,"Vencida hace "&(FechaRef-$AS6)&IF(FechaRef-$AS6=1," día"," días"),IF($AS6=FechaRef,"Vence hoy",IF($AS6-FechaRef<=DiasAlerta,"Vence en "&($AS6-FechaRef)&IF($AS6-FechaRef=1," día"," días"),"En plazo")))))))) | P6: =IF(NOT((COUNTA($B6:$D6)+COUNTA($G6:$H6)+COUNTA($Q6))>0),"",IF($D6="","Propia",IF($V6<>"Macro","Solo se delegan macroactividades",IF(N($AM6)>0,"✔ Recibida por "&$D6,"⚠ "&$D6&" aún no la agrega")))) | R6: =IF(NOT((COUNTA($B6:$D6)+COUNTA($G6:$H6)+COUNTA($Q6))>0),"",IF((IF($C6="","Falta el nombre de la actividad"&" · ","")&IF(AND($V6="Sub",N($U6)=0),"Subactividad sin macroactividad arriba"&" · ","")&IF(AND($V6="Macro",$AR6=""),"Sin fecha de inicio"&" · ","")&IF(AND($V6="Macro",$AS6=""),"Sin fecha límite"&" · ","")&IF(AND(LEFT($C6,11)="[Jefatura] ",N($AQ6)=0),"No se encuentra en la hoja de la jefatura (elíjala de nuevo en la lista)"&" · ","")&IF(OR(AND($E6<>"",NOT(ISNUMBER($E6))),AND($F6<>"",NOT(ISNUMBER($F6))),AND($G6<>"",NOT(ISNUMBER($G6)))),"Fecha no válida"&" · ","")&IF(AND(ISNUMBER($AR6),ISNUMBER($AS6),$AR6>$AS6),"Inicio posterior a fecha límite"&" · ","")&IF(AND($V6="Macro",$H6<>"",OR(NOT(ISNUMBER($H6)),$H6<0,$H6>1)),"Peso fuera de rango"&" · ","")&IF(AND($V6="Sub",$H6<>"",OR(NOT(ISNUMBER($H6)),$H6<0,$H6>1)),"% de la subactividad fuera de rango 0-100%"&" · ","")&IF(AND(N($W6)>0,SUMIFS($H$5:$H$1000,$U$5:$U$1000,ROW(),$V$5:$V$1000,"Sub")>1.0001),"Las subactividades suman más de 100%"&" · ","")&IF(AND(N($W6)>0,OR(IF(ISNUMBER($I6),ROUND($I6,6)<>ROUND(MIN(1,SUMIFS($AD$5:$AD$1000,$U$5:$U$1000,ROW(),$V$5:$V$1000,"Sub")),6),FALSE),IF(ISNUMBER($J6),ROUND($J6,6)<>ROUND(MIN(1,SUMIFS($AE$5:$AE$1000,$U$5:$U$1000,ROW(),$V$5:$V$1000,"Sub")),6),FALSE),IF(ISNUMBER($K6),ROUND($K6,6)<>ROUND(MIN(1,SUMIFS($AF$5:$AF$1000,$U$5:$U$1000,ROW(),$V$5:$V$1000,"Sub")),6),FALSE),IF(ISNUMBER($L6),ROUND($L6,6)<>ROUND(MIN(1,SUMIFS($AG$5:$AG$1000,$U$5:$U$1000,ROW(),$V$5:$V$1000,"Sub")),6),FALSE))),"Con subactividades: no escriba en las semanas (se llenan solas)"&" · ","")&IF((COUNTIF($I6:$L6,">1")+COUNTIF($I6:$L6,"<0")+SUMPRODUCT((LEN($I6:$L6)>0)*NOT(ISNUMBER($I6:$L6))))>0,"Avance fuera de rango 0-100%"&" · ","")&IF(OR(AND(ISNUMBER($J6),$J6<N($I6)),AND(ISNUMBER($K6),$K6<MAX($I6:$J6)),AND(ISNUMBER($L6),$L6<MAX($I6:$K6))),"Avance semanal decreciente"&" · ","")&IF(AND(ISNUMBER($AS6),$AS6<FechaRef,IF($V6="Sub",1,N($M6))<1),"Vencida"&" · ","")&IF(AND(ObsObligatoria="Sí",ISNUMBER($AS6),$AS6<FechaRef,IF($V6="Sub",1,N($M6))<1,$Q6=""),"Vencida sin observación"&" · ",""))="","✔ OK","⚠ "&LEFT(IF($C6="","Falta el nombre de la actividad"&" · ","")&IF(AND($V6="Sub",N($U6)=0),"Subactividad sin macroactividad arriba"&" · ","")&IF(AND($V6="Macro",$AR6=""),"Sin fecha de inicio"&" · ","")&IF(AND($V6="Macro",$AS6=""),"Sin fecha límite"&" · ","")&IF(AND(LEFT($C6,11)="[Jefatura] ",N($AQ6)=0),"No se encuentra en la hoja de la jefatura (elíjala de nuevo en la lista)"&" · ","")&IF(OR(AND($E6<>"",NOT(ISNUMBER($E6))),AND($F6<>"",NOT(ISNUMBER($F6))),AND($G6<>"",NOT(ISNUMBER($G6)))),"Fecha no válida"&" · ","")&IF(AND(ISNUMBER($AR6),ISNUMBER($AS6),$AR6>$AS6),"Inicio posterior a fecha límite"&" · ","")&IF(AND($V6="Macro",$H6<>"",OR(NOT(ISNUMBER($H6)),$H6<0,$H6>1)),"Peso fuera de rango"&" · ","")&IF(AND($V6="Sub",$H6<>"",OR(NOT(ISNUMBER($H6)),$H6<0,$H6>1)),"% de la subactividad fuera de rango 0-100%"&" · ","")&IF(AND(N($W6)>0,SUMIFS($H$5:$H$1000,$U$5:$U$1000,ROW(),$V$5:$V$1000,"Sub")>1.0001),"Las subactividades suman más de 100%"&" · ","")&IF(AND(N($W6)>0,OR(IF(ISNUMBER($I6),ROUND($I6,6)<>ROUND(MIN(1,SUMIFS($AD$5:$AD$1000,$U$5:$U$1000,ROW(),$V$5:$V$1000,"Sub")),6),FALSE),IF(ISNUMBER($J6),ROUND($J6,6)<>ROUND(MIN(1,SUMIFS($AE$5:$AE$1000,$U$5:$U$1000,ROW(),$V$5:$V$1000,"Sub")),6),FALSE),IF(ISNUMBER($K6),ROUND($K6,6)<>ROUND(MIN(1,SUMIFS($AF$5:$AF$1000,$U$5:$U$1000,ROW(),$V$5:$V$1000,"Sub")),6),FALSE),IF(ISNUMBER($L6),ROUND($L6,6)<>ROUND(MIN(1,SUMIFS($AG$5:$AG$1000,$U$5:$U$1000,ROW(),$V$5:$V$1000,"Sub")),6),FALSE))),"Con subactividades: no escriba en las semanas (se llenan solas)"&" · ","")&IF((COUNTIF($I6:$L6,">1")+COUNTIF($I6:$L6,"<0")+SUMPRODUCT((LEN($I6:$L6)>0)*NOT(ISNUMBER($I6:$L6))))>0,"Avance fuera de rango 0-100%"&" · ","")&IF(OR(AND(ISNUMBER($J6),$J6<N($I6)),AND(ISNUMBER($K6),$K6<MAX($I6:$J6)),AND(ISNUMBER($L6),$L6<MAX($I6:$K6))),"Avance semanal decreciente"&" · ","")&IF(AND(ISNUMBER($AS6),$AS6<FechaRef,IF($V6="Sub",1,N($M6))<1),"Vencida"&" · ","")&IF(AND(ObsObligatoria="Sí",ISNUMBER($AS6),$AS6<FechaRef,IF($V6="Sub",1,N($M6))<1,$Q6=""),"Vencida sin observación"&" · ",""),LEN(IF($C6="","Falta el nombre de la actividad"&" · ","")&IF(AND($V6="Sub",N($U6)=0),"Subactividad sin macroactividad arriba"&" · ","")&IF(AND($V6="Macro",$AR6=""),"Sin fecha de inicio"&" · ","")&IF(AND($V6="Macro",$AS6=""),"Sin fecha límite"&" · ","")&IF(AND(LEFT($C6,11)="[Jefatura] ",N($AQ6)=0),"No se encuentra en la hoja de la jefatura (elíjala de nuevo en la lista)"&" · ","")&IF(OR(AND($E6<>"",NOT(ISNUMBER($E6))),AND($F6<>"",NOT(ISNUMBER($F6))),AND($G6<>"",NOT(ISNUMBER($G6)))),"Fecha no válida"&" · ","")&IF(AND(ISNUMBER($AR6),ISNUMBER($AS6),$AR6>$AS6),"Inicio posterior a fecha límite"&" · ","")&IF(AND($V6="Macro",$H6<>"",OR(NOT(ISNUMBER($H6)),$H6<0,$H6>1)),"Peso fuera de rango"&" · ","")&IF(AND($V6="Sub",$H6<>"",OR(NOT(ISNUMBER($H6)),$H6<0,$H6>1)),"% de la subactividad fuera de rango 0-100%"&" · ","")&IF(AND(N($W6)>0,SUMIFS($H$5:$H$1000,$U$5:$U$1000,ROW(),$V$5:$V$1000,"Sub")>1.0001),"Las subactividades suman más de 100%"&" · ","")&IF(AND(N($W6)>0,OR(IF(ISNUMBER($I6),ROUND($I6,6)<>ROUND(MIN(1,SUMIFS($AD$5:$AD$1000,$U$5:$U$1000,ROW(),$V$5:$V$1000,"Sub")),6),FALSE),IF(ISNUMBER($J6),ROUND($J6,6)<>ROUND(MIN(1,SUMIFS($AE$5:$AE$1000,$U$5:$U$1000,ROW(),$V$5:$V$1000,"Sub")),6),FALSE),IF(ISNUMBER($K6),ROUND($K6,6)<>ROUND(MIN(1,SUMIFS($AF$5:$AF$1000,$U$5:$U$1000,ROW(),$V$5:$V$1000,"Sub")),6),FALSE),IF(ISNUMBER($L6),ROUND($L6,6)<>ROUND(MIN(1,SUMIFS($AG$5:$AG$1000,$U$5:$U$1000,ROW(),$V$5:$V$1000,"Sub")),6),FALSE))),"Con subactividades: no escriba en las semanas (se llenan solas)"&" · ","")&IF((COUNTIF($I6:$L6,">1")+COUNTIF($I6:$L6,"<0")+SUMPRODUCT((LEN($I6:$L6)>0)*NOT(ISNUMBER($I6:$L6))))>0,"Avance fuera de rango 0-100%"&" · ","")&IF(OR(AND(ISNUMBER($J6),$J6<N($I6)),AND(ISNUMBER($K6),$K6<MAX($I6:$J6)),AND(ISNUMBER($L6),$L6<MAX($I6:$K6))),"Avance semanal decreciente"&" · ","")&IF(AND(ISNUMBER($AS6),$AS6<FechaRef,IF($V6="Sub",1,N($M6))<1),"Vencida"&" · ","")&IF(AND(ObsObligatoria="Sí",ISNUMBER($AS6),$AS6<FechaRef,IF($V6="Sub",1,N($M6))<1,$Q6=""),"Vencida sin observación"&" · ",""))-3))) | S6: =IF(NOT((COUNTA($B6:$D6)+COUNTA($G6:$H6)+COUNTA($Q6))>0),"",IF(AND($V6="Sub",N($U6)>0),IF(ISNUMBER(INDEX($AR$5:$AR$1000,$U6-4)),DATE(YEAR(INDEX($AR$5:$AR$1000,$U6-4)),MONTH(INDEX($AR$5:$AR$1000,$U6-4)),1),IF(ISNUMBER(INDEX($AS$5:$AS$1000,$U6-4)),DATE(YEAR(INDEX($AS$5:$AS$1000,$U6-4)),MONTH(INDEX($AS$5:$AS$1000,$U6-4)),1),MesCiclo)),IF(ISNUMBER($AR6),DATE(YEAR($AR6),MONTH($AR6),1),IF(ISNUMBER($AS6),DATE(YEAR($AS6),MONTH($AS6),1),MesCiclo)))) | T6: =IF(OR($S6="",$S6<>MesCiclo,$V6<>"Macro"),"",COUNTIFS($S$5:$S6,MesCiclo,$V$5:$V6,"Macro")) | U6: =IF($V6="","",IF($V6="Macro",ROW(),IFERROR(LOOKUP(2,1/($V$5:$V6="Macro"),ROW($V$5:$V6)),0))) | V6: =IF(NOT((COUNTA($B6:$D6)+COUNTA($G6:$H6)+COUNTA($Q6))>0),"",IF($B6="Subactividad","Sub","Macro")) | W6: =IF($V6="Macro",COUNTIFS($U$5:$U$1000,ROW(),$V$5:$V$1000,"Sub"),"") | X6: =IF($V6<>"Sub","",IF(AND(ISNUMBER($H6),N($H6)>0),$H6,IFERROR(MAX(0,1-SUMIFS($H$5:$H$1000,$U$5:$U$1000,$U6,$V$5:$V$1000,"Sub"))/(COUNTIFS($U$5:$U$1000,$U6,$V$5:$V$1000,"Sub")-COUNTIFS($U$5:$U$1000,$U6,$V$5:$V$1000,"Sub",$H$5:$H$1000,">0")),0))) | Y6: =IF($V6="","",IF($V6="Sub",N($X6)*IF(ISNUMBER($G6),1,MIN(1,MAX(0,IFERROR(LOOKUP(2,1/ISNUMBER($I6:$L6),$I6:$L6),0)))),IF(ISNUMBER($G6),1,IFERROR(LOOKUP(2,1/($I6:$L6<>""),$I6:$L6),0)))) | Z6: =IF($V6="","",IF(AND(ISNUMBER($G6),$G6<=IF($S6=MesCiclo,InicioCiclo,$S6+MOD(2-WEEKDAY($S6),7))+6),1,IF(ISNUMBER($I6),$I6,0))) | AA6: =IF($V6="","",IF(AND(ISNUMBER($G6),$G6<=IF($S6=MesCiclo,InicioCiclo,$S6+MOD(2-WEEKDAY($S6),7))+13),1,IF(ISNUMBER($J6),$J6,$Z6))) | AB6: =IF($V6="","",IF(AND(ISNUMBER($G6),$G6<=IF($S6=MesCiclo,InicioCiclo,$S6+MOD(2-WEEKDAY($S6),7))+20),1,IF(ISNUMBER($K6),$K6,$AA6))) | AC6: =IF($V6="","",IF(AND(ISNUMBER($G6),$G6<=IF($S6=MesCiclo,InicioCiclo,$S6+MOD(2-WEEKDAY($S6),7))+27),1,IF(ISNUMBER($L6),$L6,$AB6))) | AD6: =IF($V6<>"Sub","",N($X6)*IF(AND(ISNUMBER($G6),$G6<=IF($S6=MesCiclo,InicioCiclo,$S6+MOD(2-WEEKDAY($S6),7))+6),1,MIN(1,MAX(0,IF(ISNUMBER(OFFSET($A$1,ROW()-1,8)),OFFSET($A$1,ROW()-1,8),0))))) | AE6: =IF($V6<>"Sub","",N($X6)*IF(AND(ISNUMBER($G6),$G6<=IF($S6=MesCiclo,InicioCiclo,$S6+MOD(2-WEEKDAY($S6),7))+13),1,MIN(1,MAX(0,IF(ISNUMBER(OFFSET($A$1,ROW()-1,9)),OFFSET($A$1,ROW()-1,9),IF(ISNUMBER(OFFSET($A$1,ROW()-1,8)),OFFSET($A$1,ROW()-1,8),0)))))) | AF6: =IF($V6<>"Sub","",N($X6)*IF(AND(ISNUMBER($G6),$G6<=IF($S6=MesCiclo,InicioCiclo,$S6+MOD(2-WEEKDAY($S6),7))+20),1,MIN(1,MAX(0,IF(ISNUMBER(OFFSET($A$1,ROW()-1,10)),OFFSET($A$1,ROW()-1,10),IF(ISNUMBER(OFFSET($A$1,ROW()-1,9)),OFFSET($A$1,ROW()-1,9),IF(ISNUMBER(OFFSET($A$1,ROW()-1,8)),OFFSET($A$1,ROW()-1,8),0))))))) | AG6: =IF($V6<>"Sub","",N($X6)*IF(AND(ISNUMBER($G6),$G6<=IF($S6=MesCiclo,InicioCiclo,$S6+MOD(2-WEEKDAY($S6),7))+27),1,MIN(1,MAX(0,IF(ISNUMBER(OFFSET($A$1,ROW()-1,11)),OFFSET($A$1,ROW()-1,11),IF(ISNUMBER(OFFSET($A$1,ROW()-1,10)),OFFSET($A$1,ROW()-1,10),IF(ISNUMBER(OFFSET($A$1,ROW()-1,9)),OFFSET($A$1,ROW()-1,9),IF(ISNUMBER(OFFSET($A$1,ROW()-1,8)),OFFSET($A$1,ROW()-1,8),0)))))))) | AH6: =IF($V6="","",IF(AND(ISNUMBER($G6),$G6<=IF($S6=MesCiclo,InicioCiclo,$S6+MOD(2-WEEKDAY($S6),7))+6),1,IF(N($W6)>0,MIN(1,SUMIFS($AD$5:$AD$1000,$U$5:$U$1000,ROW(),$V$5:$V$1000,"Sub")),$Z6))) | AI6: =IF($V6="","",IF(AND(ISNUMBER($G6),$G6<=IF($S6=MesCiclo,InicioCiclo,$S6+MOD(2-WEEKDAY($S6),7))+13),1,IF(N($W6)>0,MIN(1,SUMIFS($AE$5:$AE$1000,$U$5:$U$1000,ROW(),$V$5:$V$1000,"Sub")),$AA6))) | AJ6: =IF($V6="","",IF(AND(ISNUMBER($G6),$G6<=IF($S6=MesCiclo,InicioCiclo,$S6+MOD(2-WEEKDAY($S6),7))+20),1,IF(N($W6)>0,MIN(1,SUMIFS($AF$5:$AF$1000,$U$5:$U$1000,ROW(),$V$5:$V$1000,"Sub")),$AB6))) | AK6: =IF($V6="","",IF(AND(ISNUMBER($G6),$G6<=IF($S6=MesCiclo,InicioCiclo,$S6+MOD(2-WEEKDAY($S6),7))+27),1,IF(N($W6)>0,MIN(1,SUMIFS($AG$5:$AG$1000,$U$5:$U$1000,ROW(),$V$5:$V$1000,"Sub")),$AC6))) | AL6: =IF($V6<>"Macro","",IF(COUNTIFS($S$5:$S$1000,$S6,$V$5:$V$1000,"Macro",$H$5:$H$1000,">0")=0,1/COUNTIFS($S$5:$S$1000,$S6,$V$5:$V$1000,"Macro"),IF(AND(ISNUMBER($H6),N($H6)>0),$H6,SUMIFS($H$5:$H$1000,$S$5:$S$1000,$S6,$V$5:$V$1000,"Macro")/COUNTIFS($S$5:$S$1000,$S6,$V$5:$V$1000,"Macro",$H$5:$H$1000,">0"))/(COUNTIFS($S$5:$S$1000,$S6,$V$5:$V$1000,"Macro")*SUMIFS($H$5:$H$1000,$S$5:$S$1000,$S6,$V$5:$V$1000,"Macro")/COUNTIFS($S$5:$S$1000,$S6,$V$5:$V$1000,"Macro",$H$5:$H$1000,">0")))) | AM6: =IF(NOT(AND($D6<>"",$V6="Macro")),"",IFERROR(CHOOSE(MATCH($D6,ListaPuestos,0),MATCH("[Jefatura] "&$C6,'Cronograma R. Operacional'!$C$5:$C$1000,0),MATCH("[Jefatura] "&$C6,'Cronograma R. Normativo'!$C$5:$C$1000,0),MATCH("[Jefatura] "&$C6,'Cronograma R. Financiero'!$C$5:$C$1000,0),MATCH("[Jefatura] "&$C6,'Cronograma Asistente Técnico'!$C$5:$C$1000,0)),0)) | AN6: =IF(AND(AND($D6<>"",$V6="Macro"),$S6=MesCiclo),COUNTIFS($D$5:$D6,$D6,$S$5:$S6,MesCiclo,$V$5:$V6,"Macro"),"") | AO6: =IF($AN6="","",$D6&"|"&$AN6) | AP6: =IF(AND($D6<>"",$V6="Macro"),$D6&"|"&$C6,"") | AQ6: ="" | AR6: =IF(N($AQ6)>0,INDEX(rIni_ADM,$AQ6),IF(ISNUMBER($E6),$E6,"")) | AS6: =IF(N($AQ6)>0,INDEX(rLim_ADM,$AQ6),IF(ISNUMBER($F6),$F6,""))
A7: =IF(NOT((COUNTA($B7:$D7)+COUNTA($G7:$H7)+COUNTA($Q7))>0),"",IF($V7="Macro",COUNTIFS($V$5:$V7,"Macro",$S$5:$S7,$S7),IF(N($U7)=0,"?",COUNTIFS(INDEX($V$5:$V$1000,1):INDEX($V$5:$V$1000,$U7-4),"Macro",INDEX($S$5:$S$1000,1):INDEX($S$5:$S$1000,$U7-4),INDEX($S$5:$S$1000,$U7-4))&"."&COUNTIFS($U$5:$U7,$U7,$V$5:$V7,"Sub")))) | I7: =IF(N($W7)=0,"",IF(AND($S7=MesCiclo,1>SemanaActual),"",MIN(1,SUMIFS(OFFSET($A$1,ROW(),29,1000-ROW(),1),OFFSET($A$1,ROW(),20,1000-ROW(),1),ROW(),OFFSET($A$1,ROW(),21,1000-ROW(),1),"Sub")))) | J7: =IF(N($W7)=0,"",IF(AND($S7=MesCiclo,2>SemanaActual),"",MIN(1,SUMIFS(OFFSET($A$1,ROW(),30,1000-ROW(),1),OFFSET($A$1,ROW(),20,1000-ROW(),1),ROW(),OFFSET($A$1,ROW(),21,1000-ROW(),1),"Sub")))) | K7: =IF(N($W7)=0,"",IF(AND($S7=MesCiclo,3>SemanaActual),"",MIN(1,SUMIFS(OFFSET($A$1,ROW(),31,1000-ROW(),1),OFFSET($A$1,ROW(),20,1000-ROW(),1),ROW(),OFFSET($A$1,ROW(),21,1000-ROW(),1),"Sub")))) | L7: =IF(N($W7)=0,"",IF(AND($S7=MesCiclo,4>SemanaActual),"",MIN(1,SUMIFS(OFFSET($A$1,ROW(),32,1000-ROW(),1),OFFSET($A$1,ROW(),20,1000-ROW(),1),ROW(),OFFSET($A$1,ROW(),21,1000-ROW(),1),"Sub")))) | M7: =IF(NOT((COUNTA($B7:$D7)+COUNTA($G7:$H7)+COUNTA($Q7))>0),"",IF(AND($D7<>"",$V7="Macro"),IF(N($AM7)>0,N(CHOOSE(MATCH($D7,ListaPuestos,0),INDEX('Cronograma R. Operacional'!$M$5:$M$1000,$AM7),INDEX('Cronograma R. Normativo'!$M$5:$M$1000,$AM7),INDEX('Cronograma R. Financiero'!$M$5:$M$1000,$AM7),INDEX('Cronograma Asistente Técnico'!$M$5:$M$1000,$AM7))),0),IF(ISNUMBER($G7),1,IF(N($W7)>0,MIN(1,SUMIFS($Y$5:$Y$1000,$U$5:$U$1000,ROW(),$V$5:$V$1000,"Sub")),$Y7)))) | N7: =IF(OR($M7="",$V7="Sub"),"",IF($M7>=1,"Completado",IF($M7>0,"En curso","Pendiente"))) | O7: =IF(NOT((COUNTA($B7:$D7)+COUNTA($G7:$H7)+COUNTA($Q7))>0),"",IF(AND(AND($D7<>"",$V7="Macro"),N($AM7)>0),CHOOSE(MATCH($D7,ListaPuestos,0),INDEX('Cronograma R. Operacional'!$O$5:$O$1000,$AM7),INDEX('Cronograma R. Normativo'!$O$5:$O$1000,$AM7),INDEX('Cronograma R. Financiero'!$O$5:$O$1000,$AM7),INDEX('Cronograma Asistente Técnico'!$O$5:$O$1000,$AM7))&"",IF(ISNUMBER($G7),IF(AND(ISNUMBER($AS7),$G7>$AS7),"Cumplida con "&($G7-$AS7)&IF($G7-$AS7=1," día"," días")&" de retraso","Cumplida"),IF(N($M7)>=1,"Cumplida",IF(NOT(ISNUMBER($AS7)),"Sin fecha límite",IF($AS7<FechaRef,"Vencida hace "&(FechaRef-$AS7)&IF(FechaRef-$AS7=1," día"," días"),IF($AS7=FechaRef,"Vence hoy",IF($AS7-FechaRef<=DiasAlerta,"Vence en "&($AS7-FechaRef)&IF($AS7-FechaRef=1," día"," días"),"En plazo")))))))) | P7: =IF(NOT((COUNTA($B7:$D7)+COUNTA($G7:$H7)+COUNTA($Q7))>0),"",IF($D7="","Propia",IF($V7<>"Macro","Solo se delegan macroactividades",IF(N($AM7)>0,"✔ Recibida por "&$D7,"⚠ "&$D7&" aún no la agrega")))) | R7: =IF(NOT((COUNTA($B7:$D7)+COUNTA($G7:$H7)+COUNTA($Q7))>0),"",IF((IF($C7="","Falta el nombre de la actividad"&" · ","")&IF(AND($V7="Sub",N($U7)=0),"Subactividad sin macroactividad arriba"&" · ","")&IF(AND($V7="Macro",$AR7=""),"Sin fecha de inicio"&" · ","")&IF(AND($V7="Macro",$AS7=""),"Sin fecha límite"&" · ","")&IF(AND(LEFT($C7,11)="[Jefatura] ",N($AQ7)=0),"No se encuentra en la hoja de la jefatura (elíjala de nuevo en la lista)"&" · ","")&IF(OR(AND($E7<>"",NOT(ISNUMBER($E7))),AND($F7<>"",NOT(ISNUMBER($F7))),AND($G7<>"",NOT(ISNUMBER($G7)))),"Fecha no válida"&" · ","")&IF(AND(ISNUMBER($AR7),ISNUMBER($AS7),$AR7>$AS7),"Inicio posterior a fecha límite"&" · ","")&IF(AND($V7="Macro",$H7<>"",OR(NOT(ISNUMBER($H7)),$H7<0,$H7>1)),"Peso fuera de rango"&" · ","")&IF(AND($V7="Sub",$H7<>"",OR(NOT(ISNUMBER($H7)),$H7<0,$H7>1)),"% de la subactividad fuera de rango 0-100%"&" · ","")&IF(AND(N($W7)>0,SUMIFS($H$5:$H$1000,$U$5:$U$1000,ROW(),$V$5:$V$1000,"Sub")>1.0001),"Las subactividades suman más de 100%"&" · ","")&IF(AND(N($W7)>0,OR(IF(ISNUMBER($I7),ROUND($I7,6)<>ROUND(MIN(1,SUMIFS($AD$5:$AD$1000,$U$5:$U$1000,ROW(),$V$5:$V$1000,"Sub")),6),FALSE),IF(ISNUMBER($J7),ROUND($J7,6)<>ROUND(MIN(1,SUMIFS($AE$5:$AE$1000,$U$5:$U$1000,ROW(),$V$5:$V$1000,"Sub")),6),FALSE),IF(ISNUMBER($K7),ROUND($K7,6)<>ROUND(MIN(1,SUMIFS($AF$5:$AF$1000,$U$5:$U$1000,ROW(),$V$5:$V$1000,"Sub")),6),FALSE),IF(ISNUMBER($L7),ROUND($L7,6)<>ROUND(MIN(1,SUMIFS($AG$5:$AG$1000,$U$5:$U$1000,ROW(),$V$5:$V$1000,"Sub")),6),FALSE))),"Con subactividades: no escriba en las semanas (se llenan solas)"&" · ","")&IF((COUNTIF($I7:$L7,">1")+COUNTIF($I7:$L7,"<0")+SUMPRODUCT((LEN($I7:$L7)>0)*NOT(ISNUMBER($I7:$L7))))>0,"Avance fuera de rango 0-100%"&" · ","")&IF(OR(AND(ISNUMBER($J7),$J7<N($I7)),AND(ISNUMBER($K7),$K7<MAX($I7:$J7)),AND(ISNUMBER($L7),$L7<MAX($I7:$K7))),"Avance semanal decreciente"&" · ","")&IF(AND(ISNUMBER($AS7),$AS7<FechaRef,IF($V7="Sub",1,N($M7))<1),"Vencida"&" · ","")&IF(AND(ObsObligatoria="Sí",ISNUMBER($AS7),$AS7<FechaRef,IF($V7="Sub",1,N($M7))<1,$Q7=""),"Vencida sin observación"&" · ",""))="","✔ OK","⚠ "&LEFT(IF($C7="","Falta el nombre de la actividad"&" · ","")&IF(AND($V7="Sub",N($U7)=0),"Subactividad sin macroactividad arriba"&" · ","")&IF(AND($V7="Macro",$AR7=""),"Sin fecha de inicio"&" · ","")&IF(AND($V7="Macro",$AS7=""),"Sin fecha límite"&" · ","")&IF(AND(LEFT($C7,11)="[Jefatura] ",N($AQ7)=0),"No se encuentra en la hoja de la jefatura (elíjala de nuevo en la lista)"&" · ","")&IF(OR(AND($E7<>"",NOT(ISNUMBER($E7))),AND($F7<>"",NOT(ISNUMBER($F7))),AND($G7<>"",NOT(ISNUMBER($G7)))),"Fecha no válida"&" · ","")&IF(AND(ISNUMBER($AR7),ISNUMBER($AS7),$AR7>$AS7),"Inicio posterior a fecha límite"&" · ","")&IF(AND($V7="Macro",$H7<>"",OR(NOT(ISNUMBER($H7)),$H7<0,$H7>1)),"Peso fuera de rango"&" · ","")&IF(AND($V7="Sub",$H7<>"",OR(NOT(ISNUMBER($H7)),$H7<0,$H7>1)),"% de la subactividad fuera de rango 0-100%"&" · ","")&IF(AND(N($W7)>0,SUMIFS($H$5:$H$1000,$U$5:$U$1000,ROW(),$V$5:$V$1000,"Sub")>1.0001),"Las subactividades suman más de 100%"&" · ","")&IF(AND(N($W7)>0,OR(IF(ISNUMBER($I7),ROUND($I7,6)<>ROUND(MIN(1,SUMIFS($AD$5:$AD$1000,$U$5:$U$1000,ROW(),$V$5:$V$1000,"Sub")),6),FALSE),IF(ISNUMBER($J7),ROUND($J7,6)<>ROUND(MIN(1,SUMIFS($AE$5:$AE$1000,$U$5:$U$1000,ROW(),$V$5:$V$1000,"Sub")),6),FALSE),IF(ISNUMBER($K7),ROUND($K7,6)<>ROUND(MIN(1,SUMIFS($AF$5:$AF$1000,$U$5:$U$1000,ROW(),$V$5:$V$1000,"Sub")),6),FALSE),IF(ISNUMBER($L7),ROUND($L7,6)<>ROUND(MIN(1,SUMIFS($AG$5:$AG$1000,$U$5:$U$1000,ROW(),$V$5:$V$1000,"Sub")),6),FALSE))),"Con subactividades: no escriba en las semanas (se llenan solas)"&" · ","")&IF((COUNTIF($I7:$L7,">1")+COUNTIF($I7:$L7,"<0")+SUMPRODUCT((LEN($I7:$L7)>0)*NOT(ISNUMBER($I7:$L7))))>0,"Avance fuera de rango 0-100%"&" · ","")&IF(OR(AND(ISNUMBER($J7),$J7<N($I7)),AND(ISNUMBER($K7),$K7<MAX($I7:$J7)),AND(ISNUMBER($L7),$L7<MAX($I7:$K7))),"Avance semanal decreciente"&" · ","")&IF(AND(ISNUMBER($AS7),$AS7<FechaRef,IF($V7="Sub",1,N($M7))<1),"Vencida"&" · ","")&IF(AND(ObsObligatoria="Sí",ISNUMBER($AS7),$AS7<FechaRef,IF($V7="Sub",1,N($M7))<1,$Q7=""),"Vencida sin observación"&" · ",""),LEN(IF($C7="","Falta el nombre de la actividad"&" · ","")&IF(AND($V7="Sub",N($U7)=0),"Subactividad sin macroactividad arriba"&" · ","")&IF(AND($V7="Macro",$AR7=""),"Sin fecha de inicio"&" · ","")&IF(AND($V7="Macro",$AS7=""),"Sin fecha límite"&" · ","")&IF(AND(LEFT($C7,11)="[Jefatura] ",N($AQ7)=0),"No se encuentra en la hoja de la jefatura (elíjala de nuevo en la lista)"&" · ","")&IF(OR(AND($E7<>"",NOT(ISNUMBER($E7))),AND($F7<>"",NOT(ISNUMBER($F7))),AND($G7<>"",NOT(ISNUMBER($G7)))),"Fecha no válida"&" · ","")&IF(AND(ISNUMBER($AR7),ISNUMBER($AS7),$AR7>$AS7),"Inicio posterior a fecha límite"&" · ","")&IF(AND($V7="Macro",$H7<>"",OR(NOT(ISNUMBER($H7)),$H7<0,$H7>1)),"Peso fuera de rango"&" · ","")&IF(AND($V7="Sub",$H7<>"",OR(NOT(ISNUMBER($H7)),$H7<0,$H7>1)),"% de la subactividad fuera de rango 0-100%"&" · ","")&IF(AND(N($W7)>0,SUMIFS($H$5:$H$1000,$U$5:$U$1000,ROW(),$V$5:$V$1000,"Sub")>1.0001),"Las subactividades suman más de 100%"&" · ","")&IF(AND(N($W7)>0,OR(IF(ISNUMBER($I7),ROUND($I7,6)<>ROUND(MIN(1,SUMIFS($AD$5:$AD$1000,$U$5:$U$1000,ROW(),$V$5:$V$1000,"Sub")),6),FALSE),IF(ISNUMBER($J7),ROUND($J7,6)<>ROUND(MIN(1,SUMIFS($AE$5:$AE$1000,$U$5:$U$1000,ROW(),$V$5:$V$1000,"Sub")),6),FALSE),IF(ISNUMBER($K7),ROUND($K7,6)<>ROUND(MIN(1,SUMIFS($AF$5:$AF$1000,$U$5:$U$1000,ROW(),$V$5:$V$1000,"Sub")),6),FALSE),IF(ISNUMBER($L7),ROUND($L7,6)<>ROUND(MIN(1,SUMIFS($AG$5:$AG$1000,$U$5:$U$1000,ROW(),$V$5:$V$1000,"Sub")),6),FALSE))),"Con subactividades: no escriba en las semanas (se llenan solas)"&" · ","")&IF((COUNTIF($I7:$L7,">1")+COUNTIF($I7:$L7,"<0")+SUMPRODUCT((LEN($I7:$L7)>0)*NOT(ISNUMBER($I7:$L7))))>0,"Avance fuera de rango 0-100%"&" · ","")&IF(OR(AND(ISNUMBER($J7),$J7<N($I7)),AND(ISNUMBER($K7),$K7<MAX($I7:$J7)),AND(ISNUMBER($L7),$L7<MAX($I7:$K7))),"Avance semanal decreciente"&" · ","")&IF(AND(ISNUMBER($AS7),$AS7<FechaRef,IF($V7="Sub",1,N($M7))<1),"Vencida"&" · ","")&IF(AND(ObsObligatoria="Sí",ISNUMBER($AS7),$AS7<FechaRef,IF($V7="Sub",1,N($M7))<1,$Q7=""),"Vencida sin observación"&" · ",""))-3))) | S7: =IF(NOT((COUNTA($B7:$D7)+COUNTA($G7:$H7)+COUNTA($Q7))>0),"",IF(AND($V7="Sub",N($U7)>0),IF(ISNUMBER(INDEX($AR$5:$AR$1000,$U7-4)),DATE(YEAR(INDEX($AR$5:$AR$1000,$U7-4)),MONTH(INDEX($AR$5:$AR$1000,$U7-4)),1),IF(ISNUMBER(INDEX($AS$5:$AS$1000,$U7-4)),DATE(YEAR(INDEX($AS$5:$AS$1000,$U7-4)),MONTH(INDEX($AS$5:$AS$1000,$U7-4)),1),MesCiclo)),IF(ISNUMBER($AR7),DATE(YEAR($AR7),MONTH($AR7),1),IF(ISNUMBER($AS7),DATE(YEAR($AS7),MONTH($AS7),1),MesCiclo)))) | T7: =IF(OR($S7="",$S7<>MesCiclo,$V7<>"Macro"),"",COUNTIFS($S$5:$S7,MesCiclo,$V$5:$V7,"Macro")) | U7: =IF($V7="","",IF($V7="Macro",ROW(),IFERROR(LOOKUP(2,1/($V$5:$V7="Macro"),ROW($V$5:$V7)),0))) | V7: =IF(NOT((COUNTA($B7:$D7)+COUNTA($G7:$H7)+COUNTA($Q7))>0),"",IF($B7="Subactividad","Sub","Macro")) | W7: =IF($V7="Macro",COUNTIFS($U$5:$U$1000,ROW(),$V$5:$V$1000,"Sub"),"") | X7: =IF($V7<>"Sub","",IF(AND(ISNUMBER($H7),N($H7)>0),$H7,IFERROR(MAX(0,1-SUMIFS($H$5:$H$1000,$U$5:$U$1000,$U7,$V$5:$V$1000,"Sub"))/(COUNTIFS($U$5:$U$1000,$U7,$V$5:$V$1000,"Sub")-COUNTIFS($U$5:$U$1000,$U7,$V$5:$V$1000,"Sub",$H$5:$H$1000,">0")),0))) | Y7: =IF($V7="","",IF($V7="Sub",N($X7)*IF(ISNUMBER($G7),1,MIN(1,MAX(0,IFERROR(LOOKUP(2,1/ISNUMBER($I7:$L7),$I7:$L7),0)))),IF(ISNUMBER($G7),1,IFERROR(LOOKUP(2,1/($I7:$L7<>""),$I7:$L7),0)))) | Z7: =IF($V7="","",IF(AND(ISNUMBER($G7),$G7<=IF($S7=MesCiclo,InicioCiclo,$S7+MOD(2-WEEKDAY($S7),7))+6),1,IF(ISNUMBER($I7),$I7,0))) | AA7: =IF($V7="","",IF(AND(ISNUMBER($G7),$G7<=IF($S7=MesCiclo,InicioCiclo,$S7+MOD(2-WEEKDAY($S7),7))+13),1,IF(ISNUMBER($J7),$J7,$Z7))) | AB7: =IF($V7="","",IF(AND(ISNUMBER($G7),$G7<=IF($S7=MesCiclo,InicioCiclo,$S7+MOD(2-WEEKDAY($S7),7))+20),1,IF(ISNUMBER($K7),$K7,$AA7))) | AC7: =IF($V7="","",IF(AND(ISNUMBER($G7),$G7<=IF($S7=MesCiclo,InicioCiclo,$S7+MOD(2-WEEKDAY($S7),7))+27),1,IF(ISNUMBER($L7),$L7,$AB7))) | AD7: =IF($V7<>"Sub","",N($X7)*IF(AND(ISNUMBER($G7),$G7<=IF($S7=MesCiclo,InicioCiclo,$S7+MOD(2-WEEKDAY($S7),7))+6),1,MIN(1,MAX(0,IF(ISNUMBER(OFFSET($A$1,ROW()-1,8)),OFFSET($A$1,ROW()-1,8),0))))) | AE7: =IF($V7<>"Sub","",N($X7)*IF(AND(ISNUMBER($G7),$G7<=IF($S7=MesCiclo,InicioCiclo,$S7+MOD(2-WEEKDAY($S7),7))+13),1,MIN(1,MAX(0,IF(ISNUMBER(OFFSET($A$1,ROW()-1,9)),OFFSET($A$1,ROW()-1,9),IF(ISNUMBER(OFFSET($A$1,ROW()-1,8)),OFFSET($A$1,ROW()-1,8),0)))))) | AF7: =IF($V7<>"Sub","",N($X7)*IF(AND(ISNUMBER($G7),$G7<=IF($S7=MesCiclo,InicioCiclo,$S7+MOD(2-WEEKDAY($S7),7))+20),1,MIN(1,MAX(0,IF(ISNUMBER(OFFSET($A$1,ROW()-1,10)),OFFSET($A$1,ROW()-1,10),IF(ISNUMBER(OFFSET($A$1,ROW()-1,9)),OFFSET($A$1,ROW()-1,9),IF(ISNUMBER(OFFSET($A$1,ROW()-1,8)),OFFSET($A$1,ROW()-1,8),0))))))) | AG7: =IF($V7<>"Sub","",N($X7)*IF(AND(ISNUMBER($G7),$G7<=IF($S7=MesCiclo,InicioCiclo,$S7+MOD(2-WEEKDAY($S7),7))+27),1,MIN(1,MAX(0,IF(ISNUMBER(OFFSET($A$1,ROW()-1,11)),OFFSET($A$1,ROW()-1,11),IF(ISNUMBER(OFFSET($A$1,ROW()-1,10)),OFFSET($A$1,ROW()-1,10),IF(ISNUMBER(OFFSET($A$1,ROW()-1,9)),OFFSET($A$1,ROW()-1,9),IF(ISNUMBER(OFFSET($A$1,ROW()-1,8)),OFFSET($A$1,ROW()-1,8),0)))))))) | AH7: =IF($V7="","",IF(AND(ISNUMBER($G7),$G7<=IF($S7=MesCiclo,InicioCiclo,$S7+MOD(2-WEEKDAY($S7),7))+6),1,IF(N($W7)>0,MIN(1,SUMIFS($AD$5:$AD$1000,$U$5:$U$1000,ROW(),$V$5:$V$1000,"Sub")),$Z7))) | AI7: =IF($V7="","",IF(AND(ISNUMBER($G7),$G7<=IF($S7=MesCiclo,InicioCiclo,$S7+MOD(2-WEEKDAY($S7),7))+13),1,IF(N($W7)>0,MIN(1,SUMIFS($AE$5:$AE$1000,$U$5:$U$1000,ROW(),$V$5:$V$1000,"Sub")),$AA7))) | AJ7: =IF($V7="","",IF(AND(ISNUMBER($G7),$G7<=IF($S7=MesCiclo,InicioCiclo,$S7+MOD(2-WEEKDAY($S7),7))+20),1,IF(N($W7)>0,MIN(1,SUMIFS($AF$5:$AF$1000,$U$5:$U$1000,ROW(),$V$5:$V$1000,"Sub")),$AB7))) | AK7: =IF($V7="","",IF(AND(ISNUMBER($G7),$G7<=IF($S7=MesCiclo,InicioCiclo,$S7+MOD(2-WEEKDAY($S7),7))+27),1,IF(N($W7)>0,MIN(1,SUMIFS($AG$5:$AG$1000,$U$5:$U$1000,ROW(),$V$5:$V$1000,"Sub")),$AC7))) | AL7: =IF($V7<>"Macro","",IF(COUNTIFS($S$5:$S$1000,$S7,$V$5:$V$1000,"Macro",$H$5:$H$1000,">0")=0,1/COUNTIFS($S$5:$S$1000,$S7,$V$5:$V$1000,"Macro"),IF(AND(ISNUMBER($H7),N($H7)>0),$H7,SUMIFS($H$5:$H$1000,$S$5:$S$1000,$S7,$V$5:$V$1000,"Macro")/COUNTIFS($S$5:$S$1000,$S7,$V$5:$V$1000,"Macro",$H$5:$H$1000,">0"))/(COUNTIFS($S$5:$S$1000,$S7,$V$5:$V$1000,"Macro")*SUMIFS($H$5:$H$1000,$S$5:$S$1000,$S7,$V$5:$V$1000,"Macro")/COUNTIFS($S$5:$S$1000,$S7,$V$5:$V$1000,"Macro",$H$5:$H$1000,">0")))) | AM7: =IF(NOT(AND($D7<>"",$V7="Macro")),"",IFERROR(CHOOSE(MATCH($D7,ListaPuestos,0),MATCH("[Jefatura] "&$C7,'Cronograma R. Operacional'!$C$5:$C$1000,0),MATCH("[Jefatura] "&$C7,'Cronograma R. Normativo'!$C$5:$C$1000,0),MATCH("[Jefatura] "&$C7,'Cronograma R. Financiero'!$C$5:$C$1000,0),MATCH("[Jefatura] "&$C7,'Cronograma Asistente Técnico'!$C$5:$C$1000,0)),0)) | AN7: =IF(AND(AND($D7<>"",$V7="Macro"),$S7=MesCiclo),COUNTIFS($D$5:$D7,$D7,$S$5:$S7,MesCiclo,$V$5:$V7,"Macro"),"") | AO7: =IF($AN7="","",$D7&"|"&$AN7) | AP7: =IF(AND($D7<>"",$V7="Macro"),$D7&"|"&$C7,"") | AQ7: ="" | AR7: =IF(N($AQ7)>0,INDEX(rIni_ADM,$AQ7),IF(ISNUMBER($E7),$E7,"")) | AS7: =IF(N($AQ7)>0,INDEX(rLim_ADM,$AQ7),IF(ISNUMBER($F7),$F7,""))
A8: =IF(NOT((COUNTA($B8:$D8)+COUNTA($G8:$H8)+COUNTA($Q8))>0),"",IF($V8="Macro",COUNTIFS($V$5:$V8,"Macro",$S$5:$S8,$S8),IF(N($U8)=0,"?",COUNTIFS(INDEX($V$5:$V$1000,1):INDEX($V$5:$V$1000,$U8-4),"Macro",INDEX($S$5:$S$1000,1):INDEX($S$5:$S$1000,$U8-4),INDEX($S$5:$S$1000,$U8-4))&"."&COUNTIFS($U$5:$U8,$U8,$V$5:$V8,"Sub")))) | I8: =IF(N($W8)=0,"",IF(AND($S8=MesCiclo,1>SemanaActual),"",MIN(1,SUMIFS(OFFSET($A$1,ROW(),29,1000-ROW(),1),OFFSET($A$1,ROW(),20,1000-ROW(),1),ROW(),OFFSET($A$1,ROW(),21,1000-ROW(),1),"Sub")))) | J8: =IF(N($W8)=0,"",IF(AND($S8=MesCiclo,2>SemanaActual),"",MIN(1,SUMIFS(OFFSET($A$1,ROW(),30,1000-ROW(),1),OFFSET($A$1,ROW(),20,1000-ROW(),1),ROW(),OFFSET($A$1,ROW(),21,1000-ROW(),1),"Sub")))) | K8: =IF(N($W8)=0,"",IF(AND($S8=MesCiclo,3>SemanaActual),"",MIN(1,SUMIFS(OFFSET($A$1,ROW(),31,1000-ROW(),1),OFFSET($A$1,ROW(),20,1000-ROW(),1),ROW(),OFFSET($A$1,ROW(),21,1000-ROW(),1),"Sub")))) | L8: =IF(N($W8)=0,"",IF(AND($S8=MesCiclo,4>SemanaActual),"",MIN(1,SUMIFS(OFFSET($A$1,ROW(),32,1000-ROW(),1),OFFSET($A$1,ROW(),20,1000-ROW(),1),ROW(),OFFSET($A$1,ROW(),21,1000-ROW(),1),"Sub")))) | M8: =IF(NOT((COUNTA($B8:$D8)+COUNTA($G8:$H8)+COUNTA($Q8))>0),"",IF(AND($D8<>"",$V8="Macro"),IF(N($AM8)>0,N(CHOOSE(MATCH($D8,ListaPuestos,0),INDEX('Cronograma R. Operacional'!$M$5:$M$1000,$AM8),INDEX('Cronograma R. Normativo'!$M$5:$M$1000,$AM8),INDEX('Cronograma R. Financiero'!$M$5:$M$1000,$AM8),INDEX('Cronograma Asistente Técnico'!$M$5:$M$1000,$AM8))),0),IF(ISNUMBER($G8),1,IF(N($W8)>0,MIN(1,SUMIFS($Y$5:$Y$1000,$U$5:$U$1000,ROW(),$V$5:$V$1000,"Sub")),$Y8)))) | N8: =IF(OR($M8="",$V8="Sub"),"",IF($M8>=1,"Completado",IF($M8>0,"En curso","Pendiente"))) | O8: =IF(NOT((COUNTA($B8:$D8)+COUNTA($G8:$H8)+COUNTA($Q8))>0),"",IF(AND(AND($D8<>"",$V8="Macro"),N($AM8)>0),CHOOSE(MATCH($D8,ListaPuestos,0),INDEX('Cronograma R. Operacional'!$O$5:$O$1000,$AM8),INDEX('Cronograma R. Normativo'!$O$5:$O$1000,$AM8),INDEX('Cronograma R. Financiero'!$O$5:$O$1000,$AM8),INDEX('Cronograma Asistente Técnico'!$O$5:$O$1000,$AM8))&"",IF(ISNUMBER($G8),IF(AND(ISNUMBER($AS8),$G8>$AS8),"Cumplida con "&($G8-$AS8)&IF($G8-$AS8=1," día"," días")&" de retraso","Cumplida"),IF(N($M8)>=1,"Cumplida",IF(NOT(ISNUMBER($AS8)),"Sin fecha límite",IF($AS8<FechaRef,"Vencida hace "&(FechaRef-$AS8)&IF(FechaRef-$AS8=1," día"," días"),IF($AS8=FechaRef,"Vence hoy",IF($AS8-FechaRef<=DiasAlerta,"Vence en "&($AS8-FechaRef)&IF($AS8-FechaRef=1," día"," días"),"En plazo")))))))) | P8: =IF(NOT((COUNTA($B8:$D8)+COUNTA($G8:$H8)+COUNTA($Q8))>0),"",IF($D8="","Propia",IF($V8<>"Macro","Solo se delegan macroactividades",IF(N($AM8)>0,"✔ Recibida por "&$D8,"⚠ "&$D8&" aún no la agrega")))) | R8: =IF(NOT((COUNTA($B8:$D8)+COUNTA($G8:$H8)+COUNTA($Q8))>0),"",IF((IF($C8="","Falta el nombre de la actividad"&" · ","")&IF(AND($V8="Sub",N($U8)=0),"Subactividad sin macroactividad arriba"&" · ","")&IF(AND($V8="Macro",$AR8=""),"Sin fecha de inicio"&" · ","")&IF(AND($V8="Macro",$AS8=""),"Sin fecha límite"&" · ","")&IF(AND(LEFT($C8,11)="[Jefatura] ",N($AQ8)=0),"No se encuentra en la hoja de la jefatura (elíjala de nuevo en la lista)"&" · ","")&IF(OR(AND($E8<>"",NOT(ISNUMBER($E8))),AND($F8<>"",NOT(ISNUMBER($F8))),AND($G8<>"",NOT(ISNUMBER($G8)))),"Fecha no válida"&" · ","")&IF(AND(ISNUMBER($AR8),ISNUMBER($AS8),$AR8>$AS8),"Inicio posterior a fecha límite"&" · ","")&IF(AND($V8="Macro",$H8<>"",OR(NOT(ISNUMBER($H8)),$H8<0,$H8>1)),"Peso fuera de rango"&" · ","")&IF(AND($V8="Sub",$H8<>"",OR(NOT(ISNUMBER($H8)),$H8<0,$H8>1)),"% de la subactividad fuera de rango 0-100%"&" · ","")&IF(AND(N($W8)>0,SUMIFS($H$5:$H$1000,$U$5:$U$1000,ROW(),$V$5:$V$1000,"Sub")>1.0001),"Las subactividades suman más de 100%"&" · ","")&IF(AND(N($W8)>0,OR(IF(ISNUMBER($I8),ROUND($I8,6)<>ROUND(MIN(1,SUMIFS($AD$5:$AD$1000,$U$5:$U$1000,ROW(),$V$5:$V$1000,"Sub")),6),FALSE),IF(ISNUMBER($J8),ROUND($J8,6)<>ROUND(MIN(1,SUMIFS($AE$5:$AE$1000,$U$5:$U$1000,ROW(),$V$5:$V$1000,"Sub")),6),FALSE),IF(ISNUMBER($K8),ROUND($K8,6)<>ROUND(MIN(1,SUMIFS($AF$5:$AF$1000,$U$5:$U$1000,ROW(),$V$5:$V$1000,"Sub")),6),FALSE),IF(ISNUMBER($L8),ROUND($L8,6)<>ROUND(MIN(1,SUMIFS($AG$5:$AG$1000,$U$5:$U$1000,ROW(),$V$5:$V$1000,"Sub")),6),FALSE))),"Con subactividades: no escriba en las semanas (se llenan solas)"&" · ","")&IF((COUNTIF($I8:$L8,">1")+COUNTIF($I8:$L8,"<0")+SUMPRODUCT((LEN($I8:$L8)>0)*NOT(ISNUMBER($I8:$L8))))>0,"Avance fuera de rango 0-100%"&" · ","")&IF(OR(AND(ISNUMBER($J8),$J8<N($I8)),AND(ISNUMBER($K8),$K8<MAX($I8:$J8)),AND(ISNUMBER($L8),$L8<MAX($I8:$K8))),"Avance semanal decreciente"&" · ","")&IF(AND(ISNUMBER($AS8),$AS8<FechaRef,IF($V8="Sub",1,N($M8))<1),"Vencida"&" · ","")&IF(AND(ObsObligatoria="Sí",ISNUMBER($AS8),$AS8<FechaRef,IF($V8="Sub",1,N($M8))<1,$Q8=""),"Vencida sin observación"&" · ",""))="","✔ OK","⚠ "&LEFT(IF($C8="","Falta el nombre de la actividad"&" · ","")&IF(AND($V8="Sub",N($U8)=0),"Subactividad sin macroactividad arriba"&" · ","")&IF(AND($V8="Macro",$AR8=""),"Sin fecha de inicio"&" · ","")&IF(AND($V8="Macro",$AS8=""),"Sin fecha límite"&" · ","")&IF(AND(LEFT($C8,11)="[Jefatura] ",N($AQ8)=0),"No se encuentra en la hoja de la jefatura (elíjala de nuevo en la lista)"&" · ","")&IF(OR(AND($E8<>"",NOT(ISNUMBER($E8))),AND($F8<>"",NOT(ISNUMBER($F8))),AND($G8<>"",NOT(ISNUMBER($G8)))),"Fecha no válida"&" · ","")&IF(AND(ISNUMBER($AR8),ISNUMBER($AS8),$AR8>$AS8),"Inicio posterior a fecha límite"&" · ","")&IF(AND($V8="Macro",$H8<>"",OR(NOT(ISNUMBER($H8)),$H8<0,$H8>1)),"Peso fuera de rango"&" · ","")&IF(AND($V8="Sub",$H8<>"",OR(NOT(ISNUMBER($H8)),$H8<0,$H8>1)),"% de la subactividad fuera de rango 0-100%"&" · ","")&IF(AND(N($W8)>0,SUMIFS($H$5:$H$1000,$U$5:$U$1000,ROW(),$V$5:$V$1000,"Sub")>1.0001),"Las subactividades suman más de 100%"&" · ","")&IF(AND(N($W8)>0,OR(IF(ISNUMBER($I8),ROUND($I8,6)<>ROUND(MIN(1,SUMIFS($AD$5:$AD$1000,$U$5:$U$1000,ROW(),$V$5:$V$1000,"Sub")),6),FALSE),IF(ISNUMBER($J8),ROUND($J8,6)<>ROUND(MIN(1,SUMIFS($AE$5:$AE$1000,$U$5:$U$1000,ROW(),$V$5:$V$1000,"Sub")),6),FALSE),IF(ISNUMBER($K8),ROUND($K8,6)<>ROUND(MIN(1,SUMIFS($AF$5:$AF$1000,$U$5:$U$1000,ROW(),$V$5:$V$1000,"Sub")),6),FALSE),IF(ISNUMBER($L8),ROUND($L8,6)<>ROUND(MIN(1,SUMIFS($AG$5:$AG$1000,$U$5:$U$1000,ROW(),$V$5:$V$1000,"Sub")),6),FALSE))),"Con subactividades: no escriba en las semanas (se llenan solas)"&" · ","")&IF((COUNTIF($I8:$L8,">1")+COUNTIF($I8:$L8,"<0")+SUMPRODUCT((LEN($I8:$L8)>0)*NOT(ISNUMBER($I8:$L8))))>0,"Avance fuera de rango 0-100%"&" · ","")&IF(OR(AND(ISNUMBER($J8),$J8<N($I8)),AND(ISNUMBER($K8),$K8<MAX($I8:$J8)),AND(ISNUMBER($L8),$L8<MAX($I8:$K8))),"Avance semanal decreciente"&" · ","")&IF(AND(ISNUMBER($AS8),$AS8<FechaRef,IF($V8="Sub",1,N($M8))<1),"Vencida"&" · ","")&IF(AND(ObsObligatoria="Sí",ISNUMBER($AS8),$AS8<FechaRef,IF($V8="Sub",1,N($M8))<1,$Q8=""),"Vencida sin observación"&" · ",""),LEN(IF($C8="","Falta el nombre de la actividad"&" · ","")&IF(AND($V8="Sub",N($U8)=0),"Subactividad sin macroactividad arriba"&" · ","")&IF(AND($V8="Macro",$AR8=""),"Sin fecha de inicio"&" · ","")&IF(AND($V8="Macro",$AS8=""),"Sin fecha límite"&" · ","")&IF(AND(LEFT($C8,11)="[Jefatura] ",N($AQ8)=0),"No se encuentra en la hoja de la jefatura (elíjala de nuevo en la lista)"&" · ","")&IF(OR(AND($E8<>"",NOT(ISNUMBER($E8))),AND($F8<>"",NOT(ISNUMBER($F8))),AND($G8<>"",NOT(ISNUMBER($G8)))),"Fecha no válida"&" · ","")&IF(AND(ISNUMBER($AR8),ISNUMBER($AS8),$AR8>$AS8),"Inicio posterior a fecha límite"&" · ","")&IF(AND($V8="Macro",$H8<>"",OR(NOT(ISNUMBER($H8)),$H8<0,$H8>1)),"Peso fuera de rango"&" · ","")&IF(AND($V8="Sub",$H8<>"",OR(NOT(ISNUMBER($H8)),$H8<0,$H8>1)),"% de la subactividad fuera de rango 0-100%"&" · ","")&IF(AND(N($W8)>0,SUMIFS($H$5:$H$1000,$U$5:$U$1000,ROW(),$V$5:$V$1000,"Sub")>1.0001),"Las subactividades suman más de 100%"&" · ","")&IF(AND(N($W8)>0,OR(IF(ISNUMBER($I8),ROUND($I8,6)<>ROUND(MIN(1,SUMIFS($AD$5:$AD$1000,$U$5:$U$1000,ROW(),$V$5:$V$1000,"Sub")),6),FALSE),IF(ISNUMBER($J8),ROUND($J8,6)<>ROUND(MIN(1,SUMIFS($AE$5:$AE$1000,$U$5:$U$1000,ROW(),$V$5:$V$1000,"Sub")),6),FALSE),IF(ISNUMBER($K8),ROUND($K8,6)<>ROUND(MIN(1,SUMIFS($AF$5:$AF$1000,$U$5:$U$1000,ROW(),$V$5:$V$1000,"Sub")),6),FALSE),IF(ISNUMBER($L8),ROUND($L8,6)<>ROUND(MIN(1,SUMIFS($AG$5:$AG$1000,$U$5:$U$1000,ROW(),$V$5:$V$1000,"Sub")),6),FALSE))),"Con subactividades: no escriba en las semanas (se llenan solas)"&" · ","")&IF((COUNTIF($I8:$L8,">1")+COUNTIF($I8:$L8,"<0")+SUMPRODUCT((LEN($I8:$L8)>0)*NOT(ISNUMBER($I8:$L8))))>0,"Avance fuera de rango 0-100%"&" · ","")&IF(OR(AND(ISNUMBER($J8),$J8<N($I8)),AND(ISNUMBER($K8),$K8<MAX($I8:$J8)),AND(ISNUMBER($L8),$L8<MAX($I8:$K8))),"Avance semanal decreciente"&" · ","")&IF(AND(ISNUMBER($AS8),$AS8<FechaRef,IF($V8="Sub",1,N($M8))<1),"Vencida"&" · ","")&IF(AND(ObsObligatoria="Sí",ISNUMBER($AS8),$AS8<FechaRef,IF($V8="Sub",1,N($M8))<1,$Q8=""),"Vencida sin observación"&" · ",""))-3))) | S8: =IF(NOT((COUNTA($B8:$D8)+COUNTA($G8:$H8)+COUNTA($Q8))>0),"",IF(AND($V8="Sub",N($U8)>0),IF(ISNUMBER(INDEX($AR$5:$AR$1000,$U8-4)),DATE(YEAR(INDEX($AR$5:$AR$1000,$U8-4)),MONTH(INDEX($AR$5:$AR$1000,$U8-4)),1),IF(ISNUMBER(INDEX($AS$5:$AS$1000,$U8-4)),DATE(YEAR(INDEX($AS$5:$AS$1000,$U8-4)),MONTH(INDEX($AS$5:$AS$1000,$U8-4)),1),MesCiclo)),IF(ISNUMBER($AR8),DATE(YEAR($AR8),MONTH($AR8),1),IF(ISNUMBER($AS8),DATE(YEAR($AS8),MONTH($AS8),1),MesCiclo)))) | T8: =IF(OR($S8="",$S8<>MesCiclo,$V8<>"Macro"),"",COUNTIFS($S$5:$S8,MesCiclo,$V$5:$V8,"Macro")) | U8: =IF($V8="","",IF($V8="Macro",ROW(),IFERROR(LOOKUP(2,1/($V$5:$V8="Macro"),ROW($V$5:$V8)),0))) | V8: =IF(NOT((COUNTA($B8:$D8)+COUNTA($G8:$H8)+COUNTA($Q8))>0),"",IF($B8="Subactividad","Sub","Macro")) | W8: =IF($V8="Macro",COUNTIFS($U$5:$U$1000,ROW(),$V$5:$V$1000,"Sub"),"") | X8: =IF($V8<>"Sub","",IF(AND(ISNUMBER($H8),N($H8)>0),$H8,IFERROR(MAX(0,1-SUMIFS($H$5:$H$1000,$U$5:$U$1000,$U8,$V$5:$V$1000,"Sub"))/(COUNTIFS($U$5:$U$1000,$U8,$V$5:$V$1000,"Sub")-COUNTIFS($U$5:$U$1000,$U8,$V$5:$V$1000,"Sub",$H$5:$H$1000,">0")),0))) | Y8: =IF($V8="","",IF($V8="Sub",N($X8)*IF(ISNUMBER($G8),1,MIN(1,MAX(0,IFERROR(LOOKUP(2,1/ISNUMBER($I8:$L8),$I8:$L8),0)))),IF(ISNUMBER($G8),1,IFERROR(LOOKUP(2,1/($I8:$L8<>""),$I8:$L8),0)))) | Z8: =IF($V8="","",IF(AND(ISNUMBER($G8),$G8<=IF($S8=MesCiclo,InicioCiclo,$S8+MOD(2-WEEKDAY($S8),7))+6),1,IF(ISNUMBER($I8),$I8,0))) | AA8: =IF($V8="","",IF(AND(ISNUMBER($G8),$G8<=IF($S8=MesCiclo,InicioCiclo,$S8+MOD(2-WEEKDAY($S8),7))+13),1,IF(ISNUMBER($J8),$J8,$Z8))) | AB8: =IF($V8="","",IF(AND(ISNUMBER($G8),$G8<=IF($S8=MesCiclo,InicioCiclo,$S8+MOD(2-WEEKDAY($S8),7))+20),1,IF(ISNUMBER($K8),$K8,$AA8))) | AC8: =IF($V8="","",IF(AND(ISNUMBER($G8),$G8<=IF($S8=MesCiclo,InicioCiclo,$S8+MOD(2-WEEKDAY($S8),7))+27),1,IF(ISNUMBER($L8),$L8,$AB8))) | AD8: =IF($V8<>"Sub","",N($X8)*IF(AND(ISNUMBER($G8),$G8<=IF($S8=MesCiclo,InicioCiclo,$S8+MOD(2-WEEKDAY($S8),7))+6),1,MIN(1,MAX(0,IF(ISNUMBER(OFFSET($A$1,ROW()-1,8)),OFFSET($A$1,ROW()-1,8),0))))) | AE8: =IF($V8<>"Sub","",N($X8)*IF(AND(ISNUMBER($G8),$G8<=IF($S8=MesCiclo,InicioCiclo,$S8+MOD(2-WEEKDAY($S8),7))+13),1,MIN(1,MAX(0,IF(ISNUMBER(OFFSET($A$1,ROW()-1,9)),OFFSET($A$1,ROW()-1,9),IF(ISNUMBER(OFFSET($A$1,ROW()-1,8)),OFFSET($A$1,ROW()-1,8),0)))))) | AF8: =IF($V8<>"Sub","",N($X8)*IF(AND(ISNUMBER($G8),$G8<=IF($S8=MesCiclo,InicioCiclo,$S8+MOD(2-WEEKDAY($S8),7))+20),1,MIN(1,MAX(0,IF(ISNUMBER(OFFSET($A$1,ROW()-1,10)),OFFSET($A$1,ROW()-1,10),IF(ISNUMBER(OFFSET($A$1,ROW()-1,9)),OFFSET($A$1,ROW()-1,9),IF(ISNUMBER(OFFSET($A$1,ROW()-1,8)),OFFSET($A$1,ROW()-1,8),0))))))) | AG8: =IF($V8<>"Sub","",N($X8)*IF(AND(ISNUMBER($G8),$G8<=IF($S8=MesCiclo,InicioCiclo,$S8+MOD(2-WEEKDAY($S8),7))+27),1,MIN(1,MAX(0,IF(ISNUMBER(OFFSET($A$1,ROW()-1,11)),OFFSET($A$1,ROW()-1,11),IF(ISNUMBER(OFFSET($A$1,ROW()-1,10)),OFFSET($A$1,ROW()-1,10),IF(ISNUMBER(OFFSET($A$1,ROW()-1,9)),OFFSET($A$1,ROW()-1,9),IF(ISNUMBER(OFFSET($A$1,ROW()-1,8)),OFFSET($A$1,ROW()-1,8),0)))))))) | AH8: =IF($V8="","",IF(AND(ISNUMBER($G8),$G8<=IF($S8=MesCiclo,InicioCiclo,$S8+MOD(2-WEEKDAY($S8),7))+6),1,IF(N($W8)>0,MIN(1,SUMIFS($AD$5:$AD$1000,$U$5:$U$1000,ROW(),$V$5:$V$1000,"Sub")),$Z8))) | AI8: =IF($V8="","",IF(AND(ISNUMBER($G8),$G8<=IF($S8=MesCiclo,InicioCiclo,$S8+MOD(2-WEEKDAY($S8),7))+13),1,IF(N($W8)>0,MIN(1,SUMIFS($AE$5:$AE$1000,$U$5:$U$1000,ROW(),$V$5:$V$1000,"Sub")),$AA8))) | AJ8: =IF($V8="","",IF(AND(ISNUMBER($G8),$G8<=IF($S8=MesCiclo,InicioCiclo,$S8+MOD(2-WEEKDAY($S8),7))+20),1,IF(N($W8)>0,MIN(1,SUMIFS($AF$5:$AF$1000,$U$5:$U$1000,ROW(),$V$5:$V$1000,"Sub")),$AB8))) | AK8: =IF($V8="","",IF(AND(ISNUMBER($G8),$G8<=IF($S8=MesCiclo,InicioCiclo,$S8+MOD(2-WEEKDAY($S8),7))+27),1,IF(N($W8)>0,MIN(1,SUMIFS($AG$5:$AG$1000,$U$5:$U$1000,ROW(),$V$5:$V$1000,"Sub")),$AC8))) | AL8: =IF($V8<>"Macro","",IF(COUNTIFS($S$5:$S$1000,$S8,$V$5:$V$1000,"Macro",$H$5:$H$1000,">0")=0,1/COUNTIFS($S$5:$S$1000,$S8,$V$5:$V$1000,"Macro"),IF(AND(ISNUMBER($H8),N($H8)>0),$H8,SUMIFS($H$5:$H$1000,$S$5:$S$1000,$S8,$V$5:$V$1000,"Macro")/COUNTIFS($S$5:$S$1000,$S8,$V$5:$V$1000,"Macro",$H$5:$H$1000,">0"))/(COUNTIFS($S$5:$S$1000,$S8,$V$5:$V$1000,"Macro")*SUMIFS($H$5:$H$1000,$S$5:$S$1000,$S8,$V$5:$V$1000,"Macro")/COUNTIFS($S$5:$S$1000,$S8,$V$5:$V$1000,"Macro",$H$5:$H$1000,">0")))) | AM8: =IF(NOT(AND($D8<>"",$V8="Macro")),"",IFERROR(CHOOSE(MATCH($D8,ListaPuestos,0),MATCH("[Jefatura] "&$C8,'Cronograma R. Operacional'!$C$5:$C$1000,0),MATCH("[Jefatura] "&$C8,'Cronograma R. Normativo'!$C$5:$C$1000,0),MATCH("[Jefatura] "&$C8,'Cronograma R. Financiero'!$C$5:$C$1000,0),MATCH("[Jefatura] "&$C8,'Cronograma Asistente Técnico'!$C$5:$C$1000,0)),0)) | AN8: =IF(AND(AND($D8<>"",$V8="Macro"),$S8=MesCiclo),COUNTIFS($D$5:$D8,$D8,$S$5:$S8,MesCiclo,$V$5:$V8,"Macro"),"") | AO8: =IF($AN8="","",$D8&"|"&$AN8) | AP8: =IF(AND($D8<>"",$V8="Macro"),$D8&"|"&$C8,"") | AQ8: ="" | AR8: =IF(N($AQ8)>0,INDEX(rIni_ADM,$AQ8),IF(ISNUMBER($E8),$E8,"")) | AS8: =IF(N($AQ8)>0,INDEX(rLim_ADM,$AQ8),IF(ISNUMBER($F8),$F8,""))
A9: =IF(NOT((COUNTA($B9:$D9)+COUNTA($G9:$H9)+COUNTA($Q9))>0),"",IF($V9="Macro",COUNTIFS($V$5:$V9,"Macro",$S$5:$S9,$S9),IF(N($U9)=0,"?",COUNTIFS(INDEX($V$5:$V$1000,1):INDEX($V$5:$V$1000,$U9-4),"Macro",INDEX($S$5:$S$1000,1):INDEX($S$5:$S$1000,$U9-4),INDEX($S$5:$S$1000,$U9-4))&"."&COUNTIFS($U$5:$U9,$U9,$V$5:$V9,"Sub")))) | I9: =IF(N($W9)=0,"",IF(AND($S9=MesCiclo,1>SemanaActual),"",MIN(1,SUMIFS(OFFSET($A$1,ROW(),29,1000-ROW(),1),OFFSET($A$1,ROW(),20,1000-ROW(),1),ROW(),OFFSET($A$1,ROW(),21,1000-ROW(),1),"Sub")))) | J9: =IF(N($W9)=0,"",IF(AND($S9=MesCiclo,2>SemanaActual),"",MIN(1,SUMIFS(OFFSET($A$1,ROW(),30,1000-ROW(),1),OFFSET($A$1,ROW(),20,1000-ROW(),1),ROW(),OFFSET($A$1,ROW(),21,1000-ROW(),1),"Sub")))) | K9: =IF(N($W9)=0,"",IF(AND($S9=MesCiclo,3>SemanaActual),"",MIN(1,SUMIFS(OFFSET($A$1,ROW(),31,1000-ROW(),1),OFFSET($A$1,ROW(),20,1000-ROW(),1),ROW(),OFFSET($A$1,ROW(),21,1000-ROW(),1),"Sub")))) | L9: =IF(N($W9)=0,"",IF(AND($S9=MesCiclo,4>SemanaActual),"",MIN(1,SUMIFS(OFFSET($A$1,ROW(),32,1000-ROW(),1),OFFSET($A$1,ROW(),20,1000-ROW(),1),ROW(),OFFSET($A$1,ROW(),21,1000-ROW(),1),"Sub")))) | M9: =IF(NOT((COUNTA($B9:$D9)+COUNTA($G9:$H9)+COUNTA($Q9))>0),"",IF(AND($D9<>"",$V9="Macro"),IF(N($AM9)>0,N(CHOOSE(MATCH($D9,ListaPuestos,0),INDEX('Cronograma R. Operacional'!$M$5:$M$1000,$AM9),INDEX('Cronograma R. Normativo'!$M$5:$M$1000,$AM9),INDEX('Cronograma R. Financiero'!$M$5:$M$1000,$AM9),INDEX('Cronograma Asistente Técnico'!$M$5:$M$1000,$AM9))),0),IF(ISNUMBER($G9),1,IF(N($W9)>0,MIN(1,SUMIFS($Y$5:$Y$1000,$U$5:$U$1000,ROW(),$V$5:$V$1000,"Sub")),$Y9)))) | N9: =IF(OR($M9="",$V9="Sub"),"",IF($M9>=1,"Completado",IF($M9>0,"En curso","Pendiente"))) | O9: =IF(NOT((COUNTA($B9:$D9)+COUNTA($G9:$H9)+COUNTA($Q9))>0),"",IF(AND(AND($D9<>"",$V9="Macro"),N($AM9)>0),CHOOSE(MATCH($D9,ListaPuestos,0),INDEX('Cronograma R. Operacional'!$O$5:$O$1000,$AM9),INDEX('Cronograma R. Normativo'!$O$5:$O$1000,$AM9),INDEX('Cronograma R. Financiero'!$O$5:$O$1000,$AM9),INDEX('Cronograma Asistente Técnico'!$O$5:$O$1000,$AM9))&"",IF(ISNUMBER($G9),IF(AND(ISNUMBER($AS9),$G9>$AS9),"Cumplida con "&($G9-$AS9)&IF($G9-$AS9=1," día"," días")&" de retraso","Cumplida"),IF(N($M9)>=1,"Cumplida",IF(NOT(ISNUMBER($AS9)),"Sin fecha límite",IF($AS9<FechaRef,"Vencida hace "&(FechaRef-$AS9)&IF(FechaRef-$AS9=1," día"," días"),IF($AS9=FechaRef,"Vence hoy",IF($AS9-FechaRef<=DiasAlerta,"Vence en "&($AS9-FechaRef)&IF($AS9-FechaRef=1," día"," días"),"En plazo")))))))) | P9: =IF(NOT((COUNTA($B9:$D9)+COUNTA($G9:$H9)+COUNTA($Q9))>0),"",IF($D9="","Propia",IF($V9<>"Macro","Solo se delegan macroactividades",IF(N($AM9)>0,"✔ Recibida por "&$D9,"⚠ "&$D9&" aún no la agrega")))) | R9: =IF(NOT((COUNTA($B9:$D9)+COUNTA($G9:$H9)+COUNTA($Q9))>0),"",IF((IF($C9="","Falta el nombre de la actividad"&" · ","")&IF(AND($V9="Sub",N($U9)=0),"Subactividad sin macroactividad arriba"&" · ","")&IF(AND($V9="Macro",$AR9=""),"Sin fecha de inicio"&" · ","")&IF(AND($V9="Macro",$AS9=""),"Sin fecha límite"&" · ","")&IF(AND(LEFT($C9,11)="[Jefatura] ",N($AQ9)=0),"No se encuentra en la hoja de la jefatura (elíjala de nuevo en la lista)"&" · ","")&IF(OR(AND($E9<>"",NOT(ISNUMBER($E9))),AND($F9<>"",NOT(ISNUMBER($F9))),AND($G9<>"",NOT(ISNUMBER($G9)))),"Fecha no válida"&" · ","")&IF(AND(ISNUMBER($AR9),ISNUMBER($AS9),$AR9>$AS9),"Inicio posterior a fecha límite"&" · ","")&IF(AND($V9="Macro",$H9<>"",OR(NOT(ISNUMBER($H9)),$H9<0,$H9>1)),"Peso fuera de rango"&" · ","")&IF(AND($V9="Sub",$H9<>"",OR(NOT(ISNUMBER($H9)),$H9<0,$H9>1)),"% de la subactividad fuera de rango 0-100%"&" · ","")&IF(AND(N($W9)>0,SUMIFS($H$5:$H$1000,$U$5:$U$1000,ROW(),$V$5:$V$1000,"Sub")>1.0001),"Las subactividades suman más de 100%"&" · ","")&IF(AND(N($W9)>0,OR(IF(ISNUMBER($I9),ROUND($I9,6)<>ROUND(MIN(1,SUMIFS($AD$5:$AD$1000,$U$5:$U$1000,ROW(),$V$5:$V$1000,"Sub")),6),FALSE),IF(ISNUMBER($J9),ROUND($J9,6)<>ROUND(MIN(1,SUMIFS($AE$5:$AE$1000,$U$5:$U$1000,ROW(),$V$5:$V$1000,"Sub")),6),FALSE),IF(ISNUMBER($K9),ROUND($K9,6)<>ROUND(MIN(1,SUMIFS($AF$5:$AF$1000,$U$5:$U$1000,ROW(),$V$5:$V$1000,"Sub")),6),FALSE),IF(ISNUMBER($L9),ROUND($L9,6)<>ROUND(MIN(1,SUMIFS($AG$5:$AG$1000,$U$5:$U$1000,ROW(),$V$5:$V$1000,"Sub")),6),FALSE))),"Con subactividades: no escriba en las semanas (se llenan solas)"&" · ","")&IF((COUNTIF($I9:$L9,">1")+COUNTIF($I9:$L9,"<0")+SUMPRODUCT((LEN($I9:$L9)>0)*NOT(ISNUMBER($I9:$L9))))>0,"Avance fuera de rango 0-100%"&" · ","")&IF(OR(AND(ISNUMBER($J9),$J9<N($I9)),AND(ISNUMBER($K9),$K9<MAX($I9:$J9)),AND(ISNUMBER($L9),$L9<MAX($I9:$K9))),"Avance semanal decreciente"&" · ","")&IF(AND(ISNUMBER($AS9),$AS9<FechaRef,IF($V9="Sub",1,N($M9))<1),"Vencida"&" · ","")&IF(AND(ObsObligatoria="Sí",ISNUMBER($AS9),$AS9<FechaRef,IF($V9="Sub",1,N($M9))<1,$Q9=""),"Vencida sin observación"&" · ",""))="","✔ OK","⚠ "&LEFT(IF($C9="","Falta el nombre de la actividad"&" · ","")&IF(AND($V9="Sub",N($U9)=0),"Subactividad sin macroactividad arriba"&" · ","")&IF(AND($V9="Macro",$AR9=""),"Sin fecha de inicio"&" · ","")&IF(AND($V9="Macro",$AS9=""),"Sin fecha límite"&" · ","")&IF(AND(LEFT($C9,11)="[Jefatura] ",N($AQ9)=0),"No se encuentra en la hoja de la jefatura (elíjala de nuevo en la lista)"&" · ","")&IF(OR(AND($E9<>"",NOT(ISNUMBER($E9))),AND($F9<>"",NOT(ISNUMBER($F9))),AND($G9<>"",NOT(ISNUMBER($G9)))),"Fecha no válida"&" · ","")&IF(AND(ISNUMBER($AR9),ISNUMBER($AS9),$AR9>$AS9),"Inicio posterior a fecha límite"&" · ","")&IF(AND($V9="Macro",$H9<>"",OR(NOT(ISNUMBER($H9)),$H9<0,$H9>1)),"Peso fuera de rango"&" · ","")&IF(AND($V9="Sub",$H9<>"",OR(NOT(ISNUMBER($H9)),$H9<0,$H9>1)),"% de la subactividad fuera de rango 0-100%"&" · ","")&IF(AND(N($W9)>0,SUMIFS($H$5:$H$1000,$U$5:$U$1000,ROW(),$V$5:$V$1000,"Sub")>1.0001),"Las subactividades suman más de 100%"&" · ","")&IF(AND(N($W9)>0,OR(IF(ISNUMBER($I9),ROUND($I9,6)<>ROUND(MIN(1,SUMIFS($AD$5:$AD$1000,$U$5:$U$1000,ROW(),$V$5:$V$1000,"Sub")),6),FALSE),IF(ISNUMBER($J9),ROUND($J9,6)<>ROUND(MIN(1,SUMIFS($AE$5:$AE$1000,$U$5:$U$1000,ROW(),$V$5:$V$1000,"Sub")),6),FALSE),IF(ISNUMBER($K9),ROUND($K9,6)<>ROUND(MIN(1,SUMIFS($AF$5:$AF$1000,$U$5:$U$1000,ROW(),$V$5:$V$1000,"Sub")),6),FALSE),IF(ISNUMBER($L9),ROUND($L9,6)<>ROUND(MIN(1,SUMIFS($AG$5:$AG$1000,$U$5:$U$1000,ROW(),$V$5:$V$1000,"Sub")),6),FALSE))),"Con subactividades: no escriba en las semanas (se llenan solas)"&" · ","")&IF((COUNTIF($I9:$L9,">1")+COUNTIF($I9:$L9,"<0")+SUMPRODUCT((LEN($I9:$L9)>0)*NOT(ISNUMBER($I9:$L9))))>0,"Avance fuera de rango 0-100%"&" · ","")&IF(OR(AND(ISNUMBER($J9),$J9<N($I9)),AND(ISNUMBER($K9),$K9<MAX($I9:$J9)),AND(ISNUMBER($L9),$L9<MAX($I9:$K9))),"Avance semanal decreciente"&" · ","")&IF(AND(ISNUMBER($AS9),$AS9<FechaRef,IF($V9="Sub",1,N($M9))<1),"Vencida"&" · ","")&IF(AND(ObsObligatoria="Sí",ISNUMBER($AS9),$AS9<FechaRef,IF($V9="Sub",1,N($M9))<1,$Q9=""),"Vencida sin observación"&" · ",""),LEN(IF($C9="","Falta el nombre de la actividad"&" · ","")&IF(AND($V9="Sub",N($U9)=0),"Subactividad sin macroactividad arriba"&" · ","")&IF(AND($V9="Macro",$AR9=""),"Sin fecha de inicio"&" · ","")&IF(AND($V9="Macro",$AS9=""),"Sin fecha límite"&" · ","")&IF(AND(LEFT($C9,11)="[Jefatura] ",N($AQ9)=0),"No se encuentra en la hoja de la jefatura (elíjala de nuevo en la lista)"&" · ","")&IF(OR(AND($E9<>"",NOT(ISNUMBER($E9))),AND($F9<>"",NOT(ISNUMBER($F9))),AND($G9<>"",NOT(ISNUMBER($G9)))),"Fecha no válida"&" · ","")&IF(AND(ISNUMBER($AR9),ISNUMBER($AS9),$AR9>$AS9),"Inicio posterior a fecha límite"&" · ","")&IF(AND($V9="Macro",$H9<>"",OR(NOT(ISNUMBER($H9)),$H9<0,$H9>1)),"Peso fuera de rango"&" · ","")&IF(AND($V9="Sub",$H9<>"",OR(NOT(ISNUMBER($H9)),$H9<0,$H9>1)),"% de la subactividad fuera de rango 0-100%"&" · ","")&IF(AND(N($W9)>0,SUMIFS($H$5:$H$1000,$U$5:$U$1000,ROW(),$V$5:$V$1000,"Sub")>1.0001),"Las subactividades suman más de 100%"&" · ","")&IF(AND(N($W9)>0,OR(IF(ISNUMBER($I9),ROUND($I9,6)<>ROUND(MIN(1,SUMIFS($AD$5:$AD$1000,$U$5:$U$1000,ROW(),$V$5:$V$1000,"Sub")),6),FALSE),IF(ISNUMBER($J9),ROUND($J9,6)<>ROUND(MIN(1,SUMIFS($AE$5:$AE$1000,$U$5:$U$1000,ROW(),$V$5:$V$1000,"Sub")),6),FALSE),IF(ISNUMBER($K9),ROUND($K9,6)<>ROUND(MIN(1,SUMIFS($AF$5:$AF$1000,$U$5:$U$1000,ROW(),$V$5:$V$1000,"Sub")),6),FALSE),IF(ISNUMBER($L9),ROUND($L9,6)<>ROUND(MIN(1,SUMIFS($AG$5:$AG$1000,$U$5:$U$1000,ROW(),$V$5:$V$1000,"Sub")),6),FALSE))),"Con subactividades: no escriba en las semanas (se llenan solas)"&" · ","")&IF((COUNTIF($I9:$L9,">1")+COUNTIF($I9:$L9,"<0")+SUMPRODUCT((LEN($I9:$L9)>0)*NOT(ISNUMBER($I9:$L9))))>0,"Avance fuera de rango 0-100%"&" · ","")&IF(OR(AND(ISNUMBER($J9),$J9<N($I9)),AND(ISNUMBER($K9),$K9<MAX($I9:$J9)),AND(ISNUMBER($L9),$L9<MAX($I9:$K9))),"Avance semanal decreciente"&" · ","")&IF(AND(ISNUMBER($AS9),$AS9<FechaRef,IF($V9="Sub",1,N($M9))<1),"Vencida"&" · ","")&IF(AND(ObsObligatoria="Sí",ISNUMBER($AS9),$AS9<FechaRef,IF($V9="Sub",1,N($M9))<1,$Q9=""),"Vencida sin observación"&" · ",""))-3))) | S9: =IF(NOT((COUNTA($B9:$D9)+COUNTA($G9:$H9)+COUNTA($Q9))>0),"",IF(AND($V9="Sub",N($U9)>0),IF(ISNUMBER(INDEX($AR$5:$AR$1000,$U9-4)),DATE(YEAR(INDEX($AR$5:$AR$1000,$U9-4)),MONTH(INDEX($AR$5:$AR$1000,$U9-4)),1),IF(ISNUMBER(INDEX($AS$5:$AS$1000,$U9-4)),DATE(YEAR(INDEX($AS$5:$AS$1000,$U9-4)),MONTH(INDEX($AS$5:$AS$1000,$U9-4)),1),MesCiclo)),IF(ISNUMBER($AR9),DATE(YEAR($AR9),MONTH($AR9),1),IF(ISNUMBER($AS9),DATE(YEAR($AS9),MONTH($AS9),1),MesCiclo)))) | T9: =IF(OR($S9="",$S9<>MesCiclo,$V9<>"Macro"),"",COUNTIFS($S$5:$S9,MesCiclo,$V$5:$V9,"Macro")) | U9: =IF($V9="","",IF($V9="Macro",ROW(),IFERROR(LOOKUP(2,1/($V$5:$V9="Macro"),ROW($V$5:$V9)),0))) | V9: =IF(NOT((COUNTA($B9:$D9)+COUNTA($G9:$H9)+COUNTA($Q9))>0),"",IF($B9="Subactividad","Sub","Macro")) | W9: =IF($V9="Macro",COUNTIFS($U$5:$U$1000,ROW(),$V$5:$V$1000,"Sub"),"") | X9: =IF($V9<>"Sub","",IF(AND(ISNUMBER($H9),N($H9)>0),$H9,IFERROR(MAX(0,1-SUMIFS($H$5:$H$1000,$U$5:$U$1000,$U9,$V$5:$V$1000,"Sub"))/(COUNTIFS($U$5:$U$1000,$U9,$V$5:$V$1000,"Sub")-COUNTIFS($U$5:$U$1000,$U9,$V$5:$V$1000,"Sub",$H$5:$H$1000,">0")),0))) | Y9: =IF($V9="","",IF($V9="Sub",N($X9)*IF(ISNUMBER($G9),1,MIN(1,MAX(0,IFERROR(LOOKUP(2,1/ISNUMBER($I9:$L9),$I9:$L9),0)))),IF(ISNUMBER($G9),1,IFERROR(LOOKUP(2,1/($I9:$L9<>""),$I9:$L9),0)))) | Z9: =IF($V9="","",IF(AND(ISNUMBER($G9),$G9<=IF($S9=MesCiclo,InicioCiclo,$S9+MOD(2-WEEKDAY($S9),7))+6),1,IF(ISNUMBER($I9),$I9,0))) | AA9: =IF($V9="","",IF(AND(ISNUMBER($G9),$G9<=IF($S9=MesCiclo,InicioCiclo,$S9+MOD(2-WEEKDAY($S9),7))+13),1,IF(ISNUMBER($J9),$J9,$Z9))) | AB9: =IF($V9="","",IF(AND(ISNUMBER($G9),$G9<=IF($S9=MesCiclo,InicioCiclo,$S9+MOD(2-WEEKDAY($S9),7))+20),1,IF(ISNUMBER($K9),$K9,$AA9))) | AC9: =IF($V9="","",IF(AND(ISNUMBER($G9),$G9<=IF($S9=MesCiclo,InicioCiclo,$S9+MOD(2-WEEKDAY($S9),7))+27),1,IF(ISNUMBER($L9),$L9,$AB9))) | AD9: =IF($V9<>"Sub","",N($X9)*IF(AND(ISNUMBER($G9),$G9<=IF($S9=MesCiclo,InicioCiclo,$S9+MOD(2-WEEKDAY($S9),7))+6),1,MIN(1,MAX(0,IF(ISNUMBER(OFFSET($A$1,ROW()-1,8)),OFFSET($A$1,ROW()-1,8),0))))) | AE9: =IF($V9<>"Sub","",N($X9)*IF(AND(ISNUMBER($G9),$G9<=IF($S9=MesCiclo,InicioCiclo,$S9+MOD(2-WEEKDAY($S9),7))+13),1,MIN(1,MAX(0,IF(ISNUMBER(OFFSET($A$1,ROW()-1,9)),OFFSET($A$1,ROW()-1,9),IF(ISNUMBER(OFFSET($A$1,ROW()-1,8)),OFFSET($A$1,ROW()-1,8),0)))))) | AF9: =IF($V9<>"Sub","",N($X9)*IF(AND(ISNUMBER($G9),$G9<=IF($S9=MesCiclo,InicioCiclo,$S9+MOD(2-WEEKDAY($S9),7))+20),1,MIN(1,MAX(0,IF(ISNUMBER(OFFSET($A$1,ROW()-1,10)),OFFSET($A$1,ROW()-1,10),IF(ISNUMBER(OFFSET($A$1,ROW()-1,9)),OFFSET($A$1,ROW()-1,9),IF(ISNUMBER(OFFSET($A$1,ROW()-1,8)),OFFSET($A$1,ROW()-1,8),0))))))) | AG9: =IF($V9<>"Sub","",N($X9)*IF(AND(ISNUMBER($G9),$G9<=IF($S9=MesCiclo,InicioCiclo,$S9+MOD(2-WEEKDAY($S9),7))+27),1,MIN(1,MAX(0,IF(ISNUMBER(OFFSET($A$1,ROW()-1,11)),OFFSET($A$1,ROW()-1,11),IF(ISNUMBER(OFFSET($A$1,ROW()-1,10)),OFFSET($A$1,ROW()-1,10),IF(ISNUMBER(OFFSET($A$1,ROW()-1,9)),OFFSET($A$1,ROW()-1,9),IF(ISNUMBER(OFFSET($A$1,ROW()-1,8)),OFFSET($A$1,ROW()-1,8),0)))))))) | AH9: =IF($V9="","",IF(AND(ISNUMBER($G9),$G9<=IF($S9=MesCiclo,InicioCiclo,$S9+MOD(2-WEEKDAY($S9),7))+6),1,IF(N($W9)>0,MIN(1,SUMIFS($AD$5:$AD$1000,$U$5:$U$1000,ROW(),$V$5:$V$1000,"Sub")),$Z9))) | AI9: =IF($V9="","",IF(AND(ISNUMBER($G9),$G9<=IF($S9=MesCiclo,InicioCiclo,$S9+MOD(2-WEEKDAY($S9),7))+13),1,IF(N($W9)>0,MIN(1,SUMIFS($AE$5:$AE$1000,$U$5:$U$1000,ROW(),$V$5:$V$1000,"Sub")),$AA9))) | AJ9: =IF($V9="","",IF(AND(ISNUMBER($G9),$G9<=IF($S9=MesCiclo,InicioCiclo,$S9+MOD(2-WEEKDAY($S9),7))+20),1,IF(N($W9)>0,MIN(1,SUMIFS($AF$5:$AF$1000,$U$5:$U$1000,ROW(),$V$5:$V$1000,"Sub")),$AB9))) | AK9: =IF($V9="","",IF(AND(ISNUMBER($G9),$G9<=IF($S9=MesCiclo,InicioCiclo,$S9+MOD(2-WEEKDAY($S9),7))+27),1,IF(N($W9)>0,MIN(1,SUMIFS($AG$5:$AG$1000,$U$5:$U$1000,ROW(),$V$5:$V$1000,"Sub")),$AC9))) | AL9: =IF($V9<>"Macro","",IF(COUNTIFS($S$5:$S$1000,$S9,$V$5:$V$1000,"Macro",$H$5:$H$1000,">0")=0,1/COUNTIFS($S$5:$S$1000,$S9,$V$5:$V$1000,"Macro"),IF(AND(ISNUMBER($H9),N($H9)>0),$H9,SUMIFS($H$5:$H$1000,$S$5:$S$1000,$S9,$V$5:$V$1000,"Macro")/COUNTIFS($S$5:$S$1000,$S9,$V$5:$V$1000,"Macro",$H$5:$H$1000,">0"))/(COUNTIFS($S$5:$S$1000,$S9,$V$5:$V$1000,"Macro")*SUMIFS($H$5:$H$1000,$S$5:$S$1000,$S9,$V$5:$V$1000,"Macro")/COUNTIFS($S$5:$S$1000,$S9,$V$5:$V$1000,"Macro",$H$5:$H$1000,">0")))) | AM9: =IF(NOT(AND($D9<>"",$V9="Macro")),"",IFERROR(CHOOSE(MATCH($D9,ListaPuestos,0),MATCH("[Jefatura] "&$C9,'Cronograma R. Operacional'!$C$5:$C$1000,0),MATCH("[Jefatura] "&$C9,'Cronograma R. Normativo'!$C$5:$C$1000,0),MATCH("[Jefatura] "&$C9,'Cronograma R. Financiero'!$C$5:$C$1000,0),MATCH("[Jefatura] "&$C9,'Cronograma Asistente Técnico'!$C$5:$C$1000,0)),0)) | AN9: =IF(AND(AND($D9<>"",$V9="Macro"),$S9=MesCiclo),COUNTIFS($D$5:$D9,$D9,$S$5:$S9,MesCiclo,$V$5:$V9,"Macro"),"") | AO9: =IF($AN9="","",$D9&"|"&$AN9) | AP9: =IF(AND($D9<>"",$V9="Macro"),$D9&"|"&$C9,"") | AQ9: ="" | AR9: =IF(N($AQ9)>0,INDEX(rIni_ADM,$AQ9),IF(ISNUMBER($E9),$E9,"")) | AS9: =IF(N($AQ9)>0,INDEX(rLim_ADM,$AQ9),IF(ISNUMBER($F9),$F9,""))
A10: =IF(NOT((COUNTA($B10:$D10)+COUNTA($G10:$H10)+COUNTA($Q10))>0),"",IF($V10="Macro",COUNTIFS($V$5:$V10,"Macro",$S$5:$S10,$S10),IF(N($U10)=0,"?",COUNTIFS(INDEX($V$5:$V$1000,1):INDEX($V$5:$V$1000,$U10-4),"Macro",INDEX($S$5:$S$1000,1):INDEX($S$5:$S$1000,$U10-4),INDEX($S$5:$S$1000,$U10-4))&"."&COUNTIFS($U$5:$U10,$U10,$V$5:$V10,"Sub")))) | I10: =IF(N($W10)=0,"",IF(AND($S10=MesCiclo,1>SemanaActual),"",MIN(1,SUMIFS(OFFSET($A$1,ROW(),29,1000-ROW(),1),OFFSET($A$1,ROW(),20,1000-ROW(),1),ROW(),OFFSET($A$1,ROW(),21,1000-ROW(),1),"Sub")))) | J10: =IF(N($W10)=0,"",IF(AND($S10=MesCiclo,2>SemanaActual),"",MIN(1,SUMIFS(OFFSET($A$1,ROW(),30,1000-ROW(),1),OFFSET($A$1,ROW(),20,1000-ROW(),1),ROW(),OFFSET($A$1,ROW(),21,1000-ROW(),1),"Sub")))) | K10: =IF(N($W10)=0,"",IF(AND($S10=MesCiclo,3>SemanaActual),"",MIN(1,SUMIFS(OFFSET($A$1,ROW(),31,1000-ROW(),1),OFFSET($A$1,ROW(),20,1000-ROW(),1),ROW(),OFFSET($A$1,ROW(),21,1000-ROW(),1),"Sub")))) | L10: =IF(N($W10)=0,"",IF(AND($S10=MesCiclo,4>SemanaActual),"",MIN(1,SUMIFS(OFFSET($A$1,ROW(),32,1000-ROW(),1),OFFSET($A$1,ROW(),20,1000-ROW(),1),ROW(),OFFSET($A$1,ROW(),21,1000-ROW(),1),"Sub")))) | M10: =IF(NOT((COUNTA($B10:$D10)+COUNTA($G10:$H10)+COUNTA($Q10))>0),"",IF(AND($D10<>"",$V10="Macro"),IF(N($AM10)>0,N(CHOOSE(MATCH($D10,ListaPuestos,0),INDEX('Cronograma R. Operacional'!$M$5:$M$1000,$AM10),INDEX('Cronograma R. Normativo'!$M$5:$M$1000,$AM10),INDEX('Cronograma R. Financiero'!$M$5:$M$1000,$AM10),INDEX('Cronograma Asistente Técnico'!$M$5:$M$1000,$AM10))),0),IF(ISNUMBER($G10),1,IF(N($W10)>0,MIN(1,SUMIFS($Y$5:$Y$1000,$U$5:$U$1000,ROW(),$V$5:$V$1000,"Sub")),$Y10)))) | N10: =IF(OR($M10="",$V10="Sub"),"",IF($M10>=1,"Completado",IF($M10>0,"En curso","Pendiente"))) | O10: =IF(NOT((COUNTA($B10:$D10)+COUNTA($G10:$H10)+COUNTA($Q10))>0),"",IF(AND(AND($D10<>"",$V10="Macro"),N($AM10)>0),CHOOSE(MATCH($D10,ListaPuestos,0),INDEX('Cronograma R. Operacional'!$O$5:$O$1000,$AM10),INDEX('Cronograma R. Normativo'!$O$5:$O$1000,$AM10),INDEX('Cronograma R. Financiero'!$O$5:$O$1000,$AM10),INDEX('Cronograma Asistente Técnico'!$O$5:$O$1000,$AM10))&"",IF(ISNUMBER($G10),IF(AND(ISNUMBER($AS10),$G10>$AS10),"Cumplida con "&($G10-$AS10)&IF($G10-$AS10=1," día"," días")&" de retraso","Cumplida"),IF(N($M10)>=1,"Cumplida",IF(NOT(ISNUMBER($AS10)),"Sin fecha límite",IF($AS10<FechaRef,"Vencida hace "&(FechaRef-$AS10)&IF(FechaRef-$AS10=1," día"," días"),IF($AS10=FechaRef,"Vence hoy",IF($AS10-FechaRef<=DiasAlerta,"Vence en "&($AS10-FechaRef)&IF($AS10-FechaRef=1," día"," días"),"En plazo")))))))) | P10: =IF(NOT((COUNTA($B10:$D10)+COUNTA($G10:$H10)+COUNTA($Q10))>0),"",IF($D10="","Propia",IF($V10<>"Macro","Solo se delegan macroactividades",IF(N($AM10)>0,"✔ Recibida por "&$D10,"⚠ "&$D10&" aún no la agrega")))) | R10: =IF(NOT((COUNTA($B10:$D10)+COUNTA($G10:$H10)+COUNTA($Q10))>0),"",IF((IF($C10="","Falta el nombre de la actividad"&" · ","")&IF(AND($V10="Sub",N($U10)=0),"Subactividad sin macroactividad arriba"&" · ","")&IF(AND($V10="Macro",$AR10=""),"Sin fecha de inicio"&" · ","")&IF(AND($V10="Macro",$AS10=""),"Sin fecha límite"&" · ","")&IF(AND(LEFT($C10,11)="[Jefatura] ",N($AQ10)=0),"No se encuentra en la hoja de la jefatura (elíjala de nuevo en la lista)"&" · ","")&IF(OR(AND($E10<>"",NOT(ISNUMBER($E10))),AND($F10<>"",NOT(ISNUMBER($F10))),AND($G10<>"",NOT(ISNUMBER($G10)))),"Fecha no válida"&" · ","")&IF(AND(ISNUMBER($AR10),ISNUMBER($AS10),$AR10>$AS10),"Inicio posterior a fecha límite"&" · ","")&IF(AND($V10="Macro",$H10<>"",OR(NOT(ISNUMBER($H10)),$H10<0,$H10>1)),"Peso fuera de rango"&" · ","")&IF(AND($V10="Sub",$H10<>"",OR(NOT(ISNUMBER($H10)),$H10<0,$H10>1)),"% de la subactividad fuera de rango 0-100%"&" · ","")&IF(AND(N($W10)>0,SUMIFS($H$5:$H$1000,$U$5:$U$1000,ROW(),$V$5:$V$1000,"Sub")>1.0001),"Las subactividades suman más de 100%"&" · ","")&IF(AND(N($W10)>0,OR(IF(ISNUMBER($I10),ROUND($I10,6)<>ROUND(MIN(1,SUMIFS($AD$5:$AD$1000,$U$5:$U$1000,ROW(),$V$5:$V$1000,"Sub")),6),FALSE),IF(ISNUMBER($J10),ROUND($J10,6)<>ROUND(MIN(1,SUMIFS($AE$5:$AE$1000,$U$5:$U$1000,ROW(),$V$5:$V$1000,"Sub")),6),FALSE),IF(ISNUMBER($K10),ROUND($K10,6)<>ROUND(MIN(1,SUMIFS($AF$5:$AF$1000,$U$5:$U$1000,ROW(),$V$5:$V$1000,"Sub")),6),FALSE),IF(ISNUMBER($L10),ROUND($L10,6)<>ROUND(MIN(1,SUMIFS($AG$5:$AG$1000,$U$5:$U$1000,ROW(),$V$5:$V$1000,"Sub")),6),FALSE))),"Con subactividades: no escriba en las semanas (se llenan solas)"&" · ","")&IF((COUNTIF($I10:$L10,">1")+COUNTIF($I10:$L10,"<0")+SUMPRODUCT((LEN($I10:$L10)>0)*NOT(ISNUMBER($I10:$L10))))>0,"Avance fuera de rango 0-100%"&" · ","")&IF(OR(AND(ISNUMBER($J10),$J10<N($I10)),AND(ISNUMBER($K10),$K10<MAX($I10:$J10)),AND(ISNUMBER($L10),$L10<MAX($I10:$K10))),"Avance semanal decreciente"&" · ","")&IF(AND(ISNUMBER($AS10),$AS10<FechaRef,IF($V10="Sub",1,N($M10))<1),"Vencida"&" · ","")&IF(AND(ObsObligatoria="Sí",ISNUMBER($AS10),$AS10<FechaRef,IF($V10="Sub",1,N($M10))<1,$Q10=""),"Vencida sin observación"&" · ",""))="","✔ OK","⚠ "&LEFT(IF($C10="","Falta el nombre de la actividad"&" · ","")&IF(AND($V10="Sub",N($U10)=0),"Subactividad sin macroactividad arriba"&" · ","")&IF(AND($V10="Macro",$AR10=""),"Sin fecha de inicio"&" · ","")&IF(AND($V10="Macro",$AS10=""),"Sin fecha límite"&" · ","")&IF(AND(LEFT($C10,11)="[Jefatura] ",N($AQ10)=0),"No se encuentra en la hoja de la jefatura (elíjala de nuevo en la lista)"&" · ","")&IF(OR(AND($E10<>"",NOT(ISNUMBER($E10))),AND($F10<>"",NOT(ISNUMBER($F10))),AND($G10<>"",NOT(ISNUMBER($G10)))),"Fecha no válida"&" · ","")&IF(AND(ISNUMBER($AR10),ISNUMBER($AS10),$AR10>$AS10),"Inicio posterior a fecha límite"&" · ","")&IF(AND($V10="Macro",$H10<>"",OR(NOT(ISNUMBER($H10)),$H10<0,$H10>1)),"Peso fuera de rango"&" · ","")&IF(AND($V10="Sub",$H10<>"",OR(NOT(ISNUMBER($H10)),$H10<0,$H10>1)),"% de la subactividad fuera de rango 0-100%"&" · ","")&IF(AND(N($W10)>0,SUMIFS($H$5:$H$1000,$U$5:$U$1000,ROW(),$V$5:$V$1000,"Sub")>1.0001),"Las subactividades suman más de 100%"&" · ","")&IF(AND(N($W10)>0,OR(IF(ISNUMBER($I10),ROUND($I10,6)<>ROUND(MIN(1,SUMIFS($AD$5:$AD$1000,$U$5:$U$1000,ROW(),$V$5:$V$1000,"Sub")),6),FALSE),IF(ISNUMBER($J10),ROUND($J10,6)<>ROUND(MIN(1,SUMIFS($AE$5:$AE$1000,$U$5:$U$1000,ROW(),$V$5:$V$1000,"Sub")),6),FALSE),IF(ISNUMBER($K10),ROUND($K10,6)<>ROUND(MIN(1,SUMIFS($AF$5:$AF$1000,$U$5:$U$1000,ROW(),$V$5:$V$1000,"Sub")),6),FALSE),IF(ISNUMBER($L10),ROUND($L10,6)<>ROUND(MIN(1,SUMIFS($AG$5:$AG$1000,$U$5:$U$1000,ROW(),$V$5:$V$1000,"Sub")),6),FALSE))),"Con subactividades: no escriba en las semanas (se llenan solas)"&" · ","")&IF((COUNTIF($I10:$L10,">1")+COUNTIF($I10:$L10,"<0")+SUMPRODUCT((LEN($I10:$L10)>0)*NOT(ISNUMBER($I10:$L10))))>0,"Avance fuera de rango 0-100%"&" · ","")&IF(OR(AND(ISNUMBER($J10),$J10<N($I10)),AND(ISNUMBER($K10),$K10<MAX($I10:$J10)),AND(ISNUMBER($L10),$L10<MAX($I10:$K10))),"Avance semanal decreciente"&" · ","")&IF(AND(ISNUMBER($AS10),$AS10<FechaRef,IF($V10="Sub",1,N($M10))<1),"Vencida"&" · ","")&IF(AND(ObsObligatoria="Sí",ISNUMBER($AS10),$AS10<FechaRef,IF($V10="Sub",1,N($M10))<1,$Q10=""),"Vencida sin observación"&" · ",""),LEN(IF($C10="","Falta el nombre de la actividad"&" · ","")&IF(AND($V10="Sub",N($U10)=0),"Subactividad sin macroactividad arriba"&" · ","")&IF(AND($V10="Macro",$AR10=""),"Sin fecha de inicio"&" · ","")&IF(AND($V10="Macro",$AS10=""),"Sin fecha límite"&" · ","")&IF(AND(LEFT($C10,11)="[Jefatura] ",N($AQ10)=0),"No se encuentra en la hoja de la jefatura (elíjala de nuevo en la lista)"&" · ","")&IF(OR(AND($E10<>"",NOT(ISNUMBER($E10))),AND($F10<>"",NOT(ISNUMBER($F10))),AND($G10<>"",NOT(ISNUMBER($G10)))),"Fecha no válida"&" · ","")&IF(AND(ISNUMBER($AR10),ISNUMBER($AS10),$AR10>$AS10),"Inicio posterior a fecha límite"&" · ","")&IF(AND($V10="Macro",$H10<>"",OR(NOT(ISNUMBER($H10)),$H10<0,$H10>1)),"Peso fuera de rango"&" · ","")&IF(AND($V10="Sub",$H10<>"",OR(NOT(ISNUMBER($H10)),$H10<0,$H10>1)),"% de la subactividad fuera de rango 0-100%"&" · ","")&IF(AND(N($W10)>0,SUMIFS($H$5:$H$1000,$U$5:$U$1000,ROW(),$V$5:$V$1000,"Sub")>1.0001),"Las subactividades suman más de 100%"&" · ","")&IF(AND(N($W10)>0,OR(IF(ISNUMBER($I10),ROUND($I10,6)<>ROUND(MIN(1,SUMIFS($AD$5:$AD$1000,$U$5:$U$1000,ROW(),$V$5:$V$1000,"Sub")),6),FALSE),IF(ISNUMBER($J10),ROUND($J10,6)<>ROUND(MIN(1,SUMIFS($AE$5:$AE$1000,$U$5:$U$1000,ROW(),$V$5:$V$1000,"Sub")),6),FALSE),IF(ISNUMBER($K10),ROUND($K10,6)<>ROUND(MIN(1,SUMIFS($AF$5:$AF$1000,$U$5:$U$1000,ROW(),$V$5:$V$1000,"Sub")),6),FALSE),IF(ISNUMBER($L10),ROUND($L10,6)<>ROUND(MIN(1,SUMIFS($AG$5:$AG$1000,$U$5:$U$1000,ROW(),$V$5:$V$1000,"Sub")),6),FALSE))),"Con subactividades: no escriba en las semanas (se llenan solas)"&" · ","")&IF((COUNTIF($I10:$L10,">1")+COUNTIF($I10:$L10,"<0")+SUMPRODUCT((LEN($I10:$L10)>0)*NOT(ISNUMBER($I10:$L10))))>0,"Avance fuera de rango 0-100%"&" · ","")&IF(OR(AND(ISNUMBER($J10),$J10<N($I10)),AND(ISNUMBER($K10),$K10<MAX($I10:$J10)),AND(ISNUMBER($L10),$L10<MAX($I10:$K10))),"Avance semanal decreciente"&" · ","")&IF(AND(ISNUMBER($AS10),$AS10<FechaRef,IF($V10="Sub",1,N($M10))<1),"Vencida"&" · ","")&IF(AND(ObsObligatoria="Sí",ISNUMBER($AS10),$AS10<FechaRef,IF($V10="Sub",1,N($M10))<1,$Q10=""),"Vencida sin observación"&" · ",""))-3))) | S10: =IF(NOT((COUNTA($B10:$D10)+COUNTA($G10:$H10)+COUNTA($Q10))>0),"",IF(AND($V10="Sub",N($U10)>0),IF(ISNUMBER(INDEX($AR$5:$AR$1000,$U10-4)),DATE(YEAR(INDEX($AR$5:$AR$1000,$U10-4)),MONTH(INDEX($AR$5:$AR$1000,$U10-4)),1),IF(ISNUMBER(INDEX($AS$5:$AS$1000,$U10-4)),DATE(YEAR(INDEX($AS$5:$AS$1000,$U10-4)),MONTH(INDEX($AS$5:$AS$1000,$U10-4)),1),MesCiclo)),IF(ISNUMBER($AR10),DATE(YEAR($AR10),MONTH($AR10),1),IF(ISNUMBER($AS10),DATE(YEAR($AS10),MONTH($AS10),1),MesCiclo)))) | T10: =IF(OR($S10="",$S10<>MesCiclo,$V10<>"Macro"),"",COUNTIFS($S$5:$S10,MesCiclo,$V$5:$V10,"Macro")) | U10: =IF($V10="","",IF($V10="Macro",ROW(),IFERROR(LOOKUP(2,1/($V$5:$V10="Macro"),ROW($V$5:$V10)),0))) | V10: =IF(NOT((COUNTA($B10:$D10)+COUNTA($G10:$H10)+COUNTA($Q10))>0),"",IF($B10="Subactividad","Sub","Macro")) | W10: =IF($V10="Macro",COUNTIFS($U$5:$U$1000,ROW(),$V$5:$V$1000,"Sub"),"") | X10: =IF($V10<>"Sub","",IF(AND(ISNUMBER($H10),N($H10)>0),$H10,IFERROR(MAX(0,1-SUMIFS($H$5:$H$1000,$U$5:$U$1000,$U10,$V$5:$V$1000,"Sub"))/(COUNTIFS($U$5:$U$1000,$U10,$V$5:$V$1000,"Sub")-COUNTIFS($U$5:$U$1000,$U10,$V$5:$V$1000,"Sub",$H$5:$H$1000,">0")),0))) | Y10: =IF($V10="","",IF($V10="Sub",N($X10)*IF(ISNUMBER($G10),1,MIN(1,MAX(0,IFERROR(LOOKUP(2,1/ISNUMBER($I10:$L10),$I10:$L10),0)))),IF(ISNUMBER($G10),1,IFERROR(LOOKUP(2,1/($I10:$L10<>""),$I10:$L10),0)))) | Z10: =IF($V10="","",IF(AND(ISNUMBER($G10),$G10<=IF($S10=MesCiclo,InicioCiclo,$S10+MOD(2-WEEKDAY($S10),7))+6),1,IF(ISNUMBER($I10),$I10,0))) | AA10: =IF($V10="","",IF(AND(ISNUMBER($G10),$G10<=IF($S10=MesCiclo,InicioCiclo,$S10+MOD(2-WEEKDAY($S10),7))+13),1,IF(ISNUMBER($J10),$J10,$Z10))) | AB10: =IF($V10="","",IF(AND(ISNUMBER($G10),$G10<=IF($S10=MesCiclo,InicioCiclo,$S10+MOD(2-WEEKDAY($S10),7))+20),1,IF(ISNUMBER($K10),$K10,$AA10))) | AC10: =IF($V10="","",IF(AND(ISNUMBER($G10),$G10<=IF($S10=MesCiclo,InicioCiclo,$S10+MOD(2-WEEKDAY($S10),7))+27),1,IF(ISNUMBER($L10),$L10,$AB10))) | AD10: =IF($V10<>"Sub","",N($X10)*IF(AND(ISNUMBER($G10),$G10<=IF($S10=MesCiclo,InicioCiclo,$S10+MOD(2-WEEKDAY($S10),7))+6),1,MIN(1,MAX(0,IF(ISNUMBER(OFFSET($A$1,ROW()-1,8)),OFFSET($A$1,ROW()-1,8),0))))) | AE10: =IF($V10<>"Sub","",N($X10)*IF(AND(ISNUMBER($G10),$G10<=IF($S10=MesCiclo,InicioCiclo,$S10+MOD(2-WEEKDAY($S10),7))+13),1,MIN(1,MAX(0,IF(ISNUMBER(OFFSET($A$1,ROW()-1,9)),OFFSET($A$1,ROW()-1,9),IF(ISNUMBER(OFFSET($A$1,ROW()-1,8)),OFFSET($A$1,ROW()-1,8),0)))))) | AF10: =IF($V10<>"Sub","",N($X10)*IF(AND(ISNUMBER($G10),$G10<=IF($S10=MesCiclo,InicioCiclo,$S10+MOD(2-WEEKDAY($S10),7))+20),1,MIN(1,MAX(0,IF(ISNUMBER(OFFSET($A$1,ROW()-1,10)),OFFSET($A$1,ROW()-1,10),IF(ISNUMBER(OFFSET($A$1,ROW()-1,9)),OFFSET($A$1,ROW()-1,9),IF(ISNUMBER(OFFSET($A$1,ROW()-1,8)),OFFSET($A$1,ROW()-1,8),0))))))) | AG10: =IF($V10<>"Sub","",N($X10)*IF(AND(ISNUMBER($G10),$G10<=IF($S10=MesCiclo,InicioCiclo,$S10+MOD(2-WEEKDAY($S10),7))+27),1,MIN(1,MAX(0,IF(ISNUMBER(OFFSET($A$1,ROW()-1,11)),OFFSET($A$1,ROW()-1,11),IF(ISNUMBER(OFFSET($A$1,ROW()-1,10)),OFFSET($A$1,ROW()-1,10),IF(ISNUMBER(OFFSET($A$1,ROW()-1,9)),OFFSET($A$1,ROW()-1,9),IF(ISNUMBER(OFFSET($A$1,ROW()-1,8)),OFFSET($A$1,ROW()-1,8),0)))))))) | AH10: =IF($V10="","",IF(AND(ISNUMBER($G10),$G10<=IF($S10=MesCiclo,InicioCiclo,$S10+MOD(2-WEEKDAY($S10),7))+6),1,IF(N($W10)>0,MIN(1,SUMIFS($AD$5:$AD$1000,$U$5:$U$1000,ROW(),$V$5:$V$1000,"Sub")),$Z10))) | AI10: =IF($V10="","",IF(AND(ISNUMBER($G10),$G10<=IF($S10=MesCiclo,InicioCiclo,$S10+MOD(2-WEEKDAY($S10),7))+13),1,IF(N($W10)>0,MIN(1,SUMIFS($AE$5:$AE$1000,$U$5:$U$1000,ROW(),$V$5:$V$1000,"Sub")),$AA10))) | AJ10: =IF($V10="","",IF(AND(ISNUMBER($G10),$G10<=IF($S10=MesCiclo,InicioCiclo,$S10+MOD(2-WEEKDAY($S10),7))+20),1,IF(N($W10)>0,MIN(1,SUMIFS($AF$5:$AF$1000,$U$5:$U$1000,ROW(),$V$5:$V$1000,"Sub")),$AB10))) | AK10: =IF($V10="","",IF(AND(ISNUMBER($G10),$G10<=IF($S10=MesCiclo,InicioCiclo,$S10+MOD(2-WEEKDAY($S10),7))+27),1,IF(N($W10)>0,MIN(1,SUMIFS($AG$5:$AG$1000,$U$5:$U$1000,ROW(),$V$5:$V$1000,"Sub")),$AC10))) | AL10: =IF($V10<>"Macro","",IF(COUNTIFS($S$5:$S$1000,$S10,$V$5:$V$1000,"Macro",$H$5:$H$1000,">0")=0,1/COUNTIFS($S$5:$S$1000,$S10,$V$5:$V$1000,"Macro"),IF(AND(ISNUMBER($H10),N($H10)>0),$H10,SUMIFS($H$5:$H$1000,$S$5:$S$1000,$S10,$V$5:$V$1000,"Macro")/COUNTIFS($S$5:$S$1000,$S10,$V$5:$V$1000,"Macro",$H$5:$H$1000,">0"))/(COUNTIFS($S$5:$S$1000,$S10,$V$5:$V$1000,"Macro")*SUMIFS($H$5:$H$1000,$S$5:$S$1000,$S10,$V$5:$V$1000,"Macro")/COUNTIFS($S$5:$S$1000,$S10,$V$5:$V$1000,"Macro",$H$5:$H$1000,">0")))) | AM10: =IF(NOT(AND($D10<>"",$V10="Macro")),"",IFERROR(CHOOSE(MATCH($D10,ListaPuestos,0),MATCH("[Jefatura] "&$C10,'Cronograma R. Operacional'!$C$5:$C$1000,0),MATCH("[Jefatura] "&$C10,'Cronograma R. Normativo'!$C$5:$C$1000,0),MATCH("[Jefatura] "&$C10,'Cronograma R. Financiero'!$C$5:$C$1000,0),MATCH("[Jefatura] "&$C10,'Cronograma Asistente Técnico'!$C$5:$C$1000,0)),0)) | AN10: =IF(AND(AND($D10<>"",$V10="Macro"),$S10=MesCiclo),COUNTIFS($D$5:$D10,$D10,$S$5:$S10,MesCiclo,$V$5:$V10,"Macro"),"") | AO10: =IF($AN10="","",$D10&"|"&$AN10) | AP10: =IF(AND($D10<>"",$V10="Macro"),$D10&"|"&$C10,"") | AQ10: ="" | AR10: =IF(N($AQ10)>0,INDEX(rIni_ADM,$AQ10),IF(ISNUMBER($E10),$E10,"")) | AS10: =IF(N($AQ10)>0,INDEX(rLim_ADM,$AQ10),IF(ISNUMBER($F10),$F10,""))
A11: =IF(NOT((COUNTA($B11:$D11)+COUNTA($G11:$H11)+COUNTA($Q11))>0),"",IF($V11="Macro",COUNTIFS($V$5:$V11,"Macro",$S$5:$S11,$S11),IF(N($U11)=0,"?",COUNTIFS(INDEX($V$5:$V$1000,1):INDEX($V$5:$V$1000,$U11-4),"Macro",INDEX($S$5:$S$1000,1):INDEX($S$5:$S$1000,$U11-4),INDEX($S$5:$S$1000,$U11-4))&"."&COUNTIFS($U$5:$U11,$U11,$V$5:$V11,"Sub")))) | I11: =IF(N($W11)=0,"",IF(AND($S11=MesCiclo,1>SemanaActual),"",MIN(1,SUMIFS(OFFSET($A$1,ROW(),29,1000-ROW(),1),OFFSET($A$1,ROW(),20,1000-ROW(),1),ROW(),OFFSET($A$1,ROW(),21,1000-ROW(),1),"Sub")))) | J11: =IF(N($W11)=0,"",IF(AND($S11=MesCiclo,2>SemanaActual),"",MIN(1,SUMIFS(OFFSET($A$1,ROW(),30,1000-ROW(),1),OFFSET($A$1,ROW(),20,1000-ROW(),1),ROW(),OFFSET($A$1,ROW(),21,1000-ROW(),1),"Sub")))) | K11: =IF(N($W11)=0,"",IF(AND($S11=MesCiclo,3>SemanaActual),"",MIN(1,SUMIFS(OFFSET($A$1,ROW(),31,1000-ROW(),1),OFFSET($A$1,ROW(),20,1000-ROW(),1),ROW(),OFFSET($A$1,ROW(),21,1000-ROW(),1),"Sub")))) | L11: =IF(N($W11)=0,"",IF(AND($S11=MesCiclo,4>SemanaActual),"",MIN(1,SUMIFS(OFFSET($A$1,ROW(),32,1000-ROW(),1),OFFSET($A$1,ROW(),20,1000-ROW(),1),ROW(),OFFSET($A$1,ROW(),21,1000-ROW(),1),"Sub")))) | M11: =IF(NOT((COUNTA($B11:$D11)+COUNTA($G11:$H11)+COUNTA($Q11))>0),"",IF(AND($D11<>"",$V11="Macro"),IF(N($AM11)>0,N(CHOOSE(MATCH($D11,ListaPuestos,0),INDEX('Cronograma R. Operacional'!$M$5:$M$1000,$AM11),INDEX('Cronograma R. Normativo'!$M$5:$M$1000,$AM11),INDEX('Cronograma R. Financiero'!$M$5:$M$1000,$AM11),INDEX('Cronograma Asistente Técnico'!$M$5:$M$1000,$AM11))),0),IF(ISNUMBER($G11),1,IF(N($W11)>0,MIN(1,SUMIFS($Y$5:$Y$1000,$U$5:$U$1000,ROW(),$V$5:$V$1000,"Sub")),$Y11)))) | N11: =IF(OR($M11="",$V11="Sub"),"",IF($M11>=1,"Completado",IF($M11>0,"En curso","Pendiente"))) | O11: =IF(NOT((COUNTA($B11:$D11)+COUNTA($G11:$H11)+COUNTA($Q11))>0),"",IF(AND(AND($D11<>"",$V11="Macro"),N($AM11)>0),CHOOSE(MATCH($D11,ListaPuestos,0),INDEX('Cronograma R. Operacional'!$O$5:$O$1000,$AM11),INDEX('Cronograma R. Normativo'!$O$5:$O$1000,$AM11),INDEX('Cronograma R. Financiero'!$O$5:$O$1000,$AM11),INDEX('Cronograma Asistente Técnico'!$O$5:$O$1000,$AM11))&"",IF(ISNUMBER($G11),IF(AND(ISNUMBER($AS11),$G11>$AS11),"Cumplida con "&($G11-$AS11)&IF($G11-$AS11=1," día"," días")&" de retraso","Cumplida"),IF(N($M11)>=1,"Cumplida",IF(NOT(ISNUMBER($AS11)),"Sin fecha límite",IF($AS11<FechaRef,"Vencida hace "&(FechaRef-$AS11)&IF(FechaRef-$AS11=1," día"," días"),IF($AS11=FechaRef,"Vence hoy",IF($AS11-FechaRef<=DiasAlerta,"Vence en "&($AS11-FechaRef)&IF($AS11-FechaRef=1," día"," días"),"En plazo")))))))) | P11: =IF(NOT((COUNTA($B11:$D11)+COUNTA($G11:$H11)+COUNTA($Q11))>0),"",IF($D11="","Propia",IF($V11<>"Macro","Solo se delegan macroactividades",IF(N($AM11)>0,"✔ Recibida por "&$D11,"⚠ "&$D11&" aún no la agrega")))) | R11: =IF(NOT((COUNTA($B11:$D11)+COUNTA($G11:$H11)+COUNTA($Q11))>0),"",IF((IF($C11="","Falta el nombre de la actividad"&" · ","")&IF(AND($V11="Sub",N($U11)=0),"Subactividad sin macroactividad arriba"&" · ","")&IF(AND($V11="Macro",$AR11=""),"Sin fecha de inicio"&" · ","")&IF(AND($V11="Macro",$AS11=""),"Sin fecha límite"&" · ","")&IF(AND(LEFT($C11,11)="[Jefatura] ",N($AQ11)=0),"No se encuentra en la hoja de la jefatura (elíjala de nuevo en la lista)"&" · ","")&IF(OR(AND($E11<>"",NOT(ISNUMBER($E11))),AND($F11<>"",NOT(ISNUMBER($F11))),AND($G11<>"",NOT(ISNUMBER($G11)))),"Fecha no válida"&" · ","")&IF(AND(ISNUMBER($AR11),ISNUMBER($AS11),$AR11>$AS11),"Inicio posterior a fecha límite"&" · ","")&IF(AND($V11="Macro",$H11<>"",OR(NOT(ISNUMBER($H11)),$H11<0,$H11>1)),"Peso fuera de rango"&" · ","")&IF(AND($V11="Sub",$H11<>"",OR(NOT(ISNUMBER($H11)),$H11<0,$H11>1)),"% de la subactividad fuera de rango 0-100%"&" · ","")&IF(AND(N($W11)>0,SUMIFS($H$5:$H$1000,$U$5:$U$1000,ROW(),$V$5:$V$1000,"Sub")>1.0001),"Las subactividades suman más de 100%"&" · ","")&IF(AND(N($W11)>0,OR(IF(ISNUMBER($I11),ROUND($I11,6)<>ROUND(MIN(1,SUMIFS($AD$5:$AD$1000,$U$5:$U$1000,ROW(),$V$5:$V$1000,"Sub")),6),FALSE),IF(ISNUMBER($J11),ROUND($J11,6)<>ROUND(MIN(1,SUMIFS($AE$5:$AE$1000,$U$5:$U$1000,ROW(),$V$5:$V$1000,"Sub")),6),FALSE),IF(ISNUMBER($K11),ROUND($K11,6)<>ROUND(MIN(1,SUMIFS($AF$5:$AF$1000,$U$5:$U$1000,ROW(),$V$5:$V$1000,"Sub")),6),FALSE),IF(ISNUMBER($L11),ROUND($L11,6)<>ROUND(MIN(1,SUMIFS($AG$5:$AG$1000,$U$5:$U$1000,ROW(),$V$5:$V$1000,"Sub")),6),FALSE))),"Con subactividades: no escriba en las semanas (se llenan solas)"&" · ","")&IF((COUNTIF($I11:$L11,">1")+COUNTIF($I11:$L11,"<0")+SUMPRODUCT((LEN($I11:$L11)>0)*NOT(ISNUMBER($I11:$L11))))>0,"Avance fuera de rango 0-100%"&" · ","")&IF(OR(AND(ISNUMBER($J11),$J11<N($I11)),AND(ISNUMBER($K11),$K11<MAX($I11:$J11)),AND(ISNUMBER($L11),$L11<MAX($I11:$K11))),"Avance semanal decreciente"&" · ","")&IF(AND(ISNUMBER($AS11),$AS11<FechaRef,IF($V11="Sub",1,N($M11))<1),"Vencida"&" · ","")&IF(AND(ObsObligatoria="Sí",ISNUMBER($AS11),$AS11<FechaRef,IF($V11="Sub",1,N($M11))<1,$Q11=""),"Vencida sin observación"&" · ",""))="","✔ OK","⚠ "&LEFT(IF($C11="","Falta el nombre de la actividad"&" · ","")&IF(AND($V11="Sub",N($U11)=0),"Subactividad sin macroactividad arriba"&" · ","")&IF(AND($V11="Macro",$AR11=""),"Sin fecha de inicio"&" · ","")&IF(AND($V11="Macro",$AS11=""),"Sin fecha límite"&" · ","")&IF(AND(LEFT($C11,11)="[Jefatura] ",N($AQ11)=0),"No se encuentra en la hoja de la jefatura (elíjala de nuevo en la lista)"&" · ","")&IF(OR(AND($E11<>"",NOT(ISNUMBER($E11))),AND($F11<>"",NOT(ISNUMBER($F11))),AND($G11<>"",NOT(ISNUMBER($G11)))),"Fecha no válida"&" · ","")&IF(AND(ISNUMBER($AR11),ISNUMBER($AS11),$AR11>$AS11),"Inicio posterior a fecha límite"&" · ","")&IF(AND($V11="Macro",$H11<>"",OR(NOT(ISNUMBER($H11)),$H11<0,$H11>1)),"Peso fuera de rango"&" · ","")&IF(AND($V11="Sub",$H11<>"",OR(NOT(ISNUMBER($H11)),$H11<0,$H11>1)),"% de la subactividad fuera de rango 0-100%"&" · ","")&IF(AND(N($W11)>0,SUMIFS($H$5:$H$1000,$U$5:$U$1000,ROW(),$V$5:$V$1000,"Sub")>1.0001),"Las subactividades suman más de 100%"&" · ","")&IF(AND(N($W11)>0,OR(IF(ISNUMBER($I11),ROUND($I11,6)<>ROUND(MIN(1,SUMIFS($AD$5:$AD$1000,$U$5:$U$1000,ROW(),$V$5:$V$1000,"Sub")),6),FALSE),IF(ISNUMBER($J11),ROUND($J11,6)<>ROUND(MIN(1,SUMIFS($AE$5:$AE$1000,$U$5:$U$1000,ROW(),$V$5:$V$1000,"Sub")),6),FALSE),IF(ISNUMBER($K11),ROUND($K11,6)<>ROUND(MIN(1,SUMIFS($AF$5:$AF$1000,$U$5:$U$1000,ROW(),$V$5:$V$1000,"Sub")),6),FALSE),IF(ISNUMBER($L11),ROUND($L11,6)<>ROUND(MIN(1,SUMIFS($AG$5:$AG$1000,$U$5:$U$1000,ROW(),$V$5:$V$1000,"Sub")),6),FALSE))),"Con subactividades: no escriba en las semanas (se llenan solas)"&" · ","")&IF((COUNTIF($I11:$L11,">1")+COUNTIF($I11:$L11,"<0")+SUMPRODUCT((LEN($I11:$L11)>0)*NOT(ISNUMBER($I11:$L11))))>0,"Avance fuera de rango 0-100%"&" · ","")&IF(OR(AND(ISNUMBER($J11),$J11<N($I11)),AND(ISNUMBER($K11),$K11<MAX($I11:$J11)),AND(ISNUMBER($L11),$L11<MAX($I11:$K11))),"Avance semanal decreciente"&" · ","")&IF(AND(ISNUMBER($AS11),$AS11<FechaRef,IF($V11="Sub",1,N($M11))<1),"Vencida"&" · ","")&IF(AND(ObsObligatoria="Sí",ISNUMBER($AS11),$AS11<FechaRef,IF($V11="Sub",1,N($M11))<1,$Q11=""),"Vencida sin observación"&" · ",""),LEN(IF($C11="","Falta el nombre de la actividad"&" · ","")&IF(AND($V11="Sub",N($U11)=0),"Subactividad sin macroactividad arriba"&" · ","")&IF(AND($V11="Macro",$AR11=""),"Sin fecha de inicio"&" · ","")&IF(AND($V11="Macro",$AS11=""),"Sin fecha límite"&" · ","")&IF(AND(LEFT($C11,11)="[Jefatura] ",N($AQ11)=0),"No se encuentra en la hoja de la jefatura (elíjala de nuevo en la lista)"&" · ","")&IF(OR(AND($E11<>"",NOT(ISNUMBER($E11))),AND($F11<>"",NOT(ISNUMBER($F11))),AND($G11<>"",NOT(ISNUMBER($G11)))),"Fecha no válida"&" · ","")&IF(AND(ISNUMBER($AR11),ISNUMBER($AS11),$AR11>$AS11),"Inicio posterior a fecha límite"&" · ","")&IF(AND($V11="Macro",$H11<>"",OR(NOT(ISNUMBER($H11)),$H11<0,$H11>1)),"Peso fuera de rango"&" · ","")&IF(AND($V11="Sub",$H11<>"",OR(NOT(ISNUMBER($H11)),$H11<0,$H11>1)),"% de la subactividad fuera de rango 0-100%"&" · ","")&IF(AND(N($W11)>0,SUMIFS($H$5:$H$1000,$U$5:$U$1000,ROW(),$V$5:$V$1000,"Sub")>1.0001),"Las subactividades suman más de 100%"&" · ","")&IF(AND(N($W11)>0,OR(IF(ISNUMBER($I11),ROUND($I11,6)<>ROUND(MIN(1,SUMIFS($AD$5:$AD$1000,$U$5:$U$1000,ROW(),$V$5:$V$1000,"Sub")),6),FALSE),IF(ISNUMBER($J11),ROUND($J11,6)<>ROUND(MIN(1,SUMIFS($AE$5:$AE$1000,$U$5:$U$1000,ROW(),$V$5:$V$1000,"Sub")),6),FALSE),IF(ISNUMBER($K11),ROUND($K11,6)<>ROUND(MIN(1,SUMIFS($AF$5:$AF$1000,$U$5:$U$1000,ROW(),$V$5:$V$1000,"Sub")),6),FALSE),IF(ISNUMBER($L11),ROUND($L11,6)<>ROUND(MIN(1,SUMIFS($AG$5:$AG$1000,$U$5:$U$1000,ROW(),$V$5:$V$1000,"Sub")),6),FALSE))),"Con subactividades: no escriba en las semanas (se llenan solas)"&" · ","")&IF((COUNTIF($I11:$L11,">1")+COUNTIF($I11:$L11,"<0")+SUMPRODUCT((LEN($I11:$L11)>0)*NOT(ISNUMBER($I11:$L11))))>0,"Avance fuera de rango 0-100%"&" · ","")&IF(OR(AND(ISNUMBER($J11),$J11<N($I11)),AND(ISNUMBER($K11),$K11<MAX($I11:$J11)),AND(ISNUMBER($L11),$L11<MAX($I11:$K11))),"Avance semanal decreciente"&" · ","")&IF(AND(ISNUMBER($AS11),$AS11<FechaRef,IF($V11="Sub",1,N($M11))<1),"Vencida"&" · ","")&IF(AND(ObsObligatoria="Sí",ISNUMBER($AS11),$AS11<FechaRef,IF($V11="Sub",1,N($M11))<1,$Q11=""),"Vencida sin observación"&" · ",""))-3))) | S11: =IF(NOT((COUNTA($B11:$D11)+COUNTA($G11:$H11)+COUNTA($Q11))>0),"",IF(AND($V11="Sub",N($U11)>0),IF(ISNUMBER(INDEX($AR$5:$AR$1000,$U11-4)),DATE(YEAR(INDEX($AR$5:$AR$1000,$U11-4)),MONTH(INDEX($AR$5:$AR$1000,$U11-4)),1),IF(ISNUMBER(INDEX($AS$5:$AS$1000,$U11-4)),DATE(YEAR(INDEX($AS$5:$AS$1000,$U11-4)),MONTH(INDEX($AS$5:$AS$1000,$U11-4)),1),MesCiclo)),IF(ISNUMBER($AR11),DATE(YEAR($AR11),MONTH($AR11),1),IF(ISNUMBER($AS11),DATE(YEAR($AS11),MONTH($AS11),1),MesCiclo)))) | T11: =IF(OR($S11="",$S11<>MesCiclo,$V11<>"Macro"),"",COUNTIFS($S$5:$S11,MesCiclo,$V$5:$V11,"Macro")) | U11: =IF($V11="","",IF($V11="Macro",ROW(),IFERROR(LOOKUP(2,1/($V$5:$V11="Macro"),ROW($V$5:$V11)),0))) | V11: =IF(NOT((COUNTA($B11:$D11)+COUNTA($G11:$H11)+COUNTA($Q11))>0),"",IF($B11="Subactividad","Sub","Macro")) | W11: =IF($V11="Macro",COUNTIFS($U$5:$U$1000,ROW(),$V$5:$V$1000,"Sub"),"") | X11: =IF($V11<>"Sub","",IF(AND(ISNUMBER($H11),N($H11)>0),$H11,IFERROR(MAX(0,1-SUMIFS($H$5:$H$1000,$U$5:$U$1000,$U11,$V$5:$V$1000,"Sub"))/(COUNTIFS($U$5:$U$1000,$U11,$V$5:$V$1000,"Sub")-COUNTIFS($U$5:$U$1000,$U11,$V$5:$V$1000,"Sub",$H$5:$H$1000,">0")),0))) | Y11: =IF($V11="","",IF($V11="Sub",N($X11)*IF(ISNUMBER($G11),1,MIN(1,MAX(0,IFERROR(LOOKUP(2,1/ISNUMBER($I11:$L11),$I11:$L11),0)))),IF(ISNUMBER($G11),1,IFERROR(LOOKUP(2,1/($I11:$L11<>""),$I11:$L11),0)))) | Z11: =IF($V11="","",IF(AND(ISNUMBER($G11),$G11<=IF($S11=MesCiclo,InicioCiclo,$S11+MOD(2-WEEKDAY($S11),7))+6),1,IF(ISNUMBER($I11),$I11,0))) | AA11: =IF($V11="","",IF(AND(ISNUMBER($G11),$G11<=IF($S11=MesCiclo,InicioCiclo,$S11+MOD(2-WEEKDAY($S11),7))+13),1,IF(ISNUMBER($J11),$J11,$Z11))) | AB11: =IF($V11="","",IF(AND(ISNUMBER($G11),$G11<=IF($S11=MesCiclo,InicioCiclo,$S11+MOD(2-WEEKDAY($S11),7))+20),1,IF(ISNUMBER($K11),$K11,$AA11))) | AC11: =IF($V11="","",IF(AND(ISNUMBER($G11),$G11<=IF($S11=MesCiclo,InicioCiclo,$S11+MOD(2-WEEKDAY($S11),7))+27),1,IF(ISNUMBER($L11),$L11,$AB11))) | AD11: =IF($V11<>"Sub","",N($X11)*IF(AND(ISNUMBER($G11),$G11<=IF($S11=MesCiclo,InicioCiclo,$S11+MOD(2-WEEKDAY($S11),7))+6),1,MIN(1,MAX(0,IF(ISNUMBER(OFFSET($A$1,ROW()-1,8)),OFFSET($A$1,ROW()-1,8),0))))) | AE11: =IF($V11<>"Sub","",N($X11)*IF(AND(ISNUMBER($G11),$G11<=IF($S11=MesCiclo,InicioCiclo,$S11+MOD(2-WEEKDAY($S11),7))+13),1,MIN(1,MAX(0,IF(ISNUMBER(OFFSET($A$1,ROW()-1,9)),OFFSET($A$1,ROW()-1,9),IF(ISNUMBER(OFFSET($A$1,ROW()-1,8)),OFFSET($A$1,ROW()-1,8),0)))))) | AF11: =IF($V11<>"Sub","",N($X11)*IF(AND(ISNUMBER($G11),$G11<=IF($S11=MesCiclo,InicioCiclo,$S11+MOD(2-WEEKDAY($S11),7))+20),1,MIN(1,MAX(0,IF(ISNUMBER(OFFSET($A$1,ROW()-1,10)),OFFSET($A$1,ROW()-1,10),IF(ISNUMBER(OFFSET($A$1,ROW()-1,9)),OFFSET($A$1,ROW()-1,9),IF(ISNUMBER(OFFSET($A$1,ROW()-1,8)),OFFSET($A$1,ROW()-1,8),0))))))) | AG11: =IF($V11<>"Sub","",N($X11)*IF(AND(ISNUMBER($G11),$G11<=IF($S11=MesCiclo,InicioCiclo,$S11+MOD(2-WEEKDAY($S11),7))+27),1,MIN(1,MAX(0,IF(ISNUMBER(OFFSET($A$1,ROW()-1,11)),OFFSET($A$1,ROW()-1,11),IF(ISNUMBER(OFFSET($A$1,ROW()-1,10)),OFFSET($A$1,ROW()-1,10),IF(ISNUMBER(OFFSET($A$1,ROW()-1,9)),OFFSET($A$1,ROW()-1,9),IF(ISNUMBER(OFFSET($A$1,ROW()-1,8)),OFFSET($A$1,ROW()-1,8),0)))))))) | AH11: =IF($V11="","",IF(AND(ISNUMBER($G11),$G11<=IF($S11=MesCiclo,InicioCiclo,$S11+MOD(2-WEEKDAY($S11),7))+6),1,IF(N($W11)>0,MIN(1,SUMIFS($AD$5:$AD$1000,$U$5:$U$1000,ROW(),$V$5:$V$1000,"Sub")),$Z11))) | AI11: =IF($V11="","",IF(AND(ISNUMBER($G11),$G11<=IF($S11=MesCiclo,InicioCiclo,$S11+MOD(2-WEEKDAY($S11),7))+13),1,IF(N($W11)>0,MIN(1,SUMIFS($AE$5:$AE$1000,$U$5:$U$1000,ROW(),$V$5:$V$1000,"Sub")),$AA11))) | AJ11: =IF($V11="","",IF(AND(ISNUMBER($G11),$G11<=IF($S11=MesCiclo,InicioCiclo,$S11+MOD(2-WEEKDAY($S11),7))+20),1,IF(N($W11)>0,MIN(1,SUMIFS($AF$5:$AF$1000,$U$5:$U$1000,ROW(),$V$5:$V$1000,"Sub")),$AB11))) | AK11: =IF($V11="","",IF(AND(ISNUMBER($G11),$G11<=IF($S11=MesCiclo,InicioCiclo,$S11+MOD(2-WEEKDAY($S11),7))+27),1,IF(N($W11)>0,MIN(1,SUMIFS($AG$5:$AG$1000,$U$5:$U$1000,ROW(),$V$5:$V$1000,"Sub")),$AC11))) | AL11: =IF($V11<>"Macro","",IF(COUNTIFS($S$5:$S$1000,$S11,$V$5:$V$1000,"Macro",$H$5:$H$1000,">0")=0,1/COUNTIFS($S$5:$S$1000,$S11,$V$5:$V$1000,"Macro"),IF(AND(ISNUMBER($H11),N($H11)>0),$H11,SUMIFS($H$5:$H$1000,$S$5:$S$1000,$S11,$V$5:$V$1000,"Macro")/COUNTIFS($S$5:$S$1000,$S11,$V$5:$V$1000,"Macro",$H$5:$H$1000,">0"))/(COUNTIFS($S$5:$S$1000,$S11,$V$5:$V$1000,"Macro")*SUMIFS($H$5:$H$1000,$S$5:$S$1000,$S11,$V$5:$V$1000,"Macro")/COUNTIFS($S$5:$S$1000,$S11,$V$5:$V$1000,"Macro",$H$5:$H$1000,">0")))) | AM11: =IF(NOT(AND($D11<>"",$V11="Macro")),"",IFERROR(CHOOSE(MATCH($D11,ListaPuestos,0),MATCH("[Jefatura] "&$C11,'Cronograma R. Operacional'!$C$5:$C$1000,0),MATCH("[Jefatura] "&$C11,'Cronograma R. Normativo'!$C$5:$C$1000,0),MATCH("[Jefatura] "&$C11,'Cronograma R. Financiero'!$C$5:$C$1000,0),MATCH("[Jefatura] "&$C11,'Cronograma Asistente Técnico'!$C$5:$C$1000,0)),0)) | AN11: =IF(AND(AND($D11<>"",$V11="Macro"),$S11=MesCiclo),COUNTIFS($D$5:$D11,$D11,$S$5:$S11,MesCiclo,$V$5:$V11,"Macro"),"") | AO11: =IF($AN11="","",$D11&"|"&$AN11) | AP11: =IF(AND($D11<>"",$V11="Macro"),$D11&"|"&$C11,"") | AQ11: ="" | AR11: =IF(N($AQ11)>0,INDEX(rIni_ADM,$AQ11),IF(ISNUMBER($E11),$E11,"")) | AS11: =IF(N($AQ11)>0,INDEX(rLim_ADM,$AQ11),IF(ISNUMBER($F11),$F11,""))
A12: =IF(NOT((COUNTA($B12:$D12)+COUNTA($G12:$H12)+COUNTA($Q12))>0),"",IF($V12="Macro",COUNTIFS($V$5:$V12,"Macro",$S$5:$S12,$S12),IF(N($U12)=0,"?",COUNTIFS(INDEX($V$5:$V$1000,1):INDEX($V$5:$V$1000,$U12-4),"Macro",INDEX($S$5:$S$1000,1):INDEX($S$5:$S$1000,$U12-4),INDEX($S$5:$S$1000,$U12-4))&"."&COUNTIFS($U$5:$U12,$U12,$V$5:$V12,"Sub")))) | I12: =IF(N($W12)=0,"",IF(AND($S12=MesCiclo,1>SemanaActual),"",MIN(1,SUMIFS(OFFSET($A$1,ROW(),29,1000-ROW(),1),OFFSET($A$1,ROW(),20,1000-ROW(),1),ROW(),OFFSET($A$1,ROW(),21,1000-ROW(),1),"Sub")))) | J12: =IF(N($W12)=0,"",IF(AND($S12=MesCiclo,2>SemanaActual),"",MIN(1,SUMIFS(OFFSET($A$1,ROW(),30,1000-ROW(),1),OFFSET($A$1,ROW(),20,1000-ROW(),1),ROW(),OFFSET($A$1,ROW(),21,1000-ROW(),1),"Sub")))) | K12: =IF(N($W12)=0,"",IF(AND($S12=MesCiclo,3>SemanaActual),"",MIN(1,SUMIFS(OFFSET($A$1,ROW(),31,1000-ROW(),1),OFFSET($A$1,ROW(),20,1000-ROW(),1),ROW(),OFFSET($A$1,ROW(),21,1000-ROW(),1),"Sub")))) | L12: =IF(N($W12)=0,"",IF(AND($S12=MesCiclo,4>SemanaActual),"",MIN(1,SUMIFS(OFFSET($A$1,ROW(),32,1000-ROW(),1),OFFSET($A$1,ROW(),20,1000-ROW(),1),ROW(),OFFSET($A$1,ROW(),21,1000-ROW(),1),"Sub")))) | M12: =IF(NOT((COUNTA($B12:$D12)+COUNTA($G12:$H12)+COUNTA($Q12))>0),"",IF(AND($D12<>"",$V12="Macro"),IF(N($AM12)>0,N(CHOOSE(MATCH($D12,ListaPuestos,0),INDEX('Cronograma R. Operacional'!$M$5:$M$1000,$AM12),INDEX('Cronograma R. Normativo'!$M$5:$M$1000,$AM12),INDEX('Cronograma R. Financiero'!$M$5:$M$1000,$AM12),INDEX('Cronograma Asistente Técnico'!$M$5:$M$1000,$AM12))),0),IF(ISNUMBER($G12),1,IF(N($W12)>0,MIN(1,SUMIFS($Y$5:$Y$1000,$U$5:$U$1000,ROW(),$V$5:$V$1000,"Sub")),$Y12)))) | N12: =IF(OR($M12="",$V12="Sub"),"",IF($M12>=1,"Completado",IF($M12>0,"En curso","Pendiente"))) | O12: =IF(NOT((COUNTA($B12:$D12)+COUNTA($G12:$H12)+COUNTA($Q12))>0),"",IF(AND(AND($D12<>"",$V12="Macro"),N($AM12)>0),CHOOSE(MATCH($D12,ListaPuestos,0),INDEX('Cronograma R. Operacional'!$O$5:$O$1000,$AM12),INDEX('Cronograma R. Normativo'!$O$5:$O$1000,$AM12),INDEX('Cronograma R. Financiero'!$O$5:$O$1000,$AM12),INDEX('Cronograma Asistente Técnico'!$O$5:$O$1000,$AM12))&"",IF(ISNUMBER($G12),IF(AND(ISNUMBER($AS12),$G12>$AS12),"Cumplida con "&($G12-$AS12)&IF($G12-$AS12=1," día"," días")&" de retraso","Cumplida"),IF(N($M12)>=1,"Cumplida",IF(NOT(ISNUMBER($AS12)),"Sin fecha límite",IF($AS12<FechaRef,"Vencida hace "&(FechaRef-$AS12)&IF(FechaRef-$AS12=1," día"," días"),IF($AS12=FechaRef,"Vence hoy",IF($AS12-FechaRef<=DiasAlerta,"Vence en "&($AS12-FechaRef)&IF($AS12-FechaRef=1," día"," días"),"En plazo")))))))) | P12: =IF(NOT((COUNTA($B12:$D12)+COUNTA($G12:$H12)+COUNTA($Q12))>0),"",IF($D12="","Propia",IF($V12<>"Macro","Solo se delegan macroactividades",IF(N($AM12)>0,"✔ Recibida por "&$D12,"⚠ "&$D12&" aún no la agrega")))) | R12: =IF(NOT((COUNTA($B12:$D12)+COUNTA($G12:$H12)+COUNTA($Q12))>0),"",IF((IF($C12="","Falta el nombre de la actividad"&" · ","")&IF(AND($V12="Sub",N($U12)=0),"Subactividad sin macroactividad arriba"&" · ","")&IF(AND($V12="Macro",$AR12=""),"Sin fecha de inicio"&" · ","")&IF(AND($V12="Macro",$AS12=""),"Sin fecha límite"&" · ","")&IF(AND(LEFT($C12,11)="[Jefatura] ",N($AQ12)=0),"No se encuentra en la hoja de la jefatura (elíjala de nuevo en la lista)"&" · ","")&IF(OR(AND($E12<>"",NOT(ISNUMBER($E12))),AND($F12<>"",NOT(ISNUMBER($F12))),AND($G12<>"",NOT(ISNUMBER($G12)))),"Fecha no válida"&" · ","")&IF(AND(ISNUMBER($AR12),ISNUMBER($AS12),$AR12>$AS12),"Inicio posterior a fecha límite"&" · ","")&IF(AND($V12="Macro",$H12<>"",OR(NOT(ISNUMBER($H12)),$H12<0,$H12>1)),"Peso fuera de rango"&" · ","")&IF(AND($V12="Sub",$H12<>"",OR(NOT(ISNUMBER($H12)),$H12<0,$H12>1)),"% de la subactividad fuera de rango 0-100%"&" · ","")&IF(AND(N($W12)>0,SUMIFS($H$5:$H$1000,$U$5:$U$1000,ROW(),$V$5:$V$1000,"Sub")>1.0001),"Las subactividades suman más de 100%"&" · ","")&IF(AND(N($W12)>0,OR(IF(ISNUMBER($I12),ROUND($I12,6)<>ROUND(MIN(1,SUMIFS($AD$5:$AD$1000,$U$5:$U$1000,ROW(),$V$5:$V$1000,"Sub")),6),FALSE),IF(ISNUMBER($J12),ROUND($J12,6)<>ROUND(MIN(1,SUMIFS($AE$5:$AE$1000,$U$5:$U$1000,ROW(),$V$5:$V$1000,"Sub")),6),FALSE),IF(ISNUMBER($K12),ROUND($K12,6)<>ROUND(MIN(1,SUMIFS($AF$5:$AF$1000,$U$5:$U$1000,ROW(),$V$5:$V$1000,"Sub")),6),FALSE),IF(ISNUMBER($L12),ROUND($L12,6)<>ROUND(MIN(1,SUMIFS($AG$5:$AG$1000,$U$5:$U$1000,ROW(),$V$5:$V$1000,"Sub")),6),FALSE))),"Con subactividades: no escriba en las semanas (se llenan solas)"&" · ","")&IF((COUNTIF($I12:$L12,">1")+COUNTIF($I12:$L12,"<0")+SUMPRODUCT((LEN($I12:$L12)>0)*NOT(ISNUMBER($I12:$L12))))>0,"Avance fuera de rango 0-100%"&" · ","")&IF(OR(AND(ISNUMBER($J12),$J12<N($I12)),AND(ISNUMBER($K12),$K12<MAX($I12:$J12)),AND(ISNUMBER($L12),$L12<MAX($I12:$K12))),"Avance semanal decreciente"&" · ","")&IF(AND(ISNUMBER($AS12),$AS12<FechaRef,IF($V12="Sub",1,N($M12))<1),"Vencida"&" · ","")&IF(AND(ObsObligatoria="Sí",ISNUMBER($AS12),$AS12<FechaRef,IF($V12="Sub",1,N($M12))<1,$Q12=""),"Vencida sin observación"&" · ",""))="","✔ OK","⚠ "&LEFT(IF($C12="","Falta el nombre de la actividad"&" · ","")&IF(AND($V12="Sub",N($U12)=0),"Subactividad sin macroactividad arriba"&" · ","")&IF(AND($V12="Macro",$AR12=""),"Sin fecha de inicio"&" · ","")&IF(AND($V12="Macro",$AS12=""),"Sin fecha límite"&" · ","")&IF(AND(LEFT($C12,11)="[Jefatura] ",N($AQ12)=0),"No se encuentra en la hoja de la jefatura (elíjala de nuevo en la lista)"&" · ","")&IF(OR(AND($E12<>"",NOT(ISNUMBER($E12))),AND($F12<>"",NOT(ISNUMBER($F12))),AND($G12<>"",NOT(ISNUMBER($G12)))),"Fecha no válida"&" · ","")&IF(AND(ISNUMBER($AR12),ISNUMBER($AS12),$AR12>$AS12),"Inicio posterior a fecha límite"&" · ","")&IF(AND($V12="Macro",$H12<>"",OR(NOT(ISNUMBER($H12)),$H12<0,$H12>1)),"Peso fuera de rango"&" · ","")&IF(AND($V12="Sub",$H12<>"",OR(NOT(ISNUMBER($H12)),$H12<0,$H12>1)),"% de la subactividad fuera de rango 0-100%"&" · ","")&IF(AND(N($W12)>0,SUMIFS($H$5:$H$1000,$U$5:$U$1000,ROW(),$V$5:$V$1000,"Sub")>1.0001),"Las subactividades suman más de 100%"&" · ","")&IF(AND(N($W12)>0,OR(IF(ISNUMBER($I12),ROUND($I12,6)<>ROUND(MIN(1,SUMIFS($AD$5:$AD$1000,$U$5:$U$1000,ROW(),$V$5:$V$1000,"Sub")),6),FALSE),IF(ISNUMBER($J12),ROUND($J12,6)<>ROUND(MIN(1,SUMIFS($AE$5:$AE$1000,$U$5:$U$1000,ROW(),$V$5:$V$1000,"Sub")),6),FALSE),IF(ISNUMBER($K12),ROUND($K12,6)<>ROUND(MIN(1,SUMIFS($AF$5:$AF$1000,$U$5:$U$1000,ROW(),$V$5:$V$1000,"Sub")),6),FALSE),IF(ISNUMBER($L12),ROUND($L12,6)<>ROUND(MIN(1,SUMIFS($AG$5:$AG$1000,$U$5:$U$1000,ROW(),$V$5:$V$1000,"Sub")),6),FALSE))),"Con subactividades: no escriba en las semanas (se llenan solas)"&" · ","")&IF((COUNTIF($I12:$L12,">1")+COUNTIF($I12:$L12,"<0")+SUMPRODUCT((LEN($I12:$L12)>0)*NOT(ISNUMBER($I12:$L12))))>0,"Avance fuera de rango 0-100%"&" · ","")&IF(OR(AND(ISNUMBER($J12),$J12<N($I12)),AND(ISNUMBER($K12),$K12<MAX($I12:$J12)),AND(ISNUMBER($L12),$L12<MAX($I12:$K12))),"Avance semanal decreciente"&" · ","")&IF(AND(ISNUMBER($AS12),$AS12<FechaRef,IF($V12="Sub",1,N($M12))<1),"Vencida"&" · ","")&IF(AND(ObsObligatoria="Sí",ISNUMBER($AS12),$AS12<FechaRef,IF($V12="Sub",1,N($M12))<1,$Q12=""),"Vencida sin observación"&" · ",""),LEN(IF($C12="","Falta el nombre de la actividad"&" · ","")&IF(AND($V12="Sub",N($U12)=0),"Subactividad sin macroactividad arriba"&" · ","")&IF(AND($V12="Macro",$AR12=""),"Sin fecha de inicio"&" · ","")&IF(AND($V12="Macro",$AS12=""),"Sin fecha límite"&" · ","")&IF(AND(LEFT($C12,11)="[Jefatura] ",N($AQ12)=0),"No se encuentra en la hoja de la jefatura (elíjala de nuevo en la lista)"&" · ","")&IF(OR(AND($E12<>"",NOT(ISNUMBER($E12))),AND($F12<>"",NOT(ISNUMBER($F12))),AND($G12<>"",NOT(ISNUMBER($G12)))),"Fecha no válida"&" · ","")&IF(AND(ISNUMBER($AR12),ISNUMBER($AS12),$AR12>$AS12),"Inicio posterior a fecha límite"&" · ","")&IF(AND($V12="Macro",$H12<>"",OR(NOT(ISNUMBER($H12)),$H12<0,$H12>1)),"Peso fuera de rango"&" · ","")&IF(AND($V12="Sub",$H12<>"",OR(NOT(ISNUMBER($H12)),$H12<0,$H12>1)),"% de la subactividad fuera de rango 0-100%"&" · ","")&IF(AND(N($W12)>0,SUMIFS($H$5:$H$1000,$U$5:$U$1000,ROW(),$V$5:$V$1000,"Sub")>1.0001),"Las subactividades suman más de 100%"&" · ","")&IF(AND(N($W12)>0,OR(IF(ISNUMBER($I12),ROUND($I12,6)<>ROUND(MIN(1,SUMIFS($AD$5:$AD$1000,$U$5:$U$1000,ROW(),$V$5:$V$1000,"Sub")),6),FALSE),IF(ISNUMBER($J12),ROUND($J12,6)<>ROUND(MIN(1,SUMIFS($AE$5:$AE$1000,$U$5:$U$1000,ROW(),$V$5:$V$1000,"Sub")),6),FALSE),IF(ISNUMBER($K12),ROUND($K12,6)<>ROUND(MIN(1,SUMIFS($AF$5:$AF$1000,$U$5:$U$1000,ROW(),$V$5:$V$1000,"Sub")),6),FALSE),IF(ISNUMBER($L12),ROUND($L12,6)<>ROUND(MIN(1,SUMIFS($AG$5:$AG$1000,$U$5:$U$1000,ROW(),$V$5:$V$1000,"Sub")),6),FALSE))),"Con subactividades: no escriba en las semanas (se llenan solas)"&" · ","")&IF((COUNTIF($I12:$L12,">1")+COUNTIF($I12:$L12,"<0")+SUMPRODUCT((LEN($I12:$L12)>0)*NOT(ISNUMBER($I12:$L12))))>0,"Avance fuera de rango 0-100%"&" · ","")&IF(OR(AND(ISNUMBER($J12),$J12<N($I12)),AND(ISNUMBER($K12),$K12<MAX($I12:$J12)),AND(ISNUMBER($L12),$L12<MAX($I12:$K12))),"Avance semanal decreciente"&" · ","")&IF(AND(ISNUMBER($AS12),$AS12<FechaRef,IF($V12="Sub",1,N($M12))<1),"Vencida"&" · ","")&IF(AND(ObsObligatoria="Sí",ISNUMBER($AS12),$AS12<FechaRef,IF($V12="Sub",1,N($M12))<1,$Q12=""),"Vencida sin observación"&" · ",""))-3))) | S12: =IF(NOT((COUNTA($B12:$D12)+COUNTA($G12:$H12)+COUNTA($Q12))>0),"",IF(AND($V12="Sub",N($U12)>0),IF(ISNUMBER(INDEX($AR$5:$AR$1000,$U12-4)),DATE(YEAR(INDEX($AR$5:$AR$1000,$U12-4)),MONTH(INDEX($AR$5:$AR$1000,$U12-4)),1),IF(ISNUMBER(INDEX($AS$5:$AS$1000,$U12-4)),DATE(YEAR(INDEX($AS$5:$AS$1000,$U12-4)),MONTH(INDEX($AS$5:$AS$1000,$U12-4)),1),MesCiclo)),IF(ISNUMBER($AR12),DATE(YEAR($AR12),MONTH($AR12),1),IF(ISNUMBER($AS12),DATE(YEAR($AS12),MONTH($AS12),1),MesCiclo)))) | T12: =IF(OR($S12="",$S12<>MesCiclo,$V12<>"Macro"),"",COUNTIFS($S$5:$S12,MesCiclo,$V$5:$V12,"Macro")) | U12: =IF($V12="","",IF($V12="Macro",ROW(),IFERROR(LOOKUP(2,1/($V$5:$V12="Macro"),ROW($V$5:$V12)),0))) | V12: =IF(NOT((COUNTA($B12:$D12)+COUNTA($G12:$H12)+COUNTA($Q12))>0),"",IF($B12="Subactividad","Sub","Macro")) | W12: =IF($V12="Macro",COUNTIFS($U$5:$U$1000,ROW(),$V$5:$V$1000,"Sub"),"") | X12: =IF($V12<>"Sub","",IF(AND(ISNUMBER($H12),N($H12)>0),$H12,IFERROR(MAX(0,1-SUMIFS($H$5:$H$1000,$U$5:$U$1000,$U12,$V$5:$V$1000,"Sub"))/(COUNTIFS($U$5:$U$1000,$U12,$V$5:$V$1000,"Sub")-COUNTIFS($U$5:$U$1000,$U12,$V$5:$V$1000,"Sub",$H$5:$H$1000,">0")),0))) | Y12: =IF($V12="","",IF($V12="Sub",N($X12)*IF(ISNUMBER($G12),1,MIN(1,MAX(0,IFERROR(LOOKUP(2,1/ISNUMBER($I12:$L12),$I12:$L12),0)))),IF(ISNUMBER($G12),1,IFERROR(LOOKUP(2,1/($I12:$L12<>""),$I12:$L12),0)))) | Z12: =IF($V12="","",IF(AND(ISNUMBER($G12),$G12<=IF($S12=MesCiclo,InicioCiclo,$S12+MOD(2-WEEKDAY($S12),7))+6),1,IF(ISNUMBER($I12),$I12,0))) | AA12: =IF($V12="","",IF(AND(ISNUMBER($G12),$G12<=IF($S12=MesCiclo,InicioCiclo,$S12+MOD(2-WEEKDAY($S12),7))+13),1,IF(ISNUMBER($J12),$J12,$Z12))) | AB12: =IF($V12="","",IF(AND(ISNUMBER($G12),$G12<=IF($S12=MesCiclo,InicioCiclo,$S12+MOD(2-WEEKDAY($S12),7))+20),1,IF(ISNUMBER($K12),$K12,$AA12))) | AC12: =IF($V12="","",IF(AND(ISNUMBER($G12),$G12<=IF($S12=MesCiclo,InicioCiclo,$S12+MOD(2-WEEKDAY($S12),7))+27),1,IF(ISNUMBER($L12),$L12,$AB12))) | AD12: =IF($V12<>"Sub","",N($X12)*IF(AND(ISNUMBER($G12),$G12<=IF($S12=MesCiclo,InicioCiclo,$S12+MOD(2-WEEKDAY($S12),7))+6),1,MIN(1,MAX(0,IF(ISNUMBER(OFFSET($A$1,ROW()-1,8)),OFFSET($A$1,ROW()-1,8),0))))) | AE12: =IF($V12<>"Sub","",N($X12)*IF(AND(ISNUMBER($G12),$G12<=IF($S12=MesCiclo,InicioCiclo,$S12+MOD(2-WEEKDAY($S12),7))+13),1,MIN(1,MAX(0,IF(ISNUMBER(OFFSET($A$1,ROW()-1,9)),OFFSET($A$1,ROW()-1,9),IF(ISNUMBER(OFFSET($A$1,ROW()-1,8)),OFFSET($A$1,ROW()-1,8),0)))))) | AF12: =IF($V12<>"Sub","",N($X12)*IF(AND(ISNUMBER($G12),$G12<=IF($S12=MesCiclo,InicioCiclo,$S12+MOD(2-WEEKDAY($S12),7))+20),1,MIN(1,MAX(0,IF(ISNUMBER(OFFSET($A$1,ROW()-1,10)),OFFSET($A$1,ROW()-1,10),IF(ISNUMBER(OFFSET($A$1,ROW()-1,9)),OFFSET($A$1,ROW()-1,9),IF(ISNUMBER(OFFSET($A$1,ROW()-1,8)),OFFSET($A$1,ROW()-1,8),0))))))) | AG12: =IF($V12<>"Sub","",N($X12)*IF(AND(ISNUMBER($G12),$G12<=IF($S12=MesCiclo,InicioCiclo,$S12+MOD(2-WEEKDAY($S12),7))+27),1,MIN(1,MAX(0,IF(ISNUMBER(OFFSET($A$1,ROW()-1,11)),OFFSET($A$1,ROW()-1,11),IF(ISNUMBER(OFFSET($A$1,ROW()-1,10)),OFFSET($A$1,ROW()-1,10),IF(ISNUMBER(OFFSET($A$1,ROW()-1,9)),OFFSET($A$1,ROW()-1,9),IF(ISNUMBER(OFFSET($A$1,ROW()-1,8)),OFFSET($A$1,ROW()-1,8),0)))))))) | AH12: =IF($V12="","",IF(AND(ISNUMBER($G12),$G12<=IF($S12=MesCiclo,InicioCiclo,$S12+MOD(2-WEEKDAY($S12),7))+6),1,IF(N($W12)>0,MIN(1,SUMIFS($AD$5:$AD$1000,$U$5:$U$1000,ROW(),$V$5:$V$1000,"Sub")),$Z12))) | AI12: =IF($V12="","",IF(AND(ISNUMBER($G12),$G12<=IF($S12=MesCiclo,InicioCiclo,$S12+MOD(2-WEEKDAY($S12),7))+13),1,IF(N($W12)>0,MIN(1,SUMIFS($AE$5:$AE$1000,$U$5:$U$1000,ROW(),$V$5:$V$1000,"Sub")),$AA12))) | AJ12: =IF($V12="","",IF(AND(ISNUMBER($G12),$G12<=IF($S12=MesCiclo,InicioCiclo,$S12+MOD(2-WEEKDAY($S12),7))+20),1,IF(N($W12)>0,MIN(1,SUMIFS($AF$5:$AF$1000,$U$5:$U$1000,ROW(),$V$5:$V$1000,"Sub")),$AB12))) | AK12: =IF($V12="","",IF(AND(ISNUMBER($G12),$G12<=IF($S12=MesCiclo,InicioCiclo,$S12+MOD(2-WEEKDAY($S12),7))+27),1,IF(N($W12)>0,MIN(1,SUMIFS($AG$5:$AG$1000,$U$5:$U$1000,ROW(),$V$5:$V$1000,"Sub")),$AC12))) | AL12: =IF($V12<>"Macro","",IF(COUNTIFS($S$5:$S$1000,$S12,$V$5:$V$1000,"Macro",$H$5:$H$1000,">0")=0,1/COUNTIFS($S$5:$S$1000,$S12,$V$5:$V$1000,"Macro"),IF(AND(ISNUMBER($H12),N($H12)>0),$H12,SUMIFS($H$5:$H$1000,$S$5:$S$1000,$S12,$V$5:$V$1000,"Macro")/COUNTIFS($S$5:$S$1000,$S12,$V$5:$V$1000,"Macro",$H$5:$H$1000,">0"))/(COUNTIFS($S$5:$S$1000,$S12,$V$5:$V$1000,"Macro")*SUMIFS($H$5:$H$1000,$S$5:$S$1000,$S12,$V$5:$V$1000,"Macro")/COUNTIFS($S$5:$S$1000,$S12,$V$5:$V$1000,"Macro",$H$5:$H$1000,">0")))) | AM12: =IF(NOT(AND($D12<>"",$V12="Macro")),"",IFERROR(CHOOSE(MATCH($D12,ListaPuestos,0),MATCH("[Jefatura] "&$C12,'Cronograma R. Operacional'!$C$5:$C$1000,0),MATCH("[Jefatura] "&$C12,'Cronograma R. Normativo'!$C$5:$C$1000,0),MATCH("[Jefatura] "&$C12,'Cronograma R. Financiero'!$C$5:$C$1000,0),MATCH("[Jefatura] "&$C12,'Cronograma Asistente Técnico'!$C$5:$C$1000,0)),0)) | AN12: =IF(AND(AND($D12<>"",$V12="Macro"),$S12=MesCiclo),COUNTIFS($D$5:$D12,$D12,$S$5:$S12,MesCiclo,$V$5:$V12,"Macro"),"") | AO12: =IF($AN12="","",$D12&"|"&$AN12) | AP12: =IF(AND($D12<>"",$V12="Macro"),$D12&"|"&$C12,"") | AQ12: ="" | AR12: =IF(N($AQ12)>0,INDEX(rIni_ADM,$AQ12),IF(ISNUMBER($E12),$E12,"")) | AS12: =IF(N($AQ12)>0,INDEX(rLim_ADM,$AQ12),IF(ISNUMBER($F12),$F12,""))
A13: =IF(NOT((COUNTA($B13:$D13)+COUNTA($G13:$H13)+COUNTA($Q13))>0),"",IF($V13="Macro",COUNTIFS($V$5:$V13,"Macro",$S$5:$S13,$S13),IF(N($U13)=0,"?",COUNTIFS(INDEX($V$5:$V$1000,1):INDEX($V$5:$V$1000,$U13-4),"Macro",INDEX($S$5:$S$1000,1):INDEX($S$5:$S$1000,$U13-4),INDEX($S$5:$S$1000,$U13-4))&"."&COUNTIFS($U$5:$U13,$U13,$V$5:$V13,"Sub")))) | I13: =IF(N($W13)=0,"",IF(AND($S13=MesCiclo,1>SemanaActual),"",MIN(1,SUMIFS(OFFSET($A$1,ROW(),29,1000-ROW(),1),OFFSET($A$1,ROW(),20,1000-ROW(),1),ROW(),OFFSET($A$1,ROW(),21,1000-ROW(),1),"Sub")))) | J13: =IF(N($W13)=0,"",IF(AND($S13=MesCiclo,2>SemanaActual),"",MIN(1,SUMIFS(OFFSET($A$1,ROW(),30,1000-ROW(),1),OFFSET($A$1,ROW(),20,1000-ROW(),1),ROW(),OFFSET($A$1,ROW(),21,1000-ROW(),1),"Sub")))) | K13: =IF(N($W13)=0,"",IF(AND($S13=MesCiclo,3>SemanaActual),"",MIN(1,SUMIFS(OFFSET($A$1,ROW(),31,1000-ROW(),1),OFFSET($A$1,ROW(),20,1000-ROW(),1),ROW(),OFFSET($A$1,ROW(),21,1000-ROW(),1),"Sub")))) | L13: =IF(N($W13)=0,"",IF(AND($S13=MesCiclo,4>SemanaActual),"",MIN(1,SUMIFS(OFFSET($A$1,ROW(),32,1000-ROW(),1),OFFSET($A$1,ROW(),20,1000-ROW(),1),ROW(),OFFSET($A$1,ROW(),21,1000-ROW(),1),"Sub")))) | M13: =IF(NOT((COUNTA($B13:$D13)+COUNTA($G13:$H13)+COUNTA($Q13))>0),"",IF(AND($D13<>"",$V13="Macro"),IF(N($AM13)>0,N(CHOOSE(MATCH($D13,ListaPuestos,0),INDEX('Cronograma R. Operacional'!$M$5:$M$1000,$AM13),INDEX('Cronograma R. Normativo'!$M$5:$M$1000,$AM13),INDEX('Cronograma R. Financiero'!$M$5:$M$1000,$AM13),INDEX('Cronograma Asistente Técnico'!$M$5:$M$1000,$AM13))),0),IF(ISNUMBER($G13),1,IF(N($W13)>0,MIN(1,SUMIFS($Y$5:$Y$1000,$U$5:$U$1000,ROW(),$V$5:$V$1000,"Sub")),$Y13)))) | N13: =IF(OR($M13="",$V13="Sub"),"",IF($M13>=1,"Completado",IF($M13>0,"En curso","Pendiente"))) | O13: =IF(NOT((COUNTA($B13:$D13)+COUNTA($G13:$H13)+COUNTA($Q13))>0),"",IF(AND(AND($D13<>"",$V13="Macro"),N($AM13)>0),CHOOSE(MATCH($D13,ListaPuestos,0),INDEX('Cronograma R. Operacional'!$O$5:$O$1000,$AM13),INDEX('Cronograma R. Normativo'!$O$5:$O$1000,$AM13),INDEX('Cronograma R. Financiero'!$O$5:$O$1000,$AM13),INDEX('Cronograma Asistente Técnico'!$O$5:$O$1000,$AM13))&"",IF(ISNUMBER($G13),IF(AND(ISNUMBER($AS13),$G13>$AS13),"Cumplida con "&($G13-$AS13)&IF($G13-$AS13=1," día"," días")&" de retraso","Cumplida"),IF(N($M13)>=1,"Cumplida",IF(NOT(ISNUMBER($AS13)),"Sin fecha límite",IF($AS13<FechaRef,"Vencida hace "&(FechaRef-$AS13)&IF(FechaRef-$AS13=1," día"," días"),IF($AS13=FechaRef,"Vence hoy",IF($AS13-FechaRef<=DiasAlerta,"Vence en "&($AS13-FechaRef)&IF($AS13-FechaRef=1," día"," días"),"En plazo")))))))) | P13: =IF(NOT((COUNTA($B13:$D13)+COUNTA($G13:$H13)+COUNTA($Q13))>0),"",IF($D13="","Propia",IF($V13<>"Macro","Solo se delegan macroactividades",IF(N($AM13)>0,"✔ Recibida por "&$D13,"⚠ "&$D13&" aún no la agrega")))) | R13: =IF(NOT((COUNTA($B13:$D13)+COUNTA($G13:$H13)+COUNTA($Q13))>0),"",IF((IF($C13="","Falta el nombre de la actividad"&" · ","")&IF(AND($V13="Sub",N($U13)=0),"Subactividad sin macroactividad arriba"&" · ","")&IF(AND($V13="Macro",$AR13=""),"Sin fecha de inicio"&" · ","")&IF(AND($V13="Macro",$AS13=""),"Sin fecha límite"&" · ","")&IF(AND(LEFT($C13,11)="[Jefatura] ",N($AQ13)=0),"No se encuentra en la hoja de la jefatura (elíjala de nuevo en la lista)"&" · ","")&IF(OR(AND($E13<>"",NOT(ISNUMBER($E13))),AND($F13<>"",NOT(ISNUMBER($F13))),AND($G13<>"",NOT(ISNUMBER($G13)))),"Fecha no válida"&" · ","")&IF(AND(ISNUMBER($AR13),ISNUMBER($AS13),$AR13>$AS13),"Inicio posterior a fecha límite"&" · ","")&IF(AND($V13="Macro",$H13<>"",OR(NOT(ISNUMBER($H13)),$H13<0,$H13>1)),"Peso fuera de rango"&" · ","")&IF(AND($V13="Sub",$H13<>"",OR(NOT(ISNUMBER($H13)),$H13<0,$H13>1)),"% de la subactividad fuera de rango 0-100%"&" · ","")&IF(AND(N($W13)>0,SUMIFS($H$5:$H$1000,$U$5:$U$1000,ROW(),$V$5:$V$1000,"Sub")>1.0001),"Las subactividades suman más de 100%"&" · ","")&IF(AND(N($W13)>0,OR(IF(ISNUMBER($I13),ROUND($I13,6)<>ROUND(MIN(1,SUMIFS($AD$5:$AD$1000,$U$5:$U$1000,ROW(),$V$5:$V$1000,"Sub")),6),FALSE),IF(ISNUMBER($J13),ROUND($J13,6)<>ROUND(MIN(1,SUMIFS($AE$5:$AE$1000,$U$5:$U$1000,ROW(),$V$5:$V$1000,"Sub")),6),FALSE),IF(ISNUMBER($K13),ROUND($K13,6)<>ROUND(MIN(1,SUMIFS($AF$5:$AF$1000,$U$5:$U$1000,ROW(),$V$5:$V$1000,"Sub")),6),FALSE),IF(ISNUMBER($L13),ROUND($L13,6)<>ROUND(MIN(1,SUMIFS($AG$5:$AG$1000,$U$5:$U$1000,ROW(),$V$5:$V$1000,"Sub")),6),FALSE))),"Con subactividades: no escriba en las semanas (se llenan solas)"&" · ","")&IF((COUNTIF($I13:$L13,">1")+COUNTIF($I13:$L13,"<0")+SUMPRODUCT((LEN($I13:$L13)>0)*NOT(ISNUMBER($I13:$L13))))>0,"Avance fuera de rango 0-100%"&" · ","")&IF(OR(AND(ISNUMBER($J13),$J13<N($I13)),AND(ISNUMBER($K13),$K13<MAX($I13:$J13)),AND(ISNUMBER($L13),$L13<MAX($I13:$K13))),"Avance semanal decreciente"&" · ","")&IF(AND(ISNUMBER($AS13),$AS13<FechaRef,IF($V13="Sub",1,N($M13))<1),"Vencida"&" · ","")&IF(AND(ObsObligatoria="Sí",ISNUMBER($AS13),$AS13<FechaRef,IF($V13="Sub",1,N($M13))<1,$Q13=""),"Vencida sin observación"&" · ",""))="","✔ OK","⚠ "&LEFT(IF($C13="","Falta el nombre de la actividad"&" · ","")&IF(AND($V13="Sub",N($U13)=0),"Subactividad sin macroactividad arriba"&" · ","")&IF(AND($V13="Macro",$AR13=""),"Sin fecha de inicio"&" · ","")&IF(AND($V13="Macro",$AS13=""),"Sin fecha límite"&" · ","")&IF(AND(LEFT($C13,11)="[Jefatura] ",N($AQ13)=0),"No se encuentra en la hoja de la jefatura (elíjala de nuevo en la lista)"&" · ","")&IF(OR(AND($E13<>"",NOT(ISNUMBER($E13))),AND($F13<>"",NOT(ISNUMBER($F13))),AND($G13<>"",NOT(ISNUMBER($G13)))),"Fecha no válida"&" · ","")&IF(AND(ISNUMBER($AR13),ISNUMBER($AS13),$AR13>$AS13),"Inicio posterior a fecha límite"&" · ","")&IF(AND($V13="Macro",$H13<>"",OR(NOT(ISNUMBER($H13)),$H13<0,$H13>1)),"Peso fuera de rango"&" · ","")&IF(AND($V13="Sub",$H13<>"",OR(NOT(ISNUMBER($H13)),$H13<0,$H13>1)),"% de la subactividad fuera de rango 0-100%"&" · ","")&IF(AND(N($W13)>0,SUMIFS($H$5:$H$1000,$U$5:$U$1000,ROW(),$V$5:$V$1000,"Sub")>1.0001),"Las subactividades suman más de 100%"&" · ","")&IF(AND(N($W13)>0,OR(IF(ISNUMBER($I13),ROUND($I13,6)<>ROUND(MIN(1,SUMIFS($AD$5:$AD$1000,$U$5:$U$1000,ROW(),$V$5:$V$1000,"Sub")),6),FALSE),IF(ISNUMBER($J13),ROUND($J13,6)<>ROUND(MIN(1,SUMIFS($AE$5:$AE$1000,$U$5:$U$1000,ROW(),$V$5:$V$1000,"Sub")),6),FALSE),IF(ISNUMBER($K13),ROUND($K13,6)<>ROUND(MIN(1,SUMIFS($AF$5:$AF$1000,$U$5:$U$1000,ROW(),$V$5:$V$1000,"Sub")),6),FALSE),IF(ISNUMBER($L13),ROUND($L13,6)<>ROUND(MIN(1,SUMIFS($AG$5:$AG$1000,$U$5:$U$1000,ROW(),$V$5:$V$1000,"Sub")),6),FALSE))),"Con subactividades: no escriba en las semanas (se llenan solas)"&" · ","")&IF((COUNTIF($I13:$L13,">1")+COUNTIF($I13:$L13,"<0")+SUMPRODUCT((LEN($I13:$L13)>0)*NOT(ISNUMBER($I13:$L13))))>0,"Avance fuera de rango 0-100%"&" · ","")&IF(OR(AND(ISNUMBER($J13),$J13<N($I13)),AND(ISNUMBER($K13),$K13<MAX($I13:$J13)),AND(ISNUMBER($L13),$L13<MAX($I13:$K13))),"Avance semanal decreciente"&" · ","")&IF(AND(ISNUMBER($AS13),$AS13<FechaRef,IF($V13="Sub",1,N($M13))<1),"Vencida"&" · ","")&IF(AND(ObsObligatoria="Sí",ISNUMBER($AS13),$AS13<FechaRef,IF($V13="Sub",1,N($M13))<1,$Q13=""),"Vencida sin observación"&" · ",""),LEN(IF($C13="","Falta el nombre de la actividad"&" · ","")&IF(AND($V13="Sub",N($U13)=0),"Subactividad sin macroactividad arriba"&" · ","")&IF(AND($V13="Macro",$AR13=""),"Sin fecha de inicio"&" · ","")&IF(AND($V13="Macro",$AS13=""),"Sin fecha límite"&" · ","")&IF(AND(LEFT($C13,11)="[Jefatura] ",N($AQ13)=0),"No se encuentra en la hoja de la jefatura (elíjala de nuevo en la lista)"&" · ","")&IF(OR(AND($E13<>"",NOT(ISNUMBER($E13))),AND($F13<>"",NOT(ISNUMBER($F13))),AND($G13<>"",NOT(ISNUMBER($G13)))),"Fecha no válida"&" · ","")&IF(AND(ISNUMBER($AR13),ISNUMBER($AS13),$AR13>$AS13),"Inicio posterior a fecha límite"&" · ","")&IF(AND($V13="Macro",$H13<>"",OR(NOT(ISNUMBER($H13)),$H13<0,$H13>1)),"Peso fuera de rango"&" · ","")&IF(AND($V13="Sub",$H13<>"",OR(NOT(ISNUMBER($H13)),$H13<0,$H13>1)),"% de la subactividad fuera de rango 0-100%"&" · ","")&IF(AND(N($W13)>0,SUMIFS($H$5:$H$1000,$U$5:$U$1000,ROW(),$V$5:$V$1000,"Sub")>1.0001),"Las subactividades suman más de 100%"&" · ","")&IF(AND(N($W13)>0,OR(IF(ISNUMBER($I13),ROUND($I13,6)<>ROUND(MIN(1,SUMIFS($AD$5:$AD$1000,$U$5:$U$1000,ROW(),$V$5:$V$1000,"Sub")),6),FALSE),IF(ISNUMBER($J13),ROUND($J13,6)<>ROUND(MIN(1,SUMIFS($AE$5:$AE$1000,$U$5:$U$1000,ROW(),$V$5:$V$1000,"Sub")),6),FALSE),IF(ISNUMBER($K13),ROUND($K13,6)<>ROUND(MIN(1,SUMIFS($AF$5:$AF$1000,$U$5:$U$1000,ROW(),$V$5:$V$1000,"Sub")),6),FALSE),IF(ISNUMBER($L13),ROUND($L13,6)<>ROUND(MIN(1,SUMIFS($AG$5:$AG$1000,$U$5:$U$1000,ROW(),$V$5:$V$1000,"Sub")),6),FALSE))),"Con subactividades: no escriba en las semanas (se llenan solas)"&" · ","")&IF((COUNTIF($I13:$L13,">1")+COUNTIF($I13:$L13,"<0")+SUMPRODUCT((LEN($I13:$L13)>0)*NOT(ISNUMBER($I13:$L13))))>0,"Avance fuera de rango 0-100%"&" · ","")&IF(OR(AND(ISNUMBER($J13),$J13<N($I13)),AND(ISNUMBER($K13),$K13<MAX($I13:$J13)),AND(ISNUMBER($L13),$L13<MAX($I13:$K13))),"Avance semanal decreciente"&" · ","")&IF(AND(ISNUMBER($AS13),$AS13<FechaRef,IF($V13="Sub",1,N($M13))<1),"Vencida"&" · ","")&IF(AND(ObsObligatoria="Sí",ISNUMBER($AS13),$AS13<FechaRef,IF($V13="Sub",1,N($M13))<1,$Q13=""),"Vencida sin observación"&" · ",""))-3))) | S13: =IF(NOT((COUNTA($B13:$D13)+COUNTA($G13:$H13)+COUNTA($Q13))>0),"",IF(AND($V13="Sub",N($U13)>0),IF(ISNUMBER(INDEX($AR$5:$AR$1000,$U13-4)),DATE(YEAR(INDEX($AR$5:$AR$1000,$U13-4)),MONTH(INDEX($AR$5:$AR$1000,$U13-4)),1),IF(ISNUMBER(INDEX($AS$5:$AS$1000,$U13-4)),DATE(YEAR(INDEX($AS$5:$AS$1000,$U13-4)),MONTH(INDEX($AS$5:$AS$1000,$U13-4)),1),MesCiclo)),IF(ISNUMBER($AR13),DATE(YEAR($AR13),MONTH($AR13),1),IF(ISNUMBER($AS13),DATE(YEAR($AS13),MONTH($AS13),1),MesCiclo)))) | T13: =IF(OR($S13="",$S13<>MesCiclo,$V13<>"Macro"),"",COUNTIFS($S$5:$S13,MesCiclo,$V$5:$V13,"Macro")) | U13: =IF($V13="","",IF($V13="Macro",ROW(),IFERROR(LOOKUP(2,1/($V$5:$V13="Macro"),ROW($V$5:$V13)),0))) | V13: =IF(NOT((COUNTA($B13:$D13)+COUNTA($G13:$H13)+COUNTA($Q13))>0),"",IF($B13="Subactividad","Sub","Macro")) | W13: =IF($V13="Macro",COUNTIFS($U$5:$U$1000,ROW(),$V$5:$V$1000,"Sub"),"") | X13: =IF($V13<>"Sub","",IF(AND(ISNUMBER($H13),N($H13)>0),$H13,IFERROR(MAX(0,1-SUMIFS($H$5:$H$1000,$U$5:$U$1000,$U13,$V$5:$V$1000,"Sub"))/(COUNTIFS($U$5:$U$1000,$U13,$V$5:$V$1000,"Sub")-COUNTIFS($U$5:$U$1000,$U13,$V$5:$V$1000,"Sub",$H$5:$H$1000,">0")),0))) | Y13: =IF($V13="","",IF($V13="Sub",N($X13)*IF(ISNUMBER($G13),1,MIN(1,MAX(0,IFERROR(LOOKUP(2,1/ISNUMBER($I13:$L13),$I13:$L13),0)))),IF(ISNUMBER($G13),1,IFERROR(LOOKUP(2,1/($I13:$L13<>""),$I13:$L13),0)))) | Z13: =IF($V13="","",IF(AND(ISNUMBER($G13),$G13<=IF($S13=MesCiclo,InicioCiclo,$S13+MOD(2-WEEKDAY($S13),7))+6),1,IF(ISNUMBER($I13),$I13,0))) | AA13: =IF($V13="","",IF(AND(ISNUMBER($G13),$G13<=IF($S13=MesCiclo,InicioCiclo,$S13+MOD(2-WEEKDAY($S13),7))+13),1,IF(ISNUMBER($J13),$J13,$Z13))) | AB13: =IF($V13="","",IF(AND(ISNUMBER($G13),$G13<=IF($S13=MesCiclo,InicioCiclo,$S13+MOD(2-WEEKDAY($S13),7))+20),1,IF(ISNUMBER($K13),$K13,$AA13))) | AC13: =IF($V13="","",IF(AND(ISNUMBER($G13),$G13<=IF($S13=MesCiclo,InicioCiclo,$S13+MOD(2-WEEKDAY($S13),7))+27),1,IF(ISNUMBER($L13),$L13,$AB13))) | AD13: =IF($V13<>"Sub","",N($X13)*IF(AND(ISNUMBER($G13),$G13<=IF($S13=MesCiclo,InicioCiclo,$S13+MOD(2-WEEKDAY($S13),7))+6),1,MIN(1,MAX(0,IF(ISNUMBER(OFFSET($A$1,ROW()-1,8)),OFFSET($A$1,ROW()-1,8),0))))) | AE13: =IF($V13<>"Sub","",N($X13)*IF(AND(ISNUMBER($G13),$G13<=IF($S13=MesCiclo,InicioCiclo,$S13+MOD(2-WEEKDAY($S13),7))+13),1,MIN(1,MAX(0,IF(ISNUMBER(OFFSET($A$1,ROW()-1,9)),OFFSET($A$1,ROW()-1,9),IF(ISNUMBER(OFFSET($A$1,ROW()-1,8)),OFFSET($A$1,ROW()-1,8),0)))))) | AF13: =IF($V13<>"Sub","",N($X13)*IF(AND(ISNUMBER($G13),$G13<=IF($S13=MesCiclo,InicioCiclo,$S13+MOD(2-WEEKDAY($S13),7))+20),1,MIN(1,MAX(0,IF(ISNUMBER(OFFSET($A$1,ROW()-1,10)),OFFSET($A$1,ROW()-1,10),IF(ISNUMBER(OFFSET($A$1,ROW()-1,9)),OFFSET($A$1,ROW()-1,9),IF(ISNUMBER(OFFSET($A$1,ROW()-1,8)),OFFSET($A$1,ROW()-1,8),0))))))) | AG13: =IF($V13<>"Sub","",N($X13)*IF(AND(ISNUMBER($G13),$G13<=IF($S13=MesCiclo,InicioCiclo,$S13+MOD(2-WEEKDAY($S13),7))+27),1,MIN(1,MAX(0,IF(ISNUMBER(OFFSET($A$1,ROW()-1,11)),OFFSET($A$1,ROW()-1,11),IF(ISNUMBER(OFFSET($A$1,ROW()-1,10)),OFFSET($A$1,ROW()-1,10),IF(ISNUMBER(OFFSET($A$1,ROW()-1,9)),OFFSET($A$1,ROW()-1,9),IF(ISNUMBER(OFFSET($A$1,ROW()-1,8)),OFFSET($A$1,ROW()-1,8),0)))))))) | AH13: =IF($V13="","",IF(AND(ISNUMBER($G13),$G13<=IF($S13=MesCiclo,InicioCiclo,$S13+MOD(2-WEEKDAY($S13),7))+6),1,IF(N($W13)>0,MIN(1,SUMIFS($AD$5:$AD$1000,$U$5:$U$1000,ROW(),$V$5:$V$1000,"Sub")),$Z13))) | AI13: =IF($V13="","",IF(AND(ISNUMBER($G13),$G13<=IF($S13=MesCiclo,InicioCiclo,$S13+MOD(2-WEEKDAY($S13),7))+13),1,IF(N($W13)>0,MIN(1,SUMIFS($AE$5:$AE$1000,$U$5:$U$1000,ROW(),$V$5:$V$1000,"Sub")),$AA13))) | AJ13: =IF($V13="","",IF(AND(ISNUMBER($G13),$G13<=IF($S13=MesCiclo,InicioCiclo,$S13+MOD(2-WEEKDAY($S13),7))+20),1,IF(N($W13)>0,MIN(1,SUMIFS($AF$5:$AF$1000,$U$5:$U$1000,ROW(),$V$5:$V$1000,"Sub")),$AB13))) | AK13: =IF($V13="","",IF(AND(ISNUMBER($G13),$G13<=IF($S13=MesCiclo,InicioCiclo,$S13+MOD(2-WEEKDAY($S13),7))+27),1,IF(N($W13)>0,MIN(1,SUMIFS($AG$5:$AG$1000,$U$5:$U$1000,ROW(),$V$5:$V$1000,"Sub")),$AC13))) | AL13: =IF($V13<>"Macro","",IF(COUNTIFS($S$5:$S$1000,$S13,$V$5:$V$1000,"Macro",$H$5:$H$1000,">0")=0,1/COUNTIFS($S$5:$S$1000,$S13,$V$5:$V$1000,"Macro"),IF(AND(ISNUMBER($H13),N($H13)>0),$H13,SUMIFS($H$5:$H$1000,$S$5:$S$1000,$S13,$V$5:$V$1000,"Macro")/COUNTIFS($S$5:$S$1000,$S13,$V$5:$V$1000,"Macro",$H$5:$H$1000,">0"))/(COUNTIFS($S$5:$S$1000,$S13,$V$5:$V$1000,"Macro")*SUMIFS($H$5:$H$1000,$S$5:$S$1000,$S13,$V$5:$V$1000,"Macro")/COUNTIFS($S$5:$S$1000,$S13,$V$5:$V$1000,"Macro",$H$5:$H$1000,">0")))) | AM13: =IF(NOT(AND($D13<>"",$V13="Macro")),"",IFERROR(CHOOSE(MATCH($D13,ListaPuestos,0),MATCH("[Jefatura] "&$C13,'Cronograma R. Operacional'!$C$5:$C$1000,0),MATCH("[Jefatura] "&$C13,'Cronograma R. Normativo'!$C$5:$C$1000,0),MATCH("[Jefatura] "&$C13,'Cronograma R. Financiero'!$C$5:$C$1000,0),MATCH("[Jefatura] "&$C13,'Cronograma Asistente Técnico'!$C$5:$C$1000,0)),0)) | AN13: =IF(AND(AND($D13<>"",$V13="Macro"),$S13=MesCiclo),COUNTIFS($D$5:$D13,$D13,$S$5:$S13,MesCiclo,$V$5:$V13,"Macro"),"") | AO13: =IF($AN13="","",$D13&"|"&$AN13) | AP13: =IF(AND($D13<>"",$V13="Macro"),$D13&"|"&$C13,"") | AQ13: ="" | AR13: =IF(N($AQ13)>0,INDEX(rIni_ADM,$AQ13),IF(ISNUMBER($E13),$E13,"")) | AS13: =IF(N($AQ13)>0,INDEX(rLim_ADM,$AQ13),IF(ISNUMBER($F13),$F13,""))
A14: =IF(NOT((COUNTA($B14:$D14)+COUNTA($G14:$H14)+COUNTA($Q14))>0),"",IF($V14="Macro",COUNTIFS($V$5:$V14,"Macro",$S$5:$S14,$S14),IF(N($U14)=0,"?",COUNTIFS(INDEX($V$5:$V$1000,1):INDEX($V$5:$V$1000,$U14-4),"Macro",INDEX($S$5:$S$1000,1):INDEX($S$5:$S$1000,$U14-4),INDEX($S$5:$S$1000,$U14-4))&"."&COUNTIFS($U$5:$U14,$U14,$V$5:$V14,"Sub")))) | I14: =IF(N($W14)=0,"",IF(AND($S14=MesCiclo,1>SemanaActual),"",MIN(1,SUMIFS(OFFSET($A$1,ROW(),29,1000-ROW(),1),OFFSET($A$1,ROW(),20,1000-ROW(),1),ROW(),OFFSET($A$1,ROW(),21,1000-ROW(),1),"Sub")))) | J14: =IF(N($W14)=0,"",IF(AND($S14=MesCiclo,2>SemanaActual),"",MIN(1,SUMIFS(OFFSET($A$1,ROW(),30,1000-ROW(),1),OFFSET($A$1,ROW(),20,1000-ROW(),1),ROW(),OFFSET($A$1,ROW(),21,1000-ROW(),1),"Sub")))) | K14: =IF(N($W14)=0,"",IF(AND($S14=MesCiclo,3>SemanaActual),"",MIN(1,SUMIFS(OFFSET($A$1,ROW(),31,1000-ROW(),1),OFFSET($A$1,ROW(),20,1000-ROW(),1),ROW(),OFFSET($A$1,ROW(),21,1000-ROW(),1),"Sub")))) | L14: =IF(N($W14)=0,"",IF(AND($S14=MesCiclo,4>SemanaActual),"",MIN(1,SUMIFS(OFFSET($A$1,ROW(),32,1000-ROW(),1),OFFSET($A$1,ROW(),20,1000-ROW(),1),ROW(),OFFSET($A$1,ROW(),21,1000-ROW(),1),"Sub")))) | M14: =IF(NOT((COUNTA($B14:$D14)+COUNTA($G14:$H14)+COUNTA($Q14))>0),"",IF(AND($D14<>"",$V14="Macro"),IF(N($AM14)>0,N(CHOOSE(MATCH($D14,ListaPuestos,0),INDEX('Cronograma R. Operacional'!$M$5:$M$1000,$AM14),INDEX('Cronograma R. Normativo'!$M$5:$M$1000,$AM14),INDEX('Cronograma R. Financiero'!$M$5:$M$1000,$AM14),INDEX('Cronograma Asistente Técnico'!$M$5:$M$1000,$AM14))),0),IF(ISNUMBER($G14),1,IF(N($W14)>0,MIN(1,SUMIFS($Y$5:$Y$1000,$U$5:$U$1000,ROW(),$V$5:$V$1000,"Sub")),$Y14)))) | N14: =IF(OR($M14="",$V14="Sub"),"",IF($M14>=1,"Completado",IF($M14>0,"En curso","Pendiente"))) | O14: =IF(NOT((COUNTA($B14:$D14)+COUNTA($G14:$H14)+COUNTA($Q14))>0),"",IF(AND(AND($D14<>"",$V14="Macro"),N($AM14)>0),CHOOSE(MATCH($D14,ListaPuestos,0),INDEX('Cronograma R. Operacional'!$O$5:$O$1000,$AM14),INDEX('Cronograma R. Normativo'!$O$5:$O$1000,$AM14),INDEX('Cronograma R. Financiero'!$O$5:$O$1000,$AM14),INDEX('Cronograma Asistente Técnico'!$O$5:$O$1000,$AM14))&"",IF(ISNUMBER($G14),IF(AND(ISNUMBER($AS14),$G14>$AS14),"Cumplida con "&($G14-$AS14)&IF($G14-$AS14=1," día"," días")&" de retraso","Cumplida"),IF(N($M14)>=1,"Cumplida",IF(NOT(ISNUMBER($AS14)),"Sin fecha límite",IF($AS14<FechaRef,"Vencida hace "&(FechaRef-$AS14)&IF(FechaRef-$AS14=1," día"," días"),IF($AS14=FechaRef,"Vence hoy",IF($AS14-FechaRef<=DiasAlerta,"Vence en "&($AS14-FechaRef)&IF($AS14-FechaRef=1," día"," días"),"En plazo")))))))) | P14: =IF(NOT((COUNTA($B14:$D14)+COUNTA($G14:$H14)+COUNTA($Q14))>0),"",IF($D14="","Propia",IF($V14<>"Macro","Solo se delegan macroactividades",IF(N($AM14)>0,"✔ Recibida por "&$D14,"⚠ "&$D14&" aún no la agrega")))) | R14: =IF(NOT((COUNTA($B14:$D14)+COUNTA($G14:$H14)+COUNTA($Q14))>0),"",IF((IF($C14="","Falta el nombre de la actividad"&" · ","")&IF(AND($V14="Sub",N($U14)=0),"Subactividad sin macroactividad arriba"&" · ","")&IF(AND($V14="Macro",$AR14=""),"Sin fecha de inicio"&" · ","")&IF(AND($V14="Macro",$AS14=""),"Sin fecha límite"&" · ","")&IF(AND(LEFT($C14,11)="[Jefatura] ",N($AQ14)=0),"No se encuentra en la hoja de la jefatura (elíjala de nuevo en la lista)"&" · ","")&IF(OR(AND($E14<>"",NOT(ISNUMBER($E14))),AND($F14<>"",NOT(ISNUMBER($F14))),AND($G14<>"",NOT(ISNUMBER($G14)))),"Fecha no válida"&" · ","")&IF(AND(ISNUMBER($AR14),ISNUMBER($AS14),$AR14>$AS14),"Inicio posterior a fecha límite"&" · ","")&IF(AND($V14="Macro",$H14<>"",OR(NOT(ISNUMBER($H14)),$H14<0,$H14>1)),"Peso fuera de rango"&" · ","")&IF(AND($V14="Sub",$H14<>"",OR(NOT(ISNUMBER($H14)),$H14<0,$H14>1)),"% de la subactividad fuera de rango 0-100%"&" · ","")&IF(AND(N($W14)>0,SUMIFS($H$5:$H$1000,$U$5:$U$1000,ROW(),$V$5:$V$1000,"Sub")>1.0001),"Las subactividades suman más de 100%"&" · ","")&IF(AND(N($W14)>0,OR(IF(ISNUMBER($I14),ROUND($I14,6)<>ROUND(MIN(1,SUMIFS($AD$5:$AD$1000,$U$5:$U$1000,ROW(),$V$5:$V$1000,"Sub")),6),FALSE),IF(ISNUMBER($J14),ROUND($J14,6)<>ROUND(MIN(1,SUMIFS($AE$5:$AE$1000,$U$5:$U$1000,ROW(),$V$5:$V$1000,"Sub")),6),FALSE),IF(ISNUMBER($K14),ROUND($K14,6)<>ROUND(MIN(1,SUMIFS($AF$5:$AF$1000,$U$5:$U$1000,ROW(),$V$5:$V$1000,"Sub")),6),FALSE),IF(ISNUMBER($L14),ROUND($L14,6)<>ROUND(MIN(1,SUMIFS($AG$5:$AG$1000,$U$5:$U$1000,ROW(),$V$5:$V$1000,"Sub")),6),FALSE))),"Con subactividades: no escriba en las semanas (se llenan solas)"&" · ","")&IF((COUNTIF($I14:$L14,">1")+COUNTIF($I14:$L14,"<0")+SUMPRODUCT((LEN($I14:$L14)>0)*NOT(ISNUMBER($I14:$L14))))>0,"Avance fuera de rango 0-100%"&" · ","")&IF(OR(AND(ISNUMBER($J14),$J14<N($I14)),AND(ISNUMBER($K14),$K14<MAX($I14:$J14)),AND(ISNUMBER($L14),$L14<MAX($I14:$K14))),"Avance semanal decreciente"&" · ","")&IF(AND(ISNUMBER($AS14),$AS14<FechaRef,IF($V14="Sub",1,N($M14))<1),"Vencida"&" · ","")&IF(AND(ObsObligatoria="Sí",ISNUMBER($AS14),$AS14<FechaRef,IF($V14="Sub",1,N($M14))<1,$Q14=""),"Vencida sin observación"&" · ",""))="","✔ OK","⚠ "&LEFT(IF($C14="","Falta el nombre de la actividad"&" · ","")&IF(AND($V14="Sub",N($U14)=0),"Subactividad sin macroactividad arriba"&" · ","")&IF(AND($V14="Macro",$AR14=""),"Sin fecha de inicio"&" · ","")&IF(AND($V14="Macro",$AS14=""),"Sin fecha límite"&" · ","")&IF(AND(LEFT($C14,11)="[Jefatura] ",N($AQ14)=0),"No se encuentra en la hoja de la jefatura (elíjala de nuevo en la lista)"&" · ","")&IF(OR(AND($E14<>"",NOT(ISNUMBER($E14))),AND($F14<>"",NOT(ISNUMBER($F14))),AND($G14<>"",NOT(ISNUMBER($G14)))),"Fecha no válida"&" · ","")&IF(AND(ISNUMBER($AR14),ISNUMBER($AS14),$AR14>$AS14),"Inicio posterior a fecha límite"&" · ","")&IF(AND($V14="Macro",$H14<>"",OR(NOT(ISNUMBER($H14)),$H14<0,$H14>1)),"Peso fuera de rango"&" · ","")&IF(AND($V14="Sub",$H14<>"",OR(NOT(ISNUMBER($H14)),$H14<0,$H14>1)),"% de la subactividad fuera de rango 0-100%"&" · ","")&IF(AND(N($W14)>0,SUMIFS($H$5:$H$1000,$U$5:$U$1000,ROW(),$V$5:$V$1000,"Sub")>1.0001),"Las subactividades suman más de 100%"&" · ","")&IF(AND(N($W14)>0,OR(IF(ISNUMBER($I14),ROUND($I14,6)<>ROUND(MIN(1,SUMIFS($AD$5:$AD$1000,$U$5:$U$1000,ROW(),$V$5:$V$1000,"Sub")),6),FALSE),IF(ISNUMBER($J14),ROUND($J14,6)<>ROUND(MIN(1,SUMIFS($AE$5:$AE$1000,$U$5:$U$1000,ROW(),$V$5:$V$1000,"Sub")),6),FALSE),IF(ISNUMBER($K14),ROUND($K14,6)<>ROUND(MIN(1,SUMIFS($AF$5:$AF$1000,$U$5:$U$1000,ROW(),$V$5:$V$1000,"Sub")),6),FALSE),IF(ISNUMBER($L14),ROUND($L14,6)<>ROUND(MIN(1,SUMIFS($AG$5:$AG$1000,$U$5:$U$1000,ROW(),$V$5:$V$1000,"Sub")),6),FALSE))),"Con subactividades: no escriba en las semanas (se llenan solas)"&" · ","")&IF((COUNTIF($I14:$L14,">1")+COUNTIF($I14:$L14,"<0")+SUMPRODUCT((LEN($I14:$L14)>0)*NOT(ISNUMBER($I14:$L14))))>0,"Avance fuera de rango 0-100%"&" · ","")&IF(OR(AND(ISNUMBER($J14),$J14<N($I14)),AND(ISNUMBER($K14),$K14<MAX($I14:$J14)),AND(ISNUMBER($L14),$L14<MAX($I14:$K14))),"Avance semanal decreciente"&" · ","")&IF(AND(ISNUMBER($AS14),$AS14<FechaRef,IF($V14="Sub",1,N($M14))<1),"Vencida"&" · ","")&IF(AND(ObsObligatoria="Sí",ISNUMBER($AS14),$AS14<FechaRef,IF($V14="Sub",1,N($M14))<1,$Q14=""),"Vencida sin observación"&" · ",""),LEN(IF($C14="","Falta el nombre de la actividad"&" · ","")&IF(AND($V14="Sub",N($U14)=0),"Subactividad sin macroactividad arriba"&" · ","")&IF(AND($V14="Macro",$AR14=""),"Sin fecha de inicio"&" · ","")&IF(AND($V14="Macro",$AS14=""),"Sin fecha límite"&" · ","")&IF(AND(LEFT($C14,11)="[Jefatura] ",N($AQ14)=0),"No se encuentra en la hoja de la jefatura (elíjala de nuevo en la lista)"&" · ","")&IF(OR(AND($E14<>"",NOT(ISNUMBER($E14))),AND($F14<>"",NOT(ISNUMBER($F14))),AND($G14<>"",NOT(ISNUMBER($G14)))),"Fecha no válida"&" · ","")&IF(AND(ISNUMBER($AR14),ISNUMBER($AS14),$AR14>$AS14),"Inicio posterior a fecha límite"&" · ","")&IF(AND($V14="Macro",$H14<>"",OR(NOT(ISNUMBER($H14)),$H14<0,$H14>1)),"Peso fuera de rango"&" · ","")&IF(AND($V14="Sub",$H14<>"",OR(NOT(ISNUMBER($H14)),$H14<0,$H14>1)),"% de la subactividad fuera de rango 0-100%"&" · ","")&IF(AND(N($W14)>0,SUMIFS($H$5:$H$1000,$U$5:$U$1000,ROW(),$V$5:$V$1000,"Sub")>1.0001),"Las subactividades suman más de 100%"&" · ","")&IF(AND(N($W14)>0,OR(IF(ISNUMBER($I14),ROUND($I14,6)<>ROUND(MIN(1,SUMIFS($AD$5:$AD$1000,$U$5:$U$1000,ROW(),$V$5:$V$1000,"Sub")),6),FALSE),IF(ISNUMBER($J14),ROUND($J14,6)<>ROUND(MIN(1,SUMIFS($AE$5:$AE$1000,$U$5:$U$1000,ROW(),$V$5:$V$1000,"Sub")),6),FALSE),IF(ISNUMBER($K14),ROUND($K14,6)<>ROUND(MIN(1,SUMIFS($AF$5:$AF$1000,$U$5:$U$1000,ROW(),$V$5:$V$1000,"Sub")),6),FALSE),IF(ISNUMBER($L14),ROUND($L14,6)<>ROUND(MIN(1,SUMIFS($AG$5:$AG$1000,$U$5:$U$1000,ROW(),$V$5:$V$1000,"Sub")),6),FALSE))),"Con subactividades: no escriba en las semanas (se llenan solas)"&" · ","")&IF((COUNTIF($I14:$L14,">1")+COUNTIF($I14:$L14,"<0")+SUMPRODUCT((LEN($I14:$L14)>0)*NOT(ISNUMBER($I14:$L14))))>0,"Avance fuera de rango 0-100%"&" · ","")&IF(OR(AND(ISNUMBER($J14),$J14<N($I14)),AND(ISNUMBER($K14),$K14<MAX($I14:$J14)),AND(ISNUMBER($L14),$L14<MAX($I14:$K14))),"Avance semanal decreciente"&" · ","")&IF(AND(ISNUMBER($AS14),$AS14<FechaRef,IF($V14="Sub",1,N($M14))<1),"Vencida"&" · ","")&IF(AND(ObsObligatoria="Sí",ISNUMBER($AS14),$AS14<FechaRef,IF($V14="Sub",1,N($M14))<1,$Q14=""),"Vencida sin observación"&" · ",""))-3))) | S14: =IF(NOT((COUNTA($B14:$D14)+COUNTA($G14:$H14)+COUNTA($Q14))>0),"",IF(AND($V14="Sub",N($U14)>0),IF(ISNUMBER(INDEX($AR$5:$AR$1000,$U14-4)),DATE(YEAR(INDEX($AR$5:$AR$1000,$U14-4)),MONTH(INDEX($AR$5:$AR$1000,$U14-4)),1),IF(ISNUMBER(INDEX($AS$5:$AS$1000,$U14-4)),DATE(YEAR(INDEX($AS$5:$AS$1000,$U14-4)),MONTH(INDEX($AS$5:$AS$1000,$U14-4)),1),MesCiclo)),IF(ISNUMBER($AR14),DATE(YEAR($AR14),MONTH($AR14),1),IF(ISNUMBER($AS14),DATE(YEAR($AS14),MONTH($AS14),1),MesCiclo)))) | T14: =IF(OR($S14="",$S14<>MesCiclo,$V14<>"Macro"),"",COUNTIFS($S$5:$S14,MesCiclo,$V$5:$V14,"Macro")) | U14: =IF($V14="","",IF($V14="Macro",ROW(),IFERROR(LOOKUP(2,1/($V$5:$V14="Macro"),ROW($V$5:$V14)),0))) | V14: =IF(NOT((COUNTA($B14:$D14)+COUNTA($G14:$H14)+COUNTA($Q14))>0),"",IF($B14="Subactividad","Sub","Macro")) | W14: =IF($V14="Macro",COUNTIFS($U$5:$U$1000,ROW(),$V$5:$V$1000,"Sub"),"") | X14: =IF($V14<>"Sub","",IF(AND(ISNUMBER($H14),N($H14)>0),$H14,IFERROR(MAX(0,1-SUMIFS($H$5:$H$1000,$U$5:$U$1000,$U14,$V$5:$V$1000,"Sub"))/(COUNTIFS($U$5:$U$1000,$U14,$V$5:$V$1000,"Sub")-COUNTIFS($U$5:$U$1000,$U14,$V$5:$V$1000,"Sub",$H$5:$H$1000,">0")),0))) | Y14: =IF($V14="","",IF($V14="Sub",N($X14)*IF(ISNUMBER($G14),1,MIN(1,MAX(0,IFERROR(LOOKUP(2,1/ISNUMBER($I14:$L14),$I14:$L14),0)))),IF(ISNUMBER($G14),1,IFERROR(LOOKUP(2,1/($I14:$L14<>""),$I14:$L14),0)))) | Z14: =IF($V14="","",IF(AND(ISNUMBER($G14),$G14<=IF($S14=MesCiclo,InicioCiclo,$S14+MOD(2-WEEKDAY($S14),7))+6),1,IF(ISNUMBER($I14),$I14,0))) | AA14: =IF($V14="","",IF(AND(ISNUMBER($G14),$G14<=IF($S14=MesCiclo,InicioCiclo,$S14+MOD(2-WEEKDAY($S14),7))+13),1,IF(ISNUMBER($J14),$J14,$Z14))) | AB14: =IF($V14="","",IF(AND(ISNUMBER($G14),$G14<=IF($S14=MesCiclo,InicioCiclo,$S14+MOD(2-WEEKDAY($S14),7))+20),1,IF(ISNUMBER($K14),$K14,$AA14))) | AC14: =IF($V14="","",IF(AND(ISNUMBER($G14),$G14<=IF($S14=MesCiclo,InicioCiclo,$S14+MOD(2-WEEKDAY($S14),7))+27),1,IF(ISNUMBER($L14),$L14,$AB14))) | AD14: =IF($V14<>"Sub","",N($X14)*IF(AND(ISNUMBER($G14),$G14<=IF($S14=MesCiclo,InicioCiclo,$S14+MOD(2-WEEKDAY($S14),7))+6),1,MIN(1,MAX(0,IF(ISNUMBER(OFFSET($A$1,ROW()-1,8)),OFFSET($A$1,ROW()-1,8),0))))) | AE14: =IF($V14<>"Sub","",N($X14)*IF(AND(ISNUMBER($G14),$G14<=IF($S14=MesCiclo,InicioCiclo,$S14+MOD(2-WEEKDAY($S14),7))+13),1,MIN(1,MAX(0,IF(ISNUMBER(OFFSET($A$1,ROW()-1,9)),OFFSET($A$1,ROW()-1,9),IF(ISNUMBER(OFFSET($A$1,ROW()-1,8)),OFFSET($A$1,ROW()-1,8),0)))))) | AF14: =IF($V14<>"Sub","",N($X14)*IF(AND(ISNUMBER($G14),$G14<=IF($S14=MesCiclo,InicioCiclo,$S14+MOD(2-WEEKDAY($S14),7))+20),1,MIN(1,MAX(0,IF(ISNUMBER(OFFSET($A$1,ROW()-1,10)),OFFSET($A$1,ROW()-1,10),IF(ISNUMBER(OFFSET($A$1,ROW()-1,9)),OFFSET($A$1,ROW()-1,9),IF(ISNUMBER(OFFSET($A$1,ROW()-1,8)),OFFSET($A$1,ROW()-1,8),0))))))) | AG14: =IF($V14<>"Sub","",N($X14)*IF(AND(ISNUMBER($G14),$G14<=IF($S14=MesCiclo,InicioCiclo,$S14+MOD(2-WEEKDAY($S14),7))+27),1,MIN(1,MAX(0,IF(ISNUMBER(OFFSET($A$1,ROW()-1,11)),OFFSET($A$1,ROW()-1,11),IF(ISNUMBER(OFFSET($A$1,ROW()-1,10)),OFFSET($A$1,ROW()-1,10),IF(ISNUMBER(OFFSET($A$1,ROW()-1,9)),OFFSET($A$1,ROW()-1,9),IF(ISNUMBER(OFFSET($A$1,ROW()-1,8)),OFFSET($A$1,ROW()-1,8),0)))))))) | AH14: =IF($V14="","",IF(AND(ISNUMBER($G14),$G14<=IF($S14=MesCiclo,InicioCiclo,$S14+MOD(2-WEEKDAY($S14),7))+6),1,IF(N($W14)>0,MIN(1,SUMIFS($AD$5:$AD$1000,$U$5:$U$1000,ROW(),$V$5:$V$1000,"Sub")),$Z14))) | AI14: =IF($V14="","",IF(AND(ISNUMBER($G14),$G14<=IF($S14=MesCiclo,InicioCiclo,$S14+MOD(2-WEEKDAY($S14),7))+13),1,IF(N($W14)>0,MIN(1,SUMIFS($AE$5:$AE$1000,$U$5:$U$1000,ROW(),$V$5:$V$1000,"Sub")),$AA14))) | AJ14: =IF($V14="","",IF(AND(ISNUMBER($G14),$G14<=IF($S14=MesCiclo,InicioCiclo,$S14+MOD(2-WEEKDAY($S14),7))+20),1,IF(N($W14)>0,MIN(1,SUMIFS($AF$5:$AF$1000,$U$5:$U$1000,ROW(),$V$5:$V$1000,"Sub")),$AB14))) | AK14: =IF($V14="","",IF(AND(ISNUMBER($G14),$G14<=IF($S14=MesCiclo,InicioCiclo,$S14+MOD(2-WEEKDAY($S14),7))+27),1,IF(N($W14)>0,MIN(1,SUMIFS($AG$5:$AG$1000,$U$5:$U$1000,ROW(),$V$5:$V$1000,"Sub")),$AC14))) | AL14: =IF($V14<>"Macro","",IF(COUNTIFS($S$5:$S$1000,$S14,$V$5:$V$1000,"Macro",$H$5:$H$1000,">0")=0,1/COUNTIFS($S$5:$S$1000,$S14,$V$5:$V$1000,"Macro"),IF(AND(ISNUMBER($H14),N($H14)>0),$H14,SUMIFS($H$5:$H$1000,$S$5:$S$1000,$S14,$V$5:$V$1000,"Macro")/COUNTIFS($S$5:$S$1000,$S14,$V$5:$V$1000,"Macro",$H$5:$H$1000,">0"))/(COUNTIFS($S$5:$S$1000,$S14,$V$5:$V$1000,"Macro")*SUMIFS($H$5:$H$1000,$S$5:$S$1000,$S14,$V$5:$V$1000,"Macro")/COUNTIFS($S$5:$S$1000,$S14,$V$5:$V$1000,"Macro",$H$5:$H$1000,">0")))) | AM14: =IF(NOT(AND($D14<>"",$V14="Macro")),"",IFERROR(CHOOSE(MATCH($D14,ListaPuestos,0),MATCH("[Jefatura] "&$C14,'Cronograma R. Operacional'!$C$5:$C$1000,0),MATCH("[Jefatura] "&$C14,'Cronograma R. Normativo'!$C$5:$C$1000,0),MATCH("[Jefatura] "&$C14,'Cronograma R. Financiero'!$C$5:$C$1000,0),MATCH("[Jefatura] "&$C14,'Cronograma Asistente Técnico'!$C$5:$C$1000,0)),0)) | AN14: =IF(AND(AND($D14<>"",$V14="Macro"),$S14=MesCiclo),COUNTIFS($D$5:$D14,$D14,$S$5:$S14,MesCiclo,$V$5:$V14,"Macro"),"") | AO14: =IF($AN14="","",$D14&"|"&$AN14) | AP14: =IF(AND($D14<>"",$V14="Macro"),$D14&"|"&$C14,"") | AQ14: ="" | AR14: =IF(N($AQ14)>0,INDEX(rIni_ADM,$AQ14),IF(ISNUMBER($E14),$E14,"")) | AS14: =IF(N($AQ14)>0,INDEX(rLim_ADM,$AQ14),IF(ISNUMBER($F14),$F14,""))
A15: =IF(NOT((COUNTA($B15:$D15)+COUNTA($G15:$H15)+COUNTA($Q15))>0),"",IF($V15="Macro",COUNTIFS($V$5:$V15,"Macro",$S$5:$S15,$S15),IF(N($U15)=0,"?",COUNTIFS(INDEX($V$5:$V$1000,1):INDEX($V$5:$V$1000,$U15-4),"Macro",INDEX($S$5:$S$1000,1):INDEX($S$5:$S$1000,$U15-4),INDEX($S$5:$S$1000,$U15-4))&"."&COUNTIFS($U$5:$U15,$U15,$V$5:$V15,"Sub")))) | I15: =IF(N($W15)=0,"",IF(AND($S15=MesCiclo,1>SemanaActual),"",MIN(1,SUMIFS(OFFSET($A$1,ROW(),29,1000-ROW(),1),OFFSET($A$1,ROW(),20,1000-ROW(),1),ROW(),OFFSET($A$1,ROW(),21,1000-ROW(),1),"Sub")))) | J15: =IF(N($W15)=0,"",IF(AND($S15=MesCiclo,2>SemanaActual),"",MIN(1,SUMIFS(OFFSET($A$1,ROW(),30,1000-ROW(),1),OFFSET($A$1,ROW(),20,1000-ROW(),1),ROW(),OFFSET($A$1,ROW(),21,1000-ROW(),1),"Sub")))) | K15: =IF(N($W15)=0,"",IF(AND($S15=MesCiclo,3>SemanaActual),"",MIN(1,SUMIFS(OFFSET($A$1,ROW(),31,1000-ROW(),1),OFFSET($A$1,ROW(),20,1000-ROW(),1),ROW(),OFFSET($A$1,ROW(),21,1000-ROW(),1),"Sub")))) | L15: =IF(N($W15)=0,"",IF(AND($S15=MesCiclo,4>SemanaActual),"",MIN(1,SUMIFS(OFFSET($A$1,ROW(),32,1000-ROW(),1),OFFSET($A$1,ROW(),20,1000-ROW(),1),ROW(),OFFSET($A$1,ROW(),21,1000-ROW(),1),"Sub")))) | M15: =IF(NOT((COUNTA($B15:$D15)+COUNTA($G15:$H15)+COUNTA($Q15))>0),"",IF(AND($D15<>"",$V15="Macro"),IF(N($AM15)>0,N(CHOOSE(MATCH($D15,ListaPuestos,0),INDEX('Cronograma R. Operacional'!$M$5:$M$1000,$AM15),INDEX('Cronograma R. Normativo'!$M$5:$M$1000,$AM15),INDEX('Cronograma R. Financiero'!$M$5:$M$1000,$AM15),INDEX('Cronograma Asistente Técnico'!$M$5:$M$1000,$AM15))),0),IF(ISNUMBER($G15),1,IF(N($W15)>0,MIN(1,SUMIFS($Y$5:$Y$1000,$U$5:$U$1000,ROW(),$V$5:$V$1000,"Sub")),$Y15)))) | N15: =IF(OR($M15="",$V15="Sub"),"",IF($M15>=1,"Completado",IF($M15>0,"En curso","Pendiente"))) | O15: =IF(NOT((COUNTA($B15:$D15)+COUNTA($G15:$H15)+COUNTA($Q15))>0),"",IF(AND(AND($D15<>"",$V15="Macro"),N($AM15)>0),CHOOSE(MATCH($D15,ListaPuestos,0),INDEX('Cronograma R. Operacional'!$O$5:$O$1000,$AM15),INDEX('Cronograma R. Normativo'!$O$5:$O$1000,$AM15),INDEX('Cronograma R. Financiero'!$O$5:$O$1000,$AM15),INDEX('Cronograma Asistente Técnico'!$O$5:$O$1000,$AM15))&"",IF(ISNUMBER($G15),IF(AND(ISNUMBER($AS15),$G15>$AS15),"Cumplida con "&($G15-$AS15)&IF($G15-$AS15=1," día"," días")&" de retraso","Cumplida"),IF(N($M15)>=1,"Cumplida",IF(NOT(ISNUMBER($AS15)),"Sin fecha límite",IF($AS15<FechaRef,"Vencida hace "&(FechaRef-$AS15)&IF(FechaRef-$AS15=1," día"," días"),IF($AS15=FechaRef,"Vence hoy",IF($AS15-FechaRef<=DiasAlerta,"Vence en "&($AS15-FechaRef)&IF($AS15-FechaRef=1," día"," días"),"En plazo")))))))) | P15: =IF(NOT((COUNTA($B15:$D15)+COUNTA($G15:$H15)+COUNTA($Q15))>0),"",IF($D15="","Propia",IF($V15<>"Macro","Solo se delegan macroactividades",IF(N($AM15)>0,"✔ Recibida por "&$D15,"⚠ "&$D15&" aún no la agrega")))) | R15: =IF(NOT((COUNTA($B15:$D15)+COUNTA($G15:$H15)+COUNTA($Q15))>0),"",IF((IF($C15="","Falta el nombre de la actividad"&" · ","")&IF(AND($V15="Sub",N($U15)=0),"Subactividad sin macroactividad arriba"&" · ","")&IF(AND($V15="Macro",$AR15=""),"Sin fecha de inicio"&" · ","")&IF(AND($V15="Macro",$AS15=""),"Sin fecha límite"&" · ","")&IF(AND(LEFT($C15,11)="[Jefatura] ",N($AQ15)=0),"No se encuentra en la hoja de la jefatura (elíjala de nuevo en la lista)"&" · ","")&IF(OR(AND($E15<>"",NOT(ISNUMBER($E15))),AND($F15<>"",NOT(ISNUMBER($F15))),AND($G15<>"",NOT(ISNUMBER($G15)))),"Fecha no válida"&" · ","")&IF(AND(ISNUMBER($AR15),ISNUMBER($AS15),$AR15>$AS15),"Inicio posterior a fecha límite"&" · ","")&IF(AND($V15="Macro",$H15<>"",OR(NOT(ISNUMBER($H15)),$H15<0,$H15>1)),"Peso fuera de rango"&" · ","")&IF(AND($V15="Sub",$H15<>"",OR(NOT(ISNUMBER($H15)),$H15<0,$H15>1)),"% de la subactividad fuera de rango 0-100%"&" · ","")&IF(AND(N($W15)>0,SUMIFS($H$5:$H$1000,$U$5:$U$1000,ROW(),$V$5:$V$1000,"Sub")>1.0001),"Las subactividades suman más de 100%"&" · ","")&IF(AND(N($W15)>0,OR(IF(ISNUMBER($I15),ROUND($I15,6)<>ROUND(MIN(1,SUMIFS($AD$5:$AD$1000,$U$5:$U$1000,ROW(),$V$5:$V$1000,"Sub")),6),FALSE),IF(ISNUMBER($J15),ROUND($J15,6)<>ROUND(MIN(1,SUMIFS($AE$5:$AE$1000,$U$5:$U$1000,ROW(),$V$5:$V$1000,"Sub")),6),FALSE),IF(ISNUMBER($K15),ROUND($K15,6)<>ROUND(MIN(1,SUMIFS($AF$5:$AF$1000,$U$5:$U$1000,ROW(),$V$5:$V$1000,"Sub")),6),FALSE),IF(ISNUMBER($L15),ROUND($L15,6)<>ROUND(MIN(1,SUMIFS($AG$5:$AG$1000,$U$5:$U$1000,ROW(),$V$5:$V$1000,"Sub")),6),FALSE))),"Con subactividades: no escriba en las semanas (se llenan solas)"&" · ","")&IF((COUNTIF($I15:$L15,">1")+COUNTIF($I15:$L15,"<0")+SUMPRODUCT((LEN($I15:$L15)>0)*NOT(ISNUMBER($I15:$L15))))>0,"Avance fuera de rango 0-100%"&" · ","")&IF(OR(AND(ISNUMBER($J15),$J15<N($I15)),AND(ISNUMBER($K15),$K15<MAX($I15:$J15)),AND(ISNUMBER($L15),$L15<MAX($I15:$K15))),"Avance semanal decreciente"&" · ","")&IF(AND(ISNUMBER($AS15),$AS15<FechaRef,IF($V15="Sub",1,N($M15))<1),"Vencida"&" · ","")&IF(AND(ObsObligatoria="Sí",ISNUMBER($AS15),$AS15<FechaRef,IF($V15="Sub",1,N($M15))<1,$Q15=""),"Vencida sin observación"&" · ",""))="","✔ OK","⚠ "&LEFT(IF($C15="","Falta el nombre de la actividad"&" · ","")&IF(AND($V15="Sub",N($U15)=0),"Subactividad sin macroactividad arriba"&" · ","")&IF(AND($V15="Macro",$AR15=""),"Sin fecha de inicio"&" · ","")&IF(AND($V15="Macro",$AS15=""),"Sin fecha límite"&" · ","")&IF(AND(LEFT($C15,11)="[Jefatura] ",N($AQ15)=0),"No se encuentra en la hoja de la jefatura (elíjala de nuevo en la lista)"&" · ","")&IF(OR(AND($E15<>"",NOT(ISNUMBER($E15))),AND($F15<>"",NOT(ISNUMBER($F15))),AND($G15<>"",NOT(ISNUMBER($G15)))),"Fecha no válida"&" · ","")&IF(AND(ISNUMBER($AR15),ISNUMBER($AS15),$AR15>$AS15),"Inicio posterior a fecha límite"&" · ","")&IF(AND($V15="Macro",$H15<>"",OR(NOT(ISNUMBER($H15)),$H15<0,$H15>1)),"Peso fuera de rango"&" · ","")&IF(AND($V15="Sub",$H15<>"",OR(NOT(ISNUMBER($H15)),$H15<0,$H15>1)),"% de la subactividad fuera de rango 0-100%"&" · ","")&IF(AND(N($W15)>0,SUMIFS($H$5:$H$1000,$U$5:$U$1000,ROW(),$V$5:$V$1000,"Sub")>1.0001),"Las subactividades suman más de 100%"&" · ","")&IF(AND(N($W15)>0,OR(IF(ISNUMBER($I15),ROUND($I15,6)<>ROUND(MIN(1,SUMIFS($AD$5:$AD$1000,$U$5:$U$1000,ROW(),$V$5:$V$1000,"Sub")),6),FALSE),IF(ISNUMBER($J15),ROUND($J15,6)<>ROUND(MIN(1,SUMIFS($AE$5:$AE$1000,$U$5:$U$1000,ROW(),$V$5:$V$1000,"Sub")),6),FALSE),IF(ISNUMBER($K15),ROUND($K15,6)<>ROUND(MIN(1,SUMIFS($AF$5:$AF$1000,$U$5:$U$1000,ROW(),$V$5:$V$1000,"Sub")),6),FALSE),IF(ISNUMBER($L15),ROUND($L15,6)<>ROUND(MIN(1,SUMIFS($AG$5:$AG$1000,$U$5:$U$1000,ROW(),$V$5:$V$1000,"Sub")),6),FALSE))),"Con subactividades: no escriba en las semanas (se llenan solas)"&" · ","")&IF((COUNTIF($I15:$L15,">1")+COUNTIF($I15:$L15,"<0")+SUMPRODUCT((LEN($I15:$L15)>0)*NOT(ISNUMBER($I15:$L15))))>0,"Avance fuera de rango 0-100%"&" · ","")&IF(OR(AND(ISNUMBER($J15),$J15<N($I15)),AND(ISNUMBER($K15),$K15<MAX($I15:$J15)),AND(ISNUMBER($L15),$L15<MAX($I15:$K15))),"Avance semanal decreciente"&" · ","")&IF(AND(ISNUMBER($AS15),$AS15<FechaRef,IF($V15="Sub",1,N($M15))<1),"Vencida"&" · ","")&IF(AND(ObsObligatoria="Sí",ISNUMBER($AS15),$AS15<FechaRef,IF($V15="Sub",1,N($M15))<1,$Q15=""),"Vencida sin observación"&" · ",""),LEN(IF($C15="","Falta el nombre de la actividad"&" · ","")&IF(AND($V15="Sub",N($U15)=0),"Subactividad sin macroactividad arriba"&" · ","")&IF(AND($V15="Macro",$AR15=""),"Sin fecha de inicio"&" · ","")&IF(AND($V15="Macro",$AS15=""),"Sin fecha límite"&" · ","")&IF(AND(LEFT($C15,11)="[Jefatura] ",N($AQ15)=0),"No se encuentra en la hoja de la jefatura (elíjala de nuevo en la lista)"&" · ","")&IF(OR(AND($E15<>"",NOT(ISNUMBER($E15))),AND($F15<>"",NOT(ISNUMBER($F15))),AND($G15<>"",NOT(ISNUMBER($G15)))),"Fecha no válida"&" · ","")&IF(AND(ISNUMBER($AR15),ISNUMBER($AS15),$AR15>$AS15),"Inicio posterior a fecha límite"&" · ","")&IF(AND($V15="Macro",$H15<>"",OR(NOT(ISNUMBER($H15)),$H15<0,$H15>1)),"Peso fuera de rango"&" · ","")&IF(AND($V15="Sub",$H15<>"",OR(NOT(ISNUMBER($H15)),$H15<0,$H15>1)),"% de la subactividad fuera de rango 0-100%"&" · ","")&IF(AND(N($W15)>0,SUMIFS($H$5:$H$1000,$U$5:$U$1000,ROW(),$V$5:$V$1000,"Sub")>1.0001),"Las subactividades suman más de 100%"&" · ","")&IF(AND(N($W15)>0,OR(IF(ISNUMBER($I15),ROUND($I15,6)<>ROUND(MIN(1,SUMIFS($AD$5:$AD$1000,$U$5:$U$1000,ROW(),$V$5:$V$1000,"Sub")),6),FALSE),IF(ISNUMBER($J15),ROUND($J15,6)<>ROUND(MIN(1,SUMIFS($AE$5:$AE$1000,$U$5:$U$1000,ROW(),$V$5:$V$1000,"Sub")),6),FALSE),IF(ISNUMBER($K15),ROUND($K15,6)<>ROUND(MIN(1,SUMIFS($AF$5:$AF$1000,$U$5:$U$1000,ROW(),$V$5:$V$1000,"Sub")),6),FALSE),IF(ISNUMBER($L15),ROUND($L15,6)<>ROUND(MIN(1,SUMIFS($AG$5:$AG$1000,$U$5:$U$1000,ROW(),$V$5:$V$1000,"Sub")),6),FALSE))),"Con subactividades: no escriba en las semanas (se llenan solas)"&" · ","")&IF((COUNTIF($I15:$L15,">1")+COUNTIF($I15:$L15,"<0")+SUMPRODUCT((LEN($I15:$L15)>0)*NOT(ISNUMBER($I15:$L15))))>0,"Avance fuera de rango 0-100%"&" · ","")&IF(OR(AND(ISNUMBER($J15),$J15<N($I15)),AND(ISNUMBER($K15),$K15<MAX($I15:$J15)),AND(ISNUMBER($L15),$L15<MAX($I15:$K15))),"Avance semanal decreciente"&" · ","")&IF(AND(ISNUMBER($AS15),$AS15<FechaRef,IF($V15="Sub",1,N($M15))<1),"Vencida"&" · ","")&IF(AND(ObsObligatoria="Sí",ISNUMBER($AS15),$AS15<FechaRef,IF($V15="Sub",1,N($M15))<1,$Q15=""),"Vencida sin observación"&" · ",""))-3))) | S15: =IF(NOT((COUNTA($B15:$D15)+COUNTA($G15:$H15)+COUNTA($Q15))>0),"",IF(AND($V15="Sub",N($U15)>0),IF(ISNUMBER(INDEX($AR$5:$AR$1000,$U15-4)),DATE(YEAR(INDEX($AR$5:$AR$1000,$U15-4)),MONTH(INDEX($AR$5:$AR$1000,$U15-4)),1),IF(ISNUMBER(INDEX($AS$5:$AS$1000,$U15-4)),DATE(YEAR(INDEX($AS$5:$AS$1000,$U15-4)),MONTH(INDEX($AS$5:$AS$1000,$U15-4)),1),MesCiclo)),IF(ISNUMBER($AR15),DATE(YEAR($AR15),MONTH($AR15),1),IF(ISNUMBER($AS15),DATE(YEAR($AS15),MONTH($AS15),1),MesCiclo)))) | T15: =IF(OR($S15="",$S15<>MesCiclo,$V15<>"Macro"),"",COUNTIFS($S$5:$S15,MesCiclo,$V$5:$V15,"Macro")) | U15: =IF($V15="","",IF($V15="Macro",ROW(),IFERROR(LOOKUP(2,1/($V$5:$V15="Macro"),ROW($V$5:$V15)),0))) | V15: =IF(NOT((COUNTA($B15:$D15)+COUNTA($G15:$H15)+COUNTA($Q15))>0),"",IF($B15="Subactividad","Sub","Macro")) | W15: =IF($V15="Macro",COUNTIFS($U$5:$U$1000,ROW(),$V$5:$V$1000,"Sub"),"") | X15: =IF($V15<>"Sub","",IF(AND(ISNUMBER($H15),N($H15)>0),$H15,IFERROR(MAX(0,1-SUMIFS($H$5:$H$1000,$U$5:$U$1000,$U15,$V$5:$V$1000,"Sub"))/(COUNTIFS($U$5:$U$1000,$U15,$V$5:$V$1000,"Sub")-COUNTIFS($U$5:$U$1000,$U15,$V$5:$V$1000,"Sub",$H$5:$H$1000,">0")),0))) | Y15: =IF($V15="","",IF($V15="Sub",N($X15)*IF(ISNUMBER($G15),1,MIN(1,MAX(0,IFERROR(LOOKUP(2,1/ISNUMBER($I15:$L15),$I15:$L15),0)))),IF(ISNUMBER($G15),1,IFERROR(LOOKUP(2,1/($I15:$L15<>""),$I15:$L15),0)))) | Z15: =IF($V15="","",IF(AND(ISNUMBER($G15),$G15<=IF($S15=MesCiclo,InicioCiclo,$S15+MOD(2-WEEKDAY($S15),7))+6),1,IF(ISNUMBER($I15),$I15,0))) | AA15: =IF($V15="","",IF(AND(ISNUMBER($G15),$G15<=IF($S15=MesCiclo,InicioCiclo,$S15+MOD(2-WEEKDAY($S15),7))+13),1,IF(ISNUMBER($J15),$J15,$Z15))) | AB15: =IF($V15="","",IF(AND(ISNUMBER($G15),$G15<=IF($S15=MesCiclo,InicioCiclo,$S15+MOD(2-WEEKDAY($S15),7))+20),1,IF(ISNUMBER($K15),$K15,$AA15))) | AC15: =IF($V15="","",IF(AND(ISNUMBER($G15),$G15<=IF($S15=MesCiclo,InicioCiclo,$S15+MOD(2-WEEKDAY($S15),7))+27),1,IF(ISNUMBER($L15),$L15,$AB15))) | AD15: =IF($V15<>"Sub","",N($X15)*IF(AND(ISNUMBER($G15),$G15<=IF($S15=MesCiclo,InicioCiclo,$S15+MOD(2-WEEKDAY($S15),7))+6),1,MIN(1,MAX(0,IF(ISNUMBER(OFFSET($A$1,ROW()-1,8)),OFFSET($A$1,ROW()-1,8),0))))) | AE15: =IF($V15<>"Sub","",N($X15)*IF(AND(ISNUMBER($G15),$G15<=IF($S15=MesCiclo,InicioCiclo,$S15+MOD(2-WEEKDAY($S15),7))+13),1,MIN(1,MAX(0,IF(ISNUMBER(OFFSET($A$1,ROW()-1,9)),OFFSET($A$1,ROW()-1,9),IF(ISNUMBER(OFFSET($A$1,ROW()-1,8)),OFFSET($A$1,ROW()-1,8),0)))))) | AF15: =IF($V15<>"Sub","",N($X15)*IF(AND(ISNUMBER($G15),$G15<=IF($S15=MesCiclo,InicioCiclo,$S15+MOD(2-WEEKDAY($S15),7))+20),1,MIN(1,MAX(0,IF(ISNUMBER(OFFSET($A$1,ROW()-1,10)),OFFSET($A$1,ROW()-1,10),IF(ISNUMBER(OFFSET($A$1,ROW()-1,9)),OFFSET($A$1,ROW()-1,9),IF(ISNUMBER(OFFSET($A$1,ROW()-1,8)),OFFSET($A$1,ROW()-1,8),0))))))) | AG15: =IF($V15<>"Sub","",N($X15)*IF(AND(ISNUMBER($G15),$G15<=IF($S15=MesCiclo,InicioCiclo,$S15+MOD(2-WEEKDAY($S15),7))+27),1,MIN(1,MAX(0,IF(ISNUMBER(OFFSET($A$1,ROW()-1,11)),OFFSET($A$1,ROW()-1,11),IF(ISNUMBER(OFFSET($A$1,ROW()-1,10)),OFFSET($A$1,ROW()-1,10),IF(ISNUMBER(OFFSET($A$1,ROW()-1,9)),OFFSET($A$1,ROW()-1,9),IF(ISNUMBER(OFFSET($A$1,ROW()-1,8)),OFFSET($A$1,ROW()-1,8),0)))))))) | AH15: =IF($V15="","",IF(AND(ISNUMBER($G15),$G15<=IF($S15=MesCiclo,InicioCiclo,$S15+MOD(2-WEEKDAY($S15),7))+6),1,IF(N($W15)>0,MIN(1,SUMIFS($AD$5:$AD$1000,$U$5:$U$1000,ROW(),$V$5:$V$1000,"Sub")),$Z15))) | AI15: =IF($V15="","",IF(AND(ISNUMBER($G15),$G15<=IF($S15=MesCiclo,InicioCiclo,$S15+MOD(2-WEEKDAY($S15),7))+13),1,IF(N($W15)>0,MIN(1,SUMIFS($AE$5:$AE$1000,$U$5:$U$1000,ROW(),$V$5:$V$1000,"Sub")),$AA15))) | AJ15: =IF($V15="","",IF(AND(ISNUMBER($G15),$G15<=IF($S15=MesCiclo,InicioCiclo,$S15+MOD(2-WEEKDAY($S15),7))+20),1,IF(N($W15)>0,MIN(1,SUMIFS($AF$5:$AF$1000,$U$5:$U$1000,ROW(),$V$5:$V$1000,"Sub")),$AB15))) | AK15: =IF($V15="","",IF(AND(ISNUMBER($G15),$G15<=IF($S15=MesCiclo,InicioCiclo,$S15+MOD(2-WEEKDAY($S15),7))+27),1,IF(N($W15)>0,MIN(1,SUMIFS($AG$5:$AG$1000,$U$5:$U$1000,ROW(),$V$5:$V$1000,"Sub")),$AC15))) | AL15: =IF($V15<>"Macro","",IF(COUNTIFS($S$5:$S$1000,$S15,$V$5:$V$1000,"Macro",$H$5:$H$1000,">0")=0,1/COUNTIFS($S$5:$S$1000,$S15,$V$5:$V$1000,"Macro"),IF(AND(ISNUMBER($H15),N($H15)>0),$H15,SUMIFS($H$5:$H$1000,$S$5:$S$1000,$S15,$V$5:$V$1000,"Macro")/COUNTIFS($S$5:$S$1000,$S15,$V$5:$V$1000,"Macro",$H$5:$H$1000,">0"))/(COUNTIFS($S$5:$S$1000,$S15,$V$5:$V$1000,"Macro")*SUMIFS($H$5:$H$1000,$S$5:$S$1000,$S15,$V$5:$V$1000,"Macro")/COUNTIFS($S$5:$S$1000,$S15,$V$5:$V$1000,"Macro",$H$5:$H$1000,">0")))) | AM15: =IF(NOT(AND($D15<>"",$V15="Macro")),"",IFERROR(CHOOSE(MATCH($D15,ListaPuestos,0),MATCH("[Jefatura] "&$C15,'Cronograma R. Operacional'!$C$5:$C$1000,0),MATCH("[Jefatura] "&$C15,'Cronograma R. Normativo'!$C$5:$C$1000,0),MATCH("[Jefatura] "&$C15,'Cronograma R. Financiero'!$C$5:$C$1000,0),MATCH("[Jefatura] "&$C15,'Cronograma Asistente Técnico'!$C$5:$C$1000,0)),0)) | AN15: =IF(AND(AND($D15<>"",$V15="Macro"),$S15=MesCiclo),COUNTIFS($D$5:$D15,$D15,$S$5:$S15,MesCiclo,$V$5:$V15,"Macro"),"") | AO15: =IF($AN15="","",$D15&"|"&$AN15) | AP15: =IF(AND($D15<>"",$V15="Macro"),$D15&"|"&$C15,"") | AQ15: ="" | AR15: =IF(N($AQ15)>0,INDEX(rIni_ADM,$AQ15),IF(ISNUMBER($E15),$E15,"")) | AS15: =IF(N($AQ15)>0,INDEX(rLim_ADM,$AQ15),IF(ISNUMBER($F15),$F15,""))
A16: =IF(NOT((COUNTA($B16:$D16)+COUNTA($G16:$H16)+COUNTA($Q16))>0),"",IF($V16="Macro",COUNTIFS($V$5:$V16,"Macro",$S$5:$S16,$S16),IF(N($U16)=0,"?",COUNTIFS(INDEX($V$5:$V$1000,1):INDEX($V$5:$V$1000,$U16-4),"Macro",INDEX($S$5:$S$1000,1):INDEX($S$5:$S$1000,$U16-4),INDEX($S$5:$S$1000,$U16-4))&"."&COUNTIFS($U$5:$U16,$U16,$V$5:$V16,"Sub")))) | I16: =IF(N($W16)=0,"",IF(AND($S16=MesCiclo,1>SemanaActual),"",MIN(1,SUMIFS(OFFSET($A$1,ROW(),29,1000-ROW(),1),OFFSET($A$1,ROW(),20,1000-ROW(),1),ROW(),OFFSET($A$1,ROW(),21,1000-ROW(),1),"Sub")))) | J16: =IF(N($W16)=0,"",IF(AND($S16=MesCiclo,2>SemanaActual),"",MIN(1,SUMIFS(OFFSET($A$1,ROW(),30,1000-ROW(),1),OFFSET($A$1,ROW(),20,1000-ROW(),1),ROW(),OFFSET($A$1,ROW(),21,1000-ROW(),1),"Sub")))) | K16: =IF(N($W16)=0,"",IF(AND($S16=MesCiclo,3>SemanaActual),"",MIN(1,SUMIFS(OFFSET($A$1,ROW(),31,1000-ROW(),1),OFFSET($A$1,ROW(),20,1000-ROW(),1),ROW(),OFFSET($A$1,ROW(),21,1000-ROW(),1),"Sub")))) | L16: =IF(N($W16)=0,"",IF(AND($S16=MesCiclo,4>SemanaActual),"",MIN(1,SUMIFS(OFFSET($A$1,ROW(),32,1000-ROW(),1),OFFSET($A$1,ROW(),20,1000-ROW(),1),ROW(),OFFSET($A$1,ROW(),21,1000-ROW(),1),"Sub")))) | M16: =IF(NOT((COUNTA($B16:$D16)+COUNTA($G16:$H16)+COUNTA($Q16))>0),"",IF(AND($D16<>"",$V16="Macro"),IF(N($AM16)>0,N(CHOOSE(MATCH($D16,ListaPuestos,0),INDEX('Cronograma R. Operacional'!$M$5:$M$1000,$AM16),INDEX('Cronograma R. Normativo'!$M$5:$M$1000,$AM16),INDEX('Cronograma R. Financiero'!$M$5:$M$1000,$AM16),INDEX('Cronograma Asistente Técnico'!$M$5:$M$1000,$AM16))),0),IF(ISNUMBER($G16),1,IF(N($W16)>0,MIN(1,SUMIFS($Y$5:$Y$1000,$U$5:$U$1000,ROW(),$V$5:$V$1000,"Sub")),$Y16)))) | N16: =IF(OR($M16="",$V16="Sub"),"",IF($M16>=1,"Completado",IF($M16>0,"En curso","Pendiente"))) | O16: =IF(NOT((COUNTA($B16:$D16)+COUNTA($G16:$H16)+COUNTA($Q16))>0),"",IF(AND(AND($D16<>"",$V16="Macro"),N($AM16)>0),CHOOSE(MATCH($D16,ListaPuestos,0),INDEX('Cronograma R. Operacional'!$O$5:$O$1000,$AM16),INDEX('Cronograma R. Normativo'!$O$5:$O$1000,$AM16),INDEX('Cronograma R. Financiero'!$O$5:$O$1000,$AM16),INDEX('Cronograma Asistente Técnico'!$O$5:$O$1000,$AM16))&"",IF(ISNUMBER($G16),IF(AND(ISNUMBER($AS16),$G16>$AS16),"Cumplida con "&($G16-$AS16)&IF($G16-$AS16=1," día"," días")&" de retraso","Cumplida"),IF(N($M16)>=1,"Cumplida",IF(NOT(ISNUMBER($AS16)),"Sin fecha límite",IF($AS16<FechaRef,"Vencida hace "&(FechaRef-$AS16)&IF(FechaRef-$AS16=1," día"," días"),IF($AS16=FechaRef,"Vence hoy",IF($AS16-FechaRef<=DiasAlerta,"Vence en "&($AS16-FechaRef)&IF($AS16-FechaRef=1," día"," días"),"En plazo")))))))) | P16: =IF(NOT((COUNTA($B16:$D16)+COUNTA($G16:$H16)+COUNTA($Q16))>0),"",IF($D16="","Propia",IF($V16<>"Macro","Solo se delegan macroactividades",IF(N($AM16)>0,"✔ Recibida por "&$D16,"⚠ "&$D16&" aún no la agrega")))) | R16: =IF(NOT((COUNTA($B16:$D16)+COUNTA($G16:$H16)+COUNTA($Q16))>0),"",IF((IF($C16="","Falta el nombre de la actividad"&" · ","")&IF(AND($V16="Sub",N($U16)=0),"Subactividad sin macroactividad arriba"&" · ","")&IF(AND($V16="Macro",$AR16=""),"Sin fecha de inicio"&" · ","")&IF(AND($V16="Macro",$AS16=""),"Sin fecha límite"&" · ","")&IF(AND(LEFT($C16,11)="[Jefatura] ",N($AQ16)=0),"No se encuentra en la hoja de la jefatura (elíjala de nuevo en la lista)"&" · ","")&IF(OR(AND($E16<>"",NOT(ISNUMBER($E16))),AND($F16<>"",NOT(ISNUMBER($F16))),AND($G16<>"",NOT(ISNUMBER($G16)))),"Fecha no válida"&" · ","")&IF(AND(ISNUMBER($AR16),ISNUMBER($AS16),$AR16>$AS16),"Inicio posterior a fecha límite"&" · ","")&IF(AND($V16="Macro",$H16<>"",OR(NOT(ISNUMBER($H16)),$H16<0,$H16>1)),"Peso fuera de rango"&" · ","")&IF(AND($V16="Sub",$H16<>"",OR(NOT(ISNUMBER($H16)),$H16<0,$H16>1)),"% de la subactividad fuera de rango 0-100%"&" · ","")&IF(AND(N($W16)>0,SUMIFS($H$5:$H$1000,$U$5:$U$1000,ROW(),$V$5:$V$1000,"Sub")>1.0001),"Las subactividades suman más de 100%"&" · ","")&IF(AND(N($W16)>0,OR(IF(ISNUMBER($I16),ROUND($I16,6)<>ROUND(MIN(1,SUMIFS($AD$5:$AD$1000,$U$5:$U$1000,ROW(),$V$5:$V$1000,"Sub")),6),FALSE),IF(ISNUMBER($J16),ROUND($J16,6)<>ROUND(MIN(1,SUMIFS($AE$5:$AE$1000,$U$5:$U$1000,ROW(),$V$5:$V$1000,"Sub")),6),FALSE),IF(ISNUMBER($K16),ROUND($K16,6)<>ROUND(MIN(1,SUMIFS($AF$5:$AF$1000,$U$5:$U$1000,ROW(),$V$5:$V$1000,"Sub")),6),FALSE),IF(ISNUMBER($L16),ROUND($L16,6)<>ROUND(MIN(1,SUMIFS($AG$5:$AG$1000,$U$5:$U$1000,ROW(),$V$5:$V$1000,"Sub")),6),FALSE))),"Con subactividades: no escriba en las semanas (se llenan solas)"&" · ","")&IF((COUNTIF($I16:$L16,">1")+COUNTIF($I16:$L16,"<0")+SUMPRODUCT((LEN($I16:$L16)>0)*NOT(ISNUMBER($I16:$L16))))>0,"Avance fuera de rango 0-100%"&" · ","")&IF(OR(AND(ISNUMBER($J16),$J16<N($I16)),AND(ISNUMBER($K16),$K16<MAX($I16:$J16)),AND(ISNUMBER($L16),$L16<MAX($I16:$K16))),"Avance semanal decreciente"&" · ","")&IF(AND(ISNUMBER($AS16),$AS16<FechaRef,IF($V16="Sub",1,N($M16))<1),"Vencida"&" · ","")&IF(AND(ObsObligatoria="Sí",ISNUMBER($AS16),$AS16<FechaRef,IF($V16="Sub",1,N($M16))<1,$Q16=""),"Vencida sin observación"&" · ",""))="","✔ OK","⚠ "&LEFT(IF($C16="","Falta el nombre de la actividad"&" · ","")&IF(AND($V16="Sub",N($U16)=0),"Subactividad sin macroactividad arriba"&" · ","")&IF(AND($V16="Macro",$AR16=""),"Sin fecha de inicio"&" · ","")&IF(AND($V16="Macro",$AS16=""),"Sin fecha límite"&" · ","")&IF(AND(LEFT($C16,11)="[Jefatura] ",N($AQ16)=0),"No se encuentra en la hoja de la jefatura (elíjala de nuevo en la lista)"&" · ","")&IF(OR(AND($E16<>"",NOT(ISNUMBER($E16))),AND($F16<>"",NOT(ISNUMBER($F16))),AND($G16<>"",NOT(ISNUMBER($G16)))),"Fecha no válida"&" · ","")&IF(AND(ISNUMBER($AR16),ISNUMBER($AS16),$AR16>$AS16),"Inicio posterior a fecha límite"&" · ","")&IF(AND($V16="Macro",$H16<>"",OR(NOT(ISNUMBER($H16)),$H16<0,$H16>1)),"Peso fuera de rango"&" · ","")&IF(AND($V16="Sub",$H16<>"",OR(NOT(ISNUMBER($H16)),$H16<0,$H16>1)),"% de la subactividad fuera de rango 0-100%"&" · ","")&IF(AND(N($W16)>0,SUMIFS($H$5:$H$1000,$U$5:$U$1000,ROW(),$V$5:$V$1000,"Sub")>1.0001),"Las subactividades suman más de 100%"&" · ","")&IF(AND(N($W16)>0,OR(IF(ISNUMBER($I16),ROUND($I16,6)<>ROUND(MIN(1,SUMIFS($AD$5:$AD$1000,$U$5:$U$1000,ROW(),$V$5:$V$1000,"Sub")),6),FALSE),IF(ISNUMBER($J16),ROUND($J16,6)<>ROUND(MIN(1,SUMIFS($AE$5:$AE$1000,$U$5:$U$1000,ROW(),$V$5:$V$1000,"Sub")),6),FALSE),IF(ISNUMBER($K16),ROUND($K16,6)<>ROUND(MIN(1,SUMIFS($AF$5:$AF$1000,$U$5:$U$1000,ROW(),$V$5:$V$1000,"Sub")),6),FALSE),IF(ISNUMBER($L16),ROUND($L16,6)<>ROUND(MIN(1,SUMIFS($AG$5:$AG$1000,$U$5:$U$1000,ROW(),$V$5:$V$1000,"Sub")),6),FALSE))),"Con subactividades: no escriba en las semanas (se llenan solas)"&" · ","")&IF((COUNTIF($I16:$L16,">1")+COUNTIF($I16:$L16,"<0")+SUMPRODUCT((LEN($I16:$L16)>0)*NOT(ISNUMBER($I16:$L16))))>0,"Avance fuera de rango 0-100%"&" · ","")&IF(OR(AND(ISNUMBER($J16),$J16<N($I16)),AND(ISNUMBER($K16),$K16<MAX($I16:$J16)),AND(ISNUMBER($L16),$L16<MAX($I16:$K16))),"Avance semanal decreciente"&" · ","")&IF(AND(ISNUMBER($AS16),$AS16<FechaRef,IF($V16="Sub",1,N($M16))<1),"Vencida"&" · ","")&IF(AND(ObsObligatoria="Sí",ISNUMBER($AS16),$AS16<FechaRef,IF($V16="Sub",1,N($M16))<1,$Q16=""),"Vencida sin observación"&" · ",""),LEN(IF($C16="","Falta el nombre de la actividad"&" · ","")&IF(AND($V16="Sub",N($U16)=0),"Subactividad sin macroactividad arriba"&" · ","")&IF(AND($V16="Macro",$AR16=""),"Sin fecha de inicio"&" · ","")&IF(AND($V16="Macro",$AS16=""),"Sin fecha límite"&" · ","")&IF(AND(LEFT($C16,11)="[Jefatura] ",N($AQ16)=0),"No se encuentra en la hoja de la jefatura (elíjala de nuevo en la lista)"&" · ","")&IF(OR(AND($E16<>"",NOT(ISNUMBER($E16))),AND($F16<>"",NOT(ISNUMBER($F16))),AND($G16<>"",NOT(ISNUMBER($G16)))),"Fecha no válida"&" · ","")&IF(AND(ISNUMBER($AR16),ISNUMBER($AS16),$AR16>$AS16),"Inicio posterior a fecha límite"&" · ","")&IF(AND($V16="Macro",$H16<>"",OR(NOT(ISNUMBER($H16)),$H16<0,$H16>1)),"Peso fuera de rango"&" · ","")&IF(AND($V16="Sub",$H16<>"",OR(NOT(ISNUMBER($H16)),$H16<0,$H16>1)),"% de la subactividad fuera de rango 0-100%"&" · ","")&IF(AND(N($W16)>0,SUMIFS($H$5:$H$1000,$U$5:$U$1000,ROW(),$V$5:$V$1000,"Sub")>1.0001),"Las subactividades suman más de 100%"&" · ","")&IF(AND(N($W16)>0,OR(IF(ISNUMBER($I16),ROUND($I16,6)<>ROUND(MIN(1,SUMIFS($AD$5:$AD$1000,$U$5:$U$1000,ROW(),$V$5:$V$1000,"Sub")),6),FALSE),IF(ISNUMBER($J16),ROUND($J16,6)<>ROUND(MIN(1,SUMIFS($AE$5:$AE$1000,$U$5:$U$1000,ROW(),$V$5:$V$1000,"Sub")),6),FALSE),IF(ISNUMBER($K16),ROUND($K16,6)<>ROUND(MIN(1,SUMIFS($AF$5:$AF$1000,$U$5:$U$1000,ROW(),$V$5:$V$1000,"Sub")),6),FALSE),IF(ISNUMBER($L16),ROUND($L16,6)<>ROUND(MIN(1,SUMIFS($AG$5:$AG$1000,$U$5:$U$1000,ROW(),$V$5:$V$1000,"Sub")),6),FALSE))),"Con subactividades: no escriba en las semanas (se llenan solas)"&" · ","")&IF((COUNTIF($I16:$L16,">1")+COUNTIF($I16:$L16,"<0")+SUMPRODUCT((LEN($I16:$L16)>0)*NOT(ISNUMBER($I16:$L16))))>0,"Avance fuera de rango 0-100%"&" · ","")&IF(OR(AND(ISNUMBER($J16),$J16<N($I16)),AND(ISNUMBER($K16),$K16<MAX($I16:$J16)),AND(ISNUMBER($L16),$L16<MAX($I16:$K16))),"Avance semanal decreciente"&" · ","")&IF(AND(ISNUMBER($AS16),$AS16<FechaRef,IF($V16="Sub",1,N($M16))<1),"Vencida"&" · ","")&IF(AND(ObsObligatoria="Sí",ISNUMBER($AS16),$AS16<FechaRef,IF($V16="Sub",1,N($M16))<1,$Q16=""),"Vencida sin observación"&" · ",""))-3))) | S16: =IF(NOT((COUNTA($B16:$D16)+COUNTA($G16:$H16)+COUNTA($Q16))>0),"",IF(AND($V16="Sub",N($U16)>0),IF(ISNUMBER(INDEX($AR$5:$AR$1000,$U16-4)),DATE(YEAR(INDEX($AR$5:$AR$1000,$U16-4)),MONTH(INDEX($AR$5:$AR$1000,$U16-4)),1),IF(ISNUMBER(INDEX($AS$5:$AS$1000,$U16-4)),DATE(YEAR(INDEX($AS$5:$AS$1000,$U16-4)),MONTH(INDEX($AS$5:$AS$1000,$U16-4)),1),MesCiclo)),IF(ISNUMBER($AR16),DATE(YEAR($AR16),MONTH($AR16),1),IF(ISNUMBER($AS16),DATE(YEAR($AS16),MONTH($AS16),1),MesCiclo)))) | T16: =IF(OR($S16="",$S16<>MesCiclo,$V16<>"Macro"),"",COUNTIFS($S$5:$S16,MesCiclo,$V$5:$V16,"Macro")) | U16: =IF($V16="","",IF($V16="Macro",ROW(),IFERROR(LOOKUP(2,1/($V$5:$V16="Macro"),ROW($V$5:$V16)),0))) | V16: =IF(NOT((COUNTA($B16:$D16)+COUNTA($G16:$H16)+COUNTA($Q16))>0),"",IF($B16="Subactividad","Sub","Macro")) | W16: =IF($V16="Macro",COUNTIFS($U$5:$U$1000,ROW(),$V$5:$V$1000,"Sub"),"") | X16: =IF($V16<>"Sub","",IF(AND(ISNUMBER($H16),N($H16)>0),$H16,IFERROR(MAX(0,1-SUMIFS($H$5:$H$1000,$U$5:$U$1000,$U16,$V$5:$V$1000,"Sub"))/(COUNTIFS($U$5:$U$1000,$U16,$V$5:$V$1000,"Sub")-COUNTIFS($U$5:$U$1000,$U16,$V$5:$V$1000,"Sub",$H$5:$H$1000,">0")),0))) | Y16: =IF($V16="","",IF($V16="Sub",N($X16)*IF(ISNUMBER($G16),1,MIN(1,MAX(0,IFERROR(LOOKUP(2,1/ISNUMBER($I16:$L16),$I16:$L16),0)))),IF(ISNUMBER($G16),1,IFERROR(LOOKUP(2,1/($I16:$L16<>""),$I16:$L16),0)))) | Z16: =IF($V16="","",IF(AND(ISNUMBER($G16),$G16<=IF($S16=MesCiclo,InicioCiclo,$S16+MOD(2-WEEKDAY($S16),7))+6),1,IF(ISNUMBER($I16),$I16,0))) | AA16: =IF($V16="","",IF(AND(ISNUMBER($G16),$G16<=IF($S16=MesCiclo,InicioCiclo,$S16+MOD(2-WEEKDAY($S16),7))+13),1,IF(ISNUMBER($J16),$J16,$Z16))) | AB16: =IF($V16="","",IF(AND(ISNUMBER($G16),$G16<=IF($S16=MesCiclo,InicioCiclo,$S16+MOD(2-WEEKDAY($S16),7))+20),1,IF(ISNUMBER($K16),$K16,$AA16))) | AC16: =IF($V16="","",IF(AND(ISNUMBER($G16),$G16<=IF($S16=MesCiclo,InicioCiclo,$S16+MOD(2-WEEKDAY($S16),7))+27),1,IF(ISNUMBER($L16),$L16,$AB16))) | AD16: =IF($V16<>"Sub","",N($X16)*IF(AND(ISNUMBER($G16),$G16<=IF($S16=MesCiclo,InicioCiclo,$S16+MOD(2-WEEKDAY($S16),7))+6),1,MIN(1,MAX(0,IF(ISNUMBER(OFFSET($A$1,ROW()-1,8)),OFFSET($A$1,ROW()-1,8),0))))) | AE16: =IF($V16<>"Sub","",N($X16)*IF(AND(ISNUMBER($G16),$G16<=IF($S16=MesCiclo,InicioCiclo,$S16+MOD(2-WEEKDAY($S16),7))+13),1,MIN(1,MAX(0,IF(ISNUMBER(OFFSET($A$1,ROW()-1,9)),OFFSET($A$1,ROW()-1,9),IF(ISNUMBER(OFFSET($A$1,ROW()-1,8)),OFFSET($A$1,ROW()-1,8),0)))))) | AF16: =IF($V16<>"Sub","",N($X16)*IF(AND(ISNUMBER($G16),$G16<=IF($S16=MesCiclo,InicioCiclo,$S16+MOD(2-WEEKDAY($S16),7))+20),1,MIN(1,MAX(0,IF(ISNUMBER(OFFSET($A$1,ROW()-1,10)),OFFSET($A$1,ROW()-1,10),IF(ISNUMBER(OFFSET($A$1,ROW()-1,9)),OFFSET($A$1,ROW()-1,9),IF(ISNUMBER(OFFSET($A$1,ROW()-1,8)),OFFSET($A$1,ROW()-1,8),0))))))) | AG16: =IF($V16<>"Sub","",N($X16)*IF(AND(ISNUMBER($G16),$G16<=IF($S16=MesCiclo,InicioCiclo,$S16+MOD(2-WEEKDAY($S16),7))+27),1,MIN(1,MAX(0,IF(ISNUMBER(OFFSET($A$1,ROW()-1,11)),OFFSET($A$1,ROW()-1,11),IF(ISNUMBER(OFFSET($A$1,ROW()-1,10)),OFFSET($A$1,ROW()-1,10),IF(ISNUMBER(OFFSET($A$1,ROW()-1,9)),OFFSET($A$1,ROW()-1,9),IF(ISNUMBER(OFFSET($A$1,ROW()-1,8)),OFFSET($A$1,ROW()-1,8),0)))))))) | AH16: =IF($V16="","",IF(AND(ISNUMBER($G16),$G16<=IF($S16=MesCiclo,InicioCiclo,$S16+MOD(2-WEEKDAY($S16),7))+6),1,IF(N($W16)>0,MIN(1,SUMIFS($AD$5:$AD$1000,$U$5:$U$1000,ROW(),$V$5:$V$1000,"Sub")),$Z16))) | AI16: =IF($V16="","",IF(AND(ISNUMBER($G16),$G16<=IF($S16=MesCiclo,InicioCiclo,$S16+MOD(2-WEEKDAY($S16),7))+13),1,IF(N($W16)>0,MIN(1,SUMIFS($AE$5:$AE$1000,$U$5:$U$1000,ROW(),$V$5:$V$1000,"Sub")),$AA16))) | AJ16: =IF($V16="","",IF(AND(ISNUMBER($G16),$G16<=IF($S16=MesCiclo,InicioCiclo,$S16+MOD(2-WEEKDAY($S16),7))+20),1,IF(N($W16)>0,MIN(1,SUMIFS($AF$5:$AF$1000,$U$5:$U$1000,ROW(),$V$5:$V$1000,"Sub")),$AB16))) | AK16: =IF($V16="","",IF(AND(ISNUMBER($G16),$G16<=IF($S16=MesCiclo,InicioCiclo,$S16+MOD(2-WEEKDAY($S16),7))+27),1,IF(N($W16)>0,MIN(1,SUMIFS($AG$5:$AG$1000,$U$5:$U$1000,ROW(),$V$5:$V$1000,"Sub")),$AC16))) | AL16: =IF($V16<>"Macro","",IF(COUNTIFS($S$5:$S$1000,$S16,$V$5:$V$1000,"Macro",$H$5:$H$1000,">0")=0,1/COUNTIFS($S$5:$S$1000,$S16,$V$5:$V$1000,"Macro"),IF(AND(ISNUMBER($H16),N($H16)>0),$H16,SUMIFS($H$5:$H$1000,$S$5:$S$1000,$S16,$V$5:$V$1000,"Macro")/COUNTIFS($S$5:$S$1000,$S16,$V$5:$V$1000,"Macro",$H$5:$H$1000,">0"))/(COUNTIFS($S$5:$S$1000,$S16,$V$5:$V$1000,"Macro")*SUMIFS($H$5:$H$1000,$S$5:$S$1000,$S16,$V$5:$V$1000,"Macro")/COUNTIFS($S$5:$S$1000,$S16,$V$5:$V$1000,"Macro",$H$5:$H$1000,">0")))) | AM16: =IF(NOT(AND($D16<>"",$V16="Macro")),"",IFERROR(CHOOSE(MATCH($D16,ListaPuestos,0),MATCH("[Jefatura] "&$C16,'Cronograma R. Operacional'!$C$5:$C$1000,0),MATCH("[Jefatura] "&$C16,'Cronograma R. Normativo'!$C$5:$C$1000,0),MATCH("[Jefatura] "&$C16,'Cronograma R. Financiero'!$C$5:$C$1000,0),MATCH("[Jefatura] "&$C16,'Cronograma Asistente Técnico'!$C$5:$C$1000,0)),0)) | AN16: =IF(AND(AND($D16<>"",$V16="Macro"),$S16=MesCiclo),COUNTIFS($D$5:$D16,$D16,$S$5:$S16,MesCiclo,$V$5:$V16,"Macro"),"") | AO16: =IF($AN16="","",$D16&"|"&$AN16) | AP16: =IF(AND($D16<>"",$V16="Macro"),$D16&"|"&$C16,"") | AQ16: ="" | AR16: =IF(N($AQ16)>0,INDEX(rIni_ADM,$AQ16),IF(ISNUMBER($E16),$E16,"")) | AS16: =IF(N($AQ16)>0,INDEX(rLim_ADM,$AQ16),IF(ISNUMBER($F16),$F16,""))
