Workbook

Sheet Instrucciones
B1: CÓMO ACTUALIZAR ESTE ARCHIVO
B3: 1. AGREGAR UN COLABORADOR (hoja 'Base Oficial')
B4: • | C4: Escriba en la primera fila vacía: Código, Nombre, Fecha de ingreso, Cargo, Grupo SSF, Departamento y Gerencia.
B5: • | C5: Departamento y Gerencia: elíjalos de la lista desplegable para que se escriban igual que los existentes.
B6: • | C6: Si es un departamento o gerencia NUEVO, escríbalo y confirme con 'Sí' en el aviso.
B7: • | C7: El colaborador aparece automáticamente como Pendiente (o Completado si ya tiene examen).
B9: 2. AGREGAR EXÁMENES (hoja 'Base Exámenes')
B10: • | C10: Pegue cada examen en la primera fila vacía, columnas A a E y G a H:
B11: • | C11: A Nombre · B Área · C Código de empleado · D Hora de inicio · E Hora de finalización · G Nota · H Correo.
B12: • | C12: NO escriba en la columna F (Duración): se calcula sola.
B13: • | C13: Desde la exportación de la plataforma: I = Nombre, L = Departamento, O = Código, B = Inicio, C = Fin, F = Total de puntos, D = Correo.
B14: • | C14: Si una persona hace el examen más de una vez, se cuenta su NOTA MÁS ALTA y queda registrado en 'Historial de Intentos'.
B16: 3. QUÉ SE ACTUALIZA SOLO
B17: • | C17: Detalle individual, Consolidado por área, Consolidado por Gerencia (incluye departamentos y gerencias nuevos).
B18: • | C18: Dashboard Gráfico, Dashboard Gerencial, Dashboard Departamentos y Estado por Colaborador.
B19: • | C19: Listado de Pendientes, Listado de Completados, Top 3 (todos) e Historial de Intentos.
B20: • | C20: Capacidad: hasta 996 colaboradores, 996 exámenes, 80 departamentos y 20 gerencias.
B22: 4. CAMBIAR UN DEPARTAMENTO DE GERENCIA
B23: • | C23: En 'Base Oficial' cambie la columna G (Gerencia) de TODAS las personas de ese departamento. Lo demás se ajusta solo.
B25: 5. IMPORTANTE
B26: • | C26: No borre ni escriba en las hojas de resultados (consolidados, listados, top 3, historial): son fórmulas.
B27: • | C27: La hoja oculta 'Cálculos' es necesaria para los dashboards: no la elimine.
B28: • | C28: Si agrega un departamento o gerencia NUEVO, las tablas se actualizan, pero los GRÁFICOS deben ampliarse:
B29: • | C29: aparecerá un aviso rojo en el dashboard. Envíe el archivo para actualizarlos.
B31: 6. SITUACIÓN ESPECIAL (vacaciones, incapacidad, maternidad, renuncia)
B32: • | C32: En 'Base Oficial', columna H, elija la situación de la persona. Déjela vacía si está activa.
B33: • | C33: Si no ha hecho el examen, aparece con esa situación y NO cuenta en el personal esperado ni en el %.
B34: • | C34: Si sí hizo el examen, cuenta como Completado normalmente.
B35: • | C35: La lista de estas personas está en 'Listado de Situación Especial'. Cuando regrese, borre la situación.

Sheet Base Oficial
A1: LISTADO OFICIAL DE COLABORADORES
A2: Base maestra de personal institucional
A4: Código | B4: Nombre del Colaborador | C4: Fecha Ingreso | D4: Cargo | E4: Grupo SSF | F4: Área / Departamento | G4: Gerencia Asignada | H4: Situación especial
A5: 977 | B5: NELSON ULISES CAMPOS FLORES | C5: 10/08/2026 | D5: GERENTE GENERAL | E5: GERENTE | F5: GERENCIA GENERAL | G5: Gerencia General
A6: 349 | B6: CARLA EUGENIA HERNANDEZ MENJIVAR | C6: 08/08/2005 | D6: GERENTE ADMINISTRATIVA | E6: GERENTE | F6: GERENCIA ADMINISTRATIVA | G6: Gerencia Administrativa
A7: 41 | B7: ROQUE RAFAEL REYES ESPINAL | C7: 25/04/1994 | D7: GERENTE DE OPERACIONES | E7: GERENTE | F7: GERENCIA DE OPERACIONES | G7: Gerencia de Operaciones
A8: 524 | B8: JOSE AUGUSTO DE LA O GALLEGOS | C8: 01/04/2013 | D8: GERENTE DE FINANZAS Y PLANIFICACION | E8: GERENTE | F8: GERENCIA DE FINANZAS Y PLANIFICACIÓN | G8: Gerencia de Finanzas y Planificación
A9: 878 | B9: ALEX VIRGILIO AGUILAR ARIAS | C9: 01/07/2024 | D9: GERENTE DE SISTEMAS | E9: GERENTE | F9: GERENCIA DE SISTEMAS | G9: Gerencia de Sistemas
A10: 862 | B10: GEORGI ROBERTO CASTILLO CHACON | C10: 01/04/2024 | D10: GERENTE DE OFICIALIA DE CUMPLIMIENTO | E10: GERENTE | F10: OFICIALIA DE CUMPLIMIENTO | G10: Gerencia de Oficialía de Cumplimiento
A11: 741 | B11: JOSE HUMBERTO BARILLAS BURGOS | C11: 16/03/2022 | D11: GERENTE DE NEGOCIOS | E11: GERENTE | F11: GERENCIA DE NEGOCIOS | G11: Gerencia de Negocios
A12: 570 | B12: ANDREA VICTORIA MAYORGA RODRIGUEZ | C12: 22/07/2016 | D12: GERENTE LEGAL Y DE CUMPLIMIENTO NORMATIVO | E12: GERENTE | F12: GERENCIA LEGAL Y DE CUMPLIMIENTO NORMATIVO | G12: Gerencia Legal y Cumplimiento Normativo
A13: 17 | B13: ANTONIA SARAI BELTRAN CARBALLO | C13: 04/04/1994 | D13: ASISTENTE ADMINISTRATIVO DE GERENCIA GENERAL | E13: EMPLEADO | F13: GERENCIA GENERAL | G13: Gerencia General
A14: 290 | B14: MELVIN ENRIQUE PORTILLO VALLE | C14: 24/07/2002 | D14: ANALISTA DE RIESGOS FINANCIEROS | E14: EMPLEADO | F14: ADMINISTRACION DE RIESGOS | G14: Gerencia General
A15: 408 | B15: SARA PATRICIA GONZALEZ JIMENEZ | C15: 02/07/2007 | D15: ASISTENTE TECNICO DE RIESGOS | E15: EMPLEADO | F15: ADMINISTRACION DE RIESGOS | G15: Gerencia General
A16: 433 | B16: SILVIA IVETH MARTINEZ RAMIREZ | C16: 01/08/2008 | D16: ANALISTA DE RIESGO OPERACIONAL | E16: EMPLEADO | F16: ADMINISTRACION DE RIESGOS | G16: Gerencia General
... A48: 973 | B48: HUGO ROLANDO VELASCO RIVERA | C48: 02/07/2026 | D48: AUXILIAR DE CUSTODIA DE VALORES | E48: EMPLEADO | F48: DEPARTAMENTO DE CUSTODIA DE GARANTÍA Y VALORES | G48: Gerencia Administrativa
A49: 65 | B49: DORA ALICIA CASTILLO | C49: 16/08/1988 | D49: JEFE DE TALENTO HUMANO | E49: EMPLEADO | F49: DEPARTAMENTO DE TALENTO HUMANO | G49: Gerencia Administrativa | H49: Vacaciones
A50: 948 | B50: NELSON KILDER QUIJADA ECHEVERRIA | C50: 20/10/2025 | D50: ASISTENTE TECNICO DE TALENTO HUMANO | E50: EMPLEADO | F50: DEPARTAMENTO DE TALENTO HUMANO | G50: Gerencia Administrativa
A51: 962 | B51: HELEN GLORIBEL PLATERO SANCHEZ | C51: 08/04/2026 | D51: ANALISTA DE DESARROLLO ORGANIZACIONAL | E51: EMPLEADO | F51: DEPARTAMENTO DE TALENTO HUMANO | G51: Gerencia Administrativa
A52: 452 | B52: SERGIO ARTURO CALDERON SALAZAR | C52: 11/01/2010 | D52: COORDINADOR DE SEGURIDAD | E52: EMPLEADO | F52: DEPARTAMENTO DE SEGURIDAD | G52: Gerencia Administrativa
A53: 901 | B53: CARLOS ALEJANDRO MARAVILLA MENDEZ | C53: 14/10/2024 | D53: OPERADOR DE MONITOREO DE LOS SISTEMAS DE SEGURIDAD | E53: EMPLEADO | F53: DEPARTAMENTO DE SEGURIDAD | G53: Gerencia Administrativa
A54: 590 | B54: LORENA ELIZABETH GALDAMEZ NUÑEZ | C54: 23/03/2017 | D54: MEDICO | E54: EMPLEADO | F54: CLINICA EMPRESARIAL | G54: Gerencia Administrativa
A55: 609 | B55: GLADIS OSIRIS VALLE HERNANDEZ | C55: 02/01/2018 | D55: ENFERMERA | E55: EMPLEADO | F55: CLINICA EMPRESARIAL | G55: Gerencia Administrativa
A56: 847 | B56: ZULEYMA ALEJANDRA VASQUEZ MARIN | C56: 18/12/2023 | D56: JEFE DE EDUCACION Y RESPONSABILIDAD SOCIAL | E56: EMPLEADO | F56: DEPARTAMENTO DE EDUCACION Y RESPONSABILIDAD SOCIAL | G56: Gerencia Administrativa
A57: 853 | B57: STEPHANIE CAROLINA MALDONADO FLORES | C57: 05/02/2024 | D57: ASISTENTE TECNICO DEPARTAMENTO DE EDUCACION Y RESPONSABILIDA | E57: EMPLEADO | F57: DEPARTAMENTO DE EDUCACION Y RESPONSABILIDAD SOCIAL | G57: Gerencia Administrativa
A58: 919 | B58: CARLOS EDUARDO SERVELLON PEREZ | C58: 23/04/2025 | D58: AUXILIAR DE EDUCACION Y RESPONSABILIDAD SOCIAL | E58: EMPLEADO | F58: DEPARTAMENTO DE EDUCACION Y RESPONSABILIDAD SOCIAL | G58: Gerencia Administrativa
A59: 34 | B59: YENIS MARILU ESCOBAR SORTO | C59: 06/05/1996 | D59: EJECUTIVO DE SOLUCIONES FINANCIERAS | E59: EMPLEADO | F59: DEPARTAMENTO DE SOLUCIONES FINANCIERAS | G59: Gerencia de Operaciones
A60: 182 | B60: ROSA ELIZABETH RIVAS AGUILUZ | C60: 20/05/1999 | D60: EJECUTIVO DE SOLUCIONES FINANCIERAS | E60: EMPLEADO | F60: DEPARTAMENTO DE SOLUCIONES FINANCIERAS | G60: Gerencia de Operaciones
A61: 263 | B61: XOCHILT VERONICA NOUBLEAU | C61: 27/08/2001 | D61: EJECUTIVO DE SOLUCIONES FINANCIERAS | E61: EMPLEADO | F61: DEPARTAMENTO DE SOLUCIONES FINANCIERAS | G61: Gerencia de Operaciones
... A67: 573 | B67: JUAN PABLO HENRIQUEZ RAMIREZ | C67: 01/09/2016 | D67: EJECUTIVO DE SOLUCIONES FINANCIERAS | E67: EMPLEADO | F67: DEPARTAMENTO DE SOLUCIONES FINANCIERAS | G67: Gerencia de Operaciones
A68: 885 | B68: ALBA BEATRIZ MELENDEZ PRUDENCIO | C68: 19/08/2024 | D68: ASISTENTE DE RECUPERACION JUDICIAL Y CARTERA CASTIGADA | E68: EMPLEADO | F68: DEPARTAMENTO DE SOLUCIONES FINANCIERAS | G68: Gerencia de Operaciones | H68: Renuncia
A69: 389 | B69: CLAUDIA CAROLINA HERNANDEZ DE PAZ | C69: 27/10/2006 | D69: ASISTENTE TECNICO DE INTERCAMBIO DE TARJETAS | E69: EMPLEADO | F69: DEPARTAMENTO DE TARJETA DE CREDITO Y DEBITO | G69: Gerencia de Operaciones
A70: 399 | B70: GEOVANNI LIZAMA PORTILLO | C70: 22/02/2007 | D70: JEFE DE TARJETA DE CREDITO Y DEBITO | E70: EMPLEADO | F70: DEPARTAMENTO DE TARJETA DE CREDITO Y DEBITO | G70: Gerencia de Operaciones | H70: Incapacidad
A71: 459 | B71: LUIS ALEXANDER RAMIREZ MONTALVO | C71: 24/05/2010 | D71: ASISTENTE TECNICO DE EMISION DE TARJETA | E71: EMPLEADO | F71: DEPARTAMENTO DE TARJETA DE CREDITO Y DEBITO | G71: Gerencia de Operaciones
A72: 725 | B72: ANA BEATRIZ QUINTEROS AVELAR | C72: 09/08/2021 | D72: ASISTENTE TECNICO DE OPERACIONES DE TARJETAS | E72: EMPLEADO | F72: DEPARTAMENTO DE TARJETA DE CREDITO Y DEBITO | G72: Gerencia de Operaciones
A73: 952 | B73: ANDREA CAROLINA RUMUALDO MARTINEZ | C73: 16/12/2025 | D73: AUXILIAR DE CONTROL DE CALIDAD | E73: EMPLEADO | F73: DEPARTAMENTO DE TARJETA DE CREDITO Y DEBITO | G73: Gerencia de Operaciones
A74: 980 | B74: FATIMA ELIZABETH LEMUS RODRIGUEZ | C74: 26/08/2026 | D74: AUXILIAR DE EMISION DE TARJETA | E74: EMPLEADO | F74: DEPARTAMENTO DE TARJETA DE CREDITO Y DEBITO | G74: Gerencia de Operaciones
A75: 284 | B75: MARIO ANTONIO NAVARRO PINEDA | C75: 05/05/2008 | D75: JEFE DE DEPOSITOS | E75: EMPLEADO | F75: DEPARTAMENTO DE DEPOSITOS | G75: Gerencia de Operaciones
A76: 632 | B76: LUCILA MARGARITA CORCIO QUINTANILLA | C76: 19/11/2018 | D76: ASISTENTE COMPENSADOR DE CHEQUES | E76: EMPLEADO | F76: DEPARTAMENTO DE DEPOSITOS | G76: Gerencia de Operaciones
A77: 773 | B77: HELLEN ESTEFANI RODRIGUEZ GARCIA | C77: 19/09/2022 | D77: ASISTENTE COMPENSADOR DE CHEQUES | E77: EMPLEADO | F77: DEPARTAMENTO DE DEPOSITOS | G77: Gerencia de Operaciones
A78: 787 | B78: WALTER OSWALDO SANCHEZ RIVAS | C78: 16/11/2022 | D78: ASISTENTE COMPENSADOR DE CHEQUES | E78: EMPLEADO | F78: DEPARTAMENTO DE DEPOSITOS | G78: Gerencia de Operaciones
A79: 16 | B79: YANETH MARLENY LANDAVERDE MORALES | C79: 16/09/1992 | D79: JEFE DE ADMINISTRACION DE CARTERA | E79: EMPLEADO | F79: ADMINISTRACIÓN DE CARTERAS | G79: Gerencia de Operaciones
A80: 477 | B80: GEMA YESENIA VILLALOBOS HERNANDEZ | C80: 05/09/2011 | D80: ANALISTA DE CARTERAS | E80: EMPLEADO | F80: ADMINISTRACIÓN DE CARTERAS | G80: Gerencia de Operaciones
A81: 572 | B81: PAMELA GIOVANNA AGUILAR SERBELLON | C81: 01/09/2016 | D81: GESTOR DE COBROS Y PAGOS DE SEGUROS | E81: EMPLEADO | F81: ADMINISTRACIÓN DE CARTERAS | G81: Gerencia de Operaciones
A82: 732 | B82: RICARDO JOSUE CACAO ROVELO | C82: 03/11/2021 | D82: ANALISTA DE CARTERAS | E82: EMPLEADO | F82: ADMINISTRACIÓN DE CARTERAS | G82: Gerencia de Operaciones
... A103: 883 | B103: ISMAEL HUMBERTO GUERRERO FLORES | C103: 15/07/2024 | D103: ADMINISTRADOR DE SEGURIDAD INFORMATICA | E103: EMPLEADO | F103: GERENCIA DE SISTEMAS | G103: Gerencia de Sistemas
A104: 90 | B104: HUGO MARVIN SERRANO SARAVIA | C104: 22/04/1996 | D104: OPERADOR DE SISTEMAS | E104: EMPLEADO | F104: DEPARTAMENTO DE OPERACIONES Y SOPORTE TECNICO | G104: Gerencia de Sistemas | H104: Vacaciones
A105: 119 | B105: JUAN JOSE LOPEZ ALFARO | C105: 06/03/1997 | D105: OPERADOR DE SISTEMAS | E105: EMPLEADO | F105: DEPARTAMENTO DE OPERACIONES Y SOPORTE TECNICO | G105: Gerencia de Sistemas
A106: 221 | B106: CARLOS ORLANDO GARCIA VELASQUEZ | C106: 02/10/2000 | D106: TECNICO EN SOPORTE | E106: EMPLEADO | F106: DEPARTAMENTO DE OPERACIONES Y SOPORTE TECNICO | G106: Gerencia de Sistemas
A107: 259 | B107: EDGAR MARGARITO POZO SHUPAN | C107: 17/08/2001 | D107: TECNICO EN SOPORTE | E107: EMPLEADO | F107: DEPARTAMENTO DE OPERACIONES Y SOPORTE TECNICO | G107: Gerencia de Sistemas
A108: 281 | B108: CARLOS ALFONSO MOLINA CARDONA | C108: 05/03/2002 | D108: OPERADOR DE SISTEMAS | E108: EMPLEADO | F108: DEPARTAMENTO DE OPERACIONES Y SOPORTE TECNICO | G108: Gerencia de Sistemas
A109: 490 | B109: JULIO ADOLFO MOLINA ARRIOLA | C109: 04/07/2012 | D109: OPERADOR DE SISTEMAS | E109: EMPLEADO | F109: DEPARTAMENTO DE OPERACIONES Y SOPORTE TECNICO | G109: Gerencia de Sistemas
A110: 880 | B110: JORGE ALBERTO BARRERA | C110: 01/07/2024 | D110: JEFE DE OPERACIONES Y SOPORTE TECNICO | E110: EMPLEADO | F110: DEPARTAMENTO DE OPERACIONES Y SOPORTE TECNICO | G110: Gerencia de Sistemas
A111: 239 | B111: CELINA MARGARITA GUTIERREZ RODRIGUEZ | C111: 13/08/2018 | D111: ANALISTA PROGRAMADOR SENIOR | E111: EMPLEADO | F111: DEPARTAMENTO DE ANALISIS Y PROGRAMACIÓN | G111: Gerencia de Sistemas
A112: 320 | B112: HILDA MARGARITA ABREGO BRAN | C112: 13/12/2004 | D112: ANALISTA QA | E112: EMPLEADO | F112: DEPARTAMENTO DE ANALISIS Y PROGRAMACIÓN | G112: Gerencia de Sistemas
A113: 410 | B113: CLAUDIA MARGARITA CAMPOS GONZÁLEZ | C113: 19/08/2022 | D113: JEFE DE ANALISIS Y PROGRAMACION | E113: EMPLEADO | F113: DEPARTAMENTO DE ANALISIS Y PROGRAMACIÓN | G113: Gerencia de Sistemas
A114: 474 | B114: GLADIS EVELIN CASTILLO TORRES | C114: 24/05/2011 | D114: ANALISTA PROGRAMADOR SENIOR | E114: EMPLEADO | F114: DEPARTAMENTO DE ANALISIS Y PROGRAMACIÓN | G114: Gerencia de Sistemas
A115: 680 | B115: CARLOS FRANCISCO HERNANDEZ MUÑOZ | C115: 24/03/2020 | D115: ANALISTA QA | E115: EMPLEADO | F115: DEPARTAMENTO DE ANALISIS Y PROGRAMACIÓN | G115: Gerencia de Sistemas
A116: 752 | B116: JEAN HARRY MIRANDA ARAUJO | C116: 01/06/2022 | D116: ANALISTA PROGRAMADOR | E116: EMPLEADO | F116: DEPARTAMENTO DE ANALISIS Y PROGRAMACIÓN | G116: Gerencia de Sistemas
... A171: 793 | B171: KRIZIA BETSABE FLORES MARTINEZ | C171: 05/12/2022 | D171: JEFE DE SEGUROS | E171: EMPLEADO | F171: DEPARTAMENTO DE SEGUROS | G171: Gerencia de Negocios
A172: 802 | B172: ERIKA VANESSA ALEMAN MIJANGO | C172: 16/03/2023 | D172: EJECUTIVO DE VENTA DE SEGUROS | E172: EMPLEADO | F172: DEPARTAMENTO DE SEGUROS | G172: Gerencia de Negocios | H172: Renuncia
A173: 805 | B173: JUANA HAZEL GARCIA COREAS | C173: 17/04/2023 | D173: EJECUTIVO DE VENTA DE SEGUROS | E173: EMPLEADO | F173: DEPARTAMENTO DE SEGUROS | G173: Gerencia de Negocios
A174: 869 | B174: JENNIFER BETSABE MARAVILLA MORENO | C174: 22/04/2024 | D174: EJECUTIVO DE VENTA DE SEGUROS | E174: EMPLEADO | F174: DEPARTAMENTO DE SEGUROS | G174: Gerencia de Negocios
A175: 894 | B175: HENRY OSWALDO PINEDA GARCIA | C175: 23/09/2024 | D175: EJECUTIVO MOVIL DE SEGUROS | E175: EMPLEADO | F175: DEPARTAMENTO DE SEGUROS | G175: Gerencia de Negocios
A176: 422 | B176: CLAUDIA VERONICA LARA RODAS | C176: 29/01/2008 | D176: ASISTENTE COMERCIAL DE TARJETA DE CREDITO | E176: EMPLEADO | F176: DEPARTAMENTO COMERCIAL DE TARJETA DE CREDITO Y DEBITO | G176: Gerencia de Negocios
A177: 533 | B177: LIDIA PATRICIA MORALES AVALOS | C177: 12/05/2014 | D177: JEFE COMERCIAL DE TARJETA DE CREDITO | E177: EMPLEADO | F177: DEPARTAMENTO COMERCIAL DE TARJETA DE CREDITO Y DEBITO | G177: Gerencia de Negocios
A178: 654 | B178: GABRIELA ALEJANDRA RODRIGUEZ ARIAS | C178: 24/06/2019 | D178: AUXILIAR DE ATENCION AL CLIENTE | E178: EMPLEADO | F178: DEPARTAMENTO COMERCIAL DE TARJETA DE CREDITO Y DEBITO | G178: Gerencia de Negocios
A179: 655 | B179: JOSE ALEXANDER ABREGO | C179: 04/07/2019 | D179: EJECUTIVO DE NEGOCIOS | E179: EMPLEADO | F179: DEPARTAMENTO COMERCIAL DE TARJETA DE CREDITO Y DEBITO | G179: Gerencia de Negocios
A180: 669 | B180: ANTONIO ALEXANDER ALFARO ARGUETA | C180: 21/10/2019 | D180: EJECUTIVO DE NEGOCIOS | E180: EMPLEADO | F180: DEPARTAMENTO COMERCIAL DE TARJETA DE CREDITO Y DEBITO | G180: Gerencia de Negocios
A181: 715 | B181: KAREN MARCELA BARILLAS MOLINA | C181: 17/05/2021 | D181: AUXILIAR DE ATENCION AL TARJETAHABIENTE | E181: EMPLEADO | F181: DEPARTAMENTO COMERCIAL DE TARJETA DE CREDITO Y DEBITO | G181: Gerencia de Negocios
A182: 835 | B182: LUIS ALBERTO MEJIA DELGADO | C182: 02/03/2024 | D182: EJECUTIVO DE NEGOCIOS | E182: EMPLEADO | F182: DEPARTAMENTO COMERCIAL DE TARJETA DE CREDITO Y DEBITO | G182: Gerencia de Negocios | H182: Renuncia
A183: 858 | B183: GABRIEL FRANCISCO MOLINA DIAZ | C183: 18/03/2024 | D183: EJECUTIVO DE NEGOCIOS | E183: EMPLEADO | F183: DEPARTAMENTO COMERCIAL DE TARJETA DE CREDITO Y DEBITO | G183: Gerencia de Negocios
A184: 215 | B184: LUIS MARCELO CRUZ VIGIL | C184: 21/08/2000 | D184: SUB GERENTE DE CANALES | E184: EMPLEADO | F184: SUB GERENCIA DE CANALES | G184: Gerencia de Negocios
A185: 581 | B185: JUAN CARLOS AGUILAR ASCENCIO | C185: 01/11/2016 | D185: CAJERO MOVIL | E185: EMPLEADO | F185: SUB GERENCIA DE CANALES | G185: Gerencia de Negocios
A186: 585 | B186: NANCY ROCIO MENJIVAR RIVAS | C186: 02/01/2017 | D186: EJECUTIVO MOVIL DE SEGUROS | E186: EMPLEADO | F186: SUB GERENCIA DE CANALES | G186: Gerencia de Negocios
A187: 651 | B187: LUIS FERNANDO MORAN GARCIA | C187: 16/02/2026 | D187: JEFE MOVIL DE AGENCIAS | E187: EMPLEADO | F187: SUB GERENCIA DE CANALES | G187: Gerencia de Negocios
A188: 713 | B188: SANDRA VERONICA ACEVEDO BELTRAN | C188: 03/05/2021 | D188: ASISTENTE PARA CORRESPONSALES FINANCIEROS | E188: EMPLEADO | F188: SUB GERENCIA DE CANALES | G188: Gerencia de Negocios
A189: 854 | B189: REBECA ABIGAIL VEGA FLORES | C189: 05/02/2024 | D189: CAJERO MOVIL | E189: EMPLEADO | F189: SUB GERENCIA DE CANALES | G189: Gerencia de Negocios
A190: 968 | B190: SAMUEL ALBERTO SALGUERO RODRIGUEZ | C190: 11/05/2026 | D190: CAJERO MOVIL | E190: EMPLEADO | F190: SUB GERENCIA DE CANALES | G190: Gerencia de Negocios
A191: 33 | B191: CAROLINA ELIZABETH RAMIREZ PONCE | C191: 20/12/1993 | D191: SUBJEFE DE AGENCIA | E191: EMPLEADO | F191: AGENCIA CENTRAL | G191: Gerencia de Negocios
A192: 49 | B192: GRISELDA DEL CARMEN DOMINGUEZ MERINO | C192: 04/07/1988 | D192: EJECUTIVO DE NEGOCIOS | E192: EMPLEADO | F192: AGENCIA CENTRAL | G192: Gerencia de Negocios
A193: 234 | B193: LETICIA ESMERALDA ROSA | C193: 21/03/2001 | D193: EJECUTIVO DE NEGOCIOS | E193: EMPLEADO | F193: AGENCIA CENTRAL | G193: Gerencia de Negocios
A194: 253 | B194: ELSY GUADALUPE COREA AGUILUZ | C194: 25/08/2001 | D194: EJECUTIVO DE NEGOCIOS | E194: EMPLEADO | F194: AGENCIA CENTRAL | G194: Gerencia de Negocios
A195: 385 | B195: BLANCA ARACELY MORENO HERNANDEZ | C195: 27/07/2006 | D195: AUXILIAR DE OPERACIONES Y ATENCION EN AGENCIA | E195: EMPLEADO | F195: AGENCIA CENTRAL | G195: Gerencia de Negocios
A196: 440 | B196: KARLA MERCEDES DELEON DELGADO | C196: 09/10/2008 | D196: JEFE DE AGENCIA | E196: EMPLEADO | F196: AGENCIA CENTRAL | G196: Gerencia de Negocios | H196: Vacaciones
A197: 542 | B197: ANA SILVIA ROQUE SANCHEZ | C197: 01/01/2015 | D197: EJECUTIVA DE SEGUROS | E197: EMPLEADO | F197: AGENCIA CENTRAL | G197: Gerencia de Negocios
A198: 739 | B198: JOHANA PATRICIA LUNA RAMOS | C198: 03/01/2022 | D198: CAJERO | E198: EMPLEADO | F198: AGENCIA CENTRAL | G198: Gerencia de Negocios | H198: Incapacidad por maternidad
A199: 757 | B199: MARIA DE LOS ANGELES OSORIO GIL | C199: 01/07/2022 | D199: CAJERO | E199: EMPLEADO | F199: AGENCIA CENTRAL | G199: Gerencia de Negocios
A200: 768 | B200: KATHERINE MICHELLE LOPEZ LOPEZ | C200: 16/08/2022 | D200: AUXILIAR DE OPERACIONES Y ATENCION EN AGENCIA | E200: EMPLEADO | F200: AGENCIA CENTRAL | G200: Gerencia de Negocios
A201: 848 | B201: JAZMIN ABIGAIL VASQUEZ AVELAR | C201: 05/01/2024 | D201: CAJERO | E201: EMPLEADO | F201: AGENCIA CENTRAL | G201: Gerencia de Negocios
A202: 857 | B202: ESTHER ABIGAIL FLORES GRANDE | C202: 01/06/2024 | D202: AUXILIAR DE OPERACIONES Y ATENCION EN AGENCIA | E202: EMPLEADO | F202: AGENCIA CENTRAL | G202: Gerencia de Negocios
A203: 953 | B203: JESUS ADRIAN MENA AVALOS | C203: 16/12/2025 | D203: CAJERO | E203: EMPLEADO | F203: AGENCIA CENTRAL | G203: Gerencia de Negocios
A204: 956 | B204: ANGELA GABRIELA REYES MOLINA | C204: 05/01/2026 | D204: CAJERO | E204: EMPLEADO | F204: AGENCIA CENTRAL | G204: Gerencia de Negocios
A205: 958 | B205: ALEXANDRA DANIELA PINEDA JIMENEZ | C205: 10/02/2026 | D205: AUXILIAR DE ATENCION A ASOCIADOS | E205: EMPLEADO | F205: AGENCIA CENTRAL | G205: Gerencia de Negocios
A206: 960 | B206: LORENA DEL CARMEN MEJIA HERRERA | C206: 16/02/2026 | D206: CAJERO | E206: EMPLEADO | F206: AGENCIA CENTRAL | G206: Gerencia de Negocios
A207: 974 | B207: LEIDY VANESSA GUZMAN SERVELLON | C207: 21/07/2026 | D207: CAJERO | E207: EMPLEADO | F207: AGENCIA CENTRAL | G207: Gerencia de Negocios
A208: 976 | B208: KEVIN ARTURO ANDRADE PALACIOS | C208: 21/07/2026 | D208: CAJERO | E208: EMPLEADO | F208: AGENCIA CENTRAL | G208: Gerencia de Negocios
A209: 26 | B209: FLOR IMELDA VILLALOBOS ARDON | C209: 09/08/1991 | D209: EJECUTIVO DE NEGOCIOS | E209: EMPLEADO | F209: AGENCIA COLEGIO MEDICO | G209: Gerencia de Negocios
A210: 29 | B210: YANIRA ELIZABETH ORTEGA MIRANDA | C210: 20/04/1995 | D210: SUBJEFE DE AGENCIA | E210: EMPLEADO | F210: AGENCIA COLEGIO MEDICO | G210: Gerencia de Negocios
... A212: 360 | B212: PATRICIA ESMERALDA PORTILLO CESPEDES | C212: 23/04/2009 | D212: JEFE DE AGENCIA | E212: EMPLEADO | F212: AGENCIA COLEGIO MEDICO | G212: Gerencia de Negocios
...

Sheet Base Exámenes
A1: REGISTROS CRUDOS DEL EXAMEN
A2: Datos exportados de la plataforma de evaluaciones
A4: Nombre en Examen | B4: Área en Examen | C4: Código de Empleado | D4: Hora de Inicio | E4: Hora de Finalización | F4: Duración (min) | G4: Nota | H4: Correo | I4: Clave auxiliar (no editar)
A5: José Augusto De la O Gallegos | B5: Gerencia de Finanzas y Planificación | C5: 524 | D5: 46296.427 | E5: 46296.43 | F5: =IF(OR(D5="",E5=""),"",(E5-D5)*1440) -> 3.6 | G5: 100 | H5: anonymous | I5: =IF(C5="","",C5&"|"&G5) -> 524|100
A6: Henry Oswaldo Pineda García | B6: Seguros | C6: 894 | D6: 46296.426 | E6: 46296.432 | F6: =IF(OR(D6="",E6=""),"",(E6-D6)*1440) -> 7.8666667 | G6: 100 | H6: anonymous | I6: =IF(C6="","",C6&"|"&G6) -> 894|100
A7: Sara Patricia González de Jiménez | B7: Departamento de Riesgos | C7: 408 | D7: 46296.437 | E7: 46296.439 | F7: =IF(OR(D7="",E7=""),"",(E7-D7)*1440) -> 3.05 | G7: 100 | H7: anonymous | I7: =IF(C7="","",C7&"|"&G7) -> 408|100
A8: THELMA ESPERANZA DIGUEROA DE SORTO | B8: AGENCIA SAN MIGUEL | C8: 197 | D8: 46296.435 | E8: 46296.441 | F8: =IF(OR(D8="",E8=""),"",(E8-D8)*1440) -> 8.25 | G8: 100 | H8: anonymous | I8: =IF(C8="","",C8&"|"&G8) -> 197|100
A9: Mauricio Edgardo Miranda Campos | B9: Procesos | C9: 817 | D9: 46296.437 | E9: 46296.441 | F9: =IF(OR(D9="",E9=""),"",(E9-D9)*1440) -> 6.8 | G9: 100 | H9: anonymous | I9: =IF(C9="","",C9&"|"&G9) -> 817|100
A10: Héctor Sebastián López Granados | B10: Procesos | C10: 932 | D10: 46296.437 | E10: 46296.441 | F10: =IF(OR(D10="",E10=""),"",(E10-D10)*1440) -> 6.1166667 | G10: 100 | H10: anonymous | I10: =IF(C10="","",C10&"|"&G10) -> 932|100
A11: Claudia Carolina Henríquez Velasco | B11: Procesos | C11: 318 | D11: 46296.437 | E11: 46296.441 | F11: =IF(OR(D11="",E11=""),"",(E11-D11)*1440) -> 7.0833333 | G11: 100 | H11: anonymous | I11: =IF(C11="","",C11&"|"&G11) -> 318|100
A12: DIEGO GERARDO GUANDIQUE TORRES | B12: AGENCIA SAN MIGUEL | C12: 776 | D12: 46296.443 | E12: 46296.445 | F12: =IF(OR(D12="",E12=""),"",(E12-D12)*1440) -> 3.4 | G12: 100 | H12: anonymous | I12: =IF(C12="","",C12&"|"&G12) -> 776|100
A13: Martha Lorena González González | B13: San Miguel | C13: 390 | D13: 46296.446 | E13: 46296.448 | F13: =IF(OR(D13="",E13=""),"",(E13-D13)*1440) -> 3 | G13: 100 | H13: anonymous | I13: =IF(C13="","",C13&"|"&G13) -> 390|100
A14: Jennifer Georgina Alvarado de Hernández | B14: Seguridad de la Informacion y Ciberseguridad | C14: 907 | D14: 46296.442 | E14: 46296.449 | F14: =IF(OR(D14="",E14=""),"",(E14-D14)*1440) -> 9.0666667 | G14: 85 | H14: anonymous | I14: =IF(C14="","",C14&"|"&G14) -> 907|85
A15: Marvin Alonso Franco Ramirez | B15: Seguridad de la información y ciberseguridad | C15: 918 | D15: 46296.442 | E15: 46296.449 | F15: =IF(OR(D15="",E15=""),"",(E15-D15)*1440) -> 9.6333333 | G15: 100 | H15: anonymous | I15: =IF(C15="","",C15&"|"&G15) -> 918|100
A16: María Azucena Bonilla Rivera | B16: Seguridad de la Información | C16: 710 | D16: 46296.441 | E16: 46296.449 | F16: =IF(OR(D16="",E16=""),"",(E16-D16)*1440) -> 11.733333 | G16: 100 | H16: anonymous | I16: =IF(C16="","",C16&"|"&G16) -> 710|100
... A293: ROQUE RAFAEL REYES ESPINAL | B293: GERENCIA DE OPERACIONES | C293: 41 | D293: 46311.803 | E293: 46311.814 | F293: =IF(OR(D293="",E293=""),"",(E293-D293)*1440) -> 15.85 | G293: 100 | H293: anonymous | I293: =IF(C293="","",C293&"|"&G293) -> 41|100
A294: NELSON ULISES CAMPOS FLORES | B294: GERENCIA GENERAL | C294: 977 | F294: =IF(OR(D294="",E294=""),"",(E294-D294)*1440) | H294: REGISTRO MANUAL: examen realizado (confirmado por la administración; sin nota ni fecha en la plataforma) | I294: =IF(C294="","",C294&"|"&G294) -> 977|
F295: =IF(OR(D295="",E295=""),"",(E295-D295)*1440) | I295: =IF(C295="","",C295&"|"&G295)
F296: =IF(OR(D296="",E296=""),"",(E296-D296)*1440) | I296: =IF(C296="","",C296&"|"&G296)
F297: =IF(OR(D297="",E297=""),"",(E297-D297)*1440) | I297: =IF(C297="","",C297&"|"&G297)
F298: =IF(OR(D298="",E298=""),"",(E298-D298)*1440) | I298: =IF(C298="","",C298&"|"&G298)
F299: =IF(OR(D299="",E299=""),"",(E299-D299)*1440) | I299: =IF(C299="","",C299&"|"&G299)
F300: =IF(OR(D300="",E300=""),"",(E300-D300)*1440) | I300: =IF(C300="","",C300&"|"&G300)
F301: =IF(OR(D301="",E301=""),"",(E301-D301)*1440) | I301: =IF(C301="","",C301&"|"&G301)
F302: =IF(OR(D302="",E302=""),"",(E302-D302)*1440) | I302: =IF(C302="","",C302&"|"&G302)
F303: =IF(OR(D303="",E303=""),"",(E303-D303)*1440) | I303: =IF(C303="","",C303&"|"&G303)
F304: =IF(OR(D304="",E304=""),"",(E304-D304)*1440) | I304: =IF(C304="","",C304&"|"&G304)
F305: =IF(OR(D305="",E305=""),"",(E305-D305)*1440) | I305: =IF(C305="","",C305&"|"&G305)
F306: =IF(OR(D306="",E306=""),"",(E306-D306)*1440) | I306: =IF(C306="","",C306&"|"&G306)
... F1000: =IF(OR(D1000="",E1000=""),"",(E1000-D1000)*1440) | I1000: =IF(C1000="","",C1000&"|"&G1000)

Sheet Detalle individual
A1: DETALLE INDIVIDUAL DE PARTICIPANTES
A2: Cruce oficial por Código de Empleado frente a la Base Oficial y Base Exámenes.
A4: Código de empleado | B4: Nombre del colaborador | C4: Área / Departamento | D4: Gerencia Asignada | E4: Cargo | F4: Estado Examen | G4: Hora de inicio | H4: Hora de finalización | I4: Duración (min) | J4: Nota | K4: Correo | L4: N° de intentos | M4: Situación especial (vigente)
A5: =IF('Base Oficial'!A5="","",TRIM('Base Oficial'!A5)) -> 977 | B5: =IF($A5="","",TRIM('Base Oficial'!B5)) -> NELSON ULISES CAMPOS FLORES | C5: =IF($A5="","",TRIM('Base Oficial'!F5)) -> GERENCIA GENERAL | D5: =IF($A5="","",TRIM('Base Oficial'!G5)) -> Gerencia General | E5: =IF($A5="","",TRIM('Base Oficial'!D5)) -> GERENTE GENERAL | F5: =IF($A5="","",IF(COUNTIF('Base Exámenes'!$C$5:$C$1000, A5)>0, "Completado", IF(M5<>"", M5, "Pendiente"))) -> Completado | G5: =IF(F5="Completado", IFERROR(IF(INDEX('Base Exámenes'!$D$5:$D$1000, MATCH(A5&"|"&J5, 'Base Exámenes'!$I$5:$I$1000, 0))="", "", INDEX('Base Exámenes'!$D$5:$D$1000, MATCH(A5&"|"&J5, 'Base Exámenes'!$I$5:$I$1000, 0))), ""), "") | H5: =IF(F5="Completado", IFERROR(IF(INDEX('Base Exámenes'!$E$5:$E$1000, MATCH(A5&"|"&J5, 'Base Exámenes'!$I$5:$I$1000, 0))="", "", INDEX('Base Exámenes'!$E$5:$E$1000, MATCH(A5&"|"&J5, 'Base Exámenes'!$I$5:$I$1000, 0))), ""), "") | I5: =IF(F5="Completado", IFERROR(IF(INDEX('Base Exámenes'!$F$5:$F$1000, MATCH(A5&"|"&J5, 'Base Exámenes'!$I$5:$I$1000, 0))="", "", INDEX('Base Exámenes'!$F$5:$F$1000, MATCH(A5&"|"&J5, 'Base Exámenes'!$I$5:$I$1000, 0))), ""), "") | J5: =IF(F5="Completado", IF(COUNTIFS('Base Exámenes'!$C$5:$C$1000, A5, 'Base Exámenes'!$G$5:$G$1000, "<>")=0, "", _xlfn.MAXIFS('Base Exámenes'!$G$5:$G$1000, 'Base Exámenes'!$C$5:$C$1000, A5)), "") | K5: =IF(F5="Completado", IFERROR(IF(INDEX('Base Exámenes'!$H$5:$H$1000, MATCH(A5&"|"&J5, 'Base Exámenes'!$I$5:$I$1000, 0))="", "", INDEX('Base Exámenes'!$H$5:$H$1000, MATCH(A5&"|"&J5, 'Base Exámenes'!$I$5:$I$1000, 0))), ""), "") -> REGISTRO MANUAL: examen realizado (confirmado por la administración; sin nota ni fecha en la plataforma) | L5: =IF($A5="","",COUNTIF('Base Exámenes'!$C$5:$C$1000, A5)) -> 1 | M5: =IF($A5="","",IF(COUNTIF('Base Exámenes'!$C$5:$C$1000, A5)>0, "", TRIM('Base Oficial'!H5)))
A6: =IF('Base Oficial'!A6="","",TRIM('Base Oficial'!A6)) -> 349 | B6: =IF($A6="","",TRIM('Base Oficial'!B6)) -> CARLA EUGENIA HERNANDEZ MENJIVAR | C6: =IF($A6="","",TRIM('Base Oficial'!F6)) -> GERENCIA ADMINISTRATIVA | D6: =IF($A6="","",TRIM('Base Oficial'!G6)) -> Gerencia Administrativa | E6: =IF($A6="","",TRIM('Base Oficial'!D6)) -> GERENTE ADMINISTRATIVA | F6: =IF($A6="","",IF(COUNTIF('Base Exámenes'!$C$5:$C$1000, A6)>0, "Completado", IF(M6<>"", M6, "Pendiente"))) -> Completado | G6: =IF(F6="Completado", IFERROR(IF(INDEX('Base Exámenes'!$D$5:$D$1000, MATCH(A6&"|"&J6, 'Base Exámenes'!$I$5:$I$1000, 0))="", "", INDEX('Base Exámenes'!$D$5:$D$1000, MATCH(A6&"|"&J6, 'Base Exámenes'!$I$5:$I$1000, 0))), ""), "") -> 46297.637 | H6: =IF(F6="Completado", IFERROR(IF(INDEX('Base Exámenes'!$E$5:$E$1000, MATCH(A6&"|"&J6, 'Base Exámenes'!$I$5:$I$1000, 0))="", "", INDEX('Base Exámenes'!$E$5:$E$1000, MATCH(A6&"|"&J6, 'Base Exámenes'!$I$5:$I$1000, 0))), ""), "") -> 46297.638 | I6: =IF(F6="Completado", IFERROR(IF(INDEX('Base Exámenes'!$F$5:$F$1000, MATCH(A6&"|"&J6, 'Base Exámenes'!$I$5:$I$1000, 0))="", "", INDEX('Base Exámenes'!$F$5:$F$1000, MATCH(A6&"|"&J6, 'Base Exámenes'!$I$5:$I$1000, 0))), ""), "") -> 2.3 | J6: =IF(F6="Completado", IF(COUNTIFS('Base Exámenes'!$C$5:$C$1000, A6, 'Base Exámenes'!$G$5:$G$1000, "<>")=0, "", _xlfn.MAXIFS('Base Exámenes'!$G$5:$G$1000, 'Base Exámenes'!$C$5:$C$1000, A6)), "") -> 100 | K6: =IF(F6="Completado", IFERROR(IF(INDEX('Base Exámenes'!$H$5:$H$1000, MATCH(A6&"|"&J6, 'Base Exámenes'!$I$5:$I$1000, 0))="", "", INDEX('Base Exámenes'!$H$5:$H$1000, MATCH(A6&"|"&J6, 'Base Exámenes'!$I$5:$I$1000, 0))), ""), "") -> anonymous | L6: =IF($A6="","",COUNTIF('Base Exámenes'!$C$5:$C$1000, A6)) -> 1 | M6: =IF($A6="","",IF(COUNTIF('Base Exámenes'!$C$5:$C$1000, A6)>0, "", TRIM('Base Oficial'!H6)))
A7: =IF('Base Oficial'!A7="","",TRIM('Base Oficial'!A7)) -> 41 | B7: =IF($A7="","",TRIM('Base Oficial'!B7)) -> ROQUE RAFAEL REYES ESPINAL | C7: =IF($A7="","",TRIM('Base Oficial'!F7)) -> GERENCIA DE OPERACIONES | D7: =IF($A7="","",TRIM('Base Oficial'!G7)) -> Gerencia de Operaciones | E7: =IF($A7="","",TRIM('Base Oficial'!D7)) -> GERENTE DE OPERACIONES | F7: =IF($A7="","",IF(COUNTIF('Base Exámenes'!$C$5:$C$1000, A7)>0, "Completado", IF(M7<>"", M7, "Pendiente"))) -> Completado | G7: =IF(F7="Completado", IFERROR(IF(INDEX('Base Exámenes'!$D$5:$D$1000, MATCH(A7&"|"&J7, 'Base Exámenes'!$I$5:$I$1000, 0))="", "", INDEX('Base Exámenes'!$D$5:$D$1000, MATCH(A7&"|"&J7, 'Base Exámenes'!$I$5:$I$1000, 0))), ""), "") -> 46311.803 | H7: =IF(F7="Completado", IFERROR(IF(INDEX('Base Exámenes'!$E$5:$E$1000, MATCH(A7&"|"&J7, 'Base Exámenes'!$I$5:$I$1000, 0))="", "", INDEX('Base Exámenes'!$E$5:$E$1000, MATCH(A7&"|"&J7, 'Base Exámenes'!$I$5:$I$1000, 0))), ""), "") -> 46311.814 | I7: =IF(F7="Completado", IFERROR(IF(INDEX('Base Exámenes'!$F$5:$F$1000, MATCH(A7&"|"&J7, 'Base Exámenes'!$I$5:$I$1000, 0))="", "", INDEX('Base Exámenes'!$F$5:$F$1000, MATCH(A7&"|"&J7, 'Base Exámenes'!$I$5:$I$1000, 0))), ""), "") -> 15.85 | J7: =IF(F7="Completado", IF(COUNTIFS('Base Exámenes'!$C$5:$C$1000, A7, 'Base Exámenes'!$G$5:$G$1000, "<>")=0, "", _xlfn.MAXIFS('Base Exámenes'!$G$5:$G$1000, 'Base Exámenes'!$C$5:$C$1000, A7)), "") -> 100 | K7: =IF(F7="Completado", IFERROR(IF(INDEX('Base Exámenes'!$H$5:$H$1000, MATCH(A7&"|"&J7, 'Base Exámenes'!$I$5:$I$1000, 0))="", "", INDEX('Base Exámenes'!$H$5:$H$1000, MATCH(A7&"|"&J7, 'Base Exámenes'!$I$5:$I$1000, 0))), ""), "") -> anonymous | L7: =IF($A7="","",COUNTIF('Base Exámenes'!$C$5:$C$1000, A7)) -> 1 | M7: =IF($A7="","",IF(COUNTIF('Base Exámenes'!$C$5:$C$1000, A7)>0, "", TRIM('Base Oficial'!H7)))
A8: =IF('Base Oficial'!A8="","",TRIM('Base Oficial'!A8)) -> 524 | B8: =IF($A8="","",TRIM('Base Oficial'!B8)) -> JOSE AUGUSTO DE LA O GALLEGOS | C8: =IF($A8="","",TRIM('Base Oficial'!F8)) -> GERENCIA DE FINANZAS Y PLANIFICACIÓN | D8: =IF($A8="","",TRIM('Base Oficial'!G8)) -> Gerencia de Finanzas y Planificación | E8: =IF($A8="","",TRIM('Base Oficial'!D8)) -> GERENTE DE FINANZAS Y PLANIFICACION | F8: =IF($A8="","",IF(COUNTIF('Base Exámenes'!$C$5:$C$1000, A8)>0, "Completado", IF(M8<>"", M8, "Pendiente"))) -> Completado | G8: =IF(F8="Completado", IFERROR(IF(INDEX('Base Exámenes'!$D$5:$D$1000, MATCH(A8&"|"&J8, 'Base Exámenes'!$I$5:$I$1000, 0))="", "", INDEX('Base Exámenes'!$D$5:$D$1000, MATCH(A8&"|"&J8, 'Base Exámenes'!$I$5:$I$1000, 0))), ""), "") -> 46296.427 | H8: =IF(F8="Completado", IFERROR(IF(INDEX('Base Exámenes'!$E$5:$E$1000, MATCH(A8&"|"&J8, 'Base Exámenes'!$I$5:$I$1000, 0))="", "", INDEX('Base Exámenes'!$E$5:$E$1000, MATCH(A8&"|"&J8, 'Base Exámenes'!$I$5:$I$1000, 0))), ""), "") -> 46296.43 | I8: =IF(F8="Completado", IFERROR(IF(INDEX('Base Exámenes'!$F$5:$F$1000, MATCH(A8&"|"&J8, 'Base Exámenes'!$I$5:$I$1000, 0))="", "", INDEX('Base Exámenes'!$F$5:$F$1000, MATCH(A8&"|"&J8, 'Base Exámenes'!$I$5:$I$1000, 0))), ""), "") -> 3.6 | J8: =IF(F8="Completado", IF(COUNTIFS('Base Exámenes'!$C$5:$C$1000, A8, 'Base Exámenes'!$G$5:$G$1000, "<>")=0, "", _xlfn.MAXIFS('Base Exámenes'!$G$5:$G$1000, 'Base Exámenes'!$C$5:$C$1000, A8)), "") -> 100 | K8: =IF(F8="Completado", IFERROR(IF(INDEX('Base Exámenes'!$H$5:$H$1000, MATCH(A8&"|"&J8, 'Base Exámenes'!$I$5:$I$1000, 0))="", "", INDEX('Base Exámenes'!$H$5:$H$1000, MATCH(A8&"|"&J8, 'Base Exámenes'!$I$5:$I$1000, 0))), ""), "") -> anonymous | L8: =IF($A8="","",COUNTIF('Base Exámenes'!$C$5:$C$1000, A8)) -> 1 | M8: =IF($A8="","",IF(COUNTIF('Base Exámenes'!$C$5:$C$1000, A8)>0, "", TRIM('Base Oficial'!H8)))
A9: =IF('Base Oficial'!A9="","",TRIM('Base Oficial'!A9)) -> 878 | B9: =IF($A9="","",TRIM('Base Oficial'!B9)) -> ALEX VIRGILIO AGUILAR ARIAS | C9: =IF($A9="","",TRIM('Base Oficial'!F9)) -> GERENCIA DE SISTEMAS | D9: =IF($A9="","",TRIM('Base Oficial'!G9)) -> Gerencia de Sistemas | E9: =IF($A9="","",TRIM('Base Oficial'!D9)) -> GERENTE DE SISTEMAS | F9: =IF($A9="","",IF(COUNTIF('Base Exámenes'!$C$5:$C$1000, A9)>0, "Completado", IF(M9<>"", M9, "Pendiente"))) -> Completado | G9: =IF(F9="Completado", IFERROR(IF(INDEX('Base Exámenes'!$D$5:$D$1000, MATCH(A9&"|"&J9, 'Base Exámenes'!$I$5:$I$1000, 0))="", "", INDEX('Base Exámenes'!$D$5:$D$1000, MATCH(A9&"|"&J9, 'Base Exámenes'!$I$5:$I$1000, 0))), ""), "") -> 46310.692 | H9: =IF(F9="Completado", IFERROR(IF(INDEX('Base Exámenes'!$E$5:$E$1000, MATCH(A9&"|"&J9, 'Base Exámenes'!$I$5:$I$1000, 0))="", "", INDEX('Base Exámenes'!$E$5:$E$1000, MATCH(A9&"|"&J9, 'Base Exámenes'!$I$5:$I$1000, 0))), ""), "") -> 46310.697 | I9: =IF(F9="Completado", IFERROR(IF(INDEX('Base Exámenes'!$F$5:$F$1000, MATCH(A9&"|"&J9, 'Base Exámenes'!$I$5:$I$1000, 0))="", "", INDEX('Base Exámenes'!$F$5:$F$1000, MATCH(A9&"|"&J9, 'Base Exámenes'!$I$5:$I$1000, 0))), ""), "") -> 7.1333333 | J9: =IF(F9="Completado", IF(COUNTIFS('Base Exámenes'!$C$5:$C$1000, A9, 'Base Exámenes'!$G$5:$G$1000, "<>")=0, "", _xlfn.MAXIFS('Base Exámenes'!$G$5:$G$1000, 'Base Exámenes'!$C$5:$C$1000, A9)), "") -> 100 | K9: =IF(F9="Completado", IFERROR(IF(INDEX('Base Exámenes'!$H$5:$H$1000, MATCH(A9&"|"&J9, 'Base Exámenes'!$I$5:$I$1000, 0))="", "", INDEX('Base Exámenes'!$H$5:$H$1000, MATCH(A9&"|"&J9, 'Base Exámenes'!$I$5:$I$1000, 0))), ""), "") -> anonymous | L9: =IF($A9="","",COUNTIF('Base Exámenes'!$C$5:$C$1000, A9)) -> 1 | M9: =IF($A9="","",IF(COUNTIF('Base Exámenes'!$C$5:$C$1000, A9)>0, "", TRIM('Base Oficial'!H9)))
A10: =IF('Base Oficial'!A10="","",TRIM('Base Oficial'!A10)) -> 862 | B10: =IF($A10="","",TRIM('Base Oficial'!B10)) -> GEORGI ROBERTO CASTILLO CHACON | C10: =IF($A10="","",TRIM('Base Oficial'!F10)) -> OFICIALIA DE CUMPLIMIENTO | D10: =IF($A10="","",TRIM('Base Oficial'!G10)) -> Gerencia de Oficialía de Cumplimiento | E10: =IF($A10="","",TRIM('Base Oficial'!D10)) -> GERENTE DE OFICIALIA DE CUMPLIMIENTO | F10: =IF($A10="","",IF(COUNTIF('Base Exámenes'!$C$5:$C$1000, A10)>0, "Completado", IF(M10<>"", M10, "Pendiente"))) -> Completado | G10: =IF(F10="Completado", IFERROR(IF(INDEX('Base Exámenes'!$D$5:$D$1000, MATCH(A10&"|"&J10, 'Base Exámenes'!$I$5:$I$1000, 0))="", "", INDEX('Base Exámenes'!$D$5:$D$1000, MATCH(A10&"|"&J10, 'Base Exámenes'!$I$5:$I$1000, 0))), ""), "") -> 46296.47 | H10: =IF(F10="Completado", IFERROR(IF(INDEX('Base Exámenes'!$E$5:$E$1000, MATCH(A10&"|"&J10, 'Base Exámenes'!$I$5:$I$1000, 0))="", "", INDEX('Base Exámenes'!$E$5:$E$1000, MATCH(A10&"|"&J10, 'Base Exámenes'!$I$5:$I$1000, 0))), ""), "") -> 46296.477 | I10: =IF(F10="Completado", IFERROR(IF(INDEX('Base Exámenes'!$F$5:$F$1000, MATCH(A10&"|"&J10, 'Base Exámenes'!$I$5:$I$1000, 0))="", "", INDEX('Base Exámenes'!$F$5:$F$1000, MATCH(A10&"|"&J10, 'Base Exámenes'!$I$5:$I$1000, 0))), ""), "") -> 10.466667 | J10: =IF(F10="Completado", IF(COUNTIFS('Base Exámenes'!$C$5:$C$1000, A10, 'Base Exámenes'!$G$5:$G$1000, "<>")=0, "", _xlfn.MAXIFS('Base Exámenes'!$G$5:$G$1000, 'Base Exámenes'!$C$5:$C$1000, A10)), "") -> 100 | K10: =IF(F10="Completado", IFERROR(IF(INDEX('Base Exámenes'!$H$5:$H$1000, MATCH(A10&"|"&J10, 'Base Exámenes'!$I$5:$I$1000, 0))="", "", INDEX('Base Exámenes'!$H$5:$H$1000, MATCH(A10&"|"&J10, 'Base Exámenes'!$I$5:$I$1000, 0))), ""), "") -> anonymous | L10: =IF($A10="","",COUNTIF('Base Exámenes'!$C$5:$C$1000, A10)) -> 1 | M10: =IF($A10="","",IF(COUNTIF('Base Exámenes'!$C$5:$C$1000, A10)>0, "", TRIM('Base Oficial'!H10)))
A11: =IF('Base Oficial'!A11="","",TRIM('Base Oficial'!A11)) -> 741 | B11: =IF($A11="","",TRIM('Base Oficial'!B11)) -> JOSE HUMBERTO BARILLAS BURGOS | C11: =IF($A11="","",TRIM('Base Oficial'!F11)) -> GERENCIA DE NEGOCIOS | D11: =IF($A11="","",TRIM('Base Oficial'!G11)) -> Gerencia de Negocios | E11: =IF($A11="","",TRIM('Base Oficial'!D11)) -> GERENTE DE NEGOCIOS | F11: =IF($A11="","",IF(COUNTIF('Base Exámenes'!$C$5:$C$1000, A11)>0, "Completado", IF(M11<>"", M11, "Pendiente"))) -> Completado | G11: =IF(F11="Completado", IFERROR(IF(INDEX('Base Exámenes'!$D$5:$D$1000, MATCH(A11&"|"&J11, 'Base Exámenes'!$I$5:$I$1000, 0))="", "", INDEX('Base Exámenes'!$D$5:$D$1000, MATCH(A11&"|"&J11, 'Base Exámenes'!$I$5:$I$1000, 0))), ""), "") -> 46310.616 | H11: =IF(F11="Completado", IFERROR(IF(INDEX('Base Exámenes'!$E$5:$E$1000, MATCH(A11&"|"&J11, 'Base Exámenes'!$I$5:$I$1000, 0))="", "", INDEX('Base Exámenes'!$E$5:$E$1000, MATCH(A11&"|"&J11, 'Base Exámenes'!$I$5:$I$1000, 0))), ""), "") -> 46310.62 | I11: =IF(F11="Completado", IFERROR(IF(INDEX('Base Exámenes'!$F$5:$F$1000, MATCH(A11&"|"&J11, 'Base Exámenes'!$I$5:$I$1000, 0))="", "", INDEX('Base Exámenes'!$F$5:$F$1000, MATCH(A11&"|"&J11, 'Base Exámenes'!$I$5:$I$1000, 0))), ""), "") -> 4.85 | J11: =IF(F11="Completado", IF(COUNTIFS('Base Exámenes'!$C$5:$C$1000, A11, 'Base Exámenes'!$G$5:$G$1000, "<>")=0, "", _xlfn.MAXIFS('Base Exámenes'!$G$5:$G$1000, 'Base Exámenes'!$C$5:$C$1000, A11)), "") -> 100 | K11: =IF(F11="Completado", IFERROR(IF(INDEX('Base Exámenes'!$H$5:$H$1000, MATCH(A11&"|"&J11, 'Base Exámenes'!$I$5:$I$1000, 0))="", "", INDEX('Base Exámenes'!$H$5:$H$1000, MATCH(A11&"|"&J11, 'Base Exámenes'!$I$5:$I$1000, 0))), ""), "") -> anonymous | L11: =IF($A11="","",COUNTIF('Base Exámenes'!$C$5:$C$1000, A11)) -> 1 | M11: =IF($A11="","",IF(COUNTIF('Base Exámenes'!$C$5:$C$1000, A11)>0, "", TRIM('Base Oficial'!H11)))
A12: =IF('Base Oficial'!A12="","",TRIM('Base Oficial'!A12)) -> 570 | B12: =IF($A12="","",TRIM('Base Oficial'!B12)) -> ANDREA VICTORIA MAYORGA RODRIGUEZ | C12: =IF($A12="","",TRIM('Base Oficial'!F12)) -> GERENCIA LEGAL Y DE CUMPLIMIENTO NORMATIVO | D12: =IF($A12="","",TRIM('Base Oficial'!G12)) -> Gerencia Legal y Cumplimiento Normativo | E12: =IF($A12="","",TRIM('Base Oficial'!D12)) -> GERENTE LEGAL Y DE CUMPLIMIENTO NORMATIVO | F12: =IF($A12="","",IF(COUNTIF('Base Exámenes'!$C$5:$C$1000, A12)>0, "Completado", IF(M12<>"", M12, "Pendiente"))) -> Completado | G12: =IF(F12="Completado", IFERROR(IF(INDEX('Base Exámenes'!$D$5:$D$1000, MATCH(A12&"|"&J12, 'Base Exámenes'!$I$5:$I$1000, 0))="", "", INDEX('Base Exámenes'!$D$5:$D$1000, MATCH(A12&"|"&J12, 'Base Exámenes'!$I$5:$I$1000, 0))), ""), "") -> 46304.693 | H12: =IF(F12="Completado", IFERROR(IF(INDEX('Base Exámenes'!$E$5:$E$1000, MATCH(A12&"|"&J12, 'Base Exámenes'!$I$5:$I$1000, 0))="", "", INDEX('Base Exámenes'!$E$5:$E$1000, MATCH(A12&"|"&J12, 'Base Exámenes'!$I$5:$I$1000, 0))), ""), "") -> 46304.695 | I12: =IF(F12="Completado", IFERROR(IF(INDEX('Base Exámenes'!$F$5:$F$1000, MATCH(A12&"|"&J12, 'Base Exámenes'!$I$5:$I$1000, 0))="", "", INDEX('Base Exámenes'!$F$5:$F$1000, MATCH(A12&"|"&J12, 'Base Exámenes'!$I$5:$I$1000, 0))), ""), "") -> 2.5666667 | J12: =IF(F12="Completado", IF(COUNTIFS('Base Exámenes'!$C$5:$C$1000, A12, 'Base Exámenes'!$G$5:$G$1000, "<>")=0, "", _xlfn.MAXIFS('Base Exámenes'!$G$5:$G$1000, 'Base Exámenes'!$C$5:$C$1000, A12)), "") -> 100 | K12: =IF(F12="Completado", IFERROR(IF(INDEX('Base Exámenes'!$H$5:$H$1000, MATCH(A12&"|"&J12, 'Base Exámenes'!$I$5:$I$1000, 0))="", "", INDEX('Base Exámenes'!$H$5:$H$1000, MATCH(A12&"|"&J12, 'Base Exámenes'!$I$5:$I$1000, 0))), ""), "") -> anonymous | L12: =IF($A12="","",COUNTIF('Base Exámenes'!$C$5:$C$1000, A12)) -> 1 | M12: =IF($A12="","",IF(COUNTIF('Base Exámenes'!$C$5:$C$1000, A12)>0, "", TRIM('Base Oficial'!H12)))
A13: =IF('Base Oficial'!A13="","",TRIM('Base Oficial'!A13)) -> 17 | B13: =IF($A13="","",TRIM('Base Oficial'!B13)) -> ANTONIA SARAI BELTRAN CARBALLO | C13: =IF($A13="","",TRIM('Base Oficial'!F13)) -> GERENCIA GENERAL | D13: =IF($A13="","",TRIM('Base Oficial'!G13)) -> Gerencia General | E13: =IF($A13="","",TRIM('Base Oficial'!D13)) -> ASISTENTE ADMINISTRATIVO DE GERENCIA GENERAL | F13: =IF($A13="","",IF(COUNTIF('Base Exámenes'!$C$5:$C$1000, A13)>0, "Completado", IF(M13<>"", M13, "Pendiente"))) -> Completado | G13: =IF(F13="Completado", IFERROR(IF(INDEX('Base Exámenes'!$D$5:$D$1000, MATCH(A13&"|"&J13, 'Base Exámenes'!$I$5:$I$1000, 0))="", "", INDEX('Base Exámenes'!$D$5:$D$1000, MATCH(A13&"|"&J13, 'Base Exámenes'!$I$5:$I$1000, 0))), ""), "") -> 46305.407 | H13: =IF(F13="Completado", IFERROR(IF(INDEX('Base Exámenes'!$E$5:$E$1000, MATCH(A13&"|"&J13, 'Base Exámenes'!$I$5:$I$1000, 0))="", "", INDEX('Base Exámenes'!$E$5:$E$1000, MATCH(A13&"|"&J13, 'Base Exámenes'!$I$5:$I$1000, 0))), ""), "") -> 46305.41 | I13: =IF(F13="Completado", IFERROR(IF(INDEX('Base Exámenes'!$F$5:$F$1000, MATCH(A13&"|"&J13, 'Base Exámenes'!$I$5:$I$1000, 0))="", "", INDEX('Base Exámenes'!$F$5:$F$1000, MATCH(A13&"|"&J13, 'Base Exámenes'!$I$5:$I$1000, 0))), ""), "") -> 4.5 | J13: =IF(F13="Completado", IF(COUNTIFS('Base Exámenes'!$C$5:$C$1000, A13, 'Base Exámenes'!$G$5:$G$1000, "<>")=0, "", _xlfn.MAXIFS('Base Exámenes'!$G$5:$G$1000, 'Base Exámenes'!$C$5:$C$1000, A13)), "") -> 100 | K13: =IF(F13="Completado", IFERROR(IF(INDEX('Base Exámenes'!$H$5:$H$1000, MATCH(A13&"|"&J13, 'Base Exámenes'!$I$5:$I$1000, 0))="", "", INDEX('Base Exámenes'!$H$5:$H$1000, MATCH(A13&"|"&J13, 'Base Exámenes'!$I$5:$I$1000, 0))), ""), "") -> anonymous | L13: =IF($A13="","",COUNTIF('Base Exámenes'!$C$5:$C$1000, A13)) -> 1 | M13: =IF($A13="","",IF(COUNTIF('Base Exámenes'!$C$5:$C$1000, A13)>0, "", TRIM('Base Oficial'!H13)))
A14: =IF('Base Oficial'!A14="","",TRIM('Base Oficial'!A14)) -> 290 | B14: =IF($A14="","",TRIM('Base Oficial'!B14)) -> MELVIN ENRIQUE PORTILLO VALLE | C14: =IF($A14="","",TRIM('Base Oficial'!F14)) -> ADMINISTRACION DE RIESGOS | D14: =IF($A14="","",TRIM('Base Oficial'!G14)) -> Gerencia General | E14: =IF($A14="","",TRIM('Base Oficial'!D14)) -> ANALISTA DE RIESGOS FINANCIEROS | F14: =IF($A14="","",IF(COUNTIF('Base Exámenes'!$C$5:$C$1000, A14)>0, "Completado", IF(M14<>"", M14, "Pendiente"))) -> Completado | G14: =IF(F14="Completado", IFERROR(IF(INDEX('Base Exámenes'!$D$5:$D$1000, MATCH(A14&"|"&J14, 'Base Exámenes'!$I$5:$I$1000, 0))="", "", INDEX('Base Exámenes'!$D$5:$D$1000, MATCH(A14&"|"&J14, 'Base Exámenes'!$I$5:$I$1000, 0))), ""), "") -> 46304.407 | H14: =IF(F14="Completado", IFERROR(IF(INDEX('Base Exámenes'!$E$5:$E$1000, MATCH(A14&"|"&J14, 'Base Exámenes'!$I$5:$I$1000, 0))="", "", INDEX('Base Exámenes'!$E$5:$E$1000, MATCH(A14&"|"&J14, 'Base Exámenes'!$I$5:$I$1000, 0))), ""), "") -> 46304.41 | I14: =IF(F14="Completado", IFERROR(IF(INDEX('Base Exámenes'!$F$5:$F$1000, MATCH(A14&"|"&J14, 'Base Exámenes'!$I$5:$I$1000, 0))="", "", INDEX('Base Exámenes'!$F$5:$F$1000, MATCH(A14&"|"&J14, 'Base Exámenes'!$I$5:$I$1000, 0))), ""), "") -> 3.9666667 | J14: =IF(F14="Completado", IF(COUNTIFS('Base Exámenes'!$C$5:$C$1000, A14, 'Base Exámenes'!$G$5:$G$1000, "<>")=0, "", _xlfn.MAXIFS('Base Exámenes'!$G$5:$G$1000, 'Base Exámenes'!$C$5:$C$1000, A14)), "") -> 100 | K14: =IF(F14="Completado", IFERROR(IF(INDEX('Base Exámenes'!$H$5:$H$1000, MATCH(A14&"|"&J14, 'Base Exámenes'!$I$5:$I$1000, 0))="", "", INDEX('Base Exámenes'!$H$5:$H$1000, MATCH(A14&"|"&J14, 'Base Exámenes'!$I$5:$I$1000, 0))), ""), "") -> anonymous | L14: =IF($A14="","",COUNTIF('Base Exámenes'!$C$5:$C$1000, A14)) -> 1 | M14: =IF($A14="","",IF(COUNTIF('Base Exámenes'!$C$5:$C$1000, A14)>0, "", TRIM('Base Oficial'!H14)))
A15: =IF('Base Oficial'!A15="","",TRIM('Base Oficial'!A15)) -> 408 | B15: =IF($A15="","",TRIM('Base Oficial'!B15)) -> SARA PATRICIA GONZALEZ JIMENEZ | C15: =IF($A15="","",TRIM('Base Oficial'!F15)) -> ADMINISTRACION DE RIESGOS | D15: =IF($A15="","",TRIM('Base Oficial'!G15)) -> Gerencia General | E15: =IF($A15="","",TRIM('Base Oficial'!D15)) -> ASISTENTE TECNICO DE RIESGOS | F15: =IF($A15="","",IF(COUNTIF('Base Exámenes'!$C$5:$C$1000, A15)>0, "Completado", IF(M15<>"", M15, "Pendiente"))) -> Completado | G15: =IF(F15="Completado", IFERROR(IF(INDEX('Base Exámenes'!$D$5:$D$1000, MATCH(A15&"|"&J15, 'Base Exámenes'!$I$5:$I$1000, 0))="", "", INDEX('Base Exámenes'!$D$5:$D$1000, MATCH(A15&"|"&J15, 'Base Exámenes'!$I$5:$I$1000, 0))), ""), "") -> 46296.437 | H15: =IF(F15="Completado", IFERROR(IF(INDEX('Base Exámenes'!$E$5:$E$1000, MATCH(A15&"|"&J15, 'Base Exámenes'!$I$5:$I$1000, 0))="", "", INDEX('Base Exámenes'!$E$5:$E$1000, MATCH(A15&"|"&J15, 'Base Exámenes'!$I$5:$I$1000, 0))), ""), "") -> 46296.439 | I15: =IF(F15="Completado", IFERROR(IF(INDEX('Base Exámenes'!$F$5:$F$1000, MATCH(A15&"|"&J15, 'Base Exámenes'!$I$5:$I$1000, 0))="", "", INDEX('Base Exámenes'!$F$5:$F$1000, MATCH(A15&"|"&J15, 'Base Exámenes'!$I$5:$I$1000, 0))), ""), "") -> 3.05 | J15: =IF(F15="Completado", IF(COUNTIFS('Base Exámenes'!$C$5:$C$1000, A15, 'Base Exámenes'!$G$5:$G$1000, "<>")=0, "", _xlfn.MAXIFS('Base Exámenes'!$G$5:$G$1000, 'Base Exámenes'!$C$5:$C$1000, A15)), "") -> 100 | K15: =IF(F15="Completado", IFERROR(IF(INDEX('Base Exámenes'!$H$5:$H$1000, MATCH(A15&"|"&J15, 'Base Exámenes'!$I$5:$I$1000, 0))="", "", INDEX('Base Exámenes'!$H$5:$H$1000, MATCH(A15&"|"&J15, 'Base Exámenes'!$I$5:$I$1000, 0))), ""), "") -> anonymous | L15: =IF($A15="","",COUNTIF('Base Exámenes'!$C$5:$C$1000, A15)) -> 1 | M15: =IF($A15="","",IF(COUNTIF('Base Exámenes'!$C$5:$C$1000, A15)>0, "", TRIM('Base Oficial'!H15)))
A16: =IF('Base Oficial'!A16="","",TRIM('Base Oficial'!A16)) -> 433 | B16: =IF($A16="","",TRIM('Base Oficial'!B16)) -> SILVIA IVETH MARTINEZ RAMIREZ | C16: =IF($A16="","",TRIM('Base Oficial'!F16)) -> ADMINISTRACION DE RIESGOS | D16: =IF($A16="","",TRIM('Base Oficial'!G16)) -> Gerencia General | E16: =IF($A16="","",TRIM('Base Oficial'!D16)) -> ANALISTA DE RIESGO OPERACIONAL | F16: =IF($A16="","",IF(COUNTIF('Base Exámenes'!$C$5:$C$1000, A16)>0, "Completado", IF(M16<>"", M16, "Pendiente"))) -> Completado | G16: =IF(F16="Completado", IFERROR(IF(INDEX('Base Exámenes'!$D$5:$D$1000, MATCH(A16&"|"&J16, 'Base Exámenes'!$I$5:$I$1000, 0))="", "", INDEX('Base Exámenes'!$D$5:$D$1000, MATCH(A16&"|"&J16, 'Base Exámenes'!$I$5:$I$1000, 0))), ""), "") -> 46300.622 | H16: =IF(F16="Completado", IFERROR(IF(INDEX('Base Exámenes'!$E$5:$E$1000, MATCH(A16&"|"&J16, 'Base Exámenes'!$I$5:$I$1000, 0))="", "", INDEX('Base Exámenes'!$E$5:$E$1000, MATCH(A16&"|"&J16, 'Base Exámenes'!$I$5:$I$1000, 0))), ""), "") -> 46300.631 | I16: =IF(F16="Completado", IFERROR(IF(INDEX('Base Exámenes'!$F$5:$F$1000, MATCH(A16&"|"&J16, 'Base Exámenes'!$I$5:$I$1000, 0))="", "", INDEX('Base Exámenes'!$F$5:$F$1000, MATCH(A16&"|"&J16, 'Base Exámenes'!$I$5:$I$1000, 0))), ""), "") -> 13.633333 | J16: =IF(F16="Completado", IF(COUNTIFS('Base Exámenes'!$C$5:$C$1000, A16, 'Base Exámenes'!$G$5:$G$1000, "<>")=0, "", _xlfn.MAXIFS('Base Exámenes'!$G$5:$G$1000, 'Base Exámenes'!$C$5:$C$1000, A16)), "") -> 100 | K16: =IF(F16="Completado", IFERROR(IF(INDEX('Base Exámenes'!$H$5:$H$1000, MATCH(A16&"|"&J16, 'Base Exámenes'!$I$5:$I$1000, 0))="", "", INDEX('Base Exámenes'!$H$5:$H$1000, MATCH(A16&"|"&J16, 'Base Exámenes'!$I$5:$I$1000, 0))), ""), "") -> anonymous | L16: =IF($A16="","",COUNTIF('Base Exámenes'!$C$5:$C$1000, A16)) -> 1 | M16: =IF($A16="","",IF(COUNTIF('Base Exámenes'!$C$5:$C$1000, A16)>0, "", TRIM('Base Oficial'!H16)))
... A1000: =IF('Base Oficial'!A1000="","",TRIM('Base Oficial'!A1000)) | B1000: =IF($A1000="","",TRIM('Base Oficial'!B1000)) | C1000: =IF($A1000="","",TRIM('Base Oficial'!F1000)) | D1000: =IF($A1000="","",TRIM('Base Oficial'!G1000)) | E1000: =IF($A1000="","",TRIM('Base Oficial'!D1000)) | F1000: =IF($A1000="","",IF(COUNTIF('Base Exámenes'!$C$5:$C$1000, A1000)>0, "Completado", IF(M1000<>"", M1000, "Pendiente"))) | G1000: =IF(F1000="Completado", IFERROR(IF(INDEX('Base Exámenes'!$D$5:$D$1000, MATCH(A1000&"|"&J1000, 'Base Exámenes'!$I$5:$I$1000, 0))="", "", INDEX('Base Exámenes'!$D$5:$D$1000, MATCH(A1000&"|"&J1000, 'Base Exámenes'!$I$5:$I$1000, 0))), ""), "") | H1000: =IF(F1000="Completado", IFERROR(IF(INDEX('Base Exámenes'!$E$5:$E$1000, MATCH(A1000&"|"&J1000, 'Base Exámenes'!$I$5:$I$1000, 0))="", "", INDEX('Base Exámenes'!$E$5:$E$1000, MATCH(A1000&"|"&J1000, 'Base Exámenes'!$I$5:$I$1000, 0))), ""), "") | I1000: =IF(F1000="Completado", IFERROR(IF(INDEX('Base Exámenes'!$F$5:$F$1000, MATCH(A1000&"|"&J1000, 'Base Exámenes'!$I$5:$I$1000, 0))="", "", INDEX('Base Exámenes'!$F$5:$F$1000, MATCH(A1000&"|"&J1000, 'Base Exámenes'!$I$5:$I$1000, 0))), ""), "") | J1000: =IF(F1000="Completado", IF(COUNTIFS('Base Exámenes'!$C$5:$C$1000, A1000, 'Base Exámenes'!$G$5:$G$1000, "<>")=0, "", _xlfn.MAXIFS('Base Exámenes'!$G$5:$G$1000, 'Base Exámenes'!$C$5:$C$1000, A1000)), "") | K1000: =IF(F1000="Completado", IFERROR(IF(INDEX('Base Exámenes'!$H$5:$H$1000, MATCH(A1000&"|"&J1000, 'Base Exámenes'!$I$5:$I$1000, 0))="", "", INDEX('Base Exámenes'!$H$5:$H$1000, MATCH(A1000&"|"&J1000, 'Base Exámenes'!$I$5:$I$1000, 0))), ""), "") | L1000: =IF($A1000="","",COUNTIF('Base Exámenes'!$C$5:$C$1000, A1000)) | M1000: =IF($A1000="","",IF(COUNTIF('Base Exámenes'!$C$5:$C$1000, A1000)>0, "", TRIM('Base Oficial'!H1000)))

Sheet Consolidado por área
A1: CONSOLIDADO DE EVALUACIÓN POR ÁREA / DEPARTAMENTO
A2: Cálculos automáticos basados en la hoja 'Detalle individual'
A4: Área / Departamento | B4: Gerencia Asignada | C4: Personal Esperado | D4: Personas Completadas | E4: Pendientes | F4: % Cumplimiento | G4: Estado | H4: Promedio Nota | I4: Nota Máxima | J4: Nota Mínima | K4: Primer Inicio | L4: Última Finalización | M4: Menor Duración (min) | N4: Promedio Duración (min) | O4: Justificados (no cuentan)
A5: =IF(Cálculos!$AE5="","",INDEX('Detalle individual'!$C:$C,Cálculos!$AE5)) -> ADMINISTRACION DE BASE DE DATOS | B5: =IF($A5="","",INDEX('Detalle individual'!$D:$D,Cálculos!$AE5)) -> Gerencia de Sistemas | C5: =IF($A5="","",COUNTIFS('Detalle individual'!$C$5:$C$1000, A5, 'Detalle individual'!$F$5:$F$1000, "Completado")+COUNTIFS('Detalle individual'!$C$5:$C$1000, A5, 'Detalle individual'!$F$5:$F$1000, "Pendiente")) -> 1 | D5: =IF($A5="","",COUNTIFS('Detalle individual'!$C$5:$C$1000, A5, 'Detalle individual'!$F$5:$F$1000, "Completado")) -> 1 | E5: =IF($A5="","",C5-D5) -> 0 | F5: =IF($A5="","",IF(C5>0, D5/C5, 0)) -> 1 | G5: =IF($A5="","",IF(AND(C5>0, D5=C5), "Completo", "Pendiente")) -> Completo | H5: =IF($A5="","",IF(D5>0, IFERROR(AVERAGEIFS('Detalle individual'!$J$5:$J$1000, 'Detalle individual'!$C$5:$C$1000, A5), ""), "")) -> 95 | I5: =IF($A5="","",IF(D5>0, IFERROR(_xlfn.MAXIFS('Detalle individual'!$J$5:$J$1000, 'Detalle individual'!$C$5:$C$1000, A5), ""), "")) -> 95 | J5: =IF($A5="","",IF(D5>0, IFERROR(_xlfn.MINIFS('Detalle individual'!$J$5:$J$1000, 'Detalle individual'!$C$5:$C$1000, A5), ""), "")) -> 95 | K5: =IF($A5="","",IF(D5>0, IFERROR(_xlfn.MINIFS('Detalle individual'!$G$5:$G$1000, 'Detalle individual'!$C$5:$C$1000, A5), ""), "")) -> 46300.685 | L5: =IF($A5="","",IF(D5>0, IFERROR(_xlfn.MAXIFS('Detalle individual'!$H$5:$H$1000, 'Detalle individual'!$C$5:$C$1000, A5), ""), "")) -> 46300.696 | M5: =IF($A5="","",IF(D5>0, IFERROR(_xlfn.MINIFS('Detalle individual'!$I$5:$I$1000, 'Detalle individual'!$C$5:$C$1000, A5), ""), "")) -> 15.383333 | N5: =IF($A5="","",IF(D5>0, IFERROR(AVERAGEIFS('Detalle individual'!$I$5:$I$1000, 'Detalle individual'!$C$5:$C$1000, A5), ""), "")) -> 15.383333 | O5: =IF($A5="","",COUNTIF('Detalle individual'!$C$5:$C$1000, A5)-C5) -> 0
A6: =IF(Cálculos!$AE6="","",INDEX('Detalle individual'!$C:$C,Cálculos!$AE6)) -> ADMINISTRACIÓN DE CARTERAS | B6: =IF($A6="","",INDEX('Detalle individual'!$D:$D,Cálculos!$AE6)) -> Gerencia de Operaciones | C6: =IF($A6="","",COUNTIFS('Detalle individual'!$C$5:$C$1000, A6, 'Detalle individual'!$F$5:$F$1000, "Completado")+COUNTIFS('Detalle individual'!$C$5:$C$1000, A6, 'Detalle individual'!$F$5:$F$1000, "Pendiente")) -> 5 | D6: =IF($A6="","",COUNTIFS('Detalle individual'!$C$5:$C$1000, A6, 'Detalle individual'!$F$5:$F$1000, "Completado")) -> 5 | E6: =IF($A6="","",C6-D6) -> 0 | F6: =IF($A6="","",IF(C6>0, D6/C6, 0)) -> 1 | G6: =IF($A6="","",IF(AND(C6>0, D6=C6), "Completo", "Pendiente")) -> Completo | H6: =IF($A6="","",IF(D6>0, IFERROR(AVERAGEIFS('Detalle individual'!$J$5:$J$1000, 'Detalle individual'!$C$5:$C$1000, A6), ""), "")) -> 100 | I6: =IF($A6="","",IF(D6>0, IFERROR(_xlfn.MAXIFS('Detalle individual'!$J$5:$J$1000, 'Detalle individual'!$C$5:$C$1000, A6), ""), "")) -> 100 | J6: =IF($A6="","",IF(D6>0, IFERROR(_xlfn.MINIFS('Detalle individual'!$J$5:$J$1000, 'Detalle individual'!$C$5:$C$1000, A6), ""), "")) -> 100 | K6: =IF($A6="","",IF(D6>0, IFERROR(_xlfn.MINIFS('Detalle individual'!$G$5:$G$1000, 'Detalle individual'!$C$5:$C$1000, A6), ""), "")) -> 46304.494 | L6: =IF($A6="","",IF(D6>0, IFERROR(_xlfn.MAXIFS('Detalle individual'!$H$5:$H$1000, 'Detalle individual'!$C$5:$C$1000, A6), ""), "")) -> 46311.676 | M6: =IF($A6="","",IF(D6>0, IFERROR(_xlfn.MINIFS('Detalle individual'!$I$5:$I$1000, 'Detalle individual'!$C$5:$C$1000, A6), ""), "")) -> 3.65 | N6: =IF($A6="","",IF(D6>0, IFERROR(AVERAGEIFS('Detalle individual'!$I$5:$I$1000, 'Detalle individual'!$C$5:$C$1000, A6), ""), "")) -> 9.53 | O6: =IF($A6="","",COUNTIF('Detalle individual'!$C$5:$C$1000, A6)-C6) -> 0
A7: =IF(Cálculos!$AE7="","",INDEX('Detalle individual'!$C:$C,Cálculos!$AE7)) -> ADMINISTRACION DE RIESGOS | B7: =IF($A7="","",INDEX('Detalle individual'!$D:$D,Cálculos!$AE7)) -> Gerencia General | C7: =IF($A7="","",COUNTIFS('Detalle individual'!$C$5:$C$1000, A7, 'Detalle individual'!$F$5:$F$1000, "Completado")+COUNTIFS('Detalle individual'!$C$5:$C$1000, A7, 'Detalle individual'!$F$5:$F$1000, "Pendiente")) -> 4 | D7: =IF($A7="","",COUNTIFS('Detalle individual'!$C$5:$C$1000, A7, 'Detalle individual'!$F$5:$F$1000, "Completado")) -> 4 | E7: =IF($A7="","",C7-D7) -> 0 | F7: =IF($A7="","",IF(C7>0, D7/C7, 0)) -> 1 | G7: =IF($A7="","",IF(AND(C7>0, D7=C7), "Completo", "Pendiente")) -> Completo | H7: =IF($A7="","",IF(D7>0, IFERROR(AVERAGEIFS('Detalle individual'!$J$5:$J$1000, 'Detalle individual'!$C$5:$C$1000, A7), ""), "")) -> 100 | I7: =IF($A7="","",IF(D7>0, IFERROR(_xlfn.MAXIFS('Detalle individual'!$J$5:$J$1000, 'Detalle individual'!$C$5:$C$1000, A7), ""), "")) -> 100 | J7: =IF($A7="","",IF(D7>0, IFERROR(_xlfn.MINIFS('Detalle individual'!$J$5:$J$1000, 'Detalle individual'!$C$5:$C$1000, A7), ""), "")) -> 100 | K7: =IF($A7="","",IF(D7>0, IFERROR(_xlfn.MINIFS('Detalle individual'!$G$5:$G$1000, 'Detalle individual'!$C$5:$C$1000, A7), ""), "")) -> 46296.437 | L7: =IF($A7="","",IF(D7>0, IFERROR(_xlfn.MAXIFS('Detalle individual'!$H$5:$H$1000, 'Detalle individual'!$C$5:$C$1000, A7), ""), "")) -> 46305.399 | M7: =IF($A7="","",IF(D7>0, IFERROR(_xlfn.MINIFS('Detalle individual'!$I$5:$I$1000, 'Detalle individual'!$C$5:$C$1000, A7), ""), "")) -> 3.05 | N7: =IF($A7="","",IF(D7>0, IFERROR(AVERAGEIFS('Detalle individual'!$I$5:$I$1000, 'Detalle individual'!$C$5:$C$1000, A7), ""), "")) -> 6.2458333 | O7: =IF($A7="","",COUNTIF('Detalle individual'!$C$5:$C$1000, A7)-C7) -> 0
A8: =IF(Cálculos!$AE8="","",INDEX('Detalle individual'!$C:$C,Cálculos!$AE8)) -> AGENCIA CENTRAL | B8: =IF($A8="","",INDEX('Detalle individual'!$D:$D,Cálculos!$AE8)) -> Gerencia de Negocios | C8: =IF($A8="","",COUNTIFS('Detalle individual'!$C$5:$C$1000, A8, 'Detalle individual'!$F$5:$F$1000, "Completado")+COUNTIFS('Detalle individual'!$C$5:$C$1000, A8, 'Detalle individual'!$F$5:$F$1000, "Pendiente")) -> 16 | D8: =IF($A8="","",COUNTIFS('Detalle individual'!$C$5:$C$1000, A8, 'Detalle individual'!$F$5:$F$1000, "Completado")) -> 16 | E8: =IF($A8="","",C8-D8) -> 0 | F8: =IF($A8="","",IF(C8>0, D8/C8, 0)) -> 1 | G8: =IF($A8="","",IF(AND(C8>0, D8=C8), "Completo", "Pendiente")) -> Completo | H8: =IF($A8="","",IF(D8>0, IFERROR(AVERAGEIFS('Detalle individual'!$J$5:$J$1000, 'Detalle individual'!$C$5:$C$1000, A8), ""), "")) -> 96.25 | I8: =IF($A8="","",IF(D8>0, IFERROR(_xlfn.MAXIFS('Detalle individual'!$J$5:$J$1000, 'Detalle individual'!$C$5:$C$1000, A8), ""), "")) -> 100 | J8: =IF($A8="","",IF(D8>0, IFERROR(_xlfn.MINIFS('Detalle individual'!$J$5:$J$1000, 'Detalle individual'!$C$5:$C$1000, A8), ""), "")) -> 75 | K8: =IF($A8="","",IF(D8>0, IFERROR(_xlfn.MINIFS('Detalle individual'!$G$5:$G$1000, 'Detalle individual'!$C$5:$C$1000, A8), ""), "")) -> 46302.47 | L8: =IF($A8="","",IF(D8>0, IFERROR(_xlfn.MAXIFS('Detalle individual'!$H$5:$H$1000, 'Detalle individual'!$C$5:$C$1000, A8), ""), "")) -> 46311.72 | M8: =IF($A8="","",IF(D8>0, IFERROR(_xlfn.MINIFS('Detalle individual'!$I$5:$I$1000, 'Detalle individual'!$C$5:$C$1000, A8), ""), "")) -> 1.75 | N8: =IF($A8="","",IF(D8>0, IFERROR(AVERAGEIFS('Detalle individual'!$I$5:$I$1000, 'Detalle individual'!$C$5:$C$1000, A8), ""), "")) -> 16.236458 | O8: =IF($A8="","",COUNTIF('Detalle individual'!$C$5:$C$1000, A8)-C8) -> 2
A9: =IF(Cálculos!$AE9="","",INDEX('Detalle individual'!$C:$C,Cálculos!$AE9)) -> AGENCIA COLEGIO MEDICO | B9: =IF($A9="","",INDEX('Detalle individual'!$D:$D,Cálculos!$AE9)) -> Gerencia de Negocios | C9: =IF($A9="","",COUNTIFS('Detalle individual'!$C$5:$C$1000, A9, 'Detalle individual'!$F$5:$F$1000, "Completado")+COUNTIFS('Detalle individual'!$C$5:$C$1000, A9, 'Detalle individual'!$F$5:$F$1000, "Pendiente")) -> 11 | D9: =IF($A9="","",COUNTIFS('Detalle individual'!$C$5:$C$1000, A9, 'Detalle individual'!$F$5:$F$1000, "Completado")) -> 11 | E9: =IF($A9="","",C9-D9) -> 0 | F9: =IF($A9="","",IF(C9>0, D9/C9, 0)) -> 1 | G9: =IF($A9="","",IF(AND(C9>0, D9=C9), "Completo", "Pendiente")) -> Completo | H9: =IF($A9="","",IF(D9>0, IFERROR(AVERAGEIFS('Detalle individual'!$J$5:$J$1000, 'Detalle individual'!$C$5:$C$1000, A9), ""), "")) -> 97.272727 | I9: =IF($A9="","",IF(D9>0, IFERROR(_xlfn.MAXIFS('Detalle individual'!$J$5:$J$1000, 'Detalle individual'!$C$5:$C$1000, A9), ""), "")) -> 100 | J9: =IF($A9="","",IF(D9>0, IFERROR(_xlfn.MINIFS('Detalle individual'!$J$5:$J$1000, 'Detalle individual'!$C$5:$C$1000, A9), ""), "")) -> 90 | K9: =IF($A9="","",IF(D9>0, IFERROR(_xlfn.MINIFS('Detalle individual'!$G$5:$G$1000, 'Detalle individual'!$C$5:$C$1000, A9), ""), "")) -> 46296.471 | L9: =IF($A9="","",IF(D9>0, IFERROR(_xlfn.MAXIFS('Detalle individual'!$H$5:$H$1000, 'Detalle individual'!$C$5:$C$1000, A9), ""), "")) -> 46310.516 | M9: =IF($A9="","",IF(D9>0, IFERROR(_xlfn.MINIFS('Detalle individual'!$I$5:$I$1000, 'Detalle individual'!$C$5:$C$1000, A9), ""), "")) -> 3.1 | N9: =IF($A9="","",IF(D9>0, IFERROR(AVERAGEIFS('Detalle individual'!$I$5:$I$1000, 'Detalle individual'!$C$5:$C$1000, A9), ""), "")) -> 9.569697 | O9: =IF($A9="","",COUNTIF('Detalle individual'!$C$5:$C$1000, A9)-C9) -> 1
A10: =IF(Cálculos!$AE10="","",INDEX('Detalle individual'!$C:$C,Cálculos!$AE10)) -> AGENCIA COLONIA MEDICA | B10: =IF($A10="","",INDEX('Detalle individual'!$D:$D,Cálculos!$AE10)) -> Gerencia de Negocios | C10: =IF($A10="","",COUNTIFS('Detalle individual'!$C$5:$C$1000, A10, 'Detalle individual'!$F$5:$F$1000, "Completado")+COUNTIFS('Detalle individual'!$C$5:$C$1000, A10, 'Detalle individual'!$F$5:$F$1000, "Pendiente")) -> 16 | D10: =IF($A10="","",COUNTIFS('Detalle individual'!$C$5:$C$1000, A10, 'Detalle individual'!$F$5:$F$1000, "Completado")) -> 16 | E10: =IF($A10="","",C10-D10) -> 0 | F10: =IF($A10="","",IF(C10>0, D10/C10, 0)) -> 1 | G10: =IF($A10="","",IF(AND(C10>0, D10=C10), "Completo", "Pendiente")) -> Completo | H10: =IF($A10="","",IF(D10>0, IFERROR(AVERAGEIFS('Detalle individual'!$J$5:$J$1000, 'Detalle individual'!$C$5:$C$1000, A10), ""), "")) -> 97.8125 | I10: =IF($A10="","",IF(D10>0, IFERROR(_xlfn.MAXIFS('Detalle individual'!$J$5:$J$1000, 'Detalle individual'!$C$5:$C$1000, A10), ""), "")) -> 100 | J10: =IF($A10="","",IF(D10>0, IFERROR(_xlfn.MINIFS('Detalle individual'!$J$5:$J$1000, 'Detalle individual'!$C$5:$C$1000, A10), ""), "")) -> 90 | K10: =IF($A10="","",IF(D10>0, IFERROR(_xlfn.MINIFS('Detalle individual'!$G$5:$G$1000, 'Detalle individual'!$C$5:$C$1000, A10), ""), "")) -> 46297.712 | L10: =IF($A10="","",IF(D10>0, IFERROR(_xlfn.MAXIFS('Detalle individual'!$H$5:$H$1000, 'Detalle individual'!$C$5:$C$1000, A10), ""), "")) -> 46311.71 | M10: =IF($A10="","",IF(D10>0, IFERROR(_xlfn.MINIFS('Detalle individual'!$I$5:$I$1000, 'Detalle individual'!$C$5:$C$1000, A10), ""), "")) -> 1.6 | N10: =IF($A10="","",IF(D10>0, IFERROR(AVERAGEIFS('Detalle individual'!$I$5:$I$1000, 'Detalle individual'!$C$5:$C$1000, A10), ""), "")) -> 17.919792 | O10: =IF($A10="","",COUNTIF('Detalle individual'!$C$5:$C$1000, A10)-C10) -> 0
A11: =IF(Cálculos!$AE11="","",INDEX('Detalle individual'!$C:$C,Cálculos!$AE11)) -> AGENCIA MERLIOT | B11: =IF($A11="","",INDEX('Detalle individual'!$D:$D,Cálculos!$AE11)) -> Gerencia de Negocios | C11: =IF($A11="","",COUNTIFS('Detalle individual'!$C$5:$C$1000, A11, 'Detalle individual'!$F$5:$F$1000, "Completado")+COUNTIFS('Detalle individual'!$C$5:$C$1000, A11, 'Detalle individual'!$F$5:$F$1000, "Pendiente")) -> 13 | D11: =IF($A11="","",COUNTIFS('Detalle individual'!$C$5:$C$1000, A11, 'Detalle individual'!$F$5:$F$1000, "Completado")) -> 13 | E11: =IF($A11="","",C11-D11) -> 0 | F11: =IF($A11="","",IF(C11>0, D11/C11, 0)) -> 1 | G11: =IF($A11="","",IF(AND(C11>0, D11=C11), "Completo", "Pendiente")) -> Completo | H11: =IF($A11="","",IF(D11>0, IFERROR(AVERAGEIFS('Detalle individual'!$J$5:$J$1000, 'Detalle individual'!$C$5:$C$1000, A11), ""), "")) -> 95.769231 | I11: =IF($A11="","",IF(D11>0, IFERROR(_xlfn.MAXIFS('Detalle individual'!$J$5:$J$1000, 'Detalle individual'!$C$5:$C$1000, A11), ""), "")) -> 100 | J11: =IF($A11="","",IF(D11>0, IFERROR(_xlfn.MINIFS('Detalle individual'!$J$5:$J$1000, 'Detalle individual'!$C$5:$C$1000, A11), ""), "")) -> 70 | K11: =IF($A11="","",IF(D11>0, IFERROR(_xlfn.MINIFS('Detalle individual'!$G$5:$G$1000, 'Detalle individual'!$C$5:$C$1000, A11), ""), "")) -> 46296.547 | L11: =IF($A11="","",IF(D11>0, IFERROR(_xlfn.MAXIFS('Detalle individual'!$H$5:$H$1000, 'Detalle individual'!$C$5:$C$1000, A11), ""), "")) -> 46310.525 | M11: =IF($A11="","",IF(D11>0, IFERROR(_xlfn.MINIFS('Detalle individual'!$I$5:$I$1000, 'Detalle individual'!$C$5:$C$1000, A11), ""), "")) -> 1.7833333 | N11: =IF($A11="","",IF(D11>0, IFERROR(AVERAGEIFS('Detalle individual'!$I$5:$I$1000, 'Detalle individual'!$C$5:$C$1000, A11), ""), "")) -> 8.7564103 | O11: =IF($A11="","",COUNTIF('Detalle individual'!$C$5:$C$1000, A11)-C11) -> 0
A12: =IF(Cálculos!$AE12="","",INDEX('Detalle individual'!$C:$C,Cálculos!$AE12)) -> AGENCIA PLAZA MUNDO | B12: =IF($A12="","",INDEX('Detalle individual'!$D:$D,Cálculos!$AE12)) -> Gerencia de Negocios | C12: =IF($A12="","",COUNTIFS('Detalle individual'!$C$5:$C$1000, A12, 'Detalle individual'!$F$5:$F$1000, "Completado")+COUNTIFS('Detalle individual'!$C$5:$C$1000, A12, 'Detalle individual'!$F$5:$F$1000, "Pendiente")) -> 8 | D12: =IF($A12="","",COUNTIFS('Detalle individual'!$C$5:$C$1000, A12, 'Detalle individual'!$F$5:$F$1000, "Completado")) -> 8 | E12: =IF($A12="","",C12-D12) -> 0 | F12: =IF($A12="","",IF(C12>0, D12/C12, 0)) -> 1 | G12: =IF($A12="","",IF(AND(C12>0, D12=C12), "Completo", "Pendiente")) -> Completo | H12: =IF($A12="","",IF(D12>0, IFERROR(AVERAGEIFS('Detalle individual'!$J$5:$J$1000, 'Detalle individual'!$C$5:$C$1000, A12), ""), "")) -> 98.75 | I12: =IF($A12="","",IF(D12>0, IFERROR(_xlfn.MAXIFS('Detalle individual'!$J$5:$J$1000, 'Detalle individual'!$C$5:$C$1000, A12), ""), "")) -> 100 | J12: =IF($A12="","",IF(D12>0, IFERROR(_xlfn.MINIFS('Detalle individual'!$J$5:$J$1000, 'Detalle individual'!$C$5:$C$1000, A12), ""), "")) -> 90 | K12: =IF($A12="","",IF(D12>0, IFERROR(_xlfn.MINIFS('Detalle individual'!$G$5:$G$1000, 'Detalle individual'!$C$5:$C$1000, A12), ""), "")) -> 46307.4 | L12: =IF($A12="","",IF(D12>0, IFERROR(_xlfn.MAXIFS('Detalle individual'!$H$5:$H$1000, 'Detalle individual'!$C$5:$C$1000, A12), ""), "")) -> 46310.646 | M12: =IF($A12="","",IF(D12>0, IFERROR(_xlfn.MINIFS('Detalle individual'!$I$5:$I$1000, 'Detalle individual'!$C$5:$C$1000, A12), ""), "")) -> 2.8166667 | N12: =IF($A12="","",IF(D12>0, IFERROR(AVERAGEIFS('Detalle individual'!$I$5:$I$1000, 'Detalle individual'!$C$5:$C$1000, A12), ""), "")) -> 6.2770833 | O12: =IF($A12="","",COUNTIF('Detalle individual'!$C$5:$C$1000, A12)-C12) -> 0
A13: =IF(Cálculos!$AE13="","",INDEX('Detalle individual'!$C:$C,Cálculos!$AE13)) -> AGENCIA SAN MIGUEL | B13: =IF($A13="","",INDEX('Detalle individual'!$D:$D,Cálculos!$AE13)) -> Gerencia de Negocios | C13: =IF($A13="","",COUNTIFS('Detalle individual'!$C$5:$C$1000, A13, 'Detalle individual'!$F$5:$F$1000, "Completado")+COUNTIFS('Detalle individual'!$C$5:$C$1000, A13, 'Detalle individual'!$F$5:$F$1000, "Pendiente")) -> 7 | D13: =IF($A13="","",COUNTIFS('Detalle individual'!$C$5:$C$1000, A13, 'Detalle individual'!$F$5:$F$1000, "Completado")) -> 7 | E13: =IF($A13="","",C13-D13) -> 0 | F13: =IF($A13="","",IF(C13>0, D13/C13, 0)) -> 1 | G13: =IF($A13="","",IF(AND(C13>0, D13=C13), "Completo", "Pendiente")) -> Completo | H13: =IF($A13="","",IF(D13>0, IFERROR(AVERAGEIFS('Detalle individual'!$J$5:$J$1000, 'Detalle individual'!$C$5:$C$1000, A13), ""), "")) -> 98.571429 | I13: =IF($A13="","",IF(D13>0, IFERROR(_xlfn.MAXIFS('Detalle individual'!$J$5:$J$1000, 'Detalle individual'!$C$5:$C$1000, A13), ""), "")) -> 100 | J13: =IF($A13="","",IF(D13>0, IFERROR(_xlfn.MINIFS('Detalle individual'!$J$5:$J$1000, 'Detalle individual'!$C$5:$C$1000, A13), ""), "")) -> 90 | K13: =IF($A13="","",IF(D13>0, IFERROR(_xlfn.MINIFS('Detalle individual'!$G$5:$G$1000, 'Detalle individual'!$C$5:$C$1000, A13), ""), "")) -> 46296.435 | L13: =IF($A13="","",IF(D13>0, IFERROR(_xlfn.MAXIFS('Detalle individual'!$H$5:$H$1000, 'Detalle individual'!$C$5:$C$1000, A13), ""), "")) -> 46296.492 | M13: =IF($A13="","",IF(D13>0, IFERROR(_xlfn.MINIFS('Detalle individual'!$I$5:$I$1000, 'Detalle individual'!$C$5:$C$1000, A13), ""), "")) -> 2.95 | N13: =IF($A13="","",IF(D13>0, IFERROR(AVERAGEIFS('Detalle individual'!$I$5:$I$1000, 'Detalle individual'!$C$5:$C$1000, A13), ""), "")) -> 5.1666667 | O13: =IF($A13="","",COUNTIF('Detalle individual'!$C$5:$C$1000, A13)-C13) -> 1
A14: =IF(Cálculos!$AE14="","",INDEX('Detalle individual'!$C:$C,Cálculos!$AE14)) -> AGENCIA SANTA ANA | B14: =IF($A14="","",INDEX('Detalle individual'!$D:$D,Cálculos!$AE14)) -> Gerencia de Negocios | C14: =IF($A14="","",COUNTIFS('Detalle individual'!$C$5:$C$1000, A14, 'Detalle individual'!$F$5:$F$1000, "Completado")+COUNTIFS('Detalle individual'!$C$5:$C$1000, A14, 'Detalle individual'!$F$5:$F$1000, "Pendiente")) -> 8 | D14: =IF($A14="","",COUNTIFS('Detalle individual'!$C$5:$C$1000, A14, 'Detalle individual'!$F$5:$F$1000, "Completado")) -> 8 | E14: =IF($A14="","",C14-D14) -> 0 | F14: =IF($A14="","",IF(C14>0, D14/C14, 0)) -> 1 | G14: =IF($A14="","",IF(AND(C14>0, D14=C14), "Completo", "Pendiente")) -> Completo | H14: =IF($A14="","",IF(D14>0, IFERROR(AVERAGEIFS('Detalle individual'!$J$5:$J$1000, 'Detalle individual'!$C$5:$C$1000, A14), ""), "")) -> 97.5 | I14: =IF($A14="","",IF(D14>0, IFERROR(_xlfn.MAXIFS('Detalle individual'!$J$5:$J$1000, 'Detalle individual'!$C$5:$C$1000, A14), ""), "")) -> 100 | J14: =IF($A14="","",IF(D14>0, IFERROR(_xlfn.MINIFS('Detalle individual'!$J$5:$J$1000, 'Detalle individual'!$C$5:$C$1000, A14), ""), "")) -> 90 | K14: =IF($A14="","",IF(D14>0, IFERROR(_xlfn.MINIFS('Detalle individual'!$G$5:$G$1000, 'Detalle individual'!$C$5:$C$1000, A14), ""), "")) -> 46309.337 | L14: =IF($A14="","",IF(D14>0, IFERROR(_xlfn.MAXIFS('Detalle individual'!$H$5:$H$1000, 'Detalle individual'!$C$5:$C$1000, A14), ""), "")) -> 46311.494 | M14: =IF($A14="","",IF(D14>0, IFERROR(_xlfn.MINIFS('Detalle individual'!$I$5:$I$1000, 'Detalle individual'!$C$5:$C$1000, A14), ""), "")) -> 2.2833333 | N14: =IF($A14="","",IF(D14>0, IFERROR(AVERAGEIFS('Detalle individual'!$I$5:$I$1000, 'Detalle individual'!$C$5:$C$1000, A14), ""), "")) -> 7.99375 | O14: =IF($A14="","",COUNTIF('Detalle individual'!$C$5:$C$1000, A14)-C14) -> 0
A15: =IF(Cálculos!$AE15="","",INDEX('Detalle individual'!$C:$C,Cálculos!$AE15)) -> AGENCIA SONSONATE | B15: =IF($A15="","",INDEX('Detalle individual'!$D:$D,Cálculos!$AE15)) -> Gerencia de Negocios | C15: =IF($A15="","",COUNTIFS('Detalle individual'!$C$5:$C$1000, A15, 'Detalle individual'!$F$5:$F$1000, "Completado")+COUNTIFS('Detalle individual'!$C$5:$C$1000, A15, 'Detalle individual'!$F$5:$F$1000, "Pendiente")) -> 7 | D15: =IF($A15="","",COUNTIFS('Detalle individual'!$C$5:$C$1000, A15, 'Detalle individual'!$F$5:$F$1000, "Completado")) -> 7 | E15: =IF($A15="","",C15-D15) -> 0 | F15: =IF($A15="","",IF(C15>0, D15/C15, 0)) -> 1 | G15: =IF($A15="","",IF(AND(C15>0, D15=C15), "Completo", "Pendiente")) -> Completo | H15: =IF($A15="","",IF(D15>0, IFERROR(AVERAGEIFS('Detalle individual'!$J$5:$J$1000, 'Detalle individual'!$C$5:$C$1000, A15), ""), "")) -> 97.142857 | I15: =IF($A15="","",IF(D15>0, IFERROR(_xlfn.MAXIFS('Detalle individual'!$J$5:$J$1000, 'Detalle individual'!$C$5:$C$1000, A15), ""), "")) -> 100 | J15: =IF($A15="","",IF(D15>0, IFERROR(_xlfn.MINIFS('Detalle individual'!$J$5:$J$1000, 'Detalle individual'!$C$5:$C$1000, A15), ""), "")) -> 80 | K15: =IF($A15="","",IF(D15>0, IFERROR(_xlfn.MINIFS('Detalle individual'!$G$5:$G$1000, 'Detalle individual'!$C$5:$C$1000, A15), ""), "")) -> 46308.436 | L15: =IF($A15="","",IF(D15>0, IFERROR(_xlfn.MAXIFS('Detalle individual'!$H$5:$H$1000, 'Detalle individual'!$C$5:$C$1000, A15), ""), "")) -> 46311.571 | M15: =IF($A15="","",IF(D15>0, IFERROR(_xlfn.MINIFS('Detalle individual'!$I$5:$I$1000, 'Detalle individual'!$C$5:$C$1000, A15), ""), "")) -> 1.5166667 | N15: =IF($A15="","",IF(D15>0, IFERROR(AVERAGEIFS('Detalle individual'!$I$5:$I$1000, 'Detalle individual'!$C$5:$C$1000, A15), ""), "")) -> 9.9571429 | O15: =IF($A15="","",COUNTIF('Detalle individual'!$C$5:$C$1000, A15)-C15) -> 0
A16: =IF(Cálculos!$AE16="","",INDEX('Detalle individual'!$C:$C,Cálculos!$AE16)) -> AGENCIA USULUTAN | B16: =IF($A16="","",INDEX('Detalle individual'!$D:$D,Cálculos!$AE16)) -> Gerencia de Negocios | C16: =IF($A16="","",COUNTIFS('Detalle individual'!$C$5:$C$1000, A16, 'Detalle individual'!$F$5:$F$1000, "Completado")+COUNTIFS('Detalle individual'!$C$5:$C$1000, A16, 'Detalle individual'!$F$5:$F$1000, "Pendiente")) -> 7 | D16: =IF($A16="","",COUNTIFS('Detalle individual'!$C$5:$C$1000, A16, 'Detalle individual'!$F$5:$F$1000, "Completado")) -> 7 | E16: =IF($A16="","",C16-D16) -> 0 | F16: =IF($A16="","",IF(C16>0, D16/C16, 0)) -> 1 | G16: =IF($A16="","",IF(AND(C16>0, D16=C16), "Completo", "Pendiente")) -> Completo | H16: =IF($A16="","",IF(D16>0, IFERROR(AVERAGEIFS('Detalle individual'!$J$5:$J$1000, 'Detalle individual'!$C$5:$C$1000, A16), ""), "")) -> 100 | I16: =IF($A16="","",IF(D16>0, IFERROR(_xlfn.MAXIFS('Detalle individual'!$J$5:$J$1000, 'Detalle individual'!$C$5:$C$1000, A16), ""), "")) -> 100 | J16: =IF($A16="","",IF(D16>0, IFERROR(_xlfn.MINIFS('Detalle individual'!$J$5:$J$1000, 'Detalle individual'!$C$5:$C$1000, A16), ""), "")) -> 100 | K16: =IF($A16="","",IF(D16>0, IFERROR(_xlfn.MINIFS('Detalle individual'!$G$5:$G$1000, 'Detalle individual'!$C$5:$C$1000, A16), ""), "")) -> 46301.426 | L16: =IF($A16="","",IF(D16>0, IFERROR(_xlfn.MAXIFS('Detalle individual'!$H$5:$H$1000, 'Detalle individual'!$C$5:$C$1000, A16), ""), "")) -> 46309.42 | M16: =IF($A16="","",IF(D16>0, IFERROR(_xlfn.MINIFS('Detalle individual'!$I$5:$I$1000, 'Detalle individual'!$C$5:$C$1000, A16), ""), "")) -> 2.9833333 | N16: =IF($A16="","",IF(D16>0, IFERROR(AVERAGEIFS('Detalle individual'!$I$5:$I$1000, 'Detalle individual'!$C$5:$C$1000, A16), ""), "")) -> 17.85 | O16: =IF($A16="","",COUNTIF('Detalle individual'!$C$5:$C$1000, A16)-C16) -> 0
... A84: =IF(Cálculos!$AE84="","",INDEX('Detalle individual'!$C:$C,Cálculos!$AE84)) | B84: =IF($A84="","",INDEX('Detalle individual'!$D:$D,Cálculos!$AE84)) | C84: =IF($A84="","",COUNTIFS('Detalle individual'!$C$5:$C$1000, A84, 'Detalle individual'!$F$5:$F$1000, "Completado")+COUNTIFS('Detalle individual'!$C$5:$C$1000, A84, 'Detalle individual'!$F$5:$F$1000, "Pendiente")) | D84: =IF($A84="","",COUNTIFS('Detalle individual'!$C$5:$C$1000, A84, 'Detalle individual'!$F$5:$F$1000, "Completado")) | E84: =IF($A84="","",C84-D84) | F84: =IF($A84="","",IF(C84>0, D84/C84, 0)) | G84: =IF($A84="","",IF(AND(C84>0, D84=C84), "Completo", "Pendiente")) | H84: =IF($A84="","",IF(D84>0, IFERROR(AVERAGEIFS('Detalle individual'!$J$5:$J$1000, 'Detalle individual'!$C$5:$C$1000, A84), ""), "")) | I84: =IF($A84="","",IF(D84>0, IFERROR(_xlfn.MAXIFS('Detalle individual'!$J$5:$J$1000, 'Detalle individual'!$C$5:$C$1000, A84), ""), "")) | J84: =IF($A84="","",IF(D84>0, IFERROR(_xlfn.MINIFS('Detalle individual'!$J$5:$J$1000, 'Detalle individual'!$C$5:$C$1000, A84), ""), "")) | K84: =IF($A84="","",IF(D84>0, IFERROR(_xlfn.MINIFS('Detalle individual'!$G$5:$G$1000, 'Detalle individual'!$C$5:$C$1000, A84), ""), "")) | L84: =IF($A84="","",IF(D84>0, IFERROR(_xlfn.MAXIFS('Detalle individual'!$H$5:$H$1000, 'Detalle individual'!$C$5:$C$1000, A84), ""), "")) | M84: =IF($A84="","",IF(D84>0, IFERROR(_xlfn.MINIFS('Detalle individual'!$I$5:$I$1000, 'Detalle individual'!$C$5:$C$1000, A84), ""), "")) | N84: =IF($A84="","",IF(D84>0, IFERROR(AVERAGEIFS('Detalle individual'!$I$5:$I$1000, 'Detalle individual'!$C$5:$C$1000, A84), ""), "")) | O84: =IF($A84="","",COUNTIF('Detalle individual'!$C$5:$C$1000, A84)-C84)

Sheet Consolidado por Gerencia
A1: CONSOLIDADO DE EVALUACIÓN POR GERENCIA
A2: Cálculos automáticos basados en la hoja 'Detalle individual' agrupados por Gerencia Asignada
A4: Gerencia / Área Superior | B4: Personal Esperado | C4: Personas Completadas | D4: Pendientes | E4: % Cumplimiento | F4: Estado | G4: Promedio Nota | H4: Nota Máxima | I4: Nota Mínima | J4: Primer Inicio | K4: Última Finalización | L4: Menor Duración (min) | M4: Promedio Duración (min) | N4: Justificados (no cuentan)
A5: =IF(Cálculos!$AF5="","",INDEX('Detalle individual'!$D:$D,Cálculos!$AF5)) -> Auditoría Interna | B5: =IF($A5="","",COUNTIFS('Detalle individual'!$D$5:$D$1000, A5, 'Detalle individual'!$F$5:$F$1000, "Completado")+COUNTIFS('Detalle individual'!$D$5:$D$1000, A5, 'Detalle individual'!$F$5:$F$1000, "Pendiente")) -> 7 | C5: =IF($A5="","",COUNTIFS('Detalle individual'!$D$5:$D$1000, A5, 'Detalle individual'!$F$5:$F$1000, "Completado")) -> 7 | D5: =IF($A5="","",B5-C5) -> 0 | E5: =IF($A5="","",IF(B5>0, C5/B5, 0)) -> 1 | F5: =IF($A5="","",IF(AND(B5>0, C5=B5), "Completo", "Pendiente")) -> Completo | G5: =IF($A5="","",IF(C5>0, IFERROR(AVERAGEIFS('Detalle individual'!$J$5:$J$1000, 'Detalle individual'!$D$5:$D$1000, A5), ""), "")) -> 97.142857 | H5: =IF($A5="","",IF(C5>0, IFERROR(_xlfn.MAXIFS('Detalle individual'!$J$5:$J$1000, 'Detalle individual'!$D$5:$D$1000, A5), ""), "")) -> 100 | I5: =IF($A5="","",IF(C5>0, IFERROR(_xlfn.MINIFS('Detalle individual'!$J$5:$J$1000, 'Detalle individual'!$D$5:$D$1000, A5), ""), "")) -> 90 | J5: =IF($A5="","",IF(C5>0, IFERROR(_xlfn.MINIFS('Detalle individual'!$G$5:$G$1000, 'Detalle individual'!$D$5:$D$1000, A5), ""), "")) -> 46296.618 | K5: =IF($A5="","",IF(C5>0, IFERROR(_xlfn.MAXIFS('Detalle individual'!$H$5:$H$1000, 'Detalle individual'!$D$5:$D$1000, A5), ""), "")) -> 46307.653 | L5: =IF($A5="","",IF(C5>0, IFERROR(_xlfn.MINIFS('Detalle individual'!$I$5:$I$1000, 'Detalle individual'!$D$5:$D$1000, A5), ""), "")) -> 3.8 | M5: =IF($A5="","",IF(C5>0, IFERROR(AVERAGEIFS('Detalle individual'!$I$5:$I$1000, 'Detalle individual'!$D$5:$D$1000, A5), ""), "")) -> 6.5452381 | N5: =IF($A5="","",COUNTIF('Detalle individual'!$D$5:$D$1000, A5)-B5) -> 0
A6: =IF(Cálculos!$AF6="","",INDEX('Detalle individual'!$D:$D,Cálculos!$AF6)) -> Consejo de Administración | B6: =IF($A6="","",COUNTIFS('Detalle individual'!$D$5:$D$1000, A6, 'Detalle individual'!$F$5:$F$1000, "Completado")+COUNTIFS('Detalle individual'!$D$5:$D$1000, A6, 'Detalle individual'!$F$5:$F$1000, "Pendiente")) -> 1 | C6: =IF($A6="","",COUNTIFS('Detalle individual'!$D$5:$D$1000, A6, 'Detalle individual'!$F$5:$F$1000, "Completado")) -> 1 | D6: =IF($A6="","",B6-C6) -> 0 | E6: =IF($A6="","",IF(B6>0, C6/B6, 0)) -> 1 | F6: =IF($A6="","",IF(AND(B6>0, C6=B6), "Completo", "Pendiente")) -> Completo | G6: =IF($A6="","",IF(C6>0, IFERROR(AVERAGEIFS('Detalle individual'!$J$5:$J$1000, 'Detalle individual'!$D$5:$D$1000, A6), ""), "")) -> 90 | H6: =IF($A6="","",IF(C6>0, IFERROR(_xlfn.MAXIFS('Detalle individual'!$J$5:$J$1000, 'Detalle individual'!$D$5:$D$1000, A6), ""), "")) -> 90 | I6: =IF($A6="","",IF(C6>0, IFERROR(_xlfn.MINIFS('Detalle individual'!$J$5:$J$1000, 'Detalle individual'!$D$5:$D$1000, A6), ""), "")) -> 90 | J6: =IF($A6="","",IF(C6>0, IFERROR(_xlfn.MINIFS('Detalle individual'!$G$5:$G$1000, 'Detalle individual'!$D$5:$D$1000, A6), ""), "")) -> 46300.652 | K6: =IF($A6="","",IF(C6>0, IFERROR(_xlfn.MAXIFS('Detalle individual'!$H$5:$H$1000, 'Detalle individual'!$D$5:$D$1000, A6), ""), "")) -> 46300.658 | L6: =IF($A6="","",IF(C6>0, IFERROR(_xlfn.MINIFS('Detalle individual'!$I$5:$I$1000, 'Detalle individual'!$D$5:$D$1000, A6), ""), "")) -> 7.9666667 | M6: =IF($A6="","",IF(C6>0, IFERROR(AVERAGEIFS('Detalle individual'!$I$5:$I$1000, 'Detalle individual'!$D$5:$D$1000, A6), ""), "")) -> 7.9666667 | N6: =IF($A6="","",COUNTIF('Detalle individual'!$D$5:$D$1000, A6)-B6) -> 0
A7: =IF(Cálculos!$AF7="","",INDEX('Detalle individual'!$D:$D,Cálculos!$AF7)) -> Gerencia Administrativa | B7: =IF($A7="","",COUNTIFS('Detalle individual'!$D$5:$D$1000, A7, 'Detalle individual'!$F$5:$F$1000, "Completado")+COUNTIFS('Detalle individual'!$D$5:$D$1000, A7, 'Detalle individual'!$F$5:$F$1000, "Pendiente")) -> 34 | C7: =IF($A7="","",COUNTIFS('Detalle individual'!$D$5:$D$1000, A7, 'Detalle individual'!$F$5:$F$1000, "Completado")) -> 34 | D7: =IF($A7="","",B7-C7) -> 0 | E7: =IF($A7="","",IF(B7>0, C7/B7, 0)) -> 1 | F7: =IF($A7="","",IF(AND(B7>0, C7=B7), "Completo", "Pendiente")) -> Completo | G7: =IF($A7="","",IF(C7>0, IFERROR(AVERAGEIFS('Detalle individual'!$J$5:$J$1000, 'Detalle individual'!$D$5:$D$1000, A7), ""), "")) -> 94.264706 | H7: =IF($A7="","",IF(C7>0, IFERROR(_xlfn.MAXIFS('Detalle individual'!$J$5:$J$1000, 'Detalle individual'!$D$5:$D$1000, A7), ""), "")) -> 100 | I7: =IF($A7="","",IF(C7>0, IFERROR(_xlfn.MINIFS('Detalle individual'!$J$5:$J$1000, 'Detalle individual'!$D$5:$D$1000, A7), ""), "")) -> 60 | J7: =IF($A7="","",IF(C7>0, IFERROR(_xlfn.MINIFS('Detalle individual'!$G$5:$G$1000, 'Detalle individual'!$D$5:$D$1000, A7), ""), "")) -> 46296.454 | K7: =IF($A7="","",IF(C7>0, IFERROR(_xlfn.MAXIFS('Detalle individual'!$H$5:$H$1000, 'Detalle individual'!$D$5:$D$1000, A7), ""), "")) -> 46310.511 | L7: =IF($A7="","",IF(C7>0, IFERROR(_xlfn.MINIFS('Detalle individual'!$I$5:$I$1000, 'Detalle individual'!$D$5:$D$1000, A7), ""), "")) -> 2.1166667 | M7: =IF($A7="","",IF(C7>0, IFERROR(AVERAGEIFS('Detalle individual'!$I$5:$I$1000, 'Detalle individual'!$D$5:$D$1000, A7), ""), "")) -> 10.554412 | N7: =IF($A7="","",COUNTIF('Detalle individual'!$D$5:$D$1000, A7)-B7) -> 1
A8: =IF(Cálculos!$AF8="","",INDEX('Detalle individual'!$D:$D,Cálculos!$AF8)) -> Gerencia de Finanzas y Planificación | B8: =IF($A8="","",COUNTIFS('Detalle individual'!$D$5:$D$1000, A8, 'Detalle individual'!$F$5:$F$1000, "Completado")+COUNTIFS('Detalle individual'!$D$5:$D$1000, A8, 'Detalle individual'!$F$5:$F$1000, "Pendiente")) -> 18 | C8: =IF($A8="","",COUNTIFS('Detalle individual'!$D$5:$D$1000, A8, 'Detalle individual'!$F$5:$F$1000, "Completado")) -> 18 | D8: =IF($A8="","",B8-C8) -> 0 | E8: =IF($A8="","",IF(B8>0, C8/B8, 0)) -> 1 | F8: =IF($A8="","",IF(AND(B8>0, C8=B8), "Completo", "Pendiente")) -> Completo | G8: =IF($A8="","",IF(C8>0, IFERROR(AVERAGEIFS('Detalle individual'!$J$5:$J$1000, 'Detalle individual'!$D$5:$D$1000, A8), ""), "")) -> 98.611111 | H8: =IF($A8="","",IF(C8>0, IFERROR(_xlfn.MAXIFS('Detalle individual'!$J$5:$J$1000, 'Detalle individual'!$D$5:$D$1000, A8), ""), "")) -> 100 | I8: =IF($A8="","",IF(C8>0, IFERROR(_xlfn.MINIFS('Detalle individual'!$J$5:$J$1000, 'Detalle individual'!$D$5:$D$1000, A8), ""), "")) -> 85 | J8: =IF($A8="","",IF(C8>0, IFERROR(_xlfn.MINIFS('Detalle individual'!$G$5:$G$1000, 'Detalle individual'!$D$5:$D$1000, A8), ""), "")) -> 46296.427 | K8: =IF($A8="","",IF(C8>0, IFERROR(_xlfn.MAXIFS('Detalle individual'!$H$5:$H$1000, 'Detalle individual'!$D$5:$D$1000, A8), ""), "")) -> 46311.627 | L8: =IF($A8="","",IF(C8>0, IFERROR(_xlfn.MINIFS('Detalle individual'!$I$5:$I$1000, 'Detalle individual'!$D$5:$D$1000, A8), ""), "")) -> 2.45 | M8: =IF($A8="","",IF(C8>0, IFERROR(AVERAGEIFS('Detalle individual'!$I$5:$I$1000, 'Detalle individual'!$D$5:$D$1000, A8), ""), "")) -> 7.612037 | N8: =IF($A8="","",COUNTIF('Detalle individual'!$D$5:$D$1000, A8)-B8) -> 0
A9: =IF(Cálculos!$AF9="","",INDEX('Detalle individual'!$D:$D,Cálculos!$AF9)) -> Gerencia de Negocios | B9: =IF($A9="","",COUNTIFS('Detalle individual'!$D$5:$D$1000, A9, 'Detalle individual'!$F$5:$F$1000, "Completado")+COUNTIFS('Detalle individual'!$D$5:$D$1000, A9, 'Detalle individual'!$F$5:$F$1000, "Pendiente")) -> 148 | C9: =IF($A9="","",COUNTIFS('Detalle individual'!$D$5:$D$1000, A9, 'Detalle individual'!$F$5:$F$1000, "Completado")) -> 148 | D9: =IF($A9="","",B9-C9) -> 0 | E9: =IF($A9="","",IF(B9>0, C9/B9, 0)) -> 1 | F9: =IF($A9="","",IF(AND(B9>0, C9=B9), "Completo", "Pendiente")) -> Completo | G9: =IF($A9="","",IF(C9>0, IFERROR(AVERAGEIFS('Detalle individual'!$J$5:$J$1000, 'Detalle individual'!$D$5:$D$1000, A9), ""), "")) -> 96.858108 | H9: =IF($A9="","",IF(C9>0, IFERROR(_xlfn.MAXIFS('Detalle individual'!$J$5:$J$1000, 'Detalle individual'!$D$5:$D$1000, A9), ""), "")) -> 100 | I9: =IF($A9="","",IF(C9>0, IFERROR(_xlfn.MINIFS('Detalle individual'!$J$5:$J$1000, 'Detalle individual'!$D$5:$D$1000, A9), ""), "")) -> 65 | J9: =IF($A9="","",IF(C9>0, IFERROR(_xlfn.MINIFS('Detalle individual'!$G$5:$G$1000, 'Detalle individual'!$D$5:$D$1000, A9), ""), "")) -> 46296.426 | K9: =IF($A9="","",IF(C9>0, IFERROR(_xlfn.MAXIFS('Detalle individual'!$H$5:$H$1000, 'Detalle individual'!$D$5:$D$1000, A9), ""), "")) -> 46311.72 | L9: =IF($A9="","",IF(C9>0, IFERROR(_xlfn.MINIFS('Detalle individual'!$I$5:$I$1000, 'Detalle individual'!$D$5:$D$1000, A9), ""), "")) -> 1.5166667 | M9: =IF($A9="","",IF(C9>0, IFERROR(AVERAGEIFS('Detalle individual'!$I$5:$I$1000, 'Detalle individual'!$D$5:$D$1000, A9), ""), "")) -> 12.113288 | N9: =IF($A9="","",COUNTIF('Detalle individual'!$D$5:$D$1000, A9)-B9) -> 6
A10: =IF(Cálculos!$AF10="","",INDEX('Detalle individual'!$D:$D,Cálculos!$AF10)) -> Gerencia de Oficialía de Cumplimiento | B10: =IF($A10="","",COUNTIFS('Detalle individual'!$D$5:$D$1000, A10, 'Detalle individual'!$F$5:$F$1000, "Completado")+COUNTIFS('Detalle individual'!$D$5:$D$1000, A10, 'Detalle individual'!$F$5:$F$1000, "Pendiente")) -> 7 | C10: =IF($A10="","",COUNTIFS('Detalle individual'!$D$5:$D$1000, A10, 'Detalle individual'!$F$5:$F$1000, "Completado")) -> 7 | D10: =IF($A10="","",B10-C10) -> 0 | E10: =IF($A10="","",IF(B10>0, C10/B10, 0)) -> 1 | F10: =IF($A10="","",IF(AND(B10>0, C10=B10), "Completo", "Pendiente")) -> Completo | G10: =IF($A10="","",IF(C10>0, IFERROR(AVERAGEIFS('Detalle individual'!$J$5:$J$1000, 'Detalle individual'!$D$5:$D$1000, A10), ""), "")) -> 100 | H10: =IF($A10="","",IF(C10>0, IFERROR(_xlfn.MAXIFS('Detalle individual'!$J$5:$J$1000, 'Detalle individual'!$D$5:$D$1000, A10), ""), "")) -> 100 | I10: =IF($A10="","",IF(C10>0, IFERROR(_xlfn.MINIFS('Detalle individual'!$J$5:$J$1000, 'Detalle individual'!$D$5:$D$1000, A10), ""), "")) -> 100 | J10: =IF($A10="","",IF(C10>0, IFERROR(_xlfn.MINIFS('Detalle individual'!$G$5:$G$1000, 'Detalle individual'!$D$5:$D$1000, A10), ""), "")) -> 46296.47 | K10: =IF($A10="","",IF(C10>0, IFERROR(_xlfn.MAXIFS('Detalle individual'!$H$5:$H$1000, 'Detalle individual'!$D$5:$D$1000, A10), ""), "")) -> 46296.497 | L10: =IF($A10="","",IF(C10>0, IFERROR(_xlfn.MINIFS('Detalle individual'!$I$5:$I$1000, 'Detalle individual'!$D$5:$D$1000, A10), ""), "")) -> 9.1666667 | M10: =IF($A10="","",IF(C10>0, IFERROR(AVERAGEIFS('Detalle individual'!$I$5:$I$1000, 'Detalle individual'!$D$5:$D$1000, A10), ""), "")) -> 11.964286 | N10: =IF($A10="","",COUNTIF('Detalle individual'!$D$5:$D$1000, A10)-B10) -> 0
A11: =IF(Cálculos!$AF11="","",INDEX('Detalle individual'!$D:$D,Cálculos!$AF11)) -> Gerencia de Operaciones | B11: =IF($A11="","",COUNTIFS('Detalle individual'!$D$5:$D$1000, A11, 'Detalle individual'!$F$5:$F$1000, "Completado")+COUNTIFS('Detalle individual'!$D$5:$D$1000, A11, 'Detalle individual'!$F$5:$F$1000, "Pendiente")) -> 24 | C11: =IF($A11="","",COUNTIFS('Detalle individual'!$D$5:$D$1000, A11, 'Detalle individual'!$F$5:$F$1000, "Completado")) -> 24 | D11: =IF($A11="","",B11-C11) -> 0 | E11: =IF($A11="","",IF(B11>0, C11/B11, 0)) -> 1 | F11: =IF($A11="","",IF(AND(B11>0, C11=B11), "Completo", "Pendiente")) -> Completo | G11: =IF($A11="","",IF(C11>0, IFERROR(AVERAGEIFS('Detalle individual'!$J$5:$J$1000, 'Detalle individual'!$D$5:$D$1000, A11), ""), "")) -> 95 | H11: =IF($A11="","",IF(C11>0, IFERROR(_xlfn.MAXIFS('Detalle individual'!$J$5:$J$1000, 'Detalle individual'!$D$5:$D$1000, A11), ""), "")) -> 100 | I11: =IF($A11="","",IF(C11>0, IFERROR(_xlfn.MINIFS('Detalle individual'!$J$5:$J$1000, 'Detalle individual'!$D$5:$D$1000, A11), ""), "")) -> 70 | J11: =IF($A11="","",IF(C11>0, IFERROR(_xlfn.MINIFS('Detalle individual'!$G$5:$G$1000, 'Detalle individual'!$D$5:$D$1000, A11), ""), "")) -> 46296.57 | K11: =IF($A11="","",IF(C11>0, IFERROR(_xlfn.MAXIFS('Detalle individual'!$H$5:$H$1000, 'Detalle individual'!$D$5:$D$1000, A11), ""), "")) -> 46311.814 | L11: =IF($A11="","",IF(C11>0, IFERROR(_xlfn.MINIFS('Detalle individual'!$I$5:$I$1000, 'Detalle individual'!$D$5:$D$1000, A11), ""), "")) -> 1.6833333 | M11: =IF($A11="","",IF(C11>0, IFERROR(AVERAGEIFS('Detalle individual'!$I$5:$I$1000, 'Detalle individual'!$D$5:$D$1000, A11), ""), "")) -> 9.45 | N11: =IF($A11="","",COUNTIF('Detalle individual'!$D$5:$D$1000, A11)-B11) -> 2
A12: =IF(Cálculos!$AF12="","",INDEX('Detalle individual'!$D:$D,Cálculos!$AF12)) -> Gerencia de Sistemas | B12: =IF($A12="","",COUNTIFS('Detalle individual'!$D$5:$D$1000, A12, 'Detalle individual'!$F$5:$F$1000, "Completado")+COUNTIFS('Detalle individual'!$D$5:$D$1000, A12, 'Detalle individual'!$F$5:$F$1000, "Pendiente")) -> 22 | C12: =IF($A12="","",COUNTIFS('Detalle individual'!$D$5:$D$1000, A12, 'Detalle individual'!$F$5:$F$1000, "Completado")) -> 22 | D12: =IF($A12="","",B12-C12) -> 0 | E12: =IF($A12="","",IF(B12>0, C12/B12, 0)) -> 1 | F12: =IF($A12="","",IF(AND(B12>0, C12=B12), "Completo", "Pendiente")) -> Completo | G12: =IF($A12="","",IF(C12>0, IFERROR(AVERAGEIFS('Detalle individual'!$J$5:$J$1000, 'Detalle individual'!$D$5:$D$1000, A12), ""), "")) -> 99.545455 | H12: =IF($A12="","",IF(C12>0, IFERROR(_xlfn.MAXIFS('Detalle individual'!$J$5:$J$1000, 'Detalle individual'!$D$5:$D$1000, A12), ""), "")) -> 100 | I12: =IF($A12="","",IF(C12>0, IFERROR(_xlfn.MINIFS('Detalle individual'!$J$5:$J$1000, 'Detalle individual'!$D$5:$D$1000, A12), ""), "")) -> 95 | J12: =IF($A12="","",IF(C12>0, IFERROR(_xlfn.MINIFS('Detalle individual'!$G$5:$G$1000, 'Detalle individual'!$D$5:$D$1000, A12), ""), "")) -> 46296.57 | K12: =IF($A12="","",IF(C12>0, IFERROR(_xlfn.MAXIFS('Detalle individual'!$H$5:$H$1000, 'Detalle individual'!$D$5:$D$1000, A12), ""), "")) -> 46310.697 | L12: =IF($A12="","",IF(C12>0, IFERROR(_xlfn.MINIFS('Detalle individual'!$I$5:$I$1000, 'Detalle individual'!$D$5:$D$1000, A12), ""), "")) -> 3.0166667 | M12: =IF($A12="","",IF(C12>0, IFERROR(AVERAGEIFS('Detalle individual'!$I$5:$I$1000, 'Detalle individual'!$D$5:$D$1000, A12), ""), "")) -> 13.77803 | N12: =IF($A12="","",COUNTIF('Detalle individual'!$D$5:$D$1000, A12)-B12) -> 1
A13: =IF(Cálculos!$AF13="","",INDEX('Detalle individual'!$D:$D,Cálculos!$AF13)) -> Gerencia General | B13: =IF($A13="","",COUNTIFS('Detalle individual'!$D$5:$D$1000, A13, 'Detalle individual'!$F$5:$F$1000, "Completado")+COUNTIFS('Detalle individual'!$D$5:$D$1000, A13, 'Detalle individual'!$F$5:$F$1000, "Pendiente")) -> 13 | C13: =IF($A13="","",COUNTIFS('Detalle individual'!$D$5:$D$1000, A13, 'Detalle individual'!$F$5:$F$1000, "Completado")) -> 13 | D13: =IF($A13="","",B13-C13) -> 0 | E13: =IF($A13="","",IF(B13>0, C13/B13, 0)) -> 1 | F13: =IF($A13="","",IF(AND(B13>0, C13=B13), "Completo", "Pendiente")) -> Completo | G13: =IF($A13="","",IF(C13>0, IFERROR(AVERAGEIFS('Detalle individual'!$J$5:$J$1000, 'Detalle individual'!$D$5:$D$1000, A13), ""), "")) -> 98.75 | H13: =IF($A13="","",IF(C13>0, IFERROR(_xlfn.MAXIFS('Detalle individual'!$J$5:$J$1000, 'Detalle individual'!$D$5:$D$1000, A13), ""), "")) -> 100 | I13: =IF($A13="","",IF(C13>0, IFERROR(_xlfn.MINIFS('Detalle individual'!$J$5:$J$1000, 'Detalle individual'!$D$5:$D$1000, A13), ""), "")) -> 85 | J13: =IF($A13="","",IF(C13>0, IFERROR(_xlfn.MINIFS('Detalle individual'!$G$5:$G$1000, 'Detalle individual'!$D$5:$D$1000, A13), ""), "")) -> 46296.437 | K13: =IF($A13="","",IF(C13>0, IFERROR(_xlfn.MAXIFS('Detalle individual'!$H$5:$H$1000, 'Detalle individual'!$D$5:$D$1000, A13), ""), "")) -> 46305.41 | L13: =IF($A13="","",IF(C13>0, IFERROR(_xlfn.MINIFS('Detalle individual'!$I$5:$I$1000, 'Detalle individual'!$D$5:$D$1000, A13), ""), "")) -> 3.05 | M13: =IF($A13="","",IF(C13>0, IFERROR(AVERAGEIFS('Detalle individual'!$I$5:$I$1000, 'Detalle individual'!$D$5:$D$1000, A13), ""), "")) -> 7.6541667 | N13: =IF($A13="","",COUNTIF('Detalle individual'!$D$5:$D$1000, A13)-B13) -> 0
A14: =IF(Cálculos!$AF14="","",INDEX('Detalle individual'!$D:$D,Cálculos!$AF14)) -> Gerencia Legal y Cumplimiento Normativo | B14: =IF($A14="","",COUNTIFS('Detalle individual'!$D$5:$D$1000, A14, 'Detalle individual'!$F$5:$F$1000, "Completado")+COUNTIFS('Detalle individual'!$D$5:$D$1000, A14, 'Detalle individual'!$F$5:$F$1000, "Pendiente")) -> 9 | C14: =IF($A14="","",COUNTIFS('Detalle individual'!$D$5:$D$1000, A14, 'Detalle individual'!$F$5:$F$1000, "Completado")) -> 9 | D14: =IF($A14="","",B14-C14) -> 0 | E14: =IF($A14="","",IF(B14>0, C14/B14, 0)) -> 1 | F14: =IF($A14="","",IF(AND(B14>0, C14=B14), "Completo", "Pendiente")) -> Completo | G14: =IF($A14="","",IF(C14>0, IFERROR(AVERAGEIFS('Detalle individual'!$J$5:$J$1000, 'Detalle individual'!$D$5:$D$1000, A14), ""), "")) -> 97.777778 | H14: =IF($A14="","",IF(C14>0, IFERROR(_xlfn.MAXIFS('Detalle individual'!$J$5:$J$1000, 'Detalle individual'!$D$5:$D$1000, A14), ""), "")) -> 100 | I14: =IF($A14="","",IF(C14>0, IFERROR(_xlfn.MINIFS('Detalle individual'!$J$5:$J$1000, 'Detalle individual'!$D$5:$D$1000, A14), ""), "")) -> 90 | J14: =IF($A14="","",IF(C14>0, IFERROR(_xlfn.MINIFS('Detalle individual'!$G$5:$G$1000, 'Detalle individual'!$D$5:$D$1000, A14), ""), "")) -> 46300.623 | K14: =IF($A14="","",IF(C14>0, IFERROR(_xlfn.MAXIFS('Detalle individual'!$H$5:$H$1000, 'Detalle individual'!$D$5:$D$1000, A14), ""), "")) -> 46308.621 | L14: =IF($A14="","",IF(C14>0, IFERROR(_xlfn.MINIFS('Detalle individual'!$I$5:$I$1000, 'Detalle individual'!$D$5:$D$1000, A14), ""), "")) -> 2.5666667 | M14: =IF($A14="","",IF(C14>0, IFERROR(AVERAGEIFS('Detalle individual'!$I$5:$I$1000, 'Detalle individual'!$D$5:$D$1000, A14), ""), "")) -> 12.864815 | N14: =IF($A14="","",COUNTIF('Detalle individual'!$D$5:$D$1000, A14)-B14) -> 0
A15: =IF(Cálculos!$AF15="","",INDEX('Detalle individual'!$D:$D,Cálculos!$AF15)) | B15: =IF($A15="","",COUNTIFS('Detalle individual'!$D$5:$D$1000, A15, 'Detalle individual'!$F$5:$F$1000, "Completado")+COUNTIFS('Detalle individual'!$D$5:$D$1000, A15, 'Detalle individual'!$F$5:$F$1000, "Pendiente")) | C15: =IF($A15="","",COUNTIFS('Detalle individual'!$D$5:$D$1000, A15, 'Detalle individual'!$F$5:$F$1000, "Completado")) | D15: =IF($A15="","",B15-C15) | E15: =IF($A15="","",IF(B15>0, C15/B15, 0)) | F15: =IF($A15="","",IF(AND(B15>0, C15=B15), "Completo", "Pendiente")) | G15: =IF($A15="","",IF(C15>0, IFERROR(AVERAGEIFS('Detalle individual'!$J$5:$J$1000, 'Detalle individual'!$D$5:$D$1000, A15), ""), "")) | H15: =IF($A15="","",IF(C15>0, IFERROR(_xlfn.MAXIFS('Detalle individual'!$J$5:$J$1000, 'Detalle individual'!$D$5:$D$1000, A15), ""), "")) | I15: =IF($A15="","",IF(C15>0, IFERROR(_xlfn.MINIFS('Detalle individual'!$J$5:$J$1000, 'Detalle individual'!$D$5:$D$1000, A15), ""), "")) | J15: =IF($A15="","",IF(C15>0, IFERROR(_xlfn.MINIFS('Detalle individual'!$G$5:$G$1000, 'Detalle individual'!$D$5:$D$1000, A15), ""), "")) | K15: =IF($A15="","",IF(C15>0, IFERROR(_xlfn.MAXIFS('Detalle individual'!$H$5:$H$1000, 'Detalle individual'!$D$5:$D$1000, A15), ""), "")) | L15: =IF($A15="","",IF(C15>0, IFERROR(_xlfn.MINIFS('Detalle individual'!$I$5:$I$1000, 'Detalle individual'!$D$5:$D$1000, A15), ""), "")) | M15: =IF($A15="","",IF(C15>0, IFERROR(AVERAGEIFS('Detalle individual'!$I$5:$I$1000, 'Detalle individual'!$D$5:$D$1000, A15), ""), "")) | N15: =IF($A15="","",COUNTIF('Detalle individual'!$D$5:$D$1000, A15)-B15)
A16: =IF(Cálculos!$AF16="","",INDEX('Detalle individual'!$D:$D,Cálculos!$AF16)) | B16: =IF($A16="","",COUNTIFS('Detalle individual'!$D$5:$D$1000, A16, 'Detalle individual'!$F$5:$F$1000, "Completado")+COUNTIFS('Detalle individual'!$D$5:$D$1000, A16, 'Detalle individual'!$F$5:$F$1000, "Pendiente")) | C16: =IF($A16="","",COUNTIFS('Detalle individual'!$D$5:$D$1000, A16, 'Detalle individual'!$F$5:$F$1000, "Completado")) | D16: =IF($A16="","",B16-C16) | E16: =IF($A16="","",IF(B16>0, C16/B16, 0)) | F16: =IF($A16="","",IF(AND(B16>0, C16=B16), "Completo", "Pendiente")) | G16: =IF($A16="","",IF(C16>0, IFERROR(AVERAGEIFS('Detalle individual'!$J$5:$J$1000, 'Detalle individual'!$D$5:$D$1000, A16), ""), "")) | H16: =IF($A16="","",IF(C16>0, IFERROR(_xlfn.MAXIFS('Detalle individual'!$J$5:$J$1000, 'Detalle individual'!$D$5:$D$1000, A16), ""), "")) | I16: =IF($A16="","",IF(C16>0, IFERROR(_xlfn.MINIFS('Detalle individual'!$J$5:$J$1000, 'Detalle individual'!$D$5:$D$1000, A16), ""), "")) | J16: =IF($A16="","",IF(C16>0, IFERROR(_xlfn.MINIFS('Detalle individual'!$G$5:$G$1000, 'Detalle individual'!$D$5:$D$1000, A16), ""), "")) | K16: =IF($A16="","",IF(C16>0, IFERROR(_xlfn.MAXIFS('Detalle individual'!$H$5:$H$1000, 'Detalle individual'!$D$5:$D$1000, A16), ""), "")) | L16: =IF($A16="","",IF(C16>0, IFERROR(_xlfn.MINIFS('Detalle individual'!$I$5:$I$1000, 'Detalle individual'!$D$5:$D$1000, A16), ""), "")) | M16: =IF($A16="","",IF(C16>0, IFERROR(AVERAGEIFS('Detalle individual'!$I$5:$I$1000, 'Detalle individual'!$D$5:$D$1000, A16), ""), "")) | N16: =IF($A16="","",COUNTIF('Detalle individual'!$D$5:$D$1000, A16)-B16)
... A24: =IF(Cálculos!$AF24="","",INDEX('Detalle individual'!$D:$D,Cálculos!$AF24)) | B24: =IF($A24="","",COUNTIFS('Detalle individual'!$D$5:$D$1000, A24, 'Detalle individual'!$F$5:$F$1000, "Completado")+COUNTIFS('Detalle individual'!$D$5:$D$1000, A24, 'Detalle individual'!$F$5:$F$1000, "Pendiente")) | C24: =IF($A24="","",COUNTIFS('Detalle individual'!$D$5:$D$1000, A24, 'Detalle individual'!$F$5:$F$1000, "Completado")) | D24: =IF($A24="","",B24-C24) | E24: =IF($A24="","",IF(B24>0, C24/B24, 0)) | F24: =IF($A24="","",IF(AND(B24>0, C24=B24), "Completo", "Pendiente")) | G24: =IF($A24="","",IF(C24>0, IFERROR(AVERAGEIFS('Detalle individual'!$J$5:$J$1000, 'Detalle individual'!$D$5:$D$1000, A24), ""), "")) | H24: =IF($A24="","",IF(C24>0, IFERROR(_xlfn.MAXIFS('Detalle individual'!$J$5:$J$1000, 'Detalle individual'!$D$5:$D$1000, A24), ""), "")) | I24: =IF($A24="","",IF(C24>0, IFERROR(_xlfn.MINIFS('Detalle individual'!$J$5:$J$1000, 'Detalle individual'!$D$5:$D$1000, A24), ""), "")) | J24: =IF($A24="","",IF(C24>0, IFERROR(_xlfn.MINIFS('Detalle individual'!$G$5:$G$1000, 'Detalle individual'!$D$5:$D$1000, A24), ""), "")) | K24: =IF($A24="","",IF(C24>0, IFERROR(_xlfn.MAXIFS('Detalle individual'!$H$5:$H$1000, 'Detalle individual'!$D$5:$D$1000, A24), ""), "")) | L24: =IF($A24="","",IF(C24>0, IFERROR(_xlfn.MINIFS('Detalle individual'!$I$5:$I$1000, 'Detalle individual'!$D$5:$D$1000, A24), ""), "")) | M24: =IF($A24="","",IF(C24>0, IFERROR(AVERAGEIFS('Detalle individual'!$I$5:$I$1000, 'Detalle individual'!$D$5:$D$1000, A24), ""), "")) | N24: =IF($A24="","",COUNTIF('Detalle individual'!$D$5:$D$1000, A24)-B24)

Sheet Dashboard Gerencial
B1: DASHBOARD GERENCIAL
B2: Seleccione una gerencia en la celda amarilla para ver sus indicadores y el avance de cada departamento
B4: GERENCIA SELECCIONADA
B5: Todas las gerencias | H5: =HYPERLINK("#'Estado por Colaborador'!A1","Ver la lista de colaboradores pendientes y completados →") -> Ver la lista de colaboradores pendientes y completados →
C7: PERSONAL ESPERADO | F7: COMPLETADOS | I7: PENDIENTES | L7: % CUMPLIMIENTO | O7: NOTA PROMEDIO
C8: =IF($B$5="Todas las gerencias",SUM('Consolidado por Gerencia'!$B$5:$B$24),SUMIF('Consolidado por Gerencia'!$A$5:$A$24,$B$5,'Consolidado por Gerencia'!$B$5:$B$24)) -> 283 | F8: =IF($B$5="Todas las gerencias",SUM('Consolidado por Gerencia'!$C$5:$C$24),SUMIF('Consolidado por Gerencia'!$A$5:$A$24,$B$5,'Consolidado por Gerencia'!$C$5:$C$24)) -> 283 | I8: =C8-F8 -> 0 | L8: =IF(C8>0,F8/C8,0) -> 1 | O8: =IFERROR(IF($B$5="Todas las gerencias",AVERAGE('Detalle individual'!$J$5:$J$1000),AVERAGEIFS('Detalle individual'!$J$5:$J$1000,'Detalle individual'!$D$5:$D$1000,$B$5)),"-") -> 96.879433
B12: AVANCE POR DEPARTAMENTO (ordenado de mayor a menor cumplimiento)
B13: # | C13: Departamento / Agencia | G13: Gerencia | J13: Esperado | K13: Completados | L13: Pendientes | M13: % Cumplimiento | O13: Nota prom. | P13: Estado
B14: =IF($R14="","",1) -> 1 | C14: =IF($R14="","",INDEX(Cálculos!$O:$O,$R14)) -> DEPARTAMENTO DE SERVICIOS GENERALES | G14: =IF($R14="","",INDEX(Cálculos!$P:$P,$R14)) -> Gerencia Administrativa | J14: =IF($R14="","",INDEX(Cálculos!$Q:$Q,$R14)) -> 17 | K14: =IF($R14="","",INDEX(Cálculos!$M:$M,$R14)) -> 17 | L14: =IF($R14="","",INDEX(Cálculos!$N:$N,$R14)) -> 0 | M14: =IF($R14="","",INDEX(Cálculos!$R:$R,$R14)) -> 1 | O14: =IF($R14="","",INDEX(Cálculos!$S:$S,$R14)) -> 89.705882 | P14: =IF($R14="","",IF(M14>=1,"Completo","Pendiente")) -> Completo | R14: =IFERROR(SMALL(Cálculos!$T$30:$T$109,1),"") -> 30
B15: =IF($R15="","",2) -> 2 | C15: =IF($R15="","",INDEX(Cálculos!$O:$O,$R15)) -> AGENCIA CENTRAL | G15: =IF($R15="","",INDEX(Cálculos!$P:$P,$R15)) -> Gerencia de Negocios | J15: =IF($R15="","",INDEX(Cálculos!$Q:$Q,$R15)) -> 16 | K15: =IF($R15="","",INDEX(Cálculos!$M:$M,$R15)) -> 16 | L15: =IF($R15="","",INDEX(Cálculos!$N:$N,$R15)) -> 0 | M15: =IF($R15="","",INDEX(Cálculos!$R:$R,$R15)) -> 1 | O15: =IF($R15="","",INDEX(Cálculos!$S:$S,$R15)) -> 96.25 | P15: =IF($R15="","",IF(M15>=1,"Completo","Pendiente")) -> Completo | R15: =IFERROR(SMALL(Cálculos!$T$30:$T$109,2),"") -> 31
B16: =IF($R16="","",3) -> 3 | C16: =IF($R16="","",INDEX(Cálculos!$O:$O,$R16)) -> AGENCIA COLONIA MEDICA | G16: =IF($R16="","",INDEX(Cálculos!$P:$P,$R16)) -> Gerencia de Negocios | J16: =IF($R16="","",INDEX(Cálculos!$Q:$Q,$R16)) -> 16 | K16: =IF($R16="","",INDEX(Cálculos!$M:$M,$R16)) -> 16 | L16: =IF($R16="","",INDEX(Cálculos!$N:$N,$R16)) -> 0 | M16: =IF($R16="","",INDEX(Cálculos!$R:$R,$R16)) -> 1 | O16: =IF($R16="","",INDEX(Cálculos!$S:$S,$R16)) -> 97.8125 | P16: =IF($R16="","",IF(M16>=1,"Completo","Pendiente")) -> Completo | R16: =IFERROR(SMALL(Cálculos!$T$30:$T$109,3),"") -> 32
B17: =IF($R17="","",4) -> 4 | C17: =IF($R17="","",INDEX(Cálculos!$O:$O,$R17)) -> AGENCIA MERLIOT | G17: =IF($R17="","",INDEX(Cálculos!$P:$P,$R17)) -> Gerencia de Negocios | J17: =IF($R17="","",INDEX(Cálculos!$Q:$Q,$R17)) -> 13 | K17: =IF($R17="","",INDEX(Cálculos!$M:$M,$R17)) -> 13 | L17: =IF($R17="","",INDEX(Cálculos!$N:$N,$R17)) -> 0 | M17: =IF($R17="","",INDEX(Cálculos!$R:$R,$R17)) -> 1 | O17: =IF($R17="","",INDEX(Cálculos!$S:$S,$R17)) -> 95.769231 | P17: =IF($R17="","",IF(M17>=1,"Completo","Pendiente")) -> Completo | R17: =IFERROR(SMALL(Cálculos!$T$30:$T$109,4),"") -> 33
B18: =IF($R18="","",5) -> 5 | C18: =IF($R18="","",INDEX(Cálculos!$O:$O,$R18)) -> DEPARTAMENTO DE CONTABILIDAD | G18: =IF($R18="","",INDEX(Cálculos!$P:$P,$R18)) -> Gerencia de Finanzas y Planificación | J18: =IF($R18="","",INDEX(Cálculos!$Q:$Q,$R18)) -> 13 | K18: =IF($R18="","",INDEX(Cálculos!$M:$M,$R18)) -> 13 | L18: =IF($R18="","",INDEX(Cálculos!$N:$N,$R18)) -> 0 | M18: =IF($R18="","",INDEX(Cálculos!$R:$R,$R18)) -> 1 | O18: =IF($R18="","",INDEX(Cálculos!$S:$S,$R18)) -> 98.076923 | P18: =IF($R18="","",IF(M18>=1,"Completo","Pendiente")) -> Completo | R18: =IFERROR(SMALL(Cálculos!$T$30:$T$109,5),"") -> 34
B19: =IF($R19="","",6) -> 6 | C19: =IF($R19="","",INDEX(Cálculos!$O:$O,$R19)) -> DEPARTAMENTO DE CREDITOS | G19: =IF($R19="","",INDEX(Cálculos!$P:$P,$R19)) -> Gerencia de Negocios | J19: =IF($R19="","",INDEX(Cálculos!$Q:$Q,$R19)) -> 13 | K19: =IF($R19="","",INDEX(Cálculos!$M:$M,$R19)) -> 13 | L19: =IF($R19="","",INDEX(Cálculos!$N:$N,$R19)) -> 0 | M19: =IF($R19="","",INDEX(Cálculos!$R:$R,$R19)) -> 1 | O19: =IF($R19="","",INDEX(Cálculos!$S:$S,$R19)) -> 98.461538 | P19: =IF($R19="","",IF(M19>=1,"Completo","Pendiente")) -> Completo | R19: =IFERROR(SMALL(Cálculos!$T$30:$T$109,6),"") -> 35
B20: =IF($R20="","",7) -> 7 | C20: =IF($R20="","",INDEX(Cálculos!$O:$O,$R20)) -> AGENCIA COLEGIO MEDICO | G20: =IF($R20="","",INDEX(Cálculos!$P:$P,$R20)) -> Gerencia de Negocios | J20: =IF($R20="","",INDEX(Cálculos!$Q:$Q,$R20)) -> 11 | K20: =IF($R20="","",INDEX(Cálculos!$M:$M,$R20)) -> 11 | L20: =IF($R20="","",INDEX(Cálculos!$N:$N,$R20)) -> 0 | M20: =IF($R20="","",INDEX(Cálculos!$R:$R,$R20)) -> 1 | O20: =IF($R20="","",INDEX(Cálculos!$S:$S,$R20)) -> 97.272727 | P20: =IF($R20="","",IF(M20>=1,"Completo","Pendiente")) -> Completo | R20: =IFERROR(SMALL(Cálculos!$T$30:$T$109,7),"") -> 36
B21: =IF($R21="","",8) -> 8 | C21: =IF($R21="","",INDEX(Cálculos!$O:$O,$R21)) -> DEPARTAMENTO DE ANALISIS Y PROGRAMACIÓN | G21: =IF($R21="","",INDEX(Cálculos!$P:$P,$R21)) -> Gerencia de Sistemas | J21: =IF($R21="","",INDEX(Cálculos!$Q:$Q,$R21)) -> 11 | K21: =IF($R21="","",INDEX(Cálculos!$M:$M,$R21)) -> 11 | L21: =IF($R21="","",INDEX(Cálculos!$N:$N,$R21)) -> 0 | M21: =IF($R21="","",INDEX(Cálculos!$R:$R,$R21)) -> 1 | O21: =IF($R21="","",INDEX(Cálculos!$S:$S,$R21)) -> 100 | P21: =IF($R21="","",IF(M21>=1,"Completo","Pendiente")) -> Completo | R21: =IFERROR(SMALL(Cálculos!$T$30:$T$109,8),"") -> 37
B22: =IF($R22="","",9) -> 9 | C22: =IF($R22="","",INDEX(Cálculos!$O:$O,$R22)) -> DEPARTAMENTO DE SEGUROS | G22: =IF($R22="","",INDEX(Cálculos!$P:$P,$R22)) -> Gerencia de Negocios | J22: =IF($R22="","",INDEX(Cálculos!$Q:$Q,$R22)) -> 10 | K22: =IF($R22="","",INDEX(Cálculos!$M:$M,$R22)) -> 10 | L22: =IF($R22="","",INDEX(Cálculos!$N:$N,$R22)) -> 0 | M22: =IF($R22="","",INDEX(Cálculos!$R:$R,$R22)) -> 1 | O22: =IF($R22="","",INDEX(Cálculos!$S:$S,$R22)) -> 97 | P22: =IF($R22="","",IF(M22>=1,"Completo","Pendiente")) -> Completo | R22: =IFERROR(SMALL(Cálculos!$T$30:$T$109,9),"") -> 38
B23: =IF($R23="","",10) -> 10 | C23: =IF($R23="","",INDEX(Cálculos!$O:$O,$R23)) -> DEPARTAMENTO DE SOLUCIONES FINANCIERAS | G23: =IF($R23="","",INDEX(Cálculos!$P:$P,$R23)) -> Gerencia de Operaciones | J23: =IF($R23="","",INDEX(Cálculos!$Q:$Q,$R23)) -> 9 | K23: =IF($R23="","",INDEX(Cálculos!$M:$M,$R23)) -> 9 | L23: =IF($R23="","",INDEX(Cálculos!$N:$N,$R23)) -> 0 | M23: =IF($R23="","",INDEX(Cálculos!$R:$R,$R23)) -> 1 | O23: =IF($R23="","",INDEX(Cálculos!$S:$S,$R23)) -> 87.777778 | P23: =IF($R23="","",IF(M23>=1,"Completo","Pendiente")) -> Completo | R23: =IFERROR(SMALL(Cálculos!$T$30:$T$109,10),"") -> 39
B24: =IF($R24="","",11) -> 11 | C24: =IF($R24="","",INDEX(Cálculos!$O:$O,$R24)) -> AGENCIA PLAZA MUNDO | G24: =IF($R24="","",INDEX(Cálculos!$P:$P,$R24)) -> Gerencia de Negocios | J24: =IF($R24="","",INDEX(Cálculos!$Q:$Q,$R24)) -> 8 | K24: =IF($R24="","",INDEX(Cálculos!$M:$M,$R24)) -> 8 | L24: =IF($R24="","",INDEX(Cálculos!$N:$N,$R24)) -> 0 | M24: =IF($R24="","",INDEX(Cálculos!$R:$R,$R24)) -> 1 | O24: =IF($R24="","",INDEX(Cálculos!$S:$S,$R24)) -> 98.75 | P24: =IF($R24="","",IF(M24>=1,"Completo","Pendiente")) -> Completo | R24: =IFERROR(SMALL(Cálculos!$T$30:$T$109,11),"") -> 40
B25: =IF($R25="","",12) -> 12 | C25: =IF($R25="","",INDEX(Cálculos!$O:$O,$R25)) -> AGENCIA SANTA ANA | G25: =IF($R25="","",INDEX(Cálculos!$P:$P,$R25)) -> Gerencia de Negocios | J25: =IF($R25="","",INDEX(Cálculos!$Q:$Q,$R25)) -> 8 | K25: =IF($R25="","",INDEX(Cálculos!$M:$M,$R25)) -> 8 | L25: =IF($R25="","",INDEX(Cálculos!$N:$N,$R25)) -> 0 | M25: =IF($R25="","",INDEX(Cálculos!$R:$R,$R25)) -> 1 | O25: =IF($R25="","",INDEX(Cálculos!$S:$S,$R25)) -> 97.5 | P25: =IF($R25="","",IF(M25>=1,"Completo","Pendiente")) -> Completo | R25: =IFERROR(SMALL(Cálculos!$T$30:$T$109,12),"") -> 41
B26: =IF($R26="","",13) -> 13 | C26: =IF($R26="","",INDEX(Cálculos!$O:$O,$R26)) -> DEPARTAMENTO LEGAL | G26: =IF($R26="","",INDEX(Cálculos!$P:$P,$R26)) -> Gerencia Legal y Cumplimiento Normativo | J26: =IF($R26="","",INDEX(Cálculos!$Q:$Q,$R26)) -> 8 | K26: =IF($R26="","",INDEX(Cálculos!$M:$M,$R26)) -> 8 | L26: =IF($R26="","",INDEX(Cálculos!$N:$N,$R26)) -> 0 | M26: =IF($R26="","",INDEX(Cálculos!$R:$R,$R26)) -> 1 | O26: =IF($R26="","",INDEX(Cálculos!$S:$S,$R26)) -> 97.5 | P26: =IF($R26="","",IF(M26>=1,"Completo","Pendiente")) -> Completo | R26: =IFERROR(SMALL(Cálculos!$T$30:$T$109,13),"") -> 42
B27: =IF($R27="","",14) -> 14 | C27: =IF($R27="","",INDEX(Cálculos!$O:$O,$R27)) -> AGENCIA SAN MIGUEL | G27: =IF($R27="","",INDEX(Cálculos!$P:$P,$R27)) -> Gerencia de Negocios | J27: =IF($R27="","",INDEX(Cálculos!$Q:$Q,$R27)) -> 7 | K27: =IF($R27="","",INDEX(Cálculos!$M:$M,$R27)) -> 7 | L27: =IF($R27="","",INDEX(Cálculos!$N:$N,$R27)) -> 0 | M27: =IF($R27="","",INDEX(Cálculos!$R:$R,$R27)) -> 1 | O27: =IF($R27="","",INDEX(Cálculos!$S:$S,$R27)) -> 98.571429 | P27: =IF($R27="","",IF(M27>=1,"Completo","Pendiente")) -> Completo | R27: =IFERROR(SMALL(Cálculos!$T$30:$T$109,14),"") -> 43
B28: =IF($R28="","",15) -> 15 | C28: =IF($R28="","",INDEX(Cálculos!$O:$O,$R28)) -> AGENCIA SONSONATE | G28: =IF($R28="","",INDEX(Cálculos!$P:$P,$R28)) -> Gerencia de Negocios | J28: =IF($R28="","",INDEX(Cálculos!$Q:$Q,$R28)) -> 7 | K28: =IF($R28="","",INDEX(Cálculos!$M:$M,$R28)) -> 7 | L28: =IF($R28="","",INDEX(Cálculos!$N:$N,$R28)) -> 0 | M28: =IF($R28="","",INDEX(Cálculos!$R:$R,$R28)) -> 1 | O28: =IF($R28="","",INDEX(Cálculos!$S:$S,$R28)) -> 97.142857 | P28: =IF($R28="","",IF(M28>=1,"Completo","Pendiente")) -> Completo | R28: =IFERROR(SMALL(Cálculos!$T$30:$T$109,15),"") -> 44
B29: =IF($R29="","",16) -> 16 | C29: =IF($R29="","",INDEX(Cálculos!$O:$O,$R29)) -> AGENCIA USULUTAN | G29: =IF($R29="","",INDEX(Cálculos!$P:$P,$R29)) -> Gerencia de Negocios | J29: =IF($R29="","",INDEX(Cálculos!$Q:$Q,$R29)) -> 7 | K29: =IF($R29="","",INDEX(Cálculos!$M:$M,$R29)) -> 7 | L29: =IF($R29="","",INDEX(Cálculos!$N:$N,$R29)) -> 0 | M29: =IF($R29="","",INDEX(Cálculos!$R:$R,$R29)) -> 1 | O29: =IF($R29="","",INDEX(Cálculos!$S:$S,$R29)) -> 100 | P29: =IF($R29="","",IF(M29>=1,"Completo","Pendiente")) -> Completo | R29: =IFERROR(SMALL(Cálculos!$T$30:$T$109,16),"") -> 45
B30: =IF($R30="","",17) -> 17 | C30: =IF($R30="","",INDEX(Cálculos!$O:$O,$R30)) -> DEPARTAMENTO COMERCIAL DE TARJETA DE CREDITO Y DEBITO | G30: =IF($R30="","",INDEX(Cálculos!$P:$P,$R30)) -> Gerencia de Negocios | J30: =IF($R30="","",INDEX(Cálculos!$Q:$Q,$R30)) -> 7 | K30: =IF($R30="","",INDEX(Cálculos!$M:$M,$R30)) -> 7 | L30: =IF($R30="","",INDEX(Cálculos!$N:$N,$R30)) -> 0 | M30: =IF($R30="","",INDEX(Cálculos!$R:$R,$R30)) -> 1 | O30: =IF($R30="","",INDEX(Cálculos!$S:$S,$R30)) -> 86.428571 | P30: =IF($R30="","",IF(M30>=1,"Completo","Pendiente")) -> Completo | R30: =IFERROR(SMALL(Cálculos!$T$30:$T$109,17),"") -> 46
B31: =IF($R31="","",18) -> 18 | C31: =IF($R31="","",INDEX(Cálculos!$O:$O,$R31)) -> DEPARTAMENTO DE ATENCION A ASOCIADO Y CLIENTE | G31: =IF($R31="","",INDEX(Cálculos!$P:$P,$R31)) -> Gerencia de Negocios | J31: =IF($R31="","",INDEX(Cálculos!$Q:$Q,$R31)) -> 7 | K31: =IF($R31="","",INDEX(Cálculos!$M:$M,$R31)) -> 7 | L31: =IF($R31="","",INDEX(Cálculos!$N:$N,$R31)) -> 0 | M31: =IF($R31="","",INDEX(Cálculos!$R:$R,$R31)) -> 1 | O31: =IF($R31="","",INDEX(Cálculos!$S:$S,$R31)) -> 95.714286 | P31: =IF($R31="","",IF(M31>=1,"Completo","Pendiente")) -> Completo | R31: =IFERROR(SMALL(Cálculos!$T$30:$T$109,18),"") -> 47
B32: =IF($R32="","",19) -> 19 | C32: =IF($R32="","",INDEX(Cálculos!$O:$O,$R32)) -> DEPARTAMENTO DE AUDITORIA INTERNA | G32: =IF($R32="","",INDEX(Cálculos!$P:$P,$R32)) -> Auditoría Interna | J32: =IF($R32="","",INDEX(Cálculos!$Q:$Q,$R32)) -> 7 | K32: =IF($R32="","",INDEX(Cálculos!$M:$M,$R32)) -> 7 | L32: =IF($R32="","",INDEX(Cálculos!$N:$N,$R32)) -> 0 | M32: =IF($R32="","",INDEX(Cálculos!$R:$R,$R32)) -> 1 | O32: =IF($R32="","",INDEX(Cálculos!$S:$S,$R32)) -> 97.142857 | P32: =IF($R32="","",IF(M32>=1,"Completo","Pendiente")) -> Completo | R32: =IFERROR(SMALL(Cálculos!$T$30:$T$109,19),"") -> 48
B33: =IF($R33="","",20) -> 20 | C33: =IF($R33="","",INDEX(Cálculos!$O:$O,$R33)) -> DEPARTAMENTO DE MERCADEO | G33: =IF($R33="","",INDEX(Cálculos!$P:$P,$R33)) -> Gerencia de Negocios | J33: =IF($R33="","",INDEX(Cálculos!$Q:$Q,$R33)) -> 7 | K33: =IF($R33="","",INDEX(Cálculos!$M:$M,$R33)) -> 7 | L33: =IF($R33="","",INDEX(Cálculos!$N:$N,$R33)) -> 0 | M33: =IF($R33="","",INDEX(Cálculos!$R:$R,$R33)) -> 1 | O33: =IF($R33="","",INDEX(Cálculos!$S:$S,$R33)) -> 94.285714 | P33: =IF($R33="","",IF(M33>=1,"Completo","Pendiente")) -> Completo | R33: =IFERROR(SMALL(Cálculos!$T$30:$T$109,20),"") -> 49
B34: =IF($R34="","",21) -> 21 | C34: =IF($R34="","",INDEX(Cálculos!$O:$O,$R34)) -> OFICIALIA DE CUMPLIMIENTO | G34: =IF($R34="","",INDEX(Cálculos!$P:$P,$R34)) -> Gerencia de Oficialía de Cumplimiento | J34: =IF($R34="","",INDEX(Cálculos!$Q:$Q,$R34)) -> 7 | K34: =IF($R34="","",INDEX(Cálculos!$M:$M,$R34)) -> 7 | L34: =IF($R34="","",INDEX(Cálculos!$N:$N,$R34)) -> 0 | M34: =IF($R34="","",INDEX(Cálculos!$R:$R,$R34)) -> 1 | O34: =IF($R34="","",INDEX(Cálculos!$S:$S,$R34)) -> 100 | P34: =IF($R34="","",IF(M34>=1,"Completo","Pendiente")) -> Completo | R34: =IFERROR(SMALL(Cálculos!$T$30:$T$109,21),"") -> 50
B35: =IF($R35="","",22) -> 22 | C35: =IF($R35="","",INDEX(Cálculos!$O:$O,$R35)) -> SUB GERENCIA DE CANALES | G35: =IF($R35="","",INDEX(Cálculos!$P:$P,$R35)) -> Gerencia de Negocios | J35: =IF($R35="","",INDEX(Cálculos!$Q:$Q,$R35)) -> 7 | K35: =IF($R35="","",INDEX(Cálculos!$M:$M,$R35)) -> 7 | L35: =IF($R35="","",INDEX(Cálculos!$N:$N,$R35)) -> 0 | M35: =IF($R35="","",INDEX(Cálculos!$R:$R,$R35)) -> 1 | O35: =IF($R35="","",INDEX(Cálculos!$S:$S,$R35)) -> 98.571429 | P35: =IF($R35="","",IF(M35>=1,"Completo","Pendiente")) -> Completo | R35: =IFERROR(SMALL(Cálculos!$T$30:$T$109,22),"") -> 51
B36: =IF($R36="","",23) -> 23 | C36: =IF($R36="","",INDEX(Cálculos!$O:$O,$R36)) -> DEPARTAMENTO DE CUSTODIA DE GARANTÍA Y VALORES | G36: =IF($R36="","",INDEX(Cálculos!$P:$P,$R36)) -> Gerencia Administrativa | J36: =IF($R36="","",INDEX(Cálculos!$Q:$Q,$R36)) -> 6 | K36: =IF($R36="","",INDEX(Cálculos!$M:$M,$R36)) -> 6 | L36: =IF($R36="","",INDEX(Cálculos!$N:$N,$R36)) -> 0 | M36: =IF($R36="","",INDEX(Cálculos!$R:$R,$R36)) -> 1 | O36: =IF($R36="","",INDEX(Cálculos!$S:$S,$R36)) -> 100 | P36: =IF($R36="","",IF(M36>=1,"Completo","Pendiente")) -> Completo | R36: =IFERROR(SMALL(Cálculos!$T$30:$T$109,23),"") -> 52
B37: =IF($R37="","",24) -> 24 | C37: =IF($R37="","",INDEX(Cálculos!$O:$O,$R37)) -> DEPARTAMENTO DE OPERACIONES Y SOPORTE TECNICO | G37: =IF($R37="","",INDEX(Cálculos!$P:$P,$R37)) -> Gerencia de Sistemas | J37: =IF($R37="","",INDEX(Cálculos!$Q:$Q,$R37)) -> 6 | K37: =IF($R37="","",INDEX(Cálculos!$M:$M,$R37)) -> 6 | L37: =IF($R37="","",INDEX(Cálculos!$N:$N,$R37)) -> 0 | M37: =IF($R37="","",INDEX(Cálculos!$R:$R,$R37)) -> 1 | O37: =IF($R37="","",INDEX(Cálculos!$S:$S,$R37)) -> 100 | P37: =IF($R37="","",IF(M37>=1,"Completo","Pendiente")) -> Completo | R37: =IFERROR(SMALL(Cálculos!$T$30:$T$109,24),"") -> 53
B38: =IF($R38="","",25) -> 25 | C38: =IF($R38="","",INDEX(Cálculos!$O:$O,$R38)) -> ADMINISTRACIÓN DE CARTERAS | G38: =IF($R38="","",INDEX(Cálculos!$P:$P,$R38)) -> Gerencia de Operaciones | J38: =IF($R38="","",INDEX(Cálculos!$Q:$Q,$R38)) -> 5 | K38: =IF($R38="","",INDEX(Cálculos!$M:$M,$R38)) -> 5 | L38: =IF($R38="","",INDEX(Cálculos!$N:$N,$R38)) -> 0 | M38: =IF($R38="","",INDEX(Cálculos!$R:$R,$R38)) -> 1 | O38: =IF($R38="","",INDEX(Cálculos!$S:$S,$R38)) -> 100 | P38: =IF($R38="","",IF(M38>=1,"Completo","Pendiente")) -> Completo | R38: =IFERROR(SMALL(Cálculos!$T$30:$T$109,25),"") -> 54
B39: =IF($R39="","",26) -> 26 | C39: =IF($R39="","",INDEX(Cálculos!$O:$O,$R39)) -> DEPARTAMENTO DE TARJETA DE CREDITO Y DEBITO | G39: =IF($R39="","",INDEX(Cálculos!$P:$P,$R39)) -> Gerencia de Operaciones | J39: =IF($R39="","",INDEX(Cálculos!$Q:$Q,$R39)) -> 5 | K39: =IF($R39="","",INDEX(Cálculos!$M:$M,$R39)) -> 5 | L39: =IF($R39="","",INDEX(Cálculos!$N:$N,$R39)) -> 0 | M39: =IF($R39="","",INDEX(Cálculos!$R:$R,$R39)) -> 1 | O39: =IF($R39="","",INDEX(Cálculos!$S:$S,$R39)) -> 99 | P39: =IF($R39="","",IF(M39>=1,"Completo","Pendiente")) -> Completo | R39: =IFERROR(SMALL(Cálculos!$T$30:$T$109,26),"") -> 55
B40: =IF($R40="","",27) -> 27 | C40: =IF($R40="","",INDEX(Cálculos!$O:$O,$R40)) -> ADMINISTRACION DE RIESGOS | G40: =IF($R40="","",INDEX(Cálculos!$P:$P,$R40)) -> Gerencia General | J40: =IF($R40="","",INDEX(Cálculos!$Q:$Q,$R40)) -> 4 | K40: =IF($R40="","",INDEX(Cálculos!$M:$M,$R40)) -> 4 | L40: =IF($R40="","",INDEX(Cálculos!$N:$N,$R40)) -> 0 | M40: =IF($R40="","",INDEX(Cálculos!$R:$R,$R40)) -> 1 | O40: =IF($R40="","",INDEX(Cálculos!$S:$S,$R40)) -> 100 | P40: =IF($R40="","",IF(M40>=1,"Completo","Pendiente")) -> Completo | R40: =IFERROR(SMALL(Cálculos!$T$30:$T$109,27),"") -> 56
B41: =IF($R41="","",28) -> 28 | C41: =IF($R41="","",INDEX(Cálculos!$O:$O,$R41)) -> DEPARTAMENTO DE DEPOSITOS | G41: =IF($R41="","",INDEX(Cálculos!$P:$P,$R41)) -> Gerencia de Operaciones | J41: =IF($R41="","",INDEX(Cálculos!$Q:$Q,$R41)) -> 4 | K41: =IF($R41="","",INDEX(Cálculos!$M:$M,$R41)) -> 4 | L41: =IF($R41="","",INDEX(Cálculos!$N:$N,$R41)) -> 0 | M41: =IF($R41="","",INDEX(Cálculos!$R:$R,$R41)) -> 1 | O41: =IF($R41="","",INDEX(Cálculos!$S:$S,$R41)) -> 98.75 | P41: =IF($R41="","",IF(M41>=1,"Completo","Pendiente")) -> Completo | R41: =IFERROR(SMALL(Cálculos!$T$30:$T$109,28),"") -> 57
B42: =IF($R42="","",29) -> 29 | C42: =IF($R42="","",INDEX(Cálculos!$O:$O,$R42)) -> GERENCIA DE NEGOCIOS | G42: =IF($R42="","",INDEX(Cálculos!$P:$P,$R42)) -> Gerencia de Negocios | J42: =IF($R42="","",INDEX(Cálculos!$Q:$Q,$R42)) -> 4 | K42: =IF($R42="","",INDEX(Cálculos!$M:$M,$R42)) -> 4 | L42: =IF($R42="","",INDEX(Cálculos!$N:$N,$R42)) -> 0 | M42: =IF($R42="","",INDEX(Cálculos!$R:$R,$R42)) -> 1 | O42: =IF($R42="","",INDEX(Cálculos!$S:$S,$R42)) -> 100 | P42: =IF($R42="","",IF(M42>=1,"Completo","Pendiente")) -> Completo | R42: =IFERROR(SMALL(Cálculos!$T$30:$T$109,29),"") -> 58
B43: =IF($R43="","",30) -> 30 | C43: =IF($R43="","",INDEX(Cálculos!$O:$O,$R43)) -> GERENCIA DE SISTEMAS | G43: =IF($R43="","",INDEX(Cálculos!$P:$P,$R43)) -> Gerencia de Sistemas | J43: =IF($R43="","",INDEX(Cálculos!$Q:$Q,$R43)) -> 4 | K43: =IF($R43="","",INDEX(Cálculos!$M:$M,$R43)) -> 4 | L43: =IF($R43="","",INDEX(Cálculos!$N:$N,$R43)) -> 0 | M43: =IF($R43="","",INDEX(Cálculos!$R:$R,$R43)) -> 1 | O43: =IF($R43="","",INDEX(Cálculos!$S:$S,$R43)) -> 98.75 | P43: =IF($R43="","",IF(M43>=1,"Completo","Pendiente")) -> Completo | R43: =IFERROR(SMALL(Cálculos!$T$30:$T$109,30),"") -> 59
B44: =IF($R44="","",31) -> 31 | C44: =IF($R44="","",INDEX(Cálculos!$O:$O,$R44)) -> OFICIALIA DE SEGURIDAD DE LA INFORMACION | G44: =IF($R44="","",INDEX(Cálculos!$P:$P,$R44)) -> Gerencia General | J44: =IF($R44="","",INDEX(Cálculos!$Q:$Q,$R44)) -> 4 | K44: =IF($R44="","",INDEX(Cálculos!$M:$M,$R44)) -> 4 | L44: =IF($R44="","",INDEX(Cálculos!$N:$N,$R44)) -> 0 | M44: =IF($R44="","",INDEX(Cálculos!$R:$R,$R44)) -> 1 | O44: =IF($R44="","",INDEX(Cálculos!$S:$S,$R44)) -> 96.25 | P44: =IF($R44="","",IF(M44>=1,"Completo","Pendiente")) -> Completo | R44: =IFERROR(SMALL(Cálculos!$T$30:$T$109,31),"") -> 60
B45: =IF($R45="","",32) -> 32 | C45: =IF($R45="","",INDEX(Cálculos!$O:$O,$R45)) -> DEPARTAMENTO DE EDUCACION Y RESPONSABILIDAD SOCIAL | G45: =IF($R45="","",INDEX(Cálculos!$P:$P,$R45)) -> Gerencia Administrativa | J45: =IF($R45="","",INDEX(Cálculos!$Q:$Q,$R45)) -> 3 | K45: =IF($R45="","",INDEX(Cálculos!$M:$M,$R45)) -> 3 | L45: =IF($R45="","",INDEX(Cálculos!$N:$N,$R45)) -> 0 | M45: =IF($R45="","",INDEX(Cálculos!$R:$R,$R45)) -> 1 | O45: =IF($R45="","",INDEX(Cálculos!$S:$S,$R45)) -> 100 | P45: =IF($R45="","",IF(M45>=1,"Completo","Pendiente")) -> Completo | R45: =IFERROR(SMALL(Cálculos!$T$30:$T$109,32),"") -> 61
B46: =IF($R46="","",33) -> 33 | C46: =IF($R46="","",INDEX(Cálculos!$O:$O,$R46)) -> DEPARTAMENTO DE PLANIFICACIÓN Y ANALISIS | G46: =IF($R46="","",INDEX(Cálculos!$P:$P,$R46)) -> Gerencia de Finanzas y Planificación | J46: =IF($R46="","",INDEX(Cálculos!$Q:$Q,$R46)) -> 3 | K46: =IF($R46="","",INDEX(Cálculos!$M:$M,$R46)) -> 3 | L46: =IF($R46="","",INDEX(Cálculos!$N:$N,$R46)) -> 0 | M46: =IF($R46="","",INDEX(Cálculos!$R:$R,$R46)) -> 1 | O46: =IF($R46="","",INDEX(Cálculos!$S:$S,$R46)) -> 100 | P46: =IF($R46="","",IF(M46>=1,"Completo","Pendiente")) -> Completo | R46: =IFERROR(SMALL(Cálculos!$T$30:$T$109,33),"") -> 62
B47: =IF($R47="","",34) -> 34 | C47: =IF($R47="","",INDEX(Cálculos!$O:$O,$R47)) -> DEPARTAMENTO DE PROCESOS | G47: =IF($R47="","",INDEX(Cálculos!$P:$P,$R47)) -> Gerencia General | J47: =IF($R47="","",INDEX(Cálculos!$Q:$Q,$R47)) -> 3 | K47: =IF($R47="","",INDEX(Cálculos!$M:$M,$R47)) -> 3 | L47: =IF($R47="","",INDEX(Cálculos!$N:$N,$R47)) -> 0 | M47: =IF($R47="","",INDEX(Cálculos!$R:$R,$R47)) -> 1 | O47: =IF($R47="","",INDEX(Cálculos!$S:$S,$R47)) -> 100 | P47: =IF($R47="","",IF(M47>=1,"Completo","Pendiente")) -> Completo | R47: =IFERROR(SMALL(Cálculos!$T$30:$T$109,34),"") -> 63
B48: =IF($R48="","",35) -> 35 | C48: =IF($R48="","",INDEX(Cálculos!$O:$O,$R48)) -> CLINICA EMPRESARIAL | G48: =IF($R48="","",INDEX(Cálculos!$P:$P,$R48)) -> Gerencia Administrativa | J48: =IF($R48="","",INDEX(Cálculos!$Q:$Q,$R48)) -> 2 | K48: =IF($R48="","",INDEX(Cálculos!$M:$M,$R48)) -> 2 | L48: =IF($R48="","",INDEX(Cálculos!$N:$N,$R48)) -> 0 | M48: =IF($R48="","",INDEX(Cálculos!$R:$R,$R48)) -> 1 | O48: =IF($R48="","",INDEX(Cálculos!$S:$S,$R48)) -> 100 | P48: =IF($R48="","",IF(M48>=1,"Completo","Pendiente")) -> Completo | R48: =IFERROR(SMALL(Cálculos!$T$30:$T$109,35),"") -> 64
B49: =IF($R49="","",36) -> 36 | C49: =IF($R49="","",INDEX(Cálculos!$O:$O,$R49)) -> DEPARTAMENTO DE SEGURIDAD | G49: =IF($R49="","",INDEX(Cálculos!$P:$P,$R49)) -> Gerencia Administrativa | J49: =IF($R49="","",INDEX(Cálculos!$Q:$Q,$R49)) -> 2 | K49: =IF($R49="","",INDEX(Cálculos!$M:$M,$R49)) -> 2 | L49: =IF($R49="","",INDEX(Cálculos!$N:$N,$R49)) -> 0 | M49: =IF($R49="","",INDEX(Cálculos!$R:$R,$R49)) -> 1 | O49: =IF($R49="","",INDEX(Cálculos!$S:$S,$R49)) -> 95 | P49: =IF($R49="","",IF(M49>=1,"Completo","Pendiente")) -> Completo | R49: =IFERROR(SMALL(Cálculos!$T$30:$T$109,36),"") -> 65
B50: =IF($R50="","",37) -> 37 | C50: =IF($R50="","",INDEX(Cálculos!$O:$O,$R50)) -> DEPARTAMENTO DE TALENTO HUMANO | G50: =IF($R50="","",INDEX(Cálculos!$P:$P,$R50)) -> Gerencia Administrativa | J50: =IF($R50="","",INDEX(Cálculos!$Q:$Q,$R50)) -> 2 | K50: =IF($R50="","",INDEX(Cálculos!$M:$M,$R50)) -> 2 | L50: =IF($R50="","",INDEX(Cálculos!$N:$N,$R50)) -> 0 | M50: =IF($R50="","",INDEX(Cálculos!$R:$R,$R50)) -> 1 | O50: =IF($R50="","",INDEX(Cálculos!$S:$S,$R50)) -> 95 | P50: =IF($R50="","",IF(M50>=1,"Completo","Pendiente")) -> Completo | R50: =IFERROR(SMALL(Cálculos!$T$30:$T$109,37),"") -> 66
B51: =IF($R51="","",38) -> 38 | C51: =IF($R51="","",INDEX(Cálculos!$O:$O,$R51)) -> GERENCIA ADMINISTRATIVA | G51: =IF($R51="","",INDEX(Cálculos!$P:$P,$R51)) -> Gerencia Administrativa | J51: =IF($R51="","",INDEX(Cálculos!$Q:$Q,$R51)) -> 2 | K51: =IF($R51="","",INDEX(Cálculos!$M:$M,$R51)) -> 2 | L51: =IF($R51="","",INDEX(Cálculos!$N:$N,$R51)) -> 0 | M51: =IF($R51="","",INDEX(Cálculos!$R:$R,$R51)) -> 1 | O51: =IF($R51="","",INDEX(Cálculos!$S:$S,$R51)) -> 100 | P51: =IF($R51="","",IF(M51>=1,"Completo","Pendiente")) -> Completo | R51: =IFERROR(SMALL(Cálculos!$T$30:$T$109,38),"") -> 67
B52: =IF($R52="","",39) -> 39 | C52: =IF($R52="","",INDEX(Cálculos!$O:$O,$R52)) -> GERENCIA DE FINANZAS Y PLANIFICACIÓN | G52: =IF($R52="","",INDEX(Cálculos!$P:$P,$R52)) -> Gerencia de Finanzas y Planificación | J52: =IF($R52="","",INDEX(Cálculos!$Q:$Q,$R52)) -> 2 | K52: =IF($R52="","",INDEX(Cálculos!$M:$M,$R52)) -> 2 | L52: =IF($R52="","",INDEX(Cálculos!$N:$N,$R52)) -> 0 | M52: =IF($R52="","",INDEX(Cálculos!$R:$R,$R52)) -> 1 | O52: =IF($R52="","",INDEX(Cálculos!$S:$S,$R52)) -> 100 | P52: =IF($R52="","",IF(M52>=1,"Completo","Pendiente")) -> Completo | R52: =IFERROR(SMALL(Cálculos!$T$30:$T$109,39),"") -> 68
B53: =IF($R53="","",40) -> 40 | C53: =IF($R53="","",INDEX(Cálculos!$O:$O,$R53)) -> GERENCIA GENERAL | G53: =IF($R53="","",INDEX(Cálculos!$P:$P,$R53)) -> Gerencia General | J53: =IF($R53="","",INDEX(Cálculos!$Q:$Q,$R53)) -> 2 | K53: =IF($R53="","",INDEX(Cálculos!$M:$M,$R53)) -> 2 | L53: =IF($R53="","",INDEX(Cálculos!$N:$N,$R53)) -> 0 | M53: =IF($R53="","",INDEX(Cálculos!$R:$R,$R53)) -> 1 | O53: =IF($R53="","",INDEX(Cálculos!$S:$S,$R53)) -> 100 | P53: =IF($R53="","",IF(M53>=1,"Completo","Pendiente")) -> Completo | R53: =IFERROR(SMALL(Cálculos!$T$30:$T$109,40),"") -> 69
B54: =IF($R54="","",41) -> 41 | C54: =IF($R54="","",INDEX(Cálculos!$O:$O,$R54)) -> ADMINISTRACION DE BASE DE DATOS | G54: =IF($R54="","",INDEX(Cálculos!$P:$P,$R54)) -> Gerencia de Sistemas | J54: =IF($R54="","",INDEX(Cálculos!$Q:$Q,$R54)) -> 1 | K54: =IF($R54="","",INDEX(Cálculos!$M:$M,$R54)) -> 1 | L54: =IF($R54="","",INDEX(Cálculos!$N:$N,$R54)) -> 0 | M54: =IF($R54="","",INDEX(Cálculos!$R:$R,$R54)) -> 1 | O54: =IF($R54="","",INDEX(Cálculos!$S:$S,$R54)) -> 95 | P54: =IF($R54="","",IF(M54>=1,"Completo","Pendiente")) -> Completo | R54: =IFERROR(SMALL(Cálculos!$T$30:$T$109,41),"") -> 70
B55: =IF($R55="","",42) -> 42 | C55: =IF($R55="","",INDEX(Cálculos!$O:$O,$R55)) -> CONSEJO DE ADMINISTRACION | G55: =IF($R55="","",INDEX(Cálculos!$P:$P,$R55)) -> Consejo de Administración | J55: =IF($R55="","",INDEX(Cálculos!$Q:$Q,$R55)) -> 1 | K55: =IF($R55="","",INDEX(Cálculos!$M:$M,$R55)) -> 1 | L55: =IF($R55="","",INDEX(Cálculos!$N:$N,$R55)) -> 0 | M55: =IF($R55="","",INDEX(Cálculos!$R:$R,$R55)) -> 1 | O55: =IF($R55="","",INDEX(Cálculos!$S:$S,$R55)) -> 90 | P55: =IF($R55="","",IF(M55>=1,"Completo","Pendiente")) -> Completo | R55: =IFERROR(SMALL(Cálculos!$T$30:$T$109,42),"") -> 71
B56: =IF($R56="","",43) -> 43 | C56: =IF($R56="","",INDEX(Cálculos!$O:$O,$R56)) -> GERENCIA DE OPERACIONES | G56: =IF($R56="","",INDEX(Cálculos!$P:$P,$R56)) -> Gerencia de Operaciones | J56: =IF($R56="","",INDEX(Cálculos!$Q:$Q,$R56)) -> 1 | K56: =IF($R56="","",INDEX(Cálculos!$M:$M,$R56)) -> 1 | L56: =IF($R56="","",INDEX(Cálculos!$N:$N,$R56)) -> 0 | M56: =IF($R56="","",INDEX(Cálculos!$R:$R,$R56)) -> 1 | O56: =IF($R56="","",INDEX(Cálculos!$S:$S,$R56)) -> 100 | P56: =IF($R56="","",IF(M56>=1,"Completo","Pendiente")) -> Completo | R56: =IFERROR(SMALL(Cálculos!$T$30:$T$109,43),"") -> 72
B57: =IF($R57="","",44) -> 44 | C57: =IF($R57="","",INDEX(Cálculos!$O:$O,$R57)) -> GERENCIA LEGAL Y DE CUMPLIMIENTO NORMATIVO | G57: =IF($R57="","",INDEX(Cálculos!$P:$P,$R57)) -> Gerencia Legal y Cumplimiento Normativo | J57: =IF($R57="","",INDEX(Cálculos!$Q:$Q,$R57)) -> 1 | K57: =IF($R57="","",INDEX(Cálculos!$M:$M,$R57)) -> 1 | L57: =IF($R57="","",INDEX(Cálculos!$N:$N,$R57)) -> 0 | M57: =IF($R57="","",INDEX(Cálculos!$R:$R,$R57)) -> 1 | O57: =IF($R57="","",INDEX(Cálculos!$S:$S,$R57)) -> 100 | P57: =IF($R57="","",IF(M57>=1,"Completo","Pendiente")) -> Completo | R57: =IFERROR(SMALL(Cálculos!$T$30:$T$109,44),"") -> 73
B58: =IF($R58="","",45) | C58: =IF($R58="","",INDEX(Cálculos!$O:$O,$R58)) | G58: =IF($R58="","",INDEX(Cálculos!$P:$P,$R58)) | J58: =IF($R58="","",INDEX(Cálculos!$Q:$Q,$R58)) | K58: =IF($R58="","",INDEX(Cálculos!$M:$M,$R58)) | L58: =IF($R58="","",INDEX(Cálculos!$N:$N,$R58)) | M58: =IF($R58="","",INDEX(Cálculos!$R:$R,$R58)) | O58: =IF($R58="","",INDEX(Cálculos!$S:$S,$R58)) | P58: =IF($R58="","",IF(M58>=1,"Completo","Pendiente")) | R58: =IFERROR(SMALL(Cálculos!$T$30:$T$109,45),"")
B59: =IF($R59="","",46) | C59: =IF($R59="","",INDEX(Cálculos!$O:$O,$R59)) | G59: =IF($R59="","",INDEX(Cálculos!$P:$P,$R59)) | J59: =IF($R59="","",INDEX(Cálculos!$Q:$Q,$R59)) | K59: =IF($R59="","",INDEX(Cálculos!$M:$M,$R59)) | L59: =IF($R59="","",INDEX(Cálculos!$N:$N,$R59)) | M59: =IF($R59="","",INDEX(Cálculos!$R:$R,$R59)) | O59: =IF($R59="","",INDEX(Cálculos!$S:$S,$R59)) | P59: =IF($R59="","",IF(M59>=1,"Completo","Pendiente")) | R59: =IFERROR(SMALL(Cálculos!$T$30:$T$109,46),"")
B60: =IF($R60="","",47) | C60: =IF($R60="","",INDEX(Cálculos!$O:$O,$R60)) | G60: =IF($R60="","",INDEX(Cálculos!$P:$P,$R60)) | J60: =IF($R60="","",INDEX(Cálculos!$Q:$Q,$R60)) | K60: =IF($R60="","",INDEX(Cálculos!$M:$M,$R60)) | L60: =IF($R60="","",INDEX(Cálculos!$N:$N,$R60)) | M60: =IF($R60="","",INDEX(Cálculos!$R:$R,$R60)) | O60: =IF($R60="","",INDEX(Cálculos!$S:$S,$R60)) | P60: =IF($R60="","",IF(M60>=1,"Completo","Pendiente")) | R60: =IFERROR(SMALL(Cálculos!$T$30:$T$109,47),"")
B61: =IF($R61="","",48) | C61: =IF($R61="","",INDEX(Cálculos!$O:$O,$R61)) | G61: =IF($R61="","",INDEX(Cálculos!$P:$P,$R61)) | J61: =IF($R61="","",INDEX(Cálculos!$Q:$Q,$R61)) | K61: =IF($R61="","",INDEX(Cálculos!$M:$M,$R61)) | L61: =IF($R61="","",INDEX(Cálculos!$N:$N,$R61)) | M61: =IF($R61="","",INDEX(Cálculos!$R:$R,$R61)) | O61: =IF($R61="","",INDEX(Cálculos!$S:$S,$R61)) | P61: =IF($R61="","",IF(M61>=1,"Completo","Pendiente")) | R61: =IFERROR(SMALL(Cálculos!$T$30:$T$109,48),"")
B62: =IF($R62="","",49) | C62: =IF($R62="","",INDEX(Cálculos!$O:$O,$R62)) | G62: =IF($R62="","",INDEX(Cálculos!$P:$P,$R62)) | J62: =IF($R62="","",INDEX(Cálculos!$Q:$Q,$R62)) | K62: =IF($R62="","",INDEX(Cálculos!$M:$M,$R62)) | L62: =IF($R62="","",INDEX(Cálculos!$N:$N,$R62)) | M62: =IF($R62="","",INDEX(Cálculos!$R:$R,$R62)) | O62: =IF($R62="","",INDEX(Cálculos!$S:$S,$R62)) | P62: =IF($R62="","",IF(M62>=1,"Completo","Pendiente")) | R62: =IFERROR(SMALL(Cálculos!$T$30:$T$109,49),"")
B63: =IF($R63="","",50) | C63: =IF($R63="","",INDEX(Cálculos!$O:$O,$R63)) | G63: =IF($R63="","",INDEX(Cálculos!$P:$P,$R63)) | J63: =IF($R63="","",INDEX(Cálculos!$Q:$Q,$R63)) | K63: =IF($R63="","",INDEX(Cálculos!$M:$M,$R63)) | L63: =IF($R63="","",INDEX(Cálculos!$N:$N,$R63)) | M63: =IF($R63="","",INDEX(Cálculos!$R:$R,$R63)) | O63: =IF($R63="","",INDEX(Cálculos!$S:$S,$R63)) | P63: =IF($R63="","",IF(M63>=1,"Completo","Pendiente")) | R63: =IFERROR(SMALL(Cálculos!$T$30:$T$109,50),"")
B64: =IF($R64="","",51) | C64: =IF($R64="","",INDEX(Cálculos!$O:$O,$R64)) | G64: =IF($R64="","",INDEX(Cálculos!$P:$P,$R64)) | J64: =IF($R64="","",INDEX(Cálculos!$Q:$Q,$R64)) | K64: =IF($R64="","",INDEX(Cálculos!$M:$M,$R64)) | L64: =IF($R64="","",INDEX(Cálculos!$N:$N,$R64)) | M64: =IF($R64="","",INDEX(Cálculos!$R:$R,$R64)) | O64: =IF($R64="","",INDEX(Cálculos!$S:$S,$R64)) | P64: =IF($R64="","",IF(M64>=1,"Completo","Pendiente")) | R64: =IFERROR(SMALL(Cálculos!$T$30:$T$109,51),"")
B65: =IF($R65="","",52) | C65: =IF($R65="","",INDEX(Cálculos!$O:$O,$R65)) | G65: =IF($R65="","",INDEX(Cálculos!$P:$P,$R65)) | J65: =IF($R65="","",INDEX(Cálculos!$Q:$Q,$R65)) | K65: =IF($R65="","",INDEX(Cálculos!$M:$M,$R65)) | L65: =IF($R65="","",INDEX(Cálculos!$N:$N,$R65)) | M65: =IF($R65="","",INDEX(Cálculos!$R:$R,$R65)) | O65: =IF($R65="","",INDEX(Cálculos!$S:$S,$R65)) | P65: =IF($R65="","",IF(M65>=1,"Completo","Pendiente")) | R65: =IFERROR(SMALL(Cálculos!$T$30:$T$109,52),"")
B66: =IF($R66="","",53) | C66: =IF($R66="","",INDEX(Cálculos!$O:$O,$R66)) | G66: =IF($R66="","",INDEX(Cálculos!$P:$P,$R66)) | J66: =IF($R66="","",INDEX(Cálculos!$Q:$Q,$R66)) | K66: =IF($R66="","",INDEX(Cálculos!$M:$M,$R66)) | L66: =IF($R66="","",INDEX(Cálculos!$N:$N,$R66)) | M66: =IF($R66="","",INDEX(Cálculos!$R:$R,$R66)) | O66: =IF($R66="","",INDEX(Cálculos!$S:$S,$R66)) | P66: =IF($R66="","",IF(M66>=1,"Completo","Pendiente")) | R66: =IFERROR(SMALL(Cálculos!$T$30:$T$109,53),"")
B67: =IF($R67="","",54) | C67: =IF($R67="","",INDEX(Cálculos!$O:$O,$R67)) | G67: =IF($R67="","",INDEX(Cálculos!$P:$P,$R67)) | J67: =IF($R67="","",INDEX(Cálculos!$Q:$Q,$R67)) | K67: =IF($R67="","",INDEX(Cálculos!$M:$M,$R67)) | L67: =IF($R67="","",INDEX(Cálculos!$N:$N,$R67)) | M67: =IF($R67="","",INDEX(Cálculos!$R:$R,$R67)) | O67: =IF($R67="","",INDEX(Cálculos!$S:$S,$R67)) | P67: =IF($R67="","",IF(M67>=1,"Completo","Pendiente")) | R67: =IFERROR(SMALL(Cálculos!$T$30:$T$109,54),"")
B68: =IF($R68="","",55) | C68: =IF($R68="","",INDEX(Cálculos!$O:$O,$R68)) | G68: =IF($R68="","",INDEX(Cálculos!$P:$P,$R68)) | J68: =IF($R68="","",INDEX(Cálculos!$Q:$Q,$R68)) | K68: =IF($R68="","",INDEX(Cálculos!$M:$M,$R68)) | L68: =IF($R68="","",INDEX(Cálculos!$N:$N,$R68)) | M68: =IF($R68="","",INDEX(Cálculos!$R:$R,$R68)) | O68: =IF($R68="","",INDEX(Cálculos!$S:$S,$R68)) | P68: =IF($R68="","",IF(M68>=1,"Completo","Pendiente")) | R68: =IFERROR(SMALL(Cálculos!$T$30:$T$109,55),"")
B69: =IF($R69="","",56) | C69: =IF($R69="","",INDEX(Cálculos!$O:$O,$R69)) | G69: =IF($R69="","",INDEX(Cálculos!$P:$P,$R69)) | J69: =IF($R69="","",INDEX(Cálculos!$Q:$Q,$R69)) | K69: =IF($R69="","",INDEX(Cálculos!$M:$M,$R69)) | L69: =IF($R69="","",INDEX(Cálculos!$N:$N,$R69)) | M69: =IF($R69="","",INDEX(Cálculos!$R:$R,$R69)) | O69: =IF($R69="","",INDEX(Cálculos!$S:$S,$R69)) | P69: =IF($R69="","",IF(M69>=1,"Completo","Pendiente")) | R69: =IFERROR(SMALL(Cálculos!$T$30:$T$109,56),"")
B70: =IF($R70="","",57) | C70: =IF($R70="","",INDEX(Cálculos!$O:$O,$R70)) | G70: =IF($R70="","",INDEX(Cálculos!$P:$P,$R70)) | J70: =IF($R70="","",INDEX(Cálculos!$Q:$Q,$R70)) | K70: =IF($R70="","",INDEX(Cálculos!$M:$M,$R70)) | L70: =IF($R70="","",INDEX(Cálculos!$N:$N,$R70)) | M70: =IF($R70="","",INDEX(Cálculos!$R:$R,$R70)) | O70: =IF($R70="","",INDEX(Cálculos!$S:$S,$R70)) | P70: =IF($R70="","",IF(M70>=1,"Completo","Pendiente")) | R70: =IFERROR(SMALL(Cálculos!$T$30:$T$109,57),"")
B71: =IF($R71="","",58) | C71: =IF($R71="","",INDEX(Cálculos!$O:$O,$R71)) | G71: =IF($R71="","",INDEX(Cálculos!$P:$P,$R71)) | J71: =IF($R71="","",INDEX(Cálculos!$Q:$Q,$R71)) | K71: =IF($R71="","",INDEX(Cálculos!$M:$M,$R71)) | L71: =IF($R71="","",INDEX(Cálculos!$N:$N,$R71)) | M71: =IF($R71="","",INDEX(Cálculos!$R:$R,$R71)) | O71: =IF($R71="","",INDEX(Cálculos!$S:$S,$R71)) | P71: =IF($R71="","",IF(M71>=1,"Completo","Pendiente")) | R71: =IFERROR(SMALL(Cálculos!$T$30:$T$109,58),"")
B72: =IF($R72="","",59) | C72: =IF($R72="","",INDEX(Cálculos!$O:$O,$R72)) | G72: =IF($R72="","",INDEX(Cálculos!$P:$P,$R72)) | J72: =IF($R72="","",INDEX(Cálculos!$Q:$Q,$R72)) | K72: =IF($R72="","",INDEX(Cálculos!$M:$M,$R72)) | L72: =IF($R72="","",INDEX(Cálculos!$N:$N,$R72)) | M72: =IF($R72="","",INDEX(Cálculos!$R:$R,$R72)) | O72: =IF($R72="","",INDEX(Cálculos!$S:$S,$R72)) | P72: =IF($R72="","",IF(M72>=1,"Completo","Pendiente")) | R72: =IFERROR(SMALL(Cálculos!$T$30:$T$109,59),"")
B73: =IF($R73="","",60) | C73: =IF($R73="","",INDEX(Cálculos!$O:$O,$R73)) | G73: =IF($R73="","",INDEX(Cálculos!$P:$P,$R73)) | J73: =IF($R73="","",INDEX(Cálculos!$Q:$Q,$R73)) | K73: =IF($R73="","",INDEX(Cálculos!$M:$M,$R73)) | L73: =IF($R73="","",INDEX(Cálculos!$N:$N,$R73)) | M73: =IF($R73="","",INDEX(Cálculos!$R:$R,$R73)) | O73: =IF($R73="","",INDEX(Cálculos!$S:$S,$R73)) | P73: =IF($R73="","",IF(M73>=1,"Completo","Pendiente")) | R73: =IFERROR(SMALL(Cálculos!$T$30:$T$109,60),"")
B74: =IF($R74="","",61) | C74: =IF($R74="","",INDEX(Cálculos!$O:$O,$R74)) | G74: =IF($R74="","",INDEX(Cálculos!$P:$P,$R74)) | J74: =IF($R74="","",INDEX(Cálculos!$Q:$Q,$R74)) | K74: =IF($R74="","",INDEX(Cálculos!$M:$M,$R74)) | L74: =IF($R74="","",INDEX(Cálculos!$N:$N,$R74)) | M74: =IF($R74="","",INDEX(Cálculos!$R:$R,$R74)) | O74: =IF($R74="","",INDEX(Cálculos!$S:$S,$R74)) | P74: =IF($R74="","",IF(M74>=1,"Completo","Pendiente")) | R74: =IFERROR(SMALL(Cálculos!$T$30:$T$109,61),"")
B75: =IF($R75="","",62) | C75: =IF($R75="","",INDEX(Cálculos!$O:$O,$R75)) | G75: =IF($R75="","",INDEX(Cálculos!$P:$P,$R75)) | J75: =IF($R75="","",INDEX(Cálculos!$Q:$Q,$R75)) | K75: =IF($R75="","",INDEX(Cálculos!$M:$M,$R75)) | L75: =IF($R75="","",INDEX(Cálculos!$N:$N,$R75)) | M75: =IF($R75="","",INDEX(Cálculos!$R:$R,$R75)) | O75: =IF($R75="","",INDEX(Cálculos!$S:$S,$R75)) | P75: =IF($R75="","",IF(M75>=1,"Completo","Pendiente")) | R75: =IFERROR(SMALL(Cálculos!$T$30:$T$109,62),"")
B76: =IF($R76="","",63) | C76: =IF($R76="","",INDEX(Cálculos!$O:$O,$R76)) | G76: =IF($R76="","",INDEX(Cálculos!$P:$P,$R76)) | J76: =IF($R76="","",INDEX(Cálculos!$Q:$Q,$R76)) | K76: =IF($R76="","",INDEX(Cálculos!$M:$M,$R76)) | L76: =IF($R76="","",INDEX(Cálculos!$N:$N,$R76)) | M76: =IF($R76="","",INDEX(Cálculos!$R:$R,$R76)) | O76: =IF($R76="","",INDEX(Cálculos!$S:$S,$R76)) | P76: =IF($R76="","",IF(M76>=1,"Completo","Pendiente")) | R76: =IFERROR(SMALL(Cálculos!$T$30:$T$109,63),"")
B77: =IF($R77="","",64) | C77: =IF($R77="","",INDEX(Cálculos!$O:$O,$R77)) | G77: =IF($R77="","",INDEX(Cálculos!$P:$P,$R77)) | J77: =IF($R77="","",INDEX(Cálculos!$Q:$Q,$R77)) | K77: =IF($R77="","",INDEX(Cálculos!$M:$M,$R77)) | L77: =IF($R77="","",INDEX(Cálculos!$N:$N,$R77)) | M77: =IF($R77="","",INDEX(Cálculos!$R:$R,$R77)) | O77: =IF($R77="","",INDEX(Cálculos!$S:$S,$R77)) | P77: =IF($R77="","",IF(M77>=1,"Completo","Pendiente")) | R77: =IFERROR(SMALL(Cálculos!$T$30:$T$109,64),"")
B78: =IF($R78="","",65) | C78: =IF($R78="","",INDEX(Cálculos!$O:$O,$R78)) | G78: =IF($R78="","",INDEX(Cálculos!$P:$P,$R78)) | J78: =IF($R78="","",INDEX(Cálculos!$Q:$Q,$R78)) | K78: =IF($R78="","",INDEX(Cálculos!$M:$M,$R78)) | L78: =IF($R78="","",INDEX(Cálculos!$N:$N,$R78)) | M78: =IF($R78="","",INDEX(Cálculos!$R:$R,$R78)) | O78: =IF($R78="","",INDEX(Cálculos!$S:$S,$R78)) | P78: =IF($R78="","",IF(M78>=1,"Completo","Pendiente")) | R78: =IFERROR(SMALL(Cálculos!$T$30:$T$109,65),"")
B79: =IF($R79="","",66) | C79: =IF($R79="","",INDEX(Cálculos!$O:$O,$R79)) | G79: =IF($R79="","",INDEX(Cálculos!$P:$P,$R79)) | J79: =IF($R79="","",INDEX(Cálculos!$Q:$Q,$R79)) | K79: =IF($R79="","",INDEX(Cálculos!$M:$M,$R79)) | L79: =IF($R79="","",INDEX(Cálculos!$N:$N,$R79)) | M79: =IF($R79="","",INDEX(Cálculos!$R:$R,$R79)) | O79: =IF($R79="","",INDEX(Cálculos!$S:$S,$R79)) | P79: =IF($R79="","",IF(M79>=1,"Completo","Pendiente")) | R79: =IFERROR(SMALL(Cálculos!$T$30:$T$109,66),"")
B80: =IF($R80="","",67) | C80: =IF($R80="","",INDEX(Cálculos!$O:$O,$R80)) | G80: =IF($R80="","",INDEX(Cálculos!$P:$P,$R80)) | J80: =IF($R80="","",INDEX(Cálculos!$Q:$Q,$R80)) | K80: =IF($R80="","",INDEX(Cálculos!$M:$M,$R80)) | L80: =IF($R80="","",INDEX(Cálculos!$N:$N,$R80)) | M80: =IF($R80="","",INDEX(Cálculos!$R:$R,$R80)) | O80: =IF($R80="","",INDEX(Cálculos!$S:$S,$R80)) | P80: =IF($R80="","",IF(M80>=1,"Completo","Pendiente")) | R80: =IFERROR(SMALL(Cálculos!$T$30:$T$109,67),"")
B81: =IF($R81="","",68) | C81: =IF($R81="","",INDEX(Cálculos!$O:$O,$R81)) | G81: =IF($R81="","",INDEX(Cálculos!$P:$P,$R81)) | J81: =IF($R81="","",INDEX(Cálculos!$Q:$Q,$R81)) | K81: =IF($R81="","",INDEX(Cálculos!$M:$M,$R81)) | L81: =IF($R81="","",INDEX(Cálculos!$N:$N,$R81)) | M81: =IF($R81="","",INDEX(Cálculos!$R:$R,$R81)) | O81: =IF($R81="","",INDEX(Cálculos!$S:$S,$R81)) | P81: =IF($R81="","",IF(M81>=1,"Completo","Pendiente")) | R81: =IFERROR(SMALL(Cálculos!$T$30:$T$109,68),"")
B82: =IF($R82="","",69) | C82: =IF($R82="","",INDEX(Cálculos!$O:$O,$R82)) | G82: =IF($R82="","",INDEX(Cálculos!$P:$P,$R82)) | J82: =IF($R82="","",INDEX(Cálculos!$Q:$Q,$R82)) | K82: =IF($R82="","",INDEX(Cálculos!$M:$M,$R82)) | L82: =IF($R82="","",INDEX(Cálculos!$N:$N,$R82)) | M82: =IF($R82="","",INDEX(Cálculos!$R:$R,$R82)) | O82: =IF($R82="","",INDEX(Cálculos!$S:$S,$R82)) | P82: =IF($R82="","",IF(M82>=1,"Completo","Pendiente")) | R82: =IFERROR(SMALL(Cálculos!$T$30:$T$109,69),"")
B83: =IF($R83="","",70) | C83: =IF($R83="","",INDEX(Cálculos!$O:$O,$R83)) | G83: =IF($R83="","",INDEX(Cálculos!$P:$P,$R83)) | J83: =IF($R83="","",INDEX(Cálculos!$Q:$Q,$R83)) | K83: =IF($R83="","",INDEX(Cálculos!$M:$M,$R83)) | L83: =IF($R83="","",INDEX(Cálculos!$N:$N,$R83)) | M83: =IF($R83="","",INDEX(Cálculos!$R:$R,$R83)) | O83: =IF($R83="","",INDEX(Cálculos!$S:$S,$R83)) | P83: =IF($R83="","",IF(M83>=1,"Completo","Pendiente")) | R83: =IFERROR(SMALL(Cálculos!$T$30:$T$109,70),"")
B84: =IF($R84="","",71) | C84: =IF($R84="","",INDEX(Cálculos!$O:$O,$R84)) | G84: =IF($R84="","",INDEX(Cálculos!$P:$P,$R84)) | J84: =IF($R84="","",INDEX(Cálculos!$Q:$Q,$R84)) | K84: =IF($R84="","",INDEX(Cálculos!$M:$M,$R84)) | L84: =IF($R84="","",INDEX(Cálculos!$N:$N,$R84)) | M84: =IF($R84="","",INDEX(Cálculos!$R:$R,$R84)) | O84: =IF($R84="","",INDEX(Cálculos!$S:$S,$R84)) | P84: =IF($R84="","",IF(M84>=1,"Completo","Pendiente")) | R84: =IFERROR(SMALL(Cálculos!$T$30:$T$109,71),"")
B85: =IF($R85="","",72) | C85: =IF($R85="","",INDEX(Cálculos!$O:$O,$R85)) | G85: =IF($R85="","",INDEX(Cálculos!$P:$P,$R85)) | J85: =IF($R85="","",INDEX(Cálculos!$Q:$Q,$R85)) | K85: =IF($R85="","",INDEX(Cálculos!$M:$M,$R85)) | L85: =IF($R85="","",INDEX(Cálculos!$N:$N,$R85)) | M85: =IF($R85="","",INDEX(Cálculos!$R:$R,$R85)) | O85: =IF($R85="","",INDEX(Cálculos!$S:$S,$R85)) | P85: =IF($R85="","",IF(M85>=1,"Completo","Pendiente")) | R85: =IFERROR(SMALL(Cálculos!$T$30:$T$109,72),"")
B86: =IF($R86="","",73) | C86: =IF($R86="","",INDEX(Cálculos!$O:$O,$R86)) | G86: =IF($R86="","",INDEX(Cálculos!$P:$P,$R86)) | J86: =IF($R86="","",INDEX(Cálculos!$Q:$Q,$R86)) | K86: =IF($R86="","",INDEX(Cálculos!$M:$M,$R86)) | L86: =IF($R86="","",INDEX(Cálculos!$N:$N,$R86)) | M86: =IF($R86="","",INDEX(Cálculos!$R:$R,$R86)) | O86: =IF($R86="","",INDEX(Cálculos!$S:$S,$R86)) | P86: =IF($R86="","",IF(M86>=1,"Completo","Pendiente")) | R86: =IFERROR(SMALL(Cálculos!$T$30:$T$109,73),"")
B87: =IF($R87="","",74) | C87: =IF($R87="","",INDEX(Cálculos!$O:$O,$R87)) | G87: =IF($R87="","",INDEX(Cálculos!$P:$P,$R87)) | J87: =IF($R87="","",INDEX(Cálculos!$Q:$Q,$R87)) | K87: =IF($R87="","",INDEX(Cálculos!$M:$M,$R87)) | L87: =IF($R87="","",INDEX(Cálculos!$N:$N,$R87)) | M87: =IF($R87="","",INDEX(Cálculos!$R:$R,$R87)) | O87: =IF($R87="","",INDEX(Cálculos!$S:$S,$R87)) | P87: =IF($R87="","",IF(M87>=1,"Completo","Pendiente")) | R87: =IFERROR(SMALL(Cálculos!$T$30:$T$109,74),"")
B88: =IF($R88="","",75) | C88: =IF($R88="","",INDEX(Cálculos!$O:$O,$R88)) | G88: =IF($R88="","",INDEX(Cálculos!$P:$P,$R88)) | J88: =IF($R88="","",INDEX(Cálculos!$Q:$Q,$R88)) | K88: =IF($R88="","",INDEX(Cálculos!$M:$M,$R88)) | L88: =IF($R88="","",INDEX(Cálculos!$N:$N,$R88)) | M88: =IF($R88="","",INDEX(Cálculos!$R:$R,$R88)) | O88: =IF($R88="","",INDEX(Cálculos!$S:$S,$R88)) | P88: =IF($R88="","",IF(M88>=1,"Completo","Pendiente")) | R88: =IFERROR(SMALL(Cálculos!$T$30:$T$109,75),"")
B89: =IF($R89="","",76) | C89: =IF($R89="","",INDEX(Cálculos!$O:$O,$R89)) | G89: =IF($R89="","",INDEX(Cálculos!$P:$P,$R89)) | J89: =IF($R89="","",INDEX(Cálculos!$Q:$Q,$R89)) | K89: =IF($R89="","",INDEX(Cálculos!$M:$M,$R89)) | L89: =IF($R89="","",INDEX(Cálculos!$N:$N,$R89)) | M89: =IF($R89="","",INDEX(Cálculos!$R:$R,$R89)) | O89: =IF($R89="","",INDEX(Cálculos!$S:$S,$R89)) | P89: =IF($R89="","",IF(M89>=1,"Completo","Pendiente")) | R89: =IFERROR(SMALL(Cálculos!$T$30:$T$109,76),"")
B90: =IF($R90="","",77) | C90: =IF($R90="","",INDEX(Cálculos!$O:$O,$R90)) | G90: =IF($R90="","",INDEX(Cálculos!$P:$P,$R90)) | J90: =IF($R90="","",INDEX(Cálculos!$Q:$Q,$R90)) | K90: =IF($R90="","",INDEX(Cálculos!$M:$M,$R90)) | L90: =IF($R90="","",INDEX(Cálculos!$N:$N,$R90)) | M90: =IF($R90="","",INDEX(Cálculos!$R:$R,$R90)) | O90: =IF($R90="","",INDEX(Cálculos!$S:$S,$R90)) | P90: =IF($R90="","",IF(M90>=1,"Completo","Pendiente")) | R90: =IFERROR(SMALL(Cálculos!$T$30:$T$109,77),"")
B91: =IF($R91="","",78) | C91: =IF($R91="","",INDEX(Cálculos!$O:$O,$R91)) | G91: =IF($R91="","",INDEX(Cálculos!$P:$P,$R91)) | J91: =IF($R91="","",INDEX(Cálculos!$Q:$Q,$R91)) | K91: =IF($R91="","",INDEX(Cálculos!$M:$M,$R91)) | L91: =IF($R91="","",INDEX(Cálculos!$N:$N,$R91)) | M91: =IF($R91="","",INDEX(Cálculos!$R:$R,$R91)) | O91: =IF($R91="","",INDEX(Cálculos!$S:$S,$R91)) | P91: =IF($R91="","",IF(M91>=1,"Completo","Pendiente")) | R91: =IFERROR(SMALL(Cálculos!$T$30:$T$109,78),"")
B92: =IF($R92="","",79) | C92: =IF($R92="","",INDEX(Cálculos!$O:$O,$R92)) | G92: =IF($R92="","",INDEX(Cálculos!$P:$P,$R92)) | J92: =IF($R92="","",INDEX(Cálculos!$Q:$Q,$R92)) | K92: =IF($R92="","",INDEX(Cálculos!$M:$M,$R92)) | L92: =IF($R92="","",INDEX(Cálculos!$N:$N,$R92)) | M92: =IF($R92="","",INDEX(Cálculos!$R:$R,$R92)) | O92: =IF($R92="","",INDEX(Cálculos!$S:$S,$R92)) | P92: =IF($R92="","",IF(M92>=1,"Completo","Pendiente")) | R92: =IFERROR(SMALL(Cálculos!$T$30:$T$109,79),"")
B93: =IF($R93="","",80) | C93: =IF($R93="","",INDEX(Cálculos!$O:$O,$R93)) | G93: =IF($R93="","",INDEX(Cálculos!$P:$P,$R93)) | J93: =IF($R93="","",INDEX(Cálculos!$Q:$Q,$R93)) | K93: =IF($R93="","",INDEX(Cálculos!$M:$M,$R93)) | L93: =IF($R93="","",INDEX(Cálculos!$N:$N,$R93)) | M93: =IF($R93="","",INDEX(Cálculos!$R:$R,$R93)) | O93: =IF($R93="","",INDEX(Cálculos!$S:$S,$R93)) | P93: =IF($R93="","",IF(M93>=1,"Completo","Pendiente")) | R93: =IFERROR(SMALL(Cálculos!$T$30:$T$109,80),"")

Sheet Dashboard Gráfico
B1: DASHBOARD EJECUTIVO DE CUMPLIMIENTO
B2: Evaluación de Gestión Integral de Riesgos · avance institucional y por gerencia
B3: Datos actualizados al: | E3: =MAX('Detalle individual'!$H$5:$H$1000) -> 46311.814 | H3: =IF(COUNT(Cálculos!$AF$5:$AF$24)>10,"⚠ Hay gerencias nuevas: pida actualizar los gráficos (las tablas ya están al día)",IF(COUNT(Cálculos!$AE$5:$AE$84)>44,"⚠ Hay departamentos nuevos: pida actualizar los gráficos (las tablas ya están al día)",""))
B5: PERSONAL ESPERADO | E5: COMPLETADOS | H5: PENDIENTES | K5: % CUMPLIMIENTO | N5: NOTA PROMEDIO
B6: =SUM('Consolidado por Gerencia'!$B$5:$B$24) -> 283 | E6: =SUM('Consolidado por Gerencia'!$C$5:$C$24) -> 283 | H6: =SUM('Consolidado por Gerencia'!$D$5:$D$24) -> 0 | K6: =IF(B6>0,E6/B6,0) -> 1 | N6: =IFERROR(AVERAGE('Detalle individual'!$J$5:$J$1000),"-") -> 96.879433
B8: ="Excluye "&SUM('Consolidado por Gerencia'!$N$5:$N$24)&" con situación especial" -> Excluye 10 con situación especial | E8: Exámenes realizados | H8: Aún sin realizar | K8: Meta institucional: 100% | N8: Sobre 100 puntos
B9: TOTAL DE LA BASE OFICIAL Y CASOS ESPECIALES (no cuentan en el % de cumplimiento)
B10: TOTAL BASE OFICIAL | E10: VACACIONES | H10: INCAPACIDAD | K10: INCAPACIDAD POR MATERNIDAD | N10: RENUNCIA
B11: =COUNTIF('Detalle individual'!$A$5:$A$1000,"?*") -> 293 | E11: =Cálculos!AV7 -> 4 | H11: =Cálculos!AV8 -> 1 | K11: =Cálculos!AV9 -> 2 | N11: =Cálculos!AV10 -> 3
B13: ="Esperados "&B6&" + "&SUM(Cálculos!$AV$7:$AV$10)&" casos especiales" -> Esperados 283 + 10 casos especiales | E13: No cuenta en el % | H13: No cuenta en el % | K13: No cuenta en el % | N13: No cuenta en el %

Sheet Dashboard de Estados
B1: DASHBOARD DE ESTADOS DEL PERSONAL
B2: Completados, pendientes y personal con situación especial (vacaciones, incapacidad, maternidad, renuncia)
B4: COMPLETADO | D4: PENDIENTE | F4: VACACIONES | H4: INCAPACIDAD | J4: INCAPACIDAD POR MATERNIDAD | L4: RENUNCIA
B5: =Cálculos!AV5 -> 283 | D5: =Cálculos!AV6 -> 0 | F5: =Cálculos!AV7 -> 4 | H5: =Cálculos!AV8 -> 1 | J5: =Cálculos!AV9 -> 2 | L5: =Cálculos!AV10 -> 3
B7: =IF(SUM(Cálculos!$AV$5:$AV$10)>0,Cálculos!AV5/SUM(Cálculos!$AV$5:$AV$10),0) -> 0.96587031 | D7: =IF(SUM(Cálculos!$AV$5:$AV$10)>0,Cálculos!AV6/SUM(Cálculos!$AV$5:$AV$10),0) -> 0 | F7: =IF(SUM(Cálculos!$AV$5:$AV$10)>0,Cálculos!AV7/SUM(Cálculos!$AV$5:$AV$10),0) -> 0.013651877 | H7: =IF(SUM(Cálculos!$AV$5:$AV$10)>0,Cálculos!AV8/SUM(Cálculos!$AV$5:$AV$10),0) -> 0.0034129693 | J7: =IF(SUM(Cálculos!$AV$5:$AV$10)>0,Cálculos!AV9/SUM(Cálculos!$AV$5:$AV$10),0) -> 0.0068259386 | L7: =IF(SUM(Cálculos!$AV$5:$AV$10)>0,Cálculos!AV10/SUM(Cálculos!$AV$5:$AV$10),0) -> 0.010238908
B77: Nota: el personal con situación especial que no ha realizado el examen no cuenta en el % de cumplimiento. La situación se asigna en 'Base Oficial', columna H.

Sheet Dashboard Departamentos
B1: CUMPLIMIENTO POR DEPARTAMENTO / AGENCIA
B2: Ordenado de mayor a menor % de cumplimiento · la barra muestra completados (azul) y pendientes (gris)
B3: =IF(COUNT(Cálculos!$AE$5:$AE$84)>44,"⚠ Hay departamentos nuevos que aún no aparecen en este gráfico: pida actualizarlo (las tablas ya están al día)","")

Sheet Estado por Colaborador
B1: ESTADO DE LA EVALUACIÓN POR COLABORADOR
B2: Use los filtros amarillos para ver quién completó y quién tiene pendiente el examen
B4: Gerencia: | D4: Todas las gerencias | G4: Colaboradores mostrados | H4: =COUNT(K9:K1004) -> 293
B5: Departamento: | D5: Todos los departamentos | G5: Completados | H5: =COUNTIF(H9:H1004,"Completado") -> 283
B6: Estado: | D6: Todos | G6: Pendientes | H6: =COUNTIF(H9:H1004,"Pendiente") -> 0
G7: Con situación especial | H7: =H4-H5-H6 -> 10
B8: # | C8: Código | D8: Nombre del colaborador | E8: Cargo | F8: Departamento / Agencia | G8: Gerencia | H8: Estado | I8: Fecha de finalización | J8: Nota
B9: =IF($K9="","",1) -> 1 | C9: =IF($K9="","",INDEX('Detalle individual'!$A:$A,$K9)) -> 440 | D9: =IF($K9="","",TRIM(INDEX('Detalle individual'!$B:$B,$K9))) -> KARLA MERCEDES DELEON DELGADO | E9: =IF($K9="","",TRIM(INDEX('Detalle individual'!$E:$E,$K9))) -> JEFE DE AGENCIA | F9: =IF($K9="","",TRIM(INDEX('Detalle individual'!$C:$C,$K9))) -> AGENCIA CENTRAL | G9: =IF($K9="","",INDEX('Detalle individual'!$D:$D,$K9)) -> Gerencia de Negocios | H9: =IF($K9="","",INDEX('Detalle individual'!$F:$F,$K9)) -> Vacaciones | I9: =IF($K9="","",IF(INDEX('Detalle individual'!$F:$F,$K9)="Completado",INDEX('Detalle individual'!$H:$H,$K9),"")) | J9: =IF($K9="","",IF(INDEX('Detalle individual'!$F:$F,$K9)="Completado",INDEX('Detalle individual'!$J:$J,$K9),"")) | K9: =IFERROR(MOD(SMALL(Cálculos!$Z$5:$Z$1000,1),10000),"") -> 196
B10: =IF($K10="","",2) -> 2 | C10: =IF($K10="","",INDEX('Detalle individual'!$A:$A,$K10)) -> 739 | D10: =IF($K10="","",TRIM(INDEX('Detalle individual'!$B:$B,$K10))) -> JOHANA PATRICIA LUNA RAMOS | E10: =IF($K10="","",TRIM(INDEX('Detalle individual'!$E:$E,$K10))) -> CAJERO | F10: =IF($K10="","",TRIM(INDEX('Detalle individual'!$C:$C,$K10))) -> AGENCIA CENTRAL | G10: =IF($K10="","",INDEX('Detalle individual'!$D:$D,$K10)) -> Gerencia de Negocios | H10: =IF($K10="","",INDEX('Detalle individual'!$F:$F,$K10)) -> Incapacidad por maternidad | I10: =IF($K10="","",IF(INDEX('Detalle individual'!$F:$F,$K10)="Completado",INDEX('Detalle individual'!$H:$H,$K10),"")) | J10: =IF($K10="","",IF(INDEX('Detalle individual'!$F:$F,$K10)="Completado",INDEX('Detalle individual'!$J:$J,$K10),"")) | K10: =IFERROR(MOD(SMALL(Cálculos!$Z$5:$Z$1000,2),10000),"") -> 198
B11: =IF($K11="","",3) -> 3 | C11: =IF($K11="","",INDEX('Detalle individual'!$A:$A,$K11)) -> 466 | D11: =IF($K11="","",TRIM(INDEX('Detalle individual'!$B:$B,$K11))) -> DORIS ELISA HERNANDEZ | E11: =IF($K11="","",TRIM(INDEX('Detalle individual'!$E:$E,$K11))) -> SERVICIOS VARIOS | F11: =IF($K11="","",TRIM(INDEX('Detalle individual'!$C:$C,$K11))) -> AGENCIA COLEGIO MEDICO | G11: =IF($K11="","",INDEX('Detalle individual'!$D:$D,$K11)) -> Gerencia de Negocios | H11: =IF($K11="","",INDEX('Detalle individual'!$F:$F,$K11)) -> Vacaciones | I11: =IF($K11="","",IF(INDEX('Detalle individual'!$F:$F,$K11)="Completado",INDEX('Detalle individual'!$H:$H,$K11),"")) | J11: =IF($K11="","",IF(INDEX('Detalle individual'!$F:$F,$K11)="Completado",INDEX('Detalle individual'!$J:$J,$K11),"")) | K11: =IFERROR(MOD(SMALL(Cálculos!$Z$5:$Z$1000,3),10000),"") -> 213
B12: =IF($K12="","",4) -> 4 | C12: =IF($K12="","",INDEX('Detalle individual'!$A:$A,$K12)) -> 861 | D12: =IF($K12="","",TRIM(INDEX('Detalle individual'!$B:$B,$K12))) -> SANDRA MARINA BERRIOS SANTOS | E12: =IF($K12="","",TRIM(INDEX('Detalle individual'!$E:$E,$K12))) -> CAJERO | F12: =IF($K12="","",TRIM(INDEX('Detalle individual'!$C:$C,$K12))) -> AGENCIA SAN MIGUEL | G12: =IF($K12="","",INDEX('Detalle individual'!$D:$D,$K12)) -> Gerencia de Negocios | H12: =IF($K12="","",INDEX('Detalle individual'!$F:$F,$K12)) -> Incapacidad por maternidad | I12: =IF($K12="","",IF(INDEX('Detalle individual'!$F:$F,$K12)="Completado",INDEX('Detalle individual'!$H:$H,$K12),"")) | J12: =IF($K12="","",IF(INDEX('Detalle individual'!$F:$F,$K12)="Completado",INDEX('Detalle individual'!$J:$J,$K12),"")) | K12: =IFERROR(MOD(SMALL(Cálculos!$Z$5:$Z$1000,4),10000),"") -> 228
B13: =IF($K13="","",5) -> 5 | C13: =IF($K13="","",INDEX('Detalle individual'!$A:$A,$K13)) -> 835 | D13: =IF($K13="","",TRIM(INDEX('Detalle individual'!$B:$B,$K13))) -> LUIS ALBERTO MEJIA DELGADO | E13: =IF($K13="","",TRIM(INDEX('Detalle individual'!$E:$E,$K13))) -> EJECUTIVO DE NEGOCIOS | F13: =IF($K13="","",TRIM(INDEX('Detalle individual'!$C:$C,$K13))) -> DEPARTAMENTO COMERCIAL DE TARJETA DE CREDITO Y DEBITO | G13: =IF($K13="","",INDEX('Detalle individual'!$D:$D,$K13)) -> Gerencia de Negocios | H13: =IF($K13="","",INDEX('Detalle individual'!$F:$F,$K13)) -> Renuncia | I13: =IF($K13="","",IF(INDEX('Detalle individual'!$F:$F,$K13)="Completado",INDEX('Detalle individual'!$H:$H,$K13),"")) | J13: =IF($K13="","",IF(INDEX('Detalle individual'!$F:$F,$K13)="Completado",INDEX('Detalle individual'!$J:$J,$K13),"")) | K13: =IFERROR(MOD(SMALL(Cálculos!$Z$5:$Z$1000,5),10000),"") -> 182
B14: =IF($K14="","",6) -> 6 | C14: =IF($K14="","",INDEX('Detalle individual'!$A:$A,$K14)) -> 90 | D14: =IF($K14="","",TRIM(INDEX('Detalle individual'!$B:$B,$K14))) -> HUGO MARVIN SERRANO SARAVIA | E14: =IF($K14="","",TRIM(INDEX('Detalle individual'!$E:$E,$K14))) -> OPERADOR DE SISTEMAS | F14: =IF($K14="","",TRIM(INDEX('Detalle individual'!$C:$C,$K14))) -> DEPARTAMENTO DE OPERACIONES Y SOPORTE TECNICO | G14: =IF($K14="","",INDEX('Detalle individual'!$D:$D,$K14)) -> Gerencia de Sistemas | H14: =IF($K14="","",INDEX('Detalle individual'!$F:$F,$K14)) -> Vacaciones | I14: =IF($K14="","",IF(INDEX('Detalle individual'!$F:$F,$K14)="Completado",INDEX('Detalle individual'!$H:$H,$K14),"")) | J14: =IF($K14="","",IF(INDEX('Detalle individual'!$F:$F,$K14)="Completado",INDEX('Detalle individual'!$J:$J,$K14),"")) | K14: =IFERROR(MOD(SMALL(Cálculos!$Z$5:$Z$1000,6),10000),"") -> 104
B15: =IF($K15="","",7) -> 7 | C15: =IF($K15="","",INDEX('Detalle individual'!$A:$A,$K15)) -> 802 | D15: =IF($K15="","",TRIM(INDEX('Detalle individual'!$B:$B,$K15))) -> ERIKA VANESSA ALEMAN MIJANGO | E15: =IF($K15="","",TRIM(INDEX('Detalle individual'!$E:$E,$K15))) -> EJECUTIVO DE VENTA DE SEGUROS | F15: =IF($K15="","",TRIM(INDEX('Detalle individual'!$C:$C,$K15))) -> DEPARTAMENTO DE SEGUROS | G15: =IF($K15="","",INDEX('Detalle individual'!$D:$D,$K15)) -> Gerencia de Negocios | H15: =IF($K15="","",INDEX('Detalle individual'!$F:$F,$K15)) -> Renuncia | I15: =IF($K15="","",IF(INDEX('Detalle individual'!$F:$F,$K15)="Completado",INDEX('Detalle individual'!$H:$H,$K15),"")) | J15: =IF($K15="","",IF(INDEX('Detalle individual'!$F:$F,$K15)="Completado",INDEX('Detalle individual'!$J:$J,$K15),"")) | K15: =IFERROR(MOD(SMALL(Cálculos!$Z$5:$Z$1000,7),10000),"") -> 172
B16: =IF($K16="","",8) -> 8 | C16: =IF($K16="","",INDEX('Detalle individual'!$A:$A,$K16)) -> 885 | D16: =IF($K16="","",TRIM(INDEX('Detalle individual'!$B:$B,$K16))) -> ALBA BEATRIZ MELENDEZ PRUDENCIO | E16: =IF($K16="","",TRIM(INDEX('Detalle individual'!$E:$E,$K16))) -> ASISTENTE DE RECUPERACION JUDICIAL Y CARTERA CASTIGADA | F16: =IF($K16="","",TRIM(INDEX('Detalle individual'!$C:$C,$K16))) -> DEPARTAMENTO DE SOLUCIONES FINANCIERAS | G16: =IF($K16="","",INDEX('Detalle individual'!$D:$D,$K16)) -> Gerencia de Operaciones | H16: =IF($K16="","",INDEX('Detalle individual'!$F:$F,$K16)) -> Renuncia | I16: =IF($K16="","",IF(INDEX('Detalle individual'!$F:$F,$K16)="Completado",INDEX('Detalle individual'!$H:$H,$K16),"")) | J16: =IF($K16="","",IF(INDEX('Detalle individual'!$F:$F,$K16)="Completado",INDEX('Detalle individual'!$J:$J,$K16),"")) | K16: =IFERROR(MOD(SMALL(Cálculos!$Z$5:$Z$1000,8),10000),"") -> 68
B17: =IF($K17="","",9) -> 9 | C17: =IF($K17="","",INDEX('Detalle individual'!$A:$A,$K17)) -> 65 | D17: =IF($K17="","",TRIM(INDEX('Detalle individual'!$B:$B,$K17))) -> DORA ALICIA CASTILLO | E17: =IF($K17="","",TRIM(INDEX('Detalle individual'!$E:$E,$K17))) -> JEFE DE TALENTO HUMANO | F17: =IF($K17="","",TRIM(INDEX('Detalle individual'!$C:$C,$K17))) -> DEPARTAMENTO DE TALENTO HUMANO | G17: =IF($K17="","",INDEX('Detalle individual'!$D:$D,$K17)) -> Gerencia Administrativa | H17: =IF($K17="","",INDEX('Detalle individual'!$F:$F,$K17)) -> Vacaciones | I17: =IF($K17="","",IF(INDEX('Detalle individual'!$F:$F,$K17)="Completado",INDEX('Detalle individual'!$H:$H,$K17),"")) | J17: =IF($K17="","",IF(INDEX('Detalle individual'!$F:$F,$K17)="Completado",INDEX('Detalle individual'!$J:$J,$K17),"")) | K17: =IFERROR(MOD(SMALL(Cálculos!$Z$5:$Z$1000,9),10000),"") -> 49
B18: =IF($K18="","",10) -> 10 | C18: =IF($K18="","",INDEX('Detalle individual'!$A:$A,$K18)) -> 399 | D18: =IF($K18="","",TRIM(INDEX('Detalle individual'!$B:$B,$K18))) -> GEOVANNI LIZAMA PORTILLO | E18: =IF($K18="","",TRIM(INDEX('Detalle individual'!$E:$E,$K18))) -> JEFE DE TARJETA DE CREDITO Y DEBITO | F18: =IF($K18="","",TRIM(INDEX('Detalle individual'!$C:$C,$K18))) -> DEPARTAMENTO DE TARJETA DE CREDITO Y DEBITO | G18: =IF($K18="","",INDEX('Detalle individual'!$D:$D,$K18)) -> Gerencia de Operaciones | H18: =IF($K18="","",INDEX('Detalle individual'!$F:$F,$K18)) -> Incapacidad | I18: =IF($K18="","",IF(INDEX('Detalle individual'!$F:$F,$K18)="Completado",INDEX('Detalle individual'!$H:$H,$K18),"")) | J18: =IF($K18="","",IF(INDEX('Detalle individual'!$F:$F,$K18)="Completado",INDEX('Detalle individual'!$J:$J,$K18),"")) | K18: =IFERROR(MOD(SMALL(Cálculos!$Z$5:$Z$1000,10),10000),"") -> 70
B19: =IF($K19="","",11) -> 11 | C19: =IF($K19="","",INDEX('Detalle individual'!$A:$A,$K19)) -> 409 | D19: =IF($K19="","",TRIM(INDEX('Detalle individual'!$B:$B,$K19))) -> PEDRO ERNESTO MORÁN RAMÍREZ | E19: =IF($K19="","",TRIM(INDEX('Detalle individual'!$E:$E,$K19))) -> ADMINISTRADOR DE BASE DE DATOS | F19: =IF($K19="","",TRIM(INDEX('Detalle individual'!$C:$C,$K19))) -> ADMINISTRACION DE BASE DE DATOS | G19: =IF($K19="","",INDEX('Detalle individual'!$D:$D,$K19)) -> Gerencia de Sistemas | H19: =IF($K19="","",INDEX('Detalle individual'!$F:$F,$K19)) -> Completado | I19: =IF($K19="","",IF(INDEX('Detalle individual'!$F:$F,$K19)="Completado",INDEX('Detalle individual'!$H:$H,$K19),"")) -> 46300.696 | J19: =IF($K19="","",IF(INDEX('Detalle individual'!$F:$F,$K19)="Completado",INDEX('Detalle individual'!$J:$J,$K19),"")) -> 95 | K19: =IFERROR(MOD(SMALL(Cálculos!$Z$5:$Z$1000,11),10000),"") -> 122
B20: =IF($K20="","",12) -> 12 | C20: =IF($K20="","",INDEX('Detalle individual'!$A:$A,$K20)) -> 16 | D20: =IF($K20="","",TRIM(INDEX('Detalle individual'!$B:$B,$K20))) -> YANETH MARLENY LANDAVERDE MORALES | E20: =IF($K20="","",TRIM(INDEX('Detalle individual'!$E:$E,$K20))) -> JEFE DE ADMINISTRACION DE CARTERA | F20: =IF($K20="","",TRIM(INDEX('Detalle individual'!$C:$C,$K20))) -> ADMINISTRACIÓN DE CARTERAS | G20: =IF($K20="","",INDEX('Detalle individual'!$D:$D,$K20)) -> Gerencia de Operaciones | H20: =IF($K20="","",INDEX('Detalle individual'!$F:$F,$K20)) -> Completado | I20: =IF($K20="","",IF(INDEX('Detalle individual'!$F:$F,$K20)="Completado",INDEX('Detalle individual'!$H:$H,$K20),"")) -> 46307.676 | J20: =IF($K20="","",IF(INDEX('Detalle individual'!$F:$F,$K20)="Completado",INDEX('Detalle individual'!$J:$J,$K20),"")) -> 100 | K20: =IFERROR(MOD(SMALL(Cálculos!$Z$5:$Z$1000,12),10000),"") -> 79
B21: =IF($K21="","",13) -> 13 | C21: =IF($K21="","",INDEX('Detalle individual'!$A:$A,$K21)) -> 477 | D21: =IF($K21="","",TRIM(INDEX('Detalle individual'!$B:$B,$K21))) -> GEMA YESENIA VILLALOBOS HERNANDEZ | E21: =IF($K21="","",TRIM(INDEX('Detalle individual'!$E:$E,$K21))) -> ANALISTA DE CARTERAS | F21: =IF($K21="","",TRIM(INDEX('Detalle individual'!$C:$C,$K21))) -> ADMINISTRACIÓN DE CARTERAS | G21: =IF($K21="","",INDEX('Detalle individual'!$D:$D,$K21)) -> Gerencia de Operaciones | H21: =IF($K21="","",INDEX('Detalle individual'!$F:$F,$K21)) -> Completado | I21: =IF($K21="","",IF(INDEX('Detalle individual'!$F:$F,$K21)="Completado",INDEX('Detalle individual'!$H:$H,$K21),"")) -> 46307.656 | J21: =IF($K21="","",IF(INDEX('Detalle individual'!$F:$F,$K21)="Completado",INDEX('Detalle individual'!$J:$J,$K21),"")) -> 100 | K21: =IFERROR(MOD(SMALL(Cálculos!$Z$5:$Z$1000,13),10000),"") -> 80
B22: =IF($K22="","",14) -> 14 | C22: =IF($K22="","",INDEX('Detalle individual'!$A:$A,$K22)) -> 572 | D22: =IF($K22="","",TRIM(INDEX('Detalle individual'!$B:$B,$K22))) -> PAMELA GIOVANNA AGUILAR SERBELLON | E22: =IF($K22="","",TRIM(INDEX('Detalle individual'!$E:$E,$K22))) -> GESTOR DE COBROS Y PAGOS DE SEGUROS | F22: =IF($K22="","",TRIM(INDEX('Detalle individual'!$C:$C,$K22))) -> ADMINISTRACIÓN DE CARTERAS | G22: =IF($K22="","",INDEX('Detalle individual'!$D:$D,$K22)) -> Gerencia de Operaciones | H22: =IF($K22="","",INDEX('Detalle individual'!$F:$F,$K22)) -> Completado | I22: =IF($K22="","",IF(INDEX('Detalle individual'!$F:$F,$K22)="Completado",INDEX('Detalle individual'!$H:$H,$K22),"")) -> 46304.512 | J22: =IF($K22="","",IF(INDEX('Detalle individual'!$F:$F,$K22)="Completado",INDEX('Detalle individual'!$J:$J,$K22),"")) -> 100 | K22: =IFERROR(MOD(SMALL(Cálculos!$Z$5:$Z$1000,14),10000),"") -> 81
B23: =IF($K23="","",15) -> 15 | C23: =IF($K23="","",INDEX('Detalle individual'!$A:$A,$K23)) -> 732 | D23: =IF($K23="","",TRIM(INDEX('Detalle individual'!$B:$B,$K23))) -> RICARDO JOSUE CACAO ROVELO | E23: =IF($K23="","",TRIM(INDEX('Detalle individual'!$E:$E,$K23))) -> ANALISTA DE CARTERAS | F23: =IF($K23="","",TRIM(INDEX('Detalle individual'!$C:$C,$K23))) -> ADMINISTRACIÓN DE CARTERAS | G23: =IF($K23="","",INDEX('Detalle individual'!$D:$D,$K23)) -> Gerencia de Operaciones | H23: =IF($K23="","",INDEX('Detalle individual'!$F:$F,$K23)) -> Completado | I23: =IF($K23="","",IF(INDEX('Detalle individual'!$F:$F,$K23)="Completado",INDEX('Detalle individual'!$H:$H,$K23),"")) -> 46311.676 | J23: =IF($K23="","",IF(INDEX('Detalle individual'!$F:$F,$K23)="Completado",INDEX('Detalle individual'!$J:$J,$K23),"")) -> 100 | K23: =IFERROR(MOD(SMALL(Cálculos!$Z$5:$Z$1000,15),10000),"") -> 82
B24: =IF($K24="","",16) -> 16 | C24: =IF($K24="","",INDEX('Detalle individual'!$A:$A,$K24)) -> 931 | D24: =IF($K24="","",TRIM(INDEX('Detalle individual'!$B:$B,$K24))) -> LOYDA ARACELY RAMOS CAÑENGUEZ | E24: =IF($K24="","",TRIM(INDEX('Detalle individual'!$E:$E,$K24))) -> ANALISTA DE PRESTAMOS | F24: =IF($K24="","",TRIM(INDEX('Detalle individual'!$C:$C,$K24))) -> ADMINISTRACIÓN DE CARTERAS | G24: =IF($K24="","",INDEX('Detalle individual'!$D:$D,$K24)) -> Gerencia de Operaciones | H24: =IF($K24="","",INDEX('Detalle individual'!$F:$F,$K24)) -> Completado | I24: =IF($K24="","",IF(INDEX('Detalle individual'!$F:$F,$K24)="Completado",INDEX('Detalle individual'!$H:$H,$K24),"")) -> 46304.567 | J24: =IF($K24="","",IF(INDEX('Detalle individual'!$F:$F,$K24)="Completado",INDEX('Detalle individual'!$J:$J,$K24),"")) -> 100 | K24: =IFERROR(MOD(SMALL(Cálculos!$Z$5:$Z$1000,16),10000),"") -> 83
B25: =IF($K25="","",17) -> 17 | C25: =IF($K25="","",INDEX('Detalle individual'!$A:$A,$K25)) -> 290 | D25: =IF($K25="","",TRIM(INDEX('Detalle individual'!$B:$B,$K25))) -> MELVIN ENRIQUE PORTILLO VALLE | E25: =IF($K25="","",TRIM(INDEX('Detalle individual'!$E:$E,$K25))) -> ANALISTA DE RIESGOS FINANCIEROS | F25: =IF($K25="","",TRIM(INDEX('Detalle individual'!$C:$C,$K25))) -> ADMINISTRACION DE RIESGOS | G25: =IF($K25="","",INDEX('Detalle individual'!$D:$D,$K25)) -> Gerencia General | H25: =IF($K25="","",INDEX('Detalle individual'!$F:$F,$K25)) -> Completado | I25: =IF($K25="","",IF(INDEX('Detalle individual'!$F:$F,$K25)="Completado",INDEX('Detalle individual'!$H:$H,$K25),"")) -> 46304.41 | J25: =IF($K25="","",IF(INDEX('Detalle individual'!$F:$F,$K25)="Completado",INDEX('Detalle individual'!$J:$J,$K25),"")) -> 100 | K25: =IFERROR(MOD(SMALL(Cálculos!$Z$5:$Z$1000,17),10000),"") -> 14
B26: =IF($K26="","",18) -> 18 | C26: =IF($K26="","",INDEX('Detalle individual'!$A:$A,$K26)) -> 408 | D26: =IF($K26="","",TRIM(INDEX('Detalle individual'!$B:$B,$K26))) -> SARA PATRICIA GONZALEZ JIMENEZ | E26: =IF($K26="","",TRIM(INDEX('Detalle individual'!$E:$E,$K26))) -> ASISTENTE TECNICO DE RIESGOS | F26: =IF($K26="","",TRIM(INDEX('Detalle individual'!$C:$C,$K26))) -> ADMINISTRACION DE RIESGOS | G26: =IF($K26="","",INDEX('Detalle individual'!$D:$D,$K26)) -> Gerencia General | H26: =IF($K26="","",INDEX('Detalle individual'!$F:$F,$K26)) -> Completado | I26: =IF($K26="","",IF(INDEX('Detalle individual'!$F:$F,$K26)="Completado",INDEX('Detalle individual'!$H:$H,$K26),"")) -> 46296.439 | J26: =IF($K26="","",IF(INDEX('Detalle individual'!$F:$F,$K26)="Completado",INDEX('Detalle individual'!$J:$J,$K26),"")) -> 100 | K26: =IFERROR(MOD(SMALL(Cálculos!$Z$5:$Z$1000,18),10000),"") -> 15
B27: =IF($K27="","",19) -> 19 | C27: =IF($K27="","",INDEX('Detalle individual'!$A:$A,$K27)) -> 433 | D27: =IF($K27="","",TRIM(INDEX('Detalle individual'!$B:$B,$K27))) -> SILVIA IVETH MARTINEZ RAMIREZ | E27: =IF($K27="","",TRIM(INDEX('Detalle individual'!$E:$E,$K27))) -> ANALISTA DE RIESGO OPERACIONAL | F27: =IF($K27="","",TRIM(INDEX('Detalle individual'!$C:$C,$K27))) -> ADMINISTRACION DE RIESGOS | G27: =IF($K27="","",INDEX('Detalle individual'!$D:$D,$K27)) -> Gerencia General | H27: =IF($K27="","",INDEX('Detalle individual'!$F:$F,$K27)) -> Completado | I27: =IF($K27="","",IF(INDEX('Detalle individual'!$F:$F,$K27)="Completado",INDEX('Detalle individual'!$H:$H,$K27),"")) -> 46300.631 | J27: =IF($K27="","",IF(INDEX('Detalle individual'!$F:$F,$K27)="Completado",INDEX('Detalle individual'!$J:$J,$K27),"")) -> 100 | K27: =IFERROR(MOD(SMALL(Cálculos!$Z$5:$Z$1000,19),10000),"") -> 16
B28: =IF($K28="","",20) -> 20 | C28: =IF($K28="","",INDEX('Detalle individual'!$A:$A,$K28)) -> 928 | D28: =IF($K28="","",TRIM(INDEX('Detalle individual'!$B:$B,$K28))) -> HENRRY DANIEL ESCAMILLA ZALDAÑA | E28: =IF($K28="","",TRIM(INDEX('Detalle individual'!$E:$E,$K28))) -> JEFE DE ADMINISTRACION DE RIESGOS | F28: =IF($K28="","",TRIM(INDEX('Detalle individual'!$C:$C,$K28))) -> ADMINISTRACION DE RIESGOS | G28: =IF($K28="","",INDEX('Detalle individual'!$D:$D,$K28)) -> Gerencia General | H28: =IF($K28="","",INDEX('Detalle individual'!$F:$F,$K28)) -> Completado | I28: =IF($K28="","",IF(INDEX('Detalle individual'!$F:$F,$K28)="Completado",INDEX('Detalle individual'!$H:$H,$K28),"")) -> 46305.399 | J28: =IF($K28="","",IF(INDEX('Detalle individual'!$F:$F,$K28)="Completado",INDEX('Detalle individual'!$J:$J,$K28),"")) -> 100 | K28: =IFERROR(MOD(SMALL(Cálculos!$Z$5:$Z$1000,20),10000),"") -> 17
B29: =IF($K29="","",21) -> 21 | C29: =IF($K29="","",INDEX('Detalle individual'!$A:$A,$K29)) -> 33 | D29: =IF($K29="","",TRIM(INDEX('Detalle individual'!$B:$B,$K29))) -> CAROLINA ELIZABETH RAMIREZ PONCE | E29: =IF($K29="","",TRIM(INDEX('Detalle individual'!$E:$E,$K29))) -> SUBJEFE DE AGENCIA | F29: =IF($K29="","",TRIM(INDEX('Detalle individual'!$C:$C,$K29))) -> AGENCIA CENTRAL | G29: =IF($K29="","",INDEX('Detalle individual'!$D:$D,$K29)) -> Gerencia de Negocios | H29: =IF($K29="","",INDEX('Detalle individual'!$F:$F,$K29)) -> Completado | I29: =IF($K29="","",IF(INDEX('Detalle individual'!$F:$F,$K29)="Completado",INDEX('Detalle individual'!$H:$H,$K29),"")) -> 46308.612 | J29: =IF($K29="","",IF(INDEX('Detalle individual'!$F:$F,$K29)="Completado",INDEX('Detalle individual'!$J:$J,$K29),"")) -> 100 | K29: =IFERROR(MOD(SMALL(Cálculos!$Z$5:$Z$1000,21),10000),"") -> 191
B30: =IF($K30="","",22) -> 22 | C30: =IF($K30="","",INDEX('Detalle individual'!$A:$A,$K30)) -> 49 | D30: =IF($K30="","",TRIM(INDEX('Detalle individual'!$B:$B,$K30))) -> GRISELDA DEL CARMEN DOMINGUEZ MERINO | E30: =IF($K30="","",TRIM(INDEX('Detalle individual'!$E:$E,$K30))) -> EJECUTIVO DE NEGOCIOS | F30: =IF($K30="","",TRIM(INDEX('Detalle individual'!$C:$C,$K30))) -> AGENCIA CENTRAL | G30: =IF($K30="","",INDEX('Detalle individual'!$D:$D,$K30)) -> Gerencia de Negocios | H30: =IF($K30="","",INDEX('Detalle individual'!$F:$F,$K30)) -> Completado | I30: =IF($K30="","",IF(INDEX('Detalle individual'!$F:$F,$K30)="Completado",INDEX('Detalle individual'!$H:$H,$K30),"")) -> 46310.665 | J30: =IF($K30="","",IF(INDEX('Detalle individual'!$F:$F,$K30)="Completado",INDEX('Detalle individual'!$J:$J,$K30),"")) -> 100 | K30: =IFERROR(MOD(SMALL(Cálculos!$Z$5:$Z$1000,22),10000),"") -> 192
B31: =IF($K31="","",23) -> 23 | C31: =IF($K31="","",INDEX('Detalle individual'!$A:$A,$K31)) -> 234 | D31: =IF($K31="","",TRIM(INDEX('Detalle individual'!$B:$B,$K31))) -> LETICIA ESMERALDA ROSA | E31: =IF($K31="","",TRIM(INDEX('Detalle individual'!$E:$E,$K31))) -> EJECUTIVO DE NEGOCIOS | F31: =IF($K31="","",TRIM(INDEX('Detalle individual'!$C:$C,$K31))) -> AGENCIA CENTRAL | G31: =IF($K31="","",INDEX('Detalle individual'!$D:$D,$K31)) -> Gerencia de Negocios | H31: =IF($K31="","",INDEX('Detalle individual'!$F:$F,$K31)) -> Completado | I31: =IF($K31="","",IF(INDEX('Detalle individual'!$F:$F,$K31)="Completado",INDEX('Detalle individual'!$H:$H,$K31),"")) -> 46311.715 | J31: =IF($K31="","",IF(INDEX('Detalle individual'!$F:$F,$K31)="Completado",INDEX('Detalle individual'!$J:$J,$K31),"")) -> 90 | K31: =IFERROR(MOD(SMALL(Cálculos!$Z$5:$Z$1000,23),10000),"") -> 193
B32: =IF($K32="","",24) -> 24 | C32: =IF($K32="","",INDEX('Detalle individual'!$A:$A,$K32)) -> 253 | D32: =IF($K32="","",TRIM(INDEX('Detalle individual'!$B:$B,$K32))) -> ELSY GUADALUPE COREA AGUILUZ | E32: =IF($K32="","",TRIM(INDEX('Detalle individual'!$E:$E,$K32))) -> EJECUTIVO DE NEGOCIOS | F32: =IF($K32="","",TRIM(INDEX('Detalle individual'!$C:$C,$K32))) -> AGENCIA CENTRAL | G32: =IF($K32="","",INDEX('Detalle individual'!$D:$D,$K32)) -> Gerencia de Negocios | H32: =IF($K32="","",INDEX('Detalle individual'!$F:$F,$K32)) -> Completado | I32: =IF($K32="","",IF(INDEX('Detalle individual'!$F:$F,$K32)="Completado",INDEX('Detalle individual'!$H:$H,$K32),"")) -> 46311.72 | J32: =IF($K32="","",IF(INDEX('Detalle individual'!$F:$F,$K32)="Completado",INDEX('Detalle individual'!$J:$J,$K32),"")) -> 100 | K32: =IFERROR(MOD(SMALL(Cálculos!$Z$5:$Z$1000,24),10000),"") -> 194
B33: =IF($K33="","",25) -> 25 | C33: =IF($K33="","",INDEX('Detalle individual'!$A:$A,$K33)) -> 385 | D33: =IF($K33="","",TRIM(INDEX('Detalle individual'!$B:$B,$K33))) -> BLANCA ARACELY MORENO HERNANDEZ | E33: =IF($K33="","",TRIM(INDEX('Detalle individual'!$E:$E,$K33))) -> AUXILIAR DE OPERACIONES Y ATENCION EN AGENCIA | F33: =IF($K33="","",TRIM(INDEX('Detalle individual'!$C:$C,$K33))) -> AGENCIA CENTRAL | G33: =IF($K33="","",INDEX('Detalle individual'!$D:$D,$K33)) -> Gerencia de Negocios | H33: =IF($K33="","",INDEX('Detalle individual'!$F:$F,$K33)) -> Completado | I33: =IF($K33="","",IF(INDEX('Detalle individual'!$F:$F,$K33)="Completado",INDEX('Detalle individual'!$H:$H,$K33),"")) -> 46311.507 | J33: =IF($K33="","",IF(INDEX('Detalle individual'!$F:$F,$K33)="Completado",INDEX('Detalle individual'!$J:$J,$K33),"")) -> 100 | K33: =IFERROR(MOD(SMALL(Cálculos!$Z$5:$Z$1000,25),10000),"") -> 195
B34: =IF($K34="","",26) -> 26 | C34: =IF($K34="","",INDEX('Detalle individual'!$A:$A,$K34)) -> 542 | D34: =IF($K34="","",TRIM(INDEX('Detalle individual'!$B:$B,$K34))) -> ANA SILVIA ROQUE SANCHEZ | E34: =IF($K34="","",TRIM(INDEX('Detalle individual'!$E:$E,$K34))) -> EJECUTIVA DE SEGUROS | F34: =IF($K34="","",TRIM(INDEX('Detalle individual'!$C:$C,$K34))) -> AGENCIA CENTRAL | G34: =IF($K34="","",INDEX('Detalle individual'!$D:$D,$K34)) -> Gerencia de Negocios | H34: =IF($K34="","",INDEX('Detalle individual'!$F:$F,$K34)) -> Completado | I34: =IF($K34="","",IF(INDEX('Detalle individual'!$F:$F,$K34)="Completado",INDEX('Detalle individual'!$H:$H,$K34),"")) -> 46302.674 | J34: =IF($K34="","",IF(INDEX('Detalle individual'!$F:$F,$K34)="Completado",INDEX('Detalle individual'!$J:$J,$K34),"")) -> 95 | K34: =IFERROR(MOD(SMALL(Cálculos!$Z$5:$Z$1000,26),10000),"") -> 197
B35: =IF($K35="","",27) -> 27 | C35: =IF($K35="","",INDEX('Detalle individual'!$A:$A,$K35)) -> 757 | D35: =IF($K35="","",TRIM(INDEX('Detalle individual'!$B:$B,$K35))) -> MARIA DE LOS ANGELES OSORIO GIL | E35: =IF($K35="","",TRIM(INDEX('Detalle individual'!$E:$E,$K35))) -> CAJERO | F35: =IF($K35="","",TRIM(INDEX('Detalle individual'!$C:$C,$K35))) -> AGENCIA CENTRAL | G35: =IF($K35="","",INDEX('Detalle individual'!$D:$D,$K35)) -> Gerencia de Negocios | H35: =IF($K35="","",INDEX('Detalle individual'!$F:$F,$K35)) -> Completado | I35: =IF($K35="","",IF(INDEX('Detalle individual'!$F:$F,$K35)="Completado",INDEX('Detalle individual'!$H:$H,$K35),"")) -> 46303.443 | J35: =IF($K35="","",IF(INDEX('Detalle individual'!$F:$F,$K35)="Completado",INDEX('Detalle individual'!$J:$J,$K35),"")) -> 100 | K35: =IFERROR(MOD(SMALL(Cálculos!$Z$5:$Z$1000,27),10000),"") -> 199
B36: =IF($K36="","",28) -> 28 | C36: =IF($K36="","",INDEX('Detalle individual'!$A:$A,$K36)) -> 768 | D36: =IF($K36="","",TRIM(INDEX('Detalle individual'!$B:$B,$K36))) -> KATHERINE MICHELLE LOPEZ LOPEZ | E36: =IF($K36="","",TRIM(INDEX('Detalle individual'!$E:$E,$K36))) -> AUXILIAR DE OPERACIONES Y ATENCION EN AGENCIA | F36: =IF($K36="","",TRIM(INDEX('Detalle individual'!$C:$C,$K36))) -> AGENCIA CENTRAL | G36: =IF($K36="","",INDEX('Detalle individual'!$D:$D,$K36)) -> Gerencia de Negocios | H36: =IF($K36="","",INDEX('Detalle individual'!$F:$F,$K36)) -> Completado | I36: =IF($K36="","",IF(INDEX('Detalle individual'!$F:$F,$K36)="Completado",INDEX('Detalle individual'!$H:$H,$K36),"")) -> 46310.66 | J36: =IF($K36="","",IF(INDEX('Detalle individual'!$F:$F,$K36)="Completado",INDEX('Detalle individual'!$J:$J,$K36),"")) -> 100 | K36: =IFERROR(MOD(SMALL(Cálculos!$Z$5:$Z$1000,28),10000),"") -> 200
B37: =IF($K37="","",29) -> 29 | C37: =IF($K37="","",INDEX('Detalle individual'!$A:$A,$K37)) -> 848 | D37: =IF($K37="","",TRIM(INDEX('Detalle individual'!$B:$B,$K37))) -> JAZMIN ABIGAIL VASQUEZ AVELAR | E37: =IF($K37="","",TRIM(INDEX('Detalle individual'!$E:$E,$K37))) -> CAJERO | F37: =IF($K37="","",TRIM(INDEX('Detalle individual'!$C:$C,$K37))) -> AGENCIA CENTRAL | G37: =IF($K37="","",INDEX('Detalle individual'!$D:$D,$K37)) -> Gerencia de Negocios | H37: =IF($K37="","",INDEX('Detalle individual'!$F:$F,$K37)) -> Completado | I37: =IF($K37="","",IF(INDEX('Detalle individual'!$F:$F,$K37)="Completado",INDEX('Detalle individual'!$H:$H,$K37),"")) -> 46311.485 | J37: =IF($K37="","",IF(INDEX('Detalle individual'!$F:$F,$K37)="Completado",INDEX('Detalle individual'!$J:$J,$K37),"")) -> 100 | K37: =IFERROR(MOD(SMALL(Cálculos!$Z$5:$Z$1000,29),10000),"") -> 201
B38: =IF($K38="","",30) -> 30 | C38: =IF($K38="","",INDEX('Detalle individual'!$A:$A,$K38)) -> 857 | D38: =IF($K38="","",TRIM(INDEX('Detalle individual'!$B:$B,$K38))) -> ESTHER ABIGAIL FLORES GRANDE | E38: =IF($K38="","",TRIM(INDEX('Detalle individual'!$E:$E,$K38))) -> AUXILIAR DE OPERACIONES Y ATENCION EN AGENCIA | F38: =IF($K38="","",TRIM(INDEX('Detalle individual'!$C:$C,$K38))) -> AGENCIA CENTRAL | G38: =IF($K38="","",INDEX('Detalle individual'!$D:$D,$K38)) -> Gerencia de Negocios | H38: =IF($K38="","",INDEX('Detalle individual'!$F:$F,$K38)) -> Completado | I38: =IF($K38="","",IF(INDEX('Detalle individual'!$F:$F,$K38)="Completado",INDEX('Detalle individual'!$H:$H,$K38),"")) -> 46310.557 | J38: =IF($K38="","",IF(INDEX('Detalle individual'!$F:$F,$K38)="Completado",INDEX('Detalle individual'!$J:$J,$K38),"")) -> 100 | K38: =IFERROR(MOD(SMALL(Cálculos!$Z$5:$Z$1000,30),10000),"") -> 202
B39: =IF($K39="","",31) -> 31 | C39: =IF($K39="","",INDEX('Detalle individual'!$A:$A,$K39)) -> 953 | D39: =IF($K39="","",TRIM(INDEX('Detalle individual'!$B:$B,$K39))) -> JESUS ADRIAN MENA AVALOS | E39: =IF($K39="","",TRIM(INDEX('Detalle individual'!$E:$E,$K39))) -> CAJERO | F39: =IF($K39="","",TRIM(INDEX('Detalle individual'!$C:$C,$K39))) -> AGENCIA CENTRAL | G39: =IF($K39="","",INDEX('Detalle individual'!$D:$D,$K39)) -> Gerencia de Negocios | H39: =IF($K39="","",INDEX('Detalle individual'!$F:$F,$K39)) -> Completado | I39: =IF($K39="","",IF(INDEX('Detalle individual'!$F:$F,$K39)="Completado",INDEX('Detalle individual'!$H:$H,$K39),"")) -> 46302.627 | J39: =IF($K39="","",IF(INDEX('Detalle individual'!$F:$F,$K39)="Completado",INDEX('Detalle individual'!$J:$J,$K39),"")) -> 100 | K39: =IFERROR(MOD(SMALL(Cálculos!$Z$5:$Z$1000,31),10000),"") -> 203
B40: =IF($K40="","",32) -> 32 | C40: =IF($K40="","",INDEX('Detalle individual'!$A:$A,$K40)) -> 956 | D40: =IF($K40="","",TRIM(INDEX('Detalle individual'!$B:$B,$K40))) -> ANGELA GABRIELA REYES MOLINA | E40: =IF($K40="","",TRIM(INDEX('Detalle individual'!$E:$E,$K40))) -> CAJERO | F40: =IF($K40="","",TRIM(INDEX('Detalle individual'!$C:$C,$K40))) -> AGENCIA CENTRAL | G40: =IF($K40="","",INDEX('Detalle individual'!$D:$D,$K40)) -> Gerencia de Negocios | H40: =IF($K40="","",INDEX('Detalle individual'!$F:$F,$K40)) -> Completado | I40: =IF($K40="","",IF(INDEX('Detalle individual'!$F:$F,$K40)="Completado",INDEX('Detalle individual'!$H:$H,$K40),"")) -> 46309.367 | J40: =IF($K40="","",IF(INDEX('Detalle individual'!$F:$F,$K40)="Completado",INDEX('Detalle individual'!$J:$J,$K40),"")) -> 100 | K40: =IFERROR(MOD(SMALL(Cálculos!$Z$5:$Z$1000,32),10000),"") -> 204
B41: =IF($K41="","",33) -> 33 | C41: =IF($K41="","",INDEX('Detalle individual'!$A:$A,$K41)) -> 958 | D41: =IF($K41="","",TRIM(INDEX('Detalle individual'!$B:$B,$K41))) -> ALEXANDRA DANIELA PINEDA JIMENEZ | E41: =IF($K41="","",TRIM(INDEX('Detalle individual'!$E:$E,$K41))) -> AUXILIAR DE ATENCION A ASOCIADOS | F41: =IF($K41="","",TRIM(INDEX('Detalle individual'!$C:$C,$K41))) -> AGENCIA CENTRAL | G41: =IF($K41="","",INDEX('Detalle individual'!$D:$D,$K41)) -> Gerencia de Negocios | H41: =IF($K41="","",INDEX('Detalle individual'!$F:$F,$K41)) -> Completado | I41: =IF($K41="","",IF(INDEX('Detalle individual'!$F:$F,$K41)="Completado",INDEX('Detalle individual'!$H:$H,$K41),"")) -> 46305.396 | J41: =IF($K41="","",IF(INDEX('Detalle individual'!$F:$F,$K41)="Completado",INDEX('Detalle individual'!$J:$J,$K41),"")) -> 75 | K41: =IFERROR(MOD(SMALL(Cálculos!$Z$5:$Z$1000,33),10000),"") -> 205
B42: =IF($K42="","",34) -> 34 | C42: =IF($K42="","",INDEX('Detalle individual'!$A:$A,$K42)) -> 960 | D42: =IF($K42="","",TRIM(INDEX('Detalle individual'!$B:$B,$K42))) -> LORENA DEL CARMEN MEJIA HERRERA | E42: =IF($K42="","",TRIM(INDEX('Detalle individual'!$E:$E,$K42))) -> CAJERO | F42: =IF($K42="","",TRIM(INDEX('Detalle individual'!$C:$C,$K42))) -> AGENCIA CENTRAL | G42: =IF($K42="","",INDEX('Detalle individual'!$D:$D,$K42)) -> Gerencia de Negocios | H42: =IF($K42="","",INDEX('Detalle individual'!$F:$F,$K42)) -> Completado | I42: =IF($K42="","",IF(INDEX('Detalle individual'!$F:$F,$K42)="Completado",INDEX('Detalle individual'!$H:$H,$K42),"")) -> 46302.483 | J42: =IF($K42="","",IF(INDEX('Detalle individual'!$F:$F,$K42)="Completado",INDEX('Detalle individual'!$J:$J,$K42),"")) -> 100 | K42: =IFERROR(MOD(SMALL(Cálculos!$Z$5:$Z$1000,34),10000),"") -> 206
B43: =IF($K43="","",35) -> 35 | C43: =IF($K43="","",INDEX('Detalle individual'!$A:$A,$K43)) -> 974 | D43: =IF($K43="","",TRIM(INDEX('Detalle individual'!$B:$B,$K43))) -> LEIDY VANESSA GUZMAN SERVELLON | E43: =IF($K43="","",TRIM(INDEX('Detalle individual'!$E:$E,$K43))) -> CAJERO | F43: =IF($K43="","",TRIM(INDEX('Detalle individual'!$C:$C,$K43))) -> AGENCIA CENTRAL | G43: =IF($K43="","",INDEX('Detalle individual'!$D:$D,$K43)) -> Gerencia de Negocios | H43: =IF($K43="","",INDEX('Detalle individual'!$F:$F,$K43)) -> Completado | I43: =IF($K43="","",IF(INDEX('Detalle individual'!$F:$F,$K43)="Completado",INDEX('Detalle individual'!$H:$H,$K43),"")) -> 46311.477 | J43: =IF($K43="","",IF(INDEX('Detalle individual'!$F:$F,$K43)="Completado",INDEX('Detalle individual'!$J:$J,$K43),"")) -> 80 | K43: =IFERROR(MOD(SMALL(Cálculos!$Z$5:$Z$1000,35),10000),"") -> 207
B44: =IF($K44="","",36) -> 36 | C44: =IF($K44="","",INDEX('Detalle individual'!$A:$A,$K44)) -> 976 | D44: =IF($K44="","",TRIM(INDEX('Detalle individual'!$B:$B,$K44))) -> KEVIN ARTURO ANDRADE PALACIOS | E44: =IF($K44="","",TRIM(INDEX('Detalle individual'!$E:$E,$K44))) -> CAJERO | F44: =IF($K44="","",TRIM(INDEX('Detalle individual'!$C:$C,$K44))) -> AGENCIA CENTRAL | G44: =IF($K44="","",INDEX('Detalle individual'!$D:$D,$K44)) -> Gerencia de Negocios | H44: =IF($K44="","",INDEX('Detalle individual'!$F:$F,$K44)) -> Completado | I44: =IF($K44="","",IF(INDEX('Detalle individual'!$F:$F,$K44)="Completado",INDEX('Detalle individual'!$H:$H,$K44),"")) -> 46302.599 | J44: =IF($K44="","",IF(INDEX('Detalle individual'!$F:$F,$K44)="Completado",INDEX('Detalle individual'!$J:$J,$K44),"")) -> 100 | K44: =IFERROR(MOD(SMALL(Cálculos!$Z$5:$Z$1000,36),10000),"") -> 208
B45: =IF($K45="","",37) -> 37 | C45: =IF($K45="","",INDEX('Detalle individual'!$A:$A,$K45)) -> 26 | D45: =IF($K45="","",TRIM(INDEX('Detalle individual'!$B:$B,$K45))) -> FLOR IMELDA VILLALOBOS ARDON | E45: =IF($K45="","",TRIM(INDEX('Detalle individual'!$E:$E,$K45))) -> EJECUTIVO DE NEGOCIOS | F45: =IF($K45="","",TRIM(INDEX('Detalle individual'!$C:$C,$K45))) -> AGENCIA COLEGIO MEDICO | G45: =IF($K45="","",INDEX('Detalle individual'!$D:$D,$K45)) -> Gerencia de Negocios | H45: =IF($K45="","",INDEX('Detalle individual'!$F:$F,$K45)) -> Completado | I45: =IF($K45="","",IF(INDEX('Detalle individual'!$F:$F,$K45)="Completado",INDEX('Detalle individual'!$H:$H,$K45),"")) -> 46310.516 | J45: =IF($K45="","",IF(INDEX('Detalle individual'!$F:$F,$K45)="Completado",INDEX('Detalle individual'!$J:$J,$K45),"")) -> 100 | K45: =IFERROR(MOD(SMALL(Cálculos!$Z$5:$Z$1000,37),10000),"") -> 209
B46: =IF($K46="","",38) -> 38 | C46: =IF($K46="","",INDEX('Detalle individual'!$A:$A,$K46)) -> 29 | D46: =IF($K46="","",TRIM(INDEX('Detalle individual'!$B:$B,$K46))) -> YANIRA ELIZABETH ORTEGA MIRANDA | E46: =IF($K46="","",TRIM(INDEX('Detalle individual'!$E:$E,$K46))) -> SUBJEFE DE AGENCIA | F46: =IF($K46="","",TRIM(INDEX('Detalle individual'!$C:$C,$K46))) -> AGENCIA COLEGIO MEDICO | G46: =IF($K46="","",INDEX('Detalle individual'!$D:$D,$K46)) -> Gerencia de Negocios | H46: =IF($K46="","",INDEX('Detalle individual'!$F:$F,$K46)) -> Completado | I46: =IF($K46="","",IF(INDEX('Detalle individual'!$F:$F,$K46)="Completado",INDEX('Detalle individual'!$H:$H,$K46),"")) -> 46305.431 | J46: =IF($K46="","",IF(INDEX('Detalle individual'!$F:$F,$K46)="Completado",INDEX('Detalle individual'!$J:$J,$K46),"")) -> 100 | K46: =IFERROR(MOD(SMALL(Cálculos!$Z$5:$Z$1000,38),10000),"") -> 210
B47: =IF($K47="","",39) -> 39 | C47: =IF($K47="","",INDEX('Detalle individual'!$A:$A,$K47)) -> 190 | D47: =IF($K47="","",TRIM(INDEX('Detalle individual'!$B:$B,$K47))) -> MERCI ANTONIA CERON MEJIA | E47: =IF($K47="","",TRIM(INDEX('Detalle individual'!$E:$E,$K47))) -> EJECUTIVO DE NEGOCIOS | F47: =IF($K47="","",TRIM(INDEX('Detalle individual'!$C:$C,$K47))) -> AGENCIA COLEGIO MEDICO | G47: =IF($K47="","",INDEX('Detalle individual'!$D:$D,$K47)) -> Gerencia de Negocios | H47: =IF($K47="","",INDEX('Detalle individual'!$F:$F,$K47)) -> Completado | I47: =IF($K47="","",IF(INDEX('Detalle individual'!$F:$F,$K47)="Completado",INDEX('Detalle individual'!$H:$H,$K47),"")) -> 46305.513 | J47: =IF($K47="","",IF(INDEX('Detalle individual'!$F:$F,$K47)="Completado",INDEX('Detalle individual'!$J:$J,$K47),"")) -> 100 | K47: =IFERROR(MOD(SMALL(Cálculos!$Z$5:$Z$1000,39),10000),"") -> 211
B48: =IF($K48="","",40) -> 40 | C48: =IF($K48="","",INDEX('Detalle individual'!$A:$A,$K48)) -> 360 | D48: =IF($K48="","",TRIM(INDEX('Detalle individual'!$B:$B,$K48))) -> PATRICIA ESMERALDA PORTILLO CESPEDES | E48: =IF($K48="","",TRIM(INDEX('Detalle individual'!$E:$E,$K48))) -> JEFE DE AGENCIA | F48: =IF($K48="","",TRIM(INDEX('Detalle individual'!$C:$C,$K48))) -> AGENCIA COLEGIO MEDICO | G48: =IF($K48="","",INDEX('Detalle individual'!$D:$D,$K48)) -> Gerencia de Negocios | H48: =IF($K48="","",INDEX('Detalle individual'!$F:$F,$K48)) -> Completado | I48: =IF($K48="","",IF(INDEX('Detalle individual'!$F:$F,$K48)="Completado",INDEX('Detalle individual'!$H:$H,$K48),"")) -> 46296.476 | J48: =IF($K48="","",IF(INDEX('Detalle individual'!$F:$F,$K48)="Completado",INDEX('Detalle individual'!$J:$J,$K48),"")) -> 100 | K48: =IFERROR(MOD(SMALL(Cálculos!$Z$5:$Z$1000,40),10000),"") -> 212
B49: =IF($K49="","",41) -> 41 | C49: =IF($K49="","",INDEX('Detalle individual'!$A:$A,$K49)) -> 536 | D49: =IF($K49="","",TRIM(INDEX('Detalle individual'!$B:$B,$K49))) -> MARTHA ESPERANZA VALTEZ GARCIA | E49: =IF($K49="","",TRIM(INDEX('Detalle individual'!$E:$E,$K49))) -> CAJERO | F49: =IF($K49="","",TRIM(INDEX('Detalle individual'!$C:$C,$K49))) -> AGENCIA COLEGIO MEDICO | G49: =IF($K49="","",INDEX('Detalle individual'!$D:$D,$K49)) -> Gerencia de Negocios | H49: =IF($K49="","",INDEX('Detalle individual'!$F:$F,$K49)) -> Completado | I49: =IF($K49="","",IF(INDEX('Detalle individual'!$F:$F,$K49)="Completado",INDEX('Detalle individual'!$H:$H,$K49),"")) -> 46305.514 | J49: =IF($K49="","",IF(INDEX('Detalle individual'!$F:$F,$K49)="Completado",INDEX('Detalle individual'!$J:$J,$K49),"")) -> 100 | K49: =IFERROR(MOD(SMALL(Cálculos!$Z$5:$Z$1000,41),10000),"") -> 214
B50: =IF($K50="","",42) -> 42 | C50: =IF($K50="","",INDEX('Detalle individual'!$A:$A,$K50)) -> 543 | D50: =IF($K50="","",TRIM(INDEX('Detalle individual'!$B:$B,$K50))) -> CLAUDIA ELENA GUARDADO VARELA | E50: =IF($K50="","",TRIM(INDEX('Detalle individual'!$E:$E,$K50))) -> EJECUTIVA DE SEGUROS | F50: =IF($K50="","",TRIM(INDEX('Detalle individual'!$C:$C,$K50))) -> AGENCIA COLEGIO MEDICO | G50: =IF($K50="","",INDEX('Detalle individual'!$D:$D,$K50)) -> Gerencia de Negocios | H50: =IF($K50="","",INDEX('Detalle individual'!$F:$F,$K50)) -> Completado | I50: =IF($K50="","",IF(INDEX('Detalle individual'!$F:$F,$K50)="Completado",INDEX('Detalle individual'!$H:$H,$K50),"")) -> 46305.407 | J50: =IF($K50="","",IF(INDEX('Detalle individual'!$F:$F,$K50)="Completado",INDEX('Detalle individual'!$J:$J,$K50),"")) -> 100 | K50: =IFERROR(MOD(SMALL(Cálculos!$Z$5:$Z$1000,42),10000),"") -> 215
B51: =IF($K51="","",43) -> 43 | C51: =IF($K51="","",INDEX('Detalle individual'!$A:$A,$K51)) -> 811 | D51: =IF($K51="","",TRIM(INDEX('Detalle individual'!$B:$B,$K51))) -> JACQUELINE ADRIANA CHAVEZ SARAVIA | E51: =IF($K51="","",TRIM(INDEX('Detalle individual'!$E:$E,$K51))) -> CAJERO | F51: =IF($K51="","",TRIM(INDEX('Detalle individual'!$C:$C,$K51))) -> AGENCIA COLEGIO MEDICO | G51: =IF($K51="","",INDEX('Detalle individual'!$D:$D,$K51)) -> Gerencia de Negocios | H51: =IF($K51="","",INDEX('Detalle individual'!$F:$F,$K51)) -> Completado | I51: =IF($K51="","",IF(INDEX('Detalle individual'!$F:$F,$K51)="Completado",INDEX('Detalle individual'!$H:$H,$K51),"")) -> 46305.466 | J51: =IF($K51="","",IF(INDEX('Detalle individual'!$F:$F,$K51)="Completado",INDEX('Detalle individual'!$J:$J,$K51),"")) -> 90 | K51: =IFERROR(MOD(SMALL(Cálculos!$Z$5:$Z$1000,43),10000),"") -> 216
B52: =IF($K52="","",44) -> 44 | C52: =IF($K52="","",INDEX('Detalle individual'!$A:$A,$K52)) -> 841 | D52: =IF($K52="","",TRIM(INDEX('Detalle individual'!$B:$B,$K52))) -> KRISSIA ANDREA DOMINGUEZ OSORIO | E52: =IF($K52="","",TRIM(INDEX('Detalle individual'!$E:$E,$K52))) -> CAJERO | F52: =IF($K52="","",TRIM(INDEX('Detalle individual'!$C:$C,$K52))) -> AGENCIA COLEGIO MEDICO | G52: =IF($K52="","",INDEX('Detalle individual'!$D:$D,$K52)) -> Gerencia de Negocios | H52: =IF($K52="","",INDEX('Detalle individual'!$F:$F,$K52)) -> Completado | I52: =IF($K52="","",IF(INDEX('Detalle individual'!$F:$F,$K52)="Completado",INDEX('Detalle individual'!$H:$H,$K52),"")) -> 46305.399 | J52: =IF($K52="","",IF(INDEX('Detalle individual'!$F:$F,$K52)="Completado",INDEX('Detalle individual'!$J:$J,$K52),"")) -> 100 | K52: =IFERROR(MOD(SMALL(Cálculos!$Z$5:$Z$1000,44),10000),"") -> 217
B53: =IF($K53="","",45) -> 45 | C53: =IF($K53="","",INDEX('Detalle individual'!$A:$A,$K53)) -> 890 | D53: =IF($K53="","",TRIM(INDEX('Detalle individual'!$B:$B,$K53))) -> WILBER ERNESTO DIAZ GONZALEZ | E53: =IF($K53="","",TRIM(INDEX('Detalle individual'!$E:$E,$K53))) -> CAJERO | F53: =IF($K53="","",TRIM(INDEX('Detalle individual'!$C:$C,$K53))) -> AGENCIA COLEGIO MEDICO | G53: =IF($K53="","",INDEX('Detalle individual'!$D:$D,$K53)) -> Gerencia de Negocios | H53: =IF($K53="","",INDEX('Detalle individual'!$F:$F,$K53)) -> Completado | I53: =IF($K53="","",IF(INDEX('Detalle individual'!$F:$F,$K53)="Completado",INDEX('Detalle individual'!$H:$H,$K53),"")) -> 46307.43 | J53: =IF($K53="","",IF(INDEX('Detalle individual'!$F:$F,$K53)="Completado",INDEX('Detalle individual'!$J:$J,$K53),"")) -> 90 | K53: =IFERROR(MOD(SMALL(Cálculos!$Z$5:$Z$1000,45),10000),"") -> 218
B54: =IF($K54="","",46) -> 46 | C54: =IF($K54="","",INDEX('Detalle individual'!$A:$A,$K54)) -> 971 | D54: =IF($K54="","",TRIM(INDEX('Detalle individual'!$B:$B,$K54))) -> JAQUELIN JAZMIN ROMERO FLORES | E54: =IF($K54="","",TRIM(INDEX('Detalle individual'!$E:$E,$K54))) -> CAJERO | F54: =IF($K54="","",TRIM(INDEX('Detalle individual'!$C:$C,$K54))) -> AGENCIA COLEGIO MEDICO | G54: =IF($K54="","",INDEX('Detalle individual'!$D:$D,$K54)) -> Gerencia de Negocios | H54: =IF($K54="","",INDEX('Detalle individual'!$F:$F,$K54)) -> Completado | I54: =IF($K54="","",IF(INDEX('Detalle individual'!$F:$F,$K54)="Completado",INDEX('Detalle individual'!$H:$H,$K54),"")) -> 46305.441 | J54: =IF($K54="","",IF(INDEX('Detalle individual'!$F:$F,$K54)="Completado",INDEX('Detalle individual'!$J:$J,$K54),"")) -> 100 | K54: =IFERROR(MOD(SMALL(Cálculos!$Z$5:$Z$1000,46),10000),"") -> 219
B55: =IF($K55="","",47) -> 47 | C55: =IF($K55="","",INDEX('Detalle individual'!$A:$A,$K55)) -> 975 | D55: =IF($K55="","",TRIM(INDEX('Detalle individual'!$B:$B,$K55))) -> GABRIELA CONCEPCION GARCIA GUTIERREZ | E55: =IF($K55="","",TRIM(INDEX('Detalle individual'!$E:$E,$K55))) -> AUXILIAR DE ATENCION AL ASOCIADO EN AGENCIA | F55: =IF($K55="","",TRIM(INDEX('Detalle individual'!$C:$C,$K55))) -> AGENCIA COLEGIO MEDICO | G55: =IF($K55="","",INDEX('Detalle individual'!$D:$D,$K55)) -> Gerencia de Negocios | H55: =IF($K55="","",INDEX('Detalle individual'!$F:$F,$K55)) -> Completado | I55: =IF($K55="","",IF(INDEX('Detalle individual'!$F:$F,$K55)="Completado",INDEX('Detalle individual'!$H:$H,$K55),"")) -> 46305.48 | J55: =IF($K55="","",IF(INDEX('Detalle individual'!$F:$F,$K55)="Completado",INDEX('Detalle individual'!$J:$J,$K55),"")) -> 90 | K55: =IFERROR(MOD(SMALL(Cálculos!$Z$5:$Z$1000,47),10000),"") -> 220
B56: =IF($K56="","",48) -> 48 | C56: =IF($K56="","",INDEX('Detalle individual'!$A:$A,$K56)) -> 19 | D56: =IF($K56="","",TRIM(INDEX('Detalle individual'!$B:$B,$K56))) -> ANA MARGARITA SERRANO RUBIO | E56: =IF($K56="","",TRIM(INDEX('Detalle individual'!$E:$E,$K56))) -> CAJERO | F56: =IF($K56="","",TRIM(INDEX('Detalle individual'!$C:$C,$K56))) -> AGENCIA COLONIA MEDICA | G56: =IF($K56="","",INDEX('Detalle individual'!$D:$D,$K56)) -> Gerencia de Negocios | H56: =IF($K56="","",INDEX('Detalle individual'!$F:$F,$K56)) -> Completado | I56: =IF($K56="","",IF(INDEX('Detalle individual'!$F:$F,$K56)="Completado",INDEX('Detalle individual'!$H:$H,$K56),"")) -> 46310.541 | J56: =IF($K56="","",IF(INDEX('Detalle individual'!$F:$F,$K56)="Completado",INDEX('Detalle individual'!$J:$J,$K56),"")) -> 100 | K56: =IFERROR(MOD(SMALL(Cálculos!$Z$5:$Z$1000,48),10000),"") -> 257
B57: =IF($K57="","",49) -> 49 | C57: =IF($K57="","",INDEX('Detalle individual'!$A:$A,$K57)) -> 89 | D57: =IF($K57="","",TRIM(INDEX('Detalle individual'!$B:$B,$K57))) -> PATRICIA JEANNETTE FLORES MARTINEZ | E57: =IF($K57="","",TRIM(INDEX('Detalle individual'!$E:$E,$K57))) -> AUXILIAR DE OPERACIONES Y ATENCION EN AGENCIA | F57: =IF($K57="","",TRIM(INDEX('Detalle individual'!$C:$C,$K57))) -> AGENCIA COLONIA MEDICA | G57: =IF($K57="","",INDEX('Detalle individual'!$D:$D,$K57)) -> Gerencia de Negocios | H57: =IF($K57="","",INDEX('Detalle individual'!$F:$F,$K57)) -> Completado | I57: =IF($K57="","",IF(INDEX('Detalle individual'!$F:$F,$K57)="Completado",INDEX('Detalle individual'!$H:$H,$K57),"")) -> 46302.647 | J57: =IF($K57="","",IF(INDEX('Detalle individual'!$F:$F,$K57)="Completado",INDEX('Detalle individual'!$J:$J,$K57),"")) -> 100 | K57: =IFERROR(MOD(SMALL(Cálculos!$Z$5:$Z$1000,49),10000),"") -> 258
B58: =IF($K58="","",50) -> 50 | C58: =IF($K58="","",INDEX('Detalle individual'!$A:$A,$K58)) -> 179 | D58: =IF($K58="","",TRIM(INDEX('Detalle individual'!$B:$B,$K58))) -> JULIO RAFAEL FLORES HENRIQUEZ | E58: =IF($K58="","",TRIM(INDEX('Detalle individual'!$E:$E,$K58))) -> JEFE DE AGENCIA | F58: =IF($K58="","",TRIM(INDEX('Detalle individual'!$C:$C,$K58))) -> AGENCIA COLONIA MEDICA | G58: =IF($K58="","",INDEX('Detalle individual'!$D:$D,$K58)) -> Gerencia de Negocios | H58: =IF($K58="","",INDEX('Detalle individual'!$F:$F,$K58)) -> Completado | I58: =IF($K58="","",IF(INDEX('Detalle individual'!$F:$F,$K58)="Completado",INDEX('Detalle individual'!$H:$H,$K58),"")) -> 46309.366 | J58: =IF($K58="","",IF(INDEX('Detalle individual'!$F:$F,$K58)="Completado",INDEX('Detalle individual'!$J:$J,$K58),"")) -> 100 | K58: =IFERROR(MOD(SMALL(Cálculos!$Z$5:$Z$1000,50),10000),"") -> 259
B59: =IF($K59="","",51) -> 51 | C59: =IF($K59="","",INDEX('Detalle individual'!$A:$A,$K59)) -> 308 | D59: =IF($K59="","",TRIM(INDEX('Detalle individual'!$B:$B,$K59))) -> JENNIFFER IVETTE MORALES PEREZ | E59: =IF($K59="","",TRIM(INDEX('Detalle individual'!$E:$E,$K59))) -> EJECUTIVO DE NEGOCIOS | F59: =IF($K59="","",TRIM(INDEX('Detalle individual'!$C:$C,$K59))) -> AGENCIA COLONIA MEDICA | G59: =IF($K59="","",INDEX('Detalle individual'!$D:$D,$K59)) -> Gerencia de Negocios | H59: =IF($K59="","",INDEX('Detalle individual'!$F:$F,$K59)) -> Completado | I59: =IF($K59="","",IF(INDEX('Detalle individual'!$F:$F,$K59)="Completado",INDEX('Detalle individual'!$H:$H,$K59),"")) -> 46297.715 | J59: =IF($K59="","",IF(INDEX('Detalle individual'!$F:$F,$K59)="Completado",INDEX('Detalle individual'!$J:$J,$K59),"")) -> 95 | K59: =IFERROR(MOD(SMALL(Cálculos!$Z$5:$Z$1000,51),10000),"") -> 260
B60: =IF($K60="","",52) -> 52 | C60: =IF($K60="","",INDEX('Detalle individual'!$A:$A,$K60)) -> 412 | D60: =IF($K60="","",TRIM(INDEX('Detalle individual'!$B:$B,$K60))) -> CARMEN DE JESÚS GONZÁLEZ BLANCO | E60: =IF($K60="","",TRIM(INDEX('Detalle individual'!$E:$E,$K60))) -> EJECUTIVA DE SEGUROS | F60: =IF($K60="","",TRIM(INDEX('Detalle individual'!$C:$C,$K60))) -> AGENCIA COLONIA MEDICA | G60: =IF($K60="","",INDEX('Detalle individual'!$D:$D,$K60)) -> Gerencia de Negocios | H60: =IF($K60="","",INDEX('Detalle individual'!$F:$F,$K60)) -> Completado | I60: =IF($K60="","",IF(INDEX('Detalle individual'!$F:$F,$K60)="Completado",INDEX('Detalle individual'!$H:$H,$K60),"")) -> 46302.636 | J60: =IF($K60="","",IF(INDEX('Detalle individual'!$F:$F,$K60)="Completado",INDEX('Detalle individual'!$J:$J,$K60),"")) -> 100 | K60: =IFERROR(MOD(SMALL(Cálculos!$Z$5:$Z$1000,52),10000),"") -> 261
B61: =IF($K61="","",53) -> 53 | C61: =IF($K61="","",INDEX('Detalle individual'!$A:$A,$K61)) -> 624 | D61: =IF($K61="","",TRIM(INDEX('Detalle individual'!$B:$B,$K61))) -> JULIO ENRIQUE CAMPOS ANDRADE | E61: =IF($K61="","",TRIM(INDEX('Detalle individual'!$E:$E,$K61))) -> EJECUTIVO DE NEGOCIOS | F61: =IF($K61="","",TRIM(INDEX('Detalle individual'!$C:$C,$K61))) -> AGENCIA COLONIA MEDICA | G61: =IF($K61="","",INDEX('Detalle individual'!$D:$D,$K61)) -> Gerencia de Negocios | H61: =IF($K61="","",INDEX('Detalle individual'!$F:$F,$K61)) -> Completado | I61: =IF($K61="","",IF(INDEX('Detalle individual'!$F:$F,$K61)="Completado",INDEX('Detalle individual'!$H:$H,$K61),"")) -> 46310.517 | J61: =IF($K61="","",IF(INDEX('Detalle individual'!$F:$F,$K61)="Completado",INDEX('Detalle individual'!$J:$J,$K61),"")) -> 90 | K61: =IFERROR(MOD(SMALL(Cálculos!$Z$5:$Z$1000,53),10000),"") -> 262
B62: =IF($K62="","",54) -> 54 | C62: =IF($K62="","",INDEX('Detalle individual'!$A:$A,$K62)) -> 674 | D62: =IF($K62="","",TRIM(INDEX('Detalle individual'!$B:$B,$K62))) -> ALFREDO ARMANDO RAMOS ESCOBAR | E62: =IF($K62="","",TRIM(INDEX('Detalle individual'!$E:$E,$K62))) -> CAJERO | F62: =IF($K62="","",TRIM(INDEX('Detalle individual'!$C:$C,$K62))) -> AGENCIA COLONIA MEDICA | G62: =IF($K62="","",INDEX('Detalle individual'!$D:$D,$K62)) -> Gerencia de Negocios | H62: =IF($K62="","",INDEX('Detalle individual'!$F:$F,$K62)) -> Completado | I62: =IF($K62="","",IF(INDEX('Detalle individual'!$F:$F,$K62)="Completado",INDEX('Detalle individual'!$H:$H,$K62),"")) -> 46310.535 | J62: =IF($K62="","",IF(INDEX('Detalle individual'!$F:$F,$K62)="Completado",INDEX('Detalle individual'!$J:$J,$K62),"")) -> 100 | K62: =IFERROR(MOD(SMALL(Cálculos!$Z$5:$Z$1000,54),10000),"") -> 263
B63: =IF($K63="","",55) -> 55 | C63: =IF($K63="","",INDEX('Detalle individual'!$A:$A,$K63)) -> 722 | D63: =IF($K63="","",TRIM(INDEX('Detalle individual'!$B:$B,$K63))) -> INGRID PAOLA CORADO HERNANDEZ | E63: =IF($K63="","",TRIM(INDEX('Detalle individual'!$E:$E,$K63))) -> CAJERO | F63: =IF($K63="","",TRIM(INDEX('Detalle individual'!$C:$C,$K63))) -> AGENCIA COLONIA MEDICA | G63: =IF($K63="","",INDEX('Detalle individual'!$D:$D,$K63)) -> Gerencia de Negocios | H63: =IF($K63="","",INDEX('Detalle individual'!$F:$F,$K63)) -> Completado | I63: =IF($K63="","",IF(INDEX('Detalle individual'!$F:$F,$K63)="Completado",INDEX('Detalle individual'!$H:$H,$K63),"")) -> 46308.58 | J63: =IF($K63="","",IF(INDEX('Detalle individual'!$F:$F,$K63)="Completado",INDEX('Detalle individual'!$J:$J,$K63),"")) -> 90 | K63: =IFERROR(MOD(SMALL(Cálculos!$Z$5:$Z$1000,55),10000),"") -> 264
B64: =IF($K64="","",56) -> 56 | C64: =IF($K64="","",INDEX('Detalle individual'!$A:$A,$K64)) -> 728 | D64: =IF($K64="","",TRIM(INDEX('Detalle individual'!$B:$B,$K64))) -> DIANA MARISOL BATRES BARAHONA | E64: =IF($K64="","",TRIM(INDEX('Detalle individual'!$E:$E,$K64))) -> SUBJEFE DE AGENCIA | F64: =IF($K64="","",TRIM(INDEX('Detalle individual'!$C:$C,$K64))) -> AGENCIA COLONIA MEDICA | G64: =IF($K64="","",INDEX('Detalle individual'!$D:$D,$K64)) -> Gerencia de Negocios | H64: =IF($K64="","",INDEX('Detalle individual'!$F:$F,$K64)) -> Completado | I64: =IF($K64="","",IF(INDEX('Detalle individual'!$F:$F,$K64)="Completado",INDEX('Detalle individual'!$H:$H,$K64),"")) -> 46300.684 | J64: =IF($K64="","",IF(INDEX('Detalle individual'!$F:$F,$K64)="Completado",INDEX('Detalle individual'!$J:$J,$K64),"")) -> 100 | K64: =IFERROR(MOD(SMALL(Cálculos!$Z$5:$Z$1000,56),10000),"") -> 265
B65: =IF($K65="","",57) -> 57 | C65: =IF($K65="","",INDEX('Detalle individual'!$A:$A,$K65)) -> 735 | D65: =IF($K65="","",TRIM(INDEX('Detalle individual'!$B:$B,$K65))) -> YHANA MILET VALLE HERNANDEZ | E65: =IF($K65="","",TRIM(INDEX('Detalle individual'!$E:$E,$K65))) -> CAJERO | F65: =IF($K65="","",TRIM(INDEX('Detalle individual'!$C:$C,$K65))) -> AGENCIA COLONIA MEDICA | G65: =IF($K65="","",INDEX('Detalle individual'!$D:$D,$K65)) -> Gerencia de Negocios | H65: =IF($K65="","",INDEX('Detalle individual'!$F:$F,$K65)) -> Completado | I65: =IF($K65="","",IF(INDEX('Detalle individual'!$F:$F,$K65)="Completado",INDEX('Detalle individual'!$H:$H,$K65),"")) -> 46310.531 | J65: =IF($K65="","",IF(INDEX('Detalle individual'!$F:$F,$K65)="Completado",INDEX('Detalle individual'!$J:$J,$K65),"")) -> 100 | K65: =IFERROR(MOD(SMALL(Cálculos!$Z$5:$Z$1000,57),10000),"") -> 266
B66: =IF($K66="","",58) -> 58 | C66: =IF($K66="","",INDEX('Detalle individual'!$A:$A,$K66)) -> 801 | D66: =IF($K66="","",TRIM(INDEX('Detalle individual'!$B:$B,$K66))) -> ZULMA BEATRIZ RIVAS RIVERA | E66: =IF($K66="","",TRIM(INDEX('Detalle individual'!$E:$E,$K66))) -> CAJERO | F66: =IF($K66="","",TRIM(INDEX('Detalle individual'!$C:$C,$K66))) -> AGENCIA COLONIA MEDICA | G66: =IF($K66="","",INDEX('Detalle individual'!$D:$D,$K66)) -> Gerencia de Negocios | H66: =IF($K66="","",INDEX('Detalle individual'!$F:$F,$K66)) -> Completado | I66: =IF($K66="","",IF(INDEX('Detalle individual'!$F:$F,$K66)="Completado",INDEX('Detalle individual'!$H:$H,$K66),"")) -> 46300.688 | J66: =IF($K66="","",IF(INDEX('Detalle individual'!$F:$F,$K66)="Completado",INDEX('Detalle individual'!$J:$J,$K66),"")) -> 100 | K66: =IFERROR(MOD(SMALL(Cálculos!$Z$5:$Z$1000,58),10000),"") -> 267
B67: =IF($K67="","",59) -> 59 | C67: =IF($K67="","",INDEX('Detalle individual'!$A:$A,$K67)) -> 855 | D67: =IF($K67="","",TRIM(INDEX('Detalle individual'!$B:$B,$K67))) -> STEFFANY MARIELOS MIRO HERNANDEZ | E67: =IF($K67="","",TRIM(INDEX('Detalle individual'!$E:$E,$K67))) -> CAJERO | F67: =IF($K67="","",TRIM(INDEX('Detalle individual'!$C:$C,$K67))) -> AGENCIA COLONIA MEDICA | G67: =IF($K67="","",INDEX('Detalle individual'!$D:$D,$K67)) -> Gerencia de Negocios | H67: =IF($K67="","",INDEX('Detalle individual'!$F:$F,$K67)) -> Completado | I67: =IF($K67="","",IF(INDEX('Detalle individual'!$F:$F,$K67)="Completado",INDEX('Detalle individual'!$H:$H,$K67),"")) -> 46310.527 | J67: =IF($K67="","",IF(INDEX('Detalle individual'!$F:$F,$K67)="Completado",INDEX('Detalle individual'!$J:$J,$K67),"")) -> 100 | K67: =IFERROR(MOD(SMALL(Cálculos!$Z$5:$Z$1000,59),10000),"") -> 268
B68: =IF($K68="","",60) -> 60 | C68: =IF($K68="","",INDEX('Detalle individual'!$A:$A,$K68)) -> 873 | D68: =IF($K68="","",TRIM(INDEX('Detalle individual'!$B:$B,$K68))) -> FLOR DE MARIA ROSALES SORTO | E68: =IF($K68="","",TRIM(INDEX('Detalle individual'!$E:$E,$K68))) -> CAJERO | F68: =IF($K68="","",TRIM(INDEX('Detalle individual'!$C:$C,$K68))) -> AGENCIA COLONIA MEDICA | G68: =IF($K68="","",INDEX('Detalle individual'!$D:$D,$K68)) -> Gerencia de Negocios | H68: =IF($K68="","",INDEX('Detalle individual'!$F:$F,$K68)) -> Completado | I68: =IF($K68="","",IF(INDEX('Detalle individual'!$F:$F,$K68)="Completado",INDEX('Detalle individual'!$H:$H,$K68),"")) -> 46310.521 | J68: =IF($K68="","",IF(INDEX('Detalle individual'!$F:$F,$K68)="Completado",INDEX('Detalle individual'!$J:$J,$K68),"")) -> 100 | K68: =IFERROR(MOD(SMALL(Cálculos!$Z$5:$Z$1000,60),10000),"") -> 269
B69: =IF($K69="","",61) -> 61 | C69: =IF($K69="","",INDEX('Detalle individual'!$A:$A,$K69)) -> 891 | D69: =IF($K69="","",TRIM(INDEX('Detalle individual'!$B:$B,$K69))) -> YESENIA LISSETH BARAHONA VALLE | E69: =IF($K69="","",TRIM(INDEX('Detalle individual'!$E:$E,$K69))) -> AUXILIAR DE ATENCION AL ASOCIADO EN AGENCIA | F69: =IF($K69="","",TRIM(INDEX('Detalle individual'!$C:$C,$K69))) -> AGENCIA COLONIA MEDICA | G69: =IF($K69="","",INDEX('Detalle individual'!$D:$D,$K69)) -> Gerencia de Negocios | H69: =IF($K69="","",INDEX('Detalle individual'!$F:$F,$K69)) -> Completado | I69: =IF($K69="","",IF(INDEX('Detalle individual'!$F:$F,$K69)="Completado",INDEX('Detalle individual'!$H:$H,$K69),"")) -> 46310.546 | J69: =IF($K69="","",IF(INDEX('Detalle individual'!$F:$F,$K69)="Completado",INDEX('Detalle individual'!$J:$J,$K69),"")) -> 100 | K69: =IFERROR(MOD(SMALL(Cálculos!$Z$5:$Z$1000,61),10000),"") -> 270
