Workbook

Sheet Resumen Riesgos
A1: ¿QUÉ ME AUDITAN REPETIDO? – RESUMEN DE RECURRENCIA POR REQUERIMIENTO
A2: Año a analizar: | C2: Todos | D2: ← elija "Todos" o un año. Columna "¿Se repite?" = "Sí" cuando el mismo tema lo piden 2 o más orígenes (p. ej., SSF y Auditoría Interna).
A4: N° | B4: Requerimiento | C4: Norma | D4: Interna | E4: Externa | F4: SSF | G4: Comité Sup. | H4: Consejo Adm. | I4: Otros | J4: Total Veces | K4: Auditorías / visitas distintas | L4: N° de orígenes | M4: ¿Se repite? | N4: Ranking | O4: Ene | P4: Feb | Q4: Mar | R4: Abr | S4: May | T4: Jun | U4: Jul | V4: Ago | W4: Sep | X4: Oct | Y4: Nov | Z4: Dic
A5: 1 | B5: =Catálogos!C2 -> Actas Comité de Riesgos | C5: =Catálogos!D2 -> NRP-20 | D5: =SUMPRODUCT((Consolidado!$E$5:$E$1000=$B5)*(Consolidado!$C$5:$C$1000="Auditoría Interna")*((($C$2="Todos")+(Consolidado!$I$5:$I$1000&""=$C$2&""))>0)) -> 4 | E5: =SUMPRODUCT((Consolidado!$E$5:$E$1000=$B5)*(Consolidado!$C$5:$C$1000="Auditoría Externa")*((($C$2="Todos")+(Consolidado!$I$5:$I$1000&""=$C$2&""))>0)) -> 1 | F5: =SUMPRODUCT((Consolidado!$E$5:$E$1000=$B5)*(Consolidado!$C$5:$C$1000="SSF")*((($C$2="Todos")+(Consolidado!$I$5:$I$1000&""=$C$2&""))>0)) -> 0 | G5: =SUMPRODUCT((Consolidado!$E$5:$E$1000=$B5)*(Consolidado!$C$5:$C$1000="Comité de Supervisión")*((($C$2="Todos")+(Consolidado!$I$5:$I$1000&""=$C$2&""))>0)) -> 0 | H5: =SUMPRODUCT((Consolidado!$E$5:$E$1000=$B5)*(Consolidado!$C$5:$C$1000="Consejo de Administración")*((($C$2="Todos")+(Consolidado!$I$5:$I$1000&""=$C$2&""))>0)) -> 0 | I5: =SUMPRODUCT((Consolidado!$E$5:$E$1000=$B5)*(Consolidado!$C$5:$C$1000="Otros")*((($C$2="Todos")+(Consolidado!$I$5:$I$1000&""=$C$2&""))>0)) -> 0 | J5: =SUM(D5:I5) -> 5 | K5: =SUMPRODUCT((Consolidado!$E$5:$E$1000=$B5)*(Consolidado!$AE$5:$AE$1000)*((($C$2="Todos")+(Consolidado!$I$5:$I$1000&""=$C$2&""))>0)) -> 4 | L5: =COUNTIF(D5:I5,">0") -> 2 | M5: =IF(L5>=2,"Sí","No") -> Sí | N5: =IF(J5=0,"",RANK(J5,$J$5:$J$33)) -> 5 | O5: =SUMPRODUCT((Consolidado!$E$5:$E$1000=$B5)*(MONTH(Consolidado!$B$5:$B$1000+0*(Consolidado!$B$5:$B$1000=""))=1)*(Consolidado!$B$5:$B$1000<>"")*((($C$2="Todos")+(Consolidado!$I$5:$I$1000&""=$C$2&""))>0)) -> 0 | P5: =SUMPRODUCT((Consolidado!$E$5:$E$1000=$B5)*(MONTH(Consolidado!$B$5:$B$1000+0*(Consolidado!$B$5:$B$1000=""))=2)*(Consolidado!$B$5:$B$1000<>"")*((($C$2="Todos")+(Consolidado!$I$5:$I$1000&""=$C$2&""))>0)) -> 0 | Q5: =SUMPRODUCT((Consolidado!$E$5:$E$1000=$B5)*(MONTH(Consolidado!$B$5:$B$1000+0*(Consolidado!$B$5:$B$1000=""))=3)*(Consolidado!$B$5:$B$1000<>"")*((($C$2="Todos")+(Consolidado!$I$5:$I$1000&""=$C$2&""))>0)) -> 0 | R5: =SUMPRODUCT((Consolidado!$E$5:$E$1000=$B5)*(MONTH(Consolidado!$B$5:$B$1000+0*(Consolidado!$B$5:$B$1000=""))=4)*(Consolidado!$B$5:$B$1000<>"")*((($C$2="Todos")+(Consolidado!$I$5:$I$1000&""=$C$2&""))>0)) -> 0 | S5: =SUMPRODUCT((Consolidado!$E$5:$E$1000=$B5)*(MONTH(Consolidado!$B$5:$B$1000+0*(Consolidado!$B$5:$B$1000=""))=5)*(Consolidado!$B$5:$B$1000<>"")*((($C$2="Todos")+(Consolidado!$I$5:$I$1000&""=$C$2&""))>0)) -> 1 | T5: =SUMPRODUCT((Consolidado!$E$5:$E$1000=$B5)*(MONTH(Consolidado!$B$5:$B$1000+0*(Consolidado!$B$5:$B$1000=""))=6)*(Consolidado!$B$5:$B$1000<>"")*((($C$2="Todos")+(Consolidado!$I$5:$I$1000&""=$C$2&""))>0)) -> 0 | U5: =SUMPRODUCT((Consolidado!$E$5:$E$1000=$B5)*(MONTH(Consolidado!$B$5:$B$1000+0*(Consolidado!$B$5:$B$1000=""))=7)*(Consolidado!$B$5:$B$1000<>"")*((($C$2="Todos")+(Consolidado!$I$5:$I$1000&""=$C$2&""))>0)) -> 0 | V5: =SUMPRODUCT((Consolidado!$E$5:$E$1000=$B5)*(MONTH(Consolidado!$B$5:$B$1000+0*(Consolidado!$B$5:$B$1000=""))=8)*(Consolidado!$B$5:$B$1000<>"")*((($C$2="Todos")+(Consolidado!$I$5:$I$1000&""=$C$2&""))>0)) -> 2 | W5: =SUMPRODUCT((Consolidado!$E$5:$E$1000=$B5)*(MONTH(Consolidado!$B$5:$B$1000+0*(Consolidado!$B$5:$B$1000=""))=9)*(Consolidado!$B$5:$B$1000<>"")*((($C$2="Todos")+(Consolidado!$I$5:$I$1000&""=$C$2&""))>0)) -> 0 | X5: =SUMPRODUCT((Consolidado!$E$5:$E$1000=$B5)*(MONTH(Consolidado!$B$5:$B$1000+0*(Consolidado!$B$5:$B$1000=""))=10)*(Consolidado!$B$5:$B$1000<>"")*((($C$2="Todos")+(Consolidado!$I$5:$I$1000&""=$C$2&""))>0)) -> 2 | Y5: =SUMPRODUCT((Consolidado!$E$5:$E$1000=$B5)*(MONTH(Consolidado!$B$5:$B$1000+0*(Consolidado!$B$5:$B$1000=""))=11)*(Consolidado!$B$5:$B$1000<>"")*((($C$2="Todos")+(Consolidado!$I$5:$I$1000&""=$C$2&""))>0)) -> 0 | Z5: =SUMPRODUCT((Consolidado!$E$5:$E$1000=$B5)*(MONTH(Consolidado!$B$5:$B$1000+0*(Consolidado!$B$5:$B$1000=""))=12)*(Consolidado!$B$5:$B$1000<>"")*((($C$2="Todos")+(Consolidado!$I$5:$I$1000&""=$C$2&""))>0)) -> 0
A6: 2 | B6: =Catálogos!C3 -> Informe GIR / informes al Comité y Consejo | C6: =Catálogos!D3 -> NRP-20 | D6: =SUMPRODUCT((Consolidado!$E$5:$E$1000=$B6)*(Consolidado!$C$5:$C$1000="Auditoría Interna")*((($C$2="Todos")+(Consolidado!$I$5:$I$1000&""=$C$2&""))>0)) -> 5 | E6: =SUMPRODUCT((Consolidado!$E$5:$E$1000=$B6)*(Consolidado!$C$5:$C$1000="Auditoría Externa")*((($C$2="Todos")+(Consolidado!$I$5:$I$1000&""=$C$2&""))>0)) -> 0 | F6: =SUMPRODUCT((Consolidado!$E$5:$E$1000=$B6)*(Consolidado!$C$5:$C$1000="SSF")*((($C$2="Todos")+(Consolidado!$I$5:$I$1000&""=$C$2&""))>0)) -> 0 | G6: =SUMPRODUCT((Consolidado!$E$5:$E$1000=$B6)*(Consolidado!$C$5:$C$1000="Comité de Supervisión")*((($C$2="Todos")+(Consolidado!$I$5:$I$1000&""=$C$2&""))>0)) -> 0 | H6: =SUMPRODUCT((Consolidado!$E$5:$E$1000=$B6)*(Consolidado!$C$5:$C$1000="Consejo de Administración")*((($C$2="Todos")+(Consolidado!$I$5:$I$1000&""=$C$2&""))>0)) -> 0 | I6: =SUMPRODUCT((Consolidado!$E$5:$E$1000=$B6)*(Consolidado!$C$5:$C$1000="Otros")*((($C$2="Todos")+(Consolidado!$I$5:$I$1000&""=$C$2&""))>0)) -> 0 | J6: =SUM(D6:I6) -> 5 | K6: =SUMPRODUCT((Consolidado!$E$5:$E$1000=$B6)*(Consolidado!$AE$5:$AE$1000)*((($C$2="Todos")+(Consolidado!$I$5:$I$1000&""=$C$2&""))>0)) -> 2 | L6: =COUNTIF(D6:I6,">0") -> 1 | M6: =IF(L6>=2,"Sí","No") -> No | N6: =IF(J6=0,"",RANK(J6,$J$5:$J$33)) -> 5 | O6: =SUMPRODUCT((Consolidado!$E$5:$E$1000=$B6)*(MONTH(Consolidado!$B$5:$B$1000+0*(Consolidado!$B$5:$B$1000=""))=1)*(Consolidado!$B$5:$B$1000<>"")*((($C$2="Todos")+(Consolidado!$I$5:$I$1000&""=$C$2&""))>0)) -> 0 | P6: =SUMPRODUCT((Consolidado!$E$5:$E$1000=$B6)*(MONTH(Consolidado!$B$5:$B$1000+0*(Consolidado!$B$5:$B$1000=""))=2)*(Consolidado!$B$5:$B$1000<>"")*((($C$2="Todos")+(Consolidado!$I$5:$I$1000&""=$C$2&""))>0)) -> 0 | Q6: =SUMPRODUCT((Consolidado!$E$5:$E$1000=$B6)*(MONTH(Consolidado!$B$5:$B$1000+0*(Consolidado!$B$5:$B$1000=""))=3)*(Consolidado!$B$5:$B$1000<>"")*((($C$2="Todos")+(Consolidado!$I$5:$I$1000&""=$C$2&""))>0)) -> 0 | R6: =SUMPRODUCT((Consolidado!$E$5:$E$1000=$B6)*(MONTH(Consolidado!$B$5:$B$1000+0*(Consolidado!$B$5:$B$1000=""))=4)*(Consolidado!$B$5:$B$1000<>"")*((($C$2="Todos")+(Consolidado!$I$5:$I$1000&""=$C$2&""))>0)) -> 0 | S6: =SUMPRODUCT((Consolidado!$E$5:$E$1000=$B6)*(MONTH(Consolidado!$B$5:$B$1000+0*(Consolidado!$B$5:$B$1000=""))=5)*(Consolidado!$B$5:$B$1000<>"")*((($C$2="Todos")+(Consolidado!$I$5:$I$1000&""=$C$2&""))>0)) -> 1 | T6: =SUMPRODUCT((Consolidado!$E$5:$E$1000=$B6)*(MONTH(Consolidado!$B$5:$B$1000+0*(Consolidado!$B$5:$B$1000=""))=6)*(Consolidado!$B$5:$B$1000<>"")*((($C$2="Todos")+(Consolidado!$I$5:$I$1000&""=$C$2&""))>0)) -> 0 | U6: =SUMPRODUCT((Consolidado!$E$5:$E$1000=$B6)*(MONTH(Consolidado!$B$5:$B$1000+0*(Consolidado!$B$5:$B$1000=""))=7)*(Consolidado!$B$5:$B$1000<>"")*((($C$2="Todos")+(Consolidado!$I$5:$I$1000&""=$C$2&""))>0)) -> 0 | V6: =SUMPRODUCT((Consolidado!$E$5:$E$1000=$B6)*(MONTH(Consolidado!$B$5:$B$1000+0*(Consolidado!$B$5:$B$1000=""))=8)*(Consolidado!$B$5:$B$1000<>"")*((($C$2="Todos")+(Consolidado!$I$5:$I$1000&""=$C$2&""))>0)) -> 4 | W6: =SUMPRODUCT((Consolidado!$E$5:$E$1000=$B6)*(MONTH(Consolidado!$B$5:$B$1000+0*(Consolidado!$B$5:$B$1000=""))=9)*(Consolidado!$B$5:$B$1000<>"")*((($C$2="Todos")+(Consolidado!$I$5:$I$1000&""=$C$2&""))>0)) -> 0 | X6: =SUMPRODUCT((Consolidado!$E$5:$E$1000=$B6)*(MONTH(Consolidado!$B$5:$B$1000+0*(Consolidado!$B$5:$B$1000=""))=10)*(Consolidado!$B$5:$B$1000<>"")*((($C$2="Todos")+(Consolidado!$I$5:$I$1000&""=$C$2&""))>0)) -> 0 | Y6: =SUMPRODUCT((Consolidado!$E$5:$E$1000=$B6)*(MONTH(Consolidado!$B$5:$B$1000+0*(Consolidado!$B$5:$B$1000=""))=11)*(Consolidado!$B$5:$B$1000<>"")*((($C$2="Todos")+(Consolidado!$I$5:$I$1000&""=$C$2&""))>0)) -> 0 | Z6: =SUMPRODUCT((Consolidado!$E$5:$E$1000=$B6)*(MONTH(Consolidado!$B$5:$B$1000+0*(Consolidado!$B$5:$B$1000=""))=12)*(Consolidado!$B$5:$B$1000<>"")*((($C$2="Todos")+(Consolidado!$I$5:$I$1000&""=$C$2&""))>0)) -> 0
A7: 3 | B7: =Catálogos!C4 -> Plan de trabajo y capacitaciones de riesgos | C7: =Catálogos!D4 -> NRP-20 | D7: =SUMPRODUCT((Consolidado!$E$5:$E$1000=$B7)*(Consolidado!$C$5:$C$1000="Auditoría Interna")*((($C$2="Todos")+(Consolidado!$I$5:$I$1000&""=$C$2&""))>0)) -> 7 | E7: =SUMPRODUCT((Consolidado!$E$5:$E$1000=$B7)*(Consolidado!$C$5:$C$1000="Auditoría Externa")*((($C$2="Todos")+(Consolidado!$I$5:$I$1000&""=$C$2&""))>0)) -> 0 | F7: =SUMPRODUCT((Consolidado!$E$5:$E$1000=$B7)*(Consolidado!$C$5:$C$1000="SSF")*((($C$2="Todos")+(Consolidado!$I$5:$I$1000&""=$C$2&""))>0)) -> 0 | G7: =SUMPRODUCT((Consolidado!$E$5:$E$1000=$B7)*(Consolidado!$C$5:$C$1000="Comité de Supervisión")*((($C$2="Todos")+(Consolidado!$I$5:$I$1000&""=$C$2&""))>0)) -> 0 | H7: =SUMPRODUCT((Consolidado!$E$5:$E$1000=$B7)*(Consolidado!$C$5:$C$1000="Consejo de Administración")*((($C$2="Todos")+(Consolidado!$I$5:$I$1000&""=$C$2&""))>0)) -> 0 | I7: =SUMPRODUCT((Consolidado!$E$5:$E$1000=$B7)*(Consolidado!$C$5:$C$1000="Otros")*((($C$2="Todos")+(Consolidado!$I$5:$I$1000&""=$C$2&""))>0)) -> 0 | J7: =SUM(D7:I7) -> 7 | K7: =SUMPRODUCT((Consolidado!$E$5:$E$1000=$B7)*(Consolidado!$AE$5:$AE$1000)*((($C$2="Todos")+(Consolidado!$I$5:$I$1000&""=$C$2&""))>0)) -> 2 | L7: =COUNTIF(D7:I7,">0") -> 1 | M7: =IF(L7>=2,"Sí","No") -> No | N7: =IF(J7=0,"",RANK(J7,$J$5:$J$33)) -> 3 | O7: =SUMPRODUCT((Consolidado!$E$5:$E$1000=$B7)*(MONTH(Consolidado!$B$5:$B$1000+0*(Consolidado!$B$5:$B$1000=""))=1)*(Consolidado!$B$5:$B$1000<>"")*((($C$2="Todos")+(Consolidado!$I$5:$I$1000&""=$C$2&""))>0)) -> 0 | P7: =SUMPRODUCT((Consolidado!$E$5:$E$1000=$B7)*(MONTH(Consolidado!$B$5:$B$1000+0*(Consolidado!$B$5:$B$1000=""))=2)*(Consolidado!$B$5:$B$1000<>"")*((($C$2="Todos")+(Consolidado!$I$5:$I$1000&""=$C$2&""))>0)) -> 0 | Q7: =SUMPRODUCT((Consolidado!$E$5:$E$1000=$B7)*(MONTH(Consolidado!$B$5:$B$1000+0*(Consolidado!$B$5:$B$1000=""))=3)*(Consolidado!$B$5:$B$1000<>"")*((($C$2="Todos")+(Consolidado!$I$5:$I$1000&""=$C$2&""))>0)) -> 0 | R7: =SUMPRODUCT((Consolidado!$E$5:$E$1000=$B7)*(MONTH(Consolidado!$B$5:$B$1000+0*(Consolidado!$B$5:$B$1000=""))=4)*(Consolidado!$B$5:$B$1000<>"")*((($C$2="Todos")+(Consolidado!$I$5:$I$1000&""=$C$2&""))>0)) -> 0 | S7: =SUMPRODUCT((Consolidado!$E$5:$E$1000=$B7)*(MONTH(Consolidado!$B$5:$B$1000+0*(Consolidado!$B$5:$B$1000=""))=5)*(Consolidado!$B$5:$B$1000<>"")*((($C$2="Todos")+(Consolidado!$I$5:$I$1000&""=$C$2&""))>0)) -> 1 | T7: =SUMPRODUCT((Consolidado!$E$5:$E$1000=$B7)*(MONTH(Consolidado!$B$5:$B$1000+0*(Consolidado!$B$5:$B$1000=""))=6)*(Consolidado!$B$5:$B$1000<>"")*((($C$2="Todos")+(Consolidado!$I$5:$I$1000&""=$C$2&""))>0)) -> 0 | U7: =SUMPRODUCT((Consolidado!$E$5:$E$1000=$B7)*(MONTH(Consolidado!$B$5:$B$1000+0*(Consolidado!$B$5:$B$1000=""))=7)*(Consolidado!$B$5:$B$1000<>"")*((($C$2="Todos")+(Consolidado!$I$5:$I$1000&""=$C$2&""))>0)) -> 0 | V7: =SUMPRODUCT((Consolidado!$E$5:$E$1000=$B7)*(MONTH(Consolidado!$B$5:$B$1000+0*(Consolidado!$B$5:$B$1000=""))=8)*(Consolidado!$B$5:$B$1000<>"")*((($C$2="Todos")+(Consolidado!$I$5:$I$1000&""=$C$2&""))>0)) -> 6 | W7: =SUMPRODUCT((Consolidado!$E$5:$E$1000=$B7)*(MONTH(Consolidado!$B$5:$B$1000+0*(Consolidado!$B$5:$B$1000=""))=9)*(Consolidado!$B$5:$B$1000<>"")*((($C$2="Todos")+(Consolidado!$I$5:$I$1000&""=$C$2&""))>0)) -> 0 | X7: =SUMPRODUCT((Consolidado!$E$5:$E$1000=$B7)*(MONTH(Consolidado!$B$5:$B$1000+0*(Consolidado!$B$5:$B$1000=""))=10)*(Consolidado!$B$5:$B$1000<>"")*((($C$2="Todos")+(Consolidado!$I$5:$I$1000&""=$C$2&""))>0)) -> 0 | Y7: =SUMPRODUCT((Consolidado!$E$5:$E$1000=$B7)*(MONTH(Consolidado!$B$5:$B$1000+0*(Consolidado!$B$5:$B$1000=""))=11)*(Consolidado!$B$5:$B$1000<>"")*((($C$2="Todos")+(Consolidado!$I$5:$I$1000&""=$C$2&""))>0)) -> 0 | Z7: =SUMPRODUCT((Consolidado!$E$5:$E$1000=$B7)*(MONTH(Consolidado!$B$5:$B$1000+0*(Consolidado!$B$5:$B$1000=""))=12)*(Consolidado!$B$5:$B$1000<>"")*((($C$2="Todos")+(Consolidado!$I$5:$I$1000&""=$C$2&""))>0)) -> 0
A8: 4 | B8: =Catálogos!C5 -> Políticas, manuales y divulgación GIR | C8: =Catálogos!D5 -> NRP-20 | D8: =SUMPRODUCT((Consolidado!$E$5:$E$1000=$B8)*(Consolidado!$C$5:$C$1000="Auditoría Interna")*((($C$2="Todos")+(Consolidado!$I$5:$I$1000&""=$C$2&""))>0)) -> 2 | E8: =SUMPRODUCT((Consolidado!$E$5:$E$1000=$B8)*(Consolidado!$C$5:$C$1000="Auditoría Externa")*((($C$2="Todos")+(Consolidado!$I$5:$I$1000&""=$C$2&""))>0)) -> 0 | F8: =SUMPRODUCT((Consolidado!$E$5:$E$1000=$B8)*(Consolidado!$C$5:$C$1000="SSF")*((($C$2="Todos")+(Consolidado!$I$5:$I$1000&""=$C$2&""))>0)) -> 0 | G8: =SUMPRODUCT((Consolidado!$E$5:$E$1000=$B8)*(Consolidado!$C$5:$C$1000="Comité de Supervisión")*((($C$2="Todos")+(Consolidado!$I$5:$I$1000&""=$C$2&""))>0)) -> 0 | H8: =SUMPRODUCT((Consolidado!$E$5:$E$1000=$B8)*(Consolidado!$C$5:$C$1000="Consejo de Administración")*((($C$2="Todos")+(Consolidado!$I$5:$I$1000&""=$C$2&""))>0)) -> 0 | I8: =SUMPRODUCT((Consolidado!$E$5:$E$1000=$B8)*(Consolidado!$C$5:$C$1000="Otros")*((($C$2="Todos")+(Consolidado!$I$5:$I$1000&""=$C$2&""))>0)) -> 0 | J8: =SUM(D8:I8) -> 2 | K8: =SUMPRODUCT((Consolidado!$E$5:$E$1000=$B8)*(Consolidado!$AE$5:$AE$1000)*((($C$2="Todos")+(Consolidado!$I$5:$I$1000&""=$C$2&""))>0)) -> 1 | L8: =COUNTIF(D8:I8,">0") -> 1 | M8: =IF(L8>=2,"Sí","No") -> No | N8: =IF(J8=0,"",RANK(J8,$J$5:$J$33)) -> 12 | O8: =SUMPRODUCT((Consolidado!$E$5:$E$1000=$B8)*(MONTH(Consolidado!$B$5:$B$1000+0*(Consolidado!$B$5:$B$1000=""))=1)*(Consolidado!$B$5:$B$1000<>"")*((($C$2="Todos")+(Consolidado!$I$5:$I$1000&""=$C$2&""))>0)) -> 0 | P8: =SUMPRODUCT((Consolidado!$E$5:$E$1000=$B8)*(MONTH(Consolidado!$B$5:$B$1000+0*(Consolidado!$B$5:$B$1000=""))=2)*(Consolidado!$B$5:$B$1000<>"")*((($C$2="Todos")+(Consolidado!$I$5:$I$1000&""=$C$2&""))>0)) -> 0 | Q8: =SUMPRODUCT((Consolidado!$E$5:$E$1000=$B8)*(MONTH(Consolidado!$B$5:$B$1000+0*(Consolidado!$B$5:$B$1000=""))=3)*(Consolidado!$B$5:$B$1000<>"")*((($C$2="Todos")+(Consolidado!$I$5:$I$1000&""=$C$2&""))>0)) -> 0 | R8: =SUMPRODUCT((Consolidado!$E$5:$E$1000=$B8)*(MONTH(Consolidado!$B$5:$B$1000+0*(Consolidado!$B$5:$B$1000=""))=4)*(Consolidado!$B$5:$B$1000<>"")*((($C$2="Todos")+(Consolidado!$I$5:$I$1000&""=$C$2&""))>0)) -> 0 | S8: =SUMPRODUCT((Consolidado!$E$5:$E$1000=$B8)*(MONTH(Consolidado!$B$5:$B$1000+0*(Consolidado!$B$5:$B$1000=""))=5)*(Consolidado!$B$5:$B$1000<>"")*((($C$2="Todos")+(Consolidado!$I$5:$I$1000&""=$C$2&""))>0)) -> 0 | T8: =SUMPRODUCT((Consolidado!$E$5:$E$1000=$B8)*(MONTH(Consolidado!$B$5:$B$1000+0*(Consolidado!$B$5:$B$1000=""))=6)*(Consolidado!$B$5:$B$1000<>"")*((($C$2="Todos")+(Consolidado!$I$5:$I$1000&""=$C$2&""))>0)) -> 0 | U8: =SUMPRODUCT((Consolidado!$E$5:$E$1000=$B8)*(MONTH(Consolidado!$B$5:$B$1000+0*(Consolidado!$B$5:$B$1000=""))=7)*(Consolidado!$B$5:$B$1000<>"")*((($C$2="Todos")+(Consolidado!$I$5:$I$1000&""=$C$2&""))>0)) -> 0 | V8: =SUMPRODUCT((Consolidado!$E$5:$E$1000=$B8)*(MONTH(Consolidado!$B$5:$B$1000+0*(Consolidado!$B$5:$B$1000=""))=8)*(Consolidado!$B$5:$B$1000<>"")*((($C$2="Todos")+(Consolidado!$I$5:$I$1000&""=$C$2&""))>0)) -> 2 | W8: =SUMPRODUCT((Consolidado!$E$5:$E$1000=$B8)*(MONTH(Consolidado!$B$5:$B$1000+0*(Consolidado!$B$5:$B$1000=""))=9)*(Consolidado!$B$5:$B$1000<>"")*((($C$2="Todos")+(Consolidado!$I$5:$I$1000&""=$C$2&""))>0)) -> 0 | X8: =SUMPRODUCT((Consolidado!$E$5:$E$1000=$B8)*(MONTH(Consolidado!$B$5:$B$1000+0*(Consolidado!$B$5:$B$1000=""))=10)*(Consolidado!$B$5:$B$1000<>"")*((($C$2="Todos")+(Consolidado!$I$5:$I$1000&""=$C$2&""))>0)) -> 0 | Y8: =SUMPRODUCT((Consolidado!$E$5:$E$1000=$B8)*(MONTH(Consolidado!$B$5:$B$1000+0*(Consolidado!$B$5:$B$1000=""))=11)*(Consolidado!$B$5:$B$1000<>"")*((($C$2="Todos")+(Consolidado!$I$5:$I$1000&""=$C$2&""))>0)) -> 0 | Z8: =SUMPRODUCT((Consolidado!$E$5:$E$1000=$B8)*(MONTH(Consolidado!$B$5:$B$1000+0*(Consolidado!$B$5:$B$1000=""))=12)*(Consolidado!$B$5:$B$1000<>"")*((($C$2="Todos")+(Consolidado!$I$5:$I$1000&""=$C$2&""))>0)) -> 0
A9: 5 | B9: =Catálogos!C6 -> Pérdida Esperada | C9: =Catálogos!D6 -> NCB-022 | D9: =SUMPRODUCT((Consolidado!$E$5:$E$1000=$B9)*(Consolidado!$C$5:$C$1000="Auditoría Interna")*((($C$2="Todos")+(Consolidado!$I$5:$I$1000&""=$C$2&""))>0)) -> 1 | E9: =SUMPRODUCT((Consolidado!$E$5:$E$1000=$B9)*(Consolidado!$C$5:$C$1000="Auditoría Externa")*((($C$2="Todos")+(Consolidado!$I$5:$I$1000&""=$C$2&""))>0)) -> 2 | F9: =SUMPRODUCT((Consolidado!$E$5:$E$1000=$B9)*(Consolidado!$C$5:$C$1000="SSF")*((($C$2="Todos")+(Consolidado!$I$5:$I$1000&""=$C$2&""))>0)) -> 0 | G9: =SUMPRODUCT((Consolidado!$E$5:$E$1000=$B9)*(Consolidado!$C$5:$C$1000="Comité de Supervisión")*((($C$2="Todos")+(Consolidado!$I$5:$I$1000&""=$C$2&""))>0)) -> 0 | H9: =SUMPRODUCT((Consolidado!$E$5:$E$1000=$B9)*(Consolidado!$C$5:$C$1000="Consejo de Administración")*((($C$2="Todos")+(Consolidado!$I$5:$I$1000&""=$C$2&""))>0)) -> 0 | I9: =SUMPRODUCT((Consolidado!$E$5:$E$1000=$B9)*(Consolidado!$C$5:$C$1000="Otros")*((($C$2="Todos")+(Consolidado!$I$5:$I$1000&""=$C$2&""))>0)) -> 0 | J9: =SUM(D9:I9) -> 3 | K9: =SUMPRODUCT((Consolidado!$E$5:$E$1000=$B9)*(Consolidado!$AE$5:$AE$1000)*((($C$2="Todos")+(Consolidado!$I$5:$I$1000&""=$C$2&""))>0)) -> 2 | L9: =COUNTIF(D9:I9,">0") -> 2 | M9: =IF(L9>=2,"Sí","No") -> Sí | N9: =IF(J9=0,"",RANK(J9,$J$5:$J$33)) -> 8 | O9: =SUMPRODUCT((Consolidado!$E$5:$E$1000=$B9)*(MONTH(Consolidado!$B$5:$B$1000+0*(Consolidado!$B$5:$B$1000=""))=1)*(Consolidado!$B$5:$B$1000<>"")*((($C$2="Todos")+(Consolidado!$I$5:$I$1000&""=$C$2&""))>0)) -> 0 | P9: =SUMPRODUCT((Consolidado!$E$5:$E$1000=$B9)*(MONTH(Consolidado!$B$5:$B$1000+0*(Consolidado!$B$5:$B$1000=""))=2)*(Consolidado!$B$5:$B$1000<>"")*((($C$2="Todos")+(Consolidado!$I$5:$I$1000&""=$C$2&""))>0)) -> 0 | Q9: =SUMPRODUCT((Consolidado!$E$5:$E$1000=$B9)*(MONTH(Consolidado!$B$5:$B$1000+0*(Consolidado!$B$5:$B$1000=""))=3)*(Consolidado!$B$5:$B$1000<>"")*((($C$2="Todos")+(Consolidado!$I$5:$I$1000&""=$C$2&""))>0)) -> 0 | R9: =SUMPRODUCT((Consolidado!$E$5:$E$1000=$B9)*(MONTH(Consolidado!$B$5:$B$1000+0*(Consolidado!$B$5:$B$1000=""))=4)*(Consolidado!$B$5:$B$1000<>"")*((($C$2="Todos")+(Consolidado!$I$5:$I$1000&""=$C$2&""))>0)) -> 0 | S9: =SUMPRODUCT((Consolidado!$E$5:$E$1000=$B9)*(MONTH(Consolidado!$B$5:$B$1000+0*(Consolidado!$B$5:$B$1000=""))=5)*(Consolidado!$B$5:$B$1000<>"")*((($C$2="Todos")+(Consolidado!$I$5:$I$1000&""=$C$2&""))>0)) -> 1 | T9: =SUMPRODUCT((Consolidado!$E$5:$E$1000=$B9)*(MONTH(Consolidado!$B$5:$B$1000+0*(Consolidado!$B$5:$B$1000=""))=6)*(Consolidado!$B$5:$B$1000<>"")*((($C$2="Todos")+(Consolidado!$I$5:$I$1000&""=$C$2&""))>0)) -> 0 | U9: =SUMPRODUCT((Consolidado!$E$5:$E$1000=$B9)*(MONTH(Consolidado!$B$5:$B$1000+0*(Consolidado!$B$5:$B$1000=""))=7)*(Consolidado!$B$5:$B$1000<>"")*((($C$2="Todos")+(Consolidado!$I$5:$I$1000&""=$C$2&""))>0)) -> 0 | V9: =SUMPRODUCT((Consolidado!$E$5:$E$1000=$B9)*(MONTH(Consolidado!$B$5:$B$1000+0*(Consolidado!$B$5:$B$1000=""))=8)*(Consolidado!$B$5:$B$1000<>"")*((($C$2="Todos")+(Consolidado!$I$5:$I$1000&""=$C$2&""))>0)) -> 0 | W9: =SUMPRODUCT((Consolidado!$E$5:$E$1000=$B9)*(MONTH(Consolidado!$B$5:$B$1000+0*(Consolidado!$B$5:$B$1000=""))=9)*(Consolidado!$B$5:$B$1000<>"")*((($C$2="Todos")+(Consolidado!$I$5:$I$1000&""=$C$2&""))>0)) -> 0 | X9: =SUMPRODUCT((Consolidado!$E$5:$E$1000=$B9)*(MONTH(Consolidado!$B$5:$B$1000+0*(Consolidado!$B$5:$B$1000=""))=10)*(Consolidado!$B$5:$B$1000<>"")*((($C$2="Todos")+(Consolidado!$I$5:$I$1000&""=$C$2&""))>0)) -> 2 | Y9: =SUMPRODUCT((Consolidado!$E$5:$E$1000=$B9)*(MONTH(Consolidado!$B$5:$B$1000+0*(Consolidado!$B$5:$B$1000=""))=11)*(Consolidado!$B$5:$B$1000<>"")*((($C$2="Todos")+(Consolidado!$I$5:$I$1000&""=$C$2&""))>0)) -> 0 | Z9: =SUMPRODUCT((Consolidado!$E$5:$E$1000=$B9)*(MONTH(Consolidado!$B$5:$B$1000+0*(Consolidado!$B$5:$B$1000=""))=12)*(Consolidado!$B$5:$B$1000<>"")*((($C$2="Todos")+(Consolidado!$I$5:$I$1000&""=$C$2&""))>0)) -> 0
A10: 6 | B10: =Catálogos!C7 -> Clasificación de cartera, mora y reservas | C10: =Catálogos!D7 -> NCB-022 | D10: =SUMPRODUCT((Consolidado!$E$5:$E$1000=$B10)*(Consolidado!$C$5:$C$1000="Auditoría Interna")*((($C$2="Todos")+(Consolidado!$I$5:$I$1000&""=$C$2&""))>0)) -> 1 | E10: =SUMPRODUCT((Consolidado!$E$5:$E$1000=$B10)*(Consolidado!$C$5:$C$1000="Auditoría Externa")*((($C$2="Todos")+(Consolidado!$I$5:$I$1000&""=$C$2&""))>0)) -> 3 | F10: =SUMPRODUCT((Consolidado!$E$5:$E$1000=$B10)*(Consolidado!$C$5:$C$1000="SSF")*((($C$2="Todos")+(Consolidado!$I$5:$I$1000&""=$C$2&""))>0)) -> 2 | G10: =SUMPRODUCT((Consolidado!$E$5:$E$1000=$B10)*(Consolidado!$C$5:$C$1000="Comité de Supervisión")*((($C$2="Todos")+(Consolidado!$I$5:$I$1000&""=$C$2&""))>0)) -> 0 | H10: =SUMPRODUCT((Consolidado!$E$5:$E$1000=$B10)*(Consolidado!$C$5:$C$1000="Consejo de Administración")*((($C$2="Todos")+(Consolidado!$I$5:$I$1000&""=$C$2&""))>0)) -> 0 | I10: =SUMPRODUCT((Consolidado!$E$5:$E$1000=$B10)*(Consolidado!$C$5:$C$1000="Otros")*((($C$2="Todos")+(Consolidado!$I$5:$I$1000&""=$C$2&""))>0)) -> 0 | J10: =SUM(D10:I10) -> 6 | K10: =SUMPRODUCT((Consolidado!$E$5:$E$1000=$B10)*(Consolidado!$AE$5:$AE$1000)*((($C$2="Todos")+(Consolidado!$I$5:$I$1000&""=$C$2&""))>0)) -> 4 | L10: =COUNTIF(D10:I10,">0") -> 3 | M10: =IF(L10>=2,"Sí","No") -> Sí | N10: =IF(J10=0,"",RANK(J10,$J$5:$J$33)) -> 4 | O10: =SUMPRODUCT((Consolidado!$E$5:$E$1000=$B10)*(MONTH(Consolidado!$B$5:$B$1000+0*(Consolidado!$B$5:$B$1000=""))=1)*(Consolidado!$B$5:$B$1000<>"")*((($C$2="Todos")+(Consolidado!$I$5:$I$1000&""=$C$2&""))>0)) -> 1 | P10: =SUMPRODUCT((Consolidado!$E$5:$E$1000=$B10)*(MONTH(Consolidado!$B$5:$B$1000+0*(Consolidado!$B$5:$B$1000=""))=2)*(Consolidado!$B$5:$B$1000<>"")*((($C$2="Todos")+(Consolidado!$I$5:$I$1000&""=$C$2&""))>0)) -> 0 | Q10: =SUMPRODUCT((Consolidado!$E$5:$E$1000=$B10)*(MONTH(Consolidado!$B$5:$B$1000+0*(Consolidado!$B$5:$B$1000=""))=3)*(Consolidado!$B$5:$B$1000<>"")*((($C$2="Todos")+(Consolidado!$I$5:$I$1000&""=$C$2&""))>0)) -> 0 | R10: =SUMPRODUCT((Consolidado!$E$5:$E$1000=$B10)*(MONTH(Consolidado!$B$5:$B$1000+0*(Consolidado!$B$5:$B$1000=""))=4)*(Consolidado!$B$5:$B$1000<>"")*((($C$2="Todos")+(Consolidado!$I$5:$I$1000&""=$C$2&""))>0)) -> 0 | S10: =SUMPRODUCT((Consolidado!$E$5:$E$1000=$B10)*(MONTH(Consolidado!$B$5:$B$1000+0*(Consolidado!$B$5:$B$1000=""))=5)*(Consolidado!$B$5:$B$1000<>"")*((($C$2="Todos")+(Consolidado!$I$5:$I$1000&""=$C$2&""))>0)) -> 1 | T10: =SUMPRODUCT((Consolidado!$E$5:$E$1000=$B10)*(MONTH(Consolidado!$B$5:$B$1000+0*(Consolidado!$B$5:$B$1000=""))=6)*(Consolidado!$B$5:$B$1000<>"")*((($C$2="Todos")+(Consolidado!$I$5:$I$1000&""=$C$2&""))>0)) -> 0 | U10: =SUMPRODUCT((Consolidado!$E$5:$E$1000=$B10)*(MONTH(Consolidado!$B$5:$B$1000+0*(Consolidado!$B$5:$B$1000=""))=7)*(Consolidado!$B$5:$B$1000<>"")*((($C$2="Todos")+(Consolidado!$I$5:$I$1000&""=$C$2&""))>0)) -> 0 | V10: =SUMPRODUCT((Consolidado!$E$5:$E$1000=$B10)*(MONTH(Consolidado!$B$5:$B$1000+0*(Consolidado!$B$5:$B$1000=""))=8)*(Consolidado!$B$5:$B$1000<>"")*((($C$2="Todos")+(Consolidado!$I$5:$I$1000&""=$C$2&""))>0)) -> 1 | W10: =SUMPRODUCT((Consolidado!$E$5:$E$1000=$B10)*(MONTH(Consolidado!$B$5:$B$1000+0*(Consolidado!$B$5:$B$1000=""))=9)*(Consolidado!$B$5:$B$1000<>"")*((($C$2="Todos")+(Consolidado!$I$5:$I$1000&""=$C$2&""))>0)) -> 0 | X10: =SUMPRODUCT((Consolidado!$E$5:$E$1000=$B10)*(MONTH(Consolidado!$B$5:$B$1000+0*(Consolidado!$B$5:$B$1000=""))=10)*(Consolidado!$B$5:$B$1000<>"")*((($C$2="Todos")+(Consolidado!$I$5:$I$1000&""=$C$2&""))>0)) -> 3 | Y10: =SUMPRODUCT((Consolidado!$E$5:$E$1000=$B10)*(MONTH(Consolidado!$B$5:$B$1000+0*(Consolidado!$B$5:$B$1000=""))=11)*(Consolidado!$B$5:$B$1000<>"")*((($C$2="Todos")+(Consolidado!$I$5:$I$1000&""=$C$2&""))>0)) -> 0 | Z10: =SUMPRODUCT((Consolidado!$E$5:$E$1000=$B10)*(MONTH(Consolidado!$B$5:$B$1000+0*(Consolidado!$B$5:$B$1000=""))=12)*(Consolidado!$B$5:$B$1000<>"")*((($C$2="Todos")+(Consolidado!$I$5:$I$1000&""=$C$2&""))>0)) -> 0
A11: 7 | B11: =Catálogos!C8 -> Concentración crediticia | C11: =Catálogos!D8 -> NPB4-49 | D11: =SUMPRODUCT((Consolidado!$E$5:$E$1000=$B11)*(Consolidado!$C$5:$C$1000="Auditoría Interna")*((($C$2="Todos")+(Consolidado!$I$5:$I$1000&""=$C$2&""))>0)) -> 0 | E11: =SUMPRODUCT((Consolidado!$E$5:$E$1000=$B11)*(Consolidado!$C$5:$C$1000="Auditoría Externa")*((($C$2="Todos")+(Consolidado!$I$5:$I$1000&""=$C$2&""))>0)) -> 3 | F11: =SUMPRODUCT((Consolidado!$E$5:$E$1000=$B11)*(Consolidado!$C$5:$C$1000="SSF")*((($C$2="Todos")+(Consolidado!$I$5:$I$1000&""=$C$2&""))>0)) -> 0 | G11: =SUMPRODUCT((Consolidado!$E$5:$E$1000=$B11)*(Consolidado!$C$5:$C$1000="Comité de Supervisión")*((($C$2="Todos")+(Consolidado!$I$5:$I$1000&""=$C$2&""))>0)) -> 0 | H11: =SUMPRODUCT((Consolidado!$E$5:$E$1000=$B11)*(Consolidado!$C$5:$C$1000="Consejo de Administración")*((($C$2="Todos")+(Consolidado!$I$5:$I$1000&""=$C$2&""))>0)) -> 0 | I11: =SUMPRODUCT((Consolidado!$E$5:$E$1000=$B11)*(Consolidado!$C$5:$C$1000="Otros")*((($C$2="Todos")+(Consolidado!$I$5:$I$1000&""=$C$2&""))>0)) -> 0 | J11: =SUM(D11:I11) -> 3 | K11: =SUMPRODUCT((Consolidado!$E$5:$E$1000=$B11)*(Consolidado!$AE$5:$AE$1000)*((($C$2="Todos")+(Consolidado!$I$5:$I$1000&""=$C$2&""))>0)) -> 1 | L11: =COUNTIF(D11:I11,">0") -> 1 | M11: =IF(L11>=2,"Sí","No") -> No | N11: =IF(J11=0,"",RANK(J11,$J$5:$J$33)) -> 8 | O11: =SUMPRODUCT((Consolidado!$E$5:$E$1000=$B11)*(MONTH(Consolidado!$B$5:$B$1000+0*(Consolidado!$B$5:$B$1000=""))=1)*(Consolidado!$B$5:$B$1000<>"")*((($C$2="Todos")+(Consolidado!$I$5:$I$1000&""=$C$2&""))>0)) -> 0 | P11: =SUMPRODUCT((Consolidado!$E$5:$E$1000=$B11)*(MONTH(Consolidado!$B$5:$B$1000+0*(Consolidado!$B$5:$B$1000=""))=2)*(Consolidado!$B$5:$B$1000<>"")*((($C$2="Todos")+(Consolidado!$I$5:$I$1000&""=$C$2&""))>0)) -> 0 | Q11: =SUMPRODUCT((Consolidado!$E$5:$E$1000=$B11)*(MONTH(Consolidado!$B$5:$B$1000+0*(Consolidado!$B$5:$B$1000=""))=3)*(Consolidado!$B$5:$B$1000<>"")*((($C$2="Todos")+(Consolidado!$I$5:$I$1000&""=$C$2&""))>0)) -> 0 | R11: =SUMPRODUCT((Consolidado!$E$5:$E$1000=$B11)*(MONTH(Consolidado!$B$5:$B$1000+0*(Consolidado!$B$5:$B$1000=""))=4)*(Consolidado!$B$5:$B$1000<>"")*((($C$2="Todos")+(Consolidado!$I$5:$I$1000&""=$C$2&""))>0)) -> 0 | S11: =SUMPRODUCT((Consolidado!$E$5:$E$1000=$B11)*(MONTH(Consolidado!$B$5:$B$1000+0*(Consolidado!$B$5:$B$1000=""))=5)*(Consolidado!$B$5:$B$1000<>"")*((($C$2="Todos")+(Consolidado!$I$5:$I$1000&""=$C$2&""))>0)) -> 0 | T11: =SUMPRODUCT((Consolidado!$E$5:$E$1000=$B11)*(MONTH(Consolidado!$B$5:$B$1000+0*(Consolidado!$B$5:$B$1000=""))=6)*(Consolidado!$B$5:$B$1000<>"")*((($C$2="Todos")+(Consolidado!$I$5:$I$1000&""=$C$2&""))>0)) -> 0 | U11: =SUMPRODUCT((Consolidado!$E$5:$E$1000=$B11)*(MONTH(Consolidado!$B$5:$B$1000+0*(Consolidado!$B$5:$B$1000=""))=7)*(Consolidado!$B$5:$B$1000<>"")*((($C$2="Todos")+(Consolidado!$I$5:$I$1000&""=$C$2&""))>0)) -> 0 | V11: =SUMPRODUCT((Consolidado!$E$5:$E$1000=$B11)*(MONTH(Consolidado!$B$5:$B$1000+0*(Consolidado!$B$5:$B$1000=""))=8)*(Consolidado!$B$5:$B$1000<>"")*((($C$2="Todos")+(Consolidado!$I$5:$I$1000&""=$C$2&""))>0)) -> 0 | W11: =SUMPRODUCT((Consolidado!$E$5:$E$1000=$B11)*(MONTH(Consolidado!$B$5:$B$1000+0*(Consolidado!$B$5:$B$1000=""))=9)*(Consolidado!$B$5:$B$1000<>"")*((($C$2="Todos")+(Consolidado!$I$5:$I$1000&""=$C$2&""))>0)) -> 0 | X11: =SUMPRODUCT((Consolidado!$E$5:$E$1000=$B11)*(MONTH(Consolidado!$B$5:$B$1000+0*(Consolidado!$B$5:$B$1000=""))=10)*(Consolidado!$B$5:$B$1000<>"")*((($C$2="Todos")+(Consolidado!$I$5:$I$1000&""=$C$2&""))>0)) -> 3 | Y11: =SUMPRODUCT((Consolidado!$E$5:$E$1000=$B11)*(MONTH(Consolidado!$B$5:$B$1000+0*(Consolidado!$B$5:$B$1000=""))=11)*(Consolidado!$B$5:$B$1000<>"")*((($C$2="Todos")+(Consolidado!$I$5:$I$1000&""=$C$2&""))>0)) -> 0 | Z11: =SUMPRODUCT((Consolidado!$E$5:$E$1000=$B11)*(MONTH(Consolidado!$B$5:$B$1000+0*(Consolidado!$B$5:$B$1000=""))=12)*(Consolidado!$B$5:$B$1000<>"")*((($C$2="Todos")+(Consolidado!$I$5:$I$1000&""=$C$2&""))>0)) -> 0
A12: 8 | B12: =Catálogos!C9 -> Créditos a personas relacionadas | C12: =Catálogos!D9 -> Por validar | D12: =SUMPRODUCT((Consolidado!$E$5:$E$1000=$B12)*(Consolidado!$C$5:$C$1000="Auditoría Interna")*((($C$2="Todos")+(Consolidado!$I$5:$I$1000&""=$C$2&""))>0)) -> 0 | E12: =SUMPRODUCT((Consolidado!$E$5:$E$1000=$B12)*(Consolidado!$C$5:$C$1000="Auditoría Externa")*((($C$2="Todos")+(Consolidado!$I$5:$I$1000&""=$C$2&""))>0)) -> 1 | F12: =SUMPRODUCT((Consolidado!$E$5:$E$1000=$B12)*(Consolidado!$C$5:$C$1000="SSF")*((($C$2="Todos")+(Consolidado!$I$5:$I$1000&""=$C$2&""))>0)) -> 0 | G12: =SUMPRODUCT((Consolidado!$E$5:$E$1000=$B12)*(Consolidado!$C$5:$C$1000="Comité de Supervisión")*((($C$2="Todos")+(Consolidado!$I$5:$I$1000&""=$C$2&""))>0)) -> 0 | H12: =SUMPRODUCT((Consolidado!$E$5:$E$1000=$B12)*(Consolidado!$C$5:$C$1000="Consejo de Administración")*((($C$2="Todos")+(Consolidado!$I$5:$I$1000&""=$C$2&""))>0)) -> 0 | I12: =SUMPRODUCT((Consolidado!$E$5:$E$1000=$B12)*(Consolidado!$C$5:$C$1000="Otros")*((($C$2="Todos")+(Consolidado!$I$5:$I$1000&""=$C$2&""))>0)) -> 0 | J12: =SUM(D12:I12) -> 1 | K12: =SUMPRODUCT((Consolidado!$E$5:$E$1000=$B12)*(Consolidado!$AE$5:$AE$1000)*((($C$2="Todos")+(Consolidado!$I$5:$I$1000&""=$C$2&""))>0)) -> 1 | L12: =COUNTIF(D12:I12,">0") -> 1 | M12: =IF(L12>=2,"Sí","No") -> No | N12: =IF(J12=0,"",RANK(J12,$J$5:$J$33)) -> 17 | O12: =SUMPRODUCT((Consolidado!$E$5:$E$1000=$B12)*(MONTH(Consolidado!$B$5:$B$1000+0*(Consolidado!$B$5:$B$1000=""))=1)*(Consolidado!$B$5:$B$1000<>"")*((($C$2="Todos")+(Consolidado!$I$5:$I$1000&""=$C$2&""))>0)) -> 0 | P12: =SUMPRODUCT((Consolidado!$E$5:$E$1000=$B12)*(MONTH(Consolidado!$B$5:$B$1000+0*(Consolidado!$B$5:$B$1000=""))=2)*(Consolidado!$B$5:$B$1000<>"")*((($C$2="Todos")+(Consolidado!$I$5:$I$1000&""=$C$2&""))>0)) -> 0 | Q12: =SUMPRODUCT((Consolidado!$E$5:$E$1000=$B12)*(MONTH(Consolidado!$B$5:$B$1000+0*(Consolidado!$B$5:$B$1000=""))=3)*(Consolidado!$B$5:$B$1000<>"")*((($C$2="Todos")+(Consolidado!$I$5:$I$1000&""=$C$2&""))>0)) -> 0 | R12: =SUMPRODUCT((Consolidado!$E$5:$E$1000=$B12)*(MONTH(Consolidado!$B$5:$B$1000+0*(Consolidado!$B$5:$B$1000=""))=4)*(Consolidado!$B$5:$B$1000<>"")*((($C$2="Todos")+(Consolidado!$I$5:$I$1000&""=$C$2&""))>0)) -> 0 | S12: =SUMPRODUCT((Consolidado!$E$5:$E$1000=$B12)*(MONTH(Consolidado!$B$5:$B$1000+0*(Consolidado!$B$5:$B$1000=""))=5)*(Consolidado!$B$5:$B$1000<>"")*((($C$2="Todos")+(Consolidado!$I$5:$I$1000&""=$C$2&""))>0)) -> 0 | T12: =SUMPRODUCT((Consolidado!$E$5:$E$1000=$B12)*(MONTH(Consolidado!$B$5:$B$1000+0*(Consolidado!$B$5:$B$1000=""))=6)*(Consolidado!$B$5:$B$1000<>"")*((($C$2="Todos")+(Consolidado!$I$5:$I$1000&""=$C$2&""))>0)) -> 0 | U12: =SUMPRODUCT((Consolidado!$E$5:$E$1000=$B12)*(MONTH(Consolidado!$B$5:$B$1000+0*(Consolidado!$B$5:$B$1000=""))=7)*(Consolidado!$B$5:$B$1000<>"")*((($C$2="Todos")+(Consolidado!$I$5:$I$1000&""=$C$2&""))>0)) -> 0 | V12: =SUMPRODUCT((Consolidado!$E$5:$E$1000=$B12)*(MONTH(Consolidado!$B$5:$B$1000+0*(Consolidado!$B$5:$B$1000=""))=8)*(Consolidado!$B$5:$B$1000<>"")*((($C$2="Todos")+(Consolidado!$I$5:$I$1000&""=$C$2&""))>0)) -> 0 | W12: =SUMPRODUCT((Consolidado!$E$5:$E$1000=$B12)*(MONTH(Consolidado!$B$5:$B$1000+0*(Consolidado!$B$5:$B$1000=""))=9)*(Consolidado!$B$5:$B$1000<>"")*((($C$2="Todos")+(Consolidado!$I$5:$I$1000&""=$C$2&""))>0)) -> 0 | X12: =SUMPRODUCT((Consolidado!$E$5:$E$1000=$B12)*(MONTH(Consolidado!$B$5:$B$1000+0*(Consolidado!$B$5:$B$1000=""))=10)*(Consolidado!$B$5:$B$1000<>"")*((($C$2="Todos")+(Consolidado!$I$5:$I$1000&""=$C$2&""))>0)) -> 1 | Y12: =SUMPRODUCT((Consolidado!$E$5:$E$1000=$B12)*(MONTH(Consolidado!$B$5:$B$1000+0*(Consolidado!$B$5:$B$1000=""))=11)*(Consolidado!$B$5:$B$1000<>"")*((($C$2="Todos")+(Consolidado!$I$5:$I$1000&""=$C$2&""))>0)) -> 0 | Z12: =SUMPRODUCT((Consolidado!$E$5:$E$1000=$B12)*(MONTH(Consolidado!$B$5:$B$1000+0*(Consolidado!$B$5:$B$1000=""))=12)*(Consolidado!$B$5:$B$1000<>"")*((($C$2="Todos")+(Consolidado!$I$5:$I$1000&""=$C$2&""))>0)) -> 0
A13: 9 | B13: =Catálogos!C10 -> Valúos y garantías | C13: =Catálogos!D10 -> NRP-25 | D13: =SUMPRODUCT((Consolidado!$E$5:$E$1000=$B13)*(Consolidado!$C$5:$C$1000="Auditoría Interna")*((($C$2="Todos")+(Consolidado!$I$5:$I$1000&""=$C$2&""))>0)) -> 1 | E13: =SUMPRODUCT((Consolidado!$E$5:$E$1000=$B13)*(Consolidado!$C$5:$C$1000="Auditoría Externa")*((($C$2="Todos")+(Consolidado!$I$5:$I$1000&""=$C$2&""))>0)) -> 0 | F13: =SUMPRODUCT((Consolidado!$E$5:$E$1000=$B13)*(Consolidado!$C$5:$C$1000="SSF")*((($C$2="Todos")+(Consolidado!$I$5:$I$1000&""=$C$2&""))>0)) -> 1 | G13: =SUMPRODUCT((Consolidado!$E$5:$E$1000=$B13)*(Consolidado!$C$5:$C$1000="Comité de Supervisión")*((($C$2="Todos")+(Consolidado!$I$5:$I$1000&""=$C$2&""))>0)) -> 0 | H13: =SUMPRODUCT((Consolidado!$E$5:$E$1000=$B13)*(Consolidado!$C$5:$C$1000="Consejo de Administración")*((($C$2="Todos")+(Consolidado!$I$5:$I$1000&""=$C$2&""))>0)) -> 0 | I13: =SUMPRODUCT((Consolidado!$E$5:$E$1000=$B13)*(Consolidado!$C$5:$C$1000="Otros")*((($C$2="Todos")+(Consolidado!$I$5:$I$1000&""=$C$2&""))>0)) -> 0 | J13: =SUM(D13:I13) -> 2 | K13: =SUMPRODUCT((Consolidado!$E$5:$E$1000=$B13)*(Consolidado!$AE$5:$AE$1000)*((($C$2="Todos")+(Consolidado!$I$5:$I$1000&""=$C$2&""))>0)) -> 2 | L13: =COUNTIF(D13:I13,">0") -> 2 | M13: =IF(L13>=2,"Sí","No") -> Sí | N13: =IF(J13=0,"",RANK(J13,$J$5:$J$33)) -> 12 | O13: =SUMPRODUCT((Consolidado!$E$5:$E$1000=$B13)*(MONTH(Consolidado!$B$5:$B$1000+0*(Consolidado!$B$5:$B$1000=""))=1)*(Consolidado!$B$5:$B$1000<>"")*((($C$2="Todos")+(Consolidado!$I$5:$I$1000&""=$C$2&""))>0)) -> 0 | P13: =SUMPRODUCT((Consolidado!$E$5:$E$1000=$B13)*(MONTH(Consolidado!$B$5:$B$1000+0*(Consolidado!$B$5:$B$1000=""))=2)*(Consolidado!$B$5:$B$1000<>"")*((($C$2="Todos")+(Consolidado!$I$5:$I$1000&""=$C$2&""))>0)) -> 0 | Q13: =SUMPRODUCT((Consolidado!$E$5:$E$1000=$B13)*(MONTH(Consolidado!$B$5:$B$1000+0*(Consolidado!$B$5:$B$1000=""))=3)*(Consolidado!$B$5:$B$1000<>"")*((($C$2="Todos")+(Consolidado!$I$5:$I$1000&""=$C$2&""))>0)) -> 0 | R13: =SUMPRODUCT((Consolidado!$E$5:$E$1000=$B13)*(MONTH(Consolidado!$B$5:$B$1000+0*(Consolidado!$B$5:$B$1000=""))=4)*(Consolidado!$B$5:$B$1000<>"")*((($C$2="Todos")+(Consolidado!$I$5:$I$1000&""=$C$2&""))>0)) -> 1 | S13: =SUMPRODUCT((Consolidado!$E$5:$E$1000=$B13)*(MONTH(Consolidado!$B$5:$B$1000+0*(Consolidado!$B$5:$B$1000=""))=5)*(Consolidado!$B$5:$B$1000<>"")*((($C$2="Todos")+(Consolidado!$I$5:$I$1000&""=$C$2&""))>0)) -> 1 | T13: =SUMPRODUCT((Consolidado!$E$5:$E$1000=$B13)*(MONTH(Consolidado!$B$5:$B$1000+0*(Consolidado!$B$5:$B$1000=""))=6)*(Consolidado!$B$5:$B$1000<>"")*((($C$2="Todos")+(Consolidado!$I$5:$I$1000&""=$C$2&""))>0)) -> 0 | U13: =SUMPRODUCT((Consolidado!$E$5:$E$1000=$B13)*(MONTH(Consolidado!$B$5:$B$1000+0*(Consolidado!$B$5:$B$1000=""))=7)*(Consolidado!$B$5:$B$1000<>"")*((($C$2="Todos")+(Consolidado!$I$5:$I$1000&""=$C$2&""))>0)) -> 0 | V13: =SUMPRODUCT((Consolidado!$E$5:$E$1000=$B13)*(MONTH(Consolidado!$B$5:$B$1000+0*(Consolidado!$B$5:$B$1000=""))=8)*(Consolidado!$B$5:$B$1000<>"")*((($C$2="Todos")+(Consolidado!$I$5:$I$1000&""=$C$2&""))>0)) -> 0 | W13: =SUMPRODUCT((Consolidado!$E$5:$E$1000=$B13)*(MONTH(Consolidado!$B$5:$B$1000+0*(Consolidado!$B$5:$B$1000=""))=9)*(Consolidado!$B$5:$B$1000<>"")*((($C$2="Todos")+(Consolidado!$I$5:$I$1000&""=$C$2&""))>0)) -> 0 | X13: =SUMPRODUCT((Consolidado!$E$5:$E$1000=$B13)*(MONTH(Consolidado!$B$5:$B$1000+0*(Consolidado!$B$5:$B$1000=""))=10)*(Consolidado!$B$5:$B$1000<>"")*((($C$2="Todos")+(Consolidado!$I$5:$I$1000&""=$C$2&""))>0)) -> 0 | Y13: =SUMPRODUCT((Consolidado!$E$5:$E$1000=$B13)*(MONTH(Consolidado!$B$5:$B$1000+0*(Consolidado!$B$5:$B$1000=""))=11)*(Consolidado!$B$5:$B$1000<>"")*((($C$2="Todos")+(Consolidado!$I$5:$I$1000&""=$C$2&""))>0)) -> 0 | Z13: =SUMPRODUCT((Consolidado!$E$5:$E$1000=$B13)*(MONTH(Consolidado!$B$5:$B$1000+0*(Consolidado!$B$5:$B$1000=""))=12)*(Consolidado!$B$5:$B$1000<>"")*((($C$2="Todos")+(Consolidado!$I$5:$I$1000&""=$C$2&""))>0)) -> 0
A14: 10 | B14: =Catálogos!C11 -> Escenarios de estrés de crédito | C14: =Catálogos!D11 -> NPB4-49 | D14: =SUMPRODUCT((Consolidado!$E$5:$E$1000=$B14)*(Consolidado!$C$5:$C$1000="Auditoría Interna")*((($C$2="Todos")+(Consolidado!$I$5:$I$1000&""=$C$2&""))>0)) -> 1 | E14: =SUMPRODUCT((Consolidado!$E$5:$E$1000=$B14)*(Consolidado!$C$5:$C$1000="Auditoría Externa")*((($C$2="Todos")+(Consolidado!$I$5:$I$1000&""=$C$2&""))>0)) -> 0 | F14: =SUMPRODUCT((Consolidado!$E$5:$E$1000=$B14)*(Consolidado!$C$5:$C$1000="SSF")*((($C$2="Todos")+(Consolidado!$I$5:$I$1000&""=$C$2&""))>0)) -> 0 | G14: =SUMPRODUCT((Consolidado!$E$5:$E$1000=$B14)*(Consolidado!$C$5:$C$1000="Comité de Supervisión")*((($C$2="Todos")+(Consolidado!$I$5:$I$1000&""=$C$2&""))>0)) -> 0 | H14: =SUMPRODUCT((Consolidado!$E$5:$E$1000=$B14)*(Consolidado!$C$5:$C$1000="Consejo de Administración")*((($C$2="Todos")+(Consolidado!$I$5:$I$1000&""=$C$2&""))>0)) -> 0 | I14: =SUMPRODUCT((Consolidado!$E$5:$E$1000=$B14)*(Consolidado!$C$5:$C$1000="Otros")*((($C$2="Todos")+(Consolidado!$I$5:$I$1000&""=$C$2&""))>0)) -> 0 | J14: =SUM(D14:I14) -> 1 | K14: =SUMPRODUCT((Consolidado!$E$5:$E$1000=$B14)*(Consolidado!$AE$5:$AE$1000)*((($C$2="Todos")+(Consolidado!$I$5:$I$1000&""=$C$2&""))>0)) -> 1 | L14: =COUNTIF(D14:I14,">0") -> 1 | M14: =IF(L14>=2,"Sí","No") -> No | N14: =IF(J14=0,"",RANK(J14,$J$5:$J$33)) -> 17 | O14: =SUMPRODUCT((Consolidado!$E$5:$E$1000=$B14)*(MONTH(Consolidado!$B$5:$B$1000+0*(Consolidado!$B$5:$B$1000=""))=1)*(Consolidado!$B$5:$B$1000<>"")*((($C$2="Todos")+(Consolidado!$I$5:$I$1000&""=$C$2&""))>0)) -> 0 | P14: =SUMPRODUCT((Consolidado!$E$5:$E$1000=$B14)*(MONTH(Consolidado!$B$5:$B$1000+0*(Consolidado!$B$5:$B$1000=""))=2)*(Consolidado!$B$5:$B$1000<>"")*((($C$2="Todos")+(Consolidado!$I$5:$I$1000&""=$C$2&""))>0)) -> 0 | Q14: =SUMPRODUCT((Consolidado!$E$5:$E$1000=$B14)*(MONTH(Consolidado!$B$5:$B$1000+0*(Consolidado!$B$5:$B$1000=""))=3)*(Consolidado!$B$5:$B$1000<>"")*((($C$2="Todos")+(Consolidado!$I$5:$I$1000&""=$C$2&""))>0)) -> 0 | R14: =SUMPRODUCT((Consolidado!$E$5:$E$1000=$B14)*(MONTH(Consolidado!$B$5:$B$1000+0*(Consolidado!$B$5:$B$1000=""))=4)*(Consolidado!$B$5:$B$1000<>"")*((($C$2="Todos")+(Consolidado!$I$5:$I$1000&""=$C$2&""))>0)) -> 0 | S14: =SUMPRODUCT((Consolidado!$E$5:$E$1000=$B14)*(MONTH(Consolidado!$B$5:$B$1000+0*(Consolidado!$B$5:$B$1000=""))=5)*(Consolidado!$B$5:$B$1000<>"")*((($C$2="Todos")+(Consolidado!$I$5:$I$1000&""=$C$2&""))>0)) -> 1 | T14: =SUMPRODUCT((Consolidado!$E$5:$E$1000=$B14)*(MONTH(Consolidado!$B$5:$B$1000+0*(Consolidado!$B$5:$B$1000=""))=6)*(Consolidado!$B$5:$B$1000<>"")*((($C$2="Todos")+(Consolidado!$I$5:$I$1000&""=$C$2&""))>0)) -> 0 | U14: =SUMPRODUCT((Consolidado!$E$5:$E$1000=$B14)*(MONTH(Consolidado!$B$5:$B$1000+0*(Consolidado!$B$5:$B$1000=""))=7)*(Consolidado!$B$5:$B$1000<>"")*((($C$2="Todos")+(Consolidado!$I$5:$I$1000&""=$C$2&""))>0)) -> 0 | V14: =SUMPRODUCT((Consolidado!$E$5:$E$1000=$B14)*(MONTH(Consolidado!$B$5:$B$1000+0*(Consolidado!$B$5:$B$1000=""))=8)*(Consolidado!$B$5:$B$1000<>"")*((($C$2="Todos")+(Consolidado!$I$5:$I$1000&""=$C$2&""))>0)) -> 0 | W14: =SUMPRODUCT((Consolidado!$E$5:$E$1000=$B14)*(MONTH(Consolidado!$B$5:$B$1000+0*(Consolidado!$B$5:$B$1000=""))=9)*(Consolidado!$B$5:$B$1000<>"")*((($C$2="Todos")+(Consolidado!$I$5:$I$1000&""=$C$2&""))>0)) -> 0 | X14: =SUMPRODUCT((Consolidado!$E$5:$E$1000=$B14)*(MONTH(Consolidado!$B$5:$B$1000+0*(Consolidado!$B$5:$B$1000=""))=10)*(Consolidado!$B$5:$B$1000<>"")*((($C$2="Todos")+(Consolidado!$I$5:$I$1000&""=$C$2&""))>0)) -> 0 | Y14: =SUMPRODUCT((Consolidado!$E$5:$E$1000=$B14)*(MONTH(Consolidado!$B$5:$B$1000+0*(Consolidado!$B$5:$B$1000=""))=11)*(Consolidado!$B$5:$B$1000<>"")*((($C$2="Todos")+(Consolidado!$I$5:$I$1000&""=$C$2&""))>0)) -> 0 | Z14: =SUMPRODUCT((Consolidado!$E$5:$E$1000=$B14)*(MONTH(Consolidado!$B$5:$B$1000+0*(Consolidado!$B$5:$B$1000=""))=12)*(Consolidado!$B$5:$B$1000<>"")*((($C$2="Todos")+(Consolidado!$I$5:$I$1000&""=$C$2&""))>0)) -> 0
A15: 11 | B15: =Catálogos!C12 -> Matriz de migración / bases de cartera | C15: =Catálogos!D12 -> NCB-022 | D15: =SUMPRODUCT((Consolidado!$E$5:$E$1000=$B15)*(Consolidado!$C$5:$C$1000="Auditoría Interna")*((($C$2="Todos")+(Consolidado!$I$5:$I$1000&""=$C$2&""))>0)) -> 1 | E15: =SUMPRODUCT((Consolidado!$E$5:$E$1000=$B15)*(Consolidado!$C$5:$C$1000="Auditoría Externa")*((($C$2="Todos")+(Consolidado!$I$5:$I$1000&""=$C$2&""))>0)) -> 0 | F15: =SUMPRODUCT((Consolidado!$E$5:$E$1000=$B15)*(Consolidado!$C$5:$C$1000="SSF")*((($C$2="Todos")+(Consolidado!$I$5:$I$1000&""=$C$2&""))>0)) -> 0 | G15: =SUMPRODUCT((Consolidado!$E$5:$E$1000=$B15)*(Consolidado!$C$5:$C$1000="Comité de Supervisión")*((($C$2="Todos")+(Consolidado!$I$5:$I$1000&""=$C$2&""))>0)) -> 0 | H15: =SUMPRODUCT((Consolidado!$E$5:$E$1000=$B15)*(Consolidado!$C$5:$C$1000="Consejo de Administración")*((($C$2="Todos")+(Consolidado!$I$5:$I$1000&""=$C$2&""))>0)) -> 0 | I15: =SUMPRODUCT((Consolidado!$E$5:$E$1000=$B15)*(Consolidado!$C$5:$C$1000="Otros")*((($C$2="Todos")+(Consolidado!$I$5:$I$1000&""=$C$2&""))>0)) -> 0 | J15: =SUM(D15:I15) -> 1 | K15: =SUMPRODUCT((Consolidado!$E$5:$E$1000=$B15)*(Consolidado!$AE$5:$AE$1000)*((($C$2="Todos")+(Consolidado!$I$5:$I$1000&""=$C$2&""))>0)) -> 1 | L15: =COUNTIF(D15:I15,">0") -> 1 | M15: =IF(L15>=2,"Sí","No") -> No | N15: =IF(J15=0,"",RANK(J15,$J$5:$J$33)) -> 17 | O15: =SUMPRODUCT((Consolidado!$E$5:$E$1000=$B15)*(MONTH(Consolidado!$B$5:$B$1000+0*(Consolidado!$B$5:$B$1000=""))=1)*(Consolidado!$B$5:$B$1000<>"")*((($C$2="Todos")+(Consolidado!$I$5:$I$1000&""=$C$2&""))>0)) -> 0 | P15: =SUMPRODUCT((Consolidado!$E$5:$E$1000=$B15)*(MONTH(Consolidado!$B$5:$B$1000+0*(Consolidado!$B$5:$B$1000=""))=2)*(Consolidado!$B$5:$B$1000<>"")*((($C$2="Todos")+(Consolidado!$I$5:$I$1000&""=$C$2&""))>0)) -> 0 | Q15: =SUMPRODUCT((Consolidado!$E$5:$E$1000=$B15)*(MONTH(Consolidado!$B$5:$B$1000+0*(Consolidado!$B$5:$B$1000=""))=3)*(Consolidado!$B$5:$B$1000<>"")*((($C$2="Todos")+(Consolidado!$I$5:$I$1000&""=$C$2&""))>0)) -> 0 | R15: =SUMPRODUCT((Consolidado!$E$5:$E$1000=$B15)*(MONTH(Consolidado!$B$5:$B$1000+0*(Consolidado!$B$5:$B$1000=""))=4)*(Consolidado!$B$5:$B$1000<>"")*((($C$2="Todos")+(Consolidado!$I$5:$I$1000&""=$C$2&""))>0)) -> 0 | S15: =SUMPRODUCT((Consolidado!$E$5:$E$1000=$B15)*(MONTH(Consolidado!$B$5:$B$1000+0*(Consolidado!$B$5:$B$1000=""))=5)*(Consolidado!$B$5:$B$1000<>"")*((($C$2="Todos")+(Consolidado!$I$5:$I$1000&""=$C$2&""))>0)) -> 1 | T15: =SUMPRODUCT((Consolidado!$E$5:$E$1000=$B15)*(MONTH(Consolidado!$B$5:$B$1000+0*(Consolidado!$B$5:$B$1000=""))=6)*(Consolidado!$B$5:$B$1000<>"")*((($C$2="Todos")+(Consolidado!$I$5:$I$1000&""=$C$2&""))>0)) -> 0 | U15: =SUMPRODUCT((Consolidado!$E$5:$E$1000=$B15)*(MONTH(Consolidado!$B$5:$B$1000+0*(Consolidado!$B$5:$B$1000=""))=7)*(Consolidado!$B$5:$B$1000<>"")*((($C$2="Todos")+(Consolidado!$I$5:$I$1000&""=$C$2&""))>0)) -> 0 | V15: =SUMPRODUCT((Consolidado!$E$5:$E$1000=$B15)*(MONTH(Consolidado!$B$5:$B$1000+0*(Consolidado!$B$5:$B$1000=""))=8)*(Consolidado!$B$5:$B$1000<>"")*((($C$2="Todos")+(Consolidado!$I$5:$I$1000&""=$C$2&""))>0)) -> 0 | W15: =SUMPRODUCT((Consolidado!$E$5:$E$1000=$B15)*(MONTH(Consolidado!$B$5:$B$1000+0*(Consolidado!$B$5:$B$1000=""))=9)*(Consolidado!$B$5:$B$1000<>"")*((($C$2="Todos")+(Consolidado!$I$5:$I$1000&""=$C$2&""))>0)) -> 0 | X15: =SUMPRODUCT((Consolidado!$E$5:$E$1000=$B15)*(MONTH(Consolidado!$B$5:$B$1000+0*(Consolidado!$B$5:$B$1000=""))=10)*(Consolidado!$B$5:$B$1000<>"")*((($C$2="Todos")+(Consolidado!$I$5:$I$1000&""=$C$2&""))>0)) -> 0 | Y15: =SUMPRODUCT((Consolidado!$E$5:$E$1000=$B15)*(MONTH(Consolidado!$B$5:$B$1000+0*(Consolidado!$B$5:$B$1000=""))=11)*(Consolidado!$B$5:$B$1000<>"")*((($C$2="Todos")+(Consolidado!$I$5:$I$1000&""=$C$2&""))>0)) -> 0 | Z15: =SUMPRODUCT((Consolidado!$E$5:$E$1000=$B15)*(MONTH(Consolidado!$B$5:$B$1000+0*(Consolidado!$B$5:$B$1000=""))=12)*(Consolidado!$B$5:$B$1000<>"")*((($C$2="Todos")+(Consolidado!$I$5:$I$1000&""=$C$2&""))>0)) -> 0
A16: 12 | B16: =Catálogos!C13 -> Remisiones a SSF / central de riesgos | C16: =Catálogos!D13 -> NCB-022 | D16: =SUMPRODUCT((Consolidado!$E$5:$E$1000=$B16)*(Consolidado!$C$5:$C$1000="Auditoría Interna")*((($C$2="Todos")+(Consolidado!$I$5:$I$1000&""=$C$2&""))>0)) -> 2 | E16: =SUMPRODUCT((Consolidado!$E$5:$E$1000=$B16)*(Consolidado!$C$5:$C$1000="Auditoría Externa")*((($C$2="Todos")+(Consolidado!$I$5:$I$1000&""=$C$2&""))>0)) -> 1 | F16: =SUMPRODUCT((Consolidado!$E$5:$E$1000=$B16)*(Consolidado!$C$5:$C$1000="SSF")*((($C$2="Todos")+(Consolidado!$I$5:$I$1000&""=$C$2&""))>0)) -> 0 | G16: =SUMPRODUCT((Consolidado!$E$5:$E$1000=$B16)*(Consolidado!$C$5:$C$1000="Comité de Supervisión")*((($C$2="Todos")+(Consolidado!$I$5:$I$1000&""=$C$2&""))>0)) -> 0 | H16: =SUMPRODUCT((Consolidado!$E$5:$E$1000=$B16)*(Consolidado!$C$5:$C$1000="Consejo de Administración")*((($C$2="Todos")+(Consolidado!$I$5:$I$1000&""=$C$2&""))>0)) -> 0 | I16: =SUMPRODUCT((Consolidado!$E$5:$E$1000=$B16)*(Consolidado!$C$5:$C$1000="Otros")*((($C$2="Todos")+(Consolidado!$I$5:$I$1000&""=$C$2&""))>0)) -> 0 | J16: =SUM(D16:I16) -> 3 | K16: =SUMPRODUCT((Consolidado!$E$5:$E$1000=$B16)*(Consolidado!$AE$5:$AE$1000)*((($C$2="Todos")+(Consolidado!$I$5:$I$1000&""=$C$2&""))>0)) -> 2 | L16: =COUNTIF(D16:I16,">0") -> 2 | M16: =IF(L16>=2,"Sí","No") -> Sí | N16: =IF(J16=0,"",RANK(J16,$J$5:$J$33)) -> 8 | O16: =SUMPRODUCT((Consolidado!$E$5:$E$1000=$B16)*(MONTH(Consolidado!$B$5:$B$1000+0*(Consolidado!$B$5:$B$1000=""))=1)*(Consolidado!$B$5:$B$1000<>"")*((($C$2="Todos")+(Consolidado!$I$5:$I$1000&""=$C$2&""))>0)) -> 0 | P16: =SUMPRODUCT((Consolidado!$E$5:$E$1000=$B16)*(MONTH(Consolidado!$B$5:$B$1000+0*(Consolidado!$B$5:$B$1000=""))=2)*(Consolidado!$B$5:$B$1000<>"")*((($C$2="Todos")+(Consolidado!$I$5:$I$1000&""=$C$2&""))>0)) -> 0 | Q16: =SUMPRODUCT((Consolidado!$E$5:$E$1000=$B16)*(MONTH(Consolidado!$B$5:$B$1000+0*(Consolidado!$B$5:$B$1000=""))=3)*(Consolidado!$B$5:$B$1000<>"")*((($C$2="Todos")+(Consolidado!$I$5:$I$1000&""=$C$2&""))>0)) -> 0 | R16: =SUMPRODUCT((Consolidado!$E$5:$E$1000=$B16)*(MONTH(Consolidado!$B$5:$B$1000+0*(Consolidado!$B$5:$B$1000=""))=4)*(Consolidado!$B$5:$B$1000<>"")*((($C$2="Todos")+(Consolidado!$I$5:$I$1000&""=$C$2&""))>0)) -> 0 | S16: =SUMPRODUCT((Consolidado!$E$5:$E$1000=$B16)*(MONTH(Consolidado!$B$5:$B$1000+0*(Consolidado!$B$5:$B$1000=""))=5)*(Consolidado!$B$5:$B$1000<>"")*((($C$2="Todos")+(Consolidado!$I$5:$I$1000&""=$C$2&""))>0)) -> 2 | T16: =SUMPRODUCT((Consolidado!$E$5:$E$1000=$B16)*(MONTH(Consolidado!$B$5:$B$1000+0*(Consolidado!$B$5:$B$1000=""))=6)*(Consolidado!$B$5:$B$1000<>"")*((($C$2="Todos")+(Consolidado!$I$5:$I$1000&""=$C$2&""))>0)) -> 0 | U16: =SUMPRODUCT((Consolidado!$E$5:$E$1000=$B16)*(MONTH(Consolidado!$B$5:$B$1000+0*(Consolidado!$B$5:$B$1000=""))=7)*(Consolidado!$B$5:$B$1000<>"")*((($C$2="Todos")+(Consolidado!$I$5:$I$1000&""=$C$2&""))>0)) -> 0 | V16: =SUMPRODUCT((Consolidado!$E$5:$E$1000=$B16)*(MONTH(Consolidado!$B$5:$B$1000+0*(Consolidado!$B$5:$B$1000=""))=8)*(Consolidado!$B$5:$B$1000<>"")*((($C$2="Todos")+(Consolidado!$I$5:$I$1000&""=$C$2&""))>0)) -> 0 | W16: =SUMPRODUCT((Consolidado!$E$5:$E$1000=$B16)*(MONTH(Consolidado!$B$5:$B$1000+0*(Consolidado!$B$5:$B$1000=""))=9)*(Consolidado!$B$5:$B$1000<>"")*((($C$2="Todos")+(Consolidado!$I$5:$I$1000&""=$C$2&""))>0)) -> 0 | X16: =SUMPRODUCT((Consolidado!$E$5:$E$1000=$B16)*(MONTH(Consolidado!$B$5:$B$1000+0*(Consolidado!$B$5:$B$1000=""))=10)*(Consolidado!$B$5:$B$1000<>"")*((($C$2="Todos")+(Consolidado!$I$5:$I$1000&""=$C$2&""))>0)) -> 1 | Y16: =SUMPRODUCT((Consolidado!$E$5:$E$1000=$B16)*(MONTH(Consolidado!$B$5:$B$1000+0*(Consolidado!$B$5:$B$1000=""))=11)*(Consolidado!$B$5:$B$1000<>"")*((($C$2="Todos")+(Consolidado!$I$5:$I$1000&""=$C$2&""))>0)) -> 0 | Z16: =SUMPRODUCT((Consolidado!$E$5:$E$1000=$B16)*(MONTH(Consolidado!$B$5:$B$1000+0*(Consolidado!$B$5:$B$1000=""))=12)*(Consolidado!$B$5:$B$1000<>"")*((($C$2="Todos")+(Consolidado!$I$5:$I$1000&""=$C$2&""))>0)) -> 0
... A33: 29 | B33: =Catálogos!C30 -> Declaraciones juradas | C33: =Catálogos!D30 -> Ley Bancos Coop. Art. 15 | D33: =SUMPRODUCT((Consolidado!$E$5:$E$1000=$B33)*(Consolidado!$C$5:$C$1000="Auditoría Interna")*((($C$2="Todos")+(Consolidado!$I$5:$I$1000&""=$C$2&""))>0)) -> 0 | E33: =SUMPRODUCT((Consolidado!$E$5:$E$1000=$B33)*(Consolidado!$C$5:$C$1000="Auditoría Externa")*((($C$2="Todos")+(Consolidado!$I$5:$I$1000&""=$C$2&""))>0)) -> 0 | F33: =SUMPRODUCT((Consolidado!$E$5:$E$1000=$B33)*(Consolidado!$C$5:$C$1000="SSF")*((($C$2="Todos")+(Consolidado!$I$5:$I$1000&""=$C$2&""))>0)) -> 1 | G33: =SUMPRODUCT((Consolidado!$E$5:$E$1000=$B33)*(Consolidado!$C$5:$C$1000="Comité de Supervisión")*((($C$2="Todos")+(Consolidado!$I$5:$I$1000&""=$C$2&""))>0)) -> 0 | H33: =SUMPRODUCT((Consolidado!$E$5:$E$1000=$B33)*(Consolidado!$C$5:$C$1000="Consejo de Administración")*((($C$2="Todos")+(Consolidado!$I$5:$I$1000&""=$C$2&""))>0)) -> 0 | I33: =SUMPRODUCT((Consolidado!$E$5:$E$1000=$B33)*(Consolidado!$C$5:$C$1000="Otros")*((($C$2="Todos")+(Consolidado!$I$5:$I$1000&""=$C$2&""))>0)) -> 0 | J33: =SUM(D33:I33) -> 1 | K33: =SUMPRODUCT((Consolidado!$E$5:$E$1000=$B33)*(Consolidado!$AE$5:$AE$1000)*((($C$2="Todos")+(Consolidado!$I$5:$I$1000&""=$C$2&""))>0)) -> 1 | L33: =COUNTIF(D33:I33,">0") -> 1 | M33: =IF(L33>=2,"Sí","No") -> No | N33: =IF(J33=0,"",RANK(J33,$J$5:$J$33)) -> 17 | O33: =SUMPRODUCT((Consolidado!$E$5:$E$1000=$B33)*(MONTH(Consolidado!$B$5:$B$1000+0*(Consolidado!$B$5:$B$1000=""))=1)*(Consolidado!$B$5:$B$1000<>"")*((($C$2="Todos")+(Consolidado!$I$5:$I$1000&""=$C$2&""))>0)) -> 0 | P33: =SUMPRODUCT((Consolidado!$E$5:$E$1000=$B33)*(MONTH(Consolidado!$B$5:$B$1000+0*(Consolidado!$B$5:$B$1000=""))=2)*(Consolidado!$B$5:$B$1000<>"")*((($C$2="Todos")+(Consolidado!$I$5:$I$1000&""=$C$2&""))>0)) -> 0 | Q33: =SUMPRODUCT((Consolidado!$E$5:$E$1000=$B33)*(MONTH(Consolidado!$B$5:$B$1000+0*(Consolidado!$B$5:$B$1000=""))=3)*(Consolidado!$B$5:$B$1000<>"")*((($C$2="Todos")+(Consolidado!$I$5:$I$1000&""=$C$2&""))>0)) -> 0 | R33: =SUMPRODUCT((Consolidado!$E$5:$E$1000=$B33)*(MONTH(Consolidado!$B$5:$B$1000+0*(Consolidado!$B$5:$B$1000=""))=4)*(Consolidado!$B$5:$B$1000<>"")*((($C$2="Todos")+(Consolidado!$I$5:$I$1000&""=$C$2&""))>0)) -> 0 | S33: =SUMPRODUCT((Consolidado!$E$5:$E$1000=$B33)*(MONTH(Consolidado!$B$5:$B$1000+0*(Consolidado!$B$5:$B$1000=""))=5)*(Consolidado!$B$5:$B$1000<>"")*((($C$2="Todos")+(Consolidado!$I$5:$I$1000&""=$C$2&""))>0)) -> 0 | T33: =SUMPRODUCT((Consolidado!$E$5:$E$1000=$B33)*(MONTH(Consolidado!$B$5:$B$1000+0*(Consolidado!$B$5:$B$1000=""))=6)*(Consolidado!$B$5:$B$1000<>"")*((($C$2="Todos")+(Consolidado!$I$5:$I$1000&""=$C$2&""))>0)) -> 0 | U33: =SUMPRODUCT((Consolidado!$E$5:$E$1000=$B33)*(MONTH(Consolidado!$B$5:$B$1000+0*(Consolidado!$B$5:$B$1000=""))=7)*(Consolidado!$B$5:$B$1000<>"")*((($C$2="Todos")+(Consolidado!$I$5:$I$1000&""=$C$2&""))>0)) -> 1 | V33: =SUMPRODUCT((Consolidado!$E$5:$E$1000=$B33)*(MONTH(Consolidado!$B$5:$B$1000+0*(Consolidado!$B$5:$B$1000=""))=8)*(Consolidado!$B$5:$B$1000<>"")*((($C$2="Todos")+(Consolidado!$I$5:$I$1000&""=$C$2&""))>0)) -> 0 | W33: =SUMPRODUCT((Consolidado!$E$5:$E$1000=$B33)*(MONTH(Consolidado!$B$5:$B$1000+0*(Consolidado!$B$5:$B$1000=""))=9)*(Consolidado!$B$5:$B$1000<>"")*((($C$2="Todos")+(Consolidado!$I$5:$I$1000&""=$C$2&""))>0)) -> 0 | X33: =SUMPRODUCT((Consolidado!$E$5:$E$1000=$B33)*(MONTH(Consolidado!$B$5:$B$1000+0*(Consolidado!$B$5:$B$1000=""))=10)*(Consolidado!$B$5:$B$1000<>"")*((($C$2="Todos")+(Consolidado!$I$5:$I$1000&""=$C$2&""))>0)) -> 0 | Y33: =SUMPRODUCT((Consolidado!$E$5:$E$1000=$B33)*(MONTH(Consolidado!$B$5:$B$1000+0*(Consolidado!$B$5:$B$1000=""))=11)*(Consolidado!$B$5:$B$1000<>"")*((($C$2="Todos")+(Consolidado!$I$5:$I$1000&""=$C$2&""))>0)) -> 0 | Z33: =SUMPRODUCT((Consolidado!$E$5:$E$1000=$B33)*(MONTH(Consolidado!$B$5:$B$1000+0*(Consolidado!$B$5:$B$1000=""))=12)*(Consolidado!$B$5:$B$1000<>"")*((($C$2="Todos")+(Consolidado!$I$5:$I$1000&""=$C$2&""))>0)) -> 0
B34: TOTAL | D34: =SUM(D5:D33) -> 52 | E34: =SUM(E5:E33) -> 15 | F34: =SUM(F5:F33) -> 23 | G34: =SUM(G5:G33) -> 0 | H34: =SUM(H5:H33) -> 0 | I34: =SUM(I5:I33) -> 0 | J34: =SUM(J5:J33) -> 90 | K34: =SUM(K5:K33) -> 51 | L34: =SUM(L5:L33) -> 39 | M34: =COUNTIF(M5:M33,"Sí")&" repetidos" -> 8 repetidos | O34: =SUM(O5:O33) -> 2 | P34: =SUM(P5:P33) -> 3 | Q34: =SUM(Q5:Q33) -> 1 | R34: =SUM(R5:R33) -> 4 | S34: =SUM(S5:S33) -> 12 | T34: =SUM(T5:T33) -> 1 | U34: =SUM(U5:U33) -> 2 | V34: =SUM(V5:V33) -> 26 | ... Z34: =SUM(Z5:Z33) -> 0
A36: Notas:
A37: • Los conteos salen de la hoja Consolidado; cada requerimiento se agrupa en un solo "Tema" (columna E). Si un requerimiento cubre dos temas, se asignó al principal.
A38: • "Total Veces" cuenta ítems pedidos; "Auditorías / visitas distintas" cuenta cuántas auditorías o visitas diferentes tocaron el tema (p. ej., Continuidad: 18 ítems de una sola auditoría interna).
A39: • Columnas Ene–Dic: mes de recepción del requerimiento, del año elegido en C2 (con "Todos" se suman todos los años).
A40: • SSF: se omitieron 6 filas repetidas en la hoja "Resumen visita presencialSSF" (filas 21, 23, 25, 26, 27 y 30 de esa hoja).
A41: • Auditoría Interna 3 (NRP-24) no trae fecha; se usó 12/10/2026, la fecha del título de esa matriz. La visita SSF de seguimiento NRP-32 no trae fecha y no cuenta en los meses.
A42: • La norma por tema es una referencia; las marcadas "Por validar" deben confirmarse. Puede editarlas en la hoja Catálogos.

Sheet Cruce
A1: ¿QUIÉN MÁS ME PIDIÓ LO MISMO? – CRUCE DE UN REQUERIMIENTO
A2: Escriba en la celda amarilla el N° del requerimiento (columna A de la hoja Consolidado). Abajo verá todos los que piden el mismo tema, de qué origen y en qué mes.
B3: N° en Consolidado | C3: 53 | K3: Veces que me piden este tema
B4: Origen | C4: =IFERROR(INDEX(Consolidado!$C$5:$C$1000,MATCH($C$3,Consolidado!$A$5:$A$1000,0)),"") -> SSF | K4: Interna | M4: =IF($C$5="",0,COUNTIFS(Consolidado!$E$5:$E$1000,$C$5,Consolidado!$C$5:$C$1000,"Auditoría Interna")) -> 6
B5: Tema | C5: =IFERROR(INDEX(Consolidado!$E$5:$E$1000,MATCH($C$3,Consolidado!$A$5:$A$1000,0)),"") -> Gobierno Corporativo | K5: Externa | M5: =IF($C$5="",0,COUNTIFS(Consolidado!$E$5:$E$1000,$C$5,Consolidado!$C$5:$C$1000,"Auditoría Externa")) -> 0
B6: Fecha recibida | C6: =IFERROR(INDEX(Consolidado!$B$5:$B$1000,MATCH($C$3,Consolidado!$A$5:$A$1000,0)),"") -> 46255 | K6: SSF | M6: =IF($C$5="",0,COUNTIFS(Consolidado!$E$5:$E$1000,$C$5,Consolidado!$C$5:$C$1000,"SSF")) -> 2
B7: Norma | C7: =IFERROR(INDEX(Consolidado!$D$5:$D$1000,MATCH($C$3,Consolidado!$A$5:$A$1000,0)),"") -> NRP-17 | K7: Comité Sup. | M7: =IF($C$5="",0,COUNTIFS(Consolidado!$E$5:$E$1000,$C$5,Consolidado!$C$5:$C$1000,"Comité de Supervisión")) -> 0
B8: Requerimiento | C8: =IFERROR(INDEX(Consolidado!$F$5:$F$1000,MATCH($C$3,Consolidado!$A$5:$A$1000,0)),"") -> Visita de supervisión ampliada para evaluar el Gobierno Corporativo. SABAO-BCS-BC-18432 | K8: Consejo | M8: =IF($C$5="",0,COUNTIFS(Consolidado!$E$5:$E$1000,$C$5,Consolidado!$C$5:$C$1000,"Consejo de Administración")) -> 0
K9: Otros | M9: =IF($C$5="",0,COUNTIFS(Consolidado!$E$5:$E$1000,$C$5,Consolidado!$C$5:$C$1000,"Otros")) -> 0
K10: Total | M10: =SUM(M4:M9) -> 8
K11: Otros orígenes en el MISMO mes | M11: =IFERROR(INDEX(Consolidado!$X$5:$X$1000,MATCH($C$3,Consolidado!$A$5:$A$1000,0)),"") -> 6
A13: # | B13: N° | C13: Origen | D13: Fecha | E13: Mes | F13: Año | G13: Relación con el seleccionado | H13: Requerimiento | I13: Responsable | J13: Estado
A14: =IF(B14="","",1) -> 1 | B14: =IFERROR(INDEX(Consolidado!$A$5:$A$1000,MATCH(1,Consolidado!$AC$5:$AC$1000,0)),"") -> 8 | C14: =IFERROR(INDEX(Consolidado!$C$5:$C$1000,MATCH(1,Consolidado!$AC$5:$AC$1000,0))&"","") -> SSF | D14: =IFERROR(INDEX(Consolidado!$B$5:$B$1000,MATCH(1,Consolidado!$AC$5:$AC$1000,0)),"") -> 45796 | E14: =IF(OR(D14="",D14=0),"",CHOOSE(MONTH(D14),"Ene","Feb","Mar","Abr","May","Jun","Jul","Ago","Sep","Oct","Nov","Dic")) -> May | F14: =IF(OR(D14="",D14=0),"",YEAR(D14)) -> 2025 | G14: =IF(B14="","",IF(B14=$C$3,"◄ SELECCIONADO",IF(OR(D14="",D14=0,$C$6="",$C$6=0),"Sin fecha",IF(AND(YEAR(D14)=YEAR($C$6),MONTH(D14)=MONTH($C$6)),"MISMO MES",ABS((YEAR(D14)-YEAR($C$6))*12+MONTH(D14)-MONTH($C$6))&" meses "&IF(D14<$C$6,"antes","después"))))) -> 15 meses antes | H14: =IFERROR(INDEX(Consolidado!$F$5:$F$1000,MATCH(1,Consolidado!$AC$5:$AC$1000,0))&"","") -> Visita de supervision ampliada para evaluar el Gobierno Corporativo SABAO- BCS- BC-9337 | I14: =IFERROR(INDEX(Consolidado!$G$5:$G$1000,MATCH(1,Consolidado!$AC$5:$AC$1000,0))&"","") | J14: =IFERROR(INDEX(Consolidado!$H$5:$H$1000,MATCH(1,Consolidado!$AC$5:$AC$1000,0))&"","")
A15: =IF(B15="","",2) -> 2 | B15: =IFERROR(INDEX(Consolidado!$A$5:$A$1000,MATCH(2,Consolidado!$AC$5:$AC$1000,0)),"") -> 39 | C15: =IFERROR(INDEX(Consolidado!$C$5:$C$1000,MATCH(2,Consolidado!$AC$5:$AC$1000,0))&"","") -> Auditoría Interna | D15: =IFERROR(INDEX(Consolidado!$B$5:$B$1000,MATCH(2,Consolidado!$AC$5:$AC$1000,0)),"") -> 46249 | E15: =IF(OR(D15="",D15=0),"",CHOOSE(MONTH(D15),"Ene","Feb","Mar","Abr","May","Jun","Jul","Ago","Sep","Oct","Nov","Dic")) -> Ago | F15: =IF(OR(D15="",D15=0),"",YEAR(D15)) -> 2026 | G15: =IF(B15="","",IF(B15=$C$3,"◄ SELECCIONADO",IF(OR(D15="",D15=0,$C$6="",$C$6=0),"Sin fecha",IF(AND(YEAR(D15)=YEAR($C$6),MONTH(D15)=MONTH($C$6)),"MISMO MES",ABS((YEAR(D15)-YEAR($C$6))*12+MONTH(D15)-MONTH($C$6))&" meses "&IF(D15<$C$6,"antes","después"))))) -> MISMO MES | H15: =IFERROR(INDEX(Consolidado!$F$5:$F$1000,MATCH(2,Consolidado!$AC$5:$AC$1000,0))&"","") -> Informe anual de gobierno corporativo remisión y recepción de la SSF (ejecución de enero a marzo 2026) | I15: =IFERROR(INDEX(Consolidado!$G$5:$G$1000,MATCH(2,Consolidado!$AC$5:$AC$1000,0))&"","") -> Silvita | J15: =IFERROR(INDEX(Consolidado!$H$5:$H$1000,MATCH(2,Consolidado!$AC$5:$AC$1000,0))&"","")
A16: =IF(B16="","",3) -> 3 | B16: =IFERROR(INDEX(Consolidado!$A$5:$A$1000,MATCH(3,Consolidado!$AC$5:$AC$1000,0)),"") -> 40 | C16: =IFERROR(INDEX(Consolidado!$C$5:$C$1000,MATCH(3,Consolidado!$AC$5:$AC$1000,0))&"","") -> Auditoría Interna | D16: =IFERROR(INDEX(Consolidado!$B$5:$B$1000,MATCH(3,Consolidado!$AC$5:$AC$1000,0)),"") -> 46249 | E16: =IF(OR(D16="",D16=0),"",CHOOSE(MONTH(D16),"Ene","Feb","Mar","Abr","May","Jun","Jul","Ago","Sep","Oct","Nov","Dic")) -> Ago | F16: =IF(OR(D16="",D16=0),"",YEAR(D16)) -> 2026 | G16: =IF(B16="","",IF(B16=$C$3,"◄ SELECCIONADO",IF(OR(D16="",D16=0,$C$6="",$C$6=0),"Sin fecha",IF(AND(YEAR(D16)=YEAR($C$6),MONTH(D16)=MONTH($C$6)),"MISMO MES",ABS((YEAR(D16)-YEAR($C$6))*12+MONTH(D16)-MONTH($C$6))&" meses "&IF(D16<$C$6,"antes","después"))))) -> MISMO MES | H16: =IFERROR(INDEX(Consolidado!$F$5:$F$1000,MATCH(3,Consolidado!$AC$5:$AC$1000,0))&"","") -> Remisión de anexo 2 información de gobierno corporativo desagregada por sexo los primeros 30 días posteriores a cada semestre (Ejecución en Julio 2025, Enero y julio 2026) | I16: =IFERROR(INDEX(Consolidado!$G$5:$G$1000,MATCH(3,Consolidado!$AC$5:$AC$1000,0))&"","") | J16: =IFERROR(INDEX(Consolidado!$H$5:$H$1000,MATCH(3,Consolidado!$AC$5:$AC$1000,0))&"","")
A17: =IF(B17="","",4) -> 4 | B17: =IFERROR(INDEX(Consolidado!$A$5:$A$1000,MATCH(4,Consolidado!$AC$5:$AC$1000,0)),"") -> 41 | C17: =IFERROR(INDEX(Consolidado!$C$5:$C$1000,MATCH(4,Consolidado!$AC$5:$AC$1000,0))&"","") -> Auditoría Interna | D17: =IFERROR(INDEX(Consolidado!$B$5:$B$1000,MATCH(4,Consolidado!$AC$5:$AC$1000,0)),"") -> 46249 | E17: =IF(OR(D17="",D17=0),"",CHOOSE(MONTH(D17),"Ene","Feb","Mar","Abr","May","Jun","Jul","Ago","Sep","Oct","Nov","Dic")) -> Ago | F17: =IF(OR(D17="",D17=0),"",YEAR(D17)) -> 2026 | G17: =IF(B17="","",IF(B17=$C$3,"◄ SELECCIONADO",IF(OR(D17="",D17=0,$C$6="",$C$6=0),"Sin fecha",IF(AND(YEAR(D17)=YEAR($C$6),MONTH(D17)=MONTH($C$6)),"MISMO MES",ABS((YEAR(D17)-YEAR($C$6))*12+MONTH(D17)-MONTH($C$6))&" meses "&IF(D17<$C$6,"antes","después"))))) -> MISMO MES | H17: =IFERROR(INDEX(Consolidado!$F$5:$F$1000,MATCH(4,Consolidado!$AC$5:$AC$1000,0))&"","") -> Publicación en el sitio web de la información citada en el artículo 29 de la NRP-17 (ejecución de enero, marzo y julio 2026) | I17: =IFERROR(INDEX(Consolidado!$G$5:$G$1000,MATCH(4,Consolidado!$AC$5:$AC$1000,0))&"","") -> Silvita | J17: =IFERROR(INDEX(Consolidado!$H$5:$H$1000,MATCH(4,Consolidado!$AC$5:$AC$1000,0))&"","")
A18: =IF(B18="","",5) -> 5 | B18: =IFERROR(INDEX(Consolidado!$A$5:$A$1000,MATCH(5,Consolidado!$AC$5:$AC$1000,0)),"") -> 42 | C18: =IFERROR(INDEX(Consolidado!$C$5:$C$1000,MATCH(5,Consolidado!$AC$5:$AC$1000,0))&"","") -> Auditoría Interna | D18: =IFERROR(INDEX(Consolidado!$B$5:$B$1000,MATCH(5,Consolidado!$AC$5:$AC$1000,0)),"") -> 46249 | E18: =IF(OR(D18="",D18=0),"",CHOOSE(MONTH(D18),"Ene","Feb","Mar","Abr","May","Jun","Jul","Ago","Sep","Oct","Nov","Dic")) -> Ago | F18: =IF(OR(D18="",D18=0),"",YEAR(D18)) -> 2026 | G18: =IF(B18="","",IF(B18=$C$3,"◄ SELECCIONADO",IF(OR(D18="",D18=0,$C$6="",$C$6=0),"Sin fecha",IF(AND(YEAR(D18)=YEAR($C$6),MONTH(D18)=MONTH($C$6)),"MISMO MES",ABS((YEAR(D18)-YEAR($C$6))*12+MONTH(D18)-MONTH($C$6))&" meses "&IF(D18<$C$6,"antes","después"))))) -> MISMO MES | H18: =IFERROR(INDEX(Consolidado!$F$5:$F$1000,MATCH(5,Consolidado!$AC$5:$AC$1000,0))&"","") -> Creación, aprobación y publicación de Perfil Aspirante a Directores Del Consejo de Administración (ejecución de Agosto y septiembre 2025) | I18: =IFERROR(INDEX(Consolidado!$G$5:$G$1000,MATCH(5,Consolidado!$AC$5:$AC$1000,0))&"","") -> Silvita | J18: =IFERROR(INDEX(Consolidado!$H$5:$H$1000,MATCH(5,Consolidado!$AC$5:$AC$1000,0))&"","")
A19: =IF(B19="","",6) -> 6 | B19: =IFERROR(INDEX(Consolidado!$A$5:$A$1000,MATCH(6,Consolidado!$AC$5:$AC$1000,0)),"") -> 43 | C19: =IFERROR(INDEX(Consolidado!$C$5:$C$1000,MATCH(6,Consolidado!$AC$5:$AC$1000,0))&"","") -> Auditoría Interna | D19: =IFERROR(INDEX(Consolidado!$B$5:$B$1000,MATCH(6,Consolidado!$AC$5:$AC$1000,0)),"") -> 46249 | E19: =IF(OR(D19="",D19=0),"",CHOOSE(MONTH(D19),"Ene","Feb","Mar","Abr","May","Jun","Jul","Ago","Sep","Oct","Nov","Dic")) -> Ago | F19: =IF(OR(D19="",D19=0),"",YEAR(D19)) -> 2026 | G19: =IF(B19="","",IF(B19=$C$3,"◄ SELECCIONADO",IF(OR(D19="",D19=0,$C$6="",$C$6=0),"Sin fecha",IF(AND(YEAR(D19)=YEAR($C$6),MONTH(D19)=MONTH($C$6)),"MISMO MES",ABS((YEAR(D19)-YEAR($C$6))*12+MONTH(D19)-MONTH($C$6))&" meses "&IF(D19<$C$6,"antes","después"))))) -> MISMO MES | H19: =IFERROR(INDEX(Consolidado!$F$5:$F$1000,MATCH(6,Consolidado!$AC$5:$AC$1000,0))&"","") -> Revisión con Comisión de Acreditación para revisar Curriculum de Aspirantes a Directores del Consejo de Administración (ejecución de Diciembre 2025, enero y febrero 2026) | I19: =IFERROR(INDEX(Consolidado!$G$5:$G$1000,MATCH(6,Consolidado!$AC$5:$AC$1000,0))&"","") -> Silvita | J19: =IFERROR(INDEX(Consolidado!$H$5:$H$1000,MATCH(6,Consolidado!$AC$5:$AC$1000,0))&"","")
A20: =IF(B20="","",7) -> 7 | B20: =IFERROR(INDEX(Consolidado!$A$5:$A$1000,MATCH(7,Consolidado!$AC$5:$AC$1000,0)),"") -> 51 | C20: =IFERROR(INDEX(Consolidado!$C$5:$C$1000,MATCH(7,Consolidado!$AC$5:$AC$1000,0))&"","") -> Auditoría Interna | D20: =IFERROR(INDEX(Consolidado!$B$5:$B$1000,MATCH(7,Consolidado!$AC$5:$AC$1000,0)),"") -> 46249 | E20: =IF(OR(D20="",D20=0),"",CHOOSE(MONTH(D20),"Ene","Feb","Mar","Abr","May","Jun","Jul","Ago","Sep","Oct","Nov","Dic")) -> Ago | F20: =IF(OR(D20="",D20=0),"",YEAR(D20)) -> 2026 | G20: =IF(B20="","",IF(B20=$C$3,"◄ SELECCIONADO",IF(OR(D20="",D20=0,$C$6="",$C$6=0),"Sin fecha",IF(AND(YEAR(D20)=YEAR($C$6),MONTH(D20)=MONTH($C$6)),"MISMO MES",ABS((YEAR(D20)-YEAR($C$6))*12+MONTH(D20)-MONTH($C$6))&" meses "&IF(D20<$C$6,"antes","después"))))) -> MISMO MES | H20: =IFERROR(INDEX(Consolidado!$F$5:$F$1000,MATCH(7,Consolidado!$AC$5:$AC$1000,0))&"","") -> Expedientes de directivos, Consejo de Administración, Junta de Vigilancia y comités. | I20: =IFERROR(INDEX(Consolidado!$G$5:$G$1000,MATCH(7,Consolidado!$AC$5:$AC$1000,0))&"","") -> Sara | J20: =IFERROR(INDEX(Consolidado!$H$5:$H$1000,MATCH(7,Consolidado!$AC$5:$AC$1000,0))&"","")
A21: =IF(B21="","",8) -> 8 | B21: =IFERROR(INDEX(Consolidado!$A$5:$A$1000,MATCH(8,Consolidado!$AC$5:$AC$1000,0)),"") -> 53 | C21: =IFERROR(INDEX(Consolidado!$C$5:$C$1000,MATCH(8,Consolidado!$AC$5:$AC$1000,0))&"","") -> SSF | D21: =IFERROR(INDEX(Consolidado!$B$5:$B$1000,MATCH(8,Consolidado!$AC$5:$AC$1000,0)),"") -> 46255 | E21: =IF(OR(D21="",D21=0),"",CHOOSE(MONTH(D21),"Ene","Feb","Mar","Abr","May","Jun","Jul","Ago","Sep","Oct","Nov","Dic")) -> Ago | F21: =IF(OR(D21="",D21=0),"",YEAR(D21)) -> 2026 | G21: =IF(B21="","",IF(B21=$C$3,"◄ SELECCIONADO",IF(OR(D21="",D21=0,$C$6="",$C$6=0),"Sin fecha",IF(AND(YEAR(D21)=YEAR($C$6),MONTH(D21)=MONTH($C$6)),"MISMO MES",ABS((YEAR(D21)-YEAR($C$6))*12+MONTH(D21)-MONTH($C$6))&" meses "&IF(D21<$C$6,"antes","después"))))) -> ◄ SELECCIONADO | H21: =IFERROR(INDEX(Consolidado!$F$5:$F$1000,MATCH(8,Consolidado!$AC$5:$AC$1000,0))&"","") -> Visita de supervisión ampliada para evaluar el Gobierno Corporativo. SABAO-BCS-BC-18432 | I21: =IFERROR(INDEX(Consolidado!$G$5:$G$1000,MATCH(8,Consolidado!$AC$5:$AC$1000,0))&"","") | J21: =IFERROR(INDEX(Consolidado!$H$5:$H$1000,MATCH(8,Consolidado!$AC$5:$AC$1000,0))&"","")
A22: =IF(B22="","",9) | B22: =IFERROR(INDEX(Consolidado!$A$5:$A$1000,MATCH(9,Consolidado!$AC$5:$AC$1000,0)),"") | C22: =IFERROR(INDEX(Consolidado!$C$5:$C$1000,MATCH(9,Consolidado!$AC$5:$AC$1000,0))&"","") | D22: =IFERROR(INDEX(Consolidado!$B$5:$B$1000,MATCH(9,Consolidado!$AC$5:$AC$1000,0)),"") | E22: =IF(OR(D22="",D22=0),"",CHOOSE(MONTH(D22),"Ene","Feb","Mar","Abr","May","Jun","Jul","Ago","Sep","Oct","Nov","Dic")) | F22: =IF(OR(D22="",D22=0),"",YEAR(D22)) | G22: =IF(B22="","",IF(B22=$C$3,"◄ SELECCIONADO",IF(OR(D22="",D22=0,$C$6="",$C$6=0),"Sin fecha",IF(AND(YEAR(D22)=YEAR($C$6),MONTH(D22)=MONTH($C$6)),"MISMO MES",ABS((YEAR(D22)-YEAR($C$6))*12+MONTH(D22)-MONTH($C$6))&" meses "&IF(D22<$C$6,"antes","después"))))) | H22: =IFERROR(INDEX(Consolidado!$F$5:$F$1000,MATCH(9,Consolidado!$AC$5:$AC$1000,0))&"","") | I22: =IFERROR(INDEX(Consolidado!$G$5:$G$1000,MATCH(9,Consolidado!$AC$5:$AC$1000,0))&"","") | J22: =IFERROR(INDEX(Consolidado!$H$5:$H$1000,MATCH(9,Consolidado!$AC$5:$AC$1000,0))&"","")
A23: =IF(B23="","",10) | B23: =IFERROR(INDEX(Consolidado!$A$5:$A$1000,MATCH(10,Consolidado!$AC$5:$AC$1000,0)),"") | C23: =IFERROR(INDEX(Consolidado!$C$5:$C$1000,MATCH(10,Consolidado!$AC$5:$AC$1000,0))&"","") | D23: =IFERROR(INDEX(Consolidado!$B$5:$B$1000,MATCH(10,Consolidado!$AC$5:$AC$1000,0)),"") | E23: =IF(OR(D23="",D23=0),"",CHOOSE(MONTH(D23),"Ene","Feb","Mar","Abr","May","Jun","Jul","Ago","Sep","Oct","Nov","Dic")) | F23: =IF(OR(D23="",D23=0),"",YEAR(D23)) | G23: =IF(B23="","",IF(B23=$C$3,"◄ SELECCIONADO",IF(OR(D23="",D23=0,$C$6="",$C$6=0),"Sin fecha",IF(AND(YEAR(D23)=YEAR($C$6),MONTH(D23)=MONTH($C$6)),"MISMO MES",ABS((YEAR(D23)-YEAR($C$6))*12+MONTH(D23)-MONTH($C$6))&" meses "&IF(D23<$C$6,"antes","después"))))) | H23: =IFERROR(INDEX(Consolidado!$F$5:$F$1000,MATCH(10,Consolidado!$AC$5:$AC$1000,0))&"","") | I23: =IFERROR(INDEX(Consolidado!$G$5:$G$1000,MATCH(10,Consolidado!$AC$5:$AC$1000,0))&"","") | J23: =IFERROR(INDEX(Consolidado!$H$5:$H$1000,MATCH(10,Consolidado!$AC$5:$AC$1000,0))&"","")
A24: =IF(B24="","",11) | B24: =IFERROR(INDEX(Consolidado!$A$5:$A$1000,MATCH(11,Consolidado!$AC$5:$AC$1000,0)),"") | C24: =IFERROR(INDEX(Consolidado!$C$5:$C$1000,MATCH(11,Consolidado!$AC$5:$AC$1000,0))&"","") | D24: =IFERROR(INDEX(Consolidado!$B$5:$B$1000,MATCH(11,Consolidado!$AC$5:$AC$1000,0)),"") | E24: =IF(OR(D24="",D24=0),"",CHOOSE(MONTH(D24),"Ene","Feb","Mar","Abr","May","Jun","Jul","Ago","Sep","Oct","Nov","Dic")) | F24: =IF(OR(D24="",D24=0),"",YEAR(D24)) | G24: =IF(B24="","",IF(B24=$C$3,"◄ SELECCIONADO",IF(OR(D24="",D24=0,$C$6="",$C$6=0),"Sin fecha",IF(AND(YEAR(D24)=YEAR($C$6),MONTH(D24)=MONTH($C$6)),"MISMO MES",ABS((YEAR(D24)-YEAR($C$6))*12+MONTH(D24)-MONTH($C$6))&" meses "&IF(D24<$C$6,"antes","después"))))) | H24: =IFERROR(INDEX(Consolidado!$F$5:$F$1000,MATCH(11,Consolidado!$AC$5:$AC$1000,0))&"","") | I24: =IFERROR(INDEX(Consolidado!$G$5:$G$1000,MATCH(11,Consolidado!$AC$5:$AC$1000,0))&"","") | J24: =IFERROR(INDEX(Consolidado!$H$5:$H$1000,MATCH(11,Consolidado!$AC$5:$AC$1000,0))&"","")
A25: =IF(B25="","",12) | B25: =IFERROR(INDEX(Consolidado!$A$5:$A$1000,MATCH(12,Consolidado!$AC$5:$AC$1000,0)),"") | C25: =IFERROR(INDEX(Consolidado!$C$5:$C$1000,MATCH(12,Consolidado!$AC$5:$AC$1000,0))&"","") | D25: =IFERROR(INDEX(Consolidado!$B$5:$B$1000,MATCH(12,Consolidado!$AC$5:$AC$1000,0)),"") | E25: =IF(OR(D25="",D25=0),"",CHOOSE(MONTH(D25),"Ene","Feb","Mar","Abr","May","Jun","Jul","Ago","Sep","Oct","Nov","Dic")) | F25: =IF(OR(D25="",D25=0),"",YEAR(D25)) | G25: =IF(B25="","",IF(B25=$C$3,"◄ SELECCIONADO",IF(OR(D25="",D25=0,$C$6="",$C$6=0),"Sin fecha",IF(AND(YEAR(D25)=YEAR($C$6),MONTH(D25)=MONTH($C$6)),"MISMO MES",ABS((YEAR(D25)-YEAR($C$6))*12+MONTH(D25)-MONTH($C$6))&" meses "&IF(D25<$C$6,"antes","después"))))) | H25: =IFERROR(INDEX(Consolidado!$F$5:$F$1000,MATCH(12,Consolidado!$AC$5:$AC$1000,0))&"","") | I25: =IFERROR(INDEX(Consolidado!$G$5:$G$1000,MATCH(12,Consolidado!$AC$5:$AC$1000,0))&"","") | J25: =IFERROR(INDEX(Consolidado!$H$5:$H$1000,MATCH(12,Consolidado!$AC$5:$AC$1000,0))&"","")
A26: =IF(B26="","",13) | B26: =IFERROR(INDEX(Consolidado!$A$5:$A$1000,MATCH(13,Consolidado!$AC$5:$AC$1000,0)),"") | C26: =IFERROR(INDEX(Consolidado!$C$5:$C$1000,MATCH(13,Consolidado!$AC$5:$AC$1000,0))&"","") | D26: =IFERROR(INDEX(Consolidado!$B$5:$B$1000,MATCH(13,Consolidado!$AC$5:$AC$1000,0)),"") | E26: =IF(OR(D26="",D26=0),"",CHOOSE(MONTH(D26),"Ene","Feb","Mar","Abr","May","Jun","Jul","Ago","Sep","Oct","Nov","Dic")) | F26: =IF(OR(D26="",D26=0),"",YEAR(D26)) | G26: =IF(B26="","",IF(B26=$C$3,"◄ SELECCIONADO",IF(OR(D26="",D26=0,$C$6="",$C$6=0),"Sin fecha",IF(AND(YEAR(D26)=YEAR($C$6),MONTH(D26)=MONTH($C$6)),"MISMO MES",ABS((YEAR(D26)-YEAR($C$6))*12+MONTH(D26)-MONTH($C$6))&" meses "&IF(D26<$C$6,"antes","después"))))) | H26: =IFERROR(INDEX(Consolidado!$F$5:$F$1000,MATCH(13,Consolidado!$AC$5:$AC$1000,0))&"","") | I26: =IFERROR(INDEX(Consolidado!$G$5:$G$1000,MATCH(13,Consolidado!$AC$5:$AC$1000,0))&"","") | J26: =IFERROR(INDEX(Consolidado!$H$5:$H$1000,MATCH(13,Consolidado!$AC$5:$AC$1000,0))&"","")
A27: =IF(B27="","",14) | B27: =IFERROR(INDEX(Consolidado!$A$5:$A$1000,MATCH(14,Consolidado!$AC$5:$AC$1000,0)),"") | C27: =IFERROR(INDEX(Consolidado!$C$5:$C$1000,MATCH(14,Consolidado!$AC$5:$AC$1000,0))&"","") | D27: =IFERROR(INDEX(Consolidado!$B$5:$B$1000,MATCH(14,Consolidado!$AC$5:$AC$1000,0)),"") | E27: =IF(OR(D27="",D27=0),"",CHOOSE(MONTH(D27),"Ene","Feb","Mar","Abr","May","Jun","Jul","Ago","Sep","Oct","Nov","Dic")) | F27: =IF(OR(D27="",D27=0),"",YEAR(D27)) | G27: =IF(B27="","",IF(B27=$C$3,"◄ SELECCIONADO",IF(OR(D27="",D27=0,$C$6="",$C$6=0),"Sin fecha",IF(AND(YEAR(D27)=YEAR($C$6),MONTH(D27)=MONTH($C$6)),"MISMO MES",ABS((YEAR(D27)-YEAR($C$6))*12+MONTH(D27)-MONTH($C$6))&" meses "&IF(D27<$C$6,"antes","después"))))) | H27: =IFERROR(INDEX(Consolidado!$F$5:$F$1000,MATCH(14,Consolidado!$AC$5:$AC$1000,0))&"","") | I27: =IFERROR(INDEX(Consolidado!$G$5:$G$1000,MATCH(14,Consolidado!$AC$5:$AC$1000,0))&"","") | J27: =IFERROR(INDEX(Consolidado!$H$5:$H$1000,MATCH(14,Consolidado!$AC$5:$AC$1000,0))&"","")
A28: =IF(B28="","",15) | B28: =IFERROR(INDEX(Consolidado!$A$5:$A$1000,MATCH(15,Consolidado!$AC$5:$AC$1000,0)),"") | C28: =IFERROR(INDEX(Consolidado!$C$5:$C$1000,MATCH(15,Consolidado!$AC$5:$AC$1000,0))&"","") | D28: =IFERROR(INDEX(Consolidado!$B$5:$B$1000,MATCH(15,Consolidado!$AC$5:$AC$1000,0)),"") | E28: =IF(OR(D28="",D28=0),"",CHOOSE(MONTH(D28),"Ene","Feb","Mar","Abr","May","Jun","Jul","Ago","Sep","Oct","Nov","Dic")) | F28: =IF(OR(D28="",D28=0),"",YEAR(D28)) | G28: =IF(B28="","",IF(B28=$C$3,"◄ SELECCIONADO",IF(OR(D28="",D28=0,$C$6="",$C$6=0),"Sin fecha",IF(AND(YEAR(D28)=YEAR($C$6),MONTH(D28)=MONTH($C$6)),"MISMO MES",ABS((YEAR(D28)-YEAR($C$6))*12+MONTH(D28)-MONTH($C$6))&" meses "&IF(D28<$C$6,"antes","después"))))) | H28: =IFERROR(INDEX(Consolidado!$F$5:$F$1000,MATCH(15,Consolidado!$AC$5:$AC$1000,0))&"","") | I28: =IFERROR(INDEX(Consolidado!$G$5:$G$1000,MATCH(15,Consolidado!$AC$5:$AC$1000,0))&"","") | J28: =IFERROR(INDEX(Consolidado!$H$5:$H$1000,MATCH(15,Consolidado!$AC$5:$AC$1000,0))&"","")
A29: =IF(B29="","",16) | B29: =IFERROR(INDEX(Consolidado!$A$5:$A$1000,MATCH(16,Consolidado!$AC$5:$AC$1000,0)),"") | C29: =IFERROR(INDEX(Consolidado!$C$5:$C$1000,MATCH(16,Consolidado!$AC$5:$AC$1000,0))&"","") | D29: =IFERROR(INDEX(Consolidado!$B$5:$B$1000,MATCH(16,Consolidado!$AC$5:$AC$1000,0)),"") | E29: =IF(OR(D29="",D29=0),"",CHOOSE(MONTH(D29),"Ene","Feb","Mar","Abr","May","Jun","Jul","Ago","Sep","Oct","Nov","Dic")) | F29: =IF(OR(D29="",D29=0),"",YEAR(D29)) | G29: =IF(B29="","",IF(B29=$C$3,"◄ SELECCIONADO",IF(OR(D29="",D29=0,$C$6="",$C$6=0),"Sin fecha",IF(AND(YEAR(D29)=YEAR($C$6),MONTH(D29)=MONTH($C$6)),"MISMO MES",ABS((YEAR(D29)-YEAR($C$6))*12+MONTH(D29)-MONTH($C$6))&" meses "&IF(D29<$C$6,"antes","después"))))) | H29: =IFERROR(INDEX(Consolidado!$F$5:$F$1000,MATCH(16,Consolidado!$AC$5:$AC$1000,0))&"","") | I29: =IFERROR(INDEX(Consolidado!$G$5:$G$1000,MATCH(16,Consolidado!$AC$5:$AC$1000,0))&"","") | J29: =IFERROR(INDEX(Consolidado!$H$5:$H$1000,MATCH(16,Consolidado!$AC$5:$AC$1000,0))&"","")
A30: =IF(B30="","",17) | B30: =IFERROR(INDEX(Consolidado!$A$5:$A$1000,MATCH(17,Consolidado!$AC$5:$AC$1000,0)),"") | C30: =IFERROR(INDEX(Consolidado!$C$5:$C$1000,MATCH(17,Consolidado!$AC$5:$AC$1000,0))&"","") | D30: =IFERROR(INDEX(Consolidado!$B$5:$B$1000,MATCH(17,Consolidado!$AC$5:$AC$1000,0)),"") | E30: =IF(OR(D30="",D30=0),"",CHOOSE(MONTH(D30),"Ene","Feb","Mar","Abr","May","Jun","Jul","Ago","Sep","Oct","Nov","Dic")) | F30: =IF(OR(D30="",D30=0),"",YEAR(D30)) | G30: =IF(B30="","",IF(B30=$C$3,"◄ SELECCIONADO",IF(OR(D30="",D30=0,$C$6="",$C$6=0),"Sin fecha",IF(AND(YEAR(D30)=YEAR($C$6),MONTH(D30)=MONTH($C$6)),"MISMO MES",ABS((YEAR(D30)-YEAR($C$6))*12+MONTH(D30)-MONTH($C$6))&" meses "&IF(D30<$C$6,"antes","después"))))) | H30: =IFERROR(INDEX(Consolidado!$F$5:$F$1000,MATCH(17,Consolidado!$AC$5:$AC$1000,0))&"","") | I30: =IFERROR(INDEX(Consolidado!$G$5:$G$1000,MATCH(17,Consolidado!$AC$5:$AC$1000,0))&"","") | J30: =IFERROR(INDEX(Consolidado!$H$5:$H$1000,MATCH(17,Consolidado!$AC$5:$AC$1000,0))&"","")
A31: =IF(B31="","",18) | B31: =IFERROR(INDEX(Consolidado!$A$5:$A$1000,MATCH(18,Consolidado!$AC$5:$AC$1000,0)),"") | C31: =IFERROR(INDEX(Consolidado!$C$5:$C$1000,MATCH(18,Consolidado!$AC$5:$AC$1000,0))&"","") | D31: =IFERROR(INDEX(Consolidado!$B$5:$B$1000,MATCH(18,Consolidado!$AC$5:$AC$1000,0)),"") | E31: =IF(OR(D31="",D31=0),"",CHOOSE(MONTH(D31),"Ene","Feb","Mar","Abr","May","Jun","Jul","Ago","Sep","Oct","Nov","Dic")) | F31: =IF(OR(D31="",D31=0),"",YEAR(D31)) | G31: =IF(B31="","",IF(B31=$C$3,"◄ SELECCIONADO",IF(OR(D31="",D31=0,$C$6="",$C$6=0),"Sin fecha",IF(AND(YEAR(D31)=YEAR($C$6),MONTH(D31)=MONTH($C$6)),"MISMO MES",ABS((YEAR(D31)-YEAR($C$6))*12+MONTH(D31)-MONTH($C$6))&" meses "&IF(D31<$C$6,"antes","después"))))) | H31: =IFERROR(INDEX(Consolidado!$F$5:$F$1000,MATCH(18,Consolidado!$AC$5:$AC$1000,0))&"","") | I31: =IFERROR(INDEX(Consolidado!$G$5:$G$1000,MATCH(18,Consolidado!$AC$5:$AC$1000,0))&"","") | J31: =IFERROR(INDEX(Consolidado!$H$5:$H$1000,MATCH(18,Consolidado!$AC$5:$AC$1000,0))&"","")
A32: =IF(B32="","",19) | B32: =IFERROR(INDEX(Consolidado!$A$5:$A$1000,MATCH(19,Consolidado!$AC$5:$AC$1000,0)),"") | C32: =IFERROR(INDEX(Consolidado!$C$5:$C$1000,MATCH(19,Consolidado!$AC$5:$AC$1000,0))&"","") | D32: =IFERROR(INDEX(Consolidado!$B$5:$B$1000,MATCH(19,Consolidado!$AC$5:$AC$1000,0)),"") | E32: =IF(OR(D32="",D32=0),"",CHOOSE(MONTH(D32),"Ene","Feb","Mar","Abr","May","Jun","Jul","Ago","Sep","Oct","Nov","Dic")) | F32: =IF(OR(D32="",D32=0),"",YEAR(D32)) | G32: =IF(B32="","",IF(B32=$C$3,"◄ SELECCIONADO",IF(OR(D32="",D32=0,$C$6="",$C$6=0),"Sin fecha",IF(AND(YEAR(D32)=YEAR($C$6),MONTH(D32)=MONTH($C$6)),"MISMO MES",ABS((YEAR(D32)-YEAR($C$6))*12+MONTH(D32)-MONTH($C$6))&" meses "&IF(D32<$C$6,"antes","después"))))) | H32: =IFERROR(INDEX(Consolidado!$F$5:$F$1000,MATCH(19,Consolidado!$AC$5:$AC$1000,0))&"","") | I32: =IFERROR(INDEX(Consolidado!$G$5:$G$1000,MATCH(19,Consolidado!$AC$5:$AC$1000,0))&"","") | J32: =IFERROR(INDEX(Consolidado!$H$5:$H$1000,MATCH(19,Consolidado!$AC$5:$AC$1000,0))&"","")
A33: =IF(B33="","",20) | B33: =IFERROR(INDEX(Consolidado!$A$5:$A$1000,MATCH(20,Consolidado!$AC$5:$AC$1000,0)),"") | C33: =IFERROR(INDEX(Consolidado!$C$5:$C$1000,MATCH(20,Consolidado!$AC$5:$AC$1000,0))&"","") | D33: =IFERROR(INDEX(Consolidado!$B$5:$B$1000,MATCH(20,Consolidado!$AC$5:$AC$1000,0)),"") | E33: =IF(OR(D33="",D33=0),"",CHOOSE(MONTH(D33),"Ene","Feb","Mar","Abr","May","Jun","Jul","Ago","Sep","Oct","Nov","Dic")) | F33: =IF(OR(D33="",D33=0),"",YEAR(D33)) | G33: =IF(B33="","",IF(B33=$C$3,"◄ SELECCIONADO",IF(OR(D33="",D33=0,$C$6="",$C$6=0),"Sin fecha",IF(AND(YEAR(D33)=YEAR($C$6),MONTH(D33)=MONTH($C$6)),"MISMO MES",ABS((YEAR(D33)-YEAR($C$6))*12+MONTH(D33)-MONTH($C$6))&" meses "&IF(D33<$C$6,"antes","después"))))) | H33: =IFERROR(INDEX(Consolidado!$F$5:$F$1000,MATCH(20,Consolidado!$AC$5:$AC$1000,0))&"","") | I33: =IFERROR(INDEX(Consolidado!$G$5:$G$1000,MATCH(20,Consolidado!$AC$5:$AC$1000,0))&"","") | J33: =IFERROR(INDEX(Consolidado!$H$5:$H$1000,MATCH(20,Consolidado!$AC$5:$AC$1000,0))&"","")
A34: =IF(B34="","",21) | B34: =IFERROR(INDEX(Consolidado!$A$5:$A$1000,MATCH(21,Consolidado!$AC$5:$AC$1000,0)),"") | C34: =IFERROR(INDEX(Consolidado!$C$5:$C$1000,MATCH(21,Consolidado!$AC$5:$AC$1000,0))&"","") | D34: =IFERROR(INDEX(Consolidado!$B$5:$B$1000,MATCH(21,Consolidado!$AC$5:$AC$1000,0)),"") | E34: =IF(OR(D34="",D34=0),"",CHOOSE(MONTH(D34),"Ene","Feb","Mar","Abr","May","Jun","Jul","Ago","Sep","Oct","Nov","Dic")) | F34: =IF(OR(D34="",D34=0),"",YEAR(D34)) | G34: =IF(B34="","",IF(B34=$C$3,"◄ SELECCIONADO",IF(OR(D34="",D34=0,$C$6="",$C$6=0),"Sin fecha",IF(AND(YEAR(D34)=YEAR($C$6),MONTH(D34)=MONTH($C$6)),"MISMO MES",ABS((YEAR(D34)-YEAR($C$6))*12+MONTH(D34)-MONTH($C$6))&" meses "&IF(D34<$C$6,"antes","después"))))) | H34: =IFERROR(INDEX(Consolidado!$F$5:$F$1000,MATCH(21,Consolidado!$AC$5:$AC$1000,0))&"","") | I34: =IFERROR(INDEX(Consolidado!$G$5:$G$1000,MATCH(21,Consolidado!$AC$5:$AC$1000,0))&"","") | J34: =IFERROR(INDEX(Consolidado!$H$5:$H$1000,MATCH(21,Consolidado!$AC$5:$AC$1000,0))&"","")
A35: =IF(B35="","",22) | B35: =IFERROR(INDEX(Consolidado!$A$5:$A$1000,MATCH(22,Consolidado!$AC$5:$AC$1000,0)),"") | C35: =IFERROR(INDEX(Consolidado!$C$5:$C$1000,MATCH(22,Consolidado!$AC$5:$AC$1000,0))&"","") | D35: =IFERROR(INDEX(Consolidado!$B$5:$B$1000,MATCH(22,Consolidado!$AC$5:$AC$1000,0)),"") | E35: =IF(OR(D35="",D35=0),"",CHOOSE(MONTH(D35),"Ene","Feb","Mar","Abr","May","Jun","Jul","Ago","Sep","Oct","Nov","Dic")) | F35: =IF(OR(D35="",D35=0),"",YEAR(D35)) | G35: =IF(B35="","",IF(B35=$C$3,"◄ SELECCIONADO",IF(OR(D35="",D35=0,$C$6="",$C$6=0),"Sin fecha",IF(AND(YEAR(D35)=YEAR($C$6),MONTH(D35)=MONTH($C$6)),"MISMO MES",ABS((YEAR(D35)-YEAR($C$6))*12+MONTH(D35)-MONTH($C$6))&" meses "&IF(D35<$C$6,"antes","después"))))) | H35: =IFERROR(INDEX(Consolidado!$F$5:$F$1000,MATCH(22,Consolidado!$AC$5:$AC$1000,0))&"","") | I35: =IFERROR(INDEX(Consolidado!$G$5:$G$1000,MATCH(22,Consolidado!$AC$5:$AC$1000,0))&"","") | J35: =IFERROR(INDEX(Consolidado!$H$5:$H$1000,MATCH(22,Consolidado!$AC$5:$AC$1000,0))&"","")
A36: =IF(B36="","",23) | B36: =IFERROR(INDEX(Consolidado!$A$5:$A$1000,MATCH(23,Consolidado!$AC$5:$AC$1000,0)),"") | C36: =IFERROR(INDEX(Consolidado!$C$5:$C$1000,MATCH(23,Consolidado!$AC$5:$AC$1000,0))&"","") | D36: =IFERROR(INDEX(Consolidado!$B$5:$B$1000,MATCH(23,Consolidado!$AC$5:$AC$1000,0)),"") | E36: =IF(OR(D36="",D36=0),"",CHOOSE(MONTH(D36),"Ene","Feb","Mar","Abr","May","Jun","Jul","Ago","Sep","Oct","Nov","Dic")) | F36: =IF(OR(D36="",D36=0),"",YEAR(D36)) | G36: =IF(B36="","",IF(B36=$C$3,"◄ SELECCIONADO",IF(OR(D36="",D36=0,$C$6="",$C$6=0),"Sin fecha",IF(AND(YEAR(D36)=YEAR($C$6),MONTH(D36)=MONTH($C$6)),"MISMO MES",ABS((YEAR(D36)-YEAR($C$6))*12+MONTH(D36)-MONTH($C$6))&" meses "&IF(D36<$C$6,"antes","después"))))) | H36: =IFERROR(INDEX(Consolidado!$F$5:$F$1000,MATCH(23,Consolidado!$AC$5:$AC$1000,0))&"","") | I36: =IFERROR(INDEX(Consolidado!$G$5:$G$1000,MATCH(23,Consolidado!$AC$5:$AC$1000,0))&"","") | J36: =IFERROR(INDEX(Consolidado!$H$5:$H$1000,MATCH(23,Consolidado!$AC$5:$AC$1000,0))&"","")
A37: =IF(B37="","",24) | B37: =IFERROR(INDEX(Consolidado!$A$5:$A$1000,MATCH(24,Consolidado!$AC$5:$AC$1000,0)),"") | C37: =IFERROR(INDEX(Consolidado!$C$5:$C$1000,MATCH(24,Consolidado!$AC$5:$AC$1000,0))&"","") | D37: =IFERROR(INDEX(Consolidado!$B$5:$B$1000,MATCH(24,Consolidado!$AC$5:$AC$1000,0)),"") | E37: =IF(OR(D37="",D37=0),"",CHOOSE(MONTH(D37),"Ene","Feb","Mar","Abr","May","Jun","Jul","Ago","Sep","Oct","Nov","Dic")) | F37: =IF(OR(D37="",D37=0),"",YEAR(D37)) | G37: =IF(B37="","",IF(B37=$C$3,"◄ SELECCIONADO",IF(OR(D37="",D37=0,$C$6="",$C$6=0),"Sin fecha",IF(AND(YEAR(D37)=YEAR($C$6),MONTH(D37)=MONTH($C$6)),"MISMO MES",ABS((YEAR(D37)-YEAR($C$6))*12+MONTH(D37)-MONTH($C$6))&" meses "&IF(D37<$C$6,"antes","después"))))) | H37: =IFERROR(INDEX(Consolidado!$F$5:$F$1000,MATCH(24,Consolidado!$AC$5:$AC$1000,0))&"","") | I37: =IFERROR(INDEX(Consolidado!$G$5:$G$1000,MATCH(24,Consolidado!$AC$5:$AC$1000,0))&"","") | J37: =IFERROR(INDEX(Consolidado!$H$5:$H$1000,MATCH(24,Consolidado!$AC$5:$AC$1000,0))&"","")
A38: =IF(B38="","",25) | B38: =IFERROR(INDEX(Consolidado!$A$5:$A$1000,MATCH(25,Consolidado!$AC$5:$AC$1000,0)),"") | C38: =IFERROR(INDEX(Consolidado!$C$5:$C$1000,MATCH(25,Consolidado!$AC$5:$AC$1000,0))&"","") | D38: =IFERROR(INDEX(Consolidado!$B$5:$B$1000,MATCH(25,Consolidado!$AC$5:$AC$1000,0)),"") | E38: =IF(OR(D38="",D38=0),"",CHOOSE(MONTH(D38),"Ene","Feb","Mar","Abr","May","Jun","Jul","Ago","Sep","Oct","Nov","Dic")) | F38: =IF(OR(D38="",D38=0),"",YEAR(D38)) | G38: =IF(B38="","",IF(B38=$C$3,"◄ SELECCIONADO",IF(OR(D38="",D38=0,$C$6="",$C$6=0),"Sin fecha",IF(AND(YEAR(D38)=YEAR($C$6),MONTH(D38)=MONTH($C$6)),"MISMO MES",ABS((YEAR(D38)-YEAR($C$6))*12+MONTH(D38)-MONTH($C$6))&" meses "&IF(D38<$C$6,"antes","después"))))) | H38: =IFERROR(INDEX(Consolidado!$F$5:$F$1000,MATCH(25,Consolidado!$AC$5:$AC$1000,0))&"","") | I38: =IFERROR(INDEX(Consolidado!$G$5:$G$1000,MATCH(25,Consolidado!$AC$5:$AC$1000,0))&"","") | J38: =IFERROR(INDEX(Consolidado!$H$5:$H$1000,MATCH(25,Consolidado!$AC$5:$AC$1000,0))&"","")
A39: =IF(B39="","",26) | B39: =IFERROR(INDEX(Consolidado!$A$5:$A$1000,MATCH(26,Consolidado!$AC$5:$AC$1000,0)),"") | C39: =IFERROR(INDEX(Consolidado!$C$5:$C$1000,MATCH(26,Consolidado!$AC$5:$AC$1000,0))&"","") | D39: =IFERROR(INDEX(Consolidado!$B$5:$B$1000,MATCH(26,Consolidado!$AC$5:$AC$1000,0)),"") | E39: =IF(OR(D39="",D39=0),"",CHOOSE(MONTH(D39),"Ene","Feb","Mar","Abr","May","Jun","Jul","Ago","Sep","Oct","Nov","Dic")) | F39: =IF(OR(D39="",D39=0),"",YEAR(D39)) | G39: =IF(B39="","",IF(B39=$C$3,"◄ SELECCIONADO",IF(OR(D39="",D39=0,$C$6="",$C$6=0),"Sin fecha",IF(AND(YEAR(D39)=YEAR($C$6),MONTH(D39)=MONTH($C$6)),"MISMO MES",ABS((YEAR(D39)-YEAR($C$6))*12+MONTH(D39)-MONTH($C$6))&" meses "&IF(D39<$C$6,"antes","después"))))) | H39: =IFERROR(INDEX(Consolidado!$F$5:$F$1000,MATCH(26,Consolidado!$AC$5:$AC$1000,0))&"","") | I39: =IFERROR(INDEX(Consolidado!$G$5:$G$1000,MATCH(26,Consolidado!$AC$5:$AC$1000,0))&"","") | J39: =IFERROR(INDEX(Consolidado!$H$5:$H$1000,MATCH(26,Consolidado!$AC$5:$AC$1000,0))&"","")
A40: =IF(B40="","",27) | B40: =IFERROR(INDEX(Consolidado!$A$5:$A$1000,MATCH(27,Consolidado!$AC$5:$AC$1000,0)),"") | C40: =IFERROR(INDEX(Consolidado!$C$5:$C$1000,MATCH(27,Consolidado!$AC$5:$AC$1000,0))&"","") | D40: =IFERROR(INDEX(Consolidado!$B$5:$B$1000,MATCH(27,Consolidado!$AC$5:$AC$1000,0)),"") | E40: =IF(OR(D40="",D40=0),"",CHOOSE(MONTH(D40),"Ene","Feb","Mar","Abr","May","Jun","Jul","Ago","Sep","Oct","Nov","Dic")) | F40: =IF(OR(D40="",D40=0),"",YEAR(D40)) | G40: =IF(B40="","",IF(B40=$C$3,"◄ SELECCIONADO",IF(OR(D40="",D40=0,$C$6="",$C$6=0),"Sin fecha",IF(AND(YEAR(D40)=YEAR($C$6),MONTH(D40)=MONTH($C$6)),"MISMO MES",ABS((YEAR(D40)-YEAR($C$6))*12+MONTH(D40)-MONTH($C$6))&" meses "&IF(D40<$C$6,"antes","después"))))) | H40: =IFERROR(INDEX(Consolidado!$F$5:$F$1000,MATCH(27,Consolidado!$AC$5:$AC$1000,0))&"","") | I40: =IFERROR(INDEX(Consolidado!$G$5:$G$1000,MATCH(27,Consolidado!$AC$5:$AC$1000,0))&"","") | J40: =IFERROR(INDEX(Consolidado!$H$5:$H$1000,MATCH(27,Consolidado!$AC$5:$AC$1000,0))&"","")
A41: =IF(B41="","",28) | B41: =IFERROR(INDEX(Consolidado!$A$5:$A$1000,MATCH(28,Consolidado!$AC$5:$AC$1000,0)),"") | C41: =IFERROR(INDEX(Consolidado!$C$5:$C$1000,MATCH(28,Consolidado!$AC$5:$AC$1000,0))&"","") | D41: =IFERROR(INDEX(Consolidado!$B$5:$B$1000,MATCH(28,Consolidado!$AC$5:$AC$1000,0)),"") | E41: =IF(OR(D41="",D41=0),"",CHOOSE(MONTH(D41),"Ene","Feb","Mar","Abr","May","Jun","Jul","Ago","Sep","Oct","Nov","Dic")) | F41: =IF(OR(D41="",D41=0),"",YEAR(D41)) | G41: =IF(B41="","",IF(B41=$C$3,"◄ SELECCIONADO",IF(OR(D41="",D41=0,$C$6="",$C$6=0),"Sin fecha",IF(AND(YEAR(D41)=YEAR($C$6),MONTH(D41)=MONTH($C$6)),"MISMO MES",ABS((YEAR(D41)-YEAR($C$6))*12+MONTH(D41)-MONTH($C$6))&" meses "&IF(D41<$C$6,"antes","después"))))) | H41: =IFERROR(INDEX(Consolidado!$F$5:$F$1000,MATCH(28,Consolidado!$AC$5:$AC$1000,0))&"","") | I41: =IFERROR(INDEX(Consolidado!$G$5:$G$1000,MATCH(28,Consolidado!$AC$5:$AC$1000,0))&"","") | J41: =IFERROR(INDEX(Consolidado!$H$5:$H$1000,MATCH(28,Consolidado!$AC$5:$AC$1000,0))&"","")
A42: =IF(B42="","",29) | B42: =IFERROR(INDEX(Consolidado!$A$5:$A$1000,MATCH(29,Consolidado!$AC$5:$AC$1000,0)),"") | C42: =IFERROR(INDEX(Consolidado!$C$5:$C$1000,MATCH(29,Consolidado!$AC$5:$AC$1000,0))&"","") | D42: =IFERROR(INDEX(Consolidado!$B$5:$B$1000,MATCH(29,Consolidado!$AC$5:$AC$1000,0)),"") | E42: =IF(OR(D42="",D42=0),"",CHOOSE(MONTH(D42),"Ene","Feb","Mar","Abr","May","Jun","Jul","Ago","Sep","Oct","Nov","Dic")) | F42: =IF(OR(D42="",D42=0),"",YEAR(D42)) | G42: =IF(B42="","",IF(B42=$C$3,"◄ SELECCIONADO",IF(OR(D42="",D42=0,$C$6="",$C$6=0),"Sin fecha",IF(AND(YEAR(D42)=YEAR($C$6),MONTH(D42)=MONTH($C$6)),"MISMO MES",ABS((YEAR(D42)-YEAR($C$6))*12+MONTH(D42)-MONTH($C$6))&" meses "&IF(D42<$C$6,"antes","después"))))) | H42: =IFERROR(INDEX(Consolidado!$F$5:$F$1000,MATCH(29,Consolidado!$AC$5:$AC$1000,0))&"","") | I42: =IFERROR(INDEX(Consolidado!$G$5:$G$1000,MATCH(29,Consolidado!$AC$5:$AC$1000,0))&"","") | J42: =IFERROR(INDEX(Consolidado!$H$5:$H$1000,MATCH(29,Consolidado!$AC$5:$AC$1000,0))&"","")
A43: =IF(B43="","",30) | B43: =IFERROR(INDEX(Consolidado!$A$5:$A$1000,MATCH(30,Consolidado!$AC$5:$AC$1000,0)),"") | C43: =IFERROR(INDEX(Consolidado!$C$5:$C$1000,MATCH(30,Consolidado!$AC$5:$AC$1000,0))&"","") | D43: =IFERROR(INDEX(Consolidado!$B$5:$B$1000,MATCH(30,Consolidado!$AC$5:$AC$1000,0)),"") | E43: =IF(OR(D43="",D43=0),"",CHOOSE(MONTH(D43),"Ene","Feb","Mar","Abr","May","Jun","Jul","Ago","Sep","Oct","Nov","Dic")) | F43: =IF(OR(D43="",D43=0),"",YEAR(D43)) | G43: =IF(B43="","",IF(B43=$C$3,"◄ SELECCIONADO",IF(OR(D43="",D43=0,$C$6="",$C$6=0),"Sin fecha",IF(AND(YEAR(D43)=YEAR($C$6),MONTH(D43)=MONTH($C$6)),"MISMO MES",ABS((YEAR(D43)-YEAR($C$6))*12+MONTH(D43)-MONTH($C$6))&" meses "&IF(D43<$C$6,"antes","después"))))) | H43: =IFERROR(INDEX(Consolidado!$F$5:$F$1000,MATCH(30,Consolidado!$AC$5:$AC$1000,0))&"","") | I43: =IFERROR(INDEX(Consolidado!$G$5:$G$1000,MATCH(30,Consolidado!$AC$5:$AC$1000,0))&"","") | J43: =IFERROR(INDEX(Consolidado!$H$5:$H$1000,MATCH(30,Consolidado!$AC$5:$AC$1000,0))&"","")
A44: =IF(B44="","",31) | B44: =IFERROR(INDEX(Consolidado!$A$5:$A$1000,MATCH(31,Consolidado!$AC$5:$AC$1000,0)),"") | C44: =IFERROR(INDEX(Consolidado!$C$5:$C$1000,MATCH(31,Consolidado!$AC$5:$AC$1000,0))&"","") | D44: =IFERROR(INDEX(Consolidado!$B$5:$B$1000,MATCH(31,Consolidado!$AC$5:$AC$1000,0)),"") | E44: =IF(OR(D44="",D44=0),"",CHOOSE(MONTH(D44),"Ene","Feb","Mar","Abr","May","Jun","Jul","Ago","Sep","Oct","Nov","Dic")) | F44: =IF(OR(D44="",D44=0),"",YEAR(D44)) | G44: =IF(B44="","",IF(B44=$C$3,"◄ SELECCIONADO",IF(OR(D44="",D44=0,$C$6="",$C$6=0),"Sin fecha",IF(AND(YEAR(D44)=YEAR($C$6),MONTH(D44)=MONTH($C$6)),"MISMO MES",ABS((YEAR(D44)-YEAR($C$6))*12+MONTH(D44)-MONTH($C$6))&" meses "&IF(D44<$C$6,"antes","después"))))) | H44: =IFERROR(INDEX(Consolidado!$F$5:$F$1000,MATCH(31,Consolidado!$AC$5:$AC$1000,0))&"","") | I44: =IFERROR(INDEX(Consolidado!$G$5:$G$1000,MATCH(31,Consolidado!$AC$5:$AC$1000,0))&"","") | J44: =IFERROR(INDEX(Consolidado!$H$5:$H$1000,MATCH(31,Consolidado!$AC$5:$AC$1000,0))&"","")
A45: =IF(B45="","",32) | B45: =IFERROR(INDEX(Consolidado!$A$5:$A$1000,MATCH(32,Consolidado!$AC$5:$AC$1000,0)),"") | C45: =IFERROR(INDEX(Consolidado!$C$5:$C$1000,MATCH(32,Consolidado!$AC$5:$AC$1000,0))&"","") | D45: =IFERROR(INDEX(Consolidado!$B$5:$B$1000,MATCH(32,Consolidado!$AC$5:$AC$1000,0)),"") | E45: =IF(OR(D45="",D45=0),"",CHOOSE(MONTH(D45),"Ene","Feb","Mar","Abr","May","Jun","Jul","Ago","Sep","Oct","Nov","Dic")) | F45: =IF(OR(D45="",D45=0),"",YEAR(D45)) | G45: =IF(B45="","",IF(B45=$C$3,"◄ SELECCIONADO",IF(OR(D45="",D45=0,$C$6="",$C$6=0),"Sin fecha",IF(AND(YEAR(D45)=YEAR($C$6),MONTH(D45)=MONTH($C$6)),"MISMO MES",ABS((YEAR(D45)-YEAR($C$6))*12+MONTH(D45)-MONTH($C$6))&" meses "&IF(D45<$C$6,"antes","después"))))) | H45: =IFERROR(INDEX(Consolidado!$F$5:$F$1000,MATCH(32,Consolidado!$AC$5:$AC$1000,0))&"","") | I45: =IFERROR(INDEX(Consolidado!$G$5:$G$1000,MATCH(32,Consolidado!$AC$5:$AC$1000,0))&"","") | J45: =IFERROR(INDEX(Consolidado!$H$5:$H$1000,MATCH(32,Consolidado!$AC$5:$AC$1000,0))&"","")
A46: =IF(B46="","",33) | B46: =IFERROR(INDEX(Consolidado!$A$5:$A$1000,MATCH(33,Consolidado!$AC$5:$AC$1000,0)),"") | C46: =IFERROR(INDEX(Consolidado!$C$5:$C$1000,MATCH(33,Consolidado!$AC$5:$AC$1000,0))&"","") | D46: =IFERROR(INDEX(Consolidado!$B$5:$B$1000,MATCH(33,Consolidado!$AC$5:$AC$1000,0)),"") | E46: =IF(OR(D46="",D46=0),"",CHOOSE(MONTH(D46),"Ene","Feb","Mar","Abr","May","Jun","Jul","Ago","Sep","Oct","Nov","Dic")) | F46: =IF(OR(D46="",D46=0),"",YEAR(D46)) | G46: =IF(B46="","",IF(B46=$C$3,"◄ SELECCIONADO",IF(OR(D46="",D46=0,$C$6="",$C$6=0),"Sin fecha",IF(AND(YEAR(D46)=YEAR($C$6),MONTH(D46)=MONTH($C$6)),"MISMO MES",ABS((YEAR(D46)-YEAR($C$6))*12+MONTH(D46)-MONTH($C$6))&" meses "&IF(D46<$C$6,"antes","después"))))) | H46: =IFERROR(INDEX(Consolidado!$F$5:$F$1000,MATCH(33,Consolidado!$AC$5:$AC$1000,0))&"","") | I46: =IFERROR(INDEX(Consolidado!$G$5:$G$1000,MATCH(33,Consolidado!$AC$5:$AC$1000,0))&"","") | J46: =IFERROR(INDEX(Consolidado!$H$5:$H$1000,MATCH(33,Consolidado!$AC$5:$AC$1000,0))&"","")
A47: =IF(B47="","",34) | B47: =IFERROR(INDEX(Consolidado!$A$5:$A$1000,MATCH(34,Consolidado!$AC$5:$AC$1000,0)),"") | C47: =IFERROR(INDEX(Consolidado!$C$5:$C$1000,MATCH(34,Consolidado!$AC$5:$AC$1000,0))&"","") | D47: =IFERROR(INDEX(Consolidado!$B$5:$B$1000,MATCH(34,Consolidado!$AC$5:$AC$1000,0)),"") | E47: =IF(OR(D47="",D47=0),"",CHOOSE(MONTH(D47),"Ene","Feb","Mar","Abr","May","Jun","Jul","Ago","Sep","Oct","Nov","Dic")) | F47: =IF(OR(D47="",D47=0),"",YEAR(D47)) | G47: =IF(B47="","",IF(B47=$C$3,"◄ SELECCIONADO",IF(OR(D47="",D47=0,$C$6="",$C$6=0),"Sin fecha",IF(AND(YEAR(D47)=YEAR($C$6),MONTH(D47)=MONTH($C$6)),"MISMO MES",ABS((YEAR(D47)-YEAR($C$6))*12+MONTH(D47)-MONTH($C$6))&" meses "&IF(D47<$C$6,"antes","después"))))) | H47: =IFERROR(INDEX(Consolidado!$F$5:$F$1000,MATCH(34,Consolidado!$AC$5:$AC$1000,0))&"","") | I47: =IFERROR(INDEX(Consolidado!$G$5:$G$1000,MATCH(34,Consolidado!$AC$5:$AC$1000,0))&"","") | J47: =IFERROR(INDEX(Consolidado!$H$5:$H$1000,MATCH(34,Consolidado!$AC$5:$AC$1000,0))&"","")
A48: =IF(B48="","",35) | B48: =IFERROR(INDEX(Consolidado!$A$5:$A$1000,MATCH(35,Consolidado!$AC$5:$AC$1000,0)),"") | C48: =IFERROR(INDEX(Consolidado!$C$5:$C$1000,MATCH(35,Consolidado!$AC$5:$AC$1000,0))&"","") | D48: =IFERROR(INDEX(Consolidado!$B$5:$B$1000,MATCH(35,Consolidado!$AC$5:$AC$1000,0)),"") | E48: =IF(OR(D48="",D48=0),"",CHOOSE(MONTH(D48),"Ene","Feb","Mar","Abr","May","Jun","Jul","Ago","Sep","Oct","Nov","Dic")) | F48: =IF(OR(D48="",D48=0),"",YEAR(D48)) | G48: =IF(B48="","",IF(B48=$C$3,"◄ SELECCIONADO",IF(OR(D48="",D48=0,$C$6="",$C$6=0),"Sin fecha",IF(AND(YEAR(D48)=YEAR($C$6),MONTH(D48)=MONTH($C$6)),"MISMO MES",ABS((YEAR(D48)-YEAR($C$6))*12+MONTH(D48)-MONTH($C$6))&" meses "&IF(D48<$C$6,"antes","después"))))) | H48: =IFERROR(INDEX(Consolidado!$F$5:$F$1000,MATCH(35,Consolidado!$AC$5:$AC$1000,0))&"","") | I48: =IFERROR(INDEX(Consolidado!$G$5:$G$1000,MATCH(35,Consolidado!$AC$5:$AC$1000,0))&"","") | J48: =IFERROR(INDEX(Consolidado!$H$5:$H$1000,MATCH(35,Consolidado!$AC$5:$AC$1000,0))&"","")
A49: =IF(B49="","",36) | B49: =IFERROR(INDEX(Consolidado!$A$5:$A$1000,MATCH(36,Consolidado!$AC$5:$AC$1000,0)),"") | C49: =IFERROR(INDEX(Consolidado!$C$5:$C$1000,MATCH(36,Consolidado!$AC$5:$AC$1000,0))&"","") | D49: =IFERROR(INDEX(Consolidado!$B$5:$B$1000,MATCH(36,Consolidado!$AC$5:$AC$1000,0)),"") | E49: =IF(OR(D49="",D49=0),"",CHOOSE(MONTH(D49),"Ene","Feb","Mar","Abr","May","Jun","Jul","Ago","Sep","Oct","Nov","Dic")) | F49: =IF(OR(D49="",D49=0),"",YEAR(D49)) | G49: =IF(B49="","",IF(B49=$C$3,"◄ SELECCIONADO",IF(OR(D49="",D49=0,$C$6="",$C$6=0),"Sin fecha",IF(AND(YEAR(D49)=YEAR($C$6),MONTH(D49)=MONTH($C$6)),"MISMO MES",ABS((YEAR(D49)-YEAR($C$6))*12+MONTH(D49)-MONTH($C$6))&" meses "&IF(D49<$C$6,"antes","después"))))) | H49: =IFERROR(INDEX(Consolidado!$F$5:$F$1000,MATCH(36,Consolidado!$AC$5:$AC$1000,0))&"","") | I49: =IFERROR(INDEX(Consolidado!$G$5:$G$1000,MATCH(36,Consolidado!$AC$5:$AC$1000,0))&"","") | J49: =IFERROR(INDEX(Consolidado!$H$5:$H$1000,MATCH(36,Consolidado!$AC$5:$AC$1000,0))&"","")
A50: =IF(B50="","",37) | B50: =IFERROR(INDEX(Consolidado!$A$5:$A$1000,MATCH(37,Consolidado!$AC$5:$AC$1000,0)),"") | C50: =IFERROR(INDEX(Consolidado!$C$5:$C$1000,MATCH(37,Consolidado!$AC$5:$AC$1000,0))&"","") | D50: =IFERROR(INDEX(Consolidado!$B$5:$B$1000,MATCH(37,Consolidado!$AC$5:$AC$1000,0)),"") | E50: =IF(OR(D50="",D50=0),"",CHOOSE(MONTH(D50),"Ene","Feb","Mar","Abr","May","Jun","Jul","Ago","Sep","Oct","Nov","Dic")) | F50: =IF(OR(D50="",D50=0),"",YEAR(D50)) | G50: =IF(B50="","",IF(B50=$C$3,"◄ SELECCIONADO",IF(OR(D50="",D50=0,$C$6="",$C$6=0),"Sin fecha",IF(AND(YEAR(D50)=YEAR($C$6),MONTH(D50)=MONTH($C$6)),"MISMO MES",ABS((YEAR(D50)-YEAR($C$6))*12+MONTH(D50)-MONTH($C$6))&" meses "&IF(D50<$C$6,"antes","después"))))) | H50: =IFERROR(INDEX(Consolidado!$F$5:$F$1000,MATCH(37,Consolidado!$AC$5:$AC$1000,0))&"","") | I50: =IFERROR(INDEX(Consolidado!$G$5:$G$1000,MATCH(37,Consolidado!$AC$5:$AC$1000,0))&"","") | J50: =IFERROR(INDEX(Consolidado!$H$5:$H$1000,MATCH(37,Consolidado!$AC$5:$AC$1000,0))&"","")
A51: =IF(B51="","",38) | B51: =IFERROR(INDEX(Consolidado!$A$5:$A$1000,MATCH(38,Consolidado!$AC$5:$AC$1000,0)),"") | C51: =IFERROR(INDEX(Consolidado!$C$5:$C$1000,MATCH(38,Consolidado!$AC$5:$AC$1000,0))&"","") | D51: =IFERROR(INDEX(Consolidado!$B$5:$B$1000,MATCH(38,Consolidado!$AC$5:$AC$1000,0)),"") | E51: =IF(OR(D51="",D51=0),"",CHOOSE(MONTH(D51),"Ene","Feb","Mar","Abr","May","Jun","Jul","Ago","Sep","Oct","Nov","Dic")) | F51: =IF(OR(D51="",D51=0),"",YEAR(D51)) | G51: =IF(B51="","",IF(B51=$C$3,"◄ SELECCIONADO",IF(OR(D51="",D51=0,$C$6="",$C$6=0),"Sin fecha",IF(AND(YEAR(D51)=YEAR($C$6),MONTH(D51)=MONTH($C$6)),"MISMO MES",ABS((YEAR(D51)-YEAR($C$6))*12+MONTH(D51)-MONTH($C$6))&" meses "&IF(D51<$C$6,"antes","después"))))) | H51: =IFERROR(INDEX(Consolidado!$F$5:$F$1000,MATCH(38,Consolidado!$AC$5:$AC$1000,0))&"","") | I51: =IFERROR(INDEX(Consolidado!$G$5:$G$1000,MATCH(38,Consolidado!$AC$5:$AC$1000,0))&"","") | J51: =IFERROR(INDEX(Consolidado!$H$5:$H$1000,MATCH(38,Consolidado!$AC$5:$AC$1000,0))&"","")
A52: =IF(B52="","",39) | B52: =IFERROR(INDEX(Consolidado!$A$5:$A$1000,MATCH(39,Consolidado!$AC$5:$AC$1000,0)),"") | C52: =IFERROR(INDEX(Consolidado!$C$5:$C$1000,MATCH(39,Consolidado!$AC$5:$AC$1000,0))&"","") | D52: =IFERROR(INDEX(Consolidado!$B$5:$B$1000,MATCH(39,Consolidado!$AC$5:$AC$1000,0)),"") | E52: =IF(OR(D52="",D52=0),"",CHOOSE(MONTH(D52),"Ene","Feb","Mar","Abr","May","Jun","Jul","Ago","Sep","Oct","Nov","Dic")) | F52: =IF(OR(D52="",D52=0),"",YEAR(D52)) | G52: =IF(B52="","",IF(B52=$C$3,"◄ SELECCIONADO",IF(OR(D52="",D52=0,$C$6="",$C$6=0),"Sin fecha",IF(AND(YEAR(D52)=YEAR($C$6),MONTH(D52)=MONTH($C$6)),"MISMO MES",ABS((YEAR(D52)-YEAR($C$6))*12+MONTH(D52)-MONTH($C$6))&" meses "&IF(D52<$C$6,"antes","después"))))) | H52: =IFERROR(INDEX(Consolidado!$F$5:$F$1000,MATCH(39,Consolidado!$AC$5:$AC$1000,0))&"","") | I52: =IFERROR(INDEX(Consolidado!$G$5:$G$1000,MATCH(39,Consolidado!$AC$5:$AC$1000,0))&"","") | J52: =IFERROR(INDEX(Consolidado!$H$5:$H$1000,MATCH(39,Consolidado!$AC$5:$AC$1000,0))&"","")
A53: =IF(B53="","",40) | B53: =IFERROR(INDEX(Consolidado!$A$5:$A$1000,MATCH(40,Consolidado!$AC$5:$AC$1000,0)),"") | C53: =IFERROR(INDEX(Consolidado!$C$5:$C$1000,MATCH(40,Consolidado!$AC$5:$AC$1000,0))&"","") | D53: =IFERROR(INDEX(Consolidado!$B$5:$B$1000,MATCH(40,Consolidado!$AC$5:$AC$1000,0)),"") | E53: =IF(OR(D53="",D53=0),"",CHOOSE(MONTH(D53),"Ene","Feb","Mar","Abr","May","Jun","Jul","Ago","Sep","Oct","Nov","Dic")) | F53: =IF(OR(D53="",D53=0),"",YEAR(D53)) | G53: =IF(B53="","",IF(B53=$C$3,"◄ SELECCIONADO",IF(OR(D53="",D53=0,$C$6="",$C$6=0),"Sin fecha",IF(AND(YEAR(D53)=YEAR($C$6),MONTH(D53)=MONTH($C$6)),"MISMO MES",ABS((YEAR(D53)-YEAR($C$6))*12+MONTH(D53)-MONTH($C$6))&" meses "&IF(D53<$C$6,"antes","después"))))) | H53: =IFERROR(INDEX(Consolidado!$F$5:$F$1000,MATCH(40,Consolidado!$AC$5:$AC$1000,0))&"","") | I53: =IFERROR(INDEX(Consolidado!$G$5:$G$1000,MATCH(40,Consolidado!$AC$5:$AC$1000,0))&"","") | J53: =IFERROR(INDEX(Consolidado!$H$5:$H$1000,MATCH(40,Consolidado!$AC$5:$AC$1000,0))&"","")
A54: =IF(B54="","",41) | B54: =IFERROR(INDEX(Consolidado!$A$5:$A$1000,MATCH(41,Consolidado!$AC$5:$AC$1000,0)),"") | C54: =IFERROR(INDEX(Consolidado!$C$5:$C$1000,MATCH(41,Consolidado!$AC$5:$AC$1000,0))&"","") | D54: =IFERROR(INDEX(Consolidado!$B$5:$B$1000,MATCH(41,Consolidado!$AC$5:$AC$1000,0)),"") | E54: =IF(OR(D54="",D54=0),"",CHOOSE(MONTH(D54),"Ene","Feb","Mar","Abr","May","Jun","Jul","Ago","Sep","Oct","Nov","Dic")) | F54: =IF(OR(D54="",D54=0),"",YEAR(D54)) | G54: =IF(B54="","",IF(B54=$C$3,"◄ SELECCIONADO",IF(OR(D54="",D54=0,$C$6="",$C$6=0),"Sin fecha",IF(AND(YEAR(D54)=YEAR($C$6),MONTH(D54)=MONTH($C$6)),"MISMO MES",ABS((YEAR(D54)-YEAR($C$6))*12+MONTH(D54)-MONTH($C$6))&" meses "&IF(D54<$C$6,"antes","después"))))) | H54: =IFERROR(INDEX(Consolidado!$F$5:$F$1000,MATCH(41,Consolidado!$AC$5:$AC$1000,0))&"","") | I54: =IFERROR(INDEX(Consolidado!$G$5:$G$1000,MATCH(41,Consolidado!$AC$5:$AC$1000,0))&"","") | J54: =IFERROR(INDEX(Consolidado!$H$5:$H$1000,MATCH(41,Consolidado!$AC$5:$AC$1000,0))&"","")
A55: =IF(B55="","",42) | B55: =IFERROR(INDEX(Consolidado!$A$5:$A$1000,MATCH(42,Consolidado!$AC$5:$AC$1000,0)),"") | C55: =IFERROR(INDEX(Consolidado!$C$5:$C$1000,MATCH(42,Consolidado!$AC$5:$AC$1000,0))&"","") | D55: =IFERROR(INDEX(Consolidado!$B$5:$B$1000,MATCH(42,Consolidado!$AC$5:$AC$1000,0)),"") | E55: =IF(OR(D55="",D55=0),"",CHOOSE(MONTH(D55),"Ene","Feb","Mar","Abr","May","Jun","Jul","Ago","Sep","Oct","Nov","Dic")) | F55: =IF(OR(D55="",D55=0),"",YEAR(D55)) | G55: =IF(B55="","",IF(B55=$C$3,"◄ SELECCIONADO",IF(OR(D55="",D55=0,$C$6="",$C$6=0),"Sin fecha",IF(AND(YEAR(D55)=YEAR($C$6),MONTH(D55)=MONTH($C$6)),"MISMO MES",ABS((YEAR(D55)-YEAR($C$6))*12+MONTH(D55)-MONTH($C$6))&" meses "&IF(D55<$C$6,"antes","después"))))) | H55: =IFERROR(INDEX(Consolidado!$F$5:$F$1000,MATCH(42,Consolidado!$AC$5:$AC$1000,0))&"","") | I55: =IFERROR(INDEX(Consolidado!$G$5:$G$1000,MATCH(42,Consolidado!$AC$5:$AC$1000,0))&"","") | J55: =IFERROR(INDEX(Consolidado!$H$5:$H$1000,MATCH(42,Consolidado!$AC$5:$AC$1000,0))&"","")
A56: =IF(B56="","",43) | B56: =IFERROR(INDEX(Consolidado!$A$5:$A$1000,MATCH(43,Consolidado!$AC$5:$AC$1000,0)),"") | C56: =IFERROR(INDEX(Consolidado!$C$5:$C$1000,MATCH(43,Consolidado!$AC$5:$AC$1000,0))&"","") | D56: =IFERROR(INDEX(Consolidado!$B$5:$B$1000,MATCH(43,Consolidado!$AC$5:$AC$1000,0)),"") | E56: =IF(OR(D56="",D56=0),"",CHOOSE(MONTH(D56),"Ene","Feb","Mar","Abr","May","Jun","Jul","Ago","Sep","Oct","Nov","Dic")) | F56: =IF(OR(D56="",D56=0),"",YEAR(D56)) | G56: =IF(B56="","",IF(B56=$C$3,"◄ SELECCIONADO",IF(OR(D56="",D56=0,$C$6="",$C$6=0),"Sin fecha",IF(AND(YEAR(D56)=YEAR($C$6),MONTH(D56)=MONTH($C$6)),"MISMO MES",ABS((YEAR(D56)-YEAR($C$6))*12+MONTH(D56)-MONTH($C$6))&" meses "&IF(D56<$C$6,"antes","después"))))) | H56: =IFERROR(INDEX(Consolidado!$F$5:$F$1000,MATCH(43,Consolidado!$AC$5:$AC$1000,0))&"","") | I56: =IFERROR(INDEX(Consolidado!$G$5:$G$1000,MATCH(43,Consolidado!$AC$5:$AC$1000,0))&"","") | J56: =IFERROR(INDEX(Consolidado!$H$5:$H$1000,MATCH(43,Consolidado!$AC$5:$AC$1000,0))&"","")
A57: =IF(B57="","",44) | B57: =IFERROR(INDEX(Consolidado!$A$5:$A$1000,MATCH(44,Consolidado!$AC$5:$AC$1000,0)),"") | C57: =IFERROR(INDEX(Consolidado!$C$5:$C$1000,MATCH(44,Consolidado!$AC$5:$AC$1000,0))&"","") | D57: =IFERROR(INDEX(Consolidado!$B$5:$B$1000,MATCH(44,Consolidado!$AC$5:$AC$1000,0)),"") | E57: =IF(OR(D57="",D57=0),"",CHOOSE(MONTH(D57),"Ene","Feb","Mar","Abr","May","Jun","Jul","Ago","Sep","Oct","Nov","Dic")) | F57: =IF(OR(D57="",D57=0),"",YEAR(D57)) | G57: =IF(B57="","",IF(B57=$C$3,"◄ SELECCIONADO",IF(OR(D57="",D57=0,$C$6="",$C$6=0),"Sin fecha",IF(AND(YEAR(D57)=YEAR($C$6),MONTH(D57)=MONTH($C$6)),"MISMO MES",ABS((YEAR(D57)-YEAR($C$6))*12+MONTH(D57)-MONTH($C$6))&" meses "&IF(D57<$C$6,"antes","después"))))) | H57: =IFERROR(INDEX(Consolidado!$F$5:$F$1000,MATCH(44,Consolidado!$AC$5:$AC$1000,0))&"","") | I57: =IFERROR(INDEX(Consolidado!$G$5:$G$1000,MATCH(44,Consolidado!$AC$5:$AC$1000,0))&"","") | J57: =IFERROR(INDEX(Consolidado!$H$5:$H$1000,MATCH(44,Consolidado!$AC$5:$AC$1000,0))&"","")
A58: =IF(B58="","",45) | B58: =IFERROR(INDEX(Consolidado!$A$5:$A$1000,MATCH(45,Consolidado!$AC$5:$AC$1000,0)),"") | C58: =IFERROR(INDEX(Consolidado!$C$5:$C$1000,MATCH(45,Consolidado!$AC$5:$AC$1000,0))&"","") | D58: =IFERROR(INDEX(Consolidado!$B$5:$B$1000,MATCH(45,Consolidado!$AC$5:$AC$1000,0)),"") | E58: =IF(OR(D58="",D58=0),"",CHOOSE(MONTH(D58),"Ene","Feb","Mar","Abr","May","Jun","Jul","Ago","Sep","Oct","Nov","Dic")) | F58: =IF(OR(D58="",D58=0),"",YEAR(D58)) | G58: =IF(B58="","",IF(B58=$C$3,"◄ SELECCIONADO",IF(OR(D58="",D58=0,$C$6="",$C$6=0),"Sin fecha",IF(AND(YEAR(D58)=YEAR($C$6),MONTH(D58)=MONTH($C$6)),"MISMO MES",ABS((YEAR(D58)-YEAR($C$6))*12+MONTH(D58)-MONTH($C$6))&" meses "&IF(D58<$C$6,"antes","después"))))) | H58: =IFERROR(INDEX(Consolidado!$F$5:$F$1000,MATCH(45,Consolidado!$AC$5:$AC$1000,0))&"","") | I58: =IFERROR(INDEX(Consolidado!$G$5:$G$1000,MATCH(45,Consolidado!$AC$5:$AC$1000,0))&"","") | J58: =IFERROR(INDEX(Consolidado!$H$5:$H$1000,MATCH(45,Consolidado!$AC$5:$AC$1000,0))&"","")
A59: =IF(B59="","",46) | B59: =IFERROR(INDEX(Consolidado!$A$5:$A$1000,MATCH(46,Consolidado!$AC$5:$AC$1000,0)),"") | C59: =IFERROR(INDEX(Consolidado!$C$5:$C$1000,MATCH(46,Consolidado!$AC$5:$AC$1000,0))&"","") | D59: =IFERROR(INDEX(Consolidado!$B$5:$B$1000,MATCH(46,Consolidado!$AC$5:$AC$1000,0)),"") | E59: =IF(OR(D59="",D59=0),"",CHOOSE(MONTH(D59),"Ene","Feb","Mar","Abr","May","Jun","Jul","Ago","Sep","Oct","Nov","Dic")) | F59: =IF(OR(D59="",D59=0),"",YEAR(D59)) | G59: =IF(B59="","",IF(B59=$C$3,"◄ SELECCIONADO",IF(OR(D59="",D59=0,$C$6="",$C$6=0),"Sin fecha",IF(AND(YEAR(D59)=YEAR($C$6),MONTH(D59)=MONTH($C$6)),"MISMO MES",ABS((YEAR(D59)-YEAR($C$6))*12+MONTH(D59)-MONTH($C$6))&" meses "&IF(D59<$C$6,"antes","después"))))) | H59: =IFERROR(INDEX(Consolidado!$F$5:$F$1000,MATCH(46,Consolidado!$AC$5:$AC$1000,0))&"","") | I59: =IFERROR(INDEX(Consolidado!$G$5:$G$1000,MATCH(46,Consolidado!$AC$5:$AC$1000,0))&"","") | J59: =IFERROR(INDEX(Consolidado!$H$5:$H$1000,MATCH(46,Consolidado!$AC$5:$AC$1000,0))&"","")
A60: =IF(B60="","",47) | B60: =IFERROR(INDEX(Consolidado!$A$5:$A$1000,MATCH(47,Consolidado!$AC$5:$AC$1000,0)),"") | C60: =IFERROR(INDEX(Consolidado!$C$5:$C$1000,MATCH(47,Consolidado!$AC$5:$AC$1000,0))&"","") | D60: =IFERROR(INDEX(Consolidado!$B$5:$B$1000,MATCH(47,Consolidado!$AC$5:$AC$1000,0)),"") | E60: =IF(OR(D60="",D60=0),"",CHOOSE(MONTH(D60),"Ene","Feb","Mar","Abr","May","Jun","Jul","Ago","Sep","Oct","Nov","Dic")) | F60: =IF(OR(D60="",D60=0),"",YEAR(D60)) | G60: =IF(B60="","",IF(B60=$C$3,"◄ SELECCIONADO",IF(OR(D60="",D60=0,$C$6="",$C$6=0),"Sin fecha",IF(AND(YEAR(D60)=YEAR($C$6),MONTH(D60)=MONTH($C$6)),"MISMO MES",ABS((YEAR(D60)-YEAR($C$6))*12+MONTH(D60)-MONTH($C$6))&" meses "&IF(D60<$C$6,"antes","después"))))) | H60: =IFERROR(INDEX(Consolidado!$F$5:$F$1000,MATCH(47,Consolidado!$AC$5:$AC$1000,0))&"","") | I60: =IFERROR(INDEX(Consolidado!$G$5:$G$1000,MATCH(47,Consolidado!$AC$5:$AC$1000,0))&"","") | J60: =IFERROR(INDEX(Consolidado!$H$5:$H$1000,MATCH(47,Consolidado!$AC$5:$AC$1000,0))&"","")
A61: =IF(B61="","",48) | B61: =IFERROR(INDEX(Consolidado!$A$5:$A$1000,MATCH(48,Consolidado!$AC$5:$AC$1000,0)),"") | C61: =IFERROR(INDEX(Consolidado!$C$5:$C$1000,MATCH(48,Consolidado!$AC$5:$AC$1000,0))&"","") | D61: =IFERROR(INDEX(Consolidado!$B$5:$B$1000,MATCH(48,Consolidado!$AC$5:$AC$1000,0)),"") | E61: =IF(OR(D61="",D61=0),"",CHOOSE(MONTH(D61),"Ene","Feb","Mar","Abr","May","Jun","Jul","Ago","Sep","Oct","Nov","Dic")) | F61: =IF(OR(D61="",D61=0),"",YEAR(D61)) | G61: =IF(B61="","",IF(B61=$C$3,"◄ SELECCIONADO",IF(OR(D61="",D61=0,$C$6="",$C$6=0),"Sin fecha",IF(AND(YEAR(D61)=YEAR($C$6),MONTH(D61)=MONTH($C$6)),"MISMO MES",ABS((YEAR(D61)-YEAR($C$6))*12+MONTH(D61)-MONTH($C$6))&" meses "&IF(D61<$C$6,"antes","después"))))) | H61: =IFERROR(INDEX(Consolidado!$F$5:$F$1000,MATCH(48,Consolidado!$AC$5:$AC$1000,0))&"","") | I61: =IFERROR(INDEX(Consolidado!$G$5:$G$1000,MATCH(48,Consolidado!$AC$5:$AC$1000,0))&"","") | J61: =IFERROR(INDEX(Consolidado!$H$5:$H$1000,MATCH(48,Consolidado!$AC$5:$AC$1000,0))&"","")
A62: =IF(B62="","",49) | B62: =IFERROR(INDEX(Consolidado!$A$5:$A$1000,MATCH(49,Consolidado!$AC$5:$AC$1000,0)),"") | C62: =IFERROR(INDEX(Consolidado!$C$5:$C$1000,MATCH(49,Consolidado!$AC$5:$AC$1000,0))&"","") | D62: =IFERROR(INDEX(Consolidado!$B$5:$B$1000,MATCH(49,Consolidado!$AC$5:$AC$1000,0)),"") | E62: =IF(OR(D62="",D62=0),"",CHOOSE(MONTH(D62),"Ene","Feb","Mar","Abr","May","Jun","Jul","Ago","Sep","Oct","Nov","Dic")) | F62: =IF(OR(D62="",D62=0),"",YEAR(D62)) | G62: =IF(B62="","",IF(B62=$C$3,"◄ SELECCIONADO",IF(OR(D62="",D62=0,$C$6="",$C$6=0),"Sin fecha",IF(AND(YEAR(D62)=YEAR($C$6),MONTH(D62)=MONTH($C$6)),"MISMO MES",ABS((YEAR(D62)-YEAR($C$6))*12+MONTH(D62)-MONTH($C$6))&" meses "&IF(D62<$C$6,"antes","después"))))) | H62: =IFERROR(INDEX(Consolidado!$F$5:$F$1000,MATCH(49,Consolidado!$AC$5:$AC$1000,0))&"","") | I62: =IFERROR(INDEX(Consolidado!$G$5:$G$1000,MATCH(49,Consolidado!$AC$5:$AC$1000,0))&"","") | J62: =IFERROR(INDEX(Consolidado!$H$5:$H$1000,MATCH(49,Consolidado!$AC$5:$AC$1000,0))&"","")
A63: =IF(B63="","",50) | B63: =IFERROR(INDEX(Consolidado!$A$5:$A$1000,MATCH(50,Consolidado!$AC$5:$AC$1000,0)),"") | C63: =IFERROR(INDEX(Consolidado!$C$5:$C$1000,MATCH(50,Consolidado!$AC$5:$AC$1000,0))&"","") | D63: =IFERROR(INDEX(Consolidado!$B$5:$B$1000,MATCH(50,Consolidado!$AC$5:$AC$1000,0)),"") | E63: =IF(OR(D63="",D63=0),"",CHOOSE(MONTH(D63),"Ene","Feb","Mar","Abr","May","Jun","Jul","Ago","Sep","Oct","Nov","Dic")) | F63: =IF(OR(D63="",D63=0),"",YEAR(D63)) | G63: =IF(B63="","",IF(B63=$C$3,"◄ SELECCIONADO",IF(OR(D63="",D63=0,$C$6="",$C$6=0),"Sin fecha",IF(AND(YEAR(D63)=YEAR($C$6),MONTH(D63)=MONTH($C$6)),"MISMO MES",ABS((YEAR(D63)-YEAR($C$6))*12+MONTH(D63)-MONTH($C$6))&" meses "&IF(D63<$C$6,"antes","después"))))) | H63: =IFERROR(INDEX(Consolidado!$F$5:$F$1000,MATCH(50,Consolidado!$AC$5:$AC$1000,0))&"","") | I63: =IFERROR(INDEX(Consolidado!$G$5:$G$1000,MATCH(50,Consolidado!$AC$5:$AC$1000,0))&"","") | J63: =IFERROR(INDEX(Consolidado!$H$5:$H$1000,MATCH(50,Consolidado!$AC$5:$AC$1000,0))&"","")
A64: =IF(B64="","",51) | B64: =IFERROR(INDEX(Consolidado!$A$5:$A$1000,MATCH(51,Consolidado!$AC$5:$AC$1000,0)),"") | C64: =IFERROR(INDEX(Consolidado!$C$5:$C$1000,MATCH(51,Consolidado!$AC$5:$AC$1000,0))&"","") | D64: =IFERROR(INDEX(Consolidado!$B$5:$B$1000,MATCH(51,Consolidado!$AC$5:$AC$1000,0)),"") | E64: =IF(OR(D64="",D64=0),"",CHOOSE(MONTH(D64),"Ene","Feb","Mar","Abr","May","Jun","Jul","Ago","Sep","Oct","Nov","Dic")) | F64: =IF(OR(D64="",D64=0),"",YEAR(D64)) | G64: =IF(B64="","",IF(B64=$C$3,"◄ SELECCIONADO",IF(OR(D64="",D64=0,$C$6="",$C$6=0),"Sin fecha",IF(AND(YEAR(D64)=YEAR($C$6),MONTH(D64)=MONTH($C$6)),"MISMO MES",ABS((YEAR(D64)-YEAR($C$6))*12+MONTH(D64)-MONTH($C$6))&" meses "&IF(D64<$C$6,"antes","después"))))) | H64: =IFERROR(INDEX(Consolidado!$F$5:$F$1000,MATCH(51,Consolidado!$AC$5:$AC$1000,0))&"","") | I64: =IFERROR(INDEX(Consolidado!$G$5:$G$1000,MATCH(51,Consolidado!$AC$5:$AC$1000,0))&"","") | J64: =IFERROR(INDEX(Consolidado!$H$5:$H$1000,MATCH(51,Consolidado!$AC$5:$AC$1000,0))&"","")
A65: =IF(B65="","",52) | B65: =IFERROR(INDEX(Consolidado!$A$5:$A$1000,MATCH(52,Consolidado!$AC$5:$AC$1000,0)),"") | C65: =IFERROR(INDEX(Consolidado!$C$5:$C$1000,MATCH(52,Consolidado!$AC$5:$AC$1000,0))&"","") | D65: =IFERROR(INDEX(Consolidado!$B$5:$B$1000,MATCH(52,Consolidado!$AC$5:$AC$1000,0)),"") | E65: =IF(OR(D65="",D65=0),"",CHOOSE(MONTH(D65),"Ene","Feb","Mar","Abr","May","Jun","Jul","Ago","Sep","Oct","Nov","Dic")) | F65: =IF(OR(D65="",D65=0),"",YEAR(D65)) | G65: =IF(B65="","",IF(B65=$C$3,"◄ SELECCIONADO",IF(OR(D65="",D65=0,$C$6="",$C$6=0),"Sin fecha",IF(AND(YEAR(D65)=YEAR($C$6),MONTH(D65)=MONTH($C$6)),"MISMO MES",ABS((YEAR(D65)-YEAR($C$6))*12+MONTH(D65)-MONTH($C$6))&" meses "&IF(D65<$C$6,"antes","después"))))) | H65: =IFERROR(INDEX(Consolidado!$F$5:$F$1000,MATCH(52,Consolidado!$AC$5:$AC$1000,0))&"","") | I65: =IFERROR(INDEX(Consolidado!$G$5:$G$1000,MATCH(52,Consolidado!$AC$5:$AC$1000,0))&"","") | J65: =IFERROR(INDEX(Consolidado!$H$5:$H$1000,MATCH(52,Consolidado!$AC$5:$AC$1000,0))&"","")
A66: =IF(B66="","",53) | B66: =IFERROR(INDEX(Consolidado!$A$5:$A$1000,MATCH(53,Consolidado!$AC$5:$AC$1000,0)),"") | C66: =IFERROR(INDEX(Consolidado!$C$5:$C$1000,MATCH(53,Consolidado!$AC$5:$AC$1000,0))&"","") | D66: =IFERROR(INDEX(Consolidado!$B$5:$B$1000,MATCH(53,Consolidado!$AC$5:$AC$1000,0)),"") | E66: =IF(OR(D66="",D66=0),"",CHOOSE(MONTH(D66),"Ene","Feb","Mar","Abr","May","Jun","Jul","Ago","Sep","Oct","Nov","Dic")) | F66: =IF(OR(D66="",D66=0),"",YEAR(D66)) | G66: =IF(B66="","",IF(B66=$C$3,"◄ SELECCIONADO",IF(OR(D66="",D66=0,$C$6="",$C$6=0),"Sin fecha",IF(AND(YEAR(D66)=YEAR($C$6),MONTH(D66)=MONTH($C$6)),"MISMO MES",ABS((YEAR(D66)-YEAR($C$6))*12+MONTH(D66)-MONTH($C$6))&" meses "&IF(D66<$C$6,"antes","después"))))) | H66: =IFERROR(INDEX(Consolidado!$F$5:$F$1000,MATCH(53,Consolidado!$AC$5:$AC$1000,0))&"","") | I66: =IFERROR(INDEX(Consolidado!$G$5:$G$1000,MATCH(53,Consolidado!$AC$5:$AC$1000,0))&"","") | J66: =IFERROR(INDEX(Consolidado!$H$5:$H$1000,MATCH(53,Consolidado!$AC$5:$AC$1000,0))&"","")
A67: =IF(B67="","",54) | B67: =IFERROR(INDEX(Consolidado!$A$5:$A$1000,MATCH(54,Consolidado!$AC$5:$AC$1000,0)),"") | C67: =IFERROR(INDEX(Consolidado!$C$5:$C$1000,MATCH(54,Consolidado!$AC$5:$AC$1000,0))&"","") | D67: =IFERROR(INDEX(Consolidado!$B$5:$B$1000,MATCH(54,Consolidado!$AC$5:$AC$1000,0)),"") | E67: =IF(OR(D67="",D67=0),"",CHOOSE(MONTH(D67),"Ene","Feb","Mar","Abr","May","Jun","Jul","Ago","Sep","Oct","Nov","Dic")) | F67: =IF(OR(D67="",D67=0),"",YEAR(D67)) | G67: =IF(B67="","",IF(B67=$C$3,"◄ SELECCIONADO",IF(OR(D67="",D67=0,$C$6="",$C$6=0),"Sin fecha",IF(AND(YEAR(D67)=YEAR($C$6),MONTH(D67)=MONTH($C$6)),"MISMO MES",ABS((YEAR(D67)-YEAR($C$6))*12+MONTH(D67)-MONTH($C$6))&" meses "&IF(D67<$C$6,"antes","después"))))) | H67: =IFERROR(INDEX(Consolidado!$F$5:$F$1000,MATCH(54,Consolidado!$AC$5:$AC$1000,0))&"","") | I67: =IFERROR(INDEX(Consolidado!$G$5:$G$1000,MATCH(54,Consolidado!$AC$5:$AC$1000,0))&"","") | J67: =IFERROR(INDEX(Consolidado!$H$5:$H$1000,MATCH(54,Consolidado!$AC$5:$AC$1000,0))&"","")
A68: =IF(B68="","",55) | B68: =IFERROR(INDEX(Consolidado!$A$5:$A$1000,MATCH(55,Consolidado!$AC$5:$AC$1000,0)),"") | C68: =IFERROR(INDEX(Consolidado!$C$5:$C$1000,MATCH(55,Consolidado!$AC$5:$AC$1000,0))&"","") | D68: =IFERROR(INDEX(Consolidado!$B$5:$B$1000,MATCH(55,Consolidado!$AC$5:$AC$1000,0)),"") | E68: =IF(OR(D68="",D68=0),"",CHOOSE(MONTH(D68),"Ene","Feb","Mar","Abr","May","Jun","Jul","Ago","Sep","Oct","Nov","Dic")) | F68: =IF(OR(D68="",D68=0),"",YEAR(D68)) | G68: =IF(B68="","",IF(B68=$C$3,"◄ SELECCIONADO",IF(OR(D68="",D68=0,$C$6="",$C$6=0),"Sin fecha",IF(AND(YEAR(D68)=YEAR($C$6),MONTH(D68)=MONTH($C$6)),"MISMO MES",ABS((YEAR(D68)-YEAR($C$6))*12+MONTH(D68)-MONTH($C$6))&" meses "&IF(D68<$C$6,"antes","después"))))) | H68: =IFERROR(INDEX(Consolidado!$F$5:$F$1000,MATCH(55,Consolidado!$AC$5:$AC$1000,0))&"","") | I68: =IFERROR(INDEX(Consolidado!$G$5:$G$1000,MATCH(55,Consolidado!$AC$5:$AC$1000,0))&"","") | J68: =IFERROR(INDEX(Consolidado!$H$5:$H$1000,MATCH(55,Consolidado!$AC$5:$AC$1000,0))&"","")
A69: =IF(B69="","",56) | B69: =IFERROR(INDEX(Consolidado!$A$5:$A$1000,MATCH(56,Consolidado!$AC$5:$AC$1000,0)),"") | C69: =IFERROR(INDEX(Consolidado!$C$5:$C$1000,MATCH(56,Consolidado!$AC$5:$AC$1000,0))&"","") | D69: =IFERROR(INDEX(Consolidado!$B$5:$B$1000,MATCH(56,Consolidado!$AC$5:$AC$1000,0)),"") | E69: =IF(OR(D69="",D69=0),"",CHOOSE(MONTH(D69),"Ene","Feb","Mar","Abr","May","Jun","Jul","Ago","Sep","Oct","Nov","Dic")) | F69: =IF(OR(D69="",D69=0),"",YEAR(D69)) | G69: =IF(B69="","",IF(B69=$C$3,"◄ SELECCIONADO",IF(OR(D69="",D69=0,$C$6="",$C$6=0),"Sin fecha",IF(AND(YEAR(D69)=YEAR($C$6),MONTH(D69)=MONTH($C$6)),"MISMO MES",ABS((YEAR(D69)-YEAR($C$6))*12+MONTH(D69)-MONTH($C$6))&" meses "&IF(D69<$C$6,"antes","después"))))) | H69: =IFERROR(INDEX(Consolidado!$F$5:$F$1000,MATCH(56,Consolidado!$AC$5:$AC$1000,0))&"","") | I69: =IFERROR(INDEX(Consolidado!$G$5:$G$1000,MATCH(56,Consolidado!$AC$5:$AC$1000,0))&"","") | J69: =IFERROR(INDEX(Consolidado!$H$5:$H$1000,MATCH(56,Consolidado!$AC$5:$AC$1000,0))&"","")
A70: =IF(B70="","",57) | B70: =IFERROR(INDEX(Consolidado!$A$5:$A$1000,MATCH(57,Consolidado!$AC$5:$AC$1000,0)),"") | C70: =IFERROR(INDEX(Consolidado!$C$5:$C$1000,MATCH(57,Consolidado!$AC$5:$AC$1000,0))&"","") | D70: =IFERROR(INDEX(Consolidado!$B$5:$B$1000,MATCH(57,Consolidado!$AC$5:$AC$1000,0)),"") | E70: =IF(OR(D70="",D70=0),"",CHOOSE(MONTH(D70),"Ene","Feb","Mar","Abr","May","Jun","Jul","Ago","Sep","Oct","Nov","Dic")) | F70: =IF(OR(D70="",D70=0),"",YEAR(D70)) | G70: =IF(B70="","",IF(B70=$C$3,"◄ SELECCIONADO",IF(OR(D70="",D70=0,$C$6="",$C$6=0),"Sin fecha",IF(AND(YEAR(D70)=YEAR($C$6),MONTH(D70)=MONTH($C$6)),"MISMO MES",ABS((YEAR(D70)-YEAR($C$6))*12+MONTH(D70)-MONTH($C$6))&" meses "&IF(D70<$C$6,"antes","después"))))) | H70: =IFERROR(INDEX(Consolidado!$F$5:$F$1000,MATCH(57,Consolidado!$AC$5:$AC$1000,0))&"","") | I70: =IFERROR(INDEX(Consolidado!$G$5:$G$1000,MATCH(57,Consolidado!$AC$5:$AC$1000,0))&"","") | J70: =IFERROR(INDEX(Consolidado!$H$5:$H$1000,MATCH(57,Consolidado!$AC$5:$AC$1000,0))&"","")
A71: =IF(B71="","",58) | B71: =IFERROR(INDEX(Consolidado!$A$5:$A$1000,MATCH(58,Consolidado!$AC$5:$AC$1000,0)),"") | C71: =IFERROR(INDEX(Consolidado!$C$5:$C$1000,MATCH(58,Consolidado!$AC$5:$AC$1000,0))&"","") | D71: =IFERROR(INDEX(Consolidado!$B$5:$B$1000,MATCH(58,Consolidado!$AC$5:$AC$1000,0)),"") | E71: =IF(OR(D71="",D71=0),"",CHOOSE(MONTH(D71),"Ene","Feb","Mar","Abr","May","Jun","Jul","Ago","Sep","Oct","Nov","Dic")) | F71: =IF(OR(D71="",D71=0),"",YEAR(D71)) | G71: =IF(B71="","",IF(B71=$C$3,"◄ SELECCIONADO",IF(OR(D71="",D71=0,$C$6="",$C$6=0),"Sin fecha",IF(AND(YEAR(D71)=YEAR($C$6),MONTH(D71)=MONTH($C$6)),"MISMO MES",ABS((YEAR(D71)-YEAR($C$6))*12+MONTH(D71)-MONTH($C$6))&" meses "&IF(D71<$C$6,"antes","después"))))) | H71: =IFERROR(INDEX(Consolidado!$F$5:$F$1000,MATCH(58,Consolidado!$AC$5:$AC$1000,0))&"","") | I71: =IFERROR(INDEX(Consolidado!$G$5:$G$1000,MATCH(58,Consolidado!$AC$5:$AC$1000,0))&"","") | J71: =IFERROR(INDEX(Consolidado!$H$5:$H$1000,MATCH(58,Consolidado!$AC$5:$AC$1000,0))&"","")
A72: =IF(B72="","",59) | B72: =IFERROR(INDEX(Consolidado!$A$5:$A$1000,MATCH(59,Consolidado!$AC$5:$AC$1000,0)),"") | C72: =IFERROR(INDEX(Consolidado!$C$5:$C$1000,MATCH(59,Consolidado!$AC$5:$AC$1000,0))&"","") | D72: =IFERROR(INDEX(Consolidado!$B$5:$B$1000,MATCH(59,Consolidado!$AC$5:$AC$1000,0)),"") | E72: =IF(OR(D72="",D72=0),"",CHOOSE(MONTH(D72),"Ene","Feb","Mar","Abr","May","Jun","Jul","Ago","Sep","Oct","Nov","Dic")) | F72: =IF(OR(D72="",D72=0),"",YEAR(D72)) | G72: =IF(B72="","",IF(B72=$C$3,"◄ SELECCIONADO",IF(OR(D72="",D72=0,$C$6="",$C$6=0),"Sin fecha",IF(AND(YEAR(D72)=YEAR($C$6),MONTH(D72)=MONTH($C$6)),"MISMO MES",ABS((YEAR(D72)-YEAR($C$6))*12+MONTH(D72)-MONTH($C$6))&" meses "&IF(D72<$C$6,"antes","después"))))) | H72: =IFERROR(INDEX(Consolidado!$F$5:$F$1000,MATCH(59,Consolidado!$AC$5:$AC$1000,0))&"","") | I72: =IFERROR(INDEX(Consolidado!$G$5:$G$1000,MATCH(59,Consolidado!$AC$5:$AC$1000,0))&"","") | J72: =IFERROR(INDEX(Consolidado!$H$5:$H$1000,MATCH(59,Consolidado!$AC$5:$AC$1000,0))&"","")
A73: =IF(B73="","",60) | B73: =IFERROR(INDEX(Consolidado!$A$5:$A$1000,MATCH(60,Consolidado!$AC$5:$AC$1000,0)),"") | C73: =IFERROR(INDEX(Consolidado!$C$5:$C$1000,MATCH(60,Consolidado!$AC$5:$AC$1000,0))&"","") | D73: =IFERROR(INDEX(Consolidado!$B$5:$B$1000,MATCH(60,Consolidado!$AC$5:$AC$1000,0)),"") | E73: =IF(OR(D73="",D73=0),"",CHOOSE(MONTH(D73),"Ene","Feb","Mar","Abr","May","Jun","Jul","Ago","Sep","Oct","Nov","Dic")) | F73: =IF(OR(D73="",D73=0),"",YEAR(D73)) | G73: =IF(B73="","",IF(B73=$C$3,"◄ SELECCIONADO",IF(OR(D73="",D73=0,$C$6="",$C$6=0),"Sin fecha",IF(AND(YEAR(D73)=YEAR($C$6),MONTH(D73)=MONTH($C$6)),"MISMO MES",ABS((YEAR(D73)-YEAR($C$6))*12+MONTH(D73)-MONTH($C$6))&" meses "&IF(D73<$C$6,"antes","después"))))) | H73: =IFERROR(INDEX(Consolidado!$F$5:$F$1000,MATCH(60,Consolidado!$AC$5:$AC$1000,0))&"","") | I73: =IFERROR(INDEX(Consolidado!$G$5:$G$1000,MATCH(60,Consolidado!$AC$5:$AC$1000,0))&"","") | J73: =IFERROR(INDEX(Consolidado!$H$5:$H$1000,MATCH(60,Consolidado!$AC$5:$AC$1000,0))&"","")
A74: =IF(B74="","",61) | B74: =IFERROR(INDEX(Consolidado!$A$5:$A$1000,MATCH(61,Consolidado!$AC$5:$AC$1000,0)),"") | C74: =IFERROR(INDEX(Consolidado!$C$5:$C$1000,MATCH(61,Consolidado!$AC$5:$AC$1000,0))&"","") | D74: =IFERROR(INDEX(Consolidado!$B$5:$B$1000,MATCH(61,Consolidado!$AC$5:$AC$1000,0)),"") | E74: =IF(OR(D74="",D74=0),"",CHOOSE(MONTH(D74),"Ene","Feb","Mar","Abr","May","Jun","Jul","Ago","Sep","Oct","Nov","Dic")) | F74: =IF(OR(D74="",D74=0),"",YEAR(D74)) | G74: =IF(B74="","",IF(B74=$C$3,"◄ SELECCIONADO",IF(OR(D74="",D74=0,$C$6="",$C$6=0),"Sin fecha",IF(AND(YEAR(D74)=YEAR($C$6),MONTH(D74)=MONTH($C$6)),"MISMO MES",ABS((YEAR(D74)-YEAR($C$6))*12+MONTH(D74)-MONTH($C$6))&" meses "&IF(D74<$C$6,"antes","después"))))) | H74: =IFERROR(INDEX(Consolidado!$F$5:$F$1000,MATCH(61,Consolidado!$AC$5:$AC$1000,0))&"","") | I74: =IFERROR(INDEX(Consolidado!$G$5:$G$1000,MATCH(61,Consolidado!$AC$5:$AC$1000,0))&"","") | J74: =IFERROR(INDEX(Consolidado!$H$5:$H$1000,MATCH(61,Consolidado!$AC$5:$AC$1000,0))&"","")
A75: =IF(B75="","",62) | B75: =IFERROR(INDEX(Consolidado!$A$5:$A$1000,MATCH(62,Consolidado!$AC$5:$AC$1000,0)),"") | C75: =IFERROR(INDEX(Consolidado!$C$5:$C$1000,MATCH(62,Consolidado!$AC$5:$AC$1000,0))&"","") | D75: =IFERROR(INDEX(Consolidado!$B$5:$B$1000,MATCH(62,Consolidado!$AC$5:$AC$1000,0)),"") | E75: =IF(OR(D75="",D75=0),"",CHOOSE(MONTH(D75),"Ene","Feb","Mar","Abr","May","Jun","Jul","Ago","Sep","Oct","Nov","Dic")) | F75: =IF(OR(D75="",D75=0),"",YEAR(D75)) | G75: =IF(B75="","",IF(B75=$C$3,"◄ SELECCIONADO",IF(OR(D75="",D75=0,$C$6="",$C$6=0),"Sin fecha",IF(AND(YEAR(D75)=YEAR($C$6),MONTH(D75)=MONTH($C$6)),"MISMO MES",ABS((YEAR(D75)-YEAR($C$6))*12+MONTH(D75)-MONTH($C$6))&" meses "&IF(D75<$C$6,"antes","después"))))) | H75: =IFERROR(INDEX(Consolidado!$F$5:$F$1000,MATCH(62,Consolidado!$AC$5:$AC$1000,0))&"","") | I75: =IFERROR(INDEX(Consolidado!$G$5:$G$1000,MATCH(62,Consolidado!$AC$5:$AC$1000,0))&"","") | J75: =IFERROR(INDEX(Consolidado!$H$5:$H$1000,MATCH(62,Consolidado!$AC$5:$AC$1000,0))&"","")
A76: =IF(B76="","",63) | B76: =IFERROR(INDEX(Consolidado!$A$5:$A$1000,MATCH(63,Consolidado!$AC$5:$AC$1000,0)),"") | C76: =IFERROR(INDEX(Consolidado!$C$5:$C$1000,MATCH(63,Consolidado!$AC$5:$AC$1000,0))&"","") | D76: =IFERROR(INDEX(Consolidado!$B$5:$B$1000,MATCH(63,Consolidado!$AC$5:$AC$1000,0)),"") | E76: =IF(OR(D76="",D76=0),"",CHOOSE(MONTH(D76),"Ene","Feb","Mar","Abr","May","Jun","Jul","Ago","Sep","Oct","Nov","Dic")) | F76: =IF(OR(D76="",D76=0),"",YEAR(D76)) | G76: =IF(B76="","",IF(B76=$C$3,"◄ SELECCIONADO",IF(OR(D76="",D76=0,$C$6="",$C$6=0),"Sin fecha",IF(AND(YEAR(D76)=YEAR($C$6),MONTH(D76)=MONTH($C$6)),"MISMO MES",ABS((YEAR(D76)-YEAR($C$6))*12+MONTH(D76)-MONTH($C$6))&" meses "&IF(D76<$C$6,"antes","después"))))) | H76: =IFERROR(INDEX(Consolidado!$F$5:$F$1000,MATCH(63,Consolidado!$AC$5:$AC$1000,0))&"","") | I76: =IFERROR(INDEX(Consolidado!$G$5:$G$1000,MATCH(63,Consolidado!$AC$5:$AC$1000,0))&"","") | J76: =IFERROR(INDEX(Consolidado!$H$5:$H$1000,MATCH(63,Consolidado!$AC$5:$AC$1000,0))&"","")
A77: =IF(B77="","",64) | B77: =IFERROR(INDEX(Consolidado!$A$5:$A$1000,MATCH(64,Consolidado!$AC$5:$AC$1000,0)),"") | C77: =IFERROR(INDEX(Consolidado!$C$5:$C$1000,MATCH(64,Consolidado!$AC$5:$AC$1000,0))&"","") | D77: =IFERROR(INDEX(Consolidado!$B$5:$B$1000,MATCH(64,Consolidado!$AC$5:$AC$1000,0)),"") | E77: =IF(OR(D77="",D77=0),"",CHOOSE(MONTH(D77),"Ene","Feb","Mar","Abr","May","Jun","Jul","Ago","Sep","Oct","Nov","Dic")) | F77: =IF(OR(D77="",D77=0),"",YEAR(D77)) | G77: =IF(B77="","",IF(B77=$C$3,"◄ SELECCIONADO",IF(OR(D77="",D77=0,$C$6="",$C$6=0),"Sin fecha",IF(AND(YEAR(D77)=YEAR($C$6),MONTH(D77)=MONTH($C$6)),"MISMO MES",ABS((YEAR(D77)-YEAR($C$6))*12+MONTH(D77)-MONTH($C$6))&" meses "&IF(D77<$C$6,"antes","después"))))) | H77: =IFERROR(INDEX(Consolidado!$F$5:$F$1000,MATCH(64,Consolidado!$AC$5:$AC$1000,0))&"","") | I77: =IFERROR(INDEX(Consolidado!$G$5:$G$1000,MATCH(64,Consolidado!$AC$5:$AC$1000,0))&"","") | J77: =IFERROR(INDEX(Consolidado!$H$5:$H$1000,MATCH(64,Consolidado!$AC$5:$AC$1000,0))&"","")
A78: =IF(B78="","",65) | B78: =IFERROR(INDEX(Consolidado!$A$5:$A$1000,MATCH(65,Consolidado!$AC$5:$AC$1000,0)),"") | C78: =IFERROR(INDEX(Consolidado!$C$5:$C$1000,MATCH(65,Consolidado!$AC$5:$AC$1000,0))&"","") | D78: =IFERROR(INDEX(Consolidado!$B$5:$B$1000,MATCH(65,Consolidado!$AC$5:$AC$1000,0)),"") | E78: =IF(OR(D78="",D78=0),"",CHOOSE(MONTH(D78),"Ene","Feb","Mar","Abr","May","Jun","Jul","Ago","Sep","Oct","Nov","Dic")) | F78: =IF(OR(D78="",D78=0),"",YEAR(D78)) | G78: =IF(B78="","",IF(B78=$C$3,"◄ SELECCIONADO",IF(OR(D78="",D78=0,$C$6="",$C$6=0),"Sin fecha",IF(AND(YEAR(D78)=YEAR($C$6),MONTH(D78)=MONTH($C$6)),"MISMO MES",ABS((YEAR(D78)-YEAR($C$6))*12+MONTH(D78)-MONTH($C$6))&" meses "&IF(D78<$C$6,"antes","después"))))) | H78: =IFERROR(INDEX(Consolidado!$F$5:$F$1000,MATCH(65,Consolidado!$AC$5:$AC$1000,0))&"","") | I78: =IFERROR(INDEX(Consolidado!$G$5:$G$1000,MATCH(65,Consolidado!$AC$5:$AC$1000,0))&"","") | J78: =IFERROR(INDEX(Consolidado!$H$5:$H$1000,MATCH(65,Consolidado!$AC$5:$AC$1000,0))&"","")
A79: =IF(B79="","",66) | B79: =IFERROR(INDEX(Consolidado!$A$5:$A$1000,MATCH(66,Consolidado!$AC$5:$AC$1000,0)),"") | C79: =IFERROR(INDEX(Consolidado!$C$5:$C$1000,MATCH(66,Consolidado!$AC$5:$AC$1000,0))&"","") | D79: =IFERROR(INDEX(Consolidado!$B$5:$B$1000,MATCH(66,Consolidado!$AC$5:$AC$1000,0)),"") | E79: =IF(OR(D79="",D79=0),"",CHOOSE(MONTH(D79),"Ene","Feb","Mar","Abr","May","Jun","Jul","Ago","Sep","Oct","Nov","Dic")) | F79: =IF(OR(D79="",D79=0),"",YEAR(D79)) | G79: =IF(B79="","",IF(B79=$C$3,"◄ SELECCIONADO",IF(OR(D79="",D79=0,$C$6="",$C$6=0),"Sin fecha",IF(AND(YEAR(D79)=YEAR($C$6),MONTH(D79)=MONTH($C$6)),"MISMO MES",ABS((YEAR(D79)-YEAR($C$6))*12+MONTH(D79)-MONTH($C$6))&" meses "&IF(D79<$C$6,"antes","después"))))) | H79: =IFERROR(INDEX(Consolidado!$F$5:$F$1000,MATCH(66,Consolidado!$AC$5:$AC$1000,0))&"","") | I79: =IFERROR(INDEX(Consolidado!$G$5:$G$1000,MATCH(66,Consolidado!$AC$5:$AC$1000,0))&"","") | J79: =IFERROR(INDEX(Consolidado!$H$5:$H$1000,MATCH(66,Consolidado!$AC$5:$AC$1000,0))&"","")
A80: =IF(B80="","",67) | B80: =IFERROR(INDEX(Consolidado!$A$5:$A$1000,MATCH(67,Consolidado!$AC$5:$AC$1000,0)),"") | C80: =IFERROR(INDEX(Consolidado!$C$5:$C$1000,MATCH(67,Consolidado!$AC$5:$AC$1000,0))&"","") | D80: =IFERROR(INDEX(Consolidado!$B$5:$B$1000,MATCH(67,Consolidado!$AC$5:$AC$1000,0)),"") | E80: =IF(OR(D80="",D80=0),"",CHOOSE(MONTH(D80),"Ene","Feb","Mar","Abr","May","Jun","Jul","Ago","Sep","Oct","Nov","Dic")) | F80: =IF(OR(D80="",D80=0),"",YEAR(D80)) | G80: =IF(B80="","",IF(B80=$C$3,"◄ SELECCIONADO",IF(OR(D80="",D80=0,$C$6="",$C$6=0),"Sin fecha",IF(AND(YEAR(D80)=YEAR($C$6),MONTH(D80)=MONTH($C$6)),"MISMO MES",ABS((YEAR(D80)-YEAR($C$6))*12+MONTH(D80)-MONTH($C$6))&" meses "&IF(D80<$C$6,"antes","después"))))) | H80: =IFERROR(INDEX(Consolidado!$F$5:$F$1000,MATCH(67,Consolidado!$AC$5:$AC$1000,0))&"","") | I80: =IFERROR(INDEX(Consolidado!$G$5:$G$1000,MATCH(67,Consolidado!$AC$5:$AC$1000,0))&"","") | J80: =IFERROR(INDEX(Consolidado!$H$5:$H$1000,MATCH(67,Consolidado!$AC$5:$AC$1000,0))&"","")
A81: =IF(B81="","",68) | B81: =IFERROR(INDEX(Consolidado!$A$5:$A$1000,MATCH(68,Consolidado!$AC$5:$AC$1000,0)),"") | C81: =IFERROR(INDEX(Consolidado!$C$5:$C$1000,MATCH(68,Consolidado!$AC$5:$AC$1000,0))&"","") | D81: =IFERROR(INDEX(Consolidado!$B$5:$B$1000,MATCH(68,Consolidado!$AC$5:$AC$1000,0)),"") | E81: =IF(OR(D81="",D81=0),"",CHOOSE(MONTH(D81),"Ene","Feb","Mar","Abr","May","Jun","Jul","Ago","Sep","Oct","Nov","Dic")) | F81: =IF(OR(D81="",D81=0),"",YEAR(D81)) | G81: =IF(B81="","",IF(B81=$C$3,"◄ SELECCIONADO",IF(OR(D81="",D81=0,$C$6="",$C$6=0),"Sin fecha",IF(AND(YEAR(D81)=YEAR($C$6),MONTH(D81)=MONTH($C$6)),"MISMO MES",ABS((YEAR(D81)-YEAR($C$6))*12+MONTH(D81)-MONTH($C$6))&" meses "&IF(D81<$C$6,"antes","después"))))) | H81: =IFERROR(INDEX(Consolidado!$F$5:$F$1000,MATCH(68,Consolidado!$AC$5:$AC$1000,0))&"","") | I81: =IFERROR(INDEX(Consolidado!$G$5:$G$1000,MATCH(68,Consolidado!$AC$5:$AC$1000,0))&"","") | J81: =IFERROR(INDEX(Consolidado!$H$5:$H$1000,MATCH(68,Consolidado!$AC$5:$AC$1000,0))&"","")
A82: =IF(B82="","",69) | B82: =IFERROR(INDEX(Consolidado!$A$5:$A$1000,MATCH(69,Consolidado!$AC$5:$AC$1000,0)),"") | C82: =IFERROR(INDEX(Consolidado!$C$5:$C$1000,MATCH(69,Consolidado!$AC$5:$AC$1000,0))&"","") | D82: =IFERROR(INDEX(Consolidado!$B$5:$B$1000,MATCH(69,Consolidado!$AC$5:$AC$1000,0)),"") | E82: =IF(OR(D82="",D82=0),"",CHOOSE(MONTH(D82),"Ene","Feb","Mar","Abr","May","Jun","Jul","Ago","Sep","Oct","Nov","Dic")) | F82: =IF(OR(D82="",D82=0),"",YEAR(D82)) | G82: =IF(B82="","",IF(B82=$C$3,"◄ SELECCIONADO",IF(OR(D82="",D82=0,$C$6="",$C$6=0),"Sin fecha",IF(AND(YEAR(D82)=YEAR($C$6),MONTH(D82)=MONTH($C$6)),"MISMO MES",ABS((YEAR(D82)-YEAR($C$6))*12+MONTH(D82)-MONTH($C$6))&" meses "&IF(D82<$C$6,"antes","después"))))) | H82: =IFERROR(INDEX(Consolidado!$F$5:$F$1000,MATCH(69,Consolidado!$AC$5:$AC$1000,0))&"","") | I82: =IFERROR(INDEX(Consolidado!$G$5:$G$1000,MATCH(69,Consolidado!$AC$5:$AC$1000,0))&"","") | J82: =IFERROR(INDEX(Consolidado!$H$5:$H$1000,MATCH(69,Consolidado!$AC$5:$AC$1000,0))&"","")
A83: =IF(B83="","",70) | B83: =IFERROR(INDEX(Consolidado!$A$5:$A$1000,MATCH(70,Consolidado!$AC$5:$AC$1000,0)),"") | C83: =IFERROR(INDEX(Consolidado!$C$5:$C$1000,MATCH(70,Consolidado!$AC$5:$AC$1000,0))&"","") | D83: =IFERROR(INDEX(Consolidado!$B$5:$B$1000,MATCH(70,Consolidado!$AC$5:$AC$1000,0)),"") | E83: =IF(OR(D83="",D83=0),"",CHOOSE(MONTH(D83),"Ene","Feb","Mar","Abr","May","Jun","Jul","Ago","Sep","Oct","Nov","Dic")) | F83: =IF(OR(D83="",D83=0),"",YEAR(D83)) | G83: =IF(B83="","",IF(B83=$C$3,"◄ SELECCIONADO",IF(OR(D83="",D83=0,$C$6="",$C$6=0),"Sin fecha",IF(AND(YEAR(D83)=YEAR($C$6),MONTH(D83)=MONTH($C$6)),"MISMO MES",ABS((YEAR(D83)-YEAR($C$6))*12+MONTH(D83)-MONTH($C$6))&" meses "&IF(D83<$C$6,"antes","después"))))) | H83: =IFERROR(INDEX(Consolidado!$F$5:$F$1000,MATCH(70,Consolidado!$AC$5:$AC$1000,0))&"","") | I83: =IFERROR(INDEX(Consolidado!$G$5:$G$1000,MATCH(70,Consolidado!$AC$5:$AC$1000,0))&"","") | J83: =IFERROR(INDEX(Consolidado!$H$5:$H$1000,MATCH(70,Consolidado!$AC$5:$AC$1000,0))&"","")
A84: =IF(B84="","",71) | B84: =IFERROR(INDEX(Consolidado!$A$5:$A$1000,MATCH(71,Consolidado!$AC$5:$AC$1000,0)),"") | C84: =IFERROR(INDEX(Consolidado!$C$5:$C$1000,MATCH(71,Consolidado!$AC$5:$AC$1000,0))&"","") | D84: =IFERROR(INDEX(Consolidado!$B$5:$B$1000,MATCH(71,Consolidado!$AC$5:$AC$1000,0)),"") | E84: =IF(OR(D84="",D84=0),"",CHOOSE(MONTH(D84),"Ene","Feb","Mar","Abr","May","Jun","Jul","Ago","Sep","Oct","Nov","Dic")) | F84: =IF(OR(D84="",D84=0),"",YEAR(D84)) | G84: =IF(B84="","",IF(B84=$C$3,"◄ SELECCIONADO",IF(OR(D84="",D84=0,$C$6="",$C$6=0),"Sin fecha",IF(AND(YEAR(D84)=YEAR($C$6),MONTH(D84)=MONTH($C$6)),"MISMO MES",ABS((YEAR(D84)-YEAR($C$6))*12+MONTH(D84)-MONTH($C$6))&" meses "&IF(D84<$C$6,"antes","después"))))) | H84: =IFERROR(INDEX(Consolidado!$F$5:$F$1000,MATCH(71,Consolidado!$AC$5:$AC$1000,0))&"","") | I84: =IFERROR(INDEX(Consolidado!$G$5:$G$1000,MATCH(71,Consolidado!$AC$5:$AC$1000,0))&"","") | J84: =IFERROR(INDEX(Consolidado!$H$5:$H$1000,MATCH(71,Consolidado!$AC$5:$AC$1000,0))&"","")
A85: =IF(B85="","",72) | B85: =IFERROR(INDEX(Consolidado!$A$5:$A$1000,MATCH(72,Consolidado!$AC$5:$AC$1000,0)),"") | C85: =IFERROR(INDEX(Consolidado!$C$5:$C$1000,MATCH(72,Consolidado!$AC$5:$AC$1000,0))&"","") | D85: =IFERROR(INDEX(Consolidado!$B$5:$B$1000,MATCH(72,Consolidado!$AC$5:$AC$1000,0)),"") | E85: =IF(OR(D85="",D85=0),"",CHOOSE(MONTH(D85),"Ene","Feb","Mar","Abr","May","Jun","Jul","Ago","Sep","Oct","Nov","Dic")) | F85: =IF(OR(D85="",D85=0),"",YEAR(D85)) | G85: =IF(B85="","",IF(B85=$C$3,"◄ SELECCIONADO",IF(OR(D85="",D85=0,$C$6="",$C$6=0),"Sin fecha",IF(AND(YEAR(D85)=YEAR($C$6),MONTH(D85)=MONTH($C$6)),"MISMO MES",ABS((YEAR(D85)-YEAR($C$6))*12+MONTH(D85)-MONTH($C$6))&" meses "&IF(D85<$C$6,"antes","después"))))) | H85: =IFERROR(INDEX(Consolidado!$F$5:$F$1000,MATCH(72,Consolidado!$AC$5:$AC$1000,0))&"","") | I85: =IFERROR(INDEX(Consolidado!$G$5:$G$1000,MATCH(72,Consolidado!$AC$5:$AC$1000,0))&"","") | J85: =IFERROR(INDEX(Consolidado!$H$5:$H$1000,MATCH(72,Consolidado!$AC$5:$AC$1000,0))&"","")
A86: =IF(B86="","",73) | B86: =IFERROR(INDEX(Consolidado!$A$5:$A$1000,MATCH(73,Consolidado!$AC$5:$AC$1000,0)),"") | C86: =IFERROR(INDEX(Consolidado!$C$5:$C$1000,MATCH(73,Consolidado!$AC$5:$AC$1000,0))&"","") | D86: =IFERROR(INDEX(Consolidado!$B$5:$B$1000,MATCH(73,Consolidado!$AC$5:$AC$1000,0)),"") | E86: =IF(OR(D86="",D86=0),"",CHOOSE(MONTH(D86),"Ene","Feb","Mar","Abr","May","Jun","Jul","Ago","Sep","Oct","Nov","Dic")) | F86: =IF(OR(D86="",D86=0),"",YEAR(D86)) | G86: =IF(B86="","",IF(B86=$C$3,"◄ SELECCIONADO",IF(OR(D86="",D86=0,$C$6="",$C$6=0),"Sin fecha",IF(AND(YEAR(D86)=YEAR($C$6),MONTH(D86)=MONTH($C$6)),"MISMO MES",ABS((YEAR(D86)-YEAR($C$6))*12+MONTH(D86)-MONTH($C$6))&" meses "&IF(D86<$C$6,"antes","después"))))) | H86: =IFERROR(INDEX(Consolidado!$F$5:$F$1000,MATCH(73,Consolidado!$AC$5:$AC$1000,0))&"","") | I86: =IFERROR(INDEX(Consolidado!$G$5:$G$1000,MATCH(73,Consolidado!$AC$5:$AC$1000,0))&"","") | J86: =IFERROR(INDEX(Consolidado!$H$5:$H$1000,MATCH(73,Consolidado!$AC$5:$AC$1000,0))&"","")
A87: =IF(B87="","",74) | B87: =IFERROR(INDEX(Consolidado!$A$5:$A$1000,MATCH(74,Consolidado!$AC$5:$AC$1000,0)),"") | C87: =IFERROR(INDEX(Consolidado!$C$5:$C$1000,MATCH(74,Consolidado!$AC$5:$AC$1000,0))&"","") | D87: =IFERROR(INDEX(Consolidado!$B$5:$B$1000,MATCH(74,Consolidado!$AC$5:$AC$1000,0)),"") | E87: =IF(OR(D87="",D87=0),"",CHOOSE(MONTH(D87),"Ene","Feb","Mar","Abr","May","Jun","Jul","Ago","Sep","Oct","Nov","Dic")) | F87: =IF(OR(D87="",D87=0),"",YEAR(D87)) | G87: =IF(B87="","",IF(B87=$C$3,"◄ SELECCIONADO",IF(OR(D87="",D87=0,$C$6="",$C$6=0),"Sin fecha",IF(AND(YEAR(D87)=YEAR($C$6),MONTH(D87)=MONTH($C$6)),"MISMO MES",ABS((YEAR(D87)-YEAR($C$6))*12+MONTH(D87)-MONTH($C$6))&" meses "&IF(D87<$C$6,"antes","después"))))) | H87: =IFERROR(INDEX(Consolidado!$F$5:$F$1000,MATCH(74,Consolidado!$AC$5:$AC$1000,0))&"","") | I87: =IFERROR(INDEX(Consolidado!$G$5:$G$1000,MATCH(74,Consolidado!$AC$5:$AC$1000,0))&"","") | J87: =IFERROR(INDEX(Consolidado!$H$5:$H$1000,MATCH(74,Consolidado!$AC$5:$AC$1000,0))&"","")
A88: =IF(B88="","",75) | B88: =IFERROR(INDEX(Consolidado!$A$5:$A$1000,MATCH(75,Consolidado!$AC$5:$AC$1000,0)),"") | C88: =IFERROR(INDEX(Consolidado!$C$5:$C$1000,MATCH(75,Consolidado!$AC$5:$AC$1000,0))&"","") | D88: =IFERROR(INDEX(Consolidado!$B$5:$B$1000,MATCH(75,Consolidado!$AC$5:$AC$1000,0)),"") | E88: =IF(OR(D88="",D88=0),"",CHOOSE(MONTH(D88),"Ene","Feb","Mar","Abr","May","Jun","Jul","Ago","Sep","Oct","Nov","Dic")) | F88: =IF(OR(D88="",D88=0),"",YEAR(D88)) | G88: =IF(B88="","",IF(B88=$C$3,"◄ SELECCIONADO",IF(OR(D88="",D88=0,$C$6="",$C$6=0),"Sin fecha",IF(AND(YEAR(D88)=YEAR($C$6),MONTH(D88)=MONTH($C$6)),"MISMO MES",ABS((YEAR(D88)-YEAR($C$6))*12+MONTH(D88)-MONTH($C$6))&" meses "&IF(D88<$C$6,"antes","después"))))) | H88: =IFERROR(INDEX(Consolidado!$F$5:$F$1000,MATCH(75,Consolidado!$AC$5:$AC$1000,0))&"","") | I88: =IFERROR(INDEX(Consolidado!$G$5:$G$1000,MATCH(75,Consolidado!$AC$5:$AC$1000,0))&"","") | J88: =IFERROR(INDEX(Consolidado!$H$5:$H$1000,MATCH(75,Consolidado!$AC$5:$AC$1000,0))&"","")
A89: =IF(B89="","",76) | B89: =IFERROR(INDEX(Consolidado!$A$5:$A$1000,MATCH(76,Consolidado!$AC$5:$AC$1000,0)),"") | C89: =IFERROR(INDEX(Consolidado!$C$5:$C$1000,MATCH(76,Consolidado!$AC$5:$AC$1000,0))&"","") | D89: =IFERROR(INDEX(Consolidado!$B$5:$B$1000,MATCH(76,Consolidado!$AC$5:$AC$1000,0)),"") | E89: =IF(OR(D89="",D89=0),"",CHOOSE(MONTH(D89),"Ene","Feb","Mar","Abr","May","Jun","Jul","Ago","Sep","Oct","Nov","Dic")) | F89: =IF(OR(D89="",D89=0),"",YEAR(D89)) | G89: =IF(B89="","",IF(B89=$C$3,"◄ SELECCIONADO",IF(OR(D89="",D89=0,$C$6="",$C$6=0),"Sin fecha",IF(AND(YEAR(D89)=YEAR($C$6),MONTH(D89)=MONTH($C$6)),"MISMO MES",ABS((YEAR(D89)-YEAR($C$6))*12+MONTH(D89)-MONTH($C$6))&" meses "&IF(D89<$C$6,"antes","después"))))) | H89: =IFERROR(INDEX(Consolidado!$F$5:$F$1000,MATCH(76,Consolidado!$AC$5:$AC$1000,0))&"","") | I89: =IFERROR(INDEX(Consolidado!$G$5:$G$1000,MATCH(76,Consolidado!$AC$5:$AC$1000,0))&"","") | J89: =IFERROR(INDEX(Consolidado!$H$5:$H$1000,MATCH(76,Consolidado!$AC$5:$AC$1000,0))&"","")
A90: =IF(B90="","",77) | B90: =IFERROR(INDEX(Consolidado!$A$5:$A$1000,MATCH(77,Consolidado!$AC$5:$AC$1000,0)),"") | C90: =IFERROR(INDEX(Consolidado!$C$5:$C$1000,MATCH(77,Consolidado!$AC$5:$AC$1000,0))&"","") | D90: =IFERROR(INDEX(Consolidado!$B$5:$B$1000,MATCH(77,Consolidado!$AC$5:$AC$1000,0)),"") | E90: =IF(OR(D90="",D90=0),"",CHOOSE(MONTH(D90),"Ene","Feb","Mar","Abr","May","Jun","Jul","Ago","Sep","Oct","Nov","Dic")) | F90: =IF(OR(D90="",D90=0),"",YEAR(D90)) | G90: =IF(B90="","",IF(B90=$C$3,"◄ SELECCIONADO",IF(OR(D90="",D90=0,$C$6="",$C$6=0),"Sin fecha",IF(AND(YEAR(D90)=YEAR($C$6),MONTH(D90)=MONTH($C$6)),"MISMO MES",ABS((YEAR(D90)-YEAR($C$6))*12+MONTH(D90)-MONTH($C$6))&" meses "&IF(D90<$C$6,"antes","después"))))) | H90: =IFERROR(INDEX(Consolidado!$F$5:$F$1000,MATCH(77,Consolidado!$AC$5:$AC$1000,0))&"","") | I90: =IFERROR(INDEX(Consolidado!$G$5:$G$1000,MATCH(77,Consolidado!$AC$5:$AC$1000,0))&"","") | J90: =IFERROR(INDEX(Consolidado!$H$5:$H$1000,MATCH(77,Consolidado!$AC$5:$AC$1000,0))&"","")
A91: =IF(B91="","",78) | B91: =IFERROR(INDEX(Consolidado!$A$5:$A$1000,MATCH(78,Consolidado!$AC$5:$AC$1000,0)),"") | C91: =IFERROR(INDEX(Consolidado!$C$5:$C$1000,MATCH(78,Consolidado!$AC$5:$AC$1000,0))&"","") | D91: =IFERROR(INDEX(Consolidado!$B$5:$B$1000,MATCH(78,Consolidado!$AC$5:$AC$1000,0)),"") | E91: =IF(OR(D91="",D91=0),"",CHOOSE(MONTH(D91),"Ene","Feb","Mar","Abr","May","Jun","Jul","Ago","Sep","Oct","Nov","Dic")) | F91: =IF(OR(D91="",D91=0),"",YEAR(D91)) | G91: =IF(B91="","",IF(B91=$C$3,"◄ SELECCIONADO",IF(OR(D91="",D91=0,$C$6="",$C$6=0),"Sin fecha",IF(AND(YEAR(D91)=YEAR($C$6),MONTH(D91)=MONTH($C$6)),"MISMO MES",ABS((YEAR(D91)-YEAR($C$6))*12+MONTH(D91)-MONTH($C$6))&" meses "&IF(D91<$C$6,"antes","después"))))) | H91: =IFERROR(INDEX(Consolidado!$F$5:$F$1000,MATCH(78,Consolidado!$AC$5:$AC$1000,0))&"","") | I91: =IFERROR(INDEX(Consolidado!$G$5:$G$1000,MATCH(78,Consolidado!$AC$5:$AC$1000,0))&"","") | J91: =IFERROR(INDEX(Consolidado!$H$5:$H$1000,MATCH(78,Consolidado!$AC$5:$AC$1000,0))&"","")
A92: =IF(B92="","",79) | B92: =IFERROR(INDEX(Consolidado!$A$5:$A$1000,MATCH(79,Consolidado!$AC$5:$AC$1000,0)),"") | C92: =IFERROR(INDEX(Consolidado!$C$5:$C$1000,MATCH(79,Consolidado!$AC$5:$AC$1000,0))&"","") | D92: =IFERROR(INDEX(Consolidado!$B$5:$B$1000,MATCH(79,Consolidado!$AC$5:$AC$1000,0)),"") | E92: =IF(OR(D92="",D92=0),"",CHOOSE(MONTH(D92),"Ene","Feb","Mar","Abr","May","Jun","Jul","Ago","Sep","Oct","Nov","Dic")) | F92: =IF(OR(D92="",D92=0),"",YEAR(D92)) | G92: =IF(B92="","",IF(B92=$C$3,"◄ SELECCIONADO",IF(OR(D92="",D92=0,$C$6="",$C$6=0),"Sin fecha",IF(AND(YEAR(D92)=YEAR($C$6),MONTH(D92)=MONTH($C$6)),"MISMO MES",ABS((YEAR(D92)-YEAR($C$6))*12+MONTH(D92)-MONTH($C$6))&" meses "&IF(D92<$C$6,"antes","después"))))) | H92: =IFERROR(INDEX(Consolidado!$F$5:$F$1000,MATCH(79,Consolidado!$AC$5:$AC$1000,0))&"","") | I92: =IFERROR(INDEX(Consolidado!$G$5:$G$1000,MATCH(79,Consolidado!$AC$5:$AC$1000,0))&"","") | J92: =IFERROR(INDEX(Consolidado!$H$5:$H$1000,MATCH(79,Consolidado!$AC$5:$AC$1000,0))&"","")
A93: =IF(B93="","",80) | B93: =IFERROR(INDEX(Consolidado!$A$5:$A$1000,MATCH(80,Consolidado!$AC$5:$AC$1000,0)),"") | C93: =IFERROR(INDEX(Consolidado!$C$5:$C$1000,MATCH(80,Consolidado!$AC$5:$AC$1000,0))&"","") | D93: =IFERROR(INDEX(Consolidado!$B$5:$B$1000,MATCH(80,Consolidado!$AC$5:$AC$1000,0)),"") | E93: =IF(OR(D93="",D93=0),"",CHOOSE(MONTH(D93),"Ene","Feb","Mar","Abr","May","Jun","Jul","Ago","Sep","Oct","Nov","Dic")) | F93: =IF(OR(D93="",D93=0),"",YEAR(D93)) | G93: =IF(B93="","",IF(B93=$C$3,"◄ SELECCIONADO",IF(OR(D93="",D93=0,$C$6="",$C$6=0),"Sin fecha",IF(AND(YEAR(D93)=YEAR($C$6),MONTH(D93)=MONTH($C$6)),"MISMO MES",ABS((YEAR(D93)-YEAR($C$6))*12+MONTH(D93)-MONTH($C$6))&" meses "&IF(D93<$C$6,"antes","después"))))) | H93: =IFERROR(INDEX(Consolidado!$F$5:$F$1000,MATCH(80,Consolidado!$AC$5:$AC$1000,0))&"","") | I93: =IFERROR(INDEX(Consolidado!$G$5:$G$1000,MATCH(80,Consolidado!$AC$5:$AC$1000,0))&"","") | J93: =IFERROR(INDEX(Consolidado!$H$5:$H$1000,MATCH(80,Consolidado!$AC$5:$AC$1000,0))&"","")

Sheet Gráficos
A1: GRÁFICOS (imagen al 26/10/2026 – no se actualizan solos; los números vivos están en Resumen Riesgos y Cruce)

Sheet Consolidado
A1: CONSOLIDADO DE REQUERIMIENTOS – AUDITORÍA INTERNA, AUDITORÍA EXTERNA Y SSF
A2: Una fila por requerimiento. Columnas en azul = datos que usted llena (Fecha, Origen, Norma, Tema, Requerimiento, Responsable, Estado). Las columnas Año, Ene–Dic y "Veces del tema" se calculan solas. Use el filtro de la fila 4 para ver un tema y comparar quién lo pide.
A4: N° | B4: Fecha Recibida | C4: Origen | D4: Norma | E4: Tema (para agrupar) | F4: Requerimiento | G4: Responsable | H4: Estado | I4: Año | J4: Ene | K4: Feb | L4: Mar | M4: Abr | N4: May | O4: Jun | P4: Jul | Q4: Ago | R4: Sep | S4: Oct | T4: Nov | U4: Dic | V4: Veces del tema | W4: Orígenes que lo piden | X4: Otros orígenes, mismo tema y mismo mes | Y4: Hoja fuente | Z4: N° en hoja fuente | AA4: Detalle / puntos | AB4: Año-Mes (aux.) | AC4: Clave cruce (aux.) | AD4: Evento (aux.) | AE4: Primer ítem del evento (aux.)
A5: 1 | B5: 45408 | C5: SSF | D5: NRP-23 | E5: Seguridad de la información y ciberseguridad | F5: Visita de supervisión focalizada para verificar los controles implementados relativos a la seguridad de la información y ciberseguridad en su plataforma tecnológica SABAO-DR-10417. | I5: =IF(B5="","",YEAR(B5)) -> 2024 | J5: =IF(B5="","",IF(MONTH(B5)=1,"X","")) | K5: =IF(B5="","",IF(MONTH(B5)=2,"X","")) | L5: =IF(B5="","",IF(MONTH(B5)=3,"X","")) | M5: =IF(B5="","",IF(MONTH(B5)=4,"X","")) -> X | N5: =IF(B5="","",IF(MONTH(B5)=5,"X","")) | O5: =IF(B5="","",IF(MONTH(B5)=6,"X","")) | P5: =IF(B5="","",IF(MONTH(B5)=7,"X","")) | Q5: =IF(B5="","",IF(MONTH(B5)=8,"X","")) | R5: =IF(B5="","",IF(MONTH(B5)=9,"X","")) | S5: =IF(B5="","",IF(MONTH(B5)=10,"X","")) | T5: =IF(B5="","",IF(MONTH(B5)=11,"X","")) | U5: =IF(B5="","",IF(MONTH(B5)=12,"X","")) | V5: =IF(E5="","",COUNTIF($E$5:$E$1000,E5)) -> 2 | W5: =IF(E5="","",_xlfn.TEXTJOIN(" + ",TRUE(),IF(COUNTIFS($E$5:$E$1000,E5,$C$5:$C$1000,"Auditoría Interna")>0,"Interna",""),IF(COUNTIFS($E$5:$E$1000,E5,$C$5:$C$1000,"Auditoría Externa")>0,"Externa",""),IF(COUNTIFS($E$5:$E$1000,E5,$C$5:$C$1000,"SSF")>0,"SSF",""),IF(COUNTIFS($E$5:$E$1000,E5,$C$5:$C$1000,"Comité de Supervisión")>0,"Comité Sup.",""),IF(COUNTIFS($E$5:$E$1000,E5,$C$5:$C$1000,"Consejo de Administración")>0,"Consejo",""),IF(COUNTIFS($E$5:$E$1000,E5,$C$5:$C$1000,"Otros")>0,"Otros",""))) -> SSF | X5: =IF(E5="","",COUNTIFS($E$5:$E$1000,E5,$AB$5:$AB$1000,AB5,$C$5:$C$1000,"<>"&C5)) -> 0 | Y5: Resumen visita presencialSSF | Z5: 1 | AA5: 11 Puntos I Requerimiento: 26/04/2024 Observaciones: 7 | AB5: =IF(B5="","",YEAR(B5)*100+MONTH(B5)) -> 202404 | AC5: =IF(AND(E5<>"",E5=Cruce!$C$5),COUNTIF($E$5:E5,E5),"") | AD5: =IF(E5="","",C5&"|"&Y5&"|"&IF(B5="","s/f",TEXT(B5,"yyyymmdd"))) -> SSF|Resumen visita presencialSSF|20240426 | AE5: =IF(E5="",0,IF(COUNTIFS($E$5:E5,E5,$AD$5:AD5,AD5)=1,1,0)) -> 1
A6: 2 | B6: 45674 | C6: SSF | D6: NCB-022 | E6: Clasificación de cartera, mora y reservas | F6: Visita a Supervision Ampliada Para evaluar la cartera de Credito DS-SABAO-BCS-BC-32285 | I6: =IF(B6="","",YEAR(B6)) -> 2025 | J6: =IF(B6="","",IF(MONTH(B6)=1,"X","")) -> X | K6: =IF(B6="","",IF(MONTH(B6)=2,"X","")) | L6: =IF(B6="","",IF(MONTH(B6)=3,"X","")) | M6: =IF(B6="","",IF(MONTH(B6)=4,"X","")) | N6: =IF(B6="","",IF(MONTH(B6)=5,"X","")) | O6: =IF(B6="","",IF(MONTH(B6)=6,"X","")) | P6: =IF(B6="","",IF(MONTH(B6)=7,"X","")) | Q6: =IF(B6="","",IF(MONTH(B6)=8,"X","")) | R6: =IF(B6="","",IF(MONTH(B6)=9,"X","")) | S6: =IF(B6="","",IF(MONTH(B6)=10,"X","")) | T6: =IF(B6="","",IF(MONTH(B6)=11,"X","")) | U6: =IF(B6="","",IF(MONTH(B6)=12,"X","")) | V6: =IF(E6="","",COUNTIF($E$5:$E$1000,E6)) -> 6 | W6: =IF(E6="","",_xlfn.TEXTJOIN(" + ",TRUE(),IF(COUNTIFS($E$5:$E$1000,E6,$C$5:$C$1000,"Auditoría Interna")>0,"Interna",""),IF(COUNTIFS($E$5:$E$1000,E6,$C$5:$C$1000,"Auditoría Externa")>0,"Externa",""),IF(COUNTIFS($E$5:$E$1000,E6,$C$5:$C$1000,"SSF")>0,"SSF",""),IF(COUNTIFS($E$5:$E$1000,E6,$C$5:$C$1000,"Comité de Supervisión")>0,"Comité Sup.",""),IF(COUNTIFS($E$5:$E$1000,E6,$C$5:$C$1000,"Consejo de Administración")>0,"Consejo",""),IF(COUNTIFS($E$5:$E$1000,E6,$C$5:$C$1000,"Otros")>0,"Otros",""))) -> Interna + Externa + SSF | X6: =IF(E6="","",COUNTIFS($E$5:$E$1000,E6,$AB$5:$AB$1000,AB6,$C$5:$C$1000,"<>"&C6)) -> 0 | Y6: Resumen visita presencialSSF | Z6: 1 | AA6: 9 Puntos Requerimiento: 17/01/2025 2 Puntos II Requerimiento: 20/02/2025 4 Puntos III Requerimiento 21/02/2025 1 Punto IV Requerimiento 27/02/2025 Observaciones: 7 | AB6: =IF(B6="","",YEAR(B6)*100+MONTH(B6)) -> 202501 | AC6: =IF(AND(E6<>"",E6=Cruce!$C$5),COUNTIF($E$5:E6,E6),"") | AD6: =IF(E6="","",C6&"|"&Y6&"|"&IF(B6="","s/f",TEXT(B6,"yyyymmdd"))) -> SSF|Resumen visita presencialSSF|20250117 | AE6: =IF(E6="",0,IF(COUNTIFS($E$5:E6,E6,$AD$5:AD6,AD6)=1,1,0)) -> 1
A7: 3 | B7: 45699 | C7: SSF | D7: NRP-37 | E7: Registro de accionistas | F7: Visita de Supervisión Ampliada para evaluar las Normas NRP-37 Recoleccion de Informacion para el Registro de Accionistas DS-SABAO-BCS-BC-2774 | I7: =IF(B7="","",YEAR(B7)) -> 2025 | J7: =IF(B7="","",IF(MONTH(B7)=1,"X","")) | K7: =IF(B7="","",IF(MONTH(B7)=2,"X","")) -> X | L7: =IF(B7="","",IF(MONTH(B7)=3,"X","")) | M7: =IF(B7="","",IF(MONTH(B7)=4,"X","")) | N7: =IF(B7="","",IF(MONTH(B7)=5,"X","")) | O7: =IF(B7="","",IF(MONTH(B7)=6,"X","")) | P7: =IF(B7="","",IF(MONTH(B7)=7,"X","")) | Q7: =IF(B7="","",IF(MONTH(B7)=8,"X","")) | R7: =IF(B7="","",IF(MONTH(B7)=9,"X","")) | S7: =IF(B7="","",IF(MONTH(B7)=10,"X","")) | T7: =IF(B7="","",IF(MONTH(B7)=11,"X","")) | U7: =IF(B7="","",IF(MONTH(B7)=12,"X","")) | V7: =IF(E7="","",COUNTIF($E$5:$E$1000,E7)) -> 1 | W7: =IF(E7="","",_xlfn.TEXTJOIN(" + ",TRUE(),IF(COUNTIFS($E$5:$E$1000,E7,$C$5:$C$1000,"Auditoría Interna")>0,"Interna",""),IF(COUNTIFS($E$5:$E$1000,E7,$C$5:$C$1000,"Auditoría Externa")>0,"Externa",""),IF(COUNTIFS($E$5:$E$1000,E7,$C$5:$C$1000,"SSF")>0,"SSF",""),IF(COUNTIFS($E$5:$E$1000,E7,$C$5:$C$1000,"Comité de Supervisión")>0,"Comité Sup.",""),IF(COUNTIFS($E$5:$E$1000,E7,$C$5:$C$1000,"Consejo de Administración")>0,"Consejo",""),IF(COUNTIFS($E$5:$E$1000,E7,$C$5:$C$1000,"Otros")>0,"Otros",""))) -> SSF | X7: =IF(E7="","",COUNTIFS($E$5:$E$1000,E7,$AB$5:$AB$1000,AB7,$C$5:$C$1000,"<>"&C7)) -> 0 | Y7: Resumen visita presencialSSF | Z7: 2 | AA7: 1 Punto II Requerimiento 03/03/2025 Observaciones: 2 | AB7: =IF(B7="","",YEAR(B7)*100+MONTH(B7)) -> 202502 | AC7: =IF(AND(E7<>"",E7=Cruce!$C$5),COUNTIF($E$5:E7,E7),"") | AD7: =IF(E7="","",C7&"|"&Y7&"|"&IF(B7="","s/f",TEXT(B7,"yyyymmdd"))) -> SSF|Resumen visita presencialSSF|20250211 | AE7: =IF(E7="",0,IF(COUNTIFS($E$5:E7,E7,$AD$5:AD7,AD7)=1,1,0)) -> 1
A8: 4 | B8: 45734 | C8: SSF | D8: NRP-20 | E8: Gestión de riesgos específicos (visita integral) | F8: Visita de supervision ampliada para evaluar riesgos especificos - Riesgo de Credito, Operacional y Tecnologico SABAO- BCS- BC- 6489 | I8: =IF(B8="","",YEAR(B8)) -> 2025 | J8: =IF(B8="","",IF(MONTH(B8)=1,"X","")) | K8: =IF(B8="","",IF(MONTH(B8)=2,"X","")) | L8: =IF(B8="","",IF(MONTH(B8)=3,"X","")) -> X | M8: =IF(B8="","",IF(MONTH(B8)=4,"X","")) | N8: =IF(B8="","",IF(MONTH(B8)=5,"X","")) | O8: =IF(B8="","",IF(MONTH(B8)=6,"X","")) | P8: =IF(B8="","",IF(MONTH(B8)=7,"X","")) | Q8: =IF(B8="","",IF(MONTH(B8)=8,"X","")) | R8: =IF(B8="","",IF(MONTH(B8)=9,"X","")) | S8: =IF(B8="","",IF(MONTH(B8)=10,"X","")) | T8: =IF(B8="","",IF(MONTH(B8)=11,"X","")) | U8: =IF(B8="","",IF(MONTH(B8)=12,"X","")) | V8: =IF(E8="","",COUNTIF($E$5:$E$1000,E8)) -> 4 | W8: =IF(E8="","",_xlfn.TEXTJOIN(" + ",TRUE(),IF(COUNTIFS($E$5:$E$1000,E8,$C$5:$C$1000,"Auditoría Interna")>0,"Interna",""),IF(COUNTIFS($E$5:$E$1000,E8,$C$5:$C$1000,"Auditoría Externa")>0,"Externa",""),IF(COUNTIFS($E$5:$E$1000,E8,$C$5:$C$1000,"SSF")>0,"SSF",""),IF(COUNTIFS($E$5:$E$1000,E8,$C$5:$C$1000,"Comité de Supervisión")>0,"Comité Sup.",""),IF(COUNTIFS($E$5:$E$1000,E8,$C$5:$C$1000,"Consejo de Administración")>0,"Consejo",""),IF(COUNTIFS($E$5:$E$1000,E8,$C$5:$C$1000,"Otros")>0,"Otros",""))) -> SSF | X8: =IF(E8="","",COUNTIFS($E$5:$E$1000,E8,$AB$5:$AB$1000,AB8,$C$5:$C$1000,"<>"&C8)) -> 0 | Y8: Resumen visita presencialSSF | Z8: 3 | AA8: 25 Puntos Requerimiento: 18/03/2025 7 Puntos II Requerimiento: 08/04/2025 Observaciones: 3 | AB8: =IF(B8="","",YEAR(B8)*100+MONTH(B8)) -> 202503 | AC8: =IF(AND(E8<>"",E8=Cruce!$C$5),COUNTIF($E$5:E8,E8),"") | AD8: =IF(E8="","",C8&"|"&Y8&"|"&IF(B8="","s/f",TEXT(B8,"yyyymmdd"))) -> SSF|Resumen visita presencialSSF|20250318 | AE8: =IF(E8="",0,IF(COUNTIFS($E$5:E8,E8,$AD$5:AD8,AD8)=1,1,0)) -> 1
A9: 5 | B9: 45749 | C9: SSF | D9: NRP-25 | E9: Valúos y garantías | F9: Visita de supervision ampliada para revisión de avalúos e inspección de garantías DS-SABAO- BCS- BC- 7037 | I9: =IF(B9="","",YEAR(B9)) -> 2025 | J9: =IF(B9="","",IF(MONTH(B9)=1,"X","")) | K9: =IF(B9="","",IF(MONTH(B9)=2,"X","")) | L9: =IF(B9="","",IF(MONTH(B9)=3,"X","")) | M9: =IF(B9="","",IF(MONTH(B9)=4,"X","")) -> X | N9: =IF(B9="","",IF(MONTH(B9)=5,"X","")) | O9: =IF(B9="","",IF(MONTH(B9)=6,"X","")) | P9: =IF(B9="","",IF(MONTH(B9)=7,"X","")) | Q9: =IF(B9="","",IF(MONTH(B9)=8,"X","")) | R9: =IF(B9="","",IF(MONTH(B9)=9,"X","")) | S9: =IF(B9="","",IF(MONTH(B9)=10,"X","")) | T9: =IF(B9="","",IF(MONTH(B9)=11,"X","")) | U9: =IF(B9="","",IF(MONTH(B9)=12,"X","")) | V9: =IF(E9="","",COUNTIF($E$5:$E$1000,E9)) -> 2 | W9: =IF(E9="","",_xlfn.TEXTJOIN(" + ",TRUE(),IF(COUNTIFS($E$5:$E$1000,E9,$C$5:$C$1000,"Auditoría Interna")>0,"Interna",""),IF(COUNTIFS($E$5:$E$1000,E9,$C$5:$C$1000,"Auditoría Externa")>0,"Externa",""),IF(COUNTIFS($E$5:$E$1000,E9,$C$5:$C$1000,"SSF")>0,"SSF",""),IF(COUNTIFS($E$5:$E$1000,E9,$C$5:$C$1000,"Comité de Supervisión")>0,"Comité Sup.",""),IF(COUNTIFS($E$5:$E$1000,E9,$C$5:$C$1000,"Consejo de Administración")>0,"Consejo",""),IF(COUNTIFS($E$5:$E$1000,E9,$C$5:$C$1000,"Otros")>0,"Otros",""))) -> Interna + SSF | X9: =IF(E9="","",COUNTIFS($E$5:$E$1000,E9,$AB$5:$AB$1000,AB9,$C$5:$C$1000,"<>"&C9)) -> 0 | Y9: Resumen visita presencialSSF | Z9: 4 | AA9: 9 Puntos Requerimiento: 02/04/2025 3 Puntos II Requerimiento: 08/04/2025 4 Puntos III Requerimiento: 24/04/2025 2 Puntos IV Requerimiento: 24/04/2025 Observaciones: 11 | AB9: =IF(B9="","",YEAR(B9)*100+MONTH(B9)) -> 202504 | AC9: =IF(AND(E9<>"",E9=Cruce!$C$5),COUNTIF($E$5:E9,E9),"") | AD9: =IF(E9="","",C9&"|"&Y9&"|"&IF(B9="","s/f",TEXT(B9,"yyyymmdd"))) -> SSF|Resumen visita presencialSSF|20250402 | AE9: =IF(E9="",0,IF(COUNTIFS($E$5:E9,E9,$AD$5:AD9,AD9)=1,1,0)) -> 1
A10: 6 | B10: 45754 | C10: SSF | D10: NRP-53 | E10: Riesgo ambiental y social | F10: Visita de supervision ampliada para evaluar avance de Implementación de las Normas NRP-53 Riesgos AS DS-SABAO- BCS- BC- 7043 | I10: =IF(B10="","",YEAR(B10)) -> 2025 | J10: =IF(B10="","",IF(MONTH(B10)=1,"X","")) | K10: =IF(B10="","",IF(MONTH(B10)=2,"X","")) | L10: =IF(B10="","",IF(MONTH(B10)=3,"X","")) | M10: =IF(B10="","",IF(MONTH(B10)=4,"X","")) -> X | N10: =IF(B10="","",IF(MONTH(B10)=5,"X","")) | O10: =IF(B10="","",IF(MONTH(B10)=6,"X","")) | P10: =IF(B10="","",IF(MONTH(B10)=7,"X","")) | Q10: =IF(B10="","",IF(MONTH(B10)=8,"X","")) | R10: =IF(B10="","",IF(MONTH(B10)=9,"X","")) | S10: =IF(B10="","",IF(MONTH(B10)=10,"X","")) | T10: =IF(B10="","",IF(MONTH(B10)=11,"X","")) | U10: =IF(B10="","",IF(MONTH(B10)=12,"X","")) | V10: =IF(E10="","",COUNTIF($E$5:$E$1000,E10)) -> 3 | W10: =IF(E10="","",_xlfn.TEXTJOIN(" + ",TRUE(),IF(COUNTIFS($E$5:$E$1000,E10,$C$5:$C$1000,"Auditoría Interna")>0,"Interna",""),IF(COUNTIFS($E$5:$E$1000,E10,$C$5:$C$1000,"Auditoría Externa")>0,"Externa",""),IF(COUNTIFS($E$5:$E$1000,E10,$C$5:$C$1000,"SSF")>0,"SSF",""),IF(COUNTIFS($E$5:$E$1000,E10,$C$5:$C$1000,"Comité de Supervisión")>0,"Comité Sup.",""),IF(COUNTIFS($E$5:$E$1000,E10,$C$5:$C$1000,"Consejo de Administración")>0,"Consejo",""),IF(COUNTIFS($E$5:$E$1000,E10,$C$5:$C$1000,"Otros")>0,"Otros",""))) -> Interna + SSF | X10: =IF(E10="","",COUNTIFS($E$5:$E$1000,E10,$AB$5:$AB$1000,AB10,$C$5:$C$1000,"<>"&C10)) -> 0 | Y10: Resumen visita presencialSSF | Z10: 5 | AA10: 4 Puntos Requerimiento: 04/04/2025 Observaciones: 3 | AB10: =IF(B10="","",YEAR(B10)*100+MONTH(B10)) -> 202504 | AC10: =IF(AND(E10<>"",E10=Cruce!$C$5),COUNTIF($E$5:E10,E10),"") | AD10: =IF(E10="","",C10&"|"&Y10&"|"&IF(B10="","s/f",TEXT(B10,"yyyymmdd"))) -> SSF|Resumen visita presencialSSF|20250407 | AE10: =IF(E10="",0,IF(COUNTIFS($E$5:E10,E10,$AD$5:AD10,AD10)=1,1,0)) -> 1
A11: 7 | B11: 45775 | C11: SSF | D11: NCM-02 | E11: Transparencia y atención al usuario | F11: Visita de supervision ampliada para la verificación de las Normas NCM-02 - Transparencia y Divulgacion de la Informacion de Servicios Financieros - Atencion al Adulto Mayor SABAO- BCS- BC-8567 | I11: =IF(B11="","",YEAR(B11)) -> 2025 | J11: =IF(B11="","",IF(MONTH(B11)=1,"X","")) | K11: =IF(B11="","",IF(MONTH(B11)=2,"X","")) | L11: =IF(B11="","",IF(MONTH(B11)=3,"X","")) | M11: =IF(B11="","",IF(MONTH(B11)=4,"X","")) -> X | N11: =IF(B11="","",IF(MONTH(B11)=5,"X","")) | O11: =IF(B11="","",IF(MONTH(B11)=6,"X","")) | P11: =IF(B11="","",IF(MONTH(B11)=7,"X","")) | Q11: =IF(B11="","",IF(MONTH(B11)=8,"X","")) | R11: =IF(B11="","",IF(MONTH(B11)=9,"X","")) | S11: =IF(B11="","",IF(MONTH(B11)=10,"X","")) | T11: =IF(B11="","",IF(MONTH(B11)=11,"X","")) | U11: =IF(B11="","",IF(MONTH(B11)=12,"X","")) | V11: =IF(E11="","",COUNTIF($E$5:$E$1000,E11)) -> 2 | W11: =IF(E11="","",_xlfn.TEXTJOIN(" + ",TRUE(),IF(COUNTIFS($E$5:$E$1000,E11,$C$5:$C$1000,"Auditoría Interna")>0,"Interna",""),IF(COUNTIFS($E$5:$E$1000,E11,$C$5:$C$1000,"Auditoría Externa")>0,"Externa",""),IF(COUNTIFS($E$5:$E$1000,E11,$C$5:$C$1000,"SSF")>0,"SSF",""),IF(COUNTIFS($E$5:$E$1000,E11,$C$5:$C$1000,"Comité de Supervisión")>0,"Comité Sup.",""),IF(COUNTIFS($E$5:$E$1000,E11,$C$5:$C$1000,"Consejo de Administración")>0,"Consejo",""),IF(COUNTIFS($E$5:$E$1000,E11,$C$5:$C$1000,"Otros")>0,"Otros",""))) -> SSF | X11: =IF(E11="","",COUNTIFS($E$5:$E$1000,E11,$AB$5:$AB$1000,AB11,$C$5:$C$1000,"<>"&C11)) -> 0 | Y11: Resumen visita presencialSSF | Z11: 6 | AA11: 4 Puntos Requerimiento: 28/04/2025 Observaciones: 3 | AB11: =IF(B11="","",YEAR(B11)*100+MONTH(B11)) -> 202504 | AC11: =IF(AND(E11<>"",E11=Cruce!$C$5),COUNTIF($E$5:E11,E11),"") | AD11: =IF(E11="","",C11&"|"&Y11&"|"&IF(B11="","s/f",TEXT(B11,"yyyymmdd"))) -> SSF|Resumen visita presencialSSF|20250428 | AE11: =IF(E11="",0,IF(COUNTIFS($E$5:E11,E11,$AD$5:AD11,AD11)=1,1,0)) -> 1
A12: 8 | B12: 45796 | C12: SSF | D12: NRP-17 | E12: Gobierno Corporativo | F12: Visita de supervision ampliada para evaluar el Gobierno Corporativo SABAO- BCS- BC-9337 | I12: =IF(B12="","",YEAR(B12)) -> 2025 | J12: =IF(B12="","",IF(MONTH(B12)=1,"X","")) | K12: =IF(B12="","",IF(MONTH(B12)=2,"X","")) | L12: =IF(B12="","",IF(MONTH(B12)=3,"X","")) | M12: =IF(B12="","",IF(MONTH(B12)=4,"X","")) | N12: =IF(B12="","",IF(MONTH(B12)=5,"X","")) -> X | O12: =IF(B12="","",IF(MONTH(B12)=6,"X","")) | P12: =IF(B12="","",IF(MONTH(B12)=7,"X","")) | Q12: =IF(B12="","",IF(MONTH(B12)=8,"X","")) | R12: =IF(B12="","",IF(MONTH(B12)=9,"X","")) | S12: =IF(B12="","",IF(MONTH(B12)=10,"X","")) | T12: =IF(B12="","",IF(MONTH(B12)=11,"X","")) | U12: =IF(B12="","",IF(MONTH(B12)=12,"X","")) | V12: =IF(E12="","",COUNTIF($E$5:$E$1000,E12)) -> 8 | W12: =IF(E12="","",_xlfn.TEXTJOIN(" + ",TRUE(),IF(COUNTIFS($E$5:$E$1000,E12,$C$5:$C$1000,"Auditoría Interna")>0,"Interna",""),IF(COUNTIFS($E$5:$E$1000,E12,$C$5:$C$1000,"Auditoría Externa")>0,"Externa",""),IF(COUNTIFS($E$5:$E$1000,E12,$C$5:$C$1000,"SSF")>0,"SSF",""),IF(COUNTIFS($E$5:$E$1000,E12,$C$5:$C$1000,"Comité de Supervisión")>0,"Comité Sup.",""),IF(COUNTIFS($E$5:$E$1000,E12,$C$5:$C$1000,"Consejo de Administración")>0,"Consejo",""),IF(COUNTIFS($E$5:$E$1000,E12,$C$5:$C$1000,"Otros")>0,"Otros",""))) -> Interna + SSF | X12: =IF(E12="","",COUNTIFS($E$5:$E$1000,E12,$AB$5:$AB$1000,AB12,$C$5:$C$1000,"<>"&C12)) -> 0 | Y12: Resumen visita presencialSSF | Z12: 7 | AA12: 10 Puntos Requerimiento: 15/05/2025 10 Puntos II Requerimiento 11/06/2025 1 Punto III Requerimiento 13/06/2025 4 Puntos IV Requerimiento: 13/06/2025 11 Puntos V Requerimiento: 20/06/2025 7 Puntos VI Requerimiento: 24/06/2025 Observaciones: 9 | AB12: =IF(B12="","",YEAR(B12)*100+MONTH(B12)) -> 202505 | AC12: =IF(AND(E12<>"",E12=Cruce!$C$5),COUNTIF($E$5:E12,E12),"") -> 1 | AD12: =IF(E12="","",C12&"|"&Y12&"|"&IF(B12="","s/f",TEXT(B12,"yyyymmdd"))) -> SSF|Resumen visita presencialSSF|20250519 | AE12: =IF(E12="",0,IF(COUNTIFS($E$5:E12,E12,$AD$5:AD12,AD12)=1,1,0)) -> 1
A13: 9 | B13: 45807 | C13: SSF | D13: NRP-23 / NRP-24 | E13: Plan de Continuidad (BCP/DRP) | F13: Visita de Supervisión Ampliada para verificar la Gestión de Seguridad de la Información y Continuidad del Negocio. SABAO-BCS-BC-12064 | I13: =IF(B13="","",YEAR(B13)) -> 2025 | J13: =IF(B13="","",IF(MONTH(B13)=1,"X","")) | K13: =IF(B13="","",IF(MONTH(B13)=2,"X","")) | L13: =IF(B13="","",IF(MONTH(B13)=3,"X","")) | M13: =IF(B13="","",IF(MONTH(B13)=4,"X","")) | N13: =IF(B13="","",IF(MONTH(B13)=5,"X","")) -> X | O13: =IF(B13="","",IF(MONTH(B13)=6,"X","")) | P13: =IF(B13="","",IF(MONTH(B13)=7,"X","")) | Q13: =IF(B13="","",IF(MONTH(B13)=8,"X","")) | R13: =IF(B13="","",IF(MONTH(B13)=9,"X","")) | S13: =IF(B13="","",IF(MONTH(B13)=10,"X","")) | T13: =IF(B13="","",IF(MONTH(B13)=11,"X","")) | U13: =IF(B13="","",IF(MONTH(B13)=12,"X","")) | V13: =IF(E13="","",COUNTIF($E$5:$E$1000,E13)) -> 20 | W13: =IF(E13="","",_xlfn.TEXTJOIN(" + ",TRUE(),IF(COUNTIFS($E$5:$E$1000,E13,$C$5:$C$1000,"Auditoría Interna")>0,"Interna",""),IF(COUNTIFS($E$5:$E$1000,E13,$C$5:$C$1000,"Auditoría Externa")>0,"Externa",""),IF(COUNTIFS($E$5:$E$1000,E13,$C$5:$C$1000,"SSF")>0,"SSF",""),IF(COUNTIFS($E$5:$E$1000,E13,$C$5:$C$1000,"Comité de Supervisión")>0,"Comité Sup.",""),IF(COUNTIFS($E$5:$E$1000,E13,$C$5:$C$1000,"Consejo de Administración")>0,"Consejo",""),IF(COUNTIFS($E$5:$E$1000,E13,$C$5:$C$1000,"Otros")>0,"Otros",""))) -> Interna + Externa + SSF | X13: =IF(E13="","",COUNTIFS($E$5:$E$1000,E13,$AB$5:$AB$1000,AB13,$C$5:$C$1000,"<>"&C13)) -> 0 | Y13: Resumen visita presencialSSF | Z13: 8 | AA13: 14 Puntos Requerimiento: 28/05/2025 Observaciones: 2 | AB13: =IF(B13="","",YEAR(B13)*100+MONTH(B13)) -> 202505 | AC13: =IF(AND(E13<>"",E13=Cruce!$C$5),COUNTIF($E$5:E13,E13),"") | AD13: =IF(E13="","",C13&"|"&Y13&"|"&IF(B13="","s/f",TEXT(B13,"yyyymmdd"))) -> SSF|Resumen visita presencialSSF|20250530 | AE13: =IF(E13="",0,IF(COUNTIFS($E$5:E13,E13,$AD$5:AD13,AD13)=1,1,0)) -> 1
A14: 10 | B14: 45820 | C14: SSF | D14: NRP-36 | E14: PLD/FT/FPADM | F14: Visita de Supervisión Ampliada para verificar las Normas NRP-36. PLD/FT/FPADM DS-SABAO-BCS-BC-13042 | I14: =IF(B14="","",YEAR(B14)) -> 2025 | J14: =IF(B14="","",IF(MONTH(B14)=1,"X","")) | K14: =IF(B14="","",IF(MONTH(B14)=2,"X","")) | L14: =IF(B14="","",IF(MONTH(B14)=3,"X","")) | M14: =IF(B14="","",IF(MONTH(B14)=4,"X","")) | N14: =IF(B14="","",IF(MONTH(B14)=5,"X","")) | O14: =IF(B14="","",IF(MONTH(B14)=6,"X","")) -> X | P14: =IF(B14="","",IF(MONTH(B14)=7,"X","")) | Q14: =IF(B14="","",IF(MONTH(B14)=8,"X","")) | R14: =IF(B14="","",IF(MONTH(B14)=9,"X","")) | S14: =IF(B14="","",IF(MONTH(B14)=10,"X","")) | T14: =IF(B14="","",IF(MONTH(B14)=11,"X","")) | U14: =IF(B14="","",IF(MONTH(B14)=12,"X","")) | V14: =IF(E14="","",COUNTIF($E$5:$E$1000,E14)) -> 1 | W14: =IF(E14="","",_xlfn.TEXTJOIN(" + ",TRUE(),IF(COUNTIFS($E$5:$E$1000,E14,$C$5:$C$1000,"Auditoría Interna")>0,"Interna",""),IF(COUNTIFS($E$5:$E$1000,E14,$C$5:$C$1000,"Auditoría Externa")>0,"Externa",""),IF(COUNTIFS($E$5:$E$1000,E14,$C$5:$C$1000,"SSF")>0,"SSF",""),IF(COUNTIFS($E$5:$E$1000,E14,$C$5:$C$1000,"Comité de Supervisión")>0,"Comité Sup.",""),IF(COUNTIFS($E$5:$E$1000,E14,$C$5:$C$1000,"Consejo de Administración")>0,"Consejo",""),IF(COUNTIFS($E$5:$E$1000,E14,$C$5:$C$1000,"Otros")>0,"Otros",""))) -> SSF | X14: =IF(E14="","",COUNTIFS($E$5:$E$1000,E14,$AB$5:$AB$1000,AB14,$C$5:$C$1000,"<>"&C14)) -> 0 | Y14: Resumen visita presencialSSF | Z14: 9 | AA14: 7 Puntos Requerimiento: 12/06/2025 Observaciones: 3 | AB14: =IF(B14="","",YEAR(B14)*100+MONTH(B14)) -> 202506 | AC14: =IF(AND(E14<>"",E14=Cruce!$C$5),COUNTIF($E$5:E14,E14),"") | AD14: =IF(E14="","",C14&"|"&Y14&"|"&IF(B14="","s/f",TEXT(B14,"yyyymmdd"))) -> SSF|Resumen visita presencialSSF|20250612 | AE14: =IF(E14="",0,IF(COUNTIFS($E$5:E14,E14,$AD$5:AD14,AD14)=1,1,0)) -> 1
A15: 11 | B15: 45855 | C15: SSF | D15: Ley Bancos Coop. Art. 15 | E15: Declaraciones juradas | F15: Observaciones a Declaraciones Juradas a que se refiere el Art. 15 de la Ley de Bancos Cooperativos y Sociedades de Ahorro y Crédito. No. DS-SABAO-BCS-BC-16934 | I15: =IF(B15="","",YEAR(B15)) -> 2025 | J15: =IF(B15="","",IF(MONTH(B15)=1,"X","")) | K15: =IF(B15="","",IF(MONTH(B15)=2,"X","")) | L15: =IF(B15="","",IF(MONTH(B15)=3,"X","")) | M15: =IF(B15="","",IF(MONTH(B15)=4,"X","")) | N15: =IF(B15="","",IF(MONTH(B15)=5,"X","")) | O15: =IF(B15="","",IF(MONTH(B15)=6,"X","")) | P15: =IF(B15="","",IF(MONTH(B15)=7,"X","")) -> X | Q15: =IF(B15="","",IF(MONTH(B15)=8,"X","")) | R15: =IF(B15="","",IF(MONTH(B15)=9,"X","")) | S15: =IF(B15="","",IF(MONTH(B15)=10,"X","")) | T15: =IF(B15="","",IF(MONTH(B15)=11,"X","")) | U15: =IF(B15="","",IF(MONTH(B15)=12,"X","")) | V15: =IF(E15="","",COUNTIF($E$5:$E$1000,E15)) -> 1 | W15: =IF(E15="","",_xlfn.TEXTJOIN(" + ",TRUE(),IF(COUNTIFS($E$5:$E$1000,E15,$C$5:$C$1000,"Auditoría Interna")>0,"Interna",""),IF(COUNTIFS($E$5:$E$1000,E15,$C$5:$C$1000,"Auditoría Externa")>0,"Externa",""),IF(COUNTIFS($E$5:$E$1000,E15,$C$5:$C$1000,"SSF")>0,"SSF",""),IF(COUNTIFS($E$5:$E$1000,E15,$C$5:$C$1000,"Comité de Supervisión")>0,"Comité Sup.",""),IF(COUNTIFS($E$5:$E$1000,E15,$C$5:$C$1000,"Consejo de Administración")>0,"Consejo",""),IF(COUNTIFS($E$5:$E$1000,E15,$C$5:$C$1000,"Otros")>0,"Otros",""))) -> SSF | X15: =IF(E15="","",COUNTIFS($E$5:$E$1000,E15,$AB$5:$AB$1000,AB15,$C$5:$C$1000,"<>"&C15)) -> 0 | Y15: Resumen visita presencialSSF | Z15: 10 | AB15: =IF(B15="","",YEAR(B15)*100+MONTH(B15)) -> 202507 | AC15: =IF(AND(E15<>"",E15=Cruce!$C$5),COUNTIF($E$5:E15,E15),"") | AD15: =IF(E15="","",C15&"|"&Y15&"|"&IF(B15="","s/f",TEXT(B15,"yyyymmdd"))) -> SSF|Resumen visita presencialSSF|20250717 | AE15: =IF(E15="",0,IF(COUNTIFS($E$5:E15,E15,$AD$5:AD15,AD15)=1,1,0)) -> 1
A16: 12 | B16: 45894 | C16: SSF | D16: NCB-022 | E16: Clasificación de cartera, mora y reservas | F16: Visita de Supervisión ampliada, para evaluar la mora financiera No. DS-SABAO-BCS-BC-18028 | I16: =IF(B16="","",YEAR(B16)) -> 2025 | J16: =IF(B16="","",IF(MONTH(B16)=1,"X","")) | K16: =IF(B16="","",IF(MONTH(B16)=2,"X","")) | L16: =IF(B16="","",IF(MONTH(B16)=3,"X","")) | M16: =IF(B16="","",IF(MONTH(B16)=4,"X","")) | N16: =IF(B16="","",IF(MONTH(B16)=5,"X","")) | O16: =IF(B16="","",IF(MONTH(B16)=6,"X","")) | P16: =IF(B16="","",IF(MONTH(B16)=7,"X","")) | Q16: =IF(B16="","",IF(MONTH(B16)=8,"X","")) -> X | R16: =IF(B16="","",IF(MONTH(B16)=9,"X","")) | S16: =IF(B16="","",IF(MONTH(B16)=10,"X","")) | T16: =IF(B16="","",IF(MONTH(B16)=11,"X","")) | U16: =IF(B16="","",IF(MONTH(B16)=12,"X","")) | V16: =IF(E16="","",COUNTIF($E$5:$E$1000,E16)) -> 6 | W16: =IF(E16="","",_xlfn.TEXTJOIN(" + ",TRUE(),IF(COUNTIFS($E$5:$E$1000,E16,$C$5:$C$1000,"Auditoría Interna")>0,"Interna",""),IF(COUNTIFS($E$5:$E$1000,E16,$C$5:$C$1000,"Auditoría Externa")>0,"Externa",""),IF(COUNTIFS($E$5:$E$1000,E16,$C$5:$C$1000,"SSF")>0,"SSF",""),IF(COUNTIFS($E$5:$E$1000,E16,$C$5:$C$1000,"Comité de Supervisión")>0,"Comité Sup.",""),IF(COUNTIFS($E$5:$E$1000,E16,$C$5:$C$1000,"Consejo de Administración")>0,"Consejo",""),IF(COUNTIFS($E$5:$E$1000,E16,$C$5:$C$1000,"Otros")>0,"Otros",""))) -> Interna + Externa + SSF | X16: =IF(E16="","",COUNTIFS($E$5:$E$1000,E16,$AB$5:$AB$1000,AB16,$C$5:$C$1000,"<>"&C16)) -> 0 | Y16: Resumen visita presencialSSF | Z16: 11 | AA16: 5 Puntos I Requerimiento: 22/08/2025 Observaciones: 8 | AB16: =IF(B16="","",YEAR(B16)*100+MONTH(B16)) -> 202508 | AC16: =IF(AND(E16<>"",E16=Cruce!$C$5),COUNTIF($E$5:E16,E16),"") | AD16: =IF(E16="","",C16&"|"&Y16&"|"&IF(B16="","s/f",TEXT(B16,"yyyymmdd"))) -> SSF|Resumen visita presencialSSF|20250825 | AE16: =IF(E16="",0,IF(COUNTIFS($E$5:E16,E16,$AD$5:AD16,AD16)=1,1,0)) -> 1
A17: 13 | B17: 45939 | C17: SSF | D17: Otros | E17: Sostenibilidad e inclusión financiera | F17: Solicitud de infirmación vía correo electrónico con relación a: *Productos con enfoque sostenible *Productos, servicios y canales dirigidos a personas con discapacidad *Productos y/o servicios específicos para mujeres *Retos identificados por las entidades o la industria en materia de sostenibilidad e inclusión financiera Cualquier otra información que se considere relevante incluir | I17: =IF(B17="","",YEAR(B17)) -> 2025 | J17: =IF(B17="","",IF(MONTH(B17)=1,"X","")) | K17: =IF(B17="","",IF(MONTH(B17)=2,"X","")) | L17: =IF(B17="","",IF(MONTH(B17)=3,"X","")) | M17: =IF(B17="","",IF(MONTH(B17)=4,"X","")) | N17: =IF(B17="","",IF(MONTH(B17)=5,"X","")) | O17: =IF(B17="","",IF(MONTH(B17)=6,"X","")) | P17: =IF(B17="","",IF(MONTH(B17)=7,"X","")) | Q17: =IF(B17="","",IF(MONTH(B17)=8,"X","")) | R17: =IF(B17="","",IF(MONTH(B17)=9,"X","")) | S17: =IF(B17="","",IF(MONTH(B17)=10,"X","")) -> X | T17: =IF(B17="","",IF(MONTH(B17)=11,"X","")) | U17: =IF(B17="","",IF(MONTH(B17)=12,"X","")) | V17: =IF(E17="","",COUNTIF($E$5:$E$1000,E17)) -> 1 | W17: =IF(E17="","",_xlfn.TEXTJOIN(" + ",TRUE(),IF(COUNTIFS($E$5:$E$1000,E17,$C$5:$C$1000,"Auditoría Interna")>0,"Interna",""),IF(COUNTIFS($E$5:$E$1000,E17,$C$5:$C$1000,"Auditoría Externa")>0,"Externa",""),IF(COUNTIFS($E$5:$E$1000,E17,$C$5:$C$1000,"SSF")>0,"SSF",""),IF(COUNTIFS($E$5:$E$1000,E17,$C$5:$C$1000,"Comité de Supervisión")>0,"Comité Sup.",""),IF(COUNTIFS($E$5:$E$1000,E17,$C$5:$C$1000,"Consejo de Administración")>0,"Consejo",""),IF(COUNTIFS($E$5:$E$1000,E17,$C$5:$C$1000,"Otros")>0,"Otros",""))) -> SSF | X17: =IF(E17="","",COUNTIFS($E$5:$E$1000,E17,$AB$5:$AB$1000,AB17,$C$5:$C$1000,"<>"&C17)) -> 0 | Y17: Resumen visita presencialSSF | Z17: 14 | AA17: 5 Puntos I Requerimiento: 14/10/2025 | AB17: =IF(B17="","",YEAR(B17)*100+MONTH(B17)) -> 202510 | AC17: =IF(AND(E17<>"",E17=Cruce!$C$5),COUNTIF($E$5:E17,E17),"") | AD17: =IF(E17="","",C17&"|"&Y17&"|"&IF(B17="","s/f",TEXT(B17,"yyyymmdd"))) -> SSF|Resumen visita presencialSSF|20251009 | AE17: =IF(E17="",0,IF(COUNTIFS($E$5:E17,E17,$AD$5:AD17,AD17)=1,1,0)) -> 1
A18: 14 | B18: 45957 | C18: SSF | D18: NRP-20 | E18: Gestión de riesgos específicos (visita integral) | F18: Visita de supervision ampliada para evaluar gestión de riesgos especificos. DS-SABAO- BCS- BC- 24708 RIA #1 Riesgos específicos a septiembre 2025 RIA #2 Riesgos específicos a septiembre 2025 | I18: =IF(B18="","",YEAR(B18)) -> 2025 | J18: =IF(B18="","",IF(MONTH(B18)=1,"X","")) | K18: =IF(B18="","",IF(MONTH(B18)=2,"X","")) | L18: =IF(B18="","",IF(MONTH(B18)=3,"X","")) | M18: =IF(B18="","",IF(MONTH(B18)=4,"X","")) | N18: =IF(B18="","",IF(MONTH(B18)=5,"X","")) | O18: =IF(B18="","",IF(MONTH(B18)=6,"X","")) | P18: =IF(B18="","",IF(MONTH(B18)=7,"X","")) | Q18: =IF(B18="","",IF(MONTH(B18)=8,"X","")) | R18: =IF(B18="","",IF(MONTH(B18)=9,"X","")) | S18: =IF(B18="","",IF(MONTH(B18)=10,"X","")) -> X | T18: =IF(B18="","",IF(MONTH(B18)=11,"X","")) | U18: =IF(B18="","",IF(MONTH(B18)=12,"X","")) | V18: =IF(E18="","",COUNTIF($E$5:$E$1000,E18)) -> 4 | W18: =IF(E18="","",_xlfn.TEXTJOIN(" + ",TRUE(),IF(COUNTIFS($E$5:$E$1000,E18,$C$5:$C$1000,"Auditoría Interna")>0,"Interna",""),IF(COUNTIFS($E$5:$E$1000,E18,$C$5:$C$1000,"Auditoría Externa")>0,"Externa",""),IF(COUNTIFS($E$5:$E$1000,E18,$C$5:$C$1000,"SSF")>0,"SSF",""),IF(COUNTIFS($E$5:$E$1000,E18,$C$5:$C$1000,"Comité de Supervisión")>0,"Comité Sup.",""),IF(COUNTIFS($E$5:$E$1000,E18,$C$5:$C$1000,"Consejo de Administración")>0,"Consejo",""),IF(COUNTIFS($E$5:$E$1000,E18,$C$5:$C$1000,"Otros")>0,"Otros",""))) -> SSF | X18: =IF(E18="","",COUNTIFS($E$5:$E$1000,E18,$AB$5:$AB$1000,AB18,$C$5:$C$1000,"<>"&C18)) -> 0 | Y18: Resumen visita presencialSSF | Z18: 13 | AA18: 42 Puntos Requerimiento inicial 24/10/2025 Observaciones: 8 9 Puntos Requerimiento 10/11/2025 Fecha de Envio informacion: 12/11/2025 Literal B: 10 Puntos Requerimiento 14/11/2025 Fecha de Envio informacion: 17/11/2025 | AB18: =IF(B18="","",YEAR(B18)*100+MONTH(B18)) -> 202510 | AC18: =IF(AND(E18<>"",E18=Cruce!$C$5),COUNTIF($E$5:E18,E18),"") | AD18: =IF(E18="","",C18&"|"&Y18&"|"&IF(B18="","s/f",TEXT(B18,"yyyymmdd"))) -> SSF|Resumen visita presencialSSF|20251027 | AE18: =IF(E18="",0,IF(COUNTIFS($E$5:E18,E18,$AD$5:AD18,AD18)=1,1,0)) -> 1
A19: 15 | B19: 46041 | C19: SSF | D19: NRP-23 | E19: Seguridad de la información y ciberseguridad | F19: Visita de supervisión focalizada para evaluar seguridad de la información y ciberseguridad Circular No. SABAO-BCS-BC-1134 | I19: =IF(B19="","",YEAR(B19)) -> 2026 | J19: =IF(B19="","",IF(MONTH(B19)=1,"X","")) -> X | K19: =IF(B19="","",IF(MONTH(B19)=2,"X","")) | L19: =IF(B19="","",IF(MONTH(B19)=3,"X","")) | M19: =IF(B19="","",IF(MONTH(B19)=4,"X","")) | N19: =IF(B19="","",IF(MONTH(B19)=5,"X","")) | O19: =IF(B19="","",IF(MONTH(B19)=6,"X","")) | P19: =IF(B19="","",IF(MONTH(B19)=7,"X","")) | Q19: =IF(B19="","",IF(MONTH(B19)=8,"X","")) | R19: =IF(B19="","",IF(MONTH(B19)=9,"X","")) | S19: =IF(B19="","",IF(MONTH(B19)=10,"X","")) | T19: =IF(B19="","",IF(MONTH(B19)=11,"X","")) | U19: =IF(B19="","",IF(MONTH(B19)=12,"X","")) | V19: =IF(E19="","",COUNTIF($E$5:$E$1000,E19)) -> 2 | W19: =IF(E19="","",_xlfn.TEXTJOIN(" + ",TRUE(),IF(COUNTIFS($E$5:$E$1000,E19,$C$5:$C$1000,"Auditoría Interna")>0,"Interna",""),IF(COUNTIFS($E$5:$E$1000,E19,$C$5:$C$1000,"Auditoría Externa")>0,"Externa",""),IF(COUNTIFS($E$5:$E$1000,E19,$C$5:$C$1000,"SSF")>0,"SSF",""),IF(COUNTIFS($E$5:$E$1000,E19,$C$5:$C$1000,"Comité de Supervisión")>0,"Comité Sup.",""),IF(COUNTIFS($E$5:$E$1000,E19,$C$5:$C$1000,"Consejo de Administración")>0,"Consejo",""),IF(COUNTIFS($E$5:$E$1000,E19,$C$5:$C$1000,"Otros")>0,"Otros",""))) -> SSF | X19: =IF(E19="","",COUNTIFS($E$5:$E$1000,E19,$AB$5:$AB$1000,AB19,$C$5:$C$1000,"<>"&C19)) -> 0 | Y19: Resumen visita presencialSSF | Z19: 15 | AA19: I requerimiento: 13 puntos 19/01/2026 | AB19: =IF(B19="","",YEAR(B19)*100+MONTH(B19)) -> 202601 | AC19: =IF(AND(E19<>"",E19=Cruce!$C$5),COUNTIF($E$5:E19,E19),"") | AD19: =IF(E19="","",C19&"|"&Y19&"|"&IF(B19="","s/f",TEXT(B19,"yyyymmdd"))) -> SSF|Resumen visita presencialSSF|20260119 | AE19: =IF(E19="",0,IF(COUNTIFS($E$5:E19,E19,$AD$5:AD19,AD19)=1,1,0)) -> 1
A20: 16 | B20: 46055 | C20: SSF | D20: NRSF-01 / NRSF-03 | E20: Información financiera (NRSF-01 / NRSF-03) | F20: Resultado visita de supervisión para evaluar el cumplimiento de las Normas NRSF01, NRSF-03 y E04-NTE01. No. SABAO-BCS-BC-2402 | I20: =IF(B20="","",YEAR(B20)) -> 2026 | J20: =IF(B20="","",IF(MONTH(B20)=1,"X","")) | K20: =IF(B20="","",IF(MONTH(B20)=2,"X","")) -> X | L20: =IF(B20="","",IF(MONTH(B20)=3,"X","")) | M20: =IF(B20="","",IF(MONTH(B20)=4,"X","")) | N20: =IF(B20="","",IF(MONTH(B20)=5,"X","")) | O20: =IF(B20="","",IF(MONTH(B20)=6,"X","")) | P20: =IF(B20="","",IF(MONTH(B20)=7,"X","")) | Q20: =IF(B20="","",IF(MONTH(B20)=8,"X","")) | R20: =IF(B20="","",IF(MONTH(B20)=9,"X","")) | S20: =IF(B20="","",IF(MONTH(B20)=10,"X","")) | T20: =IF(B20="","",IF(MONTH(B20)=11,"X","")) | U20: =IF(B20="","",IF(MONTH(B20)=12,"X","")) | V20: =IF(E20="","",COUNTIF($E$5:$E$1000,E20)) -> 2 | W20: =IF(E20="","",_xlfn.TEXTJOIN(" + ",TRUE(),IF(COUNTIFS($E$5:$E$1000,E20,$C$5:$C$1000,"Auditoría Interna")>0,"Interna",""),IF(COUNTIFS($E$5:$E$1000,E20,$C$5:$C$1000,"Auditoría Externa")>0,"Externa",""),IF(COUNTIFS($E$5:$E$1000,E20,$C$5:$C$1000,"SSF")>0,"SSF",""),IF(COUNTIFS($E$5:$E$1000,E20,$C$5:$C$1000,"Comité de Supervisión")>0,"Comité Sup.",""),IF(COUNTIFS($E$5:$E$1000,E20,$C$5:$C$1000,"Consejo de Administración")>0,"Consejo",""),IF(COUNTIFS($E$5:$E$1000,E20,$C$5:$C$1000,"Otros")>0,"Otros",""))) -> SSF | X20: =IF(E20="","",COUNTIFS($E$5:$E$1000,E20,$AB$5:$AB$1000,AB20,$C$5:$C$1000,"<>"&C20)) -> 0 | Y20: Resumen visita presencialSSF | Z20: 18 | AA20: N/A | AB20: =IF(B20="","",YEAR(B20)*100+MONTH(B20)) -> 202602 | AC20: =IF(AND(E20<>"",E20=Cruce!$C$5),COUNTIF($E$5:E20,E20),"") | AD20: =IF(E20="","",C20&"|"&Y20&"|"&IF(B20="","s/f",TEXT(B20,"yyyymmdd"))) -> SSF|Resumen visita presencialSSF|20260202 | AE20: =IF(E20="",0,IF(COUNTIFS($E$5:E20,E20,$AD$5:AD20,AD20)=1,1,0)) -> 1
A21: 17 | B21: 46056 | C21: SSF | D21: NCM-02 | E21: Transparencia y atención al usuario | F21: Nombramiento para realizar visita de supervisión ampliada para verificar el cumplimiento de las Normas Técnicas para la Transparencia y Divulgación de la Información de los Servicios Financieros Bancarios (NCM-02). No. SABAO-BCS-BC-2274 | I21: =IF(B21="","",YEAR(B21)) -> 2026 | J21: =IF(B21="","",IF(MONTH(B21)=1,"X","")) | K21: =IF(B21="","",IF(MONTH(B21)=2,"X","")) -> X | L21: =IF(B21="","",IF(MONTH(B21)=3,"X","")) | M21: =IF(B21="","",IF(MONTH(B21)=4,"X","")) | N21: =IF(B21="","",IF(MONTH(B21)=5,"X","")) | O21: =IF(B21="","",IF(MONTH(B21)=6,"X","")) | P21: =IF(B21="","",IF(MONTH(B21)=7,"X","")) | Q21: =IF(B21="","",IF(MONTH(B21)=8,"X","")) | R21: =IF(B21="","",IF(MONTH(B21)=9,"X","")) | S21: =IF(B21="","",IF(MONTH(B21)=10,"X","")) | T21: =IF(B21="","",IF(MONTH(B21)=11,"X","")) | U21: =IF(B21="","",IF(MONTH(B21)=12,"X","")) | V21: =IF(E21="","",COUNTIF($E$5:$E$1000,E21)) -> 2 | W21: =IF(E21="","",_xlfn.TEXTJOIN(" + ",TRUE(),IF(COUNTIFS($E$5:$E$1000,E21,$C$5:$C$1000,"Auditoría Interna")>0,"Interna",""),IF(COUNTIFS($E$5:$E$1000,E21,$C$5:$C$1000,"Auditoría Externa")>0,"Externa",""),IF(COUNTIFS($E$5:$E$1000,E21,$C$5:$C$1000,"SSF")>0,"SSF",""),IF(COUNTIFS($E$5:$E$1000,E21,$C$5:$C$1000,"Comité de Supervisión")>0,"Comité Sup.",""),IF(COUNTIFS($E$5:$E$1000,E21,$C$5:$C$1000,"Consejo de Administración")>0,"Consejo",""),IF(COUNTIFS($E$5:$E$1000,E21,$C$5:$C$1000,"Otros")>0,"Otros",""))) -> SSF | X21: =IF(E21="","",COUNTIFS($E$5:$E$1000,E21,$AB$5:$AB$1000,AB21,$C$5:$C$1000,"<>"&C21)) -> 0 | Y21: Resumen visita presencialSSF | Z21: 16 | AA21: I requerimiento: 14 puntos 03/02/2026 II requerimiento: 1 punto (10 expedientes de créditos) 12/02/2026 III requerimiento: 3 puntos 16/02/2026 IV requerimiento: 4 puntos 17/02/2026 V requerimiento: 5 puntos 20/02/2026 VI requerimiento: 2 puntos 25/02/2026 VII requerimiento: 6 puntos 02/03/2026 VIII Requerimiento: 1 punto 05/03/2026 | AB21: =IF(B21="","",YEAR(B21)*100+MONTH(B21)) -> 202602 | AC21: =IF(AND(E21<>"",E21=Cruce!$C$5),COUNTIF($E$5:E21,E21),"") | AD21: =IF(E21="","",C21&"|"&Y21&"|"&IF(B21="","s/f",TEXT(B21,"yyyymmdd"))) -> SSF|Resumen visita presencialSSF|20260203 | AE21: =IF(E21="",0,IF(COUNTIFS($E$5:E21,E21,$AD$5:AD21,AD21)=1,1,0)) -> 1
A22: 18 | B22: 46148 | C22: Auditoría Interna | D22: NRP-20 | E22: Plan de trabajo y capacitaciones de riesgos | F22: Plan de trabajo Operativo Año 2026 del Depto. de Admón. de Riesgos | G22: Lic. Escamilla | I22: =IF(B22="","",YEAR(B22)) -> 2026 | J22: =IF(B22="","",IF(MONTH(B22)=1,"X","")) | K22: =IF(B22="","",IF(MONTH(B22)=2,"X","")) | L22: =IF(B22="","",IF(MONTH(B22)=3,"X","")) | M22: =IF(B22="","",IF(MONTH(B22)=4,"X","")) | N22: =IF(B22="","",IF(MONTH(B22)=5,"X","")) -> X | O22: =IF(B22="","",IF(MONTH(B22)=6,"X","")) | P22: =IF(B22="","",IF(MONTH(B22)=7,"X","")) | Q22: =IF(B22="","",IF(MONTH(B22)=8,"X","")) | R22: =IF(B22="","",IF(MONTH(B22)=9,"X","")) | S22: =IF(B22="","",IF(MONTH(B22)=10,"X","")) | T22: =IF(B22="","",IF(MONTH(B22)=11,"X","")) | U22: =IF(B22="","",IF(MONTH(B22)=12,"X","")) | V22: =IF(E22="","",COUNTIF($E$5:$E$1000,E22)) -> 7 | W22: =IF(E22="","",_xlfn.TEXTJOIN(" + ",TRUE(),IF(COUNTIFS($E$5:$E$1000,E22,$C$5:$C$1000,"Auditoría Interna")>0,"Interna",""),IF(COUNTIFS($E$5:$E$1000,E22,$C$5:$C$1000,"Auditoría Externa")>0,"Externa",""),IF(COUNTIFS($E$5:$E$1000,E22,$C$5:$C$1000,"SSF")>0,"SSF",""),IF(COUNTIFS($E$5:$E$1000,E22,$C$5:$C$1000,"Comité de Supervisión")>0,"Comité Sup.",""),IF(COUNTIFS($E$5:$E$1000,E22,$C$5:$C$1000,"Consejo de Administración")>0,"Consejo",""),IF(COUNTIFS($E$5:$E$1000,E22,$C$5:$C$1000,"Otros")>0,"Otros",""))) -> Interna | X22: =IF(E22="","",COUNTIFS($E$5:$E$1000,E22,$AB$5:$AB$1000,AB22,$C$5:$C$1000,"<>"&C22)) -> 0 | Y22: Auditoria interna 1 | Z22: 1 | AB22: =IF(B22="","",YEAR(B22)*100+MONTH(B22)) -> 202605 | AC22: =IF(AND(E22<>"",E22=Cruce!$C$5),COUNTIF($E$5:E22,E22),"") | AD22: =IF(E22="","",C22&"|"&Y22&"|"&IF(B22="","s/f",TEXT(B22,"yyyymmdd"))) -> Auditoría Interna|Auditoria interna 1|20260506 | AE22: =IF(E22="",0,IF(COUNTIFS($E$5:E22,E22,$AD$5:AD22,AD22)=1,1,0)) -> 1
A23: 19 | B23: 46148 | C23: Auditoría Interna | D23: NCB-022 | E23: Matriz de migración / bases de cartera | F23: Matriz de Migración de marzo y abril 2026 | G23: Melvin | I23: =IF(B23="","",YEAR(B23)) -> 2026 | J23: =IF(B23="","",IF(MONTH(B23)=1,"X","")) | K23: =IF(B23="","",IF(MONTH(B23)=2,"X","")) | L23: =IF(B23="","",IF(MONTH(B23)=3,"X","")) | M23: =IF(B23="","",IF(MONTH(B23)=4,"X","")) | N23: =IF(B23="","",IF(MONTH(B23)=5,"X","")) -> X | O23: =IF(B23="","",IF(MONTH(B23)=6,"X","")) | P23: =IF(B23="","",IF(MONTH(B23)=7,"X","")) | Q23: =IF(B23="","",IF(MONTH(B23)=8,"X","")) | R23: =IF(B23="","",IF(MONTH(B23)=9,"X","")) | S23: =IF(B23="","",IF(MONTH(B23)=10,"X","")) | T23: =IF(B23="","",IF(MONTH(B23)=11,"X","")) | U23: =IF(B23="","",IF(MONTH(B23)=12,"X","")) | V23: =IF(E23="","",COUNTIF($E$5:$E$1000,E23)) -> 1 | W23: =IF(E23="","",_xlfn.TEXTJOIN(" + ",TRUE(),IF(COUNTIFS($E$5:$E$1000,E23,$C$5:$C$1000,"Auditoría Interna")>0,"Interna",""),IF(COUNTIFS($E$5:$E$1000,E23,$C$5:$C$1000,"Auditoría Externa")>0,"Externa",""),IF(COUNTIFS($E$5:$E$1000,E23,$C$5:$C$1000,"SSF")>0,"SSF",""),IF(COUNTIFS($E$5:$E$1000,E23,$C$5:$C$1000,"Comité de Supervisión")>0,"Comité Sup.",""),IF(COUNTIFS($E$5:$E$1000,E23,$C$5:$C$1000,"Consejo de Administración")>0,"Consejo",""),IF(COUNTIFS($E$5:$E$1000,E23,$C$5:$C$1000,"Otros")>0,"Otros",""))) -> Interna | X23: =IF(E23="","",COUNTIFS($E$5:$E$1000,E23,$AB$5:$AB$1000,AB23,$C$5:$C$1000,"<>"&C23)) -> 0 | Y23: Auditoria interna 1 | Z23: 2 | AB23: =IF(B23="","",YEAR(B23)*100+MONTH(B23)) -> 202605 | AC23: =IF(AND(E23<>"",E23=Cruce!$C$5),COUNTIF($E$5:E23,E23),"") | AD23: =IF(E23="","",C23&"|"&Y23&"|"&IF(B23="","s/f",TEXT(B23,"yyyymmdd"))) -> Auditoría Interna|Auditoria interna 1|20260506 | AE23: =IF(E23="",0,IF(COUNTIFS($E$5:E23,E23,$AD$5:AD23,AD23)=1,1,0)) -> 1
A24: 20 | B24: 46148 | C24: Auditoría Interna | D24: NCB-022 | E24: Pérdida Esperada | F24: Base de datos para el cálculo de la perdida esperada de los meses de marzo y abril 2026 (INTCARTCREL.txt y INTTARJCREL.txt) | G24: Melvin | I24: =IF(B24="","",YEAR(B24)) -> 2026 | J24: =IF(B24="","",IF(MONTH(B24)=1,"X","")) | K24: =IF(B24="","",IF(MONTH(B24)=2,"X","")) | L24: =IF(B24="","",IF(MONTH(B24)=3,"X","")) | M24: =IF(B24="","",IF(MONTH(B24)=4,"X","")) | N24: =IF(B24="","",IF(MONTH(B24)=5,"X","")) -> X | O24: =IF(B24="","",IF(MONTH(B24)=6,"X","")) | P24: =IF(B24="","",IF(MONTH(B24)=7,"X","")) | Q24: =IF(B24="","",IF(MONTH(B24)=8,"X","")) | R24: =IF(B24="","",IF(MONTH(B24)=9,"X","")) | S24: =IF(B24="","",IF(MONTH(B24)=10,"X","")) | T24: =IF(B24="","",IF(MONTH(B24)=11,"X","")) | U24: =IF(B24="","",IF(MONTH(B24)=12,"X","")) | V24: =IF(E24="","",COUNTIF($E$5:$E$1000,E24)) -> 3 | W24: =IF(E24="","",_xlfn.TEXTJOIN(" + ",TRUE(),IF(COUNTIFS($E$5:$E$1000,E24,$C$5:$C$1000,"Auditoría Interna")>0,"Interna",""),IF(COUNTIFS($E$5:$E$1000,E24,$C$5:$C$1000,"Auditoría Externa")>0,"Externa",""),IF(COUNTIFS($E$5:$E$1000,E24,$C$5:$C$1000,"SSF")>0,"SSF",""),IF(COUNTIFS($E$5:$E$1000,E24,$C$5:$C$1000,"Comité de Supervisión")>0,"Comité Sup.",""),IF(COUNTIFS($E$5:$E$1000,E24,$C$5:$C$1000,"Consejo de Administración")>0,"Consejo",""),IF(COUNTIFS($E$5:$E$1000,E24,$C$5:$C$1000,"Otros")>0,"Otros",""))) -> Interna + Externa | X24: =IF(E24="","",COUNTIFS($E$5:$E$1000,E24,$AB$5:$AB$1000,AB24,$C$5:$C$1000,"<>"&C24)) -> 0 | Y24: Auditoria interna 1 | Z24: 3 | AB24: =IF(B24="","",YEAR(B24)*100+MONTH(B24)) -> 202605 | AC24: =IF(AND(E24<>"",E24=Cruce!$C$5),COUNTIF($E$5:E24,E24),"") | AD24: =IF(E24="","",C24&"|"&Y24&"|"&IF(B24="","s/f",TEXT(B24,"yyyymmdd"))) -> Auditoría Interna|Auditoria interna 1|20260506 | AE24: =IF(E24="",0,IF(COUNTIFS($E$5:E24,E24,$AD$5:AD24,AD24)=1,1,0)) -> 1
A25: 21 | B25: 46148 | C25: Auditoría Interna | D25: NPB4-49 | E25: Escenarios de estrés de crédito | F25: Escenario de estrés de riesgo de crédito año 2026 (variables consideradas para la realización de simulación y análisis realizado sobre resultados obtenidos) | G25: Melvin | I25: =IF(B25="","",YEAR(B25)) -> 2026 | J25: =IF(B25="","",IF(MONTH(B25)=1,"X","")) | K25: =IF(B25="","",IF(MONTH(B25)=2,"X","")) | L25: =IF(B25="","",IF(MONTH(B25)=3,"X","")) | M25: =IF(B25="","",IF(MONTH(B25)=4,"X","")) | N25: =IF(B25="","",IF(MONTH(B25)=5,"X","")) -> X | O25: =IF(B25="","",IF(MONTH(B25)=6,"X","")) | P25: =IF(B25="","",IF(MONTH(B25)=7,"X","")) | Q25: =IF(B25="","",IF(MONTH(B25)=8,"X","")) | R25: =IF(B25="","",IF(MONTH(B25)=9,"X","")) | S25: =IF(B25="","",IF(MONTH(B25)=10,"X","")) | T25: =IF(B25="","",IF(MONTH(B25)=11,"X","")) | U25: =IF(B25="","",IF(MONTH(B25)=12,"X","")) | V25: =IF(E25="","",COUNTIF($E$5:$E$1000,E25)) -> 1 | W25: =IF(E25="","",_xlfn.TEXTJOIN(" + ",TRUE(),IF(COUNTIFS($E$5:$E$1000,E25,$C$5:$C$1000,"Auditoría Interna")>0,"Interna",""),IF(COUNTIFS($E$5:$E$1000,E25,$C$5:$C$1000,"Auditoría Externa")>0,"Externa",""),IF(COUNTIFS($E$5:$E$1000,E25,$C$5:$C$1000,"SSF")>0,"SSF",""),IF(COUNTIFS($E$5:$E$1000,E25,$C$5:$C$1000,"Comité de Supervisión")>0,"Comité Sup.",""),IF(COUNTIFS($E$5:$E$1000,E25,$C$5:$C$1000,"Consejo de Administración")>0,"Consejo",""),IF(COUNTIFS($E$5:$E$1000,E25,$C$5:$C$1000,"Otros")>0,"Otros",""))) -> Interna | X25: =IF(E25="","",COUNTIFS($E$5:$E$1000,E25,$AB$5:$AB$1000,AB25,$C$5:$C$1000,"<>"&C25)) -> 0 | Y25: Auditoria interna 1 | Z25: 4 | AB25: =IF(B25="","",YEAR(B25)*100+MONTH(B25)) -> 202605 | AC25: =IF(AND(E25<>"",E25=Cruce!$C$5),COUNTIF($E$5:E25,E25),"") | AD25: =IF(E25="","",C25&"|"&Y25&"|"&IF(B25="","s/f",TEXT(B25,"yyyymmdd"))) -> Auditoría Interna|Auditoria interna 1|20260506 | AE25: =IF(E25="",0,IF(COUNTIFS($E$5:E25,E25,$AD$5:AD25,AD25)=1,1,0)) -> 1
A26: 22 | B26: 46148 | C26: Auditoría Interna | D26: NRP-20 | E26: Informe GIR / informes al Comité y Consejo | F26: Informes presentados al Comité de Riesgos por el período de julio 2025 a abril 2026. | G26: Melvin | I26: =IF(B26="","",YEAR(B26)) -> 2026 | J26: =IF(B26="","",IF(MONTH(B26)=1,"X","")) | K26: =IF(B26="","",IF(MONTH(B26)=2,"X","")) | L26: =IF(B26="","",IF(MONTH(B26)=3,"X","")) | M26: =IF(B26="","",IF(MONTH(B26)=4,"X","")) | N26: =IF(B26="","",IF(MONTH(B26)=5,"X","")) -> X | O26: =IF(B26="","",IF(MONTH(B26)=6,"X","")) | P26: =IF(B26="","",IF(MONTH(B26)=7,"X","")) | Q26: =IF(B26="","",IF(MONTH(B26)=8,"X","")) | R26: =IF(B26="","",IF(MONTH(B26)=9,"X","")) | S26: =IF(B26="","",IF(MONTH(B26)=10,"X","")) | T26: =IF(B26="","",IF(MONTH(B26)=11,"X","")) | U26: =IF(B26="","",IF(MONTH(B26)=12,"X","")) | V26: =IF(E26="","",COUNTIF($E$5:$E$1000,E26)) -> 5 | W26: =IF(E26="","",_xlfn.TEXTJOIN(" + ",TRUE(),IF(COUNTIFS($E$5:$E$1000,E26,$C$5:$C$1000,"Auditoría Interna")>0,"Interna",""),IF(COUNTIFS($E$5:$E$1000,E26,$C$5:$C$1000,"Auditoría Externa")>0,"Externa",""),IF(COUNTIFS($E$5:$E$1000,E26,$C$5:$C$1000,"SSF")>0,"SSF",""),IF(COUNTIFS($E$5:$E$1000,E26,$C$5:$C$1000,"Comité de Supervisión")>0,"Comité Sup.",""),IF(COUNTIFS($E$5:$E$1000,E26,$C$5:$C$1000,"Consejo de Administración")>0,"Consejo",""),IF(COUNTIFS($E$5:$E$1000,E26,$C$5:$C$1000,"Otros")>0,"Otros",""))) -> Interna | X26: =IF(E26="","",COUNTIFS($E$5:$E$1000,E26,$AB$5:$AB$1000,AB26,$C$5:$C$1000,"<>"&C26)) -> 0 | Y26: Auditoria interna 1 | Z26: 5 | AB26: =IF(B26="","",YEAR(B26)*100+MONTH(B26)) -> 202605 | AC26: =IF(AND(E26<>"",E26=Cruce!$C$5),COUNTIF($E$5:E26,E26),"") | AD26: =IF(E26="","",C26&"|"&Y26&"|"&IF(B26="","s/f",TEXT(B26,"yyyymmdd"))) -> Auditoría Interna|Auditoria interna 1|20260506 | AE26: =IF(E26="",0,IF(COUNTIFS($E$5:E26,E26,$AD$5:AD26,AD26)=1,1,0)) -> 1
A27: 23 | B27: 46148 | C27: Auditoría Interna | D27: NCB-022 | E27: Clasificación de cartera, mora y reservas | F27: Informe de Activos de Riesgos al 31 de julio 2025 al 30 de abril 2026 (Evaluación de la Cartera Crediticia) | G27: Melvin | I27: =IF(B27="","",YEAR(B27)) -> 2026 | J27: =IF(B27="","",IF(MONTH(B27)=1,"X","")) | K27: =IF(B27="","",IF(MONTH(B27)=2,"X","")) | L27: =IF(B27="","",IF(MONTH(B27)=3,"X","")) | M27: =IF(B27="","",IF(MONTH(B27)=4,"X","")) | N27: =IF(B27="","",IF(MONTH(B27)=5,"X","")) -> X | O27: =IF(B27="","",IF(MONTH(B27)=6,"X","")) | P27: =IF(B27="","",IF(MONTH(B27)=7,"X","")) | Q27: =IF(B27="","",IF(MONTH(B27)=8,"X","")) | R27: =IF(B27="","",IF(MONTH(B27)=9,"X","")) | S27: =IF(B27="","",IF(MONTH(B27)=10,"X","")) | T27: =IF(B27="","",IF(MONTH(B27)=11,"X","")) | U27: =IF(B27="","",IF(MONTH(B27)=12,"X","")) | V27: =IF(E27="","",COUNTIF($E$5:$E$1000,E27)) -> 6 | W27: =IF(E27="","",_xlfn.TEXTJOIN(" + ",TRUE(),IF(COUNTIFS($E$5:$E$1000,E27,$C$5:$C$1000,"Auditoría Interna")>0,"Interna",""),IF(COUNTIFS($E$5:$E$1000,E27,$C$5:$C$1000,"Auditoría Externa")>0,"Externa",""),IF(COUNTIFS($E$5:$E$1000,E27,$C$5:$C$1000,"SSF")>0,"SSF",""),IF(COUNTIFS($E$5:$E$1000,E27,$C$5:$C$1000,"Comité de Supervisión")>0,"Comité Sup.",""),IF(COUNTIFS($E$5:$E$1000,E27,$C$5:$C$1000,"Consejo de Administración")>0,"Consejo",""),IF(COUNTIFS($E$5:$E$1000,E27,$C$5:$C$1000,"Otros")>0,"Otros",""))) -> Interna + Externa + SSF | X27: =IF(E27="","",COUNTIFS($E$5:$E$1000,E27,$AB$5:$AB$1000,AB27,$C$5:$C$1000,"<>"&C27)) -> 0 | Y27: Auditoria interna 1 | Z27: 6 | AB27: =IF(B27="","",YEAR(B27)*100+MONTH(B27)) -> 202605 | AC27: =IF(AND(E27<>"",E27=Cruce!$C$5),COUNTIF($E$5:E27,E27),"") | AD27: =IF(E27="","",C27&"|"&Y27&"|"&IF(B27="","s/f",TEXT(B27,"yyyymmdd"))) -> Auditoría Interna|Auditoria interna 1|20260506 | AE27: =IF(E27="",0,IF(COUNTIFS($E$5:E27,E27,$AD$5:AD27,AD27)=1,1,0)) -> 1
A28: 24 | B28: 46148 | C28: Auditoría Interna | D28: NCB-022 / NRP-25 | E28: Remisiones a SSF / central de riesgos | F28: Evidencia de envío / recepción por la SSF / BCR por el período de julio 2025 a abril 2026 de: • Artículo 26 de la NCB-22 – Reestructuraciones o refinanciamientos de activos crediticios efectuados en el mes; • Artículo 28 de la NCB-22 – Reclasificación de categorías de menor riesgo de los 50 mayores deudores • Artículo 30 de la NCB-22 – Clasificación de la cartera de los activos crediticios y las respectivas reservas de saneamiento. • Artículo 8 NRP 25 – Anexo 1, actualización de valúos de garantías hipotecarias (SSF y BCR) • Artículo 15 NRP 25 – Anexo 2, registro de la cartera de créditos afectados por la pandemia (SSF y BCR). | G28: Melvin | I28: =IF(B28="","",YEAR(B28)) -> 2026 | J28: =IF(B28="","",IF(MONTH(B28)=1,"X","")) | K28: =IF(B28="","",IF(MONTH(B28)=2,"X","")) | L28: =IF(B28="","",IF(MONTH(B28)=3,"X","")) | M28: =IF(B28="","",IF(MONTH(B28)=4,"X","")) | N28: =IF(B28="","",IF(MONTH(B28)=5,"X","")) -> X | O28: =IF(B28="","",IF(MONTH(B28)=6,"X","")) | P28: =IF(B28="","",IF(MONTH(B28)=7,"X","")) | Q28: =IF(B28="","",IF(MONTH(B28)=8,"X","")) | R28: =IF(B28="","",IF(MONTH(B28)=9,"X","")) | S28: =IF(B28="","",IF(MONTH(B28)=10,"X","")) | T28: =IF(B28="","",IF(MONTH(B28)=11,"X","")) | U28: =IF(B28="","",IF(MONTH(B28)=12,"X","")) | V28: =IF(E28="","",COUNTIF($E$5:$E$1000,E28)) -> 3 | W28: =IF(E28="","",_xlfn.TEXTJOIN(" + ",TRUE(),IF(COUNTIFS($E$5:$E$1000,E28,$C$5:$C$1000,"Auditoría Interna")>0,"Interna",""),IF(COUNTIFS($E$5:$E$1000,E28,$C$5:$C$1000,"Auditoría Externa")>0,"Externa",""),IF(COUNTIFS($E$5:$E$1000,E28,$C$5:$C$1000,"SSF")>0,"SSF",""),IF(COUNTIFS($E$5:$E$1000,E28,$C$5:$C$1000,"Comité de Supervisión")>0,"Comité Sup.",""),IF(COUNTIFS($E$5:$E$1000,E28,$C$5:$C$1000,"Consejo de Administración")>0,"Consejo",""),IF(COUNTIFS($E$5:$E$1000,E28,$C$5:$C$1000,"Otros")>0,"Otros",""))) -> Interna + Externa | X28: =IF(E28="","",COUNTIFS($E$5:$E$1000,E28,$AB$5:$AB$1000,AB28,$C$5:$C$1000,"<>"&C28)) -> 0 | Y28: Auditoria interna 1 | Z28: 7 | AB28: =IF(B28="","",YEAR(B28)*100+MONTH(B28)) -> 202605 | AC28: =IF(AND(E28<>"",E28=Cruce!$C$5),COUNTIF($E$5:E28,E28),"") | AD28: =IF(E28="","",C28&"|"&Y28&"|"&IF(B28="","s/f",TEXT(B28,"yyyymmdd"))) -> Auditoría Interna|Auditoria interna 1|20260506 | AE28: =IF(E28="",0,IF(COUNTIFS($E$5:E28,E28,$AD$5:AD28,AD28)=1,1,0)) -> 1
A29: 25 | B29: 46148 | C29: Auditoría Interna | D29: Por validar | E29: Remisiones a SSF / central de riesgos | F29: Evidencia de envío a la SSF por el período de julio 2025 a abril 2026 de la actualización de información de la central de riesgos (Reporte de Envío de Datos) | G29: Melvin | I29: =IF(B29="","",YEAR(B29)) -> 2026 | J29: =IF(B29="","",IF(MONTH(B29)=1,"X","")) | K29: =IF(B29="","",IF(MONTH(B29)=2,"X","")) | L29: =IF(B29="","",IF(MONTH(B29)=3,"X","")) | M29: =IF(B29="","",IF(MONTH(B29)=4,"X","")) | N29: =IF(B29="","",IF(MONTH(B29)=5,"X","")) -> X | O29: =IF(B29="","",IF(MONTH(B29)=6,"X","")) | P29: =IF(B29="","",IF(MONTH(B29)=7,"X","")) | Q29: =IF(B29="","",IF(MONTH(B29)=8,"X","")) | R29: =IF(B29="","",IF(MONTH(B29)=9,"X","")) | S29: =IF(B29="","",IF(MONTH(B29)=10,"X","")) | T29: =IF(B29="","",IF(MONTH(B29)=11,"X","")) | U29: =IF(B29="","",IF(MONTH(B29)=12,"X","")) | V29: =IF(E29="","",COUNTIF($E$5:$E$1000,E29)) -> 3 | W29: =IF(E29="","",_xlfn.TEXTJOIN(" + ",TRUE(),IF(COUNTIFS($E$5:$E$1000,E29,$C$5:$C$1000,"Auditoría Interna")>0,"Interna",""),IF(COUNTIFS($E$5:$E$1000,E29,$C$5:$C$1000,"Auditoría Externa")>0,"Externa",""),IF(COUNTIFS($E$5:$E$1000,E29,$C$5:$C$1000,"SSF")>0,"SSF",""),IF(COUNTIFS($E$5:$E$1000,E29,$C$5:$C$1000,"Comité de Supervisión")>0,"Comité Sup.",""),IF(COUNTIFS($E$5:$E$1000,E29,$C$5:$C$1000,"Consejo de Administración")>0,"Consejo",""),IF(COUNTIFS($E$5:$E$1000,E29,$C$5:$C$1000,"Otros")>0,"Otros",""))) -> Interna + Externa | X29: =IF(E29="","",COUNTIFS($E$5:$E$1000,E29,$AB$5:$AB$1000,AB29,$C$5:$C$1000,"<>"&C29)) -> 0 | Y29: Auditoria interna 1 | Z29: 8 | AB29: =IF(B29="","",YEAR(B29)*100+MONTH(B29)) -> 202605 | AC29: =IF(AND(E29<>"",E29=Cruce!$C$5),COUNTIF($E$5:E29,E29),"") | AD29: =IF(E29="","",C29&"|"&Y29&"|"&IF(B29="","s/f",TEXT(B29,"yyyymmdd"))) -> Auditoría Interna|Auditoria interna 1|20260506 | AE29: =IF(E29="",0,IF(COUNTIFS($E$5:E29,E29,$AD$5:AD29,AD29)=1,1,0)) -> 0
A30: 26 | B30: 46148 | C30: Auditoría Interna | D30: NRP-20 | E30: Actas Comité de Riesgos | F30: Actas de comité de riesgo julio 2025 a abril 2026 | G30: Sara | I30: =IF(B30="","",YEAR(B30)) -> 2026 | J30: =IF(B30="","",IF(MONTH(B30)=1,"X","")) | K30: =IF(B30="","",IF(MONTH(B30)=2,"X","")) | L30: =IF(B30="","",IF(MONTH(B30)=3,"X","")) | M30: =IF(B30="","",IF(MONTH(B30)=4,"X","")) | N30: =IF(B30="","",IF(MONTH(B30)=5,"X","")) -> X | O30: =IF(B30="","",IF(MONTH(B30)=6,"X","")) | P30: =IF(B30="","",IF(MONTH(B30)=7,"X","")) | Q30: =IF(B30="","",IF(MONTH(B30)=8,"X","")) | R30: =IF(B30="","",IF(MONTH(B30)=9,"X","")) | S30: =IF(B30="","",IF(MONTH(B30)=10,"X","")) | T30: =IF(B30="","",IF(MONTH(B30)=11,"X","")) | U30: =IF(B30="","",IF(MONTH(B30)=12,"X","")) | V30: =IF(E30="","",COUNTIF($E$5:$E$1000,E30)) -> 5 | W30: =IF(E30="","",_xlfn.TEXTJOIN(" + ",TRUE(),IF(COUNTIFS($E$5:$E$1000,E30,$C$5:$C$1000,"Auditoría Interna")>0,"Interna",""),IF(COUNTIFS($E$5:$E$1000,E30,$C$5:$C$1000,"Auditoría Externa")>0,"Externa",""),IF(COUNTIFS($E$5:$E$1000,E30,$C$5:$C$1000,"SSF")>0,"SSF",""),IF(COUNTIFS($E$5:$E$1000,E30,$C$5:$C$1000,"Comité de Supervisión")>0,"Comité Sup.",""),IF(COUNTIFS($E$5:$E$1000,E30,$C$5:$C$1000,"Consejo de Administración")>0,"Consejo",""),IF(COUNTIFS($E$5:$E$1000,E30,$C$5:$C$1000,"Otros")>0,"Otros",""))) -> Interna + Externa | X30: =IF(E30="","",COUNTIFS($E$5:$E$1000,E30,$AB$5:$AB$1000,AB30,$C$5:$C$1000,"<>"&C30)) -> 0 | Y30: Auditoria interna 1 | Z30: 9 | AB30: =IF(B30="","",YEAR(B30)*100+MONTH(B30)) -> 202605 | AC30: =IF(AND(E30<>"",E30=Cruce!$C$5),COUNTIF($E$5:E30,E30),"") | AD30: =IF(E30="","",C30&"|"&Y30&"|"&IF(B30="","s/f",TEXT(B30,"yyyymmdd"))) -> Auditoría Interna|Auditoria interna 1|20260506 | AE30: =IF(E30="",0,IF(COUNTIFS($E$5:E30,E30,$AD$5:AD30,AD30)=1,1,0)) -> 1
A31: 27 | B31: 46148 | C31: Auditoría Interna | D31: NRP-25 | E31: Valúos y garantías | F31: Plan de actualización de valúos periciales (compartir el avance a la fecha). Base de valúos y el cuadro resumen de valúos pendientes de actualizar. | G31: Sara | I31: =IF(B31="","",YEAR(B31)) -> 2026 | J31: =IF(B31="","",IF(MONTH(B31)=1,"X","")) | K31: =IF(B31="","",IF(MONTH(B31)=2,"X","")) | L31: =IF(B31="","",IF(MONTH(B31)=3,"X","")) | M31: =IF(B31="","",IF(MONTH(B31)=4,"X","")) | N31: =IF(B31="","",IF(MONTH(B31)=5,"X","")) -> X | O31: =IF(B31="","",IF(MONTH(B31)=6,"X","")) | P31: =IF(B31="","",IF(MONTH(B31)=7,"X","")) | Q31: =IF(B31="","",IF(MONTH(B31)=8,"X","")) | R31: =IF(B31="","",IF(MONTH(B31)=9,"X","")) | S31: =IF(B31="","",IF(MONTH(B31)=10,"X","")) | T31: =IF(B31="","",IF(MONTH(B31)=11,"X","")) | U31: =IF(B31="","",IF(MONTH(B31)=12,"X","")) | V31: =IF(E31="","",COUNTIF($E$5:$E$1000,E31)) -> 2 | W31: =IF(E31="","",_xlfn.TEXTJOIN(" + ",TRUE(),IF(COUNTIFS($E$5:$E$1000,E31,$C$5:$C$1000,"Auditoría Interna")>0,"Interna",""),IF(COUNTIFS($E$5:$E$1000,E31,$C$5:$C$1000,"Auditoría Externa")>0,"Externa",""),IF(COUNTIFS($E$5:$E$1000,E31,$C$5:$C$1000,"SSF")>0,"SSF",""),IF(COUNTIFS($E$5:$E$1000,E31,$C$5:$C$1000,"Comité de Supervisión")>0,"Comité Sup.",""),IF(COUNTIFS($E$5:$E$1000,E31,$C$5:$C$1000,"Consejo de Administración")>0,"Consejo",""),IF(COUNTIFS($E$5:$E$1000,E31,$C$5:$C$1000,"Otros")>0,"Otros",""))) -> Interna + SSF | X31: =IF(E31="","",COUNTIFS($E$5:$E$1000,E31,$AB$5:$AB$1000,AB31,$C$5:$C$1000,"<>"&C31)) -> 0 | Y31: Auditoria interna 1 | Z31: 10 | AB31: =IF(B31="","",YEAR(B31)*100+MONTH(B31)) -> 202605 | AC31: =IF(AND(E31<>"",E31=Cruce!$C$5),COUNTIF($E$5:E31,E31),"") | AD31: =IF(E31="","",C31&"|"&Y31&"|"&IF(B31="","s/f",TEXT(B31,"yyyymmdd"))) -> Auditoría Interna|Auditoria interna 1|20260506 | AE31: =IF(E31="",0,IF(COUNTIFS($E$5:E31,E31,$AD$5:AD31,AD31)=1,1,0)) -> 1
A32: 28 | B32: 46217 | C32: SSF | D32: NRP-20 | E32: Gestión de riesgos específicos (visita integral) | F32: Nombramiento de visita de supervisión ampliada para evaluar la calidad de la gestión de riesgos específicos. No. SABAO-BCS-BC-15527 | I32: =IF(B32="","",YEAR(B32)) -> 2026 | J32: =IF(B32="","",IF(MONTH(B32)=1,"X","")) | K32: =IF(B32="","",IF(MONTH(B32)=2,"X","")) | L32: =IF(B32="","",IF(MONTH(B32)=3,"X","")) | M32: =IF(B32="","",IF(MONTH(B32)=4,"X","")) | N32: =IF(B32="","",IF(MONTH(B32)=5,"X","")) | O32: =IF(B32="","",IF(MONTH(B32)=6,"X","")) | P32: =IF(B32="","",IF(MONTH(B32)=7,"X","")) -> X | Q32: =IF(B32="","",IF(MONTH(B32)=8,"X","")) | R32: =IF(B32="","",IF(MONTH(B32)=9,"X","")) | S32: =IF(B32="","",IF(MONTH(B32)=10,"X","")) | T32: =IF(B32="","",IF(MONTH(B32)=11,"X","")) | U32: =IF(B32="","",IF(MONTH(B32)=12,"X","")) | V32: =IF(E32="","",COUNTIF($E$5:$E$1000,E32)) -> 4 | W32: =IF(E32="","",_xlfn.TEXTJOIN(" + ",TRUE(),IF(COUNTIFS($E$5:$E$1000,E32,$C$5:$C$1000,"Auditoría Interna")>0,"Interna",""),IF(COUNTIFS($E$5:$E$1000,E32,$C$5:$C$1000,"Auditoría Externa")>0,"Externa",""),IF(COUNTIFS($E$5:$E$1000,E32,$C$5:$C$1000,"SSF")>0,"SSF",""),IF(COUNTIFS($E$5:$E$1000,E32,$C$5:$C$1000,"Comité de Supervisión")>0,"Comité Sup.",""),IF(COUNTIFS($E$5:$E$1000,E32,$C$5:$C$1000,"Consejo de Administración")>0,"Consejo",""),IF(COUNTIFS($E$5:$E$1000,E32,$C$5:$C$1000,"Otros")>0,"Otros",""))) -> SSF | X32: =IF(E32="","",COUNTIFS($E$5:$E$1000,E32,$AB$5:$AB$1000,AB32,$C$5:$C$1000,"<>"&C32)) -> 0 | Y32: Resumen visita presencialSSF | Z32: 20 | AA32: I requerimiento: 92 puntos 14/07/2026 11 requerimientos adicionales entre el 20/07/2026 - 26/08/2026 | AB32: =IF(B32="","",YEAR(B32)*100+MONTH(B32)) -> 202607 | AC32: =IF(AND(E32<>"",E32=Cruce!$C$5),COUNTIF($E$5:E32,E32),"") | AD32: =IF(E32="","",C32&"|"&Y32&"|"&IF(B32="","s/f",TEXT(B32,"yyyymmdd"))) -> SSF|Resumen visita presencialSSF|20260714 | AE32: =IF(E32="",0,IF(COUNTIFS($E$5:E32,E32,$AD$5:AD32,AD32)=1,1,0)) -> 1
A33: 29 | B33: 46249 | C33: Auditoría Interna | D33: NRP-20 | E33: Plan de trabajo y capacitaciones de riesgos | F33: Acuerdo del Concejo de Administración de aprobación del Plan de trabajo DAR 2026 y programa de capacitaciones 2026 | G33: Silvita | I33: =IF(B33="","",YEAR(B33)) -> 2026 | J33: =IF(B33="","",IF(MONTH(B33)=1,"X","")) | K33: =IF(B33="","",IF(MONTH(B33)=2,"X","")) | L33: =IF(B33="","",IF(MONTH(B33)=3,"X","")) | M33: =IF(B33="","",IF(MONTH(B33)=4,"X","")) | N33: =IF(B33="","",IF(MONTH(B33)=5,"X","")) | O33: =IF(B33="","",IF(MONTH(B33)=6,"X","")) | P33: =IF(B33="","",IF(MONTH(B33)=7,"X","")) | Q33: =IF(B33="","",IF(MONTH(B33)=8,"X","")) -> X | R33: =IF(B33="","",IF(MONTH(B33)=9,"X","")) | S33: =IF(B33="","",IF(MONTH(B33)=10,"X","")) | T33: =IF(B33="","",IF(MONTH(B33)=11,"X","")) | U33: =IF(B33="","",IF(MONTH(B33)=12,"X","")) | V33: =IF(E33="","",COUNTIF($E$5:$E$1000,E33)) -> 7 | W33: =IF(E33="","",_xlfn.TEXTJOIN(" + ",TRUE(),IF(COUNTIFS($E$5:$E$1000,E33,$C$5:$C$1000,"Auditoría Interna")>0,"Interna",""),IF(COUNTIFS($E$5:$E$1000,E33,$C$5:$C$1000,"Auditoría Externa")>0,"Externa",""),IF(COUNTIFS($E$5:$E$1000,E33,$C$5:$C$1000,"SSF")>0,"SSF",""),IF(COUNTIFS($E$5:$E$1000,E33,$C$5:$C$1000,"Comité de Supervisión")>0,"Comité Sup.",""),IF(COUNTIFS($E$5:$E$1000,E33,$C$5:$C$1000,"Consejo de Administración")>0,"Consejo",""),IF(COUNTIFS($E$5:$E$1000,E33,$C$5:$C$1000,"Otros")>0,"Otros",""))) -> Interna | X33: =IF(E33="","",COUNTIFS($E$5:$E$1000,E33,$AB$5:$AB$1000,AB33,$C$5:$C$1000,"<>"&C33)) -> 0 | Y33: Auditoria interna 2 | Z33: 1 | AB33: =IF(B33="","",YEAR(B33)*100+MONTH(B33)) -> 202608 | AC33: =IF(AND(E33<>"",E33=Cruce!$C$5),COUNTIF($E$5:E33,E33),"") | AD33: =IF(E33="","",C33&"|"&Y33&"|"&IF(B33="","s/f",TEXT(B33,"yyyymmdd"))) -> Auditoría Interna|Auditoria interna 2|20260815 | AE33: =IF(E33="",0,IF(COUNTIFS($E$5:E33,E33,$AD$5:AD33,AD33)=1,1,0)) -> 1
A34: 30 | B34: 46249 | C34: Auditoría Interna | D34: NRP-20 | E34: Informe GIR / informes al Comité y Consejo | F34: Informe Gestión Integral de Riesgos informados al comité de mayo 2025 a julio 2026 | G34: Melvin | I34: =IF(B34="","",YEAR(B34)) -> 2026 | J34: =IF(B34="","",IF(MONTH(B34)=1,"X","")) | K34: =IF(B34="","",IF(MONTH(B34)=2,"X","")) | L34: =IF(B34="","",IF(MONTH(B34)=3,"X","")) | M34: =IF(B34="","",IF(MONTH(B34)=4,"X","")) | N34: =IF(B34="","",IF(MONTH(B34)=5,"X","")) | O34: =IF(B34="","",IF(MONTH(B34)=6,"X","")) | P34: =IF(B34="","",IF(MONTH(B34)=7,"X","")) | Q34: =IF(B34="","",IF(MONTH(B34)=8,"X","")) -> X | R34: =IF(B34="","",IF(MONTH(B34)=9,"X","")) | S34: =IF(B34="","",IF(MONTH(B34)=10,"X","")) | T34: =IF(B34="","",IF(MONTH(B34)=11,"X","")) | U34: =IF(B34="","",IF(MONTH(B34)=12,"X","")) | V34: =IF(E34="","",COUNTIF($E$5:$E$1000,E34)) -> 5 | W34: =IF(E34="","",_xlfn.TEXTJOIN(" + ",TRUE(),IF(COUNTIFS($E$5:$E$1000,E34,$C$5:$C$1000,"Auditoría Interna")>0,"Interna",""),IF(COUNTIFS($E$5:$E$1000,E34,$C$5:$C$1000,"Auditoría Externa")>0,"Externa",""),IF(COUNTIFS($E$5:$E$1000,E34,$C$5:$C$1000,"SSF")>0,"SSF",""),IF(COUNTIFS($E$5:$E$1000,E34,$C$5:$C$1000,"Comité de Supervisión")>0,"Comité Sup.",""),IF(COUNTIFS($E$5:$E$1000,E34,$C$5:$C$1000,"Consejo de Administración")>0,"Consejo",""),IF(COUNTIFS($E$5:$E$1000,E34,$C$5:$C$1000,"Otros")>0,"Otros",""))) -> Interna | X34: =IF(E34="","",COUNTIFS($E$5:$E$1000,E34,$AB$5:$AB$1000,AB34,$C$5:$C$1000,"<>"&C34)) -> 0 | Y34: Auditoria interna 2 | Z34: 2 | AB34: =IF(B34="","",YEAR(B34)*100+MONTH(B34)) -> 202608 | AC34: =IF(AND(E34<>"",E34=Cruce!$C$5),COUNTIF($E$5:E34,E34),"") | AD34: =IF(E34="","",C34&"|"&Y34&"|"&IF(B34="","s/f",TEXT(B34,"yyyymmdd"))) -> Auditoría Interna|Auditoria interna 2|20260815 | AE34: =IF(E34="",0,IF(COUNTIFS($E$5:E34,E34,$AD$5:AD34,AD34)=1,1,0)) -> 1
A35: 31 | B35: 46249 | C35: Auditoría Interna | D35: NRP-20 | E35: Actas Comité de Riesgos | F35: Actas de comité de riesgos dentro del periodo de mayo 2026 a la fecha | G35: Sara | I35: =IF(B35="","",YEAR(B35)) -> 2026 | J35: =IF(B35="","",IF(MONTH(B35)=1,"X","")) | K35: =IF(B35="","",IF(MONTH(B35)=2,"X","")) | L35: =IF(B35="","",IF(MONTH(B35)=3,"X","")) | M35: =IF(B35="","",IF(MONTH(B35)=4,"X","")) | N35: =IF(B35="","",IF(MONTH(B35)=5,"X","")) | O35: =IF(B35="","",IF(MONTH(B35)=6,"X","")) | P35: =IF(B35="","",IF(MONTH(B35)=7,"X","")) | Q35: =IF(B35="","",IF(MONTH(B35)=8,"X","")) -> X | R35: =IF(B35="","",IF(MONTH(B35)=9,"X","")) | S35: =IF(B35="","",IF(MONTH(B35)=10,"X","")) | T35: =IF(B35="","",IF(MONTH(B35)=11,"X","")) | U35: =IF(B35="","",IF(MONTH(B35)=12,"X","")) | V35: =IF(E35="","",COUNTIF($E$5:$E$1000,E35)) -> 5 | W35: =IF(E35="","",_xlfn.TEXTJOIN(" + ",TRUE(),IF(COUNTIFS($E$5:$E$1000,E35,$C$5:$C$1000,"Auditoría Interna")>0,"Interna",""),IF(COUNTIFS($E$5:$E$1000,E35,$C$5:$C$1000,"Auditoría Externa")>0,"Externa",""),IF(COUNTIFS($E$5:$E$1000,E35,$C$5:$C$1000,"SSF")>0,"SSF",""),IF(COUNTIFS($E$5:$E$1000,E35,$C$5:$C$1000,"Comité de Supervisión")>0,"Comité Sup.",""),IF(COUNTIFS($E$5:$E$1000,E35,$C$5:$C$1000,"Consejo de Administración")>0,"Consejo",""),IF(COUNTIFS($E$5:$E$1000,E35,$C$5:$C$1000,"Otros")>0,"Otros",""))) -> Interna + Externa | X35: =IF(E35="","",COUNTIFS($E$5:$E$1000,E35,$AB$5:$AB$1000,AB35,$C$5:$C$1000,"<>"&C35)) -> 0 | Y35: Auditoria interna 2 | Z35: 3 | AB35: =IF(B35="","",YEAR(B35)*100+MONTH(B35)) -> 202608 | AC35: =IF(AND(E35<>"",E35=Cruce!$C$5),COUNTIF($E$5:E35,E35),"") | AD35: =IF(E35="","",C35&"|"&Y35&"|"&IF(B35="","s/f",TEXT(B35,"yyyymmdd"))) -> Auditoría Interna|Auditoria interna 2|20260815 | AE35: =IF(E35="",0,IF(COUNTIFS($E$5:E35,E35,$AD$5:AD35,AD35)=1,1,0)) -> 1
